{
  "type": "Feature",
  "properties": {
    "gn:admin1_code":"11.0",
    "gn:admin2_code":"MMR016D003",
    "gn:admin3_code":"MMR016011",
    "gn:asciiname":"Wan Namhpawng",
    "gn:country_code":"MM",
    "gn:dem":1219,
    "gn:feature_class":"P",
    "gn:feature_code":"PPL",
    "gn:name":"W\u0101n Namhpawng",
    "gn:population":0,
    "gn:timezone":"Asia/Yangon",
    "iso:country":"MM",
    "wof:name":"Wan Namhpawng",
    "wof:placetype":"locality"
},
  "geometry": {"coordinates":[100.38709,21.26411],"type":"Point"}
}