{
  "type": "Feature",
  "properties": {
    "gn:admin1_code":"11.0",
    "gn:asciiname":"Kawnghking",
    "gn:country_code":"MM",
    "gn:dem":754,
    "gn:feature_class":"P",
    "gn:feature_code":"PPL",
    "gn:name":"Kawnghking",
    "gn:population":0,
    "gn:timezone":"Asia/Yangon",
    "iso:country":"MM",
    "wof:name":"Kawnghking",
    "wof:placetype":"locality"
},
  "geometry": {"coordinates":[97.73427,23.89971],"type":"Point"}
}