{
  "type": "Feature",
  "properties": {
    "gn:admin1_code":"10.0",
    "gn:admin2_code":"MMR005D004",
    "gn:admin3_code":"MMR005025",
    "gn:asciiname":"Nyaungchidauk",
    "gn:country_code":"MM",
    "gn:dem":317,
    "gn:feature_class":"P",
    "gn:feature_code":"PPL",
    "gn:name":"Nyaungchidauk",
    "gn:population":0,
    "gn:timezone":"Asia/Yangon",
    "iso:country":"MM",
    "wof:name":"Nyaungchidauk",
    "wof:placetype":"locality"
},
  "geometry": {"coordinates":[95.73754,24.00936],"type":"Point"}
}