{
  "type": "Feature",
  "properties": {
    "gn:admin1_code":"3.0",
    "gn:admin2_code":"MMR017D001",
    "gn:admin3_code":"MMR017002",
    "gn:asciiname":"Htinbonzeik",
    "gn:country_code":"MM",
    "gn:dem":6,
    "gn:feature_class":"P",
    "gn:feature_code":"PPL",
    "gn:name":"Htinbonzeik",
    "gn:population":0,
    "gn:timezone":"Asia/Yangon",
    "iso:country":"MM",
    "wof:name":"Htinbonzeik",
    "wof:placetype":"locality"
},
  "geometry": {"coordinates":[94.8925,16.76169],"type":"Point"}
}