{
  "type": "Feature",
  "properties": {
    "gn:admin1_code":"11.0",
    "gn:admin2_code":"MMR014D001",
    "gn:admin3_code":"MMR014010",
    "gn:asciiname":"Wan Hsam-mok",
    "gn:country_code":"MM",
    "gn:dem":909,
    "gn:feature_class":"P",
    "gn:feature_code":"PPL",
    "gn:name":"W\u0101n Hsam-mok",
    "gn:population":0,
    "gn:timezone":"Asia/Yangon",
    "iso:country":"MM",
    "wof:name":"Wan Hsam-mok",
    "wof:placetype":"locality"
},
  "geometry": {"coordinates":[97.09430999999999,19.94807],"type":"Point"}
}