{
  "type": "Feature",
  "properties": {
    "gn:admin1_code":"15.0",
    "gn:admin2_code":"MMR009D001",
    "gn:admin3_code":"MMR009004",
    "gn:asciiname":"Nyaungbintha",
    "gn:country_code":"MM",
    "gn:dem":138,
    "gn:feature_class":"P",
    "gn:feature_code":"PPL",
    "gn:name":"Nyaungbintha",
    "gn:population":0,
    "gn:timezone":"Asia/Yangon",
    "iso:country":"MM",
    "wof:name":"Nyaungbintha",
    "wof:placetype":"locality"
},
  "geometry": {"coordinates":[95.51667999999999,19.90584],"type":"Point"}
}