{
  "type": "Feature",
  "properties": {
    "gn:admin1_code":"4.0",
    "gn:admin2_code":"MMR001D003",
    "gn:admin3_code":"MMR001012",
    "gn:asciiname":"Lana",
    "gn:country_code":"MM",
    "gn:dem":755,
    "gn:feature_class":"P",
    "gn:feature_code":"PPL",
    "gn:name":"Lana",
    "gn:population":0,
    "gn:timezone":"Asia/Yangon",
    "iso:country":"MM",
    "name:ceb_x_preferred":[
        "Lana"
    ],
    "name:deu_x_preferred":[
        "Lana"
    ],
    "name:fas_x_preferred":[
        "\u0644\u0627\u0646\u0627"
    ],
    "name:fin_x_preferred":[
        "Lana"
    ],
    "name:fra_x_preferred":[
        "Lana"
    ],
    "name:hun_x_preferred":[
        "Lana"
    ],
    "name:ita_x_preferred":[
        "Lana"
    ],
    "name:nld_x_preferred":[
        "Lana"
    ],
    "name:nor_x_preferred":[
        "Lana"
    ],
    "name:oci_x_preferred":[
        "Lana"
    ],
    "name:pol_x_preferred":[
        "Lana"
    ],
    "name:por_x_preferred":[
        "Lana"
    ],
    "name:rus_x_preferred":[
        "\u041b\u0430\u043d\u0430"
    ],
    "name:sco_x_preferred":[
        "Lana"
    ],
    "name:spa_x_preferred":[
        "Lana"
    ],
    "name:srp_x_preferred":[
        "\u041b\u0430\u043d\u0430"
    ],
    "name:swe_x_preferred":[
        "Lana"
    ],
    "name:ukr_x_preferred":[
        "\u041b\u0430\u043d\u0430"
    ],
    "name:war_x_preferred":[
        "Lana"
    ],
    "wof:name":"Lana",
    "wof:placetype":"locality"
},
  "geometry": {"coordinates":[97.49664,24.61631],"type":"Point"}
}