{
  "type": "Feature",
  "properties": {
    "gn:admin1_code":"11.0",
    "gn:admin2_code":"MMR014D001",
    "gn:admin3_code":"MMR014005",
    "gn:asciiname":"Salondaung",
    "gn:country_code":"MM",
    "gn:dem":1518,
    "gn:feature_class":"P",
    "gn:feature_code":"PPL",
    "gn:name":"Salondaung",
    "gn:population":0,
    "gn:timezone":"Asia/Yangon",
    "iso:country":"MM",
    "wof:name":"Salondaung",
    "wof:placetype":"locality"
},
  "geometry": {"coordinates":[96.54013999999999,20.4644],"type":"Point"}
}