{
  "type": "Feature",
  "properties": {
    "gn:admin1_code":"11.0",
    "gn:admin2_code":"MMR016D003",
    "gn:admin3_code":"MMR016011",
    "gn:asciiname":"Wan Ho-namhkan",
    "gn:country_code":"MM",
    "gn:dem":946,
    "gn:feature_class":"P",
    "gn:feature_code":"PPL",
    "gn:name":"W\u0101n Ho-namhkan",
    "gn:population":0,
    "gn:timezone":"Asia/Yangon",
    "iso:country":"MM",
    "name:und_x_variant":[
        "W\u0101n Ho-namhkam",
        "W\u0101n Ho-namhkan"
    ],
    "wof:name":"Wan Ho-namhkan",
    "wof:placetype":"locality"
},
  "geometry": {"coordinates":[100.90049,21.47906],"type":"Point"}
}