{
  "type": "Feature",
  "properties": {
    "gn:admin1_code":"6.0",
    "gn:admin2_code":"MMR002D001",
    "gn:admin3_code":"MMR002004",
    "gn:asciiname":"Dawlya-hku",
    "gn:country_code":"MM",
    "gn:dem":1310,
    "gn:feature_class":"P",
    "gn:feature_code":"PPL",
    "gn:name":"Dawlya-hku",
    "gn:population":0,
    "gn:timezone":"Asia/Yangon",
    "iso:country":"MM",
    "wof:name":"Dawlya-hku",
    "wof:placetype":"locality"
},
  "geometry": {"coordinates":[97.48685999999999,19.8712],"type":"Point"}
}