{
  "type": "Feature",
  "properties": {
    "gn:admin1_code":"10.0",
    "gn:admin2_code":"MMR005D004",
    "gn:admin3_code":"MMR005020",
    "gn:asciiname":"Thetle",
    "gn:country_code":"MM",
    "gn:dem":95,
    "gn:feature_class":"P",
    "gn:feature_code":"PPL",
    "gn:name":"Thetle",
    "gn:population":0,
    "gn:timezone":"Asia/Yangon",
    "iso:country":"MM",
    "wof:name":"Thetle",
    "wof:placetype":"locality"
},
  "geometry": {"coordinates":[96.5368,24.25494],"type":"Point"}
}