{
  "type": "Feature",
  "properties": {
    "gn:admin1_code":"16.0",
    "gn:admin2_code":"MMR007D002",
    "gn:admin3_code":"MMR007013",
    "gn:asciiname":"Thandaingkhin",
    "gn:country_code":"MM",
    "gn:dem":44,
    "gn:feature_class":"P",
    "gn:feature_code":"PPL",
    "gn:name":"Thandaingkhin",
    "gn:population":0,
    "gn:timezone":"Asia/Yangon",
    "iso:country":"MM",
    "name:und_x_variant":[
        "Thardaingkin",
        "Thandaingkhin"
    ],
    "wof:name":"Thandaingkhin",
    "wof:placetype":"locality"
},
  "geometry": {"coordinates":[96.4273,18.79492],"type":"Point"}
}