{
  "type": "Feature",
  "properties": {
    "gn:admin1_code":"10.0",
    "gn:admin2_code":"MMR005D004",
    "gn:admin3_code":"MMR005026",
    "gn:asciiname":"Shinpa",
    "gn:country_code":"MM",
    "gn:dem":544,
    "gn:feature_class":"P",
    "gn:feature_code":"PPL",
    "gn:name":"Shinpa",
    "gn:population":0,
    "gn:timezone":"Asia/Yangon",
    "iso:country":"MM",
    "name:fra_x_preferred":[
        "Shinpa"
    ],
    "name:ita_x_preferred":[
        "Shinpa"
    ],
    "name:kor_x_preferred":[
        "\uc2e0\ud30c\uadf9"
    ],
    "name:zho_x_preferred":[
        "\u65b0\u6d3e\u5287"
    ],
    "wof:name":"Shinpa",
    "wof:placetype":"locality"
},
  "geometry": {"coordinates":[95.63203,24.1891],"type":"Point"}
}