{
  "type": "Feature",
  "properties": {
    "gn:admin1_code":"4.0",
    "gn:admin2_code":"MMR001D001",
    "gn:admin3_code":"MMR001001",
    "gn:asciiname":"Paneng",
    "gn:country_code":"MM",
    "gn:dem":356,
    "gn:feature_class":"P",
    "gn:feature_code":"PPL",
    "gn:name":"Paneng",
    "gn:population":0,
    "gn:timezone":"Asia/Yangon",
    "iso:country":"MM",
    "name:und_x_variant":[
        "Kumja",
        "Paneng Kumja",
        "Paneng"
    ],
    "wof:name":"Paneng",
    "wof:placetype":"locality"
},
  "geometry": {"coordinates":[97.41449,24.92172],"type":"Point"}
}