{
  "type": "Feature",
  "properties": {
    "gn:admin1_code":"10.0",
    "gn:admin2_code":"MMR005D009",
    "gn:admin3_code":"MMR005017",
    "gn:asciiname":"Tabon",
    "gn:country_code":"MM",
    "gn:dem":119,
    "gn:feature_class":"P",
    "gn:feature_code":"PPL",
    "gn:name":"Tab\u00f4n",
    "gn:population":0,
    "gn:timezone":"Asia/Yangon",
    "iso:country":"MM",
    "wof:name":"Tabon",
    "wof:placetype":"locality"
},
  "geometry": {"coordinates":[94.8776,22.53929],"type":"Point"}
}