{
  "type": "Feature",
  "properties": {
    "gn:admin1_code":"3.0",
    "gn:admin2_code":"MMR017D001",
    "gn:admin3_code":"MMR017003",
    "gn:asciiname":"Shwele-kwin",
    "gn:country_code":"MM",
    "gn:dem":8,
    "gn:feature_class":"P",
    "gn:feature_code":"PPL",
    "gn:name":"Shwele-kwin",
    "gn:population":0,
    "gn:timezone":"Asia/Yangon",
    "iso:country":"MM",
    "wof:name":"Shwele-kwin",
    "wof:placetype":"locality"
},
  "geometry": {"coordinates":[94.92872,17.21373],"type":"Point"}
}