{
  "type": "Feature",
  "properties": {
    "gn:admin1_code":"16.0",
    "gn:admin2_code":"MMR007D002",
    "gn:admin3_code":"MMR007010",
    "gn:asciiname":"Seinywa",
    "gn:country_code":"MM",
    "gn:dem":74,
    "gn:feature_class":"P",
    "gn:feature_code":"PPL",
    "gn:name":"Seinywa",
    "gn:population":0,
    "gn:timezone":"Asia/Yangon",
    "iso:country":"MM",
    "wof:name":"Seinywa",
    "wof:placetype":"locality"
},
  "geometry": {"coordinates":[96.30364,19.15281],"type":"Point"}
}