{
  "type": "Feature",
  "properties": {
    "gn:admin1_code":"16.0",
    "gn:admin2_code":"MMR007D002",
    "gn:admin3_code":"MMR007011",
    "gn:asciiname":"Yegyo",
    "gn:country_code":"MM",
    "gn:dem":27,
    "gn:feature_class":"P",
    "gn:feature_code":"PPL",
    "gn:name":"Yegyo",
    "gn:population":0,
    "gn:timezone":"Asia/Yangon",
    "iso:country":"MM",
    "wof:name":"Yegyo",
    "wof:placetype":"locality"
},
  "geometry": {"coordinates":[96.64579999999999,18.42549],"type":"Point"}
}