{
  "type": "Feature",
  "properties": {
    "gn:admin1_code":"6.0",
    "gn:admin2_code":"MMR002D002",
    "gn:admin3_code":"MMR002005",
    "gn:asciiname":"Wan Mak-uenlao",
    "gn:country_code":"MM",
    "gn:dem":223,
    "gn:feature_class":"P",
    "gn:feature_code":"PPL",
    "gn:name":"W\u0101n Mak-\u00fcnlao",
    "gn:population":0,
    "gn:timezone":"Asia/Yangon",
    "iso:country":"MM",
    "wof:name":"Wan Mak-uenlao",
    "wof:placetype":"locality"
},
  "geometry": {"coordinates":[97.35466,19.11888],"type":"Point"}
}