{
  "type": "Feature",
  "properties": {
    "gn:admin1_code":"16.0",
    "gn:admin2_code":"MMR007D002",
    "gn:admin3_code":"MMR007012",
    "gn:asciiname":"Thinbawmyaung",
    "gn:country_code":"MM",
    "gn:dem":372,
    "gn:feature_class":"P",
    "gn:feature_code":"PPL",
    "gn:name":"Thinbawmyaung",
    "gn:population":0,
    "gn:timezone":"Asia/Yangon",
    "iso:country":"MM",
    "name:und_x_variant":[
        "Thewa Myaung",
        "Thittawmyaung",
        "Thewa",
        "Thinbawmyaung"
    ],
    "wof:name":"Thinbawmyaung",
    "wof:placetype":"locality"
},
  "geometry": {"coordinates":[96.34542,18.53825],"type":"Point"}
}