{
  "type": "Feature",
  "properties": {
    "gn:admin1_code":"8.0",
    "gn:admin2_code":"MMR010D002",
    "gn:admin3_code":"MMR010011",
    "gn:asciiname":"Palaungchaunggyi",
    "gn:country_code":"MM",
    "gn:dem":1509,
    "gn:feature_class":"P",
    "gn:feature_code":"PPL",
    "gn:name":"Palaungchaunggyi",
    "gn:population":0,
    "gn:timezone":"Asia/Yangon",
    "iso:country":"MM",
    "wof:name":"Palaungchaunggyi",
    "wof:placetype":"locality"
},
  "geometry": {"coordinates":[96.49522,22.96761],"type":"Point"}
}