{
  "type": "Feature",
  "properties": {
    "gn:admin1_code":"5.0",
    "gn:admin2_code":"MMR003D003",
    "gn:admin3_code":"MMR003007",
    "gn:asciiname":"Paka",
    "gn:country_code":"MM",
    "gn:dem":26,
    "gn:feature_class":"P",
    "gn:feature_code":"PPL",
    "gn:name":"Paka",
    "gn:population":0,
    "gn:timezone":"Asia/Yangon",
    "iso:country":"MM",
    "name:bos_x_preferred":[
        "Paka"
    ],
    "name:ceb_x_preferred":[
        "Paka"
    ],
    "name:fra_x_preferred":[
        "Paka"
    ],
    "name:hrv_x_preferred":[
        "Paka"
    ],
    "name:hun_x_preferred":[
        "Paka"
    ],
    "name:nld_x_preferred":[
        "Paka"
    ],
    "name:pol_x_preferred":[
        "Paka"
    ],
    "name:slv_x_preferred":[
        "Paka"
    ],
    "name:srp_x_preferred":[
        "\u041f\u0430\u043a\u0430"
    ],
    "name:swa_x_preferred":[
        "Paka"
    ],
    "wof:name":"Paka",
    "wof:placetype":"locality"
},
  "geometry": {"coordinates":[98.30783,16.33607],"type":"Point"}
}