{
  "type": "Feature",
  "properties": {
    "gn:admin1_code":"11.0",
    "gn:admin2_code":"MMR014D001",
    "gn:admin3_code":"MMR014009",
    "gn:asciiname":"Namnein Ywahaung",
    "gn:country_code":"MM",
    "gn:dem":1347,
    "gn:feature_class":"P",
    "gn:feature_code":"PPL",
    "gn:name":"Namnein Ywahaung",
    "gn:population":0,
    "gn:timezone":"Asia/Yangon",
    "iso:country":"MM",
    "wof:name":"Namnein Ywahaung",
    "wof:placetype":"locality"
},
  "geometry": {"coordinates":[96.82953999999999,19.90346],"type":"Point"}
}