{
  "type": "Feature",
  "properties": {
    "gn:admin1_code":"3.0",
    "gn:admin2_code":"MMR017D006",
    "gn:admin3_code":"MMR017023",
    "gn:asciiname":"Kamabo",
    "gn:country_code":"MM",
    "gn:dem":5,
    "gn:feature_class":"P",
    "gn:feature_code":"PPL",
    "gn:name":"Kam\u0101bo",
    "gn:population":0,
    "gn:timezone":"Asia/Yangon",
    "iso:country":"MM",
    "wof:name":"Kamabo",
    "wof:placetype":"locality"
},
  "geometry": {"coordinates":[95.64249,16.09769],"type":"Point"}
}