{
  "type": "Feature",
  "properties": {
    "gn:admin1_code":"11.0",
    "gn:admin2_code":"MMR014D002",
    "gn:admin3_code":"MMR014015",
    "gn:asciiname":"Nawng-hen-yawn",
    "gn:country_code":"MM",
    "gn:dem":1052,
    "gn:feature_class":"P",
    "gn:feature_code":"PPL",
    "gn:name":"Nawng-hen-yawn",
    "gn:population":0,
    "gn:timezone":"Asia/Yangon",
    "iso:country":"MM",
    "name:und_x_variant":[
        "Nawng Hen Yawng",
        "Nawng-hen-yawn"
    ],
    "wof:name":"Nawng-hen-yawn",
    "wof:placetype":"locality"
},
  "geometry": {"coordinates":[97.87692,21.83402],"type":"Point"}
}