{
  "type": "Feature",
  "properties": {
    "gn:admin1_code":"5.0",
    "gn:admin2_code":"MMR003D004",
    "gn:admin3_code":"MMR003003",
    "gn:asciiname":"Bawbookyo",
    "gn:country_code":"MM",
    "gn:dem":613,
    "gn:feature_class":"P",
    "gn:feature_code":"PPL",
    "gn:name":"Bawbookyo",
    "gn:population":0,
    "gn:timezone":"Asia/Yangon",
    "iso:country":"MM",
    "name:und_x_variant":[
        "Bawbookya",
        "Bawbookyo"
    ],
    "wof:name":"Bawbookyo",
    "wof:placetype":"locality"
},
  "geometry": {"coordinates":[97.53619,18.17474],"type":"Point"}
}