{
  "type": "Feature",
  "properties": {
    "gn:admin1_code":"15.0",
    "gn:admin2_code":"MMR009D003",
    "gn:admin3_code":"MMR009016",
    "gn:asciiname":"Paungdin",
    "gn:country_code":"MM",
    "gn:dem":95,
    "gn:feature_class":"P",
    "gn:feature_code":"PPL",
    "gn:name":"Paungdin",
    "gn:population":0,
    "gn:timezone":"Asia/Yangon",
    "iso:country":"MM",
    "wof:name":"Paungdin",
    "wof:placetype":"locality"
},
  "geometry": {"coordinates":[95.37161999999999,19.46741],"type":"Point"}
}