{
  "type": "Feature",
  "properties": {
    "gn:admin1_code":"16.0",
    "gn:admin2_code":"MMR007D001",
    "gn:admin3_code":"MMR007003",
    "gn:asciiname":"Adu",
    "gn:country_code":"MM",
    "gn:dem":15,
    "gn:feature_class":"P",
    "gn:feature_code":"PPL",
    "gn:name":"Adu",
    "gn:population":0,
    "gn:timezone":"Asia/Yangon",
    "iso:country":"MM",
    "name:ceb_x_preferred":[
        "Adu"
    ],
    "name:fra_x_preferred":[
        "Adu"
    ],
    "name:heb_x_preferred":[
        "\u05d0\u05d3\u05d5"
    ],
    "name:rus_x_preferred":[
        "\u0410\u0434\u0443"
    ],
    "name:swe_x_preferred":[
        "Adu"
    ],
    "wof:name":"Adu",
    "wof:placetype":"locality"
},
  "geometry": {"coordinates":[96.66835,17.15424],"type":"Point"}
}