{
  "type": "Feature",
  "properties": {
    "gn:admin1_code":"8.0",
    "gn:admin2_code":"MMR010D005",
    "gn:admin3_code":"MMR010022",
    "gn:asciiname":"Ayadaw",
    "gn:country_code":"MM",
    "gn:dem":262,
    "gn:feature_class":"P",
    "gn:feature_code":"PPL",
    "gn:name":"Ayadaw",
    "gn:population":0,
    "gn:timezone":"Asia/Yangon",
    "iso:country":"MM",
    "name:mya_x_preferred":[
        "\u1021\u101b\u102c\u1010\u1031\u102c\u103a\u1019\u103c\u102d\u102f\u1037"
    ],
    "name:tgl_x_preferred":[
        "Ayadaw"
    ],
    "wof:name":"Ayadaw",
    "wof:placetype":"locality"
},
  "geometry": {"coordinates":[94.98745,20.91537000000001],"type":"Point"}
}