{
  "type": "Feature",
  "properties": {
    "gn:admin1_code":"11.0",
    "gn:admin2_code":"MMR014D003",
    "gn:admin3_code":"MMR014021",
    "gn:asciiname":"Ho-hpai",
    "gn:country_code":"MM",
    "gn:dem":672,
    "gn:feature_class":"P",
    "gn:feature_code":"PPL",
    "gn:name":"Ho-hpai",
    "gn:population":0,
    "gn:timezone":"Asia/Yangon",
    "iso:country":"MM",
    "wof:name":"Ho-hpai",
    "wof:placetype":"locality"
},
  "geometry": {"coordinates":[98.26777,20.3097],"type":"Point"}
}