{
  "type": "Feature",
  "properties": {
    "gn:admin1_code":"2.0",
    "gn:admin2_code":"MMR004D001",
    "gn:admin3_code":"MMR004001",
    "gn:asciiname":"Lunghrawh",
    "gn:country_code":"MM",
    "gn:dem":1040,
    "gn:feature_class":"P",
    "gn:feature_code":"PPL",
    "gn:name":"Lunghrawh",
    "gn:population":0,
    "gn:timezone":"Asia/Yangon",
    "iso:country":"MM",
    "wof:name":"Lunghrawh",
    "wof:placetype":"locality"
},
  "geometry": {"coordinates":[93.73717000000001,23.02929],"type":"Point"}
}