{
  "type": "Feature",
  "properties": {
    "gn:admin1_code":"11.0",
    "gn:admin2_code":"MMR015D003",
    "gn:admin3_code":"MMR015014",
    "gn:asciiname":"Loi-yoimanmaoe",
    "gn:country_code":"MM",
    "gn:dem":669,
    "gn:feature_class":"P",
    "gn:feature_code":"PPL",
    "gn:name":"Loi-yoimanma\u00f6",
    "gn:population":0,
    "gn:timezone":"Asia/Yangon",
    "iso:country":"MM",
    "name:und_x_variant":[
        "M\u0101n Loi-m\u0101nmao",
        "Loi-yoimanma\u00f6"
    ],
    "wof:name":"Loi-yoimanmaoe",
    "wof:placetype":"locality"
},
  "geometry": {"coordinates":[97.43299,22.04605],"type":"Point"}
}