{
  "type": "Feature",
  "properties": {
    "gn:admin1_code":"8.0",
    "gn:admin2_code":"MMR010D005",
    "gn:admin3_code":"MMR010020",
    "gn:asciiname":"Ywataza",
    "gn:country_code":"MM",
    "gn:dem":499,
    "gn:feature_class":"P",
    "gn:feature_code":"PPL",
    "gn:name":"Ywataza",
    "gn:population":0,
    "gn:timezone":"Asia/Yangon",
    "iso:country":"MM",
    "wof:name":"Ywataza",
    "wof:placetype":"locality"
},
  "geometry": {"coordinates":[95.42282,20.89431],"type":"Point"}
}