{
  "type": "Feature",
  "properties": {
    "gn:admin1_code":"11.0",
    "gn:admin2_code":"MMR016D003",
    "gn:admin3_code":"MMR016009",
    "gn:asciiname":"Wan Nawnghsamlem",
    "gn:country_code":"MM",
    "gn:dem":402,
    "gn:feature_class":"P",
    "gn:feature_code":"PPL",
    "gn:name":"W\u0101n Nawnghsamlem",
    "gn:population":0,
    "gn:timezone":"Asia/Yangon",
    "iso:country":"MM",
    "wof:name":"Wan Nawnghsamlem",
    "wof:placetype":"locality"
},
  "geometry": {"coordinates":[100.13957000000001,20.69995],"type":"Point"}
}