{
  "type": "Feature",
  "properties": {
    "gn:admin1_code":"8.0",
    "gn:admin2_code":"MMR010D004",
    "gn:admin3_code":"MMR010021",
    "gn:asciiname":"Nyaungbintha",
    "gn:country_code":"MM",
    "gn:dem":232,
    "gn:feature_class":"P",
    "gn:feature_code":"PPL",
    "gn:name":"Nyaungbintha",
    "gn:population":0,
    "gn:timezone":"Asia/Yangon",
    "iso:country":"MM",
    "wof:name":"Nyaungbintha",
    "wof:placetype":"locality"
},
  "geometry": {"coordinates":[95.66998,21.63227],"type":"Point"}
}