{
  "type": "Feature",
  "properties": {
    "gn:admin1_code":"8.0",
    "gn:admin2_code":"MMR010D003",
    "gn:admin3_code":"MMR010014",
    "gn:asciiname":"Nyaungbintha",
    "gn:country_code":"MM",
    "gn:dem":78,
    "gn:feature_class":"P",
    "gn:feature_code":"PPL",
    "gn:name":"Nyaungbintha",
    "gn:population":0,
    "gn:timezone":"Asia/Yangon",
    "iso:country":"MM",
    "wof:name":"Nyaungbintha",
    "wof:placetype":"locality"
},
  "geometry": {"coordinates":[96.16824,21.77611],"type":"Point"}
}