{
  "type": "Feature",
  "properties": {
    "gn:admin1_code":"11.0",
    "gn:admin2_code":"MMR015D003",
    "gn:admin3_code":"MMR015015",
    "gn:asciiname":"Kong-mon",
    "gn:country_code":"MM",
    "gn:dem":705,
    "gn:feature_class":"P",
    "gn:feature_code":"PPL",
    "gn:name":"Kong-mon",
    "gn:population":0,
    "gn:timezone":"Asia/Yangon",
    "iso:country":"MM",
    "wof:name":"Kong-mon",
    "wof:placetype":"locality"
},
  "geometry": {"coordinates":[97.51130999999999,22.92423],"type":"Point"}
}