{
  "type": "Feature",
  "properties": {
    "gn:admin1_code":"8.0",
    "gn:admin2_code":"MMR010D001",
    "gn:admin3_code":"MMR010006",
    "gn:asciiname":"Mandawywa",
    "gn:country_code":"MM",
    "gn:dem":82,
    "gn:feature_class":"P",
    "gn:feature_code":"PPL",
    "gn:name":"Mandawywa",
    "gn:population":0,
    "gn:timezone":"Asia/Yangon",
    "iso:country":"MM",
    "name:und_x_variant":[
        "Mandaw",
        "Mandawywa"
    ],
    "wof:name":"Mandawywa",
    "wof:placetype":"locality"
},
  "geometry": {"coordinates":[96.19123,21.78884],"type":"Point"}
}