{
  "type": "Feature",
  "properties": {
    "gn:admin1_code":"18.0",
    "gn:admin2_code":"MMR018D002",
    "gn:admin3_code":"MMR018007",
    "gn:asciiname":"Tedaung",
    "gn:country_code":"MM",
    "gn:dem":96,
    "gn:feature_class":"P",
    "gn:feature_code":"PPL",
    "gn:name":"Tedaung",
    "gn:population":0,
    "gn:timezone":"Asia/Yangon",
    "iso:country":"MM",
    "wof:name":"Tedaung",
    "wof:placetype":"locality"
},
  "geometry": {"coordinates":[96.21471,19.53299],"type":"Point"}
}