{
  "type": "Feature",
  "properties": {
    "gn:admin1_code":"11.0",
    "gn:admin2_code":"MMR015D007",
    "gn:admin3_code":"MMR015005",
    "gn:asciiname":"Wan Lakme",
    "gn:country_code":"MM",
    "gn:dem":1392,
    "gn:feature_class":"P",
    "gn:feature_code":"PPL",
    "gn:name":"W\u0101n Lakme",
    "gn:population":0,
    "gn:timezone":"Asia/Yangon",
    "iso:country":"MM",
    "wof:name":"Wan Lakme",
    "wof:placetype":"locality"
},
  "geometry": {"coordinates":[98.87101,22.48996],"type":"Point"}
}