{
  "type": "Feature",
  "properties": {
    "gn:admin1_code":"16.0",
    "gn:admin2_code":"MMR008D001",
    "gn:admin3_code":"MMR008003",
    "gn:asciiname":"Ywathit",
    "gn:country_code":"MM",
    "gn:dem":68,
    "gn:feature_class":"P",
    "gn:feature_code":"PPL",
    "gn:name":"Ywathit",
    "gn:population":0,
    "gn:timezone":"Asia/Yangon",
    "iso:country":"MM",
    "wof:name":"Ywathit",
    "wof:placetype":"locality"
},
  "geometry": {"coordinates":[95.03537,18.79546],"type":"Point"}
}