{
  "type": "Feature",
  "properties": {
    "gn:admin1_code":"16.0",
    "gn:admin2_code":"MMR008D002",
    "gn:admin3_code":"MMR008012",
    "gn:asciiname":"Ngahmwe",
    "gn:country_code":"MM",
    "gn:dem":25,
    "gn:feature_class":"P",
    "gn:feature_code":"PPL",
    "gn:name":"Ngahmwe",
    "gn:population":0,
    "gn:timezone":"Asia/Yangon",
    "iso:country":"MM",
    "wof:name":"Ngahmwe",
    "wof:placetype":"locality"
},
  "geometry": {"coordinates":[95.43733,18.26873],"type":"Point"}
}