{
  "type": "Feature",
  "properties": {
    "gn:admin1_code":"3.0",
    "gn:admin2_code":"MMR017D002",
    "gn:admin3_code":"MMR017010",
    "gn:asciiname":"Legongyi",
    "gn:country_code":"MM",
    "gn:dem":25,
    "gn:feature_class":"P",
    "gn:feature_code":"PPL",
    "gn:name":"L\u0113g\u00f4ngyi",
    "gn:population":0,
    "gn:timezone":"Asia/Yangon",
    "iso:country":"MM",
    "wof:name":"Legongyi",
    "wof:placetype":"locality"
},
  "geometry": {"coordinates":[94.98313,17.62941],"type":"Point"}
}