{
  "type": "Feature",
  "properties": {
    "gn:admin1_code":"11.0",
    "gn:admin2_code":"MMR016D003",
    "gn:admin3_code":"MMR016009",
    "gn:asciiname":"Wan Hsenkao",
    "gn:country_code":"MM",
    "gn:dem":1242,
    "gn:feature_class":"P",
    "gn:feature_code":"PPL",
    "gn:name":"W\u0101n Hsenkao",
    "gn:population":0,
    "gn:timezone":"Asia/Yangon",
    "iso:country":"MM",
    "name:und_x_variant":[
        "W\u0101n Mu-hs\u00f6 Hsenkao",
        "W\u0101n Hsenkao"
    ],
    "wof:name":"Wan Hsenkao",
    "wof:placetype":"locality"
},
  "geometry": {"coordinates":[99.66051,20.54498],"type":"Point"}
}