{
  "type": "Feature",
  "properties": {
    "gn:admin1_code":"5.0",
    "gn:admin2_code":"MMR003D002",
    "gn:admin3_code":"MMR003005",
    "gn:asciiname":"Sukali",
    "gn:country_code":"MM",
    "gn:dem":509,
    "gn:feature_class":"P",
    "gn:feature_code":"PPL",
    "gn:name":"Sukali",
    "gn:population":0,
    "gn:timezone":"Asia/Yangon",
    "iso:country":"MM",
    "name:mya_x_preferred":[
        "\u1005\u102f\u1000\u101c\u102d\u1019\u103c\u102d\u102f\u1037"
    ],
    "name:shn_x_preferred":[
        "\u1078\u102f\u1075\u101c\u102d\u104a \u101d\u1035\u1004\u103a\u1038"
    ],
    "wof:name":"Sukali",
    "wof:placetype":"locality"
},
  "geometry": {"coordinates":[98.59629,16.15276],"type":"Point"}
}