{
  "type": "Feature",
  "properties": {
    "gn:admin1_code":"11.0",
    "gn:admin2_code":"MMR015D003",
    "gn:admin3_code":"MMR015014",
    "gn:asciiname":"Na-sang",
    "gn:country_code":"MM",
    "gn:dem":929,
    "gn:feature_class":"P",
    "gn:feature_code":"PPL",
    "gn:name":"N\u0101-sang",
    "gn:population":0,
    "gn:timezone":"Asia/Yangon",
    "iso:country":"MM",
    "wof:name":"Na-sang",
    "wof:placetype":"locality"
},
  "geometry": {"coordinates":[97.84453000000001,22.18191],"type":"Point"}
}