{
  "type": "Feature",
  "properties": {
    "gn:admin1_code":"15.0",
    "gn:admin2_code":"MMR009D003",
    "gn:admin3_code":"MMR009016",
    "gn:asciiname":"Mogaung",
    "gn:country_code":"MM",
    "gn:dem":83,
    "gn:feature_class":"P",
    "gn:feature_code":"PPL",
    "gn:name":"Mogaung",
    "gn:population":0,
    "gn:timezone":"Asia/Yangon",
    "iso:country":"MM",
    "name:cat_x_preferred":[
        "Mongkawng"
    ],
    "name:epo_x_preferred":[
        "Mogaung"
    ],
    "name:fra_x_preferred":[
        "Mogaung"
    ],
    "name:ita_x_preferred":[
        "Mogaung"
    ],
    "name:jpn_x_preferred":[
        "\u30e2\u30ac\u30a6\u30f3"
    ],
    "name:kor_x_preferred":[
        "\ubaa8\uac00\uc6c5"
    ],
    "name:mya_x_preferred":[
        "\u1019\u102d\u102f\u1038\u1000\u1031\u102c\u1004\u103a\u1038\u1019\u103c\u102d\u102f\u1037"
    ],
    "name:shn_x_preferred":[
        "\u1019\u102d\u1030\u1004\u103a\u1038\u1075\u103d\u1004\u103a\u1038\u104a \u101d\u1035\u1004\u103a\u1038"
    ],
    "name:slv_x_preferred":[
        "Mogaung"
    ],
    "name:srp_x_preferred":[
        "\u041c\u043e\u0433\u0430\u0443\u043d\u0433"
    ],
    "name:swe_x_preferred":[
        "Mogaung"
    ],
    "name:tha_x_preferred":[
        "\u0e42\u0e21\u0e48\u0e01\u0e49\u0e2d\u0e07"
    ],
    "wof:name":"Mogaung",
    "wof:placetype":"locality"
},
  "geometry": {"coordinates":[95.22517999999999,19.45979],"type":"Point"}
}