{
  "type": "Feature",
  "properties": {
    "gn:admin1_code":"4.0",
    "gn:admin2_code":"MMR001D003",
    "gn:admin3_code":"MMR001010",
    "gn:asciiname":"Myazedi",
    "gn:country_code":"MM",
    "gn:dem":118,
    "gn:feature_class":"P",
    "gn:feature_code":"PPL",
    "gn:name":"Myazedi",
    "gn:population":0,
    "gn:timezone":"Asia/Yangon",
    "iso:country":"MM",
    "name:urd_x_preferred":[
        "\u0645\u06cc\u0627\u0632\u06cc\u062f\u06cc"
    ],
    "wof:name":"Myazedi",
    "wof:placetype":"locality"
},
  "geometry": {"coordinates":[97.1412,24.33133],"type":"Point"}
}