{
  "type": "Feature",
  "properties": {
    "gn:admin1_code":"10.0",
    "gn:admin2_code":"MMR005D008",
    "gn:admin3_code":"MMR005035",
    "gn:asciiname":"Heirnkut",
    "gn:country_code":"MM",
    "gn:dem":1589,
    "gn:feature_class":"P",
    "gn:feature_code":"PPL",
    "gn:name":"Heirnkut",
    "gn:population":0,
    "gn:timezone":"Asia/Yangon",
    "iso:country":"MM",
    "name:und_x_variant":[
        "Fort Keary",
        "Heirnkut"
    ],
    "wof:name":"Heirnkut",
    "wof:placetype":"locality"
},
  "geometry": {"coordinates":[94.76309000000001,25.24658],"type":"Point"}
}