{
  "type": "Feature",
  "properties": {
    "gn:admin1_code":"11.0",
    "gn:admin2_code":"MMR014D003",
    "gn:admin3_code":"MMR014019",
    "gn:asciiname":"Makka",
    "gn:country_code":"MM",
    "gn:dem":650,
    "gn:feature_class":"P",
    "gn:feature_code":"PPL",
    "gn:name":"Makk\u0101",
    "gn:population":0,
    "gn:timezone":"Asia/Yangon",
    "iso:country":"MM",
    "wof:name":"Makka",
    "wof:placetype":"locality"
},
  "geometry": {"coordinates":[98.34142,20.75978],"type":"Point"}
}