{
  "type": "Feature",
  "properties": {
    "gn:admin1_code":"10.0",
    "gn:asciiname":"Myotha",
    "gn:country_code":"MM",
    "gn:dem":179,
    "gn:feature_class":"P",
    "gn:feature_code":"PPL",
    "gn:name":"Myotha",
    "gn:population":0,
    "gn:timezone":"Asia/Yangon",
    "iso:country":"MM",
    "name:und_x_variant":[
        "Myothia",
        "Myotha"
    ],
    "wof:name":"Myotha",
    "wof:placetype":"locality"
},
  "geometry": {"coordinates":[95.71044999999999,21.68894],"type":"Point"}
}