{
  "type": "Feature",
  "properties": {
    "gn:admin1_code":"10.0",
    "gn:admin2_code":"MMR005D004",
    "gn:admin3_code":"MMR005023",
    "gn:asciiname":"Napin",
    "gn:country_code":"MM",
    "gn:dem":227,
    "gn:feature_class":"P",
    "gn:feature_code":"PPL",
    "gn:name":"Napin",
    "gn:population":0,
    "gn:timezone":"Asia/Yangon",
    "iso:country":"MM",
    "wof:name":"Napin",
    "wof:placetype":"locality"
},
  "geometry": {"coordinates":[95.63565,24.50855],"type":"Point"}
}