{
  "type": "Feature",
  "properties": {
    "gn:admin1_code":"11.0",
    "gn:admin2_code":"MMR014D001",
    "gn:admin3_code":"MMR014007",
    "gn:asciiname":"Gwebin",
    "gn:country_code":"MM",
    "gn:dem":1032,
    "gn:feature_class":"P",
    "gn:feature_code":"PPL",
    "gn:name":"Gwebin",
    "gn:population":0,
    "gn:timezone":"Asia/Yangon",
    "iso:country":"MM",
    "wof:name":"Gwebin",
    "wof:placetype":"locality"
},
  "geometry": {"coordinates":[96.44611999999999,21.05087],"type":"Point"}
}