{
  "type": "Feature",
  "properties": {
    "gn:admin1_code":"1.0",
    "gn:admin2_code":"MMR012D004",
    "gn:admin3_code":"MMR012017",
    "gn:asciiname":"Inbon",
    "gn:country_code":"MM",
    "gn:dem":17,
    "gn:feature_class":"P",
    "gn:feature_code":"PPL",
    "gn:name":"Inbon",
    "gn:population":0,
    "gn:timezone":"Asia/Yangon",
    "iso:country":"MM",
    "wof:name":"Inbon",
    "wof:placetype":"locality"
},
  "geometry": {"coordinates":[94.56757,17.81411],"type":"Point"}
}