{
  "type": "Feature",
  "properties": {
    "gn:admin1_code":"17.0",
    "gn:admin2_code":"MMR013D002",
    "gn:admin3_code":"MMR013020",
    "gn:asciiname":"Tewainggyi",
    "gn:country_code":"MM",
    "gn:dem":6,
    "gn:feature_class":"P",
    "gn:feature_code":"PPL",
    "gn:name":"Tewainggyi",
    "gn:population":0,
    "gn:timezone":"Asia/Yangon",
    "iso:country":"MM",
    "wof:name":"Tewainggyi",
    "wof:placetype":"locality"
},
  "geometry": {"coordinates":[96.27207,16.91061],"type":"Point"}
}