{
  "type": "Feature",
  "properties": {
    "gn:admin1_code":"11.0",
    "gn:asciiname":"Hangnam",
    "gn:country_code":"MM",
    "gn:dem":672,
    "gn:feature_class":"P",
    "gn:feature_code":"PPL",
    "gn:name":"Hangnam",
    "gn:population":0,
    "gn:timezone":"Asia/Yangon",
    "iso:country":"MM",
    "wof:name":"Hangnam",
    "wof:placetype":"locality"
},
  "geometry": {"coordinates":[96.52849000000001,22.8189],"type":"Point"}
}