{
  "type": "Feature",
  "properties": {
    "gn:admin1_code":"10.0",
    "gn:admin2_code":"MMR005D002",
    "gn:admin3_code":"MMR005004",
    "gn:asciiname":"Kanthagon",
    "gn:country_code":"MM",
    "gn:dem":109,
    "gn:feature_class":"P",
    "gn:feature_code":"PPL",
    "gn:name":"Kanthagon",
    "gn:population":0,
    "gn:timezone":"Asia/Yangon",
    "iso:country":"MM",
    "wof:name":"Kanthagon",
    "wof:placetype":"locality"
},
  "geometry": {"coordinates":[95.54415,22.65246],"type":"Point"}
}