{
  "type": "Feature",
  "properties": {
    "gn:admin1_code":"11.0",
    "gn:admin2_code":"MMR014D001",
    "gn:admin3_code":"MMR014004",
    "gn:asciiname":"Pangsong",
    "gn:country_code":"MM",
    "gn:dem":1006,
    "gn:feature_class":"P",
    "gn:feature_code":"PPL",
    "gn:name":"P\u0101ngsong",
    "gn:population":0,
    "gn:timezone":"Asia/Yangon",
    "iso:country":"MM",
    "wof:name":"Pangsong",
    "wof:placetype":"locality"
},
  "geometry": {"coordinates":[97.21205999999999,20.29037000000001],"type":"Point"}
}