{
  "type": "Feature",
  "properties": {
    "gn:admin1_code":"2.0",
    "gn:admin2_code":"MMR004D003",
    "gn:admin3_code":"MMR004002",
    "gn:asciiname":"Hausen",
    "gn:country_code":"MM",
    "gn:dem":1273,
    "gn:feature_class":"P",
    "gn:feature_code":"PPL",
    "gn:name":"Hausen",
    "gn:population":0,
    "gn:timezone":"Asia/Yangon",
    "iso:country":"MM",
    "wof:name":"Hausen",
    "wof:placetype":"locality"
},
  "geometry": {"coordinates":[93.65000000000001,22.31667],"type":"Point"}
}