{
  "type": "Feature",
  "properties": {
    "gn:admin1_code":"1.0",
    "gn:admin2_code":"MMR012D002",
    "gn:admin3_code":"MMR012009",
    "gn:asciiname":"Panthara",
    "gn:country_code":"MM",
    "gn:dem":15,
    "gn:feature_class":"P",
    "gn:feature_code":"PPL",
    "gn:name":"Panthara",
    "gn:population":0,
    "gn:timezone":"Asia/Yangon",
    "iso:country":"MM",
    "wof:name":"Panthara",
    "wof:placetype":"locality"
},
  "geometry": {"coordinates":[92.23999999999999,21.14111],"type":"Point"}
}