{
  "type": "Feature",
  "properties": {
    "gn:admin1_code":"8.0",
    "gn:admin2_code":"MMR010D003",
    "gn:admin3_code":"MMR010015",
    "gn:asciiname":"Yeywa",
    "gn:country_code":"MM",
    "gn:dem":104,
    "gn:feature_class":"P",
    "gn:feature_code":"PPL",
    "gn:name":"Yeywa",
    "gn:population":0,
    "gn:timezone":"Asia/Yangon",
    "iso:country":"MM",
    "wof:name":"Yeywa",
    "wof:placetype":"locality"
},
  "geometry": {"coordinates":[96.19181,21.4518],"type":"Point"}
}