{
  "type": "Feature",
  "properties": {
    "gn:admin1_code":"11.0",
    "gn:admin2_code":"MMR016D003",
    "gn:admin3_code":"MMR016009",
    "gn:asciiname":"Wan Ho-moeng",
    "gn:country_code":"MM",
    "gn:dem":924,
    "gn:elevation":"918.0",
    "gn:feature_class":"P",
    "gn:feature_code":"PPL",
    "gn:name":"W\u0101n H\u014d-m\u00f6ng",
    "gn:population":0,
    "gn:timezone":"Asia/Yangon",
    "iso:country":"MM",
    "wof:name":"Wan Ho-moeng",
    "wof:placetype":"locality"
},
  "geometry": {"coordinates":[99.57745,20.70067],"type":"Point"}
}