{
  "type": "Feature",
  "properties": {
    "gn:admin1_code":"4.0",
    "gn:admin2_code":"MMR001D003",
    "gn:admin3_code":"MMR001011",
    "gn:asciiname":"Hgnettada",
    "gn:country_code":"MM",
    "gn:dem":122,
    "gn:feature_class":"P",
    "gn:feature_code":"PPL",
    "gn:name":"Hgnettada",
    "gn:population":0,
    "gn:timezone":"Asia/Yangon",
    "iso:country":"MM",
    "wof:name":"Hgnettada",
    "wof:placetype":"locality"
},
  "geometry": {"coordinates":[96.75887,24.14591],"type":"Point"}
}