{
  "type": "Feature",
  "properties": {
    "gn:admin1_code":"6.0",
    "gn:admin2_code":"MMR002D002",
    "gn:admin3_code":"MMR002005",
    "gn:asciiname":"Ho-hwe-man",
    "gn:country_code":"MM",
    "gn:dem":553,
    "gn:feature_class":"P",
    "gn:feature_code":"PPL",
    "gn:name":"Ho-hw\u00e8-m\u0101n",
    "gn:population":0,
    "gn:timezone":"Asia/Yangon",
    "iso:country":"MM",
    "wof:name":"Ho-hwe-man",
    "wof:placetype":"locality"
},
  "geometry": {"coordinates":[97.55018,19.29447],"type":"Point"}
}