{
  "type": "Feature",
  "properties": {
    "gn:admin1_code":"10.0",
    "gn:admin2_code":"MMR005D004",
    "gn:admin3_code":"MMR005022",
    "gn:asciiname":"Konywa",
    "gn:country_code":"MM",
    "gn:dem":96,
    "gn:feature_class":"P",
    "gn:feature_code":"PPL",
    "gn:name":"Konywa",
    "gn:population":0,
    "gn:timezone":"Asia/Yangon",
    "iso:country":"MM",
    "wof:name":"Konywa",
    "wof:placetype":"locality"
},
  "geometry": {"coordinates":[96.0436,23.83586],"type":"Point"}
}