{
  "type": "Feature",
  "properties": {
    "gn:admin1_code":"16.0",
    "gn:admin2_code":"MMR007D002",
    "gn:admin3_code":"MMR007012",
    "gn:asciiname":"Myapago Kayinywa",
    "gn:country_code":"MM",
    "gn:dem":26,
    "gn:feature_class":"P",
    "gn:feature_code":"PPL",
    "gn:name":"Myapago Kayinywa",
    "gn:population":0,
    "gn:timezone":"Asia/Yangon",
    "iso:country":"MM",
    "name:und_x_variant":[
        "Myapagokaren",
        "Myapago Kayinywa"
    ],
    "wof:name":"Myapago Kayinywa",
    "wof:placetype":"locality"
},
  "geometry": {"coordinates":[96.66925999999999,18.32014],"type":"Point"}
}