{
  "type": "Feature",
  "properties": {
    "gn:admin1_code":"11.0",
    "gn:admin2_code":"MMR014D003",
    "gn:admin3_code":"MMR014019",
    "gn:asciiname":"Kongkeng",
    "gn:country_code":"MM",
    "gn:dem":919,
    "gn:feature_class":"P",
    "gn:feature_code":"PPL",
    "gn:name":"Kongkeng",
    "gn:population":0,
    "gn:timezone":"Asia/Yangon",
    "iso:country":"MM",
    "wof:name":"Kongkeng",
    "wof:placetype":"locality"
},
  "geometry": {"coordinates":[98.05219,20.56033],"type":"Point"}
}