{
  "type": "Feature",
  "properties": {
    "gn:admin1_code":"1.0",
    "gn:admin2_code":"MMR012D003",
    "gn:admin3_code":"MMR012012",
    "gn:asciiname":"Budaunggwe",
    "gn:country_code":"MM",
    "gn:dem":19,
    "gn:feature_class":"P",
    "gn:feature_code":"PPL",
    "gn:name":"Budaunggwe",
    "gn:population":0,
    "gn:timezone":"Asia/Yangon",
    "iso:country":"MM",
    "wof:name":"Budaunggwe",
    "wof:placetype":"locality"
},
  "geometry": {"coordinates":[93.66759999999999,18.83059],"type":"Point"}
}