{
  "type": "Feature",
  "properties": {
    "gn:admin1_code":"11.0",
    "gn:admin2_code":"MMR016D002",
    "gn:admin3_code":"MMR016008",
    "gn:asciiname":"Moeng Kyawt",
    "gn:country_code":"MM",
    "gn:dem":620,
    "gn:feature_class":"P",
    "gn:feature_code":"PPL",
    "gn:name":"M\u00f6ng Kyawt",
    "gn:population":0,
    "gn:timezone":"Asia/Yangon",
    "iso:country":"MM",
    "name:und_x_variant":[
        "Pangyun",
        "M\u00f6ng Kyawt"
    ],
    "wof:name":"Moeng Kyawt",
    "wof:placetype":"locality"
},
  "geometry": {"coordinates":[98.74666999999999,19.951],"type":"Point"}
}