{
  "type": "Feature",
  "properties": {
    "gn:admin1_code":"13.0",
    "gn:admin2_code":"MMR011D001",
    "gn:admin3_code":"MMR011006",
    "gn:asciiname":"Hnitsok",
    "gn:country_code":"MM",
    "gn:dem":22,
    "gn:feature_class":"P",
    "gn:feature_code":"PPL",
    "gn:name":"Hnitsok",
    "gn:population":0,
    "gn:timezone":"Asia/Yangon",
    "iso:country":"MM",
    "wof:name":"Hnitsok",
    "wof:placetype":"locality"
},
  "geometry": {"coordinates":[97.88912000000001,15.42694],"type":"Point"}
}