{
  "type": "Feature",
  "properties": {
    "gn:admin1_code":"8.0",
    "gn:admin2_code":"MMR010D004",
    "gn:admin3_code":"MMR010021",
    "gn:asciiname":"Thayetkan",
    "gn:country_code":"MM",
    "gn:dem":208,
    "gn:feature_class":"P",
    "gn:feature_code":"PPL",
    "gn:name":"Thayetkan",
    "gn:population":0,
    "gn:timezone":"Asia/Yangon",
    "iso:country":"MM",
    "wof:name":"Thayetkan",
    "wof:placetype":"locality"
},
  "geometry": {"coordinates":[95.73383,21.65041],"type":"Point"}
}