{
  "type": "Feature",
  "properties": {
    "gn:admin1_code":"15.0",
    "gn:admin2_code":"MMR009D004",
    "gn:admin3_code":"MMR009021",
    "gn:asciiname":"Myogintha",
    "gn:country_code":"MM",
    "gn:dem":185,
    "gn:feature_class":"P",
    "gn:feature_code":"PPL",
    "gn:name":"Myogintha",
    "gn:population":0,
    "gn:timezone":"Asia/Yangon",
    "iso:country":"MM",
    "wof:name":"Myogintha",
    "wof:placetype":"locality"
},
  "geometry": {"coordinates":[94.51545,21.50644],"type":"Point"}
}