{
  "type": "Feature",
  "properties": {
    "gn:admin1_code":"1.0",
    "gn:admin2_code":"MMR012D001",
    "gn:admin3_code":"MMR012002",
    "gn:asciiname":"Awrama Hkamwe",
    "gn:country_code":"MM",
    "gn:dem":36,
    "gn:feature_class":"P",
    "gn:feature_code":"PPL",
    "gn:name":"Awrama Hkamwe",
    "gn:population":0,
    "gn:timezone":"Asia/Yangon",
    "iso:country":"MM",
    "wof:name":"Awrama Hkamwe",
    "wof:placetype":"locality"
},
  "geometry": {"coordinates":[92.78660000000001,20.67717],"type":"Point"}
}