{
  "type": "Feature",
  "properties": {
    "gn:admin1_code":"11.0",
    "gn:admin2_code":"MMR015D006",
    "gn:admin3_code":"MMR015021",
    "gn:asciiname":"Taklu",
    "gn:country_code":"MM",
    "gn:dem":1767,
    "gn:feature_class":"P",
    "gn:feature_code":"PPL",
    "gn:name":"Taklu",
    "gn:population":0,
    "gn:timezone":"Asia/Yangon",
    "iso:country":"MM",
    "name:und_x_variant":[
        "Takiu",
        "Taklu"
    ],
    "wof:name":"Taklu",
    "wof:placetype":"locality"
},
  "geometry": {"coordinates":[98.8711,23.38035],"type":"Point"}
}