{
  "type": "Feature",
  "properties": {
    "gn:admin1_code":"11.0",
    "gn:admin2_code":"MMR016D003",
    "gn:admin3_code":"MMR016009",
    "gn:asciiname":"Wan Sa-tawke",
    "gn:country_code":"MM",
    "gn:dem":1354,
    "gn:feature_class":"P",
    "gn:feature_code":"PPL",
    "gn:name":"W\u0101n Sa-tawk\u0113",
    "gn:population":0,
    "gn:timezone":"Asia/Yangon",
    "iso:country":"MM",
    "name:und_x_variant":[
        "W\u0101n Sa-tawk\u0101",
        "W\u0101n Sa-tawk\u0113"
    ],
    "wof:name":"Wan Sa-tawke",
    "wof:placetype":"locality"
},
  "geometry": {"coordinates":[99.62341000000001,20.69133],"type":"Point"}
}