{
  "type": "Feature",
  "properties": {
    "gn:admin1_code":"10.0",
    "gn:admin2_code":"MMR005D001",
    "gn:admin3_code":"MMR005003",
    "gn:asciiname":"Anyon",
    "gn:country_code":"MM",
    "gn:dem":67,
    "gn:feature_class":"P",
    "gn:feature_code":"PPL",
    "gn:name":"Anyon",
    "gn:population":0,
    "gn:timezone":"Asia/Yangon",
    "iso:country":"MM",
    "name:deu_x_preferred":[
        "Anyon"
    ],
    "name:fra_x_preferred":[
        "Anyon"
    ],
    "name:ita_x_preferred":[
        "Qualunquone"
    ],
    "name:jpn_x_preferred":[
        "\u30a8\u30cb\u30aa\u30f3"
    ],
    "name:kor_x_preferred":[
        "\uc560\ub2c8\uc628"
    ],
    "name:nno_x_preferred":[
        "Anyon"
    ],
    "name:pnb_x_preferred":[
        "\u0627\u0646\u06cc\u0648\u0646"
    ],
    "name:pol_x_preferred":[
        "Anyon"
    ],
    "name:rus_x_preferred":[
        "\u042d\u043d\u0438\u043e\u043d"
    ],
    "name:ukr_x_preferred":[
        "\u0415\u043d\u0456\u043e\u043d"
    ],
    "name:zho_x_preferred":[
        "\u4efb\u610f\u5b50"
    ],
    "wof:name":"Anyon",
    "wof:placetype":"locality"
},
  "geometry": {"coordinates":[95.4071,21.77894],"type":"Point"}
}