{
  "type": "Feature",
  "properties": {
    "gn:admin1_code":"10.0",
    "gn:asciiname":"Chaunggwa",
    "gn:country_code":"MM",
    "gn:dem":111,
    "gn:feature_class":"P",
    "gn:feature_code":"PPL",
    "gn:name":"Chaunggwa",
    "gn:population":0,
    "gn:timezone":"Asia/Yangon",
    "iso:country":"MM",
    "name:und_x_variant":[
        "Chaungwa",
        "Chaunggwa"
    ],
    "wof:name":"Chaunggwa",
    "wof:placetype":"locality"
},
  "geometry": {"coordinates":[95.92393,21.67197],"type":"Point"}
}