{
  "type": "Feature",
  "properties": {
    "gn:admin1_code":"11.0",
    "gn:admin2_code":"MMR016D003",
    "gn:admin3_code":"MMR016011",
    "gn:asciiname":"Keng Kum",
    "gn:country_code":"MM",
    "gn:dem":450,
    "gn:feature_class":"P",
    "gn:feature_code":"PPL",
    "gn:name":"K\u0113ng K\u016bm",
    "gn:population":0,
    "gn:timezone":"Asia/Yangon",
    "iso:country":"MM",
    "wof:name":"Keng Kum",
    "wof:placetype":"locality"
},
  "geometry": {"coordinates":[100.63831999999999,21.06715],"type":"Point"}
}