{
  "type": "Feature",
  "properties": {
    "gn:admin1_code":"10.0",
    "gn:admin2_code":"MMR005D008",
    "gn:admin3_code":"MMR005036",
    "gn:asciiname":"Lasam Nawkun",
    "gn:country_code":"MM",
    "gn:dem":1633,
    "gn:feature_class":"P",
    "gn:feature_code":"PPL",
    "gn:name":"Las\u0101m Nawkun",
    "gn:population":0,
    "gn:timezone":"Asia/Yangon",
    "iso:country":"MM",
    "wof:name":"Lasam Nawkun",
    "wof:placetype":"locality"
},
  "geometry": {"coordinates":[95.46386,26.39805],"type":"Point"}
}