{
  "type": "Feature",
  "properties": {
    "gn:admin1_code":"10.0",
    "gn:admin2_code":"MMR005D003",
    "gn:admin3_code":"MMR005014",
    "gn:asciiname":"Taunggon",
    "gn:country_code":"MM",
    "gn:dem":136,
    "gn:feature_class":"P",
    "gn:feature_code":"PPL",
    "gn:name":"Taunggon",
    "gn:population":0,
    "gn:timezone":"Asia/Yangon",
    "iso:country":"MM",
    "wof:name":"Taunggon",
    "wof:placetype":"locality"
},
  "geometry": {"coordinates":[95.33723000000001,22.47713],"type":"Point"}
}