{
  "type": "Feature",
  "properties": {
    "gn:admin1_code":"16.0",
    "gn:admin2_code":"MMR008D001",
    "gn:admin3_code":"MMR008002",
    "gn:asciiname":"Kyawhlehmwa",
    "gn:country_code":"MM",
    "gn:dem":244,
    "gn:feature_class":"P",
    "gn:feature_code":"PPL",
    "gn:name":"Kyawhlehmwa",
    "gn:population":0,
    "gn:timezone":"Asia/Yangon",
    "iso:country":"MM",
    "wof:name":"Kyawhlehmwa",
    "wof:placetype":"locality"
},
  "geometry": {"coordinates":[95.69564,19.11453],"type":"Point"}
}