{
  "type": "Feature",
  "properties": {
    "gn:admin1_code":"10.0",
    "gn:asciiname":"Thangedaw",
    "gn:country_code":"MM",
    "gn:dem":80,
    "gn:feature_class":"P",
    "gn:feature_code":"PPL",
    "gn:name":"Thangedaw",
    "gn:population":0,
    "gn:timezone":"Asia/Yangon",
    "iso:country":"MM",
    "wof:name":"Thangedaw",
    "wof:placetype":"locality"
},
  "geometry": {"coordinates":[95.94016000000001,21.79145],"type":"Point"}
}