{
  "type": "Feature",
  "properties": {
    "gn:admin1_code":"11.0",
    "gn:admin2_code":"MMR015D008",
    "gn:admin3_code":"MMR015017",
    "gn:asciiname":"Padu",
    "gn:country_code":"MM",
    "gn:dem":1294,
    "gn:feature_class":"P",
    "gn:feature_code":"PPL",
    "gn:name":"Padu",
    "gn:population":0,
    "gn:timezone":"Asia/Yangon",
    "iso:country":"MM",
    "name:und_x_variant":[
        "Ngawnpadu",
        "Padu"
    ],
    "wof:name":"Padu",
    "wof:placetype":"locality"
},
  "geometry": {"coordinates":[96.84545,23.29009],"type":"Point"}
}