{
  "type": "Feature",
  "properties": {
    "gn:admin1_code":"6.0",
    "gn:admin2_code":"MMR002D001",
    "gn:admin3_code":"MMR002002",
    "gn:asciiname":"Daw Gla-te",
    "gn:country_code":"MM",
    "gn:dem":908,
    "gn:feature_class":"P",
    "gn:feature_code":"PPL",
    "gn:name":"Daw Gla-te",
    "gn:population":0,
    "gn:timezone":"Asia/Yangon",
    "iso:country":"MM",
    "wof:name":"Daw Gla-te",
    "wof:placetype":"locality"
},
  "geometry": {"coordinates":[97.20948,19.60517],"type":"Point"}
}