{
  "type": "Feature",
  "properties": {
    "gn:admin1_code":"8.0",
    "gn:admin2_code":"MMR010D005",
    "gn:admin3_code":"MMR010020",
    "gn:asciiname":"Kyatkon",
    "gn:country_code":"MM",
    "gn:dem":271,
    "gn:feature_class":"P",
    "gn:feature_code":"PPL",
    "gn:name":"Kyatkon",
    "gn:population":0,
    "gn:timezone":"Asia/Yangon",
    "iso:country":"MM",
    "wof:name":"Kyatkon",
    "wof:placetype":"locality"
},
  "geometry": {"coordinates":[95.24473,20.80811],"type":"Point"}
}