{
  "type": "Feature",
  "properties": {
    "gn:admin1_code":"10.0",
    "gn:admin2_code":"MMR005D002",
    "gn:admin3_code":"MMR005007",
    "gn:asciiname":"Katta",
    "gn:country_code":"MM",
    "gn:dem":245,
    "gn:feature_class":"P",
    "gn:feature_code":"PPL",
    "gn:name":"Katta",
    "gn:population":0,
    "gn:timezone":"Asia/Yangon",
    "iso:country":"MM",
    "wof:name":"Katta",
    "wof:placetype":"locality"
},
  "geometry": {"coordinates":[95.84269,23.39392],"type":"Point"}
}