{
  "type": "Feature",
  "properties": {
    "gn:admin1_code":"1.0",
    "gn:admin2_code":"MMR012D002",
    "gn:admin3_code":"MMR012009",
    "gn:asciiname":"Letyagyaung",
    "gn:country_code":"MM",
    "gn:dem":24,
    "gn:feature_class":"P",
    "gn:feature_code":"PPL",
    "gn:name":"Letyagyaung",
    "gn:population":0,
    "gn:timezone":"Asia/Yangon",
    "iso:country":"MM",
    "wof:name":"Letyagyaung",
    "wof:placetype":"locality"
},
  "geometry": {"coordinates":[92.35549,21.28966],"type":"Point"}
}