{
  "type": "Feature",
  "properties": {
    "gn:admin1_code":"8.0",
    "gn:admin2_code":"MMR010D002",
    "gn:admin3_code":"MMR010012",
    "gn:asciiname":"Thabeikkyin",
    "gn:country_code":"MM",
    "gn:dem":97,
    "gn:feature_class":"P",
    "gn:feature_code":"PPL",
    "gn:name":"Thabeikkyin",
    "gn:population":0,
    "gn:timezone":"Asia/Yangon",
    "iso:country":"MM",
    "name:mya_x_preferred":[
        "\u101e\u1015\u102d\u1010\u103a\u1000\u103b\u1004\u103a\u1038\u1019\u103c\u102d\u102f\u1037"
    ],
    "name:shn_x_preferred":[
        "\u1010\u1015\u1035\u1075\u103a\u1089\u1075\u103b\u102d\u107c\u103a\u1038\u104a \u101d\u1035\u1004\u103a\u1038"
    ],
    "name:und_x_variant":[
        "Thabeitkyin",
        "Thabeitkyan",
        "Thabeikkyin"
    ],
    "wof:name":"Thabeikkyin",
    "wof:placetype":"locality"
},
  "geometry": {"coordinates":[95.97432999999999,22.88504],"type":"Point"}
}