{
  "type": "Feature",
  "properties": {
    "gn:admin1_code":"8.0",
    "gn:admin2_code":"MMR010D002",
    "gn:admin3_code":"MMR010012",
    "gn:asciiname":"Thabeikkyin",
    "gn:country_code":"MM",
    "gn:dem":97,
    "gn:feature_class":"P",
    "gn:feature_code":"PPL",
    "gn:name":"Thabeikkyin",
    "gn:population":0,
    "gn:timezone":"Asia/Yangon",
    "iso:country":"MM",
    "name:und_x_variant":[
        "Thabeitkyin",
        "Thabeitkyan",
        "Thabeikkyin"
    ],
    "wof:name":"Thabeikkyin",
    "wof:placetype":"locality"
},
  "geometry": {"coordinates":[95.97432999999999,22.88504],"type":"Point"}
}