{
  "type": "Feature",
  "properties": {
    "gn:admin1_code":"13.0",
    "gn:admin2_code":"MMR011D002",
    "gn:admin3_code":"MMR011008",
    "gn:asciiname":"Tanbingyaung",
    "gn:country_code":"MM",
    "gn:dem":9,
    "gn:feature_class":"P",
    "gn:feature_code":"PPL",
    "gn:name":"Tanbingyaung",
    "gn:population":0,
    "gn:timezone":"Asia/Yangon",
    "iso:country":"MM",
    "wof:name":"Tanbingyaung",
    "wof:placetype":"locality"
},
  "geometry": {"coordinates":[97.289,16.78029],"type":"Point"}
}