{
  "type": "Feature",
  "properties": {
    "gn:admin1_code":"4.0",
    "gn:admin2_code":"MMR001D001",
    "gn:admin3_code":"MMR001003",
    "gn:asciiname":"Lahti Ga",
    "gn:country_code":"MM",
    "gn:dem":922,
    "gn:feature_class":"P",
    "gn:feature_code":"PPL",
    "gn:name":"Lahti Ga",
    "gn:population":0,
    "gn:timezone":"Asia/Yangon",
    "iso:country":"MM",
    "wof:name":"Lahti Ga",
    "wof:placetype":"locality"
},
  "geometry": {"coordinates":[97.98842,26.52031],"type":"Point"}
}