{
  "type": "Feature",
  "properties": {
    "gn:admin1_code":"11.0",
    "gn:admin2_code":"MMR016D003",
    "gn:admin3_code":"MMR016009",
    "gn:asciiname":"Wan Ra-sa-hkoen",
    "gn:country_code":"MM",
    "gn:dem":767,
    "gn:feature_class":"P",
    "gn:feature_code":"PPL",
    "gn:name":"W\u0101n Ra-sa-hk\u00f6n",
    "gn:population":0,
    "gn:timezone":"Asia/Yangon",
    "iso:country":"MM",
    "wof:name":"Wan Ra-sa-hkoen",
    "wof:placetype":"locality"
},
  "geometry": {"coordinates":[100.44638999999999,20.87083],"type":"Point"}
}