{
  "type": "Feature",
  "properties": {
    "gn:admin1_code":"11.0",
    "gn:admin2_code":"MMR015D001",
    "gn:admin3_code":"MMR015020",
    "gn:asciiname":"Man Kawng Song",
    "gn:country_code":"MM",
    "gn:dem":1190,
    "gn:feature_class":"P",
    "gn:feature_code":"PPL",
    "gn:name":"M\u0101n Kawng Song",
    "gn:population":0,
    "gn:timezone":"Asia/Yangon",
    "iso:country":"MM",
    "wof:name":"Man Kawng Song",
    "wof:placetype":"locality"
},
  "geometry": {"coordinates":[98.56010999999999,23.59795],"type":"Point"}
}