{
  "type": "Feature",
  "properties": {
    "gn:admin1_code":"6.0",
    "gn:admin2_code":"MMR002D001",
    "gn:admin3_code":"MMR002004",
    "gn:asciiname":"Dawhto-plo",
    "gn:country_code":"MM",
    "gn:dem":1134,
    "gn:feature_class":"P",
    "gn:feature_code":"PPL",
    "gn:name":"Dawhto-plo",
    "gn:population":0,
    "gn:timezone":"Asia/Yangon",
    "iso:country":"MM",
    "wof:name":"Dawhto-plo",
    "wof:placetype":"locality"
},
  "geometry": {"coordinates":[97.47301,19.6439],"type":"Point"}
}