{
  "type": "Feature",
  "properties": {
    "gn:admin1_code":"15.0",
    "gn:admin2_code":"MMR009D001",
    "gn:admin3_code":"MMR009003",
    "gn:asciiname":"Mingan",
    "gn:country_code":"MM",
    "gn:dem":76,
    "gn:feature_class":"P",
    "gn:feature_code":"PPL",
    "gn:name":"Mingan",
    "gn:population":0,
    "gn:timezone":"Asia/Yangon",
    "iso:country":"MM",
    "name:ben_x_preferred":[
        "\u09ae\u09bf\u0982\u0997\u09be\u09a8"
    ],
    "name:ell_x_preferred":[
        "\u039c\u03af\u03bd\u03b3\u03ba\u03b1\u03bd"
    ],
    "name:fas_x_preferred":[
        "\u0645\u06cc\u0646\u06af\u0627\u0646"
    ],
    "name:heb_x_preferred":[
        "\u05de\u05d9\u05e0\u05d2\u05df"
    ],
    "name:hin_x_preferred":[
        "\u092e\u093f\u0902\u0917\u0928"
    ],
    "name:hun_x_preferred":[
        "Mingan"
    ],
    "name:jpn_x_preferred":[
        "\u30df\u30f3\u30ac\u30f3"
    ],
    "name:kor_x_preferred":[
        "\ubc0d\uac04"
    ],
    "name:pol_x_preferred":[
        "Mingan"
    ],
    "name:rus_x_preferred":[
        "\u041c\u0438\u043d\u0433\u0430\u043d"
    ],
    "name:tur_x_preferred":[
        "Mingan"
    ],
    "name:ukr_x_preferred":[
        "\u041c\u0456\u043d\u0433\u0430\u043d"
    ],
    "name:urd_x_preferred":[
        "\u0645\u0646\u06af\u0627\u0646"
    ],
    "name:vie_x_preferred":[
        "Mingan"
    ],
    "name:zho_cn_x_preferred":[
        "\u660e\u6839"
    ],
    "name:zho_tw_x_preferred":[
        "\u6c11\u5b89"
    ],
    "wof:name":"Mingan",
    "wof:placetype":"locality"
},
  "geometry": {"coordinates":[94.75819,20.72162],"type":"Point"}
}