{
  "type": "Feature",
  "properties": {
    "gn:admin1_code":"2.0",
    "gn:admin2_code":"MMR004D002",
    "gn:admin3_code":"MMR004008",
    "gn:asciiname":"Mali",
    "gn:country_code":"MM",
    "gn:dem":1222,
    "gn:feature_class":"P",
    "gn:feature_code":"PPL",
    "gn:name":"Mali",
    "gn:population":0,
    "gn:timezone":"Asia/Yangon",
    "iso:country":"MM",
    "wof:name":"Mali",
    "wof:placetype":"locality"
},
  "geometry": {"coordinates":[93.81742,21.16769],"type":"Point"}
}