{
  "type": "Feature",
  "properties": {
    "gn:admin1_code":"11.0",
    "gn:admin2_code":"MMR014D002",
    "gn:admin3_code":"MMR014016",
    "gn:asciiname":"Lukhpakha",
    "gn:country_code":"MM",
    "gn:dem":840,
    "gn:feature_class":"P",
    "gn:feature_code":"PPL",
    "gn:name":"Lukhpakha",
    "gn:population":0,
    "gn:timezone":"Asia/Yangon",
    "iso:country":"MM",
    "wof:name":"Lukhpakha",
    "wof:placetype":"locality"
},
  "geometry": {"coordinates":[97.50006999999999,22.00539],"type":"Point"}
}