{
  "type": "Feature",
  "properties": {
    "gn:admin1_code":"16.0",
    "gn:admin2_code":"MMR007D002",
    "gn:admin3_code":"MMR007011",
    "gn:asciiname":"Hledobo",
    "gn:country_code":"MM",
    "gn:dem":189,
    "gn:feature_class":"P",
    "gn:feature_code":"PPL",
    "gn:name":"Hl\u00e8dobo",
    "gn:population":0,
    "gn:timezone":"Asia/Yangon",
    "iso:country":"MM",
    "name:und_x_variant":[
        "Hi\u00e8dobo",
        "Hl\u00e8dobo"
    ],
    "wof:name":"Hledobo",
    "wof:placetype":"locality"
},
  "geometry": {"coordinates":[96.82055,18.47252000000001],"type":"Point"}
}