{
  "type": "Feature",
  "properties": {
    "gn:admin1_code":"11.0",
    "gn:admin2_code":"MMR014D003",
    "gn:admin3_code":"MMR014021",
    "gn:asciiname":"Wan Wo-lai",
    "gn:country_code":"MM",
    "gn:dem":748,
    "gn:feature_class":"P",
    "gn:feature_code":"PPL",
    "gn:name":"W\u0101n Wo-lai",
    "gn:population":0,
    "gn:timezone":"Asia/Yangon",
    "iso:country":"MM",
    "wof:name":"Wan Wo-lai",
    "wof:placetype":"locality"
},
  "geometry": {"coordinates":[98.42778,20.36361],"type":"Point"}
}