{
  "type": "Feature",
  "properties": {
    "gn:admin1_code":"5.0",
    "gn:admin2_code":"MMR003D001",
    "gn:admin3_code":"MMR003002",
    "gn:asciiname":"Thadikho",
    "gn:country_code":"MM",
    "gn:dem":28,
    "gn:feature_class":"P",
    "gn:feature_code":"PPL",
    "gn:name":"Thadikho",
    "gn:population":0,
    "gn:timezone":"Asia/Yangon",
    "iso:country":"MM",
    "wof:name":"Thadikho",
    "wof:placetype":"locality"
},
  "geometry": {"coordinates":[97.76922,17.14056],"type":"Point"}
}