{
  "type": "Feature",
  "properties": {
    "gn:admin1_code":"4.0",
    "gn:admin2_code":"MMR001D003",
    "gn:admin3_code":"MMR001012",
    "gn:asciiname":"Wabaw-gahtawng",
    "gn:country_code":"MM",
    "gn:dem":846,
    "gn:feature_class":"P",
    "gn:feature_code":"PPL",
    "gn:name":"Wabaw-gahtawng",
    "gn:population":0,
    "gn:timezone":"Asia/Yangon",
    "iso:country":"MM",
    "wof:name":"Wabaw-gahtawng",
    "wof:placetype":"locality"
},
  "geometry": {"coordinates":[97.39655999999999,24.19124],"type":"Point"}
}