{
  "type": "Feature",
  "properties": {
    "gn:admin1_code":"10.0",
    "gn:admin2_code":"MMR005D008",
    "gn:admin3_code":"MMR005035",
    "gn:asciiname":"Saungkin",
    "gn:country_code":"MM",
    "gn:dem":1107,
    "gn:feature_class":"P",
    "gn:feature_code":"PPL",
    "gn:name":"Saungkin",
    "gn:population":0,
    "gn:timezone":"Asia/Yangon",
    "iso:country":"MM",
    "wof:name":"Saungkin",
    "wof:placetype":"locality"
},
  "geometry": {"coordinates":[95.03333000000001,25.43333],"type":"Point"}
}