{
  "type": "Feature",
  "properties": {
    "gn:admin1_code":"4.0",
    "gn:admin2_code":"MMR001D004",
    "gn:admin3_code":"MMR001014",
    "gn:asciiname":"Shinai Ga",
    "gn:country_code":"MM",
    "gn:dem":1225,
    "gn:feature_class":"P",
    "gn:feature_code":"PPL",
    "gn:name":"Shinai Ga",
    "gn:population":0,
    "gn:timezone":"Asia/Yangon",
    "iso:country":"MM",
    "wof:name":"Shinai Ga",
    "wof:placetype":"locality"
},
  "geometry": {"coordinates":[97.49476,27.78523],"type":"Point"}
}