{
  "type": "Feature",
  "properties": {
    "gn:admin1_code":"10.0",
    "gn:admin2_code":"MMR005D002",
    "gn:admin3_code":"MMR005006",
    "gn:asciiname":"Ngabatchaung",
    "gn:country_code":"MM",
    "gn:dem":82,
    "gn:feature_class":"P",
    "gn:feature_code":"PPL",
    "gn:name":"Ngabatchaung",
    "gn:population":0,
    "gn:timezone":"Asia/Yangon",
    "iso:country":"MM",
    "wof:name":"Ngabatchaung",
    "wof:placetype":"locality"
},
  "geometry": {"coordinates":[95.95672,22.39617],"type":"Point"}
}