{
  "type": "Feature",
  "properties": {
    "gn:admin1_code":"16.0",
    "gn:admin2_code":"MMR008D002",
    "gn:admin3_code":"MMR008007",
    "gn:asciiname":"Hlelangu",
    "gn:country_code":"MM",
    "gn:dem":45,
    "gn:feature_class":"P",
    "gn:feature_code":"PPL",
    "gn:name":"Hlelangu",
    "gn:population":0,
    "gn:timezone":"Asia/Yangon",
    "iso:country":"MM",
    "wof:name":"Hlelangu",
    "wof:placetype":"locality"
},
  "geometry": {"coordinates":[95.91108,17.6947],"type":"Point"}
}