{
  "type": "Feature",
  "properties": {
    "gn:admin1_code":"8.0",
    "gn:admin2_code":"MMR010D002",
    "gn:admin3_code":"MMR010008",
    "gn:asciiname":"Myebon",
    "gn:country_code":"MM",
    "gn:dem":982,
    "gn:feature_class":"P",
    "gn:feature_code":"PPL",
    "gn:name":"Myebon",
    "gn:population":0,
    "gn:timezone":"Asia/Yangon",
    "iso:country":"MM",
    "wof:name":"Myebon",
    "wof:placetype":"locality"
},
  "geometry": {"coordinates":[96.38851,21.85238],"type":"Point"}
}