{
  "type": "Feature",
  "properties": {
    "gn:admin1_code":"16.0",
    "gn:admin2_code":"MMR007D002",
    "gn:admin3_code":"MMR007010",
    "gn:asciiname":"Thayagon",
    "gn:country_code":"MM",
    "gn:dem":58,
    "gn:feature_class":"P",
    "gn:feature_code":"PPL",
    "gn:name":"Thayagon",
    "gn:population":0,
    "gn:timezone":"Asia/Yangon",
    "iso:country":"MM",
    "wof:name":"Thayagon",
    "wof:placetype":"locality"
},
  "geometry": {"coordinates":[96.36951999999999,19.22084],"type":"Point"}
}