{
  "type": "Feature",
  "properties": {
    "gn:admin1_code":"11.0",
    "gn:admin2_code":"MMR014D001",
    "gn:admin3_code":"MMR014001",
    "gn:asciiname":"Ho-hko",
    "gn:country_code":"MM",
    "gn:dem":1002,
    "gn:feature_class":"P",
    "gn:feature_code":"PPL",
    "gn:name":"Ho-hko",
    "gn:population":0,
    "gn:timezone":"Asia/Yangon",
    "iso:country":"MM",
    "wof:name":"Ho-hko",
    "wof:placetype":"locality"
},
  "geometry": {"coordinates":[97.15089999999999,20.43383],"type":"Point"}
}