{
  "type": "Feature",
  "properties": {
    "gn:admin1_code":"10.0",
    "gn:admin2_code":"MMR005D008",
    "gn:admin3_code":"MMR005037",
    "gn:asciiname":"Kalan",
    "gn:country_code":"MM",
    "gn:dem":1025,
    "gn:feature_class":"P",
    "gn:feature_code":"PPL",
    "gn:name":"K\u0101l\u0101n",
    "gn:population":0,
    "gn:timezone":"Asia/Yangon",
    "iso:country":"MM",
    "name:ceb_x_preferred":[
        "Kalan"
    ],
    "name:deu_x_preferred":[
        "Kalan"
    ],
    "name:fas_x_preferred":[
        "\u06a9\u0644\u0627\u0646"
    ],
    "name:fra_x_preferred":[
        "Kalan"
    ],
    "name:hrv_x_preferred":[
        "Kalan"
    ],
    "name:nld_x_preferred":[
        "Kalan"
    ],
    "name:rus_x_preferred":[
        "\u041a\u0430\u043b\u0430\u043d"
    ],
    "name:slv_x_preferred":[
        "Kalan"
    ],
    "name:swe_x_preferred":[
        "Kalan"
    ],
    "name:ukr_x_preferred":[
        "\u041a\u0430\u043b\u0430\u043d"
    ],
    "wof:name":"Kalan",
    "wof:placetype":"locality"
},
  "geometry": {"coordinates":[95.56270000000001,26.61772],"type":"Point"}
}