{
  "type": "Feature",
  "properties": {
    "gn:admin1_code":"11.0",
    "gn:admin2_code":"MMR014D002",
    "gn:admin3_code":"MMR014013",
    "gn:asciiname":"Pa-tueng",
    "gn:country_code":"MM",
    "gn:dem":910,
    "gn:feature_class":"P",
    "gn:feature_code":"PPL",
    "gn:name":"Pa-t\u00fcng",
    "gn:population":0,
    "gn:timezone":"Asia/Yangon",
    "iso:country":"MM",
    "wof:name":"Pa-tueng",
    "wof:placetype":"locality"
},
  "geometry": {"coordinates":[98.02691,20.91871],"type":"Point"}
}