{
  "type": "Feature",
  "properties": {
    "gn:admin1_code":"8.0",
    "gn:admin2_code":"MMR010D002",
    "gn:admin3_code":"MMR010012",
    "gn:asciiname":"Tagaung",
    "gn:country_code":"MM",
    "gn:dem":93,
    "gn:feature_class":"P",
    "gn:feature_code":"PPL",
    "gn:name":"Tagaung",
    "gn:population":0,
    "gn:timezone":"Asia/Yangon",
    "iso:country":"MM",
    "name:und_x_variant":[
        "Tagaung-myo",
        "Tagoung",
        "Tagaung"
    ],
    "wof:name":"Tagaung",
    "wof:placetype":"locality"
},
  "geometry": {"coordinates":[96.01314000000001,23.50372],"type":"Point"}
}