{
  "type": "Feature",
  "properties": {
    "gn:admin1_code":"11.0",
    "gn:admin2_code":"MMR015D008",
    "gn:admin3_code":"MMR015018",
    "gn:asciiname":"Chauhpa Hkun",
    "gn:country_code":"MM",
    "gn:dem":908,
    "gn:feature_class":"P",
    "gn:feature_code":"PPL",
    "gn:name":"Chauhpa Hkun",
    "gn:population":0,
    "gn:timezone":"Asia/Yangon",
    "iso:country":"MM",
    "wof:name":"Chauhpa Hkun",
    "wof:placetype":"locality"
},
  "geometry": {"coordinates":[97.10105,23.54618],"type":"Point"}
}