{
  "type": "Feature",
  "properties": {
    "gn:admin1_code":"11.0",
    "gn:admin2_code":"MMR014D003",
    "gn:admin3_code":"MMR014021",
    "gn:asciiname":"Nawng-yunno",
    "gn:country_code":"MM",
    "gn:dem":895,
    "gn:feature_class":"P",
    "gn:feature_code":"PPL",
    "gn:name":"Nawng-yunno",
    "gn:population":0,
    "gn:timezone":"Asia/Yangon",
    "iso:country":"MM",
    "wof:name":"Nawng-yunno",
    "wof:placetype":"locality"
},
  "geometry": {"coordinates":[98.41943999999999,20.16278],"type":"Point"}
}