{
  "type": "Feature",
  "properties": {
    "gn:admin1_code":"11.0",
    "gn:admin2_code":"MMR014D002",
    "gn:admin3_code":"MMR014016",
    "gn:asciiname":"Wan Lokpa",
    "gn:country_code":"MM",
    "gn:dem":722,
    "gn:feature_class":"P",
    "gn:feature_code":"PPL",
    "gn:name":"W\u0101n Lokpa",
    "gn:population":0,
    "gn:timezone":"Asia/Yangon",
    "iso:country":"MM",
    "wof:name":"Wan Lokpa",
    "wof:placetype":"locality"
},
  "geometry": {"coordinates":[97.22892,21.65388],"type":"Point"}
}