{
  "type": "Feature",
  "properties": {
    "gn:admin1_code":"10.0",
    "gn:admin2_code":"MMR005D002",
    "gn:admin3_code":"MMR005008",
    "gn:asciiname":"Kani",
    "gn:country_code":"MM",
    "gn:dem":145,
    "gn:feature_class":"P",
    "gn:feature_code":"PPL",
    "gn:name":"Kani",
    "gn:population":0,
    "gn:timezone":"Asia/Yangon",
    "iso:country":"MM",
    "name:aze_x_preferred":[
        "Kani"
    ],
    "name:ceb_x_preferred":[
        "Kani"
    ],
    "name:deu_x_preferred":[
        "Kani"
    ],
    "name:fin_x_preferred":[
        "Kani"
    ],
    "name:fra_x_preferred":[
        "Kani"
    ],
    "name:ita_x_preferred":[
        "Kani"
    ],
    "name:jpn_x_preferred":[
        "\u30ab\u30cb"
    ],
    "name:nld_x_preferred":[
        "Kani"
    ],
    "name:swa_x_preferred":[
        "Kani"
    ],
    "name:swe_x_preferred":[
        "Kani"
    ],
    "name:ukr_x_preferred":[
        "\u041a\u0430\u043d\u0456"
    ],
    "wof:name":"Kani",
    "wof:placetype":"locality"
},
  "geometry": {"coordinates":[95.31965,23.25708],"type":"Point"}
}