{
  "type": "Feature",
  "properties": {
    "gn:admin1_code":"11.0",
    "gn:admin2_code":"MMR014D001",
    "gn:admin3_code":"MMR014005",
    "gn:asciiname":"Ngonthon",
    "gn:country_code":"MM",
    "gn:dem":1333,
    "gn:feature_class":"P",
    "gn:feature_code":"PPL",
    "gn:name":"Ngonthon",
    "gn:population":0,
    "gn:timezone":"Asia/Yangon",
    "iso:country":"MM",
    "wof:name":"Ngonthon",
    "wof:placetype":"locality"
},
  "geometry": {"coordinates":[96.69748,20.62655],"type":"Point"}
}