{
  "type": "Feature",
  "properties": {
    "gn:admin1_code":"11.0",
    "gn:admin2_code":"MMR015D003",
    "gn:admin3_code":"MMR015014",
    "gn:asciiname":"Mawk-pan-hse",
    "gn:country_code":"MM",
    "gn:dem":797,
    "gn:feature_class":"P",
    "gn:feature_code":"PPL",
    "gn:name":"Mawk-pan-hse",
    "gn:population":0,
    "gn:timezone":"Asia/Yangon",
    "iso:country":"MM",
    "wof:name":"Mawk-pan-hse",
    "wof:placetype":"locality"
},
  "geometry": {"coordinates":[97.61123000000001,22.2713],"type":"Point"}
}