{
  "type": "Feature",
  "properties": {
    "gn:admin1_code":"4.0",
    "gn:admin2_code":"MMR001D002",
    "gn:admin3_code":"MMR001007",
    "gn:asciiname":"Chathoyang",
    "gn:country_code":"MM",
    "gn:dem":178,
    "gn:feature_class":"P",
    "gn:feature_code":"PPL",
    "gn:name":"Ch\u0101thoyang",
    "gn:population":0,
    "gn:timezone":"Asia/Yangon",
    "iso:country":"MM",
    "wof:name":"Chathoyang",
    "wof:placetype":"locality"
},
  "geometry": {"coordinates":[96.50794,24.62134],"type":"Point"}
}