{
  "type": "Feature",
  "properties": {
    "gn:admin1_code":"17.0",
    "gn:asciiname":"Kyizun",
    "gn:country_code":"MM",
    "gn:dem":24,
    "gn:feature_class":"P",
    "gn:feature_code":"PPL",
    "gn:name":"Kyizun",
    "gn:population":0,
    "gn:timezone":"Asia/Yangon",
    "iso:country":"MM",
    "wof:name":"Kyizun",
    "wof:placetype":"locality"
},
  "geometry": {"coordinates":[96.31594,17.20362],"type":"Point"}
}