{
  "type": "Feature",
  "properties": {
    "gn:admin1_code":"2.0",
    "gn:admin2_code":"MMR004D002",
    "gn:admin3_code":"MMR004007",
    "gn:asciiname":"Baneng",
    "gn:country_code":"MM",
    "gn:dem":1100,
    "gn:feature_class":"P",
    "gn:feature_code":"PPL",
    "gn:name":"Baneng",
    "gn:population":0,
    "gn:timezone":"Asia/Yangon",
    "iso:country":"MM",
    "wof:name":"Baneng",
    "wof:placetype":"locality"
},
  "geometry": {"coordinates":[93.39453,21.79283],"type":"Point"}
}