{
  "type": "Feature",
  "properties": {
    "gn:admin1_code":"12.0",
    "gn:asciiname":"Peiksagan",
    "gn:country_code":"MM",
    "gn:dem":-9999,
    "gn:feature_class":"P",
    "gn:feature_code":"PPL",
    "gn:name":"Peiksagan",
    "gn:population":0,
    "gn:timezone":"Asia/Yangon",
    "iso:country":"MM",
    "wof:name":"Peiksagan",
    "wof:placetype":"locality"
},
  "geometry": {"coordinates":[97.91667,14.53333],"type":"Point"}
}