{
  "type": "Feature",
  "properties": {
    "gn:admin1_code":"15.0",
    "gn:admin2_code":"MMR009D003",
    "gn:admin3_code":"MMR009014",
    "gn:asciiname":"Ywathit",
    "gn:country_code":"MM",
    "gn:dem":117,
    "gn:feature_class":"P",
    "gn:feature_code":"PPL",
    "gn:name":"Ywathit",
    "gn:population":0,
    "gn:timezone":"Asia/Yangon",
    "iso:country":"MM",
    "wof:name":"Ywathit",
    "wof:placetype":"locality"
},
  "geometry": {"coordinates":[94.68213,19.25873],"type":"Point"}
}