{
  "type": "Feature",
  "properties": {
    "gn:admin1_code":"2.0",
    "gn:admin2_code":"MMR004D001",
    "gn:admin3_code":"MMR004001",
    "gn:asciiname":"Kulzam",
    "gn:country_code":"MM",
    "gn:dem":1810,
    "gn:feature_class":"P",
    "gn:feature_code":"PPL",
    "gn:name":"Kulzam",
    "gn:population":0,
    "gn:timezone":"Asia/Yangon",
    "iso:country":"MM",
    "wof:name":"Kulzam",
    "wof:placetype":"locality"
},
  "geometry": {"coordinates":[93.68333,23.01667],"type":"Point"}
}