{
  "type": "Feature",
  "properties": {
    "gn:admin1_code":"15.0",
    "gn:admin2_code":"MMR009D003",
    "gn:admin3_code":"MMR009015",
    "gn:asciiname":"Kinywa",
    "gn:country_code":"MM",
    "gn:dem":37,
    "gn:feature_class":"P",
    "gn:feature_code":"PPL",
    "gn:name":"Kinywa",
    "gn:population":0,
    "gn:timezone":"Asia/Yangon",
    "iso:country":"MM",
    "wof:name":"Kinywa",
    "wof:placetype":"locality"
},
  "geometry": {"coordinates":[95.10648,19.06381],"type":"Point"}
}