{
  "type": "Feature",
  "properties": {
    "gn:admin1_code":"16.0",
    "gn:admin2_code":"MMR007D001",
    "gn:admin3_code":"MMR007001",
    "gn:asciiname":"Thitseingon",
    "gn:country_code":"MM",
    "gn:dem":27,
    "gn:feature_class":"P",
    "gn:feature_code":"PPL",
    "gn:name":"Thitseingon",
    "gn:population":0,
    "gn:timezone":"Asia/Yangon",
    "iso:country":"MM",
    "wof:name":"Thitseingon",
    "wof:placetype":"locality"
},
  "geometry": {"coordinates":[96.33101000000001,17.52184],"type":"Point"}
}