{
  "type": "Feature",
  "properties": {
    "gn:admin1_code":"16.0",
    "gn:admin2_code":"MMR008D002",
    "gn:admin3_code":"MMR008012",
    "gn:asciiname":"Ywathagon",
    "gn:country_code":"MM",
    "gn:dem":31,
    "gn:feature_class":"P",
    "gn:feature_code":"PPL",
    "gn:name":"Ywathagon",
    "gn:population":0,
    "gn:timezone":"Asia/Yangon",
    "iso:country":"MM",
    "wof:name":"Ywathagon",
    "wof:placetype":"locality"
},
  "geometry": {"coordinates":[95.53091999999999,18.30519],"type":"Point"}
}