{
  "type": "Feature",
  "properties": {
    "gn:admin1_code":"11.0",
    "gn:admin2_code":"MMR015D003",
    "gn:admin3_code":"MMR015012",
    "gn:asciiname":"Nahku",
    "gn:country_code":"MM",
    "gn:dem":690,
    "gn:feature_class":"P",
    "gn:feature_code":"PPL",
    "gn:name":"N\u0101hku",
    "gn:population":0,
    "gn:timezone":"Asia/Yangon",
    "iso:country":"MM",
    "wof:name":"Nahku",
    "wof:placetype":"locality"
},
  "geometry": {"coordinates":[97.08056000000001,22.53578],"type":"Point"}
}