{
  "type": "Feature",
  "properties": {
    "gn:admin1_code":"6.0",
    "gn:admin2_code":"MMR002D002",
    "gn:admin3_code":"MMR002006",
    "gn:asciiname":"Buku",
    "gn:country_code":"MM",
    "gn:dem":1252,
    "gn:feature_class":"P",
    "gn:feature_code":"PPL",
    "gn:name":"Buku",
    "gn:population":0,
    "gn:timezone":"Asia/Yangon",
    "iso:country":"MM",
    "name:ceb_x_preferred":[
        "Buku"
    ],
    "name:swe_x_preferred":[
        "Buku"
    ],
    "name:und_x_variant":[
        "Buko-ywa",
        "Buku"
    ],
    "wof:name":"Buku",
    "wof:placetype":"locality"
},
  "geometry": {"coordinates":[97.03798999999999,18.96746],"type":"Point"}
}