{
  "type": "Feature",
  "properties": {
    "gn:admin1_code":"8.0",
    "gn:admin2_code":"MMR010D005",
    "gn:admin3_code":"MMR010020",
    "gn:asciiname":"Thanbo",
    "gn:country_code":"MM",
    "gn:dem":376,
    "gn:feature_class":"P",
    "gn:feature_code":"PPL",
    "gn:name":"Thanbo",
    "gn:population":0,
    "gn:timezone":"Asia/Yangon",
    "iso:country":"MM",
    "wof:name":"Thanbo",
    "wof:placetype":"locality"
},
  "geometry": {"coordinates":[95.17474,20.90701],"type":"Point"}
}