{
  "type": "Feature",
  "properties": {
    "gn:admin1_code":"10.0",
    "gn:admin2_code":"MMR005D001",
    "gn:admin3_code":"MMR005002",
    "gn:asciiname":"Konywa",
    "gn:country_code":"MM",
    "gn:dem":127,
    "gn:feature_class":"P",
    "gn:feature_code":"PPL",
    "gn:name":"Konywa",
    "gn:population":0,
    "gn:timezone":"Asia/Yangon",
    "iso:country":"MM",
    "wof:name":"Konywa",
    "wof:placetype":"locality"
},
  "geometry": {"coordinates":[95.41705,21.98682],"type":"Point"}
}