{
  "type": "Feature",
  "properties": {
    "gn:admin1_code":"11.0",
    "gn:admin2_code":"MMR015D001",
    "gn:admin3_code":"MMR015002",
    "gn:asciiname":"Panghkam",
    "gn:country_code":"MM",
    "gn:dem":720,
    "gn:feature_class":"P",
    "gn:feature_code":"PPL",
    "gn:name":"Panghkam",
    "gn:population":0,
    "gn:timezone":"Asia/Yangon",
    "iso:country":"MM",
    "wof:name":"Panghkam",
    "wof:placetype":"locality"
},
  "geometry": {"coordinates":[97.82143000000001,23.27068],"type":"Point"}
}