{
  "type": "Feature",
  "properties": {
    "gn:admin1_code":"11.0",
    "gn:admin2_code":"MMR016D001",
    "gn:admin3_code":"MMR016001",
    "gn:asciiname":"Wan Hkun",
    "gn:country_code":"MM",
    "gn:dem":840,
    "gn:feature_class":"P",
    "gn:feature_code":"PPL",
    "gn:name":"W\u0101n Hkun",
    "gn:population":0,
    "gn:timezone":"Asia/Yangon",
    "iso:country":"MM",
    "wof:name":"Wan Hkun",
    "wof:placetype":"locality"
},
  "geometry": {"coordinates":[99.32286999999999,21.33392000000001],"type":"Point"}
}