{
  "type": "Feature",
  "properties": {
    "gn:admin1_code":"6.0",
    "gn:admin2_code":"MMR002D001",
    "gn:admin3_code":"MMR002003",
    "gn:asciiname":"Duhko",
    "gn:country_code":"MM",
    "gn:dem":865,
    "gn:feature_class":"P",
    "gn:feature_code":"PPL",
    "gn:name":"Duhko",
    "gn:population":0,
    "gn:timezone":"Asia/Yangon",
    "iso:country":"MM",
    "wof:name":"Duhko",
    "wof:placetype":"locality"
},
  "geometry": {"coordinates":[96.88988999999999,19.1875],"type":"Point"}
}