{
  "type": "Feature",
  "properties": {
    "gn:admin1_code":"8.0",
    "gn:admin2_code":"MMR010D002",
    "gn:admin3_code":"MMR010010",
    "gn:asciiname":"Wettogon",
    "gn:country_code":"MM",
    "gn:dem":81,
    "gn:feature_class":"P",
    "gn:feature_code":"PPL",
    "gn:name":"Wettogon",
    "gn:population":0,
    "gn:timezone":"Asia/Yangon",
    "iso:country":"MM",
    "name:und_x_variant":[
        "Wettogan",
        "Wettogon"
    ],
    "wof:name":"Wettogon",
    "wof:placetype":"locality"
},
  "geometry": {"coordinates":[95.98381999999999,22.60109],"type":"Point"}
}