{
  "type": "Feature",
  "properties": {
    "gn:admin1_code":"12.0",
    "gn:admin2_code":"MMR006D002",
    "gn:admin3_code":"MMR006008",
    "gn:asciiname":"Mayingyi",
    "gn:country_code":"MM",
    "gn:dem":16,
    "gn:feature_class":"P",
    "gn:feature_code":"PPL",
    "gn:name":"Mayingyi",
    "gn:population":0,
    "gn:timezone":"Asia/Yangon",
    "iso:country":"MM",
    "wof:name":"Mayingyi",
    "wof:placetype":"locality"
},
  "geometry": {"coordinates":[99.00239000000001,12.12978],"type":"Point"}
}