{
  "type": "Feature",
  "properties": {
    "gn:admin1_code":"3.0",
    "gn:admin2_code":"MMR017D005",
    "gn:admin3_code":"MMR017022",
    "gn:asciiname":"Akyaw",
    "gn:country_code":"MM",
    "gn:dem":16,
    "gn:feature_class":"P",
    "gn:feature_code":"PPL",
    "gn:name":"Akyaw",
    "gn:population":0,
    "gn:timezone":"Asia/Yangon",
    "iso:country":"MM",
    "wof:name":"Akyaw",
    "wof:placetype":"locality"
},
  "geometry": {"coordinates":[95.53118000000001,17.23868],"type":"Point"}
}