{
  "type": "Feature",
  "properties": {
    "gn:admin1_code":"4.0",
    "gn:admin2_code":"MMR001D001",
    "gn:admin3_code":"MMR001002",
    "gn:asciiname":"Nawku",
    "gn:country_code":"MM",
    "gn:dem":353,
    "gn:feature_class":"P",
    "gn:feature_code":"PPL",
    "gn:name":"Nawku",
    "gn:population":0,
    "gn:timezone":"Asia/Yangon",
    "iso:country":"MM",
    "wof:name":"Nawku",
    "wof:placetype":"locality"
},
  "geometry": {"coordinates":[97.48414,25.07167],"type":"Point"}
}