{
  "type": "Feature",
  "properties": {
    "gn:admin1_code":"16.0",
    "gn:admin2_code":"MMR008D002",
    "gn:admin3_code":"MMR008013",
    "gn:asciiname":"Yegin",
    "gn:country_code":"MM",
    "gn:dem":24,
    "gn:feature_class":"P",
    "gn:feature_code":"PPL",
    "gn:name":"Yegin",
    "gn:population":0,
    "gn:timezone":"Asia/Yangon",
    "iso:country":"MM",
    "wof:name":"Yegin",
    "wof:placetype":"locality"
},
  "geometry": {"coordinates":[95.43145,18.12032],"type":"Point"}
}