{
  "type": "Feature",
  "properties": {
    "gn:admin1_code":"11.0",
    "gn:admin2_code":"MMR016D003",
    "gn:admin3_code":"MMR016011",
    "gn:asciiname":"Wan Hsenhkamleng",
    "gn:country_code":"MM",
    "gn:dem":1291,
    "gn:feature_class":"P",
    "gn:feature_code":"PPL",
    "gn:name":"W\u0101n Hsenhkaml\u0113ng",
    "gn:population":0,
    "gn:timezone":"Asia/Yangon",
    "iso:country":"MM",
    "name:und_x_variant":[
        "W\u0101n Hsenlikamleng",
        "W\u0101n Hsenhkaml\u0113ng"
    ],
    "wof:name":"Wan Hsenhkamleng",
    "wof:placetype":"locality"
},
  "geometry": {"coordinates":[101.03728,21.51719],"type":"Point"}
}