{
  "type": "Feature",
  "properties": {
    "gn:admin1_code":"15.0",
    "gn:admin2_code":"MMR009D003",
    "gn:admin3_code":"MMR009013",
    "gn:asciiname":"Sinmagyat",
    "gn:country_code":"MM",
    "gn:dem":291,
    "gn:feature_class":"P",
    "gn:feature_code":"PPL",
    "gn:name":"Sinmagyat",
    "gn:population":0,
    "gn:timezone":"Asia/Yangon",
    "iso:country":"MM",
    "wof:name":"Sinmagyat",
    "wof:placetype":"locality"
},
  "geometry": {"coordinates":[94.74298,19.80659],"type":"Point"}
}