{
  "type": "Feature",
  "properties": {
    "gn:admin1_code":"6.0",
    "gn:admin2_code":"MMR002D001",
    "gn:admin3_code":"MMR002001",
    "gn:asciiname":"Daw I-la",
    "gn:country_code":"MM",
    "gn:dem":892,
    "gn:feature_class":"P",
    "gn:feature_code":"PPL",
    "gn:name":"Daw I-l\u00e0",
    "gn:population":0,
    "gn:timezone":"Asia/Yangon",
    "iso:country":"MM",
    "wof:name":"Daw I-la",
    "wof:placetype":"locality"
},
  "geometry": {"coordinates":[97.14959,19.74559],"type":"Point"}
}