{
  "type": "Feature",
  "properties": {
    "gn:admin1_code":"11.0",
    "gn:admin2_code":"MMR015D001",
    "gn:admin3_code":"MMR015001",
    "gn:asciiname":"Nam-hawm",
    "gn:country_code":"MM",
    "gn:dem":943,
    "gn:feature_class":"P",
    "gn:feature_code":"PPL",
    "gn:name":"Nam-hawm",
    "gn:population":0,
    "gn:timezone":"Asia/Yangon",
    "iso:country":"MM",
    "wof:name":"Nam-hawm",
    "wof:placetype":"locality"
},
  "geometry": {"coordinates":[97.68026999999999,22.75138],"type":"Point"}
}