{
  "type": "Feature",
  "properties": {
    "gn:admin1_code":"4.0",
    "gn:admin2_code":"MMR001D004",
    "gn:admin3_code":"MMR001015",
    "gn:asciiname":"Shakrintu",
    "gn:country_code":"MM",
    "gn:dem":659,
    "gn:feature_class":"P",
    "gn:feature_code":"PPL",
    "gn:name":"Shakrintu",
    "gn:population":0,
    "gn:timezone":"Asia/Yangon",
    "iso:country":"MM",
    "wof:name":"Shakrintu",
    "wof:placetype":"locality"
},
  "geometry": {"coordinates":[97.73681999999999,26.69971],"type":"Point"}
}