{
  "type": "Feature",
  "properties": {
    "gn:admin1_code":"4.0",
    "gn:admin2_code":"MMR001D003",
    "gn:admin3_code":"MMR001012",
    "gn:asciiname":"Dingsa Chyari",
    "gn:country_code":"MM",
    "gn:dem":779,
    "gn:feature_class":"P",
    "gn:feature_code":"PPL",
    "gn:name":"Dingsa Chy\u0101ri",
    "gn:population":0,
    "gn:timezone":"Asia/Yangon",
    "iso:country":"MM",
    "wof:name":"Dingsa Chyari",
    "wof:placetype":"locality"
},
  "geometry": {"coordinates":[97.40877,24.21256],"type":"Point"}
}