{
  "type": "Feature",
  "properties": {
    "gn:admin1_code":"16.0",
    "gn:admin2_code":"MMR007D001",
    "gn:admin3_code":"MMR007008",
    "gn:asciiname":"Lewa",
    "gn:country_code":"MM",
    "gn:dem":44,
    "gn:feature_class":"P",
    "gn:feature_code":"PPL",
    "gn:name":"L\u00e8wa",
    "gn:population":0,
    "gn:timezone":"Asia/Yangon",
    "iso:country":"MM",
    "name:ceb_x_preferred":[
        "Lewa"
    ],
    "name:deu_x_preferred":[
        "Lewa"
    ],
    "name:swe_x_preferred":[
        "Lewa"
    ],
    "wof:name":"Lewa",
    "wof:placetype":"locality"
},
  "geometry": {"coordinates":[96.97898000000001,18.15963],"type":"Point"}
}