{
  "type": "Feature",
  "properties": {
    "gn:admin1_code":"11.0",
    "gn:admin2_code":"MMR014D002",
    "gn:admin3_code":"MMR014015",
    "gn:asciiname":"Wan Nyawnghsai",
    "gn:country_code":"MM",
    "gn:dem":972,
    "gn:feature_class":"P",
    "gn:feature_code":"PPL",
    "gn:name":"W\u0101n Nyawnghsai",
    "gn:population":0,
    "gn:timezone":"Asia/Yangon",
    "iso:country":"MM",
    "wof:name":"Wan Nyawnghsai",
    "wof:placetype":"locality"
},
  "geometry": {"coordinates":[98.08367,21.38814],"type":"Point"}
}