{
  "type": "Feature",
  "properties": {
    "gn:admin1_code":"15.0",
    "gn:admin2_code":"MMR009D003",
    "gn:admin3_code":"MMR009017",
    "gn:asciiname":"Lezin",
    "gn:country_code":"MM",
    "gn:dem":198,
    "gn:feature_class":"P",
    "gn:feature_code":"PPL",
    "gn:name":"Lezin",
    "gn:population":0,
    "gn:timezone":"Asia/Yangon",
    "iso:country":"MM",
    "wof:name":"Lezin",
    "wof:placetype":"locality"
},
  "geometry": {"coordinates":[95.54852,19.55951],"type":"Point"}
}