{
  "type": "Feature",
  "properties": {
    "gn:admin1_code":"12.0",
    "gn:asciiname":"Manwebyin",
    "gn:country_code":"MM",
    "gn:dem":0,
    "gn:feature_class":"P",
    "gn:feature_code":"PPL",
    "gn:name":"Manwebyin",
    "gn:population":0,
    "gn:timezone":"Asia/Yangon",
    "iso:country":"MM",
    "wof:name":"Manwebyin",
    "wof:placetype":"locality"
},
  "geometry": {"coordinates":[98.27948000000001,12.55237],"type":"Point"}
}