{
  "type": "Feature",
  "properties": {
    "gn:admin1_code":"4.0",
    "gn:admin2_code":"MMR001D004",
    "gn:admin3_code":"MMR001016",
    "gn:asciiname":"Hting Bu Ga",
    "gn:country_code":"MM",
    "gn:dem":483,
    "gn:feature_class":"P",
    "gn:feature_code":"PPL",
    "gn:name":"Hting Bu Ga",
    "gn:population":0,
    "gn:timezone":"Asia/Yangon",
    "iso:country":"MM",
    "wof:name":"Hting Bu Ga",
    "wof:placetype":"locality"
},
  "geometry": {"coordinates":[97.73533999999999,26.90856],"type":"Point"}
}