{
  "type": "Feature",
  "properties": {
    "gn:admin1_code":"10.0",
    "gn:admin2_code":"MMR005D003",
    "gn:admin3_code":"MMR005013",
    "gn:asciiname":"Thabyebindaw",
    "gn:country_code":"MM",
    "gn:dem":132,
    "gn:feature_class":"P",
    "gn:feature_code":"PPL",
    "gn:name":"Thabyebindaw",
    "gn:population":0,
    "gn:timezone":"Asia/Yangon",
    "iso:country":"MM",
    "wof:name":"Thabyebindaw",
    "wof:placetype":"locality"
},
  "geometry": {"coordinates":[95.15722,22.38926],"type":"Point"}
}