{
  "type": "Feature",
  "properties": {
    "gn:admin1_code":"11.0",
    "gn:admin2_code":"MMR014D001",
    "gn:admin3_code":"MMR014004",
    "gn:asciiname":"Kongloeng",
    "gn:country_code":"MM",
    "gn:dem":1018,
    "gn:feature_class":"P",
    "gn:feature_code":"PPL",
    "gn:name":"Kongl\u00f6ng",
    "gn:population":0,
    "gn:timezone":"Asia/Yangon",
    "iso:country":"MM",
    "wof:name":"Kongloeng",
    "wof:placetype":"locality"
},
  "geometry": {"coordinates":[97.15758,20.43307],"type":"Point"}
}