{
  "type": "Feature",
  "properties": {
    "gn:admin1_code":"2.0",
    "gn:admin2_code":"MMR004D003",
    "gn:admin3_code":"MMR004003",
    "gn:asciiname":"Hriphi",
    "gn:cc2":"MM",
    "gn:country_code":"MM",
    "gn:dem":1795,
    "gn:feature_class":"P",
    "gn:feature_code":"PPL",
    "gn:name":"Hriphi",
    "gn:population":0,
    "gn:timezone":"Asia/Yangon",
    "iso:country":"MM",
    "name:und_x_variant":[
        "Hripi",
        "Hriphi"
    ],
    "wof:name":"Hriphi",
    "wof:placetype":"locality"
},
  "geometry": {"coordinates":[93.36667,22.55],"type":"Point"}
}