{
  "type": "Feature",
  "properties": {
    "gn:admin1_code":"16.0",
    "gn:admin2_code":"MMR007D001",
    "gn:admin3_code":"MMR007002",
    "gn:asciiname":"Kyibinzu",
    "gn:country_code":"MM",
    "gn:dem":16,
    "gn:feature_class":"P",
    "gn:feature_code":"PPL",
    "gn:name":"Kyibinzu",
    "gn:population":0,
    "gn:timezone":"Asia/Yangon",
    "iso:country":"MM",
    "name:und_x_variant":[
        "Kyibinz",
        "Kyibinzu"
    ],
    "wof:name":"Kyibinzu",
    "wof:placetype":"locality"
},
  "geometry": {"coordinates":[96.8031,17.33477],"type":"Point"}
}