{
  "type": "Feature",
  "properties": {
    "gn:admin1_code":"6.0",
    "gn:admin2_code":"MMR002D001",
    "gn:admin3_code":"MMR002002",
    "gn:asciiname":"Bo-la",
    "gn:country_code":"MM",
    "gn:dem":838,
    "gn:feature_class":"P",
    "gn:feature_code":"PPL",
    "gn:name":"Bo-la",
    "gn:population":0,
    "gn:timezone":"Asia/Yangon",
    "iso:country":"MM",
    "wof:name":"Bo-la",
    "wof:placetype":"locality"
},
  "geometry": {"coordinates":[97.32228000000001,19.45921],"type":"Point"}
}