{
  "type": "Feature",
  "properties": {
    "gn:admin1_code":"3.0",
    "gn:admin2_code":"MMR017D002",
    "gn:admin3_code":"MMR017009",
    "gn:asciiname":"Manyeinzu",
    "gn:country_code":"MM",
    "gn:dem":21,
    "gn:feature_class":"P",
    "gn:feature_code":"PPL",
    "gn:name":"Manyeinzu",
    "gn:population":0,
    "gn:timezone":"Asia/Yangon",
    "iso:country":"MM",
    "wof:name":"Manyeinzu",
    "wof:placetype":"locality"
},
  "geometry": {"coordinates":[95.62703,17.47182999999999],"type":"Point"}
}