{
  "type": "Feature",
  "properties": {
    "gn:admin1_code":"11.0",
    "gn:admin2_code":"MMR016D002",
    "gn:admin3_code":"MMR016006",
    "gn:asciiname":"Wan Ho-me-kok",
    "gn:country_code":"MM",
    "gn:dem":856,
    "gn:feature_class":"P",
    "gn:feature_code":"PPL",
    "gn:name":"W\u0101n Ho-m\u00e8-kok",
    "gn:population":0,
    "gn:timezone":"Asia/Yangon",
    "iso:country":"MM",
    "name:und_x_variant":[
        "W\u0101n Ho-m\u0101-kok",
        "W\u0101n Ho-m\u00e8-kok"
    ],
    "wof:name":"Wan Ho-me-kok",
    "wof:placetype":"locality"
},
  "geometry": {"coordinates":[99.28467000000001,20.64686],"type":"Point"}
}