{
  "type": "Feature",
  "properties": {
    "gn:admin1_code":"11.0",
    "gn:admin2_code":"MMR015D003",
    "gn:admin3_code":"MMR015016",
    "gn:asciiname":"Man Huhpang",
    "gn:country_code":"MM",
    "gn:dem":1074,
    "gn:feature_class":"P",
    "gn:feature_code":"PPL",
    "gn:name":"M\u0101n Huhpang",
    "gn:population":0,
    "gn:timezone":"Asia/Yangon",
    "iso:country":"MM",
    "wof:name":"Man Huhpang",
    "wof:placetype":"locality"
},
  "geometry": {"coordinates":[96.96579,23.06562000000001],"type":"Point"}
}