{
  "type": "Feature",
  "properties": {
    "gn:admin1_code":"8.0",
    "gn:admin2_code":"MMR010D007",
    "gn:admin3_code":"MMR010030",
    "gn:asciiname":"Thale-in",
    "gn:country_code":"MM",
    "gn:dem":1568,
    "gn:feature_class":"P",
    "gn:feature_code":"PPL",
    "gn:name":"Thale-in",
    "gn:population":0,
    "gn:timezone":"Asia/Yangon",
    "iso:country":"MM",
    "wof:name":"Thale-in",
    "wof:placetype":"locality"
},
  "geometry": {"coordinates":[96.53067,20.51046],"type":"Point"}
}