{
  "type": "Feature",
  "properties": {
    "gn:admin1_code":"3.0",
    "gn:admin2_code":"MMR017D002",
    "gn:admin3_code":"MMR017012",
    "gn:asciiname":"Gyogyandan",
    "gn:country_code":"MM",
    "gn:dem":33,
    "gn:feature_class":"P",
    "gn:feature_code":"PPL",
    "gn:name":"Gyogyandan",
    "gn:population":0,
    "gn:timezone":"Asia/Yangon",
    "iso:country":"MM",
    "wof:name":"Gyogyandan",
    "wof:placetype":"locality"
},
  "geometry": {"coordinates":[95.20466,18.33216],"type":"Point"}
}