{
  "type": "Feature",
  "properties": {
    "gn:admin1_code":"15.0",
    "gn:admin2_code":"MMR009D002",
    "gn:admin3_code":"MMR009007",
    "gn:asciiname":"Matawgyi",
    "gn:country_code":"MM",
    "gn:dem":67,
    "gn:feature_class":"P",
    "gn:feature_code":"PPL",
    "gn:name":"Matawgyi",
    "gn:population":0,
    "gn:timezone":"Asia/Yangon",
    "iso:country":"MM",
    "wof:name":"Matawgyi",
    "wof:placetype":"locality"
},
  "geometry": {"coordinates":[94.70189999999999,20.18762000000001],"type":"Point"}
}