{
  "type": "Feature",
  "properties": {
    "gn:admin1_code":"13.0",
    "gn:admin2_code":"MMR011D001",
    "gn:admin3_code":"MMR011003",
    "gn:asciiname":"Bonet",
    "gn:country_code":"MM",
    "gn:dem":14,
    "gn:feature_class":"P",
    "gn:feature_code":"PPL",
    "gn:name":"Bonet",
    "gn:population":0,
    "gn:timezone":"Asia/Yangon",
    "iso:country":"MM",
    "name:cat_x_preferred":[
        "Bonet"
    ],
    "name:ces_x_preferred":[
        "Bonet"
    ],
    "name:deu_x_preferred":[
        "Bonet"
    ],
    "name:eus_x_preferred":[
        "Bonet"
    ],
    "name:fra_x_preferred":[
        "Bonet"
    ],
    "name:ita_x_preferred":[
        "Bonet"
    ],
    "name:jpn_x_preferred":[
        "\u30dc\u30cd\u30c3\u30c8"
    ],
    "name:por_x_preferred":[
        "Bonet"
    ],
    "name:spa_x_preferred":[
        "Bonet"
    ],
    "wof:name":"Bonet",
    "wof:placetype":"locality"
},
  "geometry": {"coordinates":[97.55972,16.41528],"type":"Point"}
}