{
  "type": "Feature",
  "properties": {
    "gn:admin1_code":"10.0",
    "gn:asciiname":"Nwakyawda",
    "gn:country_code":"MM",
    "gn:dem":78,
    "gn:feature_class":"P",
    "gn:feature_code":"PPL",
    "gn:name":"Nwakyawda",
    "gn:population":0,
    "gn:timezone":"Asia/Yangon",
    "iso:country":"MM",
    "wof:name":"Nwakyawda",
    "wof:placetype":"locality"
},
  "geometry": {"coordinates":[95.95932999999999,21.81151],"type":"Point"}
}