{
  "type": "Feature",
  "properties": {
    "gn:admin1_code":"2.0",
    "gn:admin2_code":"MMR004D002",
    "gn:admin3_code":"MMR004006",
    "gn:asciiname":"Hilawng",
    "gn:country_code":"MM",
    "gn:dem":1688,
    "gn:feature_class":"P",
    "gn:feature_code":"PPL",
    "gn:name":"Hilawng",
    "gn:population":0,
    "gn:timezone":"Asia/Yangon",
    "iso:country":"MM",
    "name:und_x_variant":[
        "Hilong",
        "Hilawng"
    ],
    "wof:name":"Hilawng",
    "wof:placetype":"locality"
},
  "geometry": {"coordinates":[93.80141999999999,21.36785],"type":"Point"}
}