{
  "type": "Feature",
  "properties": {
    "gn:admin1_code":"11.0",
    "gn:admin2_code":"MMR015D003",
    "gn:admin3_code":"MMR015019",
    "gn:asciiname":"Pang-yak",
    "gn:country_code":"MM",
    "gn:dem":1245,
    "gn:feature_class":"P",
    "gn:feature_code":"PPL",
    "gn:name":"Pang-yak",
    "gn:population":0,
    "gn:timezone":"Asia/Yangon",
    "iso:country":"MM",
    "name:und_x_variant":[
        "Pang-yok",
        "Pang-yak"
    ],
    "wof:name":"Pang-yak",
    "wof:placetype":"locality"
},
  "geometry": {"coordinates":[97.4581,23.40121],"type":"Point"}
}