{
  "type": "Feature",
  "properties": {
    "gn:admin1_code":"12.0",
    "gn:admin2_code":"MMR006D003",
    "gn:admin3_code":"MMR006006",
    "gn:asciiname":"Thameye",
    "gn:country_code":"MM",
    "gn:dem":28,
    "gn:feature_class":"P",
    "gn:feature_code":"PPL",
    "gn:name":"Tham\u0113y\u0113",
    "gn:population":0,
    "gn:timezone":"Asia/Yangon",
    "iso:country":"MM",
    "wof:name":"Thameye",
    "wof:placetype":"locality"
},
  "geometry": {"coordinates":[98.78004,11.91171],"type":"Point"}
}