{
  "type": "Feature",
  "properties": {
    "gn:admin1_code":"13.0",
    "gn:admin2_code":"MMR011D002",
    "gn:admin3_code":"MMR011010",
    "gn:asciiname":"Thebyuchaung",
    "gn:country_code":"MM",
    "gn:dem":22,
    "gn:feature_class":"P",
    "gn:feature_code":"PPL",
    "gn:name":"Thebyuchaung",
    "gn:population":0,
    "gn:timezone":"Asia/Yangon",
    "iso:country":"MM",
    "name:und_x_variant":[
        "Thebyugyaung",
        "Thebyuchaung"
    ],
    "wof:name":"Thebyuchaung",
    "wof:placetype":"locality"
},
  "geometry": {"coordinates":[97.12784000000001,17.28279],"type":"Point"}
}