{
  "type": "Feature",
  "properties": {
    "gn:admin1_code":"10.0",
    "gn:admin2_code":"MMR005D004",
    "gn:admin3_code":"MMR005021",
    "gn:asciiname":"Budalet",
    "gn:country_code":"MM",
    "gn:dem":133,
    "gn:feature_class":"P",
    "gn:feature_code":"PPL",
    "gn:name":"Budalet",
    "gn:population":0,
    "gn:timezone":"Asia/Yangon",
    "iso:country":"MM",
    "wof:name":"Budalet",
    "wof:placetype":"locality"
},
  "geometry": {"coordinates":[96.05916999999999,23.99713],"type":"Point"}
}