{
  "type": "Feature",
  "properties": {
    "gn:admin1_code":"8.0",
    "gn:admin2_code":"MMR010D003",
    "gn:admin3_code":"MMR010013",
    "gn:asciiname":"Pyidawtha",
    "gn:country_code":"MM",
    "gn:dem":101,
    "gn:feature_class":"P",
    "gn:feature_code":"PPL",
    "gn:name":"Pyidawtha",
    "gn:population":0,
    "gn:timezone":"Asia/Yangon",
    "iso:country":"MM",
    "wof:name":"Pyidawtha",
    "wof:placetype":"locality"
},
  "geometry": {"coordinates":[96.20192,21.53846],"type":"Point"}
}