{
  "type": "Feature",
  "properties": {
    "gn:admin1_code":"5.0",
    "gn:admin2_code":"MMR003D001",
    "gn:admin3_code":"MMR003004",
    "gn:asciiname":"Lunbu",
    "gn:country_code":"MM",
    "gn:dem":79,
    "gn:feature_class":"P",
    "gn:feature_code":"PPL",
    "gn:name":"Lunbu",
    "gn:population":0,
    "gn:timezone":"Asia/Yangon",
    "iso:country":"MM",
    "name:und_x_variant":[
        "Lubu",
        "Lunbu"
    ],
    "wof:name":"Lunbu",
    "wof:placetype":"locality"
},
  "geometry": {"coordinates":[96.62264,18.87429],"type":"Point"}
}