{
  "type": "Feature",
  "properties": {
    "gn:admin1_code":"11.0",
    "gn:admin2_code":"MMR014D003",
    "gn:admin3_code":"MMR014021",
    "gn:asciiname":"Hwe-hsai",
    "gn:country_code":"MM",
    "gn:dem":758,
    "gn:feature_class":"P",
    "gn:feature_code":"PPL",
    "gn:name":"Hw\u00e8-hsai",
    "gn:population":0,
    "gn:timezone":"Asia/Yangon",
    "iso:country":"MM",
    "wof:name":"Hwe-hsai",
    "wof:placetype":"locality"
},
  "geometry": {"coordinates":[98.37325,20.14429],"type":"Point"}
}