{
  "type": "Feature",
  "properties": {
    "gn:admin1_code":"8.0",
    "gn:admin2_code":"MMR010D007",
    "gn:admin3_code":"MMR010031",
    "gn:asciiname":"Tezu",
    "gn:country_code":"MM",
    "gn:dem":182,
    "gn:feature_class":"P",
    "gn:feature_code":"PPL",
    "gn:name":"Tezu",
    "gn:population":0,
    "gn:timezone":"Asia/Yangon",
    "iso:country":"MM",
    "name:ben_x_preferred":[
        "\u09a4\u09c7\u099c\u09c1"
    ],
    "name:bpy_x_preferred":[
        "\u09a4\u09c7\u099c\u09c1"
    ],
    "name:ceb_x_preferred":[
        "Tezu"
    ],
    "name:fra_x_preferred":[
        "Tezu"
    ],
    "name:guj_x_preferred":[
        "\u0aa4\u0ac7\u0a9d\u0ac1"
    ],
    "name:hin_x_preferred":[
        "\u0924\u0947\u091c\u093c\u0942"
    ],
    "name:ita_x_preferred":[
        "Tezu"
    ],
    "name:mar_x_preferred":[
        "\u0924\u0947\u091d\u0941"
    ],
    "name:mlg_x_preferred":[
        "Tezu"
    ],
    "name:msa_x_preferred":[
        "Tezu"
    ],
    "name:nld_x_preferred":[
        "Tezu"
    ],
    "name:ori_x_preferred":[
        "\u0b24\u0b47\u0b1c\u0b41"
    ],
    "name:rus_x_preferred":[
        "\u0422\u0435\u0437\u0443"
    ],
    "name:spa_x_preferred":[
        "Tezu"
    ],
    "name:swe_x_preferred":[
        "Tezu"
    ],
    "name:tam_x_preferred":[
        "\u0ba4\u0bc7\u0b9a\u0bc1"
    ],
    "name:urd_x_preferred":[
        "\u062a\u06cc\u0632\u0648"
    ],
    "name:vie_x_preferred":[
        "Tezu"
    ],
    "wof:name":"Tezu",
    "wof:placetype":"locality"
},
  "geometry": {"coordinates":[95.85455,21.14136],"type":"Point"}
}