{
  "type": "Feature",
  "properties": {
    "gn:admin1_code":"10.0",
    "gn:admin2_code":"MMR005D002",
    "gn:admin3_code":"MMR005007",
    "gn:asciiname":"Chinmyitkyin",
    "gn:country_code":"MM",
    "gn:dem":123,
    "gn:feature_class":"P",
    "gn:feature_code":"PPL",
    "gn:name":"Chinmyitkyin",
    "gn:population":0,
    "gn:timezone":"Asia/Yangon",
    "iso:country":"MM",
    "wof:name":"Chinmyitkyin",
    "wof:placetype":"locality"
},
  "geometry": {"coordinates":[95.48244,22.96661],"type":"Point"}
}