{
  "type": "Feature",
  "properties": {
    "gn:admin1_code":"11.0",
    "gn:admin2_code":"MMR015D003",
    "gn:admin3_code":"MMR015014",
    "gn:asciiname":"Makmoengheng",
    "gn:country_code":"MM",
    "gn:dem":645,
    "gn:feature_class":"P",
    "gn:feature_code":"PPL",
    "gn:name":"Makm\u00f6ngheng",
    "gn:population":0,
    "gn:timezone":"Asia/Yangon",
    "iso:country":"MM",
    "wof:name":"Makmoengheng",
    "wof:placetype":"locality"
},
  "geometry": {"coordinates":[97.43051,22.53233],"type":"Point"}
}