{
  "type": "Feature",
  "properties": {
    "gn:admin1_code":"3.0",
    "gn:admin2_code":"MMR017D003",
    "gn:admin3_code":"MMR017017",
    "gn:asciiname":"Dayin",
    "gn:country_code":"MM",
    "gn:dem":9,
    "gn:feature_class":"P",
    "gn:feature_code":"PPL",
    "gn:name":"Dayin",
    "gn:population":0,
    "gn:timezone":"Asia/Yangon",
    "iso:country":"MM",
    "wof:name":"Dayin",
    "wof:placetype":"locality"
},
  "geometry": {"coordinates":[95.16649,16.64824],"type":"Point"}
}