{
  "type": "Feature",
  "properties": {
    "gn:admin1_code":"16.0",
    "gn:admin2_code":"MMR008D002",
    "gn:admin3_code":"MMR008014",
    "gn:asciiname":"Konywa",
    "gn:country_code":"MM",
    "gn:dem":59,
    "gn:feature_class":"P",
    "gn:feature_code":"PPL",
    "gn:name":"Konywa",
    "gn:population":0,
    "gn:timezone":"Asia/Yangon",
    "iso:country":"MM",
    "wof:name":"Konywa",
    "wof:placetype":"locality"
},
  "geometry": {"coordinates":[95.80672,18.29709],"type":"Point"}
}