{
  "type": "Feature",
  "properties": {
    "gn:admin1_code":"15.0",
    "gn:admin2_code":"MMR009D003",
    "gn:admin3_code":"MMR009012",
    "gn:asciiname":"Peikthalein",
    "gn:country_code":"MM",
    "gn:dem":36,
    "gn:feature_class":"P",
    "gn:feature_code":"PPL",
    "gn:name":"Peikthalein",
    "gn:population":0,
    "gn:timezone":"Asia/Yangon",
    "iso:country":"MM",
    "wof:name":"Peikthalein",
    "wof:placetype":"locality"
},
  "geometry": {"coordinates":[95.17446,19.24627000000001],"type":"Point"}
}