{
  "type": "Feature",
  "properties": {
    "gn:admin1_code":"15.0",
    "gn:admin2_code":"MMR009D001",
    "gn:admin3_code":"MMR009001",
    "gn:asciiname":"Shabinhla",
    "gn:country_code":"MM",
    "gn:dem":75,
    "gn:feature_class":"P",
    "gn:feature_code":"PPL",
    "gn:name":"Shabinhla",
    "gn:population":0,
    "gn:timezone":"Asia/Yangon",
    "iso:country":"MM",
    "wof:name":"Shabinhla",
    "wof:placetype":"locality"
},
  "geometry": {"coordinates":[95.09582,20.10504],"type":"Point"}
}