{
  "type": "Feature",
  "properties": {
    "gn:admin1_code":"11.0",
    "gn:admin2_code":"MMR015D002",
    "gn:admin3_code":"MMR015011",
    "gn:asciiname":"Man Hsai-hkao",
    "gn:country_code":"MM",
    "gn:dem":1275,
    "gn:feature_class":"P",
    "gn:feature_code":"PPL",
    "gn:name":"M\u0101n Hsai-hkao",
    "gn:population":0,
    "gn:timezone":"Asia/Yangon",
    "iso:country":"MM",
    "wof:name":"Man Hsai-hkao",
    "wof:placetype":"locality"
},
  "geometry": {"coordinates":[98.44486999999999,23.58763],"type":"Point"}
}