{
  "type": "Feature",
  "properties": {
    "gn:admin1_code":"10.0",
    "gn:admin2_code":"MMR005D009",
    "gn:admin3_code":"MMR005019",
    "gn:asciiname":"Chinbyit",
    "gn:country_code":"MM",
    "gn:dem":146,
    "gn:feature_class":"P",
    "gn:feature_code":"PPL",
    "gn:name":"Chinbyit",
    "gn:population":0,
    "gn:timezone":"Asia/Yangon",
    "iso:country":"MM",
    "wof:name":"Chinbyit",
    "wof:placetype":"locality"
},
  "geometry": {"coordinates":[94.69280000000001,22.04116],"type":"Point"}
}