{
  "type": "Feature",
  "properties": {
    "gn:admin1_code":"10.0",
    "gn:admin2_code":"MMR005D001",
    "gn:admin3_code":"MMR005002",
    "gn:asciiname":"E-gandaung",
    "gn:country_code":"MM",
    "gn:dem":218,
    "gn:feature_class":"P",
    "gn:feature_code":"PPL",
    "gn:name":"E-gandaung",
    "gn:population":0,
    "gn:timezone":"Asia/Yangon",
    "iso:country":"MM",
    "name:und_x_variant":[
        "E-gantaung",
        "E-gandaung"
    ],
    "wof:name":"E-gandaung",
    "wof:placetype":"locality"
},
  "geometry": {"coordinates":[95.40227,22.10394],"type":"Point"}
}