{
  "type": "Feature",
  "properties": {
    "gn:admin1_code":"10.0",
    "gn:admin2_code":"MMR005D008",
    "gn:admin3_code":"MMR005034",
    "gn:asciiname":"Sinnga",
    "gn:country_code":"MM",
    "gn:dem":139,
    "gn:feature_class":"P",
    "gn:feature_code":"PPL",
    "gn:name":"Sinnga",
    "gn:population":0,
    "gn:timezone":"Asia/Yangon",
    "iso:country":"MM",
    "wof:name":"Sinnga",
    "wof:placetype":"locality"
},
  "geometry": {"coordinates":[95.25841,25.3448],"type":"Point"}
}