{
  "type": "Feature",
  "properties": {
    "gn:admin1_code":"3.0",
    "gn:admin2_code":"MMR017D002",
    "gn:admin3_code":"MMR017013",
    "gn:asciiname":"Damingyun",
    "gn:country_code":"MM",
    "gn:dem":24,
    "gn:feature_class":"P",
    "gn:feature_code":"PPL",
    "gn:name":"Damingyun",
    "gn:population":0,
    "gn:timezone":"Asia/Yangon",
    "iso:country":"MM",
    "wof:name":"Damingyun",
    "wof:placetype":"locality"
},
  "geometry": {"coordinates":[95.39952,17.89917],"type":"Point"}
}