{
  "type": "Feature",
  "properties": {
    "gn:admin1_code":"11.0",
    "gn:admin2_code":"MMR014D002",
    "gn:admin3_code":"MMR014016",
    "gn:asciiname":"Wan Nawngpa-yem",
    "gn:country_code":"MM",
    "gn:dem":687,
    "gn:feature_class":"P",
    "gn:feature_code":"PPL",
    "gn:name":"Wan Nawngpa-yem",
    "gn:population":0,
    "gn:timezone":"Asia/Yangon",
    "iso:country":"MM",
    "wof:name":"Wan Nawngpa-yem",
    "wof:placetype":"locality"
},
  "geometry": {"coordinates":[97.29929,21.60378],"type":"Point"}
}