{
  "type": "Feature",
  "properties": {
    "gn:admin1_code":"10.0",
    "gn:admin2_code":"MMR005D004",
    "gn:admin3_code":"MMR005024",
    "gn:asciiname":"Gaungbyu",
    "gn:country_code":"MM",
    "gn:dem":160,
    "gn:feature_class":"P",
    "gn:feature_code":"PPL",
    "gn:name":"Gaungbyu",
    "gn:population":0,
    "gn:timezone":"Asia/Yangon",
    "iso:country":"MM",
    "wof:name":"Gaungbyu",
    "wof:placetype":"locality"
},
  "geometry": {"coordinates":[95.37321,23.50218],"type":"Point"}
}