{
  "type": "Feature",
  "properties": {
    "gn:admin1_code":"8.0",
    "gn:admin2_code":"MMR010D007",
    "gn:admin3_code":"MMR010031",
    "gn:asciiname":"Thanatkhadaw",
    "gn:country_code":"MM",
    "gn:dem":111,
    "gn:feature_class":"P",
    "gn:feature_code":"PPL",
    "gn:name":"Thanatkhadaw",
    "gn:population":0,
    "gn:timezone":"Asia/Yangon",
    "iso:country":"MM",
    "wof:name":"Thanatkhadaw",
    "wof:placetype":"locality"
},
  "geometry": {"coordinates":[96.07062999999999,21.26978],"type":"Point"}
}