{
  "type": "Feature",
  "properties": {
    "gn:admin1_code":"12.0",
    "gn:admin2_code":"MMR006D001",
    "gn:admin3_code":"MMR006004",
    "gn:asciiname":"Kamyaingswe",
    "gn:country_code":"MM",
    "gn:dem":18,
    "gn:feature_class":"P",
    "gn:feature_code":"PPL",
    "gn:name":"Kamyaingswe",
    "gn:population":0,
    "gn:timezone":"Asia/Yangon",
    "iso:country":"MM",
    "wof:name":"Kamyaingswe",
    "wof:placetype":"locality"
},
  "geometry": {"coordinates":[98.1071,14.26599],"type":"Point"}
}