{
  "type": "Feature",
  "properties": {
    "gn:admin1_code":"11.0",
    "gn:admin2_code":"MMR016D003",
    "gn:admin3_code":"MMR016011",
    "gn:asciiname":"Wan Hsenhkoen",
    "gn:country_code":"MM",
    "gn:dem":1270,
    "gn:feature_class":"P",
    "gn:feature_code":"PPL",
    "gn:name":"W\u0101n Hsenhk\u00f6n",
    "gn:population":0,
    "gn:timezone":"Asia/Yangon",
    "iso:country":"MM",
    "name:und_x_variant":[
        "Hsenhkon",
        "W\u0101n Hsenhk\u00f6n"
    ],
    "wof:name":"Wan Hsenhkoen",
    "wof:placetype":"locality"
},
  "geometry": {"coordinates":[100.18411999999999,21.23511],"type":"Point"}
}