{
  "type": "Feature",
  "properties": {
    "gn:admin1_code":"12.0",
    "gn:admin2_code":"MMR006D003",
    "gn:admin3_code":"MMR006006",
    "gn:asciiname":"Zegami",
    "gn:country_code":"MM",
    "gn:dem":10,
    "gn:feature_class":"P",
    "gn:feature_code":"PPL",
    "gn:name":"Zegami",
    "gn:population":0,
    "gn:timezone":"Asia/Yangon",
    "iso:country":"MM",
    "wof:name":"Zegami",
    "wof:placetype":"locality"
},
  "geometry": {"coordinates":[98.72866999999999,12.32696],"type":"Point"}
}