{
  "type": "Feature",
  "properties": {
    "gn:admin1_code":"13.0",
    "gn:admin2_code":"MMR011D001",
    "gn:admin3_code":"MMR011006",
    "gn:asciiname":"Zayat",
    "gn:country_code":"MM",
    "gn:dem":13,
    "gn:feature_class":"P",
    "gn:feature_code":"PPL",
    "gn:name":"Zayat",
    "gn:population":0,
    "gn:timezone":"Asia/Yangon",
    "iso:country":"MM",
    "wof:name":"Zayat",
    "wof:placetype":"locality"
},
  "geometry": {"coordinates":[97.74045,15.494],"type":"Point"}
}