{
  "type": "Feature",
  "properties": {
    "gn:admin1_code":"5.0",
    "gn:admin2_code":"MMR003D001",
    "gn:admin3_code":"MMR003004",
    "gn:asciiname":"Mandattaung",
    "gn:country_code":"MM",
    "gn:dem":779,
    "gn:feature_class":"P",
    "gn:feature_code":"PPL",
    "gn:name":"Mandattaung",
    "gn:population":0,
    "gn:timezone":"Asia/Yangon",
    "iso:country":"MM",
    "name:und_x_variant":[
        "Mandettaung",
        "Mandattaung"
    ],
    "wof:name":"Mandattaung",
    "wof:placetype":"locality"
},
  "geometry": {"coordinates":[96.44840000000001,19.38102],"type":"Point"}
}