{
  "type": "Feature",
  "properties": {
    "gn:admin1_code":"11.0",
    "gn:admin2_code":"MMR014D001",
    "gn:admin3_code":"MMR014010",
    "gn:asciiname":"Kwanglong",
    "gn:country_code":"MM",
    "gn:dem":896,
    "gn:feature_class":"P",
    "gn:feature_code":"PPL",
    "gn:name":"Kwanglong",
    "gn:population":0,
    "gn:timezone":"Asia/Yangon",
    "iso:country":"MM",
    "wof:name":"Kwanglong",
    "wof:placetype":"locality"
},
  "geometry": {"coordinates":[97.04476,19.83952],"type":"Point"}
}