{
  "type": "Feature",
  "properties": {
    "gn:admin1_code":"16.0",
    "gn:admin2_code":"MMR008D001",
    "gn:admin3_code":"MMR008002",
    "gn:asciiname":"Kyaukpyet",
    "gn:country_code":"MM",
    "gn:dem":108,
    "gn:feature_class":"P",
    "gn:feature_code":"PPL",
    "gn:name":"Kyaukpyet",
    "gn:population":0,
    "gn:timezone":"Asia/Yangon",
    "iso:country":"MM",
    "wof:name":"Kyaukpyet",
    "wof:placetype":"locality"
},
  "geometry": {"coordinates":[95.4216,19.08147],"type":"Point"}
}