{
  "type": "Feature",
  "properties": {
    "gn:admin1_code":"15.0",
    "gn:admin2_code":"MMR009D004",
    "gn:admin3_code":"MMR009022",
    "gn:asciiname":"Tabaung",
    "gn:country_code":"MM",
    "gn:dem":210,
    "gn:feature_class":"P",
    "gn:feature_code":"PPL",
    "gn:name":"Tabaung",
    "gn:population":0,
    "gn:timezone":"Asia/Yangon",
    "iso:country":"MM",
    "name:mya_x_preferred":[
        "\u1010\u1015\u1031\u102b\u1004\u103a\u1038\u101c"
    ],
    "wof:name":"Tabaung",
    "wof:placetype":"locality"
},
  "geometry": {"coordinates":[94.62217,21.13783],"type":"Point"}
}