{
  "type": "Feature",
  "properties": {
    "gn:admin1_code":"11.0",
    "gn:admin2_code":"MMR015D006",
    "gn:admin3_code":"MMR015021",
    "gn:asciiname":"Num Noe",
    "gn:country_code":"MM",
    "gn:dem":662,
    "gn:feature_class":"P",
    "gn:feature_code":"PPL",
    "gn:name":"Num N\u00f6",
    "gn:population":0,
    "gn:timezone":"Asia/Yangon",
    "iso:country":"MM",
    "wof:name":"Num Noe",
    "wof:placetype":"locality"
},
  "geometry": {"coordinates":[98.71774000000001,23.05992],"type":"Point"}
}