{
  "type": "Feature",
  "properties": {
    "gn:admin1_code":"11.0",
    "gn:admin2_code":"MMR016D003",
    "gn:admin3_code":"MMR016011",
    "gn:asciiname":"Wan Namkok",
    "gn:country_code":"MM",
    "gn:dem":811,
    "gn:feature_class":"P",
    "gn:feature_code":"PPL",
    "gn:name":"W\u0101n Namk\u014dk",
    "gn:population":0,
    "gn:timezone":"Asia/Yangon",
    "iso:country":"MM",
    "wof:name":"Wan Namkok",
    "wof:placetype":"locality"
},
  "geometry": {"coordinates":[100.49431,21.31159],"type":"Point"}
}