{
  "type": "Feature",
  "properties": {
    "gn:admin1_code":"15.0",
    "gn:admin2_code":"MMR009D004",
    "gn:admin3_code":"MMR009022",
    "gn:asciiname":"Taywinmyaw",
    "gn:country_code":"MM",
    "gn:dem":65,
    "gn:feature_class":"P",
    "gn:feature_code":"PPL",
    "gn:name":"Taywinmyaw",
    "gn:population":0,
    "gn:timezone":"Asia/Yangon",
    "iso:country":"MM",
    "wof:name":"Taywinmyaw",
    "wof:placetype":"locality"
},
  "geometry": {"coordinates":[94.78140999999999,20.9469],"type":"Point"}
}