{
  "type": "Feature",
  "properties": {
    "gn:admin1_code":"11.0",
    "gn:admin2_code":"MMR015D001",
    "gn:admin3_code":"MMR015020",
    "gn:asciiname":"Man Makhkam",
    "gn:country_code":"MM",
    "gn:dem":981,
    "gn:feature_class":"P",
    "gn:feature_code":"PPL",
    "gn:name":"M\u0101n Makhkam",
    "gn:population":0,
    "gn:timezone":"Asia/Yangon",
    "iso:country":"MM",
    "name:und_x_variant":[
        "Man Nakhkam",
        "M\u0101n Makhkam"
    ],
    "wof:name":"Man Makhkam",
    "wof:placetype":"locality"
},
  "geometry": {"coordinates":[98.67536,23.35994],"type":"Point"}
}