{
  "type": "Feature",
  "properties": {
    "gn:admin1_code":"11.0",
    "gn:asciiname":"Wan Hsum",
    "gn:country_code":"MM",
    "gn:dem":587,
    "gn:feature_class":"P",
    "gn:feature_code":"PPL",
    "gn:name":"W\u0101n Hs\u016bm",
    "gn:population":0,
    "gn:timezone":"Asia/Yangon",
    "iso:country":"MM",
    "wof:name":"Wan Hsum",
    "wof:placetype":"locality"
},
  "geometry": {"coordinates":[101.09999999999999,21.46667],"type":"Point"}
}