{
  "type": "Feature",
  "properties": {
    "gn:admin1_code":"8.0",
    "gn:admin2_code":"MMR010D007",
    "gn:admin3_code":"MMR010028",
    "gn:asciiname":"Shanmangge",
    "gn:country_code":"MM",
    "gn:dem":325,
    "gn:feature_class":"P",
    "gn:feature_code":"PPL",
    "gn:name":"Shanmangge",
    "gn:population":0,
    "gn:timezone":"Asia/Yangon",
    "iso:country":"MM",
    "name:und_x_variant":[
        "Thabyegon",
        "Shanmange",
        "Shanmangge"
    ],
    "wof:name":"Shanmangge",
    "wof:placetype":"locality"
},
  "geometry": {"coordinates":[95.61667,20.83853],"type":"Point"}
}