{
  "type": "Feature",
  "properties": {
    "gn:admin1_code":"10.0",
    "gn:admin2_code":"MMR005D009",
    "gn:admin3_code":"MMR005017",
    "gn:asciiname":"Kyaukpon-kan",
    "gn:country_code":"MM",
    "gn:dem":147,
    "gn:feature_class":"P",
    "gn:feature_code":"PPL",
    "gn:name":"Kyaukp\u00f4n-kan",
    "gn:population":0,
    "gn:timezone":"Asia/Yangon",
    "iso:country":"MM",
    "wof:name":"Kyaukpon-kan",
    "wof:placetype":"locality"
},
  "geometry": {"coordinates":[94.97602000000001,22.57294],"type":"Point"}
}