{
  "type": "Feature",
  "properties": {
    "gn:admin1_code":"6.0",
    "gn:admin2_code":"MMR002D001",
    "gn:admin3_code":"MMR002001",
    "gn:asciiname":"Nam-baw-wan",
    "gn:country_code":"MM",
    "gn:dem":896,
    "gn:feature_class":"P",
    "gn:feature_code":"PPL",
    "gn:name":"Nam-baw-w\u0101n",
    "gn:population":0,
    "gn:timezone":"Asia/Yangon",
    "iso:country":"MM",
    "wof:name":"Nam-baw-wan",
    "wof:placetype":"locality"
},
  "geometry": {"coordinates":[97.21928,19.65827],"type":"Point"}
}