{
  "type": "Feature",
  "properties": {
    "gn:admin1_code":"11.0",
    "gn:admin2_code":"MMR016D001",
    "gn:admin3_code":"MMR016002",
    "gn:asciiname":"Wan Hsenhkamhpu",
    "gn:country_code":"MM",
    "gn:dem":1652,
    "gn:feature_class":"P",
    "gn:feature_code":"PPL",
    "gn:name":"W\u0101n Hsenhkamhpu",
    "gn:population":0,
    "gn:timezone":"Asia/Yangon",
    "iso:country":"MM",
    "name:und_x_variant":[
        "W\u0101n Hsenhkamnpu",
        "W\u0101n Hsenhkamhpu"
    ],
    "wof:name":"Wan Hsenhkamhpu",
    "wof:placetype":"locality"
},
  "geometry": {"coordinates":[99.56437,21.64081],"type":"Point"}
}