{
  "type": "Feature",
  "properties": {
    "gn:admin1_code":"1.0",
    "gn:admin2_code":"MMR012D001",
    "gn:admin3_code":"MMR012007",
    "gn:asciiname":"Kreingshe",
    "gn:country_code":"MM",
    "gn:dem":3,
    "gn:feature_class":"P",
    "gn:feature_code":"PPL",
    "gn:name":"Kreingshe",
    "gn:population":0,
    "gn:timezone":"Asia/Yangon",
    "iso:country":"MM",
    "name:und_x_variant":[
        "Krinerhi",
        "Kreingshe"
    ],
    "wof:name":"Kreingshe",
    "wof:placetype":"locality"
},
  "geometry": {"coordinates":[93.16998,20.26958],"type":"Point"}
}