{
  "type": "Feature",
  "properties": {
    "gn:admin1_code":"17.0",
    "gn:admin2_code":"MMR013D003",
    "gn:admin3_code":"MMR013025",
    "gn:asciiname":"Kadonbaw",
    "gn:country_code":"MM",
    "gn:dem":11,
    "gn:feature_class":"P",
    "gn:feature_code":"PPL",
    "gn:name":"Kadonbaw",
    "gn:population":0,
    "gn:timezone":"Asia/Yangon",
    "iso:country":"MM",
    "name:und_x_variant":[
        "Kadonbaw-auk",
        "Kadonbaw"
    ],
    "wof:name":"Kadonbaw",
    "wof:placetype":"locality"
},
  "geometry": {"coordinates":[96.68962000000001,16.82198],"type":"Point"}
}