{
  "type": "Feature",
  "properties": {
    "gn:admin1_code":"11.0",
    "gn:admin2_code":"MMR014D002",
    "gn:admin3_code":"MMR014014",
    "gn:asciiname":"Nawngpung",
    "gn:country_code":"MM",
    "gn:dem":696,
    "gn:feature_class":"P",
    "gn:feature_code":"PPL",
    "gn:name":"Nawngpung",
    "gn:population":0,
    "gn:timezone":"Asia/Yangon",
    "iso:country":"MM",
    "wof:name":"Nawngpung",
    "wof:placetype":"locality"
},
  "geometry": {"coordinates":[98.50953,21.29017],"type":"Point"}
}