{
  "type": "Feature",
  "properties": {
    "gn:admin1_code":"11.0",
    "gn:admin2_code":"MMR016D001",
    "gn:admin3_code":"MMR016001",
    "gn:asciiname":"Wan Hsa",
    "gn:country_code":"MM",
    "gn:dem":792,
    "gn:feature_class":"P",
    "gn:feature_code":"PPL",
    "gn:name":"W\u0101n Hsa",
    "gn:population":0,
    "gn:timezone":"Asia/Yangon",
    "iso:country":"MM",
    "wof:name":"Wan Hsa",
    "wof:placetype":"locality"
},
  "geometry": {"coordinates":[99.64269,21.40284],"type":"Point"}
}