{
  "type": "Feature",
  "properties": {
    "gn:admin1_code":"11.0",
    "gn:admin2_code":"MMR016D002",
    "gn:admin3_code":"MMR016006",
    "gn:asciiname":"Wan Tinhtat",
    "gn:country_code":"MM",
    "gn:dem":584,
    "gn:feature_class":"P",
    "gn:feature_code":"PPL",
    "gn:name":"W\u0101n Tinhtat",
    "gn:population":0,
    "gn:timezone":"Asia/Yangon",
    "iso:country":"MM",
    "wof:name":"Wan Tinhtat",
    "wof:placetype":"locality"
},
  "geometry": {"coordinates":[99.60306,20.42361],"type":"Point"}
}