{
  "type": "Feature",
  "properties": {
    "gn:admin1_code":"4.0",
    "gn:admin2_code":"MMR001D004",
    "gn:admin3_code":"MMR001015",
    "gn:asciiname":"Wuja",
    "gn:country_code":"MM",
    "gn:dem":329,
    "gn:feature_class":"P",
    "gn:feature_code":"PPL",
    "gn:name":"Wuja",
    "gn:population":0,
    "gn:timezone":"Asia/Yangon",
    "iso:country":"MM",
    "name:und_x_variant":[
        "Npaunoi",
        "Waju",
        "Wuja"
    ],
    "wof:name":"Wuja",
    "wof:placetype":"locality"
},
  "geometry": {"coordinates":[97.6776,26.57338],"type":"Point"}
}