{
  "type": "Feature",
  "properties": {
    "gn:admin1_code":"6.0",
    "gn:admin2_code":"MMR002D002",
    "gn:admin3_code":"MMR002005",
    "gn:asciiname":"Namhu-pongsa-se",
    "gn:country_code":"MM",
    "gn:dem":178,
    "gn:feature_class":"P",
    "gn:feature_code":"PPL",
    "gn:name":"Namhu-pongsa-s\u0113",
    "gn:population":0,
    "gn:timezone":"Asia/Yangon",
    "iso:country":"MM",
    "wof:name":"Namhu-pongsa-se",
    "wof:placetype":"locality"
},
  "geometry": {"coordinates":[97.34424,19.10898],"type":"Point"}
}