{
  "type": "Feature",
  "properties": {
    "gn:admin1_code":"5.0",
    "gn:admin2_code":"MMR003D004",
    "gn:admin3_code":"MMR003003",
    "gn:asciiname":"Klemudo",
    "gn:country_code":"MM",
    "gn:dem":1052,
    "gn:feature_class":"P",
    "gn:feature_code":"PPL",
    "gn:name":"Klemudo",
    "gn:population":0,
    "gn:timezone":"Asia/Yangon",
    "iso:country":"MM",
    "wof:name":"Klemudo",
    "wof:placetype":"locality"
},
  "geometry": {"coordinates":[96.98896000000001,18.66111],"type":"Point"}
}