{
  "type": "Feature",
  "properties": {
    "gn:admin1_code":"15.0",
    "gn:admin2_code":"MMR009D002",
    "gn:admin3_code":"MMR009011",
    "gn:asciiname":"Pa-aing",
    "gn:country_code":"MM",
    "gn:dem":137,
    "gn:feature_class":"P",
    "gn:feature_code":"PPL",
    "gn:name":"Pa-aing",
    "gn:population":0,
    "gn:timezone":"Asia/Yangon",
    "iso:country":"MM",
    "wof:name":"Pa-aing",
    "wof:placetype":"locality"
},
  "geometry": {"coordinates":[94.34129,20.25359],"type":"Point"}
}