{
  "type": "Feature",
  "properties": {
    "gn:admin1_code":"12.0",
    "gn:admin2_code":"MMR006D001",
    "gn:admin3_code":"MMR006004",
    "gn:asciiname":"Uthayan",
    "gn:country_code":"MM",
    "gn:dem":18,
    "gn:feature_class":"P",
    "gn:feature_code":"PPL",
    "gn:name":"Uthayan",
    "gn:population":0,
    "gn:timezone":"Asia/Yangon",
    "iso:country":"MM",
    "name:sin_x_preferred":[
        "\u0d8b\u0daf\u0dba\u0db1\u0dca"
    ],
    "name:swe_x_preferred":[
        "Uthayan"
    ],
    "name:tam_x_preferred":[
        "\u0b89\u0ba4\u0baf\u0ba9\u0bcd"
    ],
    "wof:name":"Uthayan",
    "wof:placetype":"locality"
},
  "geometry": {"coordinates":[98.16901,14.35435],"type":"Point"}
}