{
  "type": "Feature",
  "properties": {
    "gn:admin1_code":"4.0",
    "gn:admin2_code":"MMR001D004",
    "gn:admin3_code":"MMR001016",
    "gn:asciiname":"Shangkabe",
    "gn:country_code":"MM",
    "gn:dem":708,
    "gn:feature_class":"P",
    "gn:feature_code":"PPL",
    "gn:name":"Shangkabe",
    "gn:population":0,
    "gn:timezone":"Asia/Yangon",
    "iso:country":"MM",
    "wof:name":"Shangkabe",
    "wof:placetype":"locality"
},
  "geometry": {"coordinates":[97.84999999999999,27.25],"type":"Point"}
}