{
  "type": "Feature",
  "properties": {
    "gn:admin1_code":"3.0",
    "gn:admin2_code":"MMR017D005",
    "gn:admin3_code":"MMR017022",
    "gn:asciiname":"Sagagyi",
    "gn:country_code":"MM",
    "gn:dem":15,
    "gn:feature_class":"P",
    "gn:feature_code":"PPL",
    "gn:name":"Sagagyi",
    "gn:population":0,
    "gn:timezone":"Asia/Yangon",
    "iso:country":"MM",
    "name:und_x_variant":[
        "Sagaywama",
        "Sagagyi"
    ],
    "wof:name":"Sagagyi",
    "wof:placetype":"locality"
},
  "geometry": {"coordinates":[95.61265,17.33134],"type":"Point"}
}