{
  "type": "Feature",
  "properties": {
    "gn:admin1_code":"11.0",
    "gn:admin2_code":"MMR014D001",
    "gn:admin3_code":"MMR014001",
    "gn:asciiname":"Koenghtun",
    "gn:country_code":"MM",
    "gn:dem":1004,
    "gn:feature_class":"P",
    "gn:feature_code":"PPL",
    "gn:name":"K\u00f6nghtun",
    "gn:population":0,
    "gn:timezone":"Asia/Yangon",
    "iso:country":"MM",
    "wof:name":"Koenghtun",
    "wof:placetype":"locality"
},
  "geometry": {"coordinates":[97.1793,20.39063],"type":"Point"}
}