{
  "type": "Feature",
  "properties": {
    "gn:admin1_code":"16.0",
    "gn:admin2_code":"MMR008D002",
    "gn:admin3_code":"MMR008009",
    "gn:asciiname":"Chaungna Anauk",
    "gn:country_code":"MM",
    "gn:dem":19,
    "gn:feature_class":"P",
    "gn:feature_code":"PPL",
    "gn:name":"Chaungna Anauk",
    "gn:population":0,
    "gn:timezone":"Asia/Yangon",
    "iso:country":"MM",
    "name:und_x_variant":[
        "Chaungna",
        "Chaungna Anauk"
    ],
    "wof:name":"Chaungna Anauk",
    "wof:placetype":"locality"
},
  "geometry": {"coordinates":[95.67361,17.91477],"type":"Point"}
}