{
  "type": "Feature",
  "properties": {
    "gn:admin1_code":"8.0",
    "gn:admin2_code":"MMR010D002",
    "gn:admin3_code":"MMR010008",
    "gn:asciiname":"Tha-bye-ye",
    "gn:country_code":"MM",
    "gn:dem":1017,
    "gn:feature_class":"P",
    "gn:feature_code":"PPL",
    "gn:name":"Tha-bye-ye",
    "gn:population":0,
    "gn:timezone":"Asia/Yangon",
    "iso:country":"MM",
    "wof:name":"Tha-bye-ye",
    "wof:placetype":"locality"
},
  "geometry": {"coordinates":[96.54730000000001,22.09564],"type":"Point"}
}