{
  "type": "Feature",
  "properties": {
    "gn:admin1_code":"11.0",
    "gn:admin2_code":"MMR016D003",
    "gn:admin3_code":"MMR016011",
    "gn:asciiname":"Wan Hpya-hkamhkuen",
    "gn:country_code":"MM",
    "gn:dem":1076,
    "gn:feature_class":"P",
    "gn:feature_code":"PPL",
    "gn:name":"W\u0101n Hpya-hkamhk\u00fcn",
    "gn:population":0,
    "gn:timezone":"Asia/Yangon",
    "iso:country":"MM",
    "name:und_x_variant":[
        "Hpya-hkamhkun",
        "W\u0101n Hpya-hkamhk\u00fcn"
    ],
    "wof:name":"Wan Hpya-hkamhkuen",
    "wof:placetype":"locality"
},
  "geometry": {"coordinates":[100.27221,21.41964],"type":"Point"}
}