{
  "type": "Feature",
  "properties": {
    "gn:admin1_code":"16.0",
    "gn:admin2_code":"MMR007D001",
    "gn:admin3_code":"MMR007008",
    "gn:asciiname":"Methana",
    "gn:country_code":"MM",
    "gn:dem":110,
    "gn:feature_class":"P",
    "gn:feature_code":"PPL",
    "gn:name":"Methana",
    "gn:population":0,
    "gn:timezone":"Asia/Yangon",
    "iso:country":"MM",
    "name:ara_x_preferred":[
        "\u0645\u064a\u062b\u0627\u0646\u0627"
    ],
    "name:cat_x_preferred":[
        "Methana"
    ],
    "name:ceb_x_preferred":[
        "M\u00e9thana"
    ],
    "name:deu_x_preferred":[
        "Methana"
    ],
    "name:ell_x_preferred":[
        "\u039c\u03ad\u03b8\u03b1\u03bd\u03b1"
    ],
    "name:fin_x_preferred":[
        "M\u00e9thana"
    ],
    "name:hye_x_preferred":[
        "\u0544\u0565\u057f\u0561\u0576\u0561"
    ],
    "name:ita_x_preferred":[
        "Methana"
    ],
    "name:lat_x_preferred":[
        "Methana"
    ],
    "name:nld_x_preferred":[
        "Methana"
    ],
    "name:nno_x_preferred":[
        "M\u00e9thana"
    ],
    "name:nor_x_preferred":[
        "Methana"
    ],
    "name:rus_x_preferred":[
        "\u041c\u0435\u0442\u0430\u043d\u0430"
    ],
    "name:spa_x_preferred":[
        "Metana"
    ],
    "name:swe_x_preferred":[
        "M\u00e9thana"
    ],
    "name:tur_x_preferred":[
        "Metana"
    ],
    "wof:name":"Methana",
    "wof:placetype":"locality"
},
  "geometry": {"coordinates":[97.06296,17.65382],"type":"Point"}
}