{
  "type": "Feature",
  "properties": {
    "gn:admin1_code":"11.0",
    "gn:admin2_code":"MMR015D006",
    "gn:admin3_code":"MMR015007",
    "gn:asciiname":"K'lawngle",
    "gn:country_code":"MM",
    "gn:dem":928,
    "gn:feature_class":"P",
    "gn:feature_code":"PPL",
    "gn:name":"K\u2019lawngle",
    "gn:population":0,
    "gn:timezone":"Asia/Yangon",
    "iso:country":"MM",
    "wof:name":"K'lawngle",
    "wof:placetype":"locality"
},
  "geometry": {"coordinates":[99.26667,23.03333],"type":"Point"}
}