{
  "type": "Feature",
  "properties": {
    "gn:admin1_code":"10.0",
    "gn:admin2_code":"MMR005D008",
    "gn:admin3_code":"MMR005033",
    "gn:asciiname":"Minsin",
    "gn:country_code":"MM",
    "gn:dem":135,
    "gn:feature_class":"P",
    "gn:feature_code":"PPL",
    "gn:name":"Minsin",
    "gn:population":0,
    "gn:timezone":"Asia/Yangon",
    "iso:country":"MM",
    "name:jpn_x_preferred":[
        "\u30df\u30f3\u30b7\u30f3"
    ],
    "wof:name":"Minsin",
    "wof:placetype":"locality"
},
  "geometry": {"coordinates":[95.37909000000001,25.52972],"type":"Point"}
}