{
  "type": "Feature",
  "properties": {
    "gn:admin1_code":"11.0",
    "gn:admin2_code":"MMR016D003",
    "gn:admin3_code":"MMR016010",
    "gn:asciiname":"Wan Pa-mun",
    "gn:country_code":"MM",
    "gn:dem":1101,
    "gn:feature_class":"P",
    "gn:feature_code":"PPL",
    "gn:name":"W\u0101n Pa-m\u016bn",
    "gn:population":0,
    "gn:timezone":"Asia/Yangon",
    "iso:country":"MM",
    "wof:name":"Wan Pa-mun",
    "wof:placetype":"locality"
},
  "geometry": {"coordinates":[100.10823000000001,20.94523],"type":"Point"}
}