{
  "type": "Feature",
  "properties": {
    "gn:admin1_code":"8.0",
    "gn:admin2_code":"MMR010D006",
    "gn:admin3_code":"MMR010023",
    "gn:asciiname":"Nwagu",
    "gn:country_code":"MM",
    "gn:dem":188,
    "gn:feature_class":"P",
    "gn:feature_code":"PPL",
    "gn:name":"Nwagu",
    "gn:population":0,
    "gn:timezone":"Asia/Yangon",
    "iso:country":"MM",
    "wof:name":"Nwagu",
    "wof:placetype":"locality"
},
  "geometry": {"coordinates":[96.16134,20.50818],"type":"Point"}
}