{
  "type": "Feature",
  "properties": {
    "gn:admin1_code":"10.0",
    "gn:admin2_code":"MMR005D002",
    "gn:admin3_code":"MMR005004",
    "gn:asciiname":"Pokkon",
    "gn:country_code":"MM",
    "gn:dem":136,
    "gn:feature_class":"P",
    "gn:feature_code":"PPL",
    "gn:name":"Pokkon",
    "gn:population":0,
    "gn:timezone":"Asia/Yangon",
    "iso:country":"MM",
    "wof:name":"Pokkon",
    "wof:placetype":"locality"
},
  "geometry": {"coordinates":[95.69046,22.67081],"type":"Point"}
}