{
  "type": "Feature",
  "properties": {
    "gn:admin1_code":"10.0",
    "gn:admin2_code":"MMR005D009",
    "gn:admin3_code":"MMR005018",
    "gn:asciiname":"Nipadan",
    "gn:country_code":"MM",
    "gn:dem":136,
    "gn:feature_class":"P",
    "gn:feature_code":"PPL",
    "gn:name":"Nipadan",
    "gn:population":0,
    "gn:timezone":"Asia/Yangon",
    "iso:country":"MM",
    "wof:name":"Nipadan",
    "wof:placetype":"locality"
},
  "geometry": {"coordinates":[95.00738,21.94367],"type":"Point"}
}