{
  "type": "Feature",
  "properties": {
    "gn:admin1_code":"11.0",
    "gn:admin2_code":"MMR015D001",
    "gn:admin3_code":"MMR015002",
    "gn:asciiname":"Makhkek",
    "gn:country_code":"MM",
    "gn:dem":623,
    "gn:feature_class":"P",
    "gn:feature_code":"PPL",
    "gn:name":"Makhkek",
    "gn:population":0,
    "gn:timezone":"Asia/Yangon",
    "iso:country":"MM",
    "wof:name":"Makhkek",
    "wof:placetype":"locality"
},
  "geometry": {"coordinates":[97.99952999999999,23.30691],"type":"Point"}
}