{
  "type": "Feature",
  "properties": {
    "gn:admin1_code":"10.0",
    "gn:admin2_code":"MMR005D002",
    "gn:admin3_code":"MMR005010",
    "gn:asciiname":"Inbin",
    "gn:country_code":"MM",
    "gn:dem":102,
    "gn:feature_class":"P",
    "gn:feature_code":"PPL",
    "gn:name":"Inbin",
    "gn:population":0,
    "gn:timezone":"Asia/Yangon",
    "iso:country":"MM",
    "wof:name":"Inbin",
    "wof:placetype":"locality"
},
  "geometry": {"coordinates":[95.41388000000001,22.6017],"type":"Point"}
}