{
  "type": "Feature",
  "properties": {
    "gn:admin1_code":"15.0",
    "gn:admin2_code":"MMR009D002",
    "gn:admin3_code":"MMR009011",
    "gn:asciiname":"Kyetkyi",
    "gn:country_code":"MM",
    "gn:dem":463,
    "gn:feature_class":"P",
    "gn:feature_code":"PPL",
    "gn:name":"Kyetkyi",
    "gn:population":0,
    "gn:timezone":"Asia/Yangon",
    "iso:country":"MM",
    "wof:name":"Kyetkyi",
    "wof:placetype":"locality"
},
  "geometry": {"coordinates":[94.21789,20.85067],"type":"Point"}
}