{
  "type": "Feature",
  "properties": {
    "gn:admin1_code":"5.0",
    "gn:admin2_code":"MMR003D004",
    "gn:admin3_code":"MMR003003",
    "gn:asciiname":"Lowakodo",
    "gn:country_code":"MM",
    "gn:dem":430,
    "gn:feature_class":"P",
    "gn:feature_code":"PPL",
    "gn:name":"Lowakodo",
    "gn:population":0,
    "gn:timezone":"Asia/Yangon",
    "iso:country":"MM",
    "name:und_x_variant":[
        "Lowakedo",
        "Lowakdo",
        "Lowakodo"
    ],
    "wof:name":"Lowakodo",
    "wof:placetype":"locality"
},
  "geometry": {"coordinates":[97.34990000000001,18.13572000000001],"type":"Point"}
}