{
  "type": "Feature",
  "properties": {
    "gn:admin1_code":"15.0",
    "gn:admin2_code":"MMR009D003",
    "gn:admin3_code":"MMR009016",
    "gn:asciiname":"Zeya",
    "gn:country_code":"MM",
    "gn:dem":37,
    "gn:feature_class":"P",
    "gn:feature_code":"PPL",
    "gn:name":"Zeya",
    "gn:population":0,
    "gn:timezone":"Asia/Yangon",
    "iso:country":"MM",
    "name:aze_x_preferred":[
        "Zeya"
    ],
    "name:ben_x_preferred":[
        "\u099c\u09bf\u09af\u09bc\u09be"
    ],
    "name:ceb_x_preferred":[
        "Zeya"
    ],
    "name:dan_x_preferred":[
        "Zeya"
    ],
    "name:ell_x_preferred":[
        "\u0396\u03ad\u03b9\u03b1"
    ],
    "name:hin_x_preferred":[
        "\u091c\u093c\u0947\u092f\u093e"
    ],
    "name:ind_x_preferred":[
        "Zeya"
    ],
    "name:jpn_x_preferred":[
        "\u30bc\u30e4"
    ],
    "name:por_x_preferred":[
        "Zeya"
    ],
    "name:spa_x_preferred":[
        "Zeya"
    ],
    "name:swe_x_preferred":[
        "Zeya"
    ],
    "name:urd_x_preferred":[
        "\u0632\u06d2 \u06cc\u0627"
    ],
    "name:vie_x_preferred":[
        "Zeya"
    ],
    "wof:name":"Zeya",
    "wof:placetype":"locality"
},
  "geometry": {"coordinates":[95.1324,19.05718],"type":"Point"}
}