{
  "type": "Feature",
  "properties": {
    "gn:admin1_code":"10.0",
    "gn:admin2_code":"MMR005D002",
    "gn:admin3_code":"MMR005005",
    "gn:asciiname":"Thanbo",
    "gn:country_code":"MM",
    "gn:dem":142,
    "gn:feature_class":"P",
    "gn:feature_code":"PPL",
    "gn:name":"Thanbo",
    "gn:population":0,
    "gn:timezone":"Asia/Yangon",
    "iso:country":"MM",
    "wof:name":"Thanbo",
    "wof:placetype":"locality"
},
  "geometry": {"coordinates":[95.67415,22.73076],"type":"Point"}
}