{
  "type": "Feature",
  "properties": {
    "gn:admin1_code":"10.0",
    "gn:admin2_code":"MMR005D008",
    "gn:admin3_code":"MMR005034",
    "gn:asciiname":"Natnan",
    "gn:country_code":"MM",
    "gn:dem":189,
    "gn:feature_class":"P",
    "gn:feature_code":"PPL",
    "gn:name":"Natnan",
    "gn:population":0,
    "gn:timezone":"Asia/Yangon",
    "iso:country":"MM",
    "wof:name":"Natnan",
    "wof:placetype":"locality"
},
  "geometry": {"coordinates":[94.99169999999999,24.58481],"type":"Point"}
}