{
  "type": "Feature",
  "properties": {
    "gn:admin1_code":"4.0",
    "gn:admin2_code":"MMR001D003",
    "gn:admin3_code":"MMR001012",
    "gn:asciiname":"Nralungbyen",
    "gn:country_code":"MM",
    "gn:dem":1452,
    "gn:feature_class":"P",
    "gn:feature_code":"PPL",
    "gn:name":"Nralungbyen",
    "gn:population":0,
    "gn:timezone":"Asia/Yangon",
    "iso:country":"MM",
    "wof:name":"Nralungbyen",
    "wof:placetype":"locality"
},
  "geometry": {"coordinates":[97.53539000000001,24.3102],"type":"Point"}
}