{
  "type": "Feature",
  "properties": {
    "gn:admin1_code":"4.0",
    "gn:admin2_code":"MMR001D001",
    "gn:admin3_code":"MMR001001",
    "gn:asciiname":"'Ngao Ga",
    "gn:country_code":"MM",
    "gn:dem":505,
    "gn:feature_class":"P",
    "gn:feature_code":"PPL",
    "gn:name":"\u2019Ngao Ga",
    "gn:population":0,
    "gn:timezone":"Asia/Yangon",
    "iso:country":"MM",
    "wof:name":"'Ngao Ga",
    "wof:placetype":"locality"
},
  "geometry": {"coordinates":[97.30745,25.88387],"type":"Point"}
}