{
  "type": "Feature",
  "properties": {
    "gn:admin1_code":"4.0",
    "gn:admin2_code":"MMR001D004",
    "gn:admin3_code":"MMR001017",
    "gn:asciiname":"Saranshamdam",
    "gn:country_code":"MM",
    "gn:dem":2079,
    "gn:feature_class":"P",
    "gn:feature_code":"PPL",
    "gn:name":"Saranshamd\u0101m",
    "gn:population":0,
    "gn:timezone":"Asia/Yangon",
    "iso:country":"MM",
    "wof:name":"Saranshamdam",
    "wof:placetype":"locality"
},
  "geometry": {"coordinates":[97.66667,28.16667],"type":"Point"}
}