{
  "type": "Feature",
  "properties": {
    "gn:admin1_code":"6.0",
    "gn:admin2_code":"MMR002D001",
    "gn:admin3_code":"MMR002004",
    "gn:asciiname":"Daw Kawle",
    "gn:country_code":"MM",
    "gn:dem":833,
    "gn:feature_class":"P",
    "gn:feature_code":"PPL",
    "gn:name":"Daw Kawl\u00e8",
    "gn:population":0,
    "gn:timezone":"Asia/Yangon",
    "iso:country":"MM",
    "wof:name":"Daw Kawle",
    "wof:placetype":"locality"
},
  "geometry": {"coordinates":[97.50851,19.56137],"type":"Point"}
}