{
  "type": "Feature",
  "properties": {
    "gn:admin1_code":"11.0",
    "gn:admin2_code":"MMR015D003",
    "gn:admin3_code":"MMR015012",
    "gn:asciiname":"Mansan",
    "gn:country_code":"MM",
    "gn:dem":1095,
    "gn:feature_class":"P",
    "gn:feature_code":"PPL",
    "gn:name":"M\u0101ns\u0101n",
    "gn:population":0,
    "gn:timezone":"Asia/Yangon",
    "iso:country":"MM",
    "name:und_x_variant":[
        "M\u0101ns\u0101n"
    ],
    "wof:name":"Mansan",
    "wof:placetype":"locality"
},
  "geometry": {"coordinates":[96.92914,22.67092],"type":"Point"}
}