{
  "type": "Feature",
  "properties": {
    "gn:admin1_code":"10.0",
    "gn:admin2_code":"MMR005D001",
    "gn:admin3_code":"MMR005001",
    "gn:asciiname":"Mutha",
    "gn:country_code":"MM",
    "gn:dem":80,
    "gn:feature_class":"P",
    "gn:feature_code":"PPL",
    "gn:name":"Mutha",
    "gn:population":0,
    "gn:timezone":"Asia/Yangon",
    "iso:country":"MM",
    "wof:name":"Mutha",
    "wof:placetype":"locality"
},
  "geometry": {"coordinates":[95.65933,22.10813],"type":"Point"}
}