{
  "type": "Feature",
  "properties": {
    "gn:admin1_code":"3.0",
    "gn:admin2_code":"MMR017D001",
    "gn:admin3_code":"MMR017003",
    "gn:asciiname":"Ponnyetmaw",
    "gn:country_code":"MM",
    "gn:dem":10,
    "gn:feature_class":"P",
    "gn:feature_code":"PPL",
    "gn:name":"Ponnyetmaw",
    "gn:population":0,
    "gn:timezone":"Asia/Yangon",
    "iso:country":"MM",
    "wof:name":"Ponnyetmaw",
    "wof:placetype":"locality"
},
  "geometry": {"coordinates":[94.55974999999999,17.42947],"type":"Point"}
}