{
  "type": "Feature",
  "properties": {
    "gn:admin1_code":"11.0",
    "gn:admin2_code":"MMR016D002",
    "gn:admin3_code":"MMR016006",
    "gn:asciiname":"Hsinlonghkamti",
    "gn:country_code":"MM",
    "gn:dem":825,
    "gn:feature_class":"P",
    "gn:feature_code":"PPL",
    "gn:name":"Hsinlonghkamti",
    "gn:population":0,
    "gn:timezone":"Asia/Yangon",
    "iso:country":"MM",
    "wof:name":"Hsinlonghkamti",
    "wof:placetype":"locality"
},
  "geometry": {"coordinates":[99.27037,20.26588],"type":"Point"}
}