{
  "type": "Feature",
  "properties": {
    "gn:admin1_code":"10.0",
    "gn:admin2_code":"MMR005D004",
    "gn:admin3_code":"MMR005023",
    "gn:asciiname":"Manhton",
    "gn:country_code":"MM",
    "gn:dem":169,
    "gn:feature_class":"P",
    "gn:feature_code":"PPL",
    "gn:name":"Manhton",
    "gn:population":0,
    "gn:timezone":"Asia/Yangon",
    "iso:country":"MM",
    "wof:name":"Manhton",
    "wof:placetype":"locality"
},
  "geometry": {"coordinates":[95.95661,24.57149],"type":"Point"}
}