{
  "type": "Feature",
  "properties": {
    "gn:admin1_code":"8.0",
    "gn:admin2_code":"MMR010D001",
    "gn:admin3_code":"MMR010006",
    "gn:asciiname":"Tawdwin",
    "gn:country_code":"MM",
    "gn:dem":87,
    "gn:feature_class":"P",
    "gn:feature_code":"PPL",
    "gn:name":"Tawdwin",
    "gn:population":0,
    "gn:timezone":"Asia/Yangon",
    "iso:country":"MM",
    "wof:name":"Tawdwin",
    "wof:placetype":"locality"
},
  "geometry": {"coordinates":[96.18527,21.87175],"type":"Point"}
}