{
  "type": "Feature",
  "properties": {
    "gn:admin1_code":"3.0",
    "gn:admin2_code":"MMR017D001",
    "gn:admin3_code":"MMR017005",
    "gn:asciiname":"Zigon",
    "gn:country_code":"MM",
    "gn:dem":9,
    "gn:feature_class":"P",
    "gn:feature_code":"PPL",
    "gn:name":"Zigon",
    "gn:population":0,
    "gn:timezone":"Asia/Yangon",
    "iso:country":"MM",
    "name:mya_x_preferred":[
        "\u1007\u102e\u1038\u1000\u102f\u1014\u103a\u1038\u1019\u103c\u102d\u102f\u1037"
    ],
    "name:shn_x_preferred":[
        "\u1078\u102e\u1038\u1075\u1030\u1004\u103a\u1038\u104a \u101d\u1035\u1004\u103a\u1038"
    ],
    "name:swe_x_preferred":[
        "Zigon"
    ],
    "wof:name":"Zigon",
    "wof:placetype":"locality"
},
  "geometry": {"coordinates":[95.218,17.37211],"type":"Point"}
}