{
  "type": "Feature",
  "properties": {
    "gn:admin1_code":"8.0",
    "gn:admin2_code":"MMR010D003",
    "gn:admin3_code":"MMR010015",
    "gn:asciiname":"Tanaungbinhla",
    "gn:country_code":"MM",
    "gn:dem":100,
    "gn:feature_class":"P",
    "gn:feature_code":"PPL",
    "gn:name":"Tanaungbinhla",
    "gn:population":0,
    "gn:timezone":"Asia/Yangon",
    "iso:country":"MM",
    "wof:name":"Tanaungbinhla",
    "wof:placetype":"locality"
},
  "geometry": {"coordinates":[95.99581000000001,21.54597],"type":"Point"}
}