{
  "type": "Feature",
  "properties": {
    "gn:admin1_code":"11.0",
    "gn:admin2_code":"MMR015D005",
    "gn:admin3_code":"MMR015023",
    "gn:asciiname":"Wayaw",
    "gn:country_code":"MM",
    "gn:dem":1423,
    "gn:feature_class":"P",
    "gn:feature_code":"PPL",
    "gn:name":"Wayaw",
    "gn:population":0,
    "gn:timezone":"Asia/Yangon",
    "iso:country":"MM",
    "wof:name":"Wayaw",
    "wof:placetype":"locality"
},
  "geometry": {"coordinates":[98.62013,24.06207],"type":"Point"}
}