{
  "type": "Feature",
  "properties": {
    "gn:admin1_code":"8.0",
    "gn:admin2_code":"MMR010D002",
    "gn:admin3_code":"MMR010008",
    "gn:asciiname":"Ye-tha-lauk-kon",
    "gn:country_code":"MM",
    "gn:dem":938,
    "gn:feature_class":"P",
    "gn:feature_code":"PPL",
    "gn:name":"Ye-tha-lauk-kon",
    "gn:population":0,
    "gn:timezone":"Asia/Yangon",
    "iso:country":"MM",
    "wof:name":"Ye-tha-lauk-kon",
    "wof:placetype":"locality"
},
  "geometry": {"coordinates":[96.58099,22.07489],"type":"Point"}
}