{
  "type": "Feature",
  "properties": {
    "gn:admin1_code":"11.0",
    "gn:admin2_code":"MMR016D002",
    "gn:admin3_code":"MMR016008",
    "gn:asciiname":"Wan Nam-hu",
    "gn:country_code":"MM",
    "gn:dem":590,
    "gn:feature_class":"P",
    "gn:feature_code":"PPL",
    "gn:name":"W\u0101n Nam-hu",
    "gn:population":0,
    "gn:timezone":"Asia/Yangon",
    "iso:country":"MM",
    "wof:name":"Wan Nam-hu",
    "wof:placetype":"locality"
},
  "geometry": {"coordinates":[98.93798,19.87288],"type":"Point"}
}