{
  "type": "Feature",
  "properties": {
    "gn:admin1_code":"10.0",
    "gn:admin2_code":"MMR005D003",
    "gn:admin3_code":"MMR005014",
    "gn:asciiname":"Zayit",
    "gn:country_code":"MM",
    "gn:dem":86,
    "gn:feature_class":"P",
    "gn:feature_code":"PPL",
    "gn:name":"Zayit",
    "gn:population":0,
    "gn:timezone":"Asia/Yangon",
    "iso:country":"MM",
    "wof:name":"Zayit",
    "wof:placetype":"locality"
},
  "geometry": {"coordinates":[95.56679,22.28734],"type":"Point"}
}