{
  "type": "Feature",
  "properties": {
    "gn:admin1_code":"16.0",
    "gn:admin2_code":"MMR007D002",
    "gn:admin3_code":"MMR007011",
    "gn:asciiname":"Kawleido",
    "gn:country_code":"MM",
    "gn:dem":674,
    "gn:feature_class":"P",
    "gn:feature_code":"PPL",
    "gn:name":"Kawleido",
    "gn:population":0,
    "gn:timezone":"Asia/Yangon",
    "iso:country":"MM",
    "name:und_x_variant":[
        "Kawlaido",
        "Kawleido"
    ],
    "wof:name":"Kawleido",
    "wof:placetype":"locality"
},
  "geometry": {"coordinates":[97.11991,18.25754],"type":"Point"}
}