{
  "type": "Feature",
  "properties": {
    "gn:admin1_code":"16.0",
    "gn:admin2_code":"MMR007D001",
    "gn:admin3_code":"MMR007001",
    "gn:asciiname":"Kyatgyi",
    "gn:country_code":"MM",
    "gn:dem":33,
    "gn:feature_class":"P",
    "gn:feature_code":"PPL",
    "gn:name":"Kyatgyi",
    "gn:population":0,
    "gn:timezone":"Asia/Yangon",
    "iso:country":"MM",
    "name:und_x_variant":[
        "Kyatkyi",
        "Kyatgyi"
    ],
    "wof:name":"Kyatgyi",
    "wof:placetype":"locality"
},
  "geometry": {"coordinates":[96.25506,17.54395],"type":"Point"}
}