{
  "type": "Feature",
  "properties": {
    "gn:admin1_code":"12.0",
    "gn:admin2_code":"MMR006D003",
    "gn:admin3_code":"MMR006010",
    "gn:asciiname":"Shangan",
    "gn:country_code":"MM",
    "gn:dem":12,
    "gn:feature_class":"P",
    "gn:feature_code":"PPL",
    "gn:name":"Shangan",
    "gn:population":0,
    "gn:timezone":"Asia/Yangon",
    "iso:country":"MM",
    "name:und_x_variant":[
        "Shan-nge Ywa",
        "Shangan"
    ],
    "wof:name":"Shangan",
    "wof:placetype":"locality"
},
  "geometry": {"coordinates":[98.74306,11.44577],"type":"Point"}
}