{
  "type": "Feature",
  "properties": {
    "gn:admin1_code":"4.0",
    "gn:admin2_code":"MMR001D004",
    "gn:admin3_code":"MMR001016",
    "gn:asciiname":"Shingiat Ga",
    "gn:country_code":"MM",
    "gn:dem":898,
    "gn:feature_class":"P",
    "gn:feature_code":"PPL",
    "gn:name":"Shingiat Ga",
    "gn:population":0,
    "gn:timezone":"Asia/Yangon",
    "iso:country":"MM",
    "wof:name":"Shingiat Ga",
    "wof:placetype":"locality"
},
  "geometry": {"coordinates":[97.91656999999999,27.11372],"type":"Point"}
}