{
  "type": "Feature",
  "properties": {
    "gn:admin1_code":"11.0",
    "gn:admin2_code":"MMR016D001",
    "gn:admin3_code":"MMR016001",
    "gn:asciiname":"Wan Ke-nai",
    "gn:country_code":"MM",
    "gn:dem":1320,
    "gn:feature_class":"P",
    "gn:feature_code":"PPL",
    "gn:name":"W\u0101n Ke-nai",
    "gn:population":0,
    "gn:timezone":"Asia/Yangon",
    "iso:country":"MM",
    "name:und_x_variant":[
        "W\u0101n Kwi Ke-nai",
        "W\u0101n Ke-nai"
    ],
    "wof:name":"Wan Ke-nai",
    "wof:placetype":"locality"
},
  "geometry": {"coordinates":[99.5688,21.02345],"type":"Point"}
}