{
  "type": "Feature",
  "properties": {
    "gn:admin1_code":"8.0",
    "gn:admin2_code":"MMR010D004",
    "gn:admin3_code":"MMR010017",
    "gn:asciiname":"Theinywa",
    "gn:country_code":"MM",
    "gn:dem":73,
    "gn:feature_class":"P",
    "gn:feature_code":"PPL",
    "gn:name":"Theinywa",
    "gn:population":0,
    "gn:timezone":"Asia/Yangon",
    "iso:country":"MM",
    "wof:name":"Theinywa",
    "wof:placetype":"locality"
},
  "geometry": {"coordinates":[95.42131000000001,21.65487000000001],"type":"Point"}
}