{
  "type": "Feature",
  "properties": {
    "gn:admin1_code":"15.0",
    "gn:admin2_code":"MMR009D004",
    "gn:admin3_code":"MMR009019",
    "gn:asciiname":"Kyakat",
    "gn:country_code":"MM",
    "gn:dem":75,
    "gn:feature_class":"P",
    "gn:feature_code":"PPL",
    "gn:name":"Kyakat",
    "gn:population":0,
    "gn:timezone":"Asia/Yangon",
    "iso:country":"MM",
    "wof:name":"Kyakat",
    "wof:placetype":"locality"
},
  "geometry": {"coordinates":[95.21666999999999,21.69032],"type":"Point"}
}