{
  "type": "Feature",
  "properties": {
    "gn:admin1_code":"11.0",
    "gn:admin2_code":"MMR016D003",
    "gn:admin3_code":"MMR016011",
    "gn:asciiname":"Wan Nawngkiao",
    "gn:country_code":"MM",
    "gn:dem":532,
    "gn:feature_class":"P",
    "gn:feature_code":"PPL",
    "gn:name":"W\u0101n Nawngkiao",
    "gn:population":0,
    "gn:timezone":"Asia/Yangon",
    "iso:country":"MM",
    "name:und_x_variant":[
        "Nawngkiao",
        "W\u0101n Nawngkiao"
    ],
    "wof:name":"Wan Nawngkiao",
    "wof:placetype":"locality"
},
  "geometry": {"coordinates":[100.39474,21.1433],"type":"Point"}
}