{
  "type": "Feature",
  "properties": {
    "gn:admin1_code":"17.0",
    "gn:admin2_code":"MMR013D003",
    "gn:admin3_code":"MMR013026",
    "gn:asciiname":"Nyaunglan",
    "gn:country_code":"MM",
    "gn:dem":6,
    "gn:feature_class":"P",
    "gn:feature_code":"PPL",
    "gn:name":"Nyaunglan",
    "gn:population":0,
    "gn:timezone":"Asia/Yangon",
    "iso:country":"MM",
    "wof:name":"Nyaunglan",
    "wof:placetype":"locality"
},
  "geometry": {"coordinates":[96.62260999999999,16.94738],"type":"Point"}
}