{
  "type": "Feature",
  "properties": {
    "gn:admin1_code":"11.0",
    "gn:admin2_code":"MMR014D001",
    "gn:admin3_code":"MMR014008",
    "gn:asciiname":"Tawnggyi",
    "gn:country_code":"MM",
    "gn:dem":1073,
    "gn:feature_class":"P",
    "gn:feature_code":"PPL",
    "gn:name":"Tawnggyi",
    "gn:population":0,
    "gn:timezone":"Asia/Yangon",
    "iso:country":"MM",
    "wof:name":"Tawnggyi",
    "wof:placetype":"locality"
},
  "geometry": {"coordinates":[96.82637,21.33296],"type":"Point"}
}