{
  "type": "Feature",
  "properties": {
    "gn:admin1_code":"17.0",
    "gn:asciiname":"Letpangon",
    "gn:country_code":"MM",
    "gn:dem":16,
    "gn:feature_class":"P",
    "gn:feature_code":"PPL",
    "gn:name":"Letpangon",
    "gn:population":0,
    "gn:timezone":"Asia/Yangon",
    "iso:country":"MM",
    "name:und_x_variant":[
        "Letpandon",
        "Letpangon"
    ],
    "wof:name":"Letpangon",
    "wof:placetype":"locality"
},
  "geometry": {"coordinates":[95.76633,17.50412],"type":"Point"}
}