{
  "type": "Feature",
  "properties": {
    "gn:admin1_code":"6.0",
    "gn:admin2_code":"MMR002D001",
    "gn:admin3_code":"MMR002004",
    "gn:asciiname":"Daw Ta-ngu",
    "gn:country_code":"MM",
    "gn:dem":1124,
    "gn:feature_class":"P",
    "gn:feature_code":"PPL",
    "gn:name":"Daw Ta-ngu",
    "gn:population":0,
    "gn:timezone":"Asia/Yangon",
    "iso:country":"MM",
    "wof:name":"Daw Ta-ngu",
    "wof:placetype":"locality"
},
  "geometry": {"coordinates":[97.52958,19.85478],"type":"Point"}
}