{
  "type": "Feature",
  "properties": {
    "gn:admin1_code":"16.0",
    "gn:admin2_code":"MMR008D001",
    "gn:admin3_code":"MMR008005",
    "gn:asciiname":"Yonbindet",
    "gn:country_code":"MM",
    "gn:dem":60,
    "gn:feature_class":"P",
    "gn:feature_code":"PPL",
    "gn:name":"Yonbindet",
    "gn:population":0,
    "gn:timezone":"Asia/Yangon",
    "iso:country":"MM",
    "wof:name":"Yonbindet",
    "wof:placetype":"locality"
},
  "geometry": {"coordinates":[95.47539,18.6651],"type":"Point"}
}