{
  "type": "Feature",
  "properties": {
    "gn:admin1_code":"11.0",
    "gn:admin2_code":"MMR015D002",
    "gn:admin3_code":"MMR015011",
    "gn:asciiname":"Lao-sai",
    "gn:country_code":"MM",
    "gn:dem":1132,
    "gn:feature_class":"P",
    "gn:feature_code":"PPL",
    "gn:name":"Lao-sai",
    "gn:population":0,
    "gn:timezone":"Asia/Yangon",
    "iso:country":"MM",
    "wof:name":"Lao-sai",
    "wof:placetype":"locality"
},
  "geometry": {"coordinates":[98.41746999999999,23.82888],"type":"Point"}
}