{
  "type": "Feature",
  "properties": {
    "gn:admin1_code":"11.0",
    "gn:admin2_code":"MMR016D002",
    "gn:admin3_code":"MMR016008",
    "gn:asciiname":"Hpya-hsumhkam",
    "gn:country_code":"MM",
    "gn:dem":1551,
    "gn:feature_class":"P",
    "gn:feature_code":"PPL",
    "gn:name":"Hpya-hsumhkam",
    "gn:population":0,
    "gn:timezone":"Asia/Yangon",
    "iso:country":"MM",
    "wof:name":"Hpya-hsumhkam",
    "wof:placetype":"locality"
},
  "geometry": {"coordinates":[98.81858,20.08034],"type":"Point"}
}