{
  "type": "Feature",
  "properties": {
    "gn:admin1_code":"12.0",
    "gn:admin2_code":"MMR006D002",
    "gn:admin3_code":"MMR006007",
    "gn:asciiname":"Nabule",
    "gn:country_code":"MM",
    "gn:dem":25,
    "gn:feature_class":"P",
    "gn:feature_code":"PPL",
    "gn:name":"Nabule",
    "gn:population":0,
    "gn:timezone":"Asia/Yangon",
    "iso:country":"MM",
    "wof:name":"Nabule",
    "wof:placetype":"locality"
},
  "geometry": {"coordinates":[98.70305999999999,13.01371],"type":"Point"}
}