{
  "type": "Feature",
  "properties": {
    "gn:admin1_code":"11.0",
    "gn:admin2_code":"MMR015D006",
    "gn:admin3_code":"MMR015007",
    "gn:asciiname":"Manhai",
    "gn:country_code":"MM",
    "gn:dem":1136,
    "gn:feature_class":"P",
    "gn:feature_code":"PPL",
    "gn:name":"Manhai",
    "gn:population":0,
    "gn:timezone":"Asia/Yangon",
    "iso:country":"MM",
    "wof:name":"Manhai",
    "wof:placetype":"locality"
},
  "geometry": {"coordinates":[99.34999999999999,23.06667],"type":"Point"}
}