{
  "type": "Feature",
  "properties": {
    "gn:admin1_code":"17.0",
    "gn:admin2_code":"MMR013D001",
    "gn:admin3_code":"MMR013004",
    "gn:asciiname":"Insein",
    "gn:country_code":"MM",
    "gn:dem":12,
    "gn:feature_class":"P",
    "gn:feature_code":"PPL",
    "gn:name":"Insein",
    "gn:population":0,
    "gn:timezone":"Asia/Yangon",
    "iso:country":"MM",
    "name:pol_x_preferred":[
        "Insein"
    ],
    "wof:name":"Insein",
    "wof:placetype":"locality"
},
  "geometry": {"coordinates":[96.26945000000001,17.15123],"type":"Point"}
}