{
  "type": "Feature",
  "properties": {
    "gn:admin1_code":"16.0",
    "gn:admin2_code":"MMR007D001",
    "gn:admin3_code":"MMR007008",
    "gn:asciiname":"Taingbinywa",
    "gn:country_code":"MM",
    "gn:dem":156,
    "gn:feature_class":"P",
    "gn:feature_code":"PPL",
    "gn:name":"Taingbinywa",
    "gn:population":0,
    "gn:timezone":"Asia/Yangon",
    "iso:country":"MM",
    "wof:name":"Taingbinywa",
    "wof:placetype":"locality"
},
  "geometry": {"coordinates":[96.90957,18.13965],"type":"Point"}
}