{
  "type": "Feature",
  "properties": {
    "gn:admin1_code":"11.0",
    "gn:admin2_code":"MMR015D003",
    "gn:admin3_code":"MMR015013",
    "gn:asciiname":"Ton-pha",
    "gn:country_code":"MM",
    "gn:dem":226,
    "gn:feature_class":"P",
    "gn:feature_code":"PPL",
    "gn:name":"Ton-pha",
    "gn:population":0,
    "gn:timezone":"Asia/Yangon",
    "iso:country":"MM",
    "name:und_x_variant":[
        "Tawnghpa",
        "Ton-pha"
    ],
    "wof:name":"Ton-pha",
    "wof:placetype":"locality"
},
  "geometry": {"coordinates":[96.75595,22.09188],"type":"Point"}
}