{
  "type": "Feature",
  "properties": {
    "gn:admin1_code":"15.0",
    "gn:admin2_code":"MMR009D001",
    "gn:admin3_code":"MMR009004",
    "gn:asciiname":"Pagangon",
    "gn:country_code":"MM",
    "gn:dem":143,
    "gn:feature_class":"P",
    "gn:feature_code":"PPL",
    "gn:name":"Pagang\u00f4n",
    "gn:population":0,
    "gn:timezone":"Asia/Yangon",
    "iso:country":"MM",
    "wof:name":"Pagangon",
    "wof:placetype":"locality"
},
  "geometry": {"coordinates":[95.52643,19.96204],"type":"Point"}
}