{
  "type": "Feature",
  "properties": {
    "gn:admin1_code":"4.0",
    "gn:admin2_code":"MMR001D004",
    "gn:admin3_code":"MMR001016",
    "gn:asciiname":"Machanbaw",
    "gn:country_code":"MM",
    "gn:dem":560,
    "gn:feature_class":"P",
    "gn:feature_code":"PPL",
    "gn:name":"Machanbaw",
    "gn:population":0,
    "gn:timezone":"Asia/Yangon",
    "iso:country":"MM",
    "name:mya_x_preferred":[
        "\u1019\u1001\u103b\u1019\u103a\u1038\u1018\u1031\u102c\u1019\u103c\u102d\u102f\u1037"
    ],
    "name:shn_x_preferred":[
        "\u1019\u1062\u1075\u103a\u1087\u1078\u1062\u1004\u103a\u1038\u1015\u1031\u1083\u1038\u104a \u101d\u1035\u1004\u103a\u1038"
    ],
    "name:urd_x_preferred":[
        "\u0645\u0627\u0686\u0627\u0646\u0628\u0627\u0648"
    ],
    "wof:name":"Machanbaw",
    "wof:placetype":"locality"
},
  "geometry": {"coordinates":[97.59999999999999,27.26667],"type":"Point"}
}