{
  "type": "Feature",
  "properties": {
    "gn:admin1_code":"12.0",
    "gn:admin2_code":"MMR006D001",
    "gn:admin3_code":"MMR006002",
    "gn:asciiname":"Nga-ye-chaung",
    "gn:country_code":"MM",
    "gn:dem":27,
    "gn:feature_class":"P",
    "gn:feature_code":"PPL",
    "gn:name":"Nga-y\u00e8-chaung",
    "gn:population":0,
    "gn:timezone":"Asia/Yangon",
    "iso:country":"MM",
    "wof:name":"Nga-ye-chaung",
    "wof:placetype":"locality"
},
  "geometry": {"coordinates":[98.16792,13.66134],"type":"Point"}
}