{
  "type": "Feature",
  "properties": {
    "gn:admin1_code":"11.0",
    "gn:admin2_code":"MMR014D001",
    "gn:admin3_code":"MMR014006",
    "gn:asciiname":"Nyaunglebin",
    "gn:country_code":"MM",
    "gn:dem":1163,
    "gn:feature_class":"P",
    "gn:feature_code":"PPL",
    "gn:name":"Nyaunglebin",
    "gn:population":0,
    "gn:timezone":"Asia/Yangon",
    "iso:country":"MM",
    "name:ceb_x_preferred":[
        "Nyaunglebin"
    ],
    "name:mya_x_preferred":[
        "\u100a\u1031\u102c\u1004\u103a\u101c\u1031\u1038\u1015\u1004\u103a\u1019\u103c\u102d\u102f\u1037"
    ],
    "name:pol_x_preferred":[
        "Nyaunglebin"
    ],
    "name:rus_x_preferred":[
        "\u041d\u044c\u044f\u0443\u043d\u043b\u0435\u0431\u0438\u043d"
    ],
    "name:shn_x_preferred":[
        "\u107a\u103d\u1004\u103a\u1087\u101c\u1031\u1038\u1015\u102d\u107c\u103a\u1087\u104a \u101d\u1035\u1004\u103a\u1038"
    ],
    "name:swe_x_preferred":[
        "Nyaunglebin"
    ],
    "wof:name":"Nyaunglebin",
    "wof:placetype":"locality"
},
  "geometry": {"coordinates":[96.65693,20.99603],"type":"Point"}
}