{
  "type": "Feature",
  "properties": {
    "gn:admin1_code":"11.0",
    "gn:admin2_code":"MMR014D002",
    "gn:admin3_code":"MMR014017",
    "gn:asciiname":"Namkat",
    "gn:country_code":"MM",
    "gn:dem":702,
    "gn:feature_class":"P",
    "gn:feature_code":"PPL",
    "gn:name":"Namkat",
    "gn:population":0,
    "gn:timezone":"Asia/Yangon",
    "iso:country":"MM",
    "wof:name":"Namkat",
    "wof:placetype":"locality"
},
  "geometry": {"coordinates":[98.30582,21.89295],"type":"Point"}
}