{
  "type": "Feature",
  "properties": {
    "gn:admin1_code":"11.0",
    "gn:admin2_code":"MMR014D003",
    "gn:admin3_code":"MMR014019",
    "gn:asciiname":"Loisati",
    "gn:country_code":"MM",
    "gn:dem":1210,
    "gn:feature_class":"P",
    "gn:feature_code":"PPL",
    "gn:name":"Loisati",
    "gn:population":0,
    "gn:timezone":"Asia/Yangon",
    "iso:country":"MM",
    "wof:name":"Loisati",
    "wof:placetype":"locality"
},
  "geometry": {"coordinates":[97.77397999999999,20.5261],"type":"Point"}
}