{
  "type": "Feature",
  "properties": {
    "gn:admin1_code":"11.0",
    "gn:admin2_code":"MMR014D001",
    "gn:admin3_code":"MMR014001",
    "gn:asciiname":"Chitiwabwa",
    "gn:country_code":"MM",
    "gn:dem":888,
    "gn:feature_class":"P",
    "gn:feature_code":"PPL",
    "gn:name":"Chitiwabwa",
    "gn:population":0,
    "gn:timezone":"Asia/Yangon",
    "iso:country":"MM",
    "wof:name":"Chitiwabwa",
    "wof:placetype":"locality"
},
  "geometry": {"coordinates":[97.15218,20.21842],"type":"Point"}
}