{
  "type": "Feature",
  "properties": {
    "gn:admin1_code":"10.0",
    "gn:admin2_code":"MMR005D005",
    "gn:admin3_code":"MMR005028",
    "gn:asciiname":"Sizwe",
    "gn:country_code":"MM",
    "gn:dem":159,
    "gn:feature_class":"P",
    "gn:feature_code":"PPL",
    "gn:name":"Sizwe",
    "gn:population":0,
    "gn:timezone":"Asia/Yangon",
    "iso:country":"MM",
    "name:und_x_variant":[
        "Siswe",
        "Sizwe"
    ],
    "wof:name":"Sizwe",
    "wof:placetype":"locality"
},
  "geometry": {"coordinates":[94.40617,23.17306],"type":"Point"}
}