{
  "type": "Feature",
  "properties": {
    "gn:admin1_code":"10.0",
    "gn:admin2_code":"MMR005D002",
    "gn:admin3_code":"MMR005007",
    "gn:asciiname":"Kyauksegan",
    "gn:country_code":"MM",
    "gn:dem":151,
    "gn:feature_class":"P",
    "gn:feature_code":"PPL",
    "gn:name":"Kyauks\u00e8gan",
    "gn:population":0,
    "gn:timezone":"Asia/Yangon",
    "iso:country":"MM",
    "wof:name":"Kyauksegan",
    "wof:placetype":"locality"
},
  "geometry": {"coordinates":[95.64373999999999,22.93698],"type":"Point"}
}