{
  "type": "Feature",
  "properties": {
    "gn:admin1_code":"10.0",
    "gn:admin2_code":"MMR005D002",
    "gn:admin3_code":"MMR005009",
    "gn:asciiname":"Nabet-aing",
    "gn:country_code":"MM",
    "gn:dem":132,
    "gn:feature_class":"P",
    "gn:feature_code":"PPL",
    "gn:name":"Nabet-aing",
    "gn:population":0,
    "gn:timezone":"Asia/Yangon",
    "iso:country":"MM",
    "wof:name":"Nabet-aing",
    "wof:placetype":"locality"
},
  "geometry": {"coordinates":[95.30649,22.85513],"type":"Point"}
}