{
  "type": "Feature",
  "properties": {
    "gn:admin1_code":"11.0",
    "gn:admin2_code":"MMR014D001",
    "gn:admin3_code":"MMR014002",
    "gn:asciiname":"Linpoek Tek",
    "gn:country_code":"MM",
    "gn:dem":893,
    "gn:feature_class":"P",
    "gn:feature_code":"PPL",
    "gn:name":"Linp\u00f6k T\u00e8k",
    "gn:population":0,
    "gn:timezone":"Asia/Yangon",
    "iso:country":"MM",
    "wof:name":"Linpoek Tek",
    "wof:placetype":"locality"
},
  "geometry": {"coordinates":[97.00919,19.99508],"type":"Point"}
}