{
  "type": "Feature",
  "properties": {
    "gn:admin1_code":"12.0",
    "gn:admin2_code":"MMR006D003",
    "gn:admin3_code":"MMR006006",
    "gn:asciiname":"Singu",
    "gn:country_code":"MM",
    "gn:dem":22,
    "gn:feature_class":"P",
    "gn:feature_code":"PPL",
    "gn:name":"Singu",
    "gn:population":0,
    "gn:timezone":"Asia/Yangon",
    "iso:country":"MM",
    "name:mya_x_preferred":[
        "\u1005\u1009\u1037\u103a\u1000\u1030\u1038\u1019\u103c\u102d\u102f\u1037"
    ],
    "name:shn_x_preferred":[
        "\u1078\u102d\u107c\u103a\u1089\u1075\u1030\u1038\u104a \u101d\u1035\u1004\u103a\u1038"
    ],
    "name:und_x_variant":[
        "Kayin",
        "Singu"
    ],
    "wof:name":"Singu",
    "wof:placetype":"locality"
},
  "geometry": {"coordinates":[98.71764,11.81346],"type":"Point"}
}