{
  "type": "Feature",
  "properties": {
    "gn:admin1_code":"1.0",
    "gn:admin2_code":"MMR012D001",
    "gn:admin3_code":"MMR012002",
    "gn:asciiname":"Lukeywa",
    "gn:country_code":"MM",
    "gn:dem":62,
    "gn:feature_class":"P",
    "gn:feature_code":"PPL",
    "gn:name":"Lukeywa",
    "gn:population":0,
    "gn:timezone":"Asia/Yangon",
    "iso:country":"MM",
    "name:und_x_variant":[
        "Luke",
        "Lukeywa"
    ],
    "wof:name":"Lukeywa",
    "wof:placetype":"locality"
},
  "geometry": {"coordinates":[92.89631,20.54027],"type":"Point"}
}