{
  "type": "Feature",
  "properties": {
    "gn:admin1_code":"17.0",
    "gn:admin2_code":"MMR013D001",
    "gn:admin3_code":"MMR013005",
    "gn:asciiname":"Pienzu",
    "gn:country_code":"MM",
    "gn:dem":5,
    "gn:feature_class":"P",
    "gn:feature_code":"PPL",
    "gn:name":"Pienzu",
    "gn:population":0,
    "gn:timezone":"Asia/Yangon",
    "iso:country":"MM",
    "name:und_x_variant":[
        "Peinzu",
        "Pienzu"
    ],
    "wof:name":"Pienzu",
    "wof:placetype":"locality"
},
  "geometry": {"coordinates":[95.80847,17.2151],"type":"Point"}
}