{
  "type": "Feature",
  "properties": {
    "gn:admin1_code":"11.0",
    "gn:admin2_code":"MMR016D003",
    "gn:admin3_code":"MMR016011",
    "gn:asciiname":"Wan Hpya-longkwang",
    "gn:country_code":"MM",
    "gn:dem":1254,
    "gn:feature_class":"P",
    "gn:feature_code":"PPL",
    "gn:name":"W\u0101n Hpya-longkwang",
    "gn:population":0,
    "gn:timezone":"Asia/Yangon",
    "iso:country":"MM",
    "name:und_x_variant":[
        "Hpya-l\u014dngkwang",
        "W\u0101n Hpya-longkwang"
    ],
    "wof:name":"Wan Hpya-longkwang",
    "wof:placetype":"locality"
},
  "geometry": {"coordinates":[100.42358,21.362],"type":"Point"}
}