{
  "type": "Feature",
  "properties": {
    "gn:admin1_code":"4.0",
    "gn:admin2_code":"MMR001D003",
    "gn:admin3_code":"MMR001011",
    "gn:asciiname":"Tawbon",
    "gn:country_code":"MM",
    "gn:dem":110,
    "gn:feature_class":"P",
    "gn:feature_code":"PPL",
    "gn:name":"Tawb\u00f4n",
    "gn:population":0,
    "gn:timezone":"Asia/Yangon",
    "iso:country":"MM",
    "wof:name":"Tawbon",
    "wof:placetype":"locality"
},
  "geometry": {"coordinates":[96.7569,24.2579],"type":"Point"}
}