{
  "type": "Feature",
  "properties": {
    "gn:admin1_code":"11.0",
    "gn:admin2_code":"MMR016D001",
    "gn:admin3_code":"MMR016001",
    "gn:asciiname":"Wan Namhko",
    "gn:country_code":"MM",
    "gn:dem":1100,
    "gn:feature_class":"P",
    "gn:feature_code":"PPL",
    "gn:name":"W\u0101n Namhko",
    "gn:population":0,
    "gn:timezone":"Asia/Yangon",
    "iso:country":"MM",
    "name:und_x_variant":[
        "W\u0101n Kaw Namhko",
        "W\u0101n Namhko"
    ],
    "wof:name":"Wan Namhko",
    "wof:placetype":"locality"
},
  "geometry": {"coordinates":[99.81253,21.39384],"type":"Point"}
}