{
  "type": "Feature",
  "properties": {
    "gn:admin1_code":"11.0",
    "gn:admin2_code":"MMR016D001",
    "gn:admin3_code":"MMR016001",
    "gn:asciiname":"Wan Hpaya-hke",
    "gn:country_code":"MM",
    "gn:dem":1713,
    "gn:feature_class":"P",
    "gn:feature_code":"PPL",
    "gn:name":"W\u0101n Hpaya-hk\u00e8",
    "gn:population":0,
    "gn:timezone":"Asia/Yangon",
    "iso:country":"MM",
    "name:und_x_variant":[
        "W\u0101n Hpaya-hk\u00e8-li-hsaw",
        "W\u0101n Hpaya-hk\u00e8"
    ],
    "wof:name":"Wan Hpaya-hke",
    "wof:placetype":"locality"
},
  "geometry": {"coordinates":[99.86557000000001,21.22273],"type":"Point"}
}