{
  "type": "Feature",
  "properties": {
    "gn:admin1_code":"13.0",
    "gn:admin2_code":"MMR011D002",
    "gn:admin3_code":"MMR011009",
    "gn:asciiname":"Thongwa",
    "gn:country_code":"MM",
    "gn:dem":44,
    "gn:feature_class":"P",
    "gn:feature_code":"PPL",
    "gn:name":"Thongwa",
    "gn:population":0,
    "gn:timezone":"Asia/Yangon",
    "iso:country":"MM",
    "name:ara_x_preferred":[
        "\u062b\u0648\u0646\u063a\u0648\u0627"
    ],
    "name:ben_x_preferred":[
        "\u09a5\u09cb\u0999\u09cd\u0997\u09cb\u09df\u09be"
    ],
    "name:deu_x_preferred":[
        "Thongwa"
    ],
    "name:ell_x_preferred":[
        "\u0398\u03cc\u03bd\u03b3\u03ba\u03bf\u03c5\u03b1"
    ],
    "name:fas_x_preferred":[
        "\u062a\u0648\u0646\u06af\u0648\u0627"
    ],
    "name:fra_x_preferred":[
        "Thongwa"
    ],
    "name:heb_x_preferred":[
        "\u05d8'\u05d5\u05e0\u05d2\u05d5\u05d5\u05d4"
    ],
    "name:hin_x_preferred":[
        "\u0925\u094b\u0902\u0917\u0935\u093e"
    ],
    "name:hun_x_preferred":[
        "Thongwa"
    ],
    "name:ind_x_preferred":[
        "Thongwa"
    ],
    "name:ita_x_preferred":[
        "Thongwa"
    ],
    "name:kor_x_preferred":[
        "\ud1b5\uc640"
    ],
    "name:nld_x_preferred":[
        "Thongwa"
    ],
    "name:pol_x_preferred":[
        "Thongwa"
    ],
    "name:por_x_preferred":[
        "Thongwa"
    ],
    "name:rus_x_preferred":[
        "\u0422\u043e\u043d\u0433\u0432\u0430"
    ],
    "name:spa_x_preferred":[
        "Thongwa"
    ],
    "name:swe_x_preferred":[
        "Thongwa"
    ],
    "name:tur_x_preferred":[
        "Thongwa"
    ],
    "name:ukr_x_preferred":[
        "\u0422\u0445\u043e\u043d\u0433\u0432\u0430"
    ],
    "name:urd_x_preferred":[
        "\u062a\u06be\u0648\u0646\u06af\u0648\u0627"
    ],
    "name:vie_x_preferred":[
        "Thongwa"
    ],
    "wof:name":"Thongwa",
    "wof:placetype":"locality"
},
  "geometry": {"coordinates":[96.92715,17.54122],"type":"Point"}
}