{
  "type": "Feature",
  "properties": {
    "gn:admin1_code":"16.0",
    "gn:admin2_code":"MMR008D002",
    "gn:admin3_code":"MMR008012",
    "gn:asciiname":"Gyogyagan",
    "gn:country_code":"MM",
    "gn:dem":28,
    "gn:feature_class":"P",
    "gn:feature_code":"PPL",
    "gn:name":"Gyogyagan",
    "gn:population":0,
    "gn:timezone":"Asia/Yangon",
    "iso:country":"MM",
    "name:und_x_variant":[
        "Gyogyagon",
        "Gyogyagan"
    ],
    "wof:name":"Gyogyagan",
    "wof:placetype":"locality"
},
  "geometry": {"coordinates":[95.51953,18.33297],"type":"Point"}
}