{
  "type": "Feature",
  "properties": {
    "gn:admin1_code":"6.0",
    "gn:admin2_code":"MMR002D002",
    "gn:admin3_code":"MMR002006",
    "gn:asciiname":"Nammehek",
    "gn:country_code":"MM",
    "gn:dem":113,
    "gn:feature_class":"P",
    "gn:feature_code":"PPL",
    "gn:name":"Nammehek",
    "gn:population":0,
    "gn:timezone":"Asia/Yangon",
    "iso:country":"MM",
    "wof:name":"Nammehek",
    "wof:placetype":"locality"
},
  "geometry": {"coordinates":[97.31480999999999,18.83077],"type":"Point"}
}