{
  "type": "Feature",
  "properties": {
    "gn:admin1_code":"4.0",
    "gn:admin2_code":"MMR001D004",
    "gn:admin3_code":"MMR001014",
    "gn:asciiname":"'Nhkang Waga",
    "gn:country_code":"MM",
    "gn:dem":799,
    "gn:feature_class":"P",
    "gn:feature_code":"PPL",
    "gn:name":"\u2019Nhkang Waga",
    "gn:population":0,
    "gn:timezone":"Asia/Yangon",
    "iso:country":"MM",
    "wof:name":"'Nhkang Waga",
    "wof:placetype":"locality"
},
  "geometry": {"coordinates":[97.57708,26.73732],"type":"Point"}
}