{
  "type": "Feature",
  "properties": {
    "gn:admin1_code":"6.0",
    "gn:admin2_code":"MMR002D001",
    "gn:admin3_code":"MMR002001",
    "gn:asciiname":"Daw Le-hkra",
    "gn:country_code":"MM",
    "gn:dem":880,
    "gn:feature_class":"P",
    "gn:feature_code":"PPL",
    "gn:name":"Daw L\u00e8-hkra",
    "gn:population":0,
    "gn:timezone":"Asia/Yangon",
    "iso:country":"MM",
    "wof:name":"Daw Le-hkra",
    "wof:placetype":"locality"
},
  "geometry": {"coordinates":[97.13191999999999,19.74318],"type":"Point"}
}