{
  "type": "Feature",
  "properties": {
    "gn:admin1_code":"16.0",
    "gn:admin2_code":"MMR007D001",
    "gn:admin3_code":"MMR007006",
    "gn:asciiname":"Minlangu-shanzu",
    "gn:country_code":"MM",
    "gn:dem":44,
    "gn:feature_class":"P",
    "gn:feature_code":"PPL",
    "gn:name":"Minlangu-shanzu",
    "gn:population":0,
    "gn:timezone":"Asia/Yangon",
    "iso:country":"MM",
    "wof:name":"Minlangu-shanzu",
    "wof:placetype":"locality"
},
  "geometry": {"coordinates":[96.43333,18.36667000000001],"type":"Point"}
}