{
  "type": "Feature",
  "properties": {
    "gn:admin1_code":"2.0",
    "gn:admin2_code":"MMR004D001",
    "gn:admin3_code":"MMR004005",
    "gn:asciiname":"Talzang",
    "gn:country_code":"MM",
    "gn:dem":1318,
    "gn:feature_class":"P",
    "gn:feature_code":"PPL",
    "gn:name":"Talzang",
    "gn:population":0,
    "gn:timezone":"Asia/Yangon",
    "iso:country":"MM",
    "wof:name":"Talzang",
    "wof:placetype":"locality"
},
  "geometry": {"coordinates":[93.78333000000001,23.76667],"type":"Point"}
}