{
  "type": "Feature",
  "properties": {
    "gn:admin1_code":"11.0",
    "gn:admin2_code":"MMR015D003",
    "gn:admin3_code":"MMR015012",
    "gn:asciiname":"Mankang",
    "gn:country_code":"MM",
    "gn:dem":1452,
    "gn:feature_class":"P",
    "gn:feature_code":"PPL",
    "gn:name":"M\u00e0nk\u00e0ng",
    "gn:population":0,
    "gn:timezone":"Asia/Yangon",
    "iso:country":"MM",
    "wof:name":"Mankang",
    "wof:placetype":"locality"
},
  "geometry": {"coordinates":[96.84524999999999,22.90278],"type":"Point"}
}