{
  "type": "Feature",
  "properties": {
    "gn:admin1_code":"3.0",
    "gn:admin2_code":"MMR017D001",
    "gn:admin3_code":"MMR017005",
    "gn:asciiname":"Phalangon",
    "gn:country_code":"MM",
    "gn:dem":15,
    "gn:feature_class":"P",
    "gn:feature_code":"PPL",
    "gn:name":"Phalangon",
    "gn:population":0,
    "gn:timezone":"Asia/Yangon",
    "iso:country":"MM",
    "name:mya_x_preferred":[
        "\u1016\u101c\u1036\u1002\u102f\u100f\u103a\u101b\u103d\u102c"
    ],
    "wof:name":"Phalangon",
    "wof:placetype":"locality"
},
  "geometry": {"coordinates":[95.23609,17.43202],"type":"Point"}
}