{
  "type": "Feature",
  "properties": {
    "gn:admin1_code":"11.0",
    "gn:admin2_code":"MMR015D003",
    "gn:admin3_code":"MMR015019",
    "gn:asciiname":"Man U-hpe",
    "gn:country_code":"MM",
    "gn:dem":802,
    "gn:feature_class":"P",
    "gn:feature_code":"PPL",
    "gn:name":"M\u0101n U-hpe",
    "gn:population":0,
    "gn:timezone":"Asia/Yangon",
    "iso:country":"MM",
    "wof:name":"Man U-hpe",
    "wof:placetype":"locality"
},
  "geometry": {"coordinates":[97.64196,23.28312],"type":"Point"}
}