{
  "type": "Feature",
  "properties": {
    "gn:admin1_code":"8.0",
    "gn:admin2_code":"MMR010D001",
    "gn:admin3_code":"MMR010007",
    "gn:asciiname":"Bugon",
    "gn:country_code":"MM",
    "gn:dem":80,
    "gn:feature_class":"P",
    "gn:feature_code":"PPL",
    "gn:name":"Bugon",
    "gn:population":0,
    "gn:timezone":"Asia/Yangon",
    "iso:country":"MM",
    "name:und_x_variant":[
        "Kondan",
        "Bugon"
    ],
    "wof:name":"Bugon",
    "wof:placetype":"locality"
},
  "geometry": {"coordinates":[96.12636000000001,21.99196],"type":"Point"}
}