{
  "type": "Feature",
  "properties": {
    "gn:admin1_code":"10.0",
    "gn:admin2_code":"MMR005D009",
    "gn:admin3_code":"MMR005017",
    "gn:asciiname":"Taon",
    "gn:country_code":"MM",
    "gn:dem":97,
    "gn:feature_class":"P",
    "gn:feature_code":"PPL",
    "gn:name":"Ta\u00f4n",
    "gn:population":0,
    "gn:timezone":"Asia/Yangon",
    "iso:country":"MM",
    "wof:name":"Taon",
    "wof:placetype":"locality"
},
  "geometry": {"coordinates":[94.76017,22.65754],"type":"Point"}
}