{
  "type": "Feature",
  "properties": {
    "gn:admin1_code":"6.0",
    "gn:admin2_code":"MMR002D002",
    "gn:admin3_code":"MMR002007",
    "gn:asciiname":"Pusung",
    "gn:country_code":"MM",
    "gn:dem":268,
    "gn:feature_class":"P",
    "gn:feature_code":"PPL",
    "gn:name":"Pusung",
    "gn:population":0,
    "gn:timezone":"Asia/Yangon",
    "iso:country":"MM",
    "wof:name":"Pusung",
    "wof:placetype":"locality"
},
  "geometry": {"coordinates":[97.48908,18.66314],"type":"Point"}
}