{
  "type": "Feature",
  "properties": {
    "gn:admin1_code":"15.0",
    "gn:admin2_code":"MMR009D004",
    "gn:admin3_code":"MMR009020",
    "gn:asciiname":"Konbalu",
    "gn:country_code":"MM",
    "gn:dem":213,
    "gn:feature_class":"P",
    "gn:feature_code":"PPL",
    "gn:name":"K\u00f4nbalu",
    "gn:population":0,
    "gn:timezone":"Asia/Yangon",
    "iso:country":"MM",
    "wof:name":"Konbalu",
    "wof:placetype":"locality"
},
  "geometry": {"coordinates":[94.88278,21.71192000000001],"type":"Point"}
}