{
  "type": "Feature",
  "properties": {
    "gn:admin1_code":"11.0",
    "gn:admin2_code":"MMR016D001",
    "gn:admin3_code":"MMR016003",
    "gn:asciiname":"Wan Hu-noe",
    "gn:country_code":"MM",
    "gn:dem":960,
    "gn:feature_class":"P",
    "gn:feature_code":"PPL",
    "gn:name":"W\u0101n Hu-n\u00f6",
    "gn:population":0,
    "gn:timezone":"Asia/Yangon",
    "iso:country":"MM",
    "wof:name":"Wan Hu-noe",
    "wof:placetype":"locality"
},
  "geometry": {"coordinates":[99.72058,21.87881],"type":"Point"}
}