{
  "type": "Feature",
  "properties": {
    "gn:admin1_code":"11.0",
    "gn:admin2_code":"MMR014D003",
    "gn:admin3_code":"MMR014019",
    "gn:asciiname":"Keng Tawng",
    "gn:country_code":"MM",
    "gn:dem":655,
    "gn:feature_class":"P",
    "gn:feature_code":"PPL",
    "gn:name":"K\u0113ng Tawng",
    "gn:population":0,
    "gn:timezone":"Asia/Yangon",
    "iso:country":"MM",
    "name:und_x_variant":[
        "K\u0113ng Tawng"
    ],
    "wof:name":"Keng Tawng",
    "wof:placetype":"locality"
},
  "geometry": {"coordinates":[98.29575,20.75852],"type":"Point"}
}