{
  "type": "Feature",
  "properties": {
    "gn:admin1_code":"15.0",
    "gn:admin2_code":"MMR009D004",
    "gn:admin3_code":"MMR009018",
    "gn:asciiname":"Cheik",
    "gn:country_code":"MM",
    "gn:dem":76,
    "gn:feature_class":"P",
    "gn:feature_code":"PPL",
    "gn:name":"Cheik",
    "gn:population":0,
    "gn:timezone":"Asia/Yangon",
    "iso:country":"MM",
    "name:und_x_variant":[
        "Kyeik",
        "Cheik"
    ],
    "wof:name":"Cheik",
    "wof:placetype":"locality"
},
  "geometry": {"coordinates":[94.77079999999999,21.00136],"type":"Point"}
}