{
  "type": "Feature",
  "properties": {
    "gn:admin1_code":"15.0",
    "gn:admin2_code":"MMR009D004",
    "gn:admin3_code":"MMR009022",
    "gn:asciiname":"Thamingan",
    "gn:country_code":"MM",
    "gn:dem":216,
    "gn:feature_class":"P",
    "gn:feature_code":"PPL",
    "gn:name":"Thamingan",
    "gn:population":0,
    "gn:timezone":"Asia/Yangon",
    "iso:country":"MM",
    "wof:name":"Thamingan",
    "wof:placetype":"locality"
},
  "geometry": {"coordinates":[94.42648,20.94486],"type":"Point"}
}