{
  "type": "Feature",
  "properties": {
    "gn:admin1_code":"11.0",
    "gn:admin2_code":"MMR015D001",
    "gn:admin3_code":"MMR015003",
    "gn:asciiname":"Kong-nio",
    "gn:country_code":"MM",
    "gn:dem":602,
    "gn:feature_class":"P",
    "gn:feature_code":"PPL",
    "gn:name":"Kong-nio",
    "gn:population":0,
    "gn:timezone":"Asia/Yangon",
    "iso:country":"MM",
    "wof:name":"Kong-nio",
    "wof:placetype":"locality"
},
  "geometry": {"coordinates":[97.88957000000001,22.69517],"type":"Point"}
}