{
  "type": "Feature",
  "properties": {
    "gn:admin1_code":"11.0",
    "gn:admin2_code":"MMR014D002",
    "gn:admin3_code":"MMR014012",
    "gn:asciiname":"Hai-hseng",
    "gn:country_code":"MM",
    "gn:dem":960,
    "gn:feature_class":"P",
    "gn:feature_code":"PPL",
    "gn:name":"Hai-hseng",
    "gn:population":0,
    "gn:timezone":"Asia/Yangon",
    "iso:country":"MM",
    "wof:name":"Hai-hseng",
    "wof:placetype":"locality"
},
  "geometry": {"coordinates":[97.77227999999999,21.23902],"type":"Point"}
}