{
  "type": "Feature",
  "properties": {
    "gn:admin1_code":"4.0",
    "gn:asciiname":"Mokin",
    "gn:country_code":"MM",
    "gn:dem":126,
    "gn:feature_class":"P",
    "gn:feature_code":"PPL",
    "gn:name":"Mokin",
    "gn:population":0,
    "gn:timezone":"Asia/Yangon",
    "iso:country":"MM",
    "wof:name":"Mokin",
    "wof:placetype":"locality"
},
  "geometry": {"coordinates":[96.69219,24.10399],"type":"Point"}
}