{
  "type": "Feature",
  "properties": {
    "gn:admin1_code":"15.0",
    "gn:admin2_code":"MMR009D001",
    "gn:admin3_code":"MMR009001",
    "gn:asciiname":"Thayetlebin",
    "gn:country_code":"MM",
    "gn:dem":61,
    "gn:feature_class":"P",
    "gn:feature_code":"PPL",
    "gn:name":"Thayetlebin",
    "gn:population":0,
    "gn:timezone":"Asia/Yangon",
    "iso:country":"MM",
    "wof:name":"Thayetlebin",
    "wof:placetype":"locality"
},
  "geometry": {"coordinates":[95.11064,20.09527000000001],"type":"Point"}
}