{
  "type": "Feature",
  "properties": {
    "gn:admin1_code":"15.0",
    "gn:admin2_code":"MMR009D001",
    "gn:admin3_code":"MMR009003",
    "gn:asciiname":"Taungtha",
    "gn:country_code":"MM",
    "gn:dem":165,
    "gn:feature_class":"P",
    "gn:feature_code":"PPL",
    "gn:name":"Taungtha",
    "gn:population":0,
    "gn:timezone":"Asia/Yangon",
    "iso:country":"MM",
    "wof:name":"Taungtha",
    "wof:placetype":"locality"
},
  "geometry": {"coordinates":[94.83619,20.74229],"type":"Point"}
}