{
  "type": "Feature",
  "properties": {
    "gn:admin1_code":"11.0",
    "gn:admin2_code":"MMR016D001",
    "gn:admin3_code":"MMR016001",
    "gn:asciiname":"Wan Hsenglao",
    "gn:country_code":"MM",
    "gn:dem":1351,
    "gn:feature_class":"P",
    "gn:feature_code":"PPL",
    "gn:name":"W\u0101n Hsenglao",
    "gn:population":0,
    "gn:timezone":"Asia/Yangon",
    "iso:country":"MM",
    "name:und_x_variant":[
        "Wan Hseng Lan",
        "W\u0101n Hsenglao"
    ],
    "wof:name":"Wan Hsenglao",
    "wof:placetype":"locality"
},
  "geometry": {"coordinates":[99.49632,20.98771],"type":"Point"}
}