{
  "type": "Feature",
  "properties": {
    "gn:admin1_code":"11.0",
    "gn:admin2_code":"MMR015D006",
    "gn:admin3_code":"MMR015008",
    "gn:asciiname":"K'rangk'lang",
    "gn:country_code":"MM",
    "gn:dem":1058,
    "gn:feature_class":"P",
    "gn:feature_code":"PPL",
    "gn:name":"K\u2019rangk\u2019lang",
    "gn:population":0,
    "gn:timezone":"Asia/Yangon",
    "iso:country":"MM",
    "wof:name":"K'rangk'lang",
    "wof:placetype":"locality"
},
  "geometry": {"coordinates":[99.13333,23.06667],"type":"Point"}
}