{
  "type": "Feature",
  "properties": {
    "gn:admin1_code":"18.0",
    "gn:admin2_code":"MMR018D001",
    "gn:admin3_code":"MMR018003",
    "gn:asciiname":"Thangedaung",
    "gn:country_code":"MM",
    "gn:dem":193,
    "gn:feature_class":"P",
    "gn:feature_code":"PPL",
    "gn:name":"Thangedaung",
    "gn:population":0,
    "gn:timezone":"Asia/Yangon",
    "iso:country":"MM",
    "wof:name":"Thangedaung",
    "wof:placetype":"locality"
},
  "geometry": {"coordinates":[96.14686,20.04267],"type":"Point"}
}