{
  "type": "Feature",
  "properties": {
    "gn:admin1_code":"10.0",
    "gn:admin2_code":"MMR005D002",
    "gn:admin3_code":"MMR005006",
    "gn:asciiname":"Wetlet",
    "gn:country_code":"MM",
    "gn:dem":92,
    "gn:feature_class":"P",
    "gn:feature_code":"PPL",
    "gn:name":"Wetlet",
    "gn:population":0,
    "gn:timezone":"Asia/Yangon",
    "iso:country":"MM",
    "name:mya_x_preferred":[
        "\u101d\u1000\u103a\u101c\u1000\u103a\u1019\u103c\u102d\u102f\u1037"
    ],
    "wof:name":"Wetlet",
    "wof:placetype":"locality"
},
  "geometry": {"coordinates":[95.78852000000001,22.36826],"type":"Point"}
}