{
  "type": "Feature",
  "properties": {
    "gn:admin1_code":"11.0",
    "gn:admin2_code":"MMR016D001",
    "gn:admin3_code":"MMR016002",
    "gn:asciiname":"Wan Hpya-sai-loi-mi",
    "gn:country_code":"MM",
    "gn:dem":1679,
    "gn:feature_class":"P",
    "gn:feature_code":"PPL",
    "gn:name":"W\u0101n Hpya-sai-loi-mi",
    "gn:population":0,
    "gn:timezone":"Asia/Yangon",
    "iso:country":"MM",
    "wof:name":"Wan Hpya-sai-loi-mi",
    "wof:placetype":"locality"
},
  "geometry": {"coordinates":[99.60234,21.60957],"type":"Point"}
}