{
  "type": "Feature",
  "properties": {
    "gn:admin1_code":"10.0",
    "gn:admin2_code":"MMR005D005",
    "gn:admin3_code":"MMR005028",
    "gn:asciiname":"Thetkegyin",
    "gn:country_code":"MM",
    "gn:dem":325,
    "gn:feature_class":"P",
    "gn:feature_code":"PPL",
    "gn:name":"Thetkegyin",
    "gn:population":0,
    "gn:timezone":"Asia/Yangon",
    "iso:country":"MM",
    "wof:name":"Thetkegyin",
    "wof:placetype":"locality"
},
  "geometry": {"coordinates":[94.60997,23.20328],"type":"Point"}
}