{
  "type": "Feature",
  "properties": {
    "gn:admin1_code":"15.0",
    "gn:admin2_code":"MMR009D001",
    "gn:admin3_code":"MMR009006",
    "gn:asciiname":"Sinthegon",
    "gn:country_code":"MM",
    "gn:dem":252,
    "gn:feature_class":"P",
    "gn:feature_code":"PPL",
    "gn:name":"Sinthegon",
    "gn:population":0,
    "gn:timezone":"Asia/Yangon",
    "iso:country":"MM",
    "wof:name":"Sinthegon",
    "wof:placetype":"locality"
},
  "geometry": {"coordinates":[95.29968,20.63837],"type":"Point"}
}