{
  "type": "Feature",
  "properties": {
    "gn:admin1_code":"11.0",
    "gn:admin2_code":"MMR015D001",
    "gn:admin3_code":"MMR015020",
    "gn:asciiname":"Man Pangsa-kang",
    "gn:country_code":"MM",
    "gn:dem":1085,
    "gn:feature_class":"P",
    "gn:feature_code":"PPL",
    "gn:name":"M\u0101n Pangsa-k\u0101ng",
    "gn:population":0,
    "gn:timezone":"Asia/Yangon",
    "iso:country":"MM",
    "wof:name":"Man Pangsa-kang",
    "wof:placetype":"locality"
},
  "geometry": {"coordinates":[98.62170999999999,23.36582000000001],"type":"Point"}
}