{
  "type": "Feature",
  "properties": {
    "gn:admin1_code":"13.0",
    "gn:admin2_code":"MMR011D002",
    "gn:admin3_code":"MMR011010",
    "gn:asciiname":"Pete",
    "gn:country_code":"MM",
    "gn:dem":89,
    "gn:feature_class":"P",
    "gn:feature_code":"PPL",
    "gn:name":"P\u0113te",
    "gn:population":0,
    "gn:timezone":"Asia/Yangon",
    "iso:country":"MM",
    "wof:name":"Pete",
    "wof:placetype":"locality"
},
  "geometry": {"coordinates":[97.22467,17.48925],"type":"Point"}
}