{
  "type": "Feature",
  "properties": {
    "gn:admin1_code":"15.0",
    "gn:admin2_code":"MMR009D004",
    "gn:admin3_code":"MMR009019",
    "gn:asciiname":"Kwehmyok",
    "gn:country_code":"MM",
    "gn:dem":125,
    "gn:feature_class":"P",
    "gn:feature_code":"PPL",
    "gn:name":"Kwehmyok",
    "gn:population":0,
    "gn:timezone":"Asia/Yangon",
    "iso:country":"MM",
    "wof:name":"Kwehmyok",
    "wof:placetype":"locality"
},
  "geometry": {"coordinates":[95.15181,21.601],"type":"Point"}
}