{
  "type": "Feature",
  "properties": {
    "gn:admin1_code":"11.0",
    "gn:admin2_code":"MMR015D003",
    "gn:admin3_code":"MMR015013",
    "gn:asciiname":"Na-kyaung-kham",
    "gn:country_code":"MM",
    "gn:dem":682,
    "gn:feature_class":"P",
    "gn:feature_code":"PPL",
    "gn:name":"Na-kyaung-kham",
    "gn:population":0,
    "gn:timezone":"Asia/Yangon",
    "iso:country":"MM",
    "name:und_x_variant":[
        "Na-kyong-kham",
        "Na-kyaung-kham"
    ],
    "wof:name":"Na-kyaung-kham",
    "wof:placetype":"locality"
},
  "geometry": {"coordinates":[96.69450999999999,22.23426],"type":"Point"}
}