{
  "type": "Feature",
  "properties": {
    "gn:admin1_code":"10.0",
    "gn:admin2_code":"MMR005D002",
    "gn:admin3_code":"MMR005010",
    "gn:asciiname":"Gaungzu",
    "gn:country_code":"MM",
    "gn:dem":112,
    "gn:feature_class":"P",
    "gn:feature_code":"PPL",
    "gn:name":"Gaungzu",
    "gn:population":0,
    "gn:timezone":"Asia/Yangon",
    "iso:country":"MM",
    "name:und_x_variant":[
        "Gaungsu",
        "Gaungzu"
    ],
    "wof:name":"Gaungzu",
    "wof:placetype":"locality"
},
  "geometry": {"coordinates":[95.28654,22.56101],"type":"Point"}
}