{
  "type": "Feature",
  "properties": {
    "gn:admin1_code":"11.0",
    "gn:admin2_code":"MMR016D001",
    "gn:admin3_code":"MMR016001",
    "gn:asciiname":"Wan Hwe-kut",
    "gn:country_code":"MM",
    "gn:dem":1084,
    "gn:feature_class":"P",
    "gn:feature_code":"PPL",
    "gn:name":"W\u0101n Hw\u00e8-k\u016bt",
    "gn:population":0,
    "gn:timezone":"Asia/Yangon",
    "iso:country":"MM",
    "name:und_x_variant":[
        "W\u0101n Kaw Hw\u00e8-K\u016bt",
        "W\u0101n Hw\u00e8-k\u016bt"
    ],
    "wof:name":"Wan Hwe-kut",
    "wof:placetype":"locality"
},
  "geometry": {"coordinates":[99.76338,21.07203],"type":"Point"}
}