{
  "type": "Feature",
  "properties": {
    "gn:admin1_code":"11.0",
    "gn:admin2_code":"MMR014D003",
    "gn:admin3_code":"MMR014019",
    "gn:asciiname":"Pang Keng",
    "gn:country_code":"MM",
    "gn:dem":638,
    "gn:feature_class":"P",
    "gn:feature_code":"PPL",
    "gn:name":"Pang Keng",
    "gn:population":0,
    "gn:timezone":"Asia/Yangon",
    "iso:country":"MM",
    "wof:name":"Pang Keng",
    "wof:placetype":"locality"
},
  "geometry": {"coordinates":[98.49317000000001,20.64792000000001],"type":"Point"}
}