{
  "type": "Feature",
  "properties": {
    "gn:admin1_code":"8.0",
    "gn:admin2_code":"MMR010D004",
    "gn:admin3_code":"MMR010019",
    "gn:asciiname":"Mannaingtha",
    "gn:country_code":"MM",
    "gn:dem":213,
    "gn:feature_class":"P",
    "gn:feature_code":"PPL",
    "gn:name":"Mannaingtha",
    "gn:population":0,
    "gn:timezone":"Asia/Yangon",
    "iso:country":"MM",
    "name:und_x_variant":[
        "Mahnaingtha",
        "Mannaingtha"
    ],
    "wof:name":"Mannaingtha",
    "wof:placetype":"locality"
},
  "geometry": {"coordinates":[95.71939999999999,21.33209],"type":"Point"}
}