{
  "type": "Feature",
  "properties": {
    "gn:admin1_code":"2.0",
    "gn:admin2_code":"MMR004D002",
    "gn:admin3_code":"MMR004009",
    "gn:asciiname":"Wama",
    "gn:country_code":"MM",
    "gn:dem":14,
    "gn:feature_class":"P",
    "gn:feature_code":"PPL",
    "gn:name":"Wama",
    "gn:population":0,
    "gn:timezone":"Asia/Yangon",
    "iso:country":"MM",
    "name:ceb_x_preferred":[
        "Wama"
    ],
    "name:deu_x_preferred":[
        "Wama"
    ],
    "name:swe_x_preferred":[
        "Wama"
    ],
    "wof:name":"Wama",
    "wof:placetype":"locality"
},
  "geometry": {"coordinates":[92.98324,21.13513],"type":"Point"}
}