{
  "type": "Feature",
  "properties": {
    "gn:admin1_code":"11.0",
    "gn:admin2_code":"MMR015D008",
    "gn:admin3_code":"MMR015018",
    "gn:asciiname":"Sani",
    "gn:country_code":"MM",
    "gn:dem":419,
    "gn:feature_class":"P",
    "gn:feature_code":"PPL",
    "gn:name":"Sani",
    "gn:population":0,
    "gn:timezone":"Asia/Yangon",
    "iso:country":"MM",
    "name:ceb_x_preferred":[
        "Sani"
    ],
    "name:deu_x_preferred":[
        "Sani"
    ],
    "name:fra_x_preferred":[
        "Sani"
    ],
    "name:ind_x_preferred":[
        "Sani"
    ],
    "name:ita_x_preferred":[
        "Sani"
    ],
    "name:swe_x_preferred":[
        "Sani"
    ],
    "wof:name":"Sani",
    "wof:placetype":"locality"
},
  "geometry": {"coordinates":[96.83404,23.84953],"type":"Point"}
}