{
  "type": "Feature",
  "properties": {
    "gn:admin1_code":"16.0",
    "gn:admin2_code":"MMR007D002",
    "gn:admin3_code":"MMR007012",
    "gn:asciiname":"Kywemagu",
    "gn:country_code":"MM",
    "gn:dem":59,
    "gn:feature_class":"P",
    "gn:feature_code":"PPL",
    "gn:name":"Kyw\u00e8magu",
    "gn:population":0,
    "gn:timezone":"Asia/Yangon",
    "iso:country":"MM",
    "wof:name":"Kywemagu",
    "wof:placetype":"locality"
},
  "geometry": {"coordinates":[96.39232,18.47537],"type":"Point"}
}