{
  "type": "Feature",
  "properties": {
    "gn:admin1_code":"16.0",
    "gn:admin2_code":"MMR007D001",
    "gn:admin3_code":"MMR007005",
    "gn:asciiname":"Pazunmyaung",
    "gn:country_code":"MM",
    "gn:dem":21,
    "gn:feature_class":"P",
    "gn:feature_code":"PPL",
    "gn:name":"Pazunmyaung",
    "gn:population":0,
    "gn:timezone":"Asia/Yangon",
    "iso:country":"MM",
    "name:und_x_variant":[
        "Paxunmyaung",
        "Pazunmyaung"
    ],
    "wof:name":"Pazunmyaung",
    "wof:placetype":"locality"
},
  "geometry": {"coordinates":[96.77694,17.98004],"type":"Point"}
}