{
  "type": "Feature",
  "properties": {
    "gn:admin1_code":"15.0",
    "gn:admin2_code":"MMR009D003",
    "gn:admin3_code":"MMR009014",
    "gn:asciiname":"Uyinbu",
    "gn:country_code":"MM",
    "gn:dem":99,
    "gn:feature_class":"P",
    "gn:feature_code":"PPL",
    "gn:name":"Uyinbu",
    "gn:population":0,
    "gn:timezone":"Asia/Yangon",
    "iso:country":"MM",
    "wof:name":"Uyinbu",
    "wof:placetype":"locality"
},
  "geometry": {"coordinates":[94.74615,19.39427],"type":"Point"}
}