{
  "type": "Feature",
  "properties": {
    "gn:admin1_code":"11.0",
    "gn:admin2_code":"MMR016D001",
    "gn:admin3_code":"MMR016001",
    "gn:asciiname":"Wan Nawnghong",
    "gn:country_code":"MM",
    "gn:dem":782,
    "gn:feature_class":"P",
    "gn:feature_code":"PPL",
    "gn:name":"W\u0101n Nawngh\u014dng",
    "gn:population":0,
    "gn:timezone":"Asia/Yangon",
    "iso:country":"MM",
    "wof:name":"Wan Nawnghong",
    "wof:placetype":"locality"
},
  "geometry": {"coordinates":[99.64421,21.35004],"type":"Point"}
}