{
  "type": "Feature",
  "properties": {
    "gn:admin1_code":"11.0",
    "gn:admin2_code":"MMR016D001",
    "gn:admin3_code":"MMR016007",
    "gn:asciiname":"Wan Hwe-wai",
    "gn:country_code":"MM",
    "gn:dem":484,
    "gn:elevation":"463.0",
    "gn:feature_class":"P",
    "gn:feature_code":"PPL",
    "gn:name":"W\u0101n Hw\u00e8-wai",
    "gn:population":0,
    "gn:timezone":"Asia/Yangon",
    "iso:country":"MM",
    "wof:name":"Wan Hwe-wai",
    "wof:placetype":"locality"
},
  "geometry": {"coordinates":[98.58754999999999,20.88929],"type":"Point"}
}