{
  "type": "Feature",
  "properties": {
    "gn:admin1_code":"17.0",
    "gn:admin2_code":"MMR013D001",
    "gn:admin3_code":"MMR013002",
    "gn:asciiname":"Hteinzun",
    "gn:country_code":"MM",
    "gn:dem":17,
    "gn:feature_class":"P",
    "gn:feature_code":"PPL",
    "gn:name":"Hteinzun",
    "gn:population":0,
    "gn:timezone":"Asia/Yangon",
    "iso:country":"MM",
    "wof:name":"Hteinzun",
    "wof:placetype":"locality"
},
  "geometry": {"coordinates":[96.12708000000001,17.0731],"type":"Point"}
}