{
  "type": "Feature",
  "properties": {
    "gn:admin1_code":"4.0",
    "gn:admin2_code":"MMR001D004",
    "gn:admin3_code":"MMR001016",
    "gn:asciiname":"Nbyen Ga",
    "gn:country_code":"MM",
    "gn:dem":490,
    "gn:feature_class":"P",
    "gn:feature_code":"PPL",
    "gn:name":"Nbyen Ga",
    "gn:population":0,
    "gn:timezone":"Asia/Yangon",
    "iso:country":"MM",
    "name:und_x_variant":[
        "Byan Ga"
    ],
    "wof:name":"Nbyen Ga",
    "wof:placetype":"locality"
},
  "geometry": {"coordinates":[97.63427,27.27246],"type":"Point"}
}