{
  "type": "Feature",
  "properties": {
    "gn:admin1_code":"5.0",
    "gn:admin2_code":"MMR003D001",
    "gn:admin3_code":"MMR003002",
    "gn:asciiname":"Mawwakhi",
    "gn:country_code":"MM",
    "gn:dem":571,
    "gn:feature_class":"P",
    "gn:feature_code":"PPL",
    "gn:name":"Mawwakhi",
    "gn:population":0,
    "gn:timezone":"Asia/Yangon",
    "iso:country":"MM",
    "wof:name":"Mawwakhi",
    "wof:placetype":"locality"
},
  "geometry": {"coordinates":[98.00512999999999,17.42974],"type":"Point"}
}