{
  "type": "Feature",
  "properties": {
    "gn:admin1_code":"6.0",
    "gn:admin2_code":"MMR002D001",
    "gn:admin3_code":"MMR002003",
    "gn:asciiname":"Ta-le-hkre",
    "gn:country_code":"MM",
    "gn:dem":1035,
    "gn:feature_class":"P",
    "gn:feature_code":"PPL",
    "gn:name":"Ta-l\u00e8-hkr\u00e8",
    "gn:population":0,
    "gn:timezone":"Asia/Yangon",
    "iso:country":"MM",
    "wof:name":"Ta-le-hkre",
    "wof:placetype":"locality"
},
  "geometry": {"coordinates":[97.06729,19.24071],"type":"Point"}
}