{
  "type": "Feature",
  "properties": {
    "gn:admin1_code":"15.0",
    "gn:admin2_code":"MMR009D005",
    "gn:admin3_code":"MMR009023",
    "gn:asciiname":"Legyi",
    "gn:country_code":"MM",
    "gn:dem":148,
    "gn:feature_class":"P",
    "gn:feature_code":"PPL",
    "gn:name":"Legyi",
    "gn:population":0,
    "gn:timezone":"Asia/Yangon",
    "iso:country":"MM",
    "wof:name":"Legyi",
    "wof:placetype":"locality"
},
  "geometry": {"coordinates":[94.13423,22.66887],"type":"Point"}
}