{
  "type": "Feature",
  "properties": {
    "gn:admin1_code":"4.0",
    "gn:admin2_code":"MMR001D004",
    "gn:admin3_code":"MMR001016",
    "gn:asciiname":"Tarandam",
    "gn:country_code":"MM",
    "gn:dem":1096,
    "gn:feature_class":"P",
    "gn:feature_code":"PPL",
    "gn:name":"Tarand\u0101m",
    "gn:population":0,
    "gn:timezone":"Asia/Yangon",
    "iso:country":"MM",
    "wof:name":"Tarandam",
    "wof:placetype":"locality"
},
  "geometry": {"coordinates":[97.49912,27.62448],"type":"Point"}
}