{
  "type": "Feature",
  "properties": {
    "gn:admin1_code":"8.0",
    "gn:admin2_code":"MMR010D002",
    "gn:admin3_code":"MMR010010",
    "gn:asciiname":"Kyunbingyi",
    "gn:country_code":"MM",
    "gn:dem":195,
    "gn:feature_class":"P",
    "gn:feature_code":"PPL",
    "gn:name":"Kyunbingyi",
    "gn:population":0,
    "gn:timezone":"Asia/Yangon",
    "iso:country":"MM",
    "wof:name":"Kyunbingyi",
    "wof:placetype":"locality"
},
  "geometry": {"coordinates":[96.10858,22.67777],"type":"Point"}
}