{
  "type": "Feature",
  "properties": {
    "gn:admin1_code":"3.0",
    "gn:admin2_code":"MMR017D006",
    "gn:admin3_code":"MMR017025",
    "gn:asciiname":"Magwedan",
    "gn:country_code":"MM",
    "gn:dem":11,
    "gn:feature_class":"P",
    "gn:feature_code":"PPL",
    "gn:name":"Magwedan",
    "gn:population":0,
    "gn:timezone":"Asia/Yangon",
    "iso:country":"MM",
    "wof:name":"Magwedan",
    "wof:placetype":"locality"
},
  "geometry": {"coordinates":[95.63,16.42063],"type":"Point"}
}