{
  "type": "Feature",
  "properties": {
    "gn:admin1_code":"11.0",
    "gn:admin2_code":"MMR015D006",
    "gn:admin3_code":"MMR015008",
    "gn:asciiname":"Kungsan",
    "gn:country_code":"MM",
    "gn:dem":859,
    "gn:feature_class":"P",
    "gn:feature_code":"PPL",
    "gn:name":"Kungsan",
    "gn:population":0,
    "gn:timezone":"Asia/Yangon",
    "iso:country":"MM",
    "wof:name":"Kungsan",
    "wof:placetype":"locality"
},
  "geometry": {"coordinates":[99.03636,22.87522],"type":"Point"}
}