{
  "type": "Feature",
  "properties": {
    "gn:admin1_code":"10.0",
    "gn:admin2_code":"MMR005D008",
    "gn:admin3_code":"MMR005036",
    "gn:asciiname":"Songtai",
    "gn:country_code":"MM",
    "gn:dem":671,
    "gn:feature_class":"P",
    "gn:feature_code":"PPL",
    "gn:name":"Songt\u0101i",
    "gn:population":0,
    "gn:timezone":"Asia/Yangon",
    "iso:country":"MM",
    "wof:name":"Songtai",
    "wof:placetype":"locality"
},
  "geometry": {"coordinates":[95.53471999999999,26.30355],"type":"Point"}
}