{
  "type": "Feature",
  "properties": {
    "gn:admin1_code":"3.0",
    "gn:admin2_code":"MMR017D005",
    "gn:admin3_code":"MMR017020",
    "gn:asciiname":"Katun",
    "gn:country_code":"MM",
    "gn:dem":13,
    "gn:feature_class":"P",
    "gn:feature_code":"PPL",
    "gn:name":"Katun",
    "gn:population":0,
    "gn:timezone":"Asia/Yangon",
    "iso:country":"MM",
    "name:bos_x_preferred":[
        "Katun"
    ],
    "name:bul_x_preferred":[
        "\u041a\u0430\u0442\u0443\u043d"
    ],
    "name:deu_x_preferred":[
        "Katun"
    ],
    "name:fra_x_preferred":[
        "Katun"
    ],
    "name:hrv_x_preferred":[
        "Katun"
    ],
    "name:hun_x_preferred":[
        "Katun"
    ],
    "name:hye_x_preferred":[
        "\u053f\u0561\u057f\u0578\u0582\u0576"
    ],
    "name:ita_x_preferred":[
        "Katun"
    ],
    "name:nld_x_preferred":[
        "Katun"
    ],
    "name:rus_x_preferred":[
        "\u041a\u0430\u0442\u0443\u043d\u044c"
    ],
    "name:sco_x_preferred":[
        "Katun"
    ],
    "name:slv_x_preferred":[
        "Katun"
    ],
    "name:srp_x_preferred":[
        "\u041a\u0430\u0442\u0443\u043d"
    ],
    "wof:name":"Katun",
    "wof:placetype":"locality"
},
  "geometry": {"coordinates":[95.54083,16.87302],"type":"Point"}
}