{
  "type": "Feature",
  "properties": {
    "gn:admin1_code":"16.0",
    "gn:admin2_code":"MMR008D002",
    "gn:admin3_code":"MMR008008",
    "gn:asciiname":"Kalachaung",
    "gn:country_code":"MM",
    "gn:dem":20,
    "gn:feature_class":"P",
    "gn:feature_code":"PPL",
    "gn:name":"Kalachaung",
    "gn:population":0,
    "gn:timezone":"Asia/Yangon",
    "iso:country":"MM",
    "wof:name":"Kalachaung",
    "wof:placetype":"locality"
},
  "geometry": {"coordinates":[95.46850999999999,17.72087],"type":"Point"}
}