{
  "type": "Feature",
  "properties": {
    "gn:admin1_code":"11.0",
    "gn:admin2_code":"MMR014D002",
    "gn:admin3_code":"MMR014013",
    "gn:asciiname":"Mesari",
    "gn:country_code":"MM",
    "gn:dem":949,
    "gn:feature_class":"P",
    "gn:feature_code":"PPL",
    "gn:name":"Mesari",
    "gn:population":0,
    "gn:timezone":"Asia/Yangon",
    "iso:country":"MM",
    "name:bos_x_preferred":[
        "Mesari"
    ],
    "name:fra_x_preferred":[
        "Mesari"
    ],
    "name:srp_x_preferred":[
        "\u041c\u0435\u0441\u0430\u0440\u0438"
    ],
    "wof:name":"Mesari",
    "wof:placetype":"locality"
},
  "geometry": {"coordinates":[97.79497000000001,20.9129],"type":"Point"}
}