{
  "type": "Feature",
  "properties": {
    "gn:admin1_code":"16.0",
    "gn:admin2_code":"MMR008D001",
    "gn:admin3_code":"MMR008004",
    "gn:asciiname":"Gyobin",
    "gn:country_code":"MM",
    "gn:dem":35,
    "gn:feature_class":"P",
    "gn:feature_code":"PPL",
    "gn:name":"Gyobin",
    "gn:population":0,
    "gn:timezone":"Asia/Yangon",
    "iso:country":"MM",
    "wof:name":"Gyobin",
    "wof:placetype":"locality"
},
  "geometry": {"coordinates":[95.4901,18.45512],"type":"Point"}
}