{
  "type": "Feature",
  "properties": {
    "gn:admin1_code":"16.0",
    "gn:admin2_code":"MMR007D001",
    "gn:admin3_code":"MMR007007",
    "gn:asciiname":"Odokmyaung",
    "gn:country_code":"MM",
    "gn:dem":30,
    "gn:feature_class":"P",
    "gn:feature_code":"PPL",
    "gn:name":"Odokmyaung",
    "gn:population":0,
    "gn:timezone":"Asia/Yangon",
    "iso:country":"MM",
    "wof:name":"Odokmyaung",
    "wof:placetype":"locality"
},
  "geometry": {"coordinates":[96.52636,17.88856000000001],"type":"Point"}
}