{
  "type": "Feature",
  "properties": {
    "gn:admin1_code":"11.0",
    "gn:admin2_code":"MMR016D001",
    "gn:admin3_code":"MMR016007",
    "gn:asciiname":"Wan Nawng-lang",
    "gn:country_code":"MM",
    "gn:dem":750,
    "gn:feature_class":"P",
    "gn:feature_code":"PPL",
    "gn:name":"W\u0101n Nawng-lang",
    "gn:population":0,
    "gn:timezone":"Asia/Yangon",
    "iso:country":"MM",
    "name:und_x_variant":[
        "Wan Nawngla",
        "W\u0101n Nawng-lang"
    ],
    "wof:name":"Wan Nawng-lang",
    "wof:placetype":"locality"
},
  "geometry": {"coordinates":[99.10817,21.01908],"type":"Point"}
}