{
  "type": "Feature",
  "properties": {
    "gn:admin1_code":"2.0",
    "gn:admin2_code":"MMR004D002",
    "gn:admin3_code":"MMR004006",
    "gn:asciiname":"Mthway",
    "gn:country_code":"MM",
    "gn:dem":1332,
    "gn:feature_class":"P",
    "gn:feature_code":"PPL",
    "gn:name":"Mthway",
    "gn:population":0,
    "gn:timezone":"Asia/Yangon",
    "iso:country":"MM",
    "wof:name":"Mthway",
    "wof:placetype":"locality"
},
  "geometry": {"coordinates":[93.68850999999999,21.31699],"type":"Point"}
}