{
  "type": "Feature",
  "properties": {
    "gn:admin1_code":"2.0",
    "gn:admin2_code":"MMR004D002",
    "gn:admin3_code":"MMR004009",
    "gn:asciiname":"Chuni",
    "gn:country_code":"MM",
    "gn:dem":491,
    "gn:feature_class":"P",
    "gn:feature_code":"PPL",
    "gn:name":"Chuni",
    "gn:population":0,
    "gn:timezone":"Asia/Yangon",
    "iso:country":"MM",
    "name:ceb_x_preferred":[
        "Chuni"
    ],
    "wof:name":"Chuni",
    "wof:placetype":"locality"
},
  "geometry": {"coordinates":[93.16667,21.31667],"type":"Point"}
}