{
  "type": "Feature",
  "properties": {
    "gn:admin1_code":"8.0",
    "gn:admin2_code":"MMR010D002",
    "gn:admin3_code":"MMR010010",
    "gn:asciiname":"Malegyi",
    "gn:country_code":"MM",
    "gn:dem":109,
    "gn:feature_class":"P",
    "gn:feature_code":"PPL",
    "gn:name":"Malegyi",
    "gn:population":0,
    "gn:timezone":"Asia/Yangon",
    "iso:country":"MM",
    "wof:name":"Malegyi",
    "wof:placetype":"locality"
},
  "geometry": {"coordinates":[96.09247000000001,22.57669],"type":"Point"}
}