{
  "type": "Feature",
  "properties": {
    "gn:admin1_code":"11.0",
    "gn:admin2_code":"MMR015D002",
    "gn:admin3_code":"MMR015010",
    "gn:asciiname":"Man Tat",
    "gn:country_code":"MM",
    "gn:dem":1172,
    "gn:feature_class":"P",
    "gn:feature_code":"PPL",
    "gn:name":"M\u0101n Tat",
    "gn:population":0,
    "gn:timezone":"Asia/Yangon",
    "iso:country":"MM",
    "wof:name":"Man Tat",
    "wof:placetype":"locality"
},
  "geometry": {"coordinates":[97.48724,23.67729],"type":"Point"}
}