{
  "type": "Feature",
  "properties": {
    "gn:admin1_code":"8.0",
    "gn:asciiname":"Seywa",
    "gn:country_code":"MM",
    "gn:dem":69,
    "gn:feature_class":"P",
    "gn:feature_code":"PPL",
    "gn:name":"Seywa",
    "gn:population":0,
    "gn:timezone":"Asia/Yangon",
    "iso:country":"MM",
    "wof:name":"Seywa",
    "wof:placetype":"locality"
},
  "geometry": {"coordinates":[95.31625,21.71157],"type":"Point"}
}