{
  "type": "Feature",
  "properties": {
    "gn:admin1_code":"11.0",
    "gn:admin2_code":"MMR016D002",
    "gn:admin3_code":"MMR016008",
    "gn:asciiname":"Wan Hpya-kawng",
    "gn:country_code":"MM",
    "gn:dem":1297,
    "gn:feature_class":"P",
    "gn:feature_code":"PPL",
    "gn:name":"W\u0101n Hpya-kawng",
    "gn:population":0,
    "gn:timezone":"Asia/Yangon",
    "iso:country":"MM",
    "name:und_x_variant":[
        "Hpya-kawng",
        "W\u0101n Hpya-kawng"
    ],
    "wof:name":"Wan Hpya-kawng",
    "wof:placetype":"locality"
},
  "geometry": {"coordinates":[99.15616,20.20189],"type":"Point"}
}