{
  "type": "Feature",
  "properties": {
    "gn:admin1_code":"5.0",
    "gn:admin2_code":"MMR003D001",
    "gn:admin3_code":"MMR003002",
    "gn:asciiname":"Kawsein Ale",
    "gn:country_code":"MM",
    "gn:dem":24,
    "gn:feature_class":"P",
    "gn:feature_code":"PPL",
    "gn:name":"Kawsein Ale",
    "gn:population":0,
    "gn:timezone":"Asia/Yangon",
    "iso:country":"MM",
    "name:und_x_variant":[
        "Kawsein",
        "Kawsein Ale"
    ],
    "wof:name":"Kawsein Ale",
    "wof:placetype":"locality"
},
  "geometry": {"coordinates":[97.65676999999999,17.21287],"type":"Point"}
}