{
  "type": "Feature",
  "properties": {
    "gn:admin1_code":"16.0",
    "gn:admin2_code":"MMR007D001",
    "gn:admin3_code":"MMR007007",
    "gn:asciiname":"Letkokkwin",
    "gn:country_code":"MM",
    "gn:dem":17,
    "gn:feature_class":"P",
    "gn:feature_code":"PPL",
    "gn:name":"Letkokkwin",
    "gn:population":0,
    "gn:timezone":"Asia/Yangon",
    "iso:country":"MM",
    "name:und_x_variant":[
        "Letk\u00f4k",
        "Letkokkwin"
    ],
    "wof:name":"Letkokkwin",
    "wof:placetype":"locality"
},
  "geometry": {"coordinates":[96.58221,17.65648],"type":"Point"}
}