{
  "type": "Feature",
  "properties": {
    "gn:admin1_code":"8.0",
    "gn:admin2_code":"MMR010D002",
    "gn:admin3_code":"MMR010012",
    "gn:asciiname":"Nyaunggyin",
    "gn:country_code":"MM",
    "gn:dem":95,
    "gn:feature_class":"P",
    "gn:feature_code":"PPL",
    "gn:name":"Nyaunggyin",
    "gn:population":0,
    "gn:timezone":"Asia/Yangon",
    "iso:country":"MM",
    "name:mya_x_preferred":[
        "\u100a\u1031\u102c\u1004\u103a\u1001\u103b\u1004\u103a\u1038\u1021\u102d\u102f\u1014\u1010\u103a"
    ],
    "wof:name":"Nyaunggyin",
    "wof:placetype":"locality"
},
  "geometry": {"coordinates":[96.01613,23.02704],"type":"Point"}
}