{
  "type": "Feature",
  "properties": {
    "gn:admin1_code":"11.0",
    "gn:admin2_code":"MMR015D008",
    "gn:admin3_code":"MMR015017",
    "gn:asciiname":"Taunggon",
    "gn:country_code":"MM",
    "gn:dem":173,
    "gn:feature_class":"P",
    "gn:feature_code":"PPL",
    "gn:name":"Taunggon",
    "gn:population":0,
    "gn:timezone":"Asia/Yangon",
    "iso:country":"MM",
    "wof:name":"Taunggon",
    "wof:placetype":"locality"
},
  "geometry": {"coordinates":[96.35044000000001,23.07769],"type":"Point"}
}