{
  "type": "Feature",
  "properties": {
    "gn:admin1_code":"1.0",
    "gn:admin2_code":"MMR012D001",
    "gn:admin3_code":"MMR012007",
    "gn:asciiname":"Tatmaw",
    "gn:country_code":"MM",
    "gn:dem":1,
    "gn:feature_class":"P",
    "gn:feature_code":"PPL",
    "gn:name":"Tatmaw",
    "gn:population":0,
    "gn:timezone":"Asia/Yangon",
    "iso:country":"MM",
    "wof:name":"Tatmaw",
    "wof:placetype":"locality"
},
  "geometry": {"coordinates":[93.00108,20.22239],"type":"Point"}
}