{
  "type": "Feature",
  "properties": {
    "gn:admin1_code":"4.0",
    "gn:admin2_code":"MMR001D001",
    "gn:admin3_code":"MMR001002",
    "gn:asciiname":"Lonmahku",
    "gn:country_code":"MM",
    "gn:dem":1678,
    "gn:feature_class":"P",
    "gn:feature_code":"PPL",
    "gn:name":"Lonmahku",
    "gn:population":0,
    "gn:timezone":"Asia/Yangon",
    "iso:country":"MM",
    "wof:name":"Lonmahku",
    "wof:placetype":"locality"
},
  "geometry": {"coordinates":[98.08159000000001,25.44649],"type":"Point"}
}