{
  "type": "Feature",
  "properties": {
    "gn:admin1_code":"11.0",
    "gn:admin2_code":"MMR016D001",
    "gn:admin3_code":"MMR016001",
    "gn:asciiname":"Wan Loi-lue",
    "gn:country_code":"MM",
    "gn:dem":1352,
    "gn:feature_class":"P",
    "gn:feature_code":"PPL",
    "gn:name":"W\u0101n Loi-l\u00fc",
    "gn:population":0,
    "gn:timezone":"Asia/Yangon",
    "iso:country":"MM",
    "name:und_x_variant":[
        "W\u0101n Kaw Loi-lu",
        "W\u0101n Loi-l\u00fc"
    ],
    "wof:name":"Wan Loi-lue",
    "wof:placetype":"locality"
},
  "geometry": {"coordinates":[99.66412,21.16064],"type":"Point"}
}