{
  "type": "Feature",
  "properties": {
    "gn:admin1_code":"4.0",
    "gn:admin2_code":"MMR001D001",
    "gn:admin3_code":"MMR001005",
    "gn:asciiname":"Hkayazahkuso",
    "gn:country_code":"MM",
    "gn:dem":2093,
    "gn:feature_class":"P",
    "gn:feature_code":"PPL",
    "gn:name":"Hkayazahkuso",
    "gn:population":0,
    "gn:timezone":"Asia/Yangon",
    "iso:country":"MM",
    "wof:name":"Hkayazahkuso",
    "wof:placetype":"locality"
},
  "geometry": {"coordinates":[98.59569999999999,26.31674000000001],"type":"Point"}
}