{
  "type": "Feature",
  "properties": {
    "gn:admin1_code":"8.0",
    "gn:admin2_code":"MMR010D006",
    "gn:admin3_code":"MMR010024",
    "gn:asciiname":"Seywa",
    "gn:country_code":"MM",
    "gn:dem":186,
    "gn:feature_class":"P",
    "gn:feature_code":"PPL",
    "gn:name":"Seywa",
    "gn:population":0,
    "gn:timezone":"Asia/Yangon",
    "iso:country":"MM",
    "wof:name":"Seywa",
    "wof:placetype":"locality"
},
  "geometry": {"coordinates":[96.0936,20.614],"type":"Point"}
}