{
  "type": "Feature",
  "properties": {
    "gn:admin1_code":"10.0",
    "gn:asciiname":"Leingon",
    "gn:country_code":"MM",
    "gn:dem":93,
    "gn:feature_class":"P",
    "gn:feature_code":"PPL",
    "gn:name":"Leingon",
    "gn:population":0,
    "gn:timezone":"Asia/Yangon",
    "iso:country":"MM",
    "wof:name":"Leingon",
    "wof:placetype":"locality"
},
  "geometry": {"coordinates":[95.86272,21.80937],"type":"Point"}
}