{
  "type": "Feature",
  "properties": {
    "gn:admin1_code":"10.0",
    "gn:admin2_code":"MMR005D008",
    "gn:admin3_code":"MMR005033",
    "gn:asciiname":"Janhtang",
    "gn:country_code":"MM",
    "gn:dem":296,
    "gn:feature_class":"P",
    "gn:feature_code":"PPL",
    "gn:name":"Janhtang",
    "gn:population":0,
    "gn:timezone":"Asia/Yangon",
    "iso:country":"MM",
    "name:urd_x_preferred":[
        "\u062c\u0646\u06c1\u062a\u0646\u06af"
    ],
    "wof:name":"Janhtang",
    "wof:placetype":"locality"
},
  "geometry": {"coordinates":[96.0324,26.26368],"type":"Point"}
}