{
  "type": "Feature",
  "properties": {
    "gn:admin1_code":"11.0",
    "gn:admin2_code":"MMR014D003",
    "gn:admin3_code":"MMR014019",
    "gn:asciiname":"Tohsai",
    "gn:country_code":"MM",
    "gn:dem":805,
    "gn:feature_class":"P",
    "gn:feature_code":"PPL",
    "gn:name":"Tohsai",
    "gn:population":0,
    "gn:timezone":"Asia/Yangon",
    "iso:country":"MM",
    "wof:name":"Tohsai",
    "wof:placetype":"locality"
},
  "geometry": {"coordinates":[97.90000000000001,20.48333],"type":"Point"}
}