{
  "type": "Feature",
  "properties": {
    "gn:admin1_code":"15.0",
    "gn:admin2_code":"MMR009D001",
    "gn:admin3_code":"MMR009006",
    "gn:asciiname":"Aingmagyi",
    "gn:country_code":"MM",
    "gn:dem":361,
    "gn:feature_class":"P",
    "gn:feature_code":"PPL",
    "gn:name":"Aingmagyi",
    "gn:population":0,
    "gn:timezone":"Asia/Yangon",
    "iso:country":"MM",
    "wof:name":"Aingmagyi",
    "wof:placetype":"locality"
},
  "geometry": {"coordinates":[95.57051,20.6585],"type":"Point"}
}