{
  "type": "Feature",
  "properties": {
    "gn:admin1_code":"6.0",
    "gn:admin2_code":"MMR002D001",
    "gn:admin3_code":"MMR002004",
    "gn:asciiname":"Wan Hwe-pung",
    "gn:country_code":"MM",
    "gn:dem":631,
    "gn:feature_class":"P",
    "gn:feature_code":"PPL",
    "gn:name":"W\u0101n Hw\u00e8-p\u016bng",
    "gn:population":0,
    "gn:timezone":"Asia/Yangon",
    "iso:country":"MM",
    "wof:name":"Wan Hwe-pung",
    "wof:placetype":"locality"
},
  "geometry": {"coordinates":[97.77583,19.63722000000001],"type":"Point"}
}