{
  "type": "Feature",
  "properties": {
    "gn:admin1_code":"8.0",
    "gn:admin2_code":"MMR010D002",
    "gn:admin3_code":"MMR010011",
    "gn:asciiname":"Ingyauk",
    "gn:country_code":"MM",
    "gn:dem":1648,
    "gn:feature_class":"P",
    "gn:feature_code":"PPL",
    "gn:name":"Ingyauk",
    "gn:population":0,
    "gn:timezone":"Asia/Yangon",
    "iso:country":"MM",
    "wof:name":"Ingyauk",
    "wof:placetype":"locality"
},
  "geometry": {"coordinates":[96.44687,22.96784],"type":"Point"}
}