{
  "type": "Feature",
  "properties": {
    "gn:admin1_code":"16.0",
    "gn:admin2_code":"MMR008D001",
    "gn:admin3_code":"MMR008001",
    "gn:asciiname":"Mahabo",
    "gn:country_code":"MM",
    "gn:dem":44,
    "gn:feature_class":"P",
    "gn:feature_code":"PPL",
    "gn:name":"Mahabo",
    "gn:population":0,
    "gn:timezone":"Asia/Yangon",
    "iso:country":"MM",
    "name:fra_x_preferred":[
        "Mahabo"
    ],
    "name:ita_x_preferred":[
        "Mahabo"
    ],
    "name:mlg_x_preferred":[
        "Mahabo"
    ],
    "name:nld_x_preferred":[
        "Mahabo"
    ],
    "name:pol_x_preferred":[
        "Mahabo"
    ],
    "name:swe_x_preferred":[
        "Mahabo"
    ],
    "name:zho_x_preferred":[
        "\u99ac\u54c8\u5e03"
    ],
    "wof:name":"Mahabo",
    "wof:placetype":"locality"
},
  "geometry": {"coordinates":[95.32135,18.92523],"type":"Point"}
}