{
  "type": "Feature",
  "properties": {
    "gn:admin1_code":"12.0",
    "gn:admin2_code":"MMR006D003",
    "gn:admin3_code":"MMR006006",
    "gn:asciiname":"Katan",
    "gn:country_code":"MM",
    "gn:dem":19,
    "gn:feature_class":"P",
    "gn:feature_code":"PPL",
    "gn:name":"Katan",
    "gn:population":0,
    "gn:timezone":"Asia/Yangon",
    "iso:country":"MM",
    "name:ceb_x_preferred":[
        "Katan"
    ],
    "name:deu_x_preferred":[
        "Katan"
    ],
    "name:fra_x_preferred":[
        "Katan"
    ],
    "name:heb_x_preferred":[
        "\u05e7\u05d8\u05df"
    ],
    "name:nld_x_preferred":[
        "Katan"
    ],
    "name:pol_x_preferred":[
        "Katan"
    ],
    "name:swe_x_preferred":[
        "Katan"
    ],
    "wof:name":"Katan",
    "wof:placetype":"locality"
},
  "geometry": {"coordinates":[98.41305,12.4103],"type":"Point"}
}