{
  "type": "Feature",
  "properties": {
    "gn:admin1_code":"11.0",
    "gn:admin2_code":"MMR015D008",
    "gn:admin3_code":"MMR015017",
    "gn:asciiname":"Kaungmu",
    "gn:country_code":"MM",
    "gn:dem":933,
    "gn:feature_class":"P",
    "gn:feature_code":"PPL",
    "gn:name":"Kaungmu",
    "gn:population":0,
    "gn:timezone":"Asia/Yangon",
    "iso:country":"MM",
    "name:und_x_variant":[
        "Kaungmy",
        "Palaung"
    ],
    "wof:name":"Kaungmu",
    "wof:placetype":"locality"
},
  "geometry": {"coordinates":[96.75806,23.23325],"type":"Point"}
}