{
  "type": "Feature",
  "properties": {
    "gn:admin1_code":"16.0",
    "gn:admin2_code":"MMR008D002",
    "gn:admin3_code":"MMR008008",
    "gn:asciiname":"Seindon Ashe",
    "gn:country_code":"MM",
    "gn:dem":19,
    "gn:feature_class":"P",
    "gn:feature_code":"PPL",
    "gn:name":"Seindon Ashe",
    "gn:population":0,
    "gn:timezone":"Asia/Yangon",
    "iso:country":"MM",
    "name:und_x_variant":[
        "Seindon",
        "Seindon Ashe"
    ],
    "wof:name":"Seindon Ashe",
    "wof:placetype":"locality"
},
  "geometry": {"coordinates":[95.50689,17.67157000000001],"type":"Point"}
}