{
  "type": "Feature",
  "properties": {
    "gn:admin1_code":"11.0",
    "gn:admin2_code":"MMR015D003",
    "gn:admin3_code":"MMR015014",
    "gn:asciiname":"Koko",
    "gn:country_code":"MM",
    "gn:dem":594,
    "gn:feature_class":"P",
    "gn:feature_code":"PPL",
    "gn:name":"Koko",
    "gn:population":0,
    "gn:timezone":"Asia/Yangon",
    "iso:country":"MM",
    "name:ara_x_preferred":[
        "\u0643\u0648\u0643\u0648"
    ],
    "name:ben_x_preferred":[
        "\u0995\u09cb\u0995\u09cb"
    ],
    "name:bul_x_preferred":[
        "\u041a\u043e\u043a\u043e"
    ],
    "name:ceb_x_preferred":[
        "Koko"
    ],
    "name:ces_x_preferred":[
        "Koko"
    ],
    "name:deu_x_preferred":[
        "Koko"
    ],
    "name:ell_x_preferred":[
        "\u039a\u03cc\u03ba\u03bf"
    ],
    "name:eng_x_preferred":[
        "Koko"
    ],
    "name:epo_x_preferred":[
        "Koko"
    ],
    "name:fas_x_preferred":[
        "\u06a9\u0648\u06a9\u0648"
    ],
    "name:fin_x_preferred":[
        "Koko"
    ],
    "name:fra_x_preferred":[
        "Koko"
    ],
    "name:heb_x_preferred":[
        "\u05e7\u05d5\u05e7\u05d5"
    ],
    "name:hin_x_preferred":[
        "\u0915\u094b\u0915\u094b"
    ],
    "name:hun_x_preferred":[
        "Koko"
    ],
    "name:ind_x_preferred":[
        "Koko"
    ],
    "name:ita_x_preferred":[
        "Koko"
    ],
    "name:jpn_x_preferred":[
        "\u30b3\u30b3"
    ],
    "name:kor_x_preferred":[
        "\ucf54\ucf54"
    ],
    "name:mya_x_preferred":[
        "\u1000\u102d\u102f\u1000\u102d\u102f"
    ],
    "name:nld_x_preferred":[
        "Koko"
    ],
    "name:pol_x_preferred":[
        "Koko"
    ],
    "name:por_x_preferred":[
        "Koko"
    ],
    "name:rus_x_preferred":[
        "\u041a\u043e\u043a\u043e"
    ],
    "name:spa_x_preferred":[
        "Koko"
    ],
    "name:srp_x_preferred":[
        "\u041a\u043e\u043a\u043e"
    ],
    "name:swe_x_preferred":[
        "Koko"
    ],
    "name:tur_x_preferred":[
        "Koko"
    ],
    "name:ukr_x_preferred":[
        "\u041a\u043e\u043a\u043e"
    ],
    "name:urd_x_preferred":[
        "\u06a9\u0648\u06a9\u0648"
    ],
    "name:vie_x_preferred":[
        "Koko"
    ],
    "name:zho_cn_x_preferred":[
        "\u79d1\u79d1"
    ],
    "name:zho_tw_x_preferred":[
        "\u79d1\u79d1"
    ],
    "wof:name":"Koko",
    "wof:placetype":"locality"
},
  "geometry": {"coordinates":[97.48316,22.08934],"type":"Point"}
}