{
  "type": "Feature",
  "properties": {
    "gn:admin1_code":"10.0",
    "gn:admin2_code":"MMR005D008",
    "gn:admin3_code":"MMR005034",
    "gn:asciiname":"Yegyaw",
    "gn:country_code":"MM",
    "gn:dem":130,
    "gn:feature_class":"P",
    "gn:feature_code":"PPL",
    "gn:name":"Yegyaw",
    "gn:population":0,
    "gn:timezone":"Asia/Yangon",
    "iso:country":"MM",
    "name:urd_x_preferred":[
        "\u06cc\u06af\u06cc\u0627\u0648"
    ],
    "wof:name":"Yegyaw",
    "wof:placetype":"locality"
},
  "geometry": {"coordinates":[94.99257,24.83931],"type":"Point"}
}