{
  "type": "Feature",
  "properties": {
    "gn:admin1_code":"11.0",
    "gn:admin2_code":"MMR015D003",
    "gn:admin3_code":"MMR015016",
    "gn:asciiname":"Wengmao",
    "gn:country_code":"MM",
    "gn:dem":1587,
    "gn:feature_class":"P",
    "gn:feature_code":"PPL",
    "gn:name":"Wengmao",
    "gn:population":0,
    "gn:timezone":"Asia/Yangon",
    "iso:country":"MM",
    "wof:name":"Wengmao",
    "wof:placetype":"locality"
},
  "geometry": {"coordinates":[97.00439,22.88179],"type":"Point"}
}