{
  "type": "Feature",
  "properties": {
    "gn:admin1_code":"15.0",
    "gn:admin2_code":"MMR009D004",
    "gn:admin3_code":"MMR009019",
    "gn:asciiname":"Kyawmakya",
    "gn:country_code":"MM",
    "gn:dem":74,
    "gn:feature_class":"P",
    "gn:feature_code":"PPL",
    "gn:name":"Kyawmakya",
    "gn:population":0,
    "gn:timezone":"Asia/Yangon",
    "iso:country":"MM",
    "name:und_x_variant":[
        "Kyawmagya",
        "Kyawmakya"
    ],
    "wof:name":"Kyawmakya",
    "wof:placetype":"locality"
},
  "geometry": {"coordinates":[95.25924000000001,21.6219],"type":"Point"}
}