{
  "type": "Feature",
  "properties": {
    "gn:admin1_code":"16.0",
    "gn:admin2_code":"MMR007D002",
    "gn:admin3_code":"MMR007010",
    "gn:asciiname":"Bogyi Te",
    "gn:country_code":"MM",
    "gn:dem":232,
    "gn:feature_class":"P",
    "gn:feature_code":"PPL",
    "gn:name":"Bogyi T\u00e8",
    "gn:population":0,
    "gn:timezone":"Asia/Yangon",
    "iso:country":"MM",
    "wof:name":"Bogyi Te",
    "wof:placetype":"locality"
},
  "geometry": {"coordinates":[95.93344,19.38589],"type":"Point"}
}