{
  "type": "Feature",
  "properties": {
    "gn:admin1_code":"8.0",
    "gn:admin2_code":"MMR010D004",
    "gn:admin3_code":"MMR010021",
    "gn:asciiname":"Pyudwingon",
    "gn:country_code":"MM",
    "gn:dem":150,
    "gn:feature_class":"P",
    "gn:feature_code":"PPL",
    "gn:name":"Pyudwingon",
    "gn:population":0,
    "gn:timezone":"Asia/Yangon",
    "iso:country":"MM",
    "name:und_x_variant":[
        "Pyudwin",
        "Pyudwingon"
    ],
    "wof:name":"Pyudwingon",
    "wof:placetype":"locality"
},
  "geometry": {"coordinates":[95.58387,21.66281],"type":"Point"}
}