{
  "type": "Feature",
  "properties": {
    "gn:admin1_code":"1.0",
    "gn:admin2_code":"MMR012D001",
    "gn:admin3_code":"MMR012001",
    "gn:asciiname":"Amyingyun",
    "gn:country_code":"MM",
    "gn:dem":11,
    "gn:feature_class":"P",
    "gn:feature_code":"PPL",
    "gn:name":"Amyingyun",
    "gn:population":0,
    "gn:timezone":"Asia/Yangon",
    "iso:country":"MM",
    "wof:name":"Amyingyun",
    "wof:placetype":"locality"
},
  "geometry": {"coordinates":[92.88094,20.29672],"type":"Point"}
}