{
  "type": "Feature",
  "properties": {
    "gn:admin1_code":"8.0",
    "gn:admin2_code":"MMR010D007",
    "gn:admin3_code":"MMR010029",
    "gn:asciiname":"Paungyodaw",
    "gn:country_code":"MM",
    "gn:dem":267,
    "gn:feature_class":"P",
    "gn:feature_code":"PPL",
    "gn:name":"Paungyodaw",
    "gn:population":0,
    "gn:timezone":"Asia/Yangon",
    "iso:country":"MM",
    "wof:name":"Paungyodaw",
    "wof:placetype":"locality"
},
  "geometry": {"coordinates":[95.68771,21.07463],"type":"Point"}
}