{
  "type": "Feature",
  "properties": {
    "gn:admin1_code":"11.0",
    "gn:admin2_code":"MMR015D006",
    "gn:admin3_code":"MMR015021",
    "gn:asciiname":"Hopang",
    "gn:country_code":"MM",
    "gn:dem":467,
    "gn:feature_class":"P",
    "gn:feature_code":"PPL",
    "gn:name":"Hopang",
    "gn:population":0,
    "gn:timezone":"Asia/Yangon",
    "iso:country":"MM",
    "name:mya_x_preferred":[
        "\u101f\u102d\u102f\u1015\u1014\u103a\u1019\u103c\u102d\u102f\u1037"
    ],
    "name:por_x_preferred":[
        "Hopang"
    ],
    "name:shn_x_preferred":[
        "\u1081\u1030\u101d\u103a\u1015\u1062\u1004\u103a\u1087\u104a \u101d\u1035\u1004\u103a\u1038"
    ],
    "name:swe_x_preferred":[
        "Hopang"
    ],
    "name:tam_x_preferred":[
        "\u0bb9\u0bcb\u0baa\u0bbe\u0b99\u0bcd"
    ],
    "name:urd_x_preferred":[
        "\u06c1\u0648\u067e\u0627\u0646\u06af"
    ],
    "wof:name":"Hopang",
    "wof:placetype":"locality"
},
  "geometry": {"coordinates":[98.75187,23.42526],"type":"Point"}
}