{
  "type": "Feature",
  "properties": {
    "gn:admin1_code":"11.0",
    "gn:admin2_code":"MMR015D006",
    "gn:admin3_code":"MMR015021",
    "gn:asciiname":"Hopang",
    "gn:country_code":"MM",
    "gn:dem":467,
    "gn:feature_class":"P",
    "gn:feature_code":"PPL",
    "gn:name":"Hopang",
    "gn:population":0,
    "gn:timezone":"Asia/Yangon",
    "iso:country":"MM",
    "wof:name":"Hopang",
    "wof:placetype":"locality"
},
  "geometry": {"coordinates":[98.75187,23.42526],"type":"Point"}
}