{
  "type": "Feature",
  "properties": {
    "gn:admin1_code":"2.0",
    "gn:asciiname":"Ameikywa",
    "gn:country_code":"MM",
    "gn:dem":330,
    "gn:feature_class":"P",
    "gn:feature_code":"PPL",
    "gn:name":"Ameikywa",
    "gn:population":0,
    "gn:timezone":"Asia/Yangon",
    "iso:country":"MM",
    "wof:name":"Ameikywa",
    "wof:placetype":"locality"
},
  "geometry": {"coordinates":[94.05861,20.69255],"type":"Point"}
}