{
  "type": "Feature",
  "properties": {
    "gn:admin1_code":"16.0",
    "gn:admin2_code":"MMR007D002",
    "gn:admin3_code":"MMR007014",
    "gn:asciiname":"Myozo Ashe",
    "gn:country_code":"MM",
    "gn:dem":42,
    "gn:feature_class":"P",
    "gn:feature_code":"PPL",
    "gn:name":"Myozo Ashe",
    "gn:population":0,
    "gn:timezone":"Asia/Yangon",
    "iso:country":"MM",
    "name:und_x_variant":[
        "Myozo",
        "Myozo Ashe"
    ],
    "wof:name":"Myozo Ashe",
    "wof:placetype":"locality"
},
  "geometry": {"coordinates":[96.44521,18.68414],"type":"Point"}
}