{
  "type": "Feature",
  "properties": {
    "gn:admin1_code":"11.0",
    "gn:admin2_code":"MMR015D006",
    "gn:admin3_code":"MMR015021",
    "gn:asciiname":"Man Na",
    "gn:country_code":"MM",
    "gn:dem":1111,
    "gn:feature_class":"P",
    "gn:feature_code":"PPL",
    "gn:name":"M\u0101n Na",
    "gn:population":0,
    "gn:timezone":"Asia/Yangon",
    "iso:country":"MM",
    "wof:name":"Man Na",
    "wof:placetype":"locality"
},
  "geometry": {"coordinates":[98.65089999999999,23.09975],"type":"Point"}
}