{
  "type": "Feature",
  "properties": {
    "gn:admin1_code":"1.0",
    "gn:admin2_code":"MMR012D005",
    "gn:admin3_code":"MMR012005",
    "gn:asciiname":"Helin",
    "gn:country_code":"MM",
    "gn:dem":188,
    "gn:feature_class":"P",
    "gn:feature_code":"PPL",
    "gn:name":"Helin",
    "gn:population":0,
    "gn:timezone":"Asia/Yangon",
    "iso:country":"MM",
    "name:bel_x_preferred":[
        "\u0425\u0435\u043b\u0456\u043d"
    ],
    "name:ceb_x_preferred":[
        "Helin"
    ],
    "name:chv_x_preferred":[
        "\u0425\u0435\u043b\u0438\u043d"
    ],
    "name:deu_x_preferred":[
        "Helin"
    ],
    "name:epo_x_preferred":[
        "Helin"
    ],
    "name:nno_x_preferred":[
        "Helin"
    ],
    "name:nor_x_preferred":[
        "Helin"
    ],
    "name:rus_x_preferred":[
        "\u0425\u0435\u043b\u0438\u043d"
    ],
    "name:ukr_x_preferred":[
        "\u0413\u0435\u043b\u0456\u043d"
    ],
    "wof:name":"Helin",
    "wof:placetype":"locality"
},
  "geometry": {"coordinates":[93.55539,20.61968],"type":"Point"}
}