{
  "type": "Feature",
  "properties": {
    "gn:admin1_code":"11.0",
    "gn:admin2_code":"MMR016D001",
    "gn:admin3_code":"MMR016003",
    "gn:asciiname":"Wan Ho-luep",
    "gn:country_code":"MM",
    "gn:dem":1429,
    "gn:feature_class":"P",
    "gn:feature_code":"PPL",
    "gn:name":"W\u0101n Ho-l\u00fcp",
    "gn:population":0,
    "gn:timezone":"Asia/Yangon",
    "iso:country":"MM",
    "wof:name":"Wan Ho-luep",
    "wof:placetype":"locality"
},
  "geometry": {"coordinates":[99.82637,21.81201],"type":"Point"}
}