{
  "type": "Feature",
  "properties": {
    "gn:admin1_code":"8.0",
    "gn:admin2_code":"MMR010D002",
    "gn:admin3_code":"MMR010009",
    "gn:asciiname":"Seiktha",
    "gn:country_code":"MM",
    "gn:dem":88,
    "gn:feature_class":"P",
    "gn:feature_code":"PPL",
    "gn:name":"Seiktha",
    "gn:population":0,
    "gn:timezone":"Asia/Yangon",
    "iso:country":"MM",
    "wof:name":"Seiktha",
    "wof:placetype":"locality"
},
  "geometry": {"coordinates":[96.17807999999999,22.24996],"type":"Point"}
}