{
  "type": "Feature",
  "properties": {
    "gn:admin1_code":"1.0",
    "gn:admin2_code":"MMR012D001",
    "gn:admin3_code":"MMR012007",
    "gn:asciiname":"Kyeinnebyin",
    "gn:country_code":"MM",
    "gn:dem":1,
    "gn:feature_class":"P",
    "gn:feature_code":"PPL",
    "gn:name":"Kyeinnebyin",
    "gn:population":0,
    "gn:timezone":"Asia/Yangon",
    "iso:country":"MM",
    "wof:name":"Kyeinnebyin",
    "wof:placetype":"locality"
},
  "geometry": {"coordinates":[93.01721999999999,20.09368],"type":"Point"}
}