{
  "type": "Feature",
  "properties": {
    "gn:admin1_code":"12.0",
    "gn:admin2_code":"MMR006D003",
    "gn:admin3_code":"MMR006009",
    "gn:asciiname":"Chawm He",
    "gn:country_code":"MM",
    "gn:dem":23,
    "gn:feature_class":"P",
    "gn:feature_code":"PPL",
    "gn:name":"Chawm H\u0113",
    "gn:population":0,
    "gn:timezone":"Asia/Yangon",
    "iso:country":"MM",
    "wof:name":"Chawm He",
    "wof:placetype":"locality"
},
  "geometry": {"coordinates":[98.77158,10.61109],"type":"Point"}
}