{
  "type": "Feature",
  "properties": {
    "gn:admin1_code":"8.0",
    "gn:admin2_code":"MMR010D004",
    "gn:admin3_code":"MMR010019",
    "gn:asciiname":"Myawadi",
    "gn:country_code":"MM",
    "gn:dem":248,
    "gn:feature_class":"P",
    "gn:feature_code":"PPL",
    "gn:name":"Myawadi",
    "gn:population":0,
    "gn:timezone":"Asia/Yangon",
    "iso:country":"MM",
    "wof:name":"Myawadi",
    "wof:placetype":"locality"
},
  "geometry": {"coordinates":[95.73921,21.57601],"type":"Point"}
}