{
  "type": "Feature",
  "properties": {
    "gn:admin1_code":"3.0",
    "gn:admin2_code":"MMR017D001",
    "gn:admin3_code":"MMR017001",
    "gn:asciiname":"Taunggadon",
    "gn:country_code":"MM",
    "gn:dem":10,
    "gn:feature_class":"P",
    "gn:feature_code":"PPL",
    "gn:name":"Taunggadon",
    "gn:population":0,
    "gn:timezone":"Asia/Yangon",
    "iso:country":"MM",
    "name:und_x_variant":[
        "Taunggadun",
        "Taunggadon"
    ],
    "wof:name":"Taunggadon",
    "wof:placetype":"locality"
},
  "geometry": {"coordinates":[94.45205,17.15305],"type":"Point"}
}