{
  "type": "Feature",
  "properties": {
    "gn:admin1_code":"4.0",
    "gn:admin2_code":"MMR001D003",
    "gn:admin3_code":"MMR001013",
    "gn:asciiname":"Man Kham",
    "gn:country_code":"MM",
    "gn:dem":131,
    "gn:feature_class":"P",
    "gn:feature_code":"PPL",
    "gn:name":"M\u0101n Kham",
    "gn:population":0,
    "gn:timezone":"Asia/Yangon",
    "iso:country":"MM",
    "name:und_x_variant":[
        "M\u0101n Kham"
    ],
    "wof:name":"Man Kham",
    "wof:placetype":"locality"
},
  "geometry": {"coordinates":[97.25189,24.11205],"type":"Point"}
}