{
  "type": "Feature",
  "properties": {
    "gn:admin1_code":"11.0",
    "gn:admin2_code":"MMR014D001",
    "gn:admin3_code":"MMR014010",
    "gn:asciiname":"Kaba",
    "gn:country_code":"MM",
    "gn:dem":1460,
    "gn:feature_class":"P",
    "gn:feature_code":"PPL",
    "gn:name":"Kaba",
    "gn:population":0,
    "gn:timezone":"Asia/Yangon",
    "iso:country":"MM",
    "name:ceb_x_preferred":[
        "Kaba"
    ],
    "name:deu_x_preferred":[
        "Kaba"
    ],
    "name:fin_x_preferred":[
        "Kaba"
    ],
    "name:fra_x_preferred":[
        "Kaba"
    ],
    "name:hrv_x_preferred":[
        "Kaba"
    ],
    "name:swe_x_preferred":[
        "Kaba"
    ],
    "name:und_x_variant":[
        "Kaba-Aye",
        "Kaba"
    ],
    "wof:name":"Kaba",
    "wof:placetype":"locality"
},
  "geometry": {"coordinates":[96.86826000000001,19.71472],"type":"Point"}
}