{
  "type": "Feature",
  "properties": {
    "gn:admin1_code":"12.0",
    "gn:admin2_code":"MMR006D002",
    "gn:admin3_code":"MMR006008",
    "gn:asciiname":"Maso",
    "gn:country_code":"MM",
    "gn:dem":15,
    "gn:feature_class":"P",
    "gn:feature_code":"PPL",
    "gn:name":"Maso",
    "gn:population":0,
    "gn:timezone":"Asia/Yangon",
    "iso:country":"MM",
    "name:bul_x_preferred":[
        "\u041c\u0430\u0437\u043e\u043d"
    ],
    "name:ceb_x_preferred":[
        "Maso"
    ],
    "name:deu_x_preferred":[
        "Maso"
    ],
    "name:fra_x_preferred":[
        "Maso"
    ],
    "name:ita_x_preferred":[
        "Maso"
    ],
    "name:rus_x_preferred":[
        "\u041c\u0430\u0441\u043e"
    ],
    "name:spa_x_preferred":[
        "Maso"
    ],
    "name:srp_x_preferred":[
        "Maso"
    ],
    "name:swe_x_preferred":[
        "Maso"
    ],
    "wof:name":"Maso",
    "wof:placetype":"locality"
},
  "geometry": {"coordinates":[99.08386,12.24043],"type":"Point"}
}