{
  "type": "Feature",
  "properties": {
    "gn:admin1_code":"15.0",
    "gn:admin2_code":"MMR009D003",
    "gn:admin3_code":"MMR009014",
    "gn:asciiname":"Yebok",
    "gn:country_code":"MM",
    "gn:dem":180,
    "gn:feature_class":"P",
    "gn:feature_code":"PPL",
    "gn:name":"Yebok",
    "gn:population":0,
    "gn:timezone":"Asia/Yangon",
    "iso:country":"MM",
    "wof:name":"Yebok",
    "wof:placetype":"locality"
},
  "geometry": {"coordinates":[94.67695999999999,19.58345],"type":"Point"}
}