{
  "type": "Feature",
  "properties": {
    "gn:admin1_code":"11.0",
    "gn:admin2_code":"MMR016D003",
    "gn:admin3_code":"MMR016009",
    "gn:asciiname":"Wan Hpya-longhkoenhkamlue",
    "gn:country_code":"MM",
    "gn:dem":876,
    "gn:feature_class":"P",
    "gn:feature_code":"PPL",
    "gn:name":"W\u0101n Hpya-l\u014dnghk\u00f6nhkaml\u00fc",
    "gn:population":0,
    "gn:timezone":"Asia/Yangon",
    "iso:country":"MM",
    "wof:name":"Wan Hpya-longhkoenhkamlue",
    "wof:placetype":"locality"
},
  "geometry": {"coordinates":[100.28297000000001,20.98814],"type":"Point"}
}