{
  "type": "Feature",
  "properties": {
    "gn:admin1_code":"11.0",
    "gn:admin2_code":"MMR015D003",
    "gn:admin3_code":"MMR015014",
    "gn:asciiname":"Nawnghkio",
    "gn:country_code":"MM",
    "gn:dem":581,
    "gn:feature_class":"P",
    "gn:feature_code":"PPL",
    "gn:name":"Nawnghkio",
    "gn:population":0,
    "gn:timezone":"Asia/Yangon",
    "iso:country":"MM",
    "wof:name":"Nawnghkio",
    "wof:placetype":"locality"
},
  "geometry": {"coordinates":[97.32380000000001,22.45687],"type":"Point"}
}