{
  "type": "Feature",
  "properties": {
    "gn:admin1_code":"11.0",
    "gn:admin2_code":"MMR015D002",
    "gn:admin3_code":"MMR015009",
    "gn:asciiname":"Man Kang",
    "gn:country_code":"MM",
    "gn:dem":1538,
    "gn:feature_class":"P",
    "gn:feature_code":"PPL",
    "gn:name":"M\u0101n Kang",
    "gn:population":0,
    "gn:timezone":"Asia/Yangon",
    "iso:country":"MM",
    "wof:name":"Man Kang",
    "wof:placetype":"locality"
},
  "geometry": {"coordinates":[98.27943999999999,24.06593],"type":"Point"}
}