{
  "type": "Feature",
  "properties": {
    "gn:admin1_code":"15.0",
    "gn:admin2_code":"MMR009D004",
    "gn:admin3_code":"MMR009019",
    "gn:asciiname":"Kyaukka",
    "gn:country_code":"MM",
    "gn:dem":124,
    "gn:feature_class":"P",
    "gn:feature_code":"PPL",
    "gn:name":"Kyaukka",
    "gn:population":0,
    "gn:timezone":"Asia/Yangon",
    "iso:country":"MM",
    "wof:name":"Kyaukka",
    "wof:placetype":"locality"
},
  "geometry": {"coordinates":[95.15000000000001,21.58333],"type":"Point"}
}