{
  "type": "Feature",
  "properties": {
    "gn:admin1_code":"11.0",
    "gn:admin2_code":"MMR015D003",
    "gn:admin3_code":"MMR015012",
    "gn:asciiname":"Kunkaw",
    "gn:country_code":"MM",
    "gn:dem":997,
    "gn:feature_class":"P",
    "gn:feature_code":"PPL",
    "gn:name":"Kunkaw",
    "gn:population":0,
    "gn:timezone":"Asia/Yangon",
    "iso:country":"MM",
    "wof:name":"Kunkaw",
    "wof:placetype":"locality"
},
  "geometry": {"coordinates":[97.07687,22.66341],"type":"Point"}
}