{
  "type": "Feature",
  "properties": {
    "gn:admin1_code":"11.0",
    "gn:admin2_code":"MMR014D001",
    "gn:admin3_code":"MMR014009",
    "gn:asciiname":"Hsaungkhe",
    "gn:country_code":"MM",
    "gn:dem":1311,
    "gn:feature_class":"P",
    "gn:feature_code":"PPL",
    "gn:name":"Hsaungkhe",
    "gn:population":0,
    "gn:timezone":"Asia/Yangon",
    "iso:country":"MM",
    "wof:name":"Hsaungkhe",
    "wof:placetype":"locality"
},
  "geometry": {"coordinates":[96.79497000000001,19.91345],"type":"Point"}
}