{
  "type": "Feature",
  "properties": {
    "gn:admin1_code":"10.0",
    "gn:admin2_code":"MMR005D009",
    "gn:admin3_code":"MMR005016",
    "gn:asciiname":"Aungchantha",
    "gn:country_code":"MM",
    "gn:dem":81,
    "gn:feature_class":"P",
    "gn:feature_code":"PPL",
    "gn:name":"Aungchantha",
    "gn:population":0,
    "gn:timezone":"Asia/Yangon",
    "iso:country":"MM",
    "wof:name":"Aungchantha",
    "wof:placetype":"locality"
},
  "geometry": {"coordinates":[95.05226999999999,22.15337],"type":"Point"}
}