{
  "type": "Feature",
  "properties": {
    "gn:admin1_code":"15.0",
    "gn:admin2_code":"MMR009D004",
    "gn:admin3_code":"MMR009018",
    "gn:asciiname":"Kyunyogyi",
    "gn:country_code":"MM",
    "gn:dem":63,
    "gn:feature_class":"P",
    "gn:feature_code":"PPL",
    "gn:name":"Kyunyogyi",
    "gn:population":0,
    "gn:timezone":"Asia/Yangon",
    "iso:country":"MM",
    "name:und_x_variant":[
        "Kyunnyogyi",
        "Kyunyogyi"
    ],
    "wof:name":"Kyunyogyi",
    "wof:placetype":"locality"
},
  "geometry": {"coordinates":[95.01591999999999,21.31122],"type":"Point"}
}