{
  "type": "Feature",
  "properties": {
    "gn:admin1_code":"11.0",
    "gn:admin2_code":"MMR016D001",
    "gn:admin3_code":"MMR016001",
    "gn:asciiname":"Wan Tungong",
    "gn:country_code":"MM",
    "gn:dem":913,
    "gn:feature_class":"P",
    "gn:feature_code":"PPL",
    "gn:name":"W\u0101n Tungong",
    "gn:population":0,
    "gn:timezone":"Asia/Yangon",
    "iso:country":"MM",
    "name:und_x_variant":[
        "W\u0101n Tungl\u00f6ng",
        "W\u0101n Tungong"
    ],
    "wof:name":"Wan Tungong",
    "wof:placetype":"locality"
},
  "geometry": {"coordinates":[99.69811,21.0806],"type":"Point"}
}