{
  "type": "Feature",
  "properties": {
    "gn:admin1_code":"3.0",
    "gn:admin2_code":"MMR017D002",
    "gn:admin3_code":"MMR017012",
    "gn:asciiname":"Chinywagyi",
    "gn:country_code":"MM",
    "gn:dem":53,
    "gn:feature_class":"P",
    "gn:feature_code":"PPL",
    "gn:name":"Chinywagyi",
    "gn:population":0,
    "gn:timezone":"Asia/Yangon",
    "iso:country":"MM",
    "wof:name":"Chinywagyi",
    "wof:placetype":"locality"
},
  "geometry": {"coordinates":[95.11953,18.17605],"type":"Point"}
}