{
  "type": "Feature",
  "properties": {
    "gn:admin1_code":"11.0",
    "gn:admin2_code":"MMR015D001",
    "gn:admin3_code":"MMR015004",
    "gn:asciiname":"Man Ta-pi",
    "gn:country_code":"MM",
    "gn:dem":867,
    "gn:feature_class":"P",
    "gn:feature_code":"PPL",
    "gn:name":"M\u0101n Ta-pi",
    "gn:population":0,
    "gn:timezone":"Asia/Yangon",
    "iso:country":"MM",
    "wof:name":"Man Ta-pi",
    "wof:placetype":"locality"
},
  "geometry": {"coordinates":[98.31749000000001,22.21835],"type":"Point"}
}