{
  "type": "Feature",
  "properties": {
    "gn:admin1_code":"12.0",
    "gn:admin2_code":"MMR006D003",
    "gn:admin3_code":"MMR006010",
    "gn:asciiname":"Thaungyah",
    "gn:country_code":"MM",
    "gn:dem":38,
    "gn:feature_class":"P",
    "gn:feature_code":"PPL",
    "gn:name":"Thaungyah",
    "gn:population":0,
    "gn:timezone":"Asia/Yangon",
    "iso:country":"MM",
    "name:und_x_variant":[
        "Taung-ya Ywa",
        "Thaungyah"
    ],
    "wof:name":"Thaungyah",
    "wof:placetype":"locality"
},
  "geometry": {"coordinates":[98.73854,11.36226],"type":"Point"}
}