{
  "type": "Feature",
  "properties": {
    "gn:admin1_code":"15.0",
    "gn:admin2_code":"MMR009D003",
    "gn:admin3_code":"MMR009017",
    "gn:asciiname":"Gyogon",
    "gn:country_code":"MM",
    "gn:dem":148,
    "gn:feature_class":"P",
    "gn:feature_code":"PPL",
    "gn:name":"Gyogon",
    "gn:population":0,
    "gn:timezone":"Asia/Yangon",
    "iso:country":"MM",
    "wof:name":"Gyogon",
    "wof:placetype":"locality"
},
  "geometry": {"coordinates":[95.43113,19.49705],"type":"Point"}
}