{
  "type": "Feature",
  "properties": {
    "gn:admin1_code":"11.0",
    "gn:admin2_code":"MMR014D001",
    "gn:admin3_code":"MMR014009",
    "gn:asciiname":"Sapbo",
    "gn:country_code":"MM",
    "gn:dem":1292,
    "gn:feature_class":"P",
    "gn:feature_code":"PPL",
    "gn:name":"Sapbo",
    "gn:population":0,
    "gn:timezone":"Asia/Yangon",
    "iso:country":"MM",
    "wof:name":"Sapbo",
    "wof:placetype":"locality"
},
  "geometry": {"coordinates":[96.65818,20.18884],"type":"Point"}
}