{
  "type": "Feature",
  "properties": {
    "gn:admin1_code":"11.0",
    "gn:admin2_code":"MMR014D001",
    "gn:admin3_code":"MMR014007",
    "gn:asciiname":"Wetkabu",
    "gn:country_code":"MM",
    "gn:dem":1228,
    "gn:feature_class":"P",
    "gn:feature_code":"PPL",
    "gn:name":"Wetkabu",
    "gn:population":0,
    "gn:timezone":"Asia/Yangon",
    "iso:country":"MM",
    "wof:name":"Wetkabu",
    "wof:placetype":"locality"
},
  "geometry": {"coordinates":[96.51743999999999,21.12368],"type":"Point"}
}