{
  "type": "Feature",
  "properties": {
    "gn:admin1_code":"3.0",
    "gn:admin2_code":"MMR017D006",
    "gn:admin3_code":"MMR017026",
    "gn:asciiname":"Hmawbi",
    "gn:country_code":"MM",
    "gn:dem":8,
    "gn:feature_class":"P",
    "gn:feature_code":"PPL",
    "gn:name":"Hmawbi",
    "gn:population":0,
    "gn:timezone":"Asia/Yangon",
    "iso:country":"MM",
    "wof:name":"Hmawbi",
    "wof:placetype":"locality"
},
  "geometry": {"coordinates":[95.93536,16.3523],"type":"Point"}
}