{
  "type": "Feature",
  "properties": {
    "gn:admin1_code":"3.0",
    "gn:admin2_code":"MMR017D004",
    "gn:admin3_code":"MMR017016",
    "gn:asciiname":"Bogon",
    "gn:country_code":"MM",
    "gn:dem":11,
    "gn:feature_class":"P",
    "gn:feature_code":"PPL",
    "gn:name":"Bog\u00f4n",
    "gn:population":0,
    "gn:timezone":"Asia/Yangon",
    "iso:country":"MM",
    "name:ceb_x_preferred":[
        "Bogon"
    ],
    "wof:name":"Bogon",
    "wof:placetype":"locality"
},
  "geometry": {"coordinates":[94.76694999999999,15.98485],"type":"Point"}
}