{
  "type": "Feature",
  "properties": {
    "gn:admin1_code":"11.0",
    "gn:admin2_code":"MMR015D001",
    "gn:admin3_code":"MMR015002",
    "gn:asciiname":"Namhkam",
    "gn:country_code":"MM",
    "gn:dem":677,
    "gn:feature_class":"P",
    "gn:feature_code":"PPL",
    "gn:name":"Namhkam",
    "gn:population":0,
    "gn:timezone":"Asia/Yangon",
    "iso:country":"MM",
    "wof:name":"Namhkam",
    "wof:placetype":"locality"
},
  "geometry": {"coordinates":[98.03851,23.28037],"type":"Point"}
}