{
  "type": "Feature",
  "properties": {
    "gn:admin1_code":"6.0",
    "gn:admin2_code":"MMR002D002",
    "gn:admin3_code":"MMR002005",
    "gn:asciiname":"Wanpla Wankong",
    "gn:country_code":"MM",
    "gn:dem":154,
    "gn:feature_class":"P",
    "gn:feature_code":"PPL",
    "gn:name":"W\u0101npla W\u0101nkong",
    "gn:population":0,
    "gn:timezone":"Asia/Yangon",
    "iso:country":"MM",
    "wof:name":"Wanpla Wankong",
    "wof:placetype":"locality"
},
  "geometry": {"coordinates":[97.46796999999999,19.02658],"type":"Point"}
}