{
  "type": "Feature",
  "properties": {
    "gn:admin1_code":"6.0",
    "gn:admin2_code":"MMR002D001",
    "gn:admin3_code":"MMR002004",
    "gn:asciiname":"Wan Hwe-hpakkat-nok",
    "gn:country_code":"MM",
    "gn:dem":478,
    "gn:feature_class":"P",
    "gn:feature_code":"PPL",
    "gn:name":"W\u0101n Hw\u00e8-hpakkat-n\u014dk",
    "gn:population":0,
    "gn:timezone":"Asia/Yangon",
    "iso:country":"MM",
    "name:und_x_variant":[
        "Wan Hwe-hpak-kat-nek",
        "W\u0101n Hw\u00e8-hpakkat-n\u014dk"
    ],
    "wof:name":"Wan Hwe-hpakkat-nok",
    "wof:placetype":"locality"
},
  "geometry": {"coordinates":[97.74191999999999,19.44443],"type":"Point"}
}