{
  "type": "Feature",
  "properties": {
    "gn:admin1_code":"11.0",
    "gn:admin2_code":"MMR014D002",
    "gn:admin3_code":"MMR014011",
    "gn:asciiname":"Nawnghwe",
    "gn:country_code":"MM",
    "gn:dem":1099,
    "gn:feature_class":"P",
    "gn:feature_code":"PPL",
    "gn:name":"Nawnghwe",
    "gn:population":0,
    "gn:timezone":"Asia/Yangon",
    "iso:country":"MM",
    "wof:name":"Nawnghwe",
    "wof:placetype":"locality"
},
  "geometry": {"coordinates":[97.42592999999999,20.63048],"type":"Point"}
}