{
  "type": "Feature",
  "properties": {
    "gn:admin1_code":"16.0",
    "gn:admin2_code":"MMR007D002",
    "gn:admin3_code":"MMR007012",
    "gn:asciiname":"Le-einzu",
    "gn:country_code":"MM",
    "gn:dem":59,
    "gn:feature_class":"P",
    "gn:feature_code":"PPL",
    "gn:name":"Le-einzu",
    "gn:population":0,
    "gn:timezone":"Asia/Yangon",
    "iso:country":"MM",
    "name:und_x_variant":[
        "Lesinzu",
        "Le-einzu"
    ],
    "wof:name":"Le-einzu",
    "wof:placetype":"locality"
},
  "geometry": {"coordinates":[96.40783,18.49259],"type":"Point"}
}