{
  "type": "Feature",
  "properties": {
    "gn:admin1_code":"11.0",
    "gn:admin2_code":"MMR014D002",
    "gn:admin3_code":"MMR014012",
    "gn:asciiname":"Hona",
    "gn:country_code":"MM",
    "gn:dem":1377,
    "gn:feature_class":"P",
    "gn:feature_code":"PPL",
    "gn:name":"Hon\u0101",
    "gn:population":0,
    "gn:timezone":"Asia/Yangon",
    "iso:country":"MM",
    "wof:name":"Hona",
    "wof:placetype":"locality"
},
  "geometry": {"coordinates":[97.4538,21.2941],"type":"Point"}
}