{
  "type": "Feature",
  "properties": {
    "gn:admin1_code":"6.0",
    "gn:admin2_code":"MMR002D001",
    "gn:admin3_code":"MMR002002",
    "gn:asciiname":"Hko-ri-hku",
    "gn:country_code":"MM",
    "gn:dem":940,
    "gn:feature_class":"P",
    "gn:feature_code":"PPL",
    "gn:name":"Hko-ri-hku",
    "gn:population":0,
    "gn:timezone":"Asia/Yangon",
    "iso:country":"MM",
    "wof:name":"Hko-ri-hku",
    "wof:placetype":"locality"
},
  "geometry": {"coordinates":[97.08387,19.48096],"type":"Point"}
}