{
  "type": "Feature",
  "properties": {
    "gn:admin1_code":"16.0",
    "gn:admin2_code":"MMR007D002",
    "gn:admin3_code":"MMR007014",
    "gn:asciiname":"Zalokkyi",
    "gn:country_code":"MM",
    "gn:dem":32,
    "gn:feature_class":"P",
    "gn:feature_code":"PPL",
    "gn:name":"Zalokkyi",
    "gn:population":0,
    "gn:timezone":"Asia/Yangon",
    "iso:country":"MM",
    "wof:name":"Zalokkyi",
    "wof:placetype":"locality"
},
  "geometry": {"coordinates":[96.52694,18.59371],"type":"Point"}
}