{
  "type": "Feature",
  "properties": {
    "gn:admin1_code":"15.0",
    "gn:admin2_code":"MMR009D005",
    "gn:admin3_code":"MMR009025",
    "gn:asciiname":"Kyauk-a",
    "gn:country_code":"MM",
    "gn:dem":542,
    "gn:feature_class":"P",
    "gn:feature_code":"PPL",
    "gn:name":"Kyauk-a",
    "gn:population":0,
    "gn:timezone":"Asia/Yangon",
    "iso:country":"MM",
    "wof:name":"Kyauk-a",
    "wof:placetype":"locality"
},
  "geometry": {"coordinates":[94.10395,20.91868],"type":"Point"}
}