{
  "type": "Feature",
  "properties": {
    "gn:admin1_code":"3.0",
    "gn:admin2_code":"MMR017D005",
    "gn:admin3_code":"MMR017020",
    "gn:asciiname":"Negawla-aze",
    "gn:country_code":"MM",
    "gn:dem":3,
    "gn:feature_class":"P",
    "gn:feature_code":"PPL",
    "gn:name":"Negawla-aze",
    "gn:population":0,
    "gn:timezone":"Asia/Yangon",
    "iso:country":"MM",
    "wof:name":"Negawla-aze",
    "wof:placetype":"locality"
},
  "geometry": {"coordinates":[95.32666999999999,16.87323],"type":"Point"}
}