{
  "type": "Feature",
  "properties": {
    "gn:admin1_code":"4.0",
    "gn:admin2_code":"MMR001D004",
    "gn:admin3_code":"MMR001018",
    "gn:asciiname":"Hpawlum",
    "gn:country_code":"MM",
    "gn:dem":1163,
    "gn:feature_class":"P",
    "gn:feature_code":"PPL",
    "gn:name":"Hpawlum",
    "gn:population":0,
    "gn:timezone":"Asia/Yangon",
    "iso:country":"MM",
    "name:und_x_variant":[
        "Hpawtum",
        "Hpawlum"
    ],
    "wof:name":"Hpawlum",
    "wof:placetype":"locality"
},
  "geometry": {"coordinates":[98.20641000000001,27.21134],"type":"Point"}
}