{
  "type": "Feature",
  "properties": {
    "gn:admin1_code":"11.0",
    "gn:admin2_code":"MMR014D001",
    "gn:admin3_code":"MMR014004",
    "gn:asciiname":"Na Hsan",
    "gn:country_code":"MM",
    "gn:dem":1166,
    "gn:feature_class":"P",
    "gn:feature_code":"PPL",
    "gn:name":"Na Hsan",
    "gn:population":0,
    "gn:timezone":"Asia/Yangon",
    "iso:country":"MM",
    "wof:name":"Na Hsan",
    "wof:placetype":"locality"
},
  "geometry": {"coordinates":[97.30318,20.50708],"type":"Point"}
}