{
  "type": "Feature",
  "properties": {
    "gn:admin1_code":"4.0",
    "gn:admin2_code":"MMR001D004",
    "gn:admin3_code":"MMR001015",
    "gn:asciiname":"Ta-ngun Ga",
    "gn:country_code":"MM",
    "gn:dem":658,
    "gn:feature_class":"P",
    "gn:feature_code":"PPL",
    "gn:name":"Ta-ngun Ga",
    "gn:population":0,
    "gn:timezone":"Asia/Yangon",
    "iso:country":"MM",
    "wof:name":"Ta-ngun Ga",
    "wof:placetype":"locality"
},
  "geometry": {"coordinates":[97.81653,26.74832],"type":"Point"}
}