{
  "type": "Feature",
  "properties": {
    "gn:admin1_code":"8.0",
    "gn:admin2_code":"MMR010D004",
    "gn:admin3_code":"MMR010018",
    "gn:asciiname":"Teya",
    "gn:country_code":"MM",
    "gn:dem":157,
    "gn:feature_class":"P",
    "gn:feature_code":"PPL",
    "gn:name":"Teya",
    "gn:population":0,
    "gn:timezone":"Asia/Yangon",
    "iso:country":"MM",
    "name:ceb_x_preferred":[
        "Teya"
    ],
    "name:deu_x_preferred":[
        "Teya"
    ],
    "name:spa_x_preferred":[
        "Teya"
    ],
    "name:swe_x_preferred":[
        "Teya"
    ],
    "wof:name":"Teya",
    "wof:placetype":"locality"
},
  "geometry": {"coordinates":[95.40433,21.1707],"type":"Point"}
}