{
  "type": "Feature",
  "properties": {
    "gn:admin1_code":"6.0",
    "gn:admin2_code":"MMR002D002",
    "gn:admin3_code":"MMR002006",
    "gn:asciiname":"Papu",
    "gn:country_code":"MM",
    "gn:dem":157,
    "gn:feature_class":"P",
    "gn:feature_code":"PPL",
    "gn:name":"Papu",
    "gn:population":0,
    "gn:timezone":"Asia/Yangon",
    "iso:country":"MM",
    "wof:name":"Papu",
    "wof:placetype":"locality"
},
  "geometry": {"coordinates":[97.31958,18.89618],"type":"Point"}
}