{
  "type": "Feature",
  "properties": {
    "gn:admin1_code":"15.0",
    "gn:admin2_code":"MMR009D004",
    "gn:admin3_code":"MMR009022",
    "gn:asciiname":"Paukkon",
    "gn:country_code":"MM",
    "gn:dem":217,
    "gn:feature_class":"P",
    "gn:feature_code":"PPL",
    "gn:name":"Paukk\u00f4n",
    "gn:population":0,
    "gn:timezone":"Asia/Yangon",
    "iso:country":"MM",
    "wof:name":"Paukkon",
    "wof:placetype":"locality"
},
  "geometry": {"coordinates":[94.3995,20.91926],"type":"Point"}
}