{
  "type": "Feature",
  "properties": {
    "gn:admin1_code":"4.0",
    "gn:admin2_code":"MMR001D002",
    "gn:admin3_code":"MMR001009",
    "gn:asciiname":"Tanggon",
    "gn:country_code":"MM",
    "gn:dem":259,
    "gn:feature_class":"P",
    "gn:feature_code":"PPL",
    "gn:name":"T\u0101ngg\u00f4n",
    "gn:population":0,
    "gn:timezone":"Asia/Yangon",
    "iso:country":"MM",
    "wof:name":"Tanggon",
    "wof:placetype":"locality"
},
  "geometry": {"coordinates":[96.35899999999999,25.65941],"type":"Point"}
}