{
  "type": "Feature",
  "properties": {
    "gn:admin1_code":"4.0",
    "gn:admin2_code":"MMR001D001",
    "gn:admin3_code":"MMR001002",
    "gn:asciiname":"Naru",
    "gn:country_code":"MM",
    "gn:dem":1360,
    "gn:feature_class":"P",
    "gn:feature_code":"PPL",
    "gn:name":"Naru",
    "gn:population":0,
    "gn:timezone":"Asia/Yangon",
    "iso:country":"MM",
    "name:ceb_x_preferred":[
        "Naru"
    ],
    "name:fra_x_preferred":[
        "Naru"
    ],
    "name:nld_x_preferred":[
        "Naru"
    ],
    "name:scn_x_preferred":[
        "Naru"
    ],
    "name:swe_x_preferred":[
        "Naru"
    ],
    "name:tha_x_preferred":[
        "\u0e19\u0e32\u0e23\u0e38"
    ],
    "wof:name":"Naru",
    "wof:placetype":"locality"
},
  "geometry": {"coordinates":[97.70937000000001,24.97023],"type":"Point"}
}