{
  "type": "Feature",
  "properties": {
    "gn:admin1_code":"6.0",
    "gn:admin2_code":"MMR002D001",
    "gn:admin3_code":"MMR002002",
    "gn:asciiname":"Ma-hkawse",
    "gn:country_code":"MM",
    "gn:dem":893,
    "gn:feature_class":"P",
    "gn:feature_code":"PPL",
    "gn:name":"Ma-hkaws\u00e8",
    "gn:population":0,
    "gn:timezone":"Asia/Yangon",
    "iso:country":"MM",
    "wof:name":"Ma-hkawse",
    "wof:placetype":"locality"
},
  "geometry": {"coordinates":[97.13749,19.60672000000001],"type":"Point"}
}