{
  "type": "Feature",
  "properties": {
    "gn:admin1_code":"1.0",
    "gn:admin2_code":"MMR012D001",
    "gn:admin3_code":"MMR012007",
    "gn:asciiname":"Thalondaung",
    "gn:country_code":"MM",
    "gn:dem":2,
    "gn:feature_class":"P",
    "gn:feature_code":"PPL",
    "gn:name":"Thalondaung",
    "gn:population":0,
    "gn:timezone":"Asia/Yangon",
    "iso:country":"MM",
    "name:und_x_variant":[
        "Thalandong",
        "Thalondaung"
    ],
    "wof:name":"Thalondaung",
    "wof:placetype":"locality"
},
  "geometry": {"coordinates":[93.11463999999999,20.09147],"type":"Point"}
}