{
  "type": "Feature",
  "properties": {
    "gn:admin1_code":"15.0",
    "gn:admin2_code":"MMR009D004",
    "gn:admin3_code":"MMR009021",
    "gn:asciiname":"Thanbya-aing",
    "gn:country_code":"MM",
    "gn:dem":145,
    "gn:feature_class":"P",
    "gn:feature_code":"PPL",
    "gn:name":"Thanbya-aing",
    "gn:population":0,
    "gn:timezone":"Asia/Yangon",
    "iso:country":"MM",
    "wof:name":"Thanbya-aing",
    "wof:placetype":"locality"
},
  "geometry": {"coordinates":[94.56874000000001,21.44099],"type":"Point"}
}