{
  "type": "Feature",
  "properties": {
    "gn:admin1_code":"11.0",
    "gn:admin2_code":"MMR016D001",
    "gn:admin3_code":"MMR016001",
    "gn:asciiname":"Wan Namkhet",
    "gn:country_code":"MM",
    "gn:dem":1823,
    "gn:feature_class":"P",
    "gn:feature_code":"PPL",
    "gn:name":"W\u0101n Namkh\u0113t",
    "gn:population":0,
    "gn:timezone":"Asia/Yangon",
    "iso:country":"MM",
    "name:und_x_variant":[
        "W\u0101n Kaw Namkhet",
        "W\u0101n Namkh\u0113t"
    ],
    "wof:name":"Wan Namkhet",
    "wof:placetype":"locality"
},
  "geometry": {"coordinates":[99.89286,21.27457],"type":"Point"}
}