{
  "type": "Feature",
  "properties": {
    "gn:admin1_code":"11.0",
    "gn:admin2_code":"MMR014D001",
    "gn:admin3_code":"MMR014008",
    "gn:asciiname":"Pan-ainggon",
    "gn:country_code":"MM",
    "gn:dem":825,
    "gn:feature_class":"P",
    "gn:feature_code":"PPL",
    "gn:name":"Pan-ainggon",
    "gn:population":0,
    "gn:timezone":"Asia/Yangon",
    "iso:country":"MM",
    "wof:name":"Pan-ainggon",
    "wof:placetype":"locality"
},
  "geometry": {"coordinates":[96.97068,21.78444],"type":"Point"}
}