{
  "type": "Feature",
  "properties": {
    "gn:admin1_code":"5.0",
    "gn:admin2_code":"MMR003D002",
    "gn:admin3_code":"MMR003005",
    "gn:asciiname":"Mipa",
    "gn:country_code":"MM",
    "gn:dem":260,
    "gn:feature_class":"P",
    "gn:feature_code":"PPL",
    "gn:name":"Mipa",
    "gn:population":0,
    "gn:timezone":"Asia/Yangon",
    "iso:country":"MM",
    "name:und_x_variant":[
        "Miba",
        "Mina",
        "Mipa"
    ],
    "wof:name":"Mipa",
    "wof:placetype":"locality"
},
  "geometry": {"coordinates":[98.64963,16.36965],"type":"Point"}
}