{
  "type": "Feature",
  "properties": {
    "gn:admin1_code":"16.0",
    "gn:admin2_code":"MMR007D002",
    "gn:admin3_code":"MMR007009",
    "gn:asciiname":"Mawa",
    "gn:country_code":"MM",
    "gn:dem":56,
    "gn:feature_class":"P",
    "gn:feature_code":"PPL",
    "gn:name":"Mawa",
    "gn:population":0,
    "gn:timezone":"Asia/Yangon",
    "iso:country":"MM",
    "name:ceb_x_preferred":[
        "Mawa"
    ],
    "name:fra_x_preferred":[
        "Mawa"
    ],
    "name:swe_x_preferred":[
        "Mawa"
    ],
    "wof:name":"Mawa",
    "wof:placetype":"locality"
},
  "geometry": {"coordinates":[96.42055999999999,19.0989],"type":"Point"}
}