{
  "type": "Feature",
  "properties": {
    "gn:admin1_code":"11.0",
    "gn:admin2_code":"MMR015D003",
    "gn:admin3_code":"MMR015013",
    "gn:asciiname":"Taung-gaung-bwe",
    "gn:country_code":"MM",
    "gn:dem":750,
    "gn:feature_class":"P",
    "gn:feature_code":"PPL",
    "gn:name":"Taung-gaung-bwe",
    "gn:population":0,
    "gn:timezone":"Asia/Yangon",
    "iso:country":"MM",
    "name:und_x_variant":[
        "Taung-Kaung-pwa",
        "Taung-gaung-bwe"
    ],
    "wof:name":"Taung-gaung-bwe",
    "wof:placetype":"locality"
},
  "geometry": {"coordinates":[96.64225,22.24706],"type":"Point"}
}