{
  "type": "Feature",
  "properties": {
    "gn:admin1_code":"4.0",
    "gn:admin2_code":"MMR001D004",
    "gn:admin3_code":"MMR001015",
    "gn:asciiname":"'Nbang Ga",
    "gn:country_code":"MM",
    "gn:dem":611,
    "gn:feature_class":"P",
    "gn:feature_code":"PPL",
    "gn:name":"\u2019Nbang Ga",
    "gn:population":0,
    "gn:timezone":"Asia/Yangon",
    "iso:country":"MM",
    "wof:name":"'Nbang Ga",
    "wof:placetype":"locality"
},
  "geometry": {"coordinates":[97.46458,26.61169000000001],"type":"Point"}
}