{
  "type": "Feature",
  "properties": {
    "gn:admin1_code":"10.0",
    "gn:admin2_code":"MMR005D002",
    "gn:admin3_code":"MMR005004",
    "gn:asciiname":"Tagantha",
    "gn:country_code":"MM",
    "gn:dem":121,
    "gn:feature_class":"P",
    "gn:feature_code":"PPL",
    "gn:name":"Tagantha",
    "gn:population":0,
    "gn:timezone":"Asia/Yangon",
    "iso:country":"MM",
    "wof:name":"Tagantha",
    "wof:placetype":"locality"
},
  "geometry": {"coordinates":[95.79376000000001,22.52685],"type":"Point"}
}