{
  "type": "Feature",
  "properties": {
    "gn:admin1_code":"4.0",
    "gn:admin2_code":"MMR001D002",
    "gn:admin3_code":"MMR001009",
    "gn:asciiname":"Maran",
    "gn:country_code":"MM",
    "gn:dem":278,
    "gn:feature_class":"P",
    "gn:feature_code":"PPL",
    "gn:name":"Maran",
    "gn:population":0,
    "gn:timezone":"Asia/Yangon",
    "iso:country":"MM",
    "name:fra_x_preferred":[
        "Maran"
    ],
    "name:heb_x_preferred":[
        "\u05de\u05e8\u05df"
    ],
    "name:lad_x_preferred":[
        "Maran"
    ],
    "name:spa_x_preferred":[
        "Maran"
    ],
    "name:vie_x_preferred":[
        "Maran"
    ],
    "wof:name":"Maran",
    "wof:placetype":"locality"
},
  "geometry": {"coordinates":[96.69701000000001,25.7142],"type":"Point"}
}