{
  "type": "Feature",
  "properties": {
    "gn:admin1_code":"6.0",
    "gn:admin2_code":"MMR002D001",
    "gn:admin3_code":"MMR002004",
    "gn:asciiname":"Hsop Me-la-yu",
    "gn:country_code":"MM",
    "gn:dem":129,
    "gn:feature_class":"P",
    "gn:feature_code":"PPL",
    "gn:name":"Hs\u014dp M\u00e8-la-yu",
    "gn:population":0,
    "gn:timezone":"Asia/Yangon",
    "iso:country":"MM",
    "wof:name":"Hsop Me-la-yu",
    "wof:placetype":"locality"
},
  "geometry": {"coordinates":[97.60278,19.49583],"type":"Point"}
}