{
  "type": "Feature",
  "properties": {
    "gn:admin1_code":"3.0",
    "gn:admin2_code":"MMR017D001",
    "gn:admin3_code":"MMR017007",
    "gn:asciiname":"Daunggyi",
    "gn:country_code":"MM",
    "gn:dem":10,
    "gn:feature_class":"P",
    "gn:feature_code":"PPL",
    "gn:name":"Daunggyi",
    "gn:population":0,
    "gn:timezone":"Asia/Yangon",
    "iso:country":"MM",
    "name:und_x_variant":[
        "Daunggy",
        "Daunggyi"
    ],
    "wof:name":"Daunggyi",
    "wof:placetype":"locality"
},
  "geometry": {"coordinates":[95.19266,16.99905],"type":"Point"}
}