{
  "type": "Feature",
  "properties": {
    "gn:admin1_code":"11.0",
    "gn:admin2_code":"MMR015D006",
    "gn:admin3_code":"MMR015007",
    "gn:asciiname":"I-se",
    "gn:country_code":"MM",
    "gn:dem":1527,
    "gn:feature_class":"P",
    "gn:feature_code":"PPL",
    "gn:name":"I-se",
    "gn:population":0,
    "gn:timezone":"Asia/Yangon",
    "iso:country":"MM",
    "wof:name":"I-se",
    "wof:placetype":"locality"
},
  "geometry": {"coordinates":[99.33334000000001,22.8408],"type":"Point"}
}