{
  "type": "Feature",
  "properties": {
    "gn:admin1_code":"3.0",
    "gn:admin2_code":"MMR017D004",
    "gn:admin3_code":"MMR017016",
    "gn:asciiname":"Kyeinnigale",
    "gn:country_code":"MM",
    "gn:dem":7,
    "gn:feature_class":"P",
    "gn:feature_code":"PPL",
    "gn:name":"Kyeinnigale",
    "gn:population":0,
    "gn:timezone":"Asia/Yangon",
    "iso:country":"MM",
    "wof:name":"Kyeinnigale",
    "wof:placetype":"locality"
},
  "geometry": {"coordinates":[95.00494999999999,15.86294],"type":"Point"}
}