{
  "type": "Feature",
  "properties": {
    "gn:admin1_code":"10.0",
    "gn:admin2_code":"MMR005D005",
    "gn:admin3_code":"MMR005029",
    "gn:asciiname":"Zanabok",
    "gn:country_code":"MM",
    "gn:dem":246,
    "gn:feature_class":"P",
    "gn:feature_code":"PPL",
    "gn:name":"Zanabok",
    "gn:population":0,
    "gn:timezone":"Asia/Yangon",
    "iso:country":"MM",
    "wof:name":"Zanabok",
    "wof:placetype":"locality"
},
  "geometry": {"coordinates":[94.33816,22.69974],"type":"Point"}
}