{
  "type": "Feature",
  "properties": {
    "gn:admin1_code":"6.0",
    "gn:admin2_code":"MMR002D002",
    "gn:admin3_code":"MMR002006",
    "gn:asciiname":"Pwako",
    "gn:country_code":"MM",
    "gn:dem":667,
    "gn:feature_class":"P",
    "gn:feature_code":"PPL",
    "gn:name":"Pwako",
    "gn:population":0,
    "gn:timezone":"Asia/Yangon",
    "iso:country":"MM",
    "name:und_x_variant":[
        "Bwako",
        "Pwako"
    ],
    "wof:name":"Pwako",
    "wof:placetype":"locality"
},
  "geometry": {"coordinates":[97.19683999999999,18.95098],"type":"Point"}
}