{
  "type": "Feature",
  "properties": {
    "gn:admin1_code":"18.0",
    "gn:admin2_code":"MMR018D002",
    "gn:admin3_code":"MMR018004",
    "gn:asciiname":"Zalokkyi",
    "gn:country_code":"MM",
    "gn:dem":169,
    "gn:feature_class":"P",
    "gn:feature_code":"PPL",
    "gn:name":"Zalokkyi",
    "gn:population":0,
    "gn:timezone":"Asia/Yangon",
    "iso:country":"MM",
    "wof:name":"Zalokkyi",
    "wof:placetype":"locality"
},
  "geometry": {"coordinates":[96.01935,19.76268],"type":"Point"}
}