{
  "type": "Feature",
  "properties": {
    "gn:admin1_code":"11.0",
    "gn:admin2_code":"MMR014D002",
    "gn:admin3_code":"MMR014015",
    "gn:asciiname":"Namhsa-yawng",
    "gn:country_code":"MM",
    "gn:dem":1039,
    "gn:feature_class":"P",
    "gn:feature_code":"PPL",
    "gn:name":"Namhsa-yawng",
    "gn:population":0,
    "gn:timezone":"Asia/Yangon",
    "iso:country":"MM",
    "wof:name":"Namhsa-yawng",
    "wof:placetype":"locality"
},
  "geometry": {"coordinates":[97.89319999999999,21.95214],"type":"Point"}
}