{
  "type": "Feature",
  "properties": {
    "gn:admin1_code":"4.0",
    "gn:admin2_code":"MMR001D004",
    "gn:admin3_code":"MMR001018",
    "gn:asciiname":"Zala",
    "gn:country_code":"MM",
    "gn:dem":1253,
    "gn:feature_class":"P",
    "gn:feature_code":"PPL",
    "gn:name":"Zala",
    "gn:population":0,
    "gn:timezone":"Asia/Yangon",
    "iso:country":"MM",
    "name:als_x_preferred":[
        "Zala"
    ],
    "name:bos_x_preferred":[
        "Zala"
    ],
    "name:bul_x_preferred":[
        "\u0417\u0430\u043b\u0430"
    ],
    "name:ceb_x_preferred":[
        "Zala"
    ],
    "name:deu_x_preferred":[
        "Zala"
    ],
    "name:fra_x_preferred":[
        "Zala"
    ],
    "name:hrv_x_preferred":[
        "Zala"
    ],
    "name:hun_x_preferred":[
        "Zala"
    ],
    "name:lit_x_preferred":[
        "Zala"
    ],
    "name:nld_x_preferred":[
        "Zala"
    ],
    "name:pol_x_preferred":[
        "Zala"
    ],
    "name:por_x_preferred":[
        "Zala"
    ],
    "name:rus_x_preferred":[
        "\u0417\u0430\u043b\u0430"
    ],
    "name:slk_x_preferred":[
        "Zala"
    ],
    "name:slv_x_preferred":[
        "Zala"
    ],
    "name:spa_x_preferred":[
        "Zala"
    ],
    "name:srp_x_preferred":[
        "\u0417\u0430\u043b\u0430"
    ],
    "name:swe_x_preferred":[
        "Zala"
    ],
    "wof:name":"Zala",
    "wof:placetype":"locality"
},
  "geometry": {"coordinates":[98.52547,27.2113],"type":"Point"}
}