{
  "type": "Feature",
  "properties": {
    "gn:admin1_code":"3.0",
    "gn:admin2_code":"MMR017D001",
    "gn:admin3_code":"MMR017004",
    "gn:asciiname":"Konbat",
    "gn:country_code":"MM",
    "gn:dem":16,
    "gn:feature_class":"P",
    "gn:feature_code":"PPL",
    "gn:name":"K\u00f4nbat",
    "gn:population":0,
    "gn:timezone":"Asia/Yangon",
    "iso:country":"MM",
    "name:und_x_variant":[
        "Kn\u00f4bat",
        "K\u00f4nbat"
    ],
    "wof:name":"Konbat",
    "wof:placetype":"locality"
},
  "geometry": {"coordinates":[94.26972000000001,16.46507],"type":"Point"}
}