{
  "type": "Feature",
  "properties": {
    "gn:admin1_code":"4.0",
    "gn:admin2_code":"MMR001D001",
    "gn:admin3_code":"MMR001003",
    "gn:asciiname":"Ningpawnkrawn",
    "gn:country_code":"MM",
    "gn:dem":620,
    "gn:feature_class":"P",
    "gn:feature_code":"PPL",
    "gn:name":"Ningpawnkrawn",
    "gn:population":0,
    "gn:timezone":"Asia/Yangon",
    "iso:country":"MM",
    "wof:name":"Ningpawnkrawn",
    "wof:placetype":"locality"
},
  "geometry": {"coordinates":[97.82937,25.86332],"type":"Point"}
}