{
  "type": "Feature",
  "properties": {
    "gn:admin1_code":"8.0",
    "gn:admin2_code":"MMR010D004",
    "gn:admin3_code":"MMR010021",
    "gn:asciiname":"Pyinhladaw",
    "gn:country_code":"MM",
    "gn:dem":203,
    "gn:feature_class":"P",
    "gn:feature_code":"PPL",
    "gn:name":"Pyinhladaw",
    "gn:population":0,
    "gn:timezone":"Asia/Yangon",
    "iso:country":"MM",
    "wof:name":"Pyinhladaw",
    "wof:placetype":"locality"
},
  "geometry": {"coordinates":[95.64331,21.62565],"type":"Point"}
}