{
  "type": "Feature",
  "properties": {
    "gn:admin1_code":"11.0",
    "gn:admin2_code":"MMR016D002",
    "gn:admin3_code":"MMR016006",
    "gn:asciiname":"Wan Pu-hsin",
    "gn:country_code":"MM",
    "gn:dem":901,
    "gn:feature_class":"P",
    "gn:feature_code":"PPL",
    "gn:name":"W\u0101n Pu-hsin",
    "gn:population":0,
    "gn:timezone":"Asia/Yangon",
    "iso:country":"MM",
    "name:und_x_variant":[
        "W\u0101n Pu-hsain",
        "W\u0101n Pu-hsin"
    ],
    "wof:name":"Wan Pu-hsin",
    "wof:placetype":"locality"
},
  "geometry": {"coordinates":[99.31684,20.55602],"type":"Point"}
}