{
  "type": "Feature",
  "properties": {
    "gn:admin1_code":"4.0",
    "gn:admin2_code":"MMR001D002",
    "gn:admin3_code":"MMR001007",
    "gn:asciiname":"Sumpaung",
    "gn:country_code":"MM",
    "gn:dem":871,
    "gn:feature_class":"P",
    "gn:feature_code":"PPL",
    "gn:name":"Sumpaung",
    "gn:population":0,
    "gn:timezone":"Asia/Yangon",
    "iso:country":"MM",
    "wof:name":"Sumpaung",
    "wof:placetype":"locality"
},
  "geometry": {"coordinates":[96.00584000000001,24.73489],"type":"Point"}
}