{
  "type": "Feature",
  "properties": {
    "gn:admin1_code":"3.0",
    "gn:admin2_code":"MMR017D001",
    "gn:admin3_code":"MMR017002",
    "gn:asciiname":"Kyidaw",
    "gn:country_code":"MM",
    "gn:dem":7,
    "gn:feature_class":"P",
    "gn:feature_code":"PPL",
    "gn:name":"Kyidaw",
    "gn:population":0,
    "gn:timezone":"Asia/Yangon",
    "iso:country":"MM",
    "wof:name":"Kyidaw",
    "wof:placetype":"locality"
},
  "geometry": {"coordinates":[94.89098,16.78181],"type":"Point"}
}