{
  "type": "Feature",
  "properties": {
    "gn:admin1_code":"11.0",
    "gn:admin2_code":"MMR016D001",
    "gn:admin3_code":"MMR016001",
    "gn:asciiname":"Wan Nawngnguen",
    "gn:country_code":"MM",
    "gn:dem":793,
    "gn:feature_class":"P",
    "gn:feature_code":"PPL",
    "gn:name":"W\u0101n Nawngng\u00fcn",
    "gn:population":0,
    "gn:timezone":"Asia/Yangon",
    "iso:country":"MM",
    "name:und_x_variant":[
        "Nawngng\u00fcn",
        "W\u0101n Nawngng\u00fcn"
    ],
    "wof:name":"Wan Nawngnguen",
    "wof:placetype":"locality"
},
  "geometry": {"coordinates":[99.64382000000001,21.34186],"type":"Point"}
}