{
  "type": "Feature",
  "properties": {
    "gn:admin1_code":"11.0",
    "gn:admin2_code":"MMR014D001",
    "gn:admin3_code":"MMR014005",
    "gn:asciiname":"Pawlamaw",
    "gn:country_code":"MM",
    "gn:dem":1259,
    "gn:feature_class":"P",
    "gn:feature_code":"PPL",
    "gn:name":"Pawlamaw",
    "gn:population":0,
    "gn:timezone":"Asia/Yangon",
    "iso:country":"MM",
    "wof:name":"Pawlamaw",
    "wof:placetype":"locality"
},
  "geometry": {"coordinates":[96.81382000000001,20.62801],"type":"Point"}
}