{
  "type": "Feature",
  "properties": {
    "gn:admin1_code":"11.0",
    "gn:asciiname":"Wan Hsinlongmonsai",
    "gn:country_code":"MM",
    "gn:dem":757,
    "gn:feature_class":"P",
    "gn:feature_code":"PPL",
    "gn:name":"W\u0101n Hsinlongmonsai",
    "gn:population":0,
    "gn:timezone":"Asia/Yangon",
    "iso:country":"MM",
    "wof:name":"Wan Hsinlongmonsai",
    "wof:placetype":"locality"
},
  "geometry": {"coordinates":[99.37389,20.07472000000001],"type":"Point"}
}