{
  "type": "Feature",
  "properties": {
    "gn:admin1_code":"10.0",
    "gn:admin2_code":"MMR005D009",
    "gn:admin3_code":"MMR005016",
    "gn:asciiname":"Thalauk",
    "gn:country_code":"MM",
    "gn:dem":197,
    "gn:feature_class":"P",
    "gn:feature_code":"PPL",
    "gn:name":"Thalauk",
    "gn:population":0,
    "gn:timezone":"Asia/Yangon",
    "iso:country":"MM",
    "wof:name":"Thalauk",
    "wof:placetype":"locality"
},
  "geometry": {"coordinates":[94.65980999999999,22.25451],"type":"Point"}
}