{
  "type": "Feature",
  "properties": {
    "gn:admin1_code":"1.0",
    "gn:admin2_code":"MMR012D003",
    "gn:admin3_code":"MMR012014",
    "gn:asciiname":"Let-ya",
    "gn:country_code":"MM",
    "gn:dem":38,
    "gn:feature_class":"P",
    "gn:feature_code":"PPL",
    "gn:name":"Let-ya",
    "gn:population":0,
    "gn:timezone":"Asia/Yangon",
    "iso:country":"MM",
    "wof:name":"Let-ya",
    "wof:placetype":"locality"
},
  "geometry": {"coordinates":[94.13861,19.42237],"type":"Point"}
}