{
  "type": "Feature",
  "properties": {
    "gn:admin1_code":"11.0",
    "gn:admin2_code":"MMR015D005",
    "gn:admin3_code":"MMR015022",
    "gn:asciiname":"Hsiao-ai-fang",
    "gn:country_code":"MM",
    "gn:dem":1603,
    "gn:feature_class":"P",
    "gn:feature_code":"PPL",
    "gn:name":"Hsiao-ai-fang",
    "gn:population":0,
    "gn:timezone":"Asia/Yangon",
    "iso:country":"MM",
    "name:und_x_variant":[
        "Hsiao-ai-feng",
        "Hsiao-ai-fang"
    ],
    "wof:name":"Hsiao-ai-fang",
    "wof:placetype":"locality"
},
  "geometry": {"coordinates":[98.80955,23.55515],"type":"Point"}
}