{
  "type": "Feature",
  "properties": {
    "gn:admin1_code":"6.0",
    "gn:admin2_code":"MMR002D001",
    "gn:admin3_code":"MMR002003",
    "gn:asciiname":"Wewa Doko",
    "gn:country_code":"MM",
    "gn:dem":1006,
    "gn:feature_class":"P",
    "gn:feature_code":"PPL",
    "gn:name":"Wewa Doko",
    "gn:population":0,
    "gn:timezone":"Asia/Yangon",
    "iso:country":"MM",
    "name:und_x_variant":[
        "Wewa Dako",
        "Wewa Doko"
    ],
    "wof:name":"Wewa Doko",
    "wof:placetype":"locality"
},
  "geometry": {"coordinates":[96.95102,19.03522],"type":"Point"}
}