{
  "type": "Feature",
  "properties": {
    "gn:admin1_code":"8.0",
    "gn:admin2_code":"MMR010D005",
    "gn:admin3_code":"MMR010022",
    "gn:asciiname":"Palin",
    "gn:country_code":"MM",
    "gn:dem":65,
    "gn:feature_class":"P",
    "gn:feature_code":"PPL",
    "gn:name":"Palin",
    "gn:population":0,
    "gn:timezone":"Asia/Yangon",
    "iso:country":"MM",
    "name:ces_x_preferred":[
        "Palin"
    ],
    "wof:name":"Palin",
    "wof:placetype":"locality"
},
  "geometry": {"coordinates":[94.97828,21.2175],"type":"Point"}
}