{
  "type": "Feature",
  "properties": {
    "gn:admin1_code":"1.0",
    "gn:admin2_code":"MMR012D004",
    "gn:admin3_code":"MMR012016",
    "gn:asciiname":"Wet-ya",
    "gn:country_code":"MM",
    "gn:dem":15,
    "gn:feature_class":"P",
    "gn:feature_code":"PPL",
    "gn:name":"Wet-ya",
    "gn:population":0,
    "gn:timezone":"Asia/Yangon",
    "iso:country":"MM",
    "wof:name":"Wet-ya",
    "wof:placetype":"locality"
},
  "geometry": {"coordinates":[94.18980999999999,19.28676],"type":"Point"}
}