{
  "type": "Feature",
  "properties": {
    "gn:admin1_code":"11.0",
    "gn:admin2_code":"MMR016D001",
    "gn:admin3_code":"MMR016007",
    "gn:asciiname":"Wan Ta-long",
    "gn:country_code":"MM",
    "gn:dem":323,
    "gn:feature_class":"P",
    "gn:feature_code":"PPL",
    "gn:name":"W\u0101n T\u0101-long",
    "gn:population":0,
    "gn:timezone":"Asia/Yangon",
    "iso:country":"MM",
    "name:und_x_variant":[
        "Ta-long",
        "W\u0101n T\u0101-long"
    ],
    "wof:name":"Wan Ta-long",
    "wof:placetype":"locality"
},
  "geometry": {"coordinates":[98.61404,21.42713],"type":"Point"}
}