{
  "type": "Feature",
  "properties": {
    "gn:admin1_code":"11.0",
    "gn:admin2_code":"MMR016D001",
    "gn:admin3_code":"MMR016003",
    "gn:asciiname":"Wan Sueng",
    "gn:country_code":"MM",
    "gn:dem":982,
    "gn:feature_class":"P",
    "gn:feature_code":"PPL",
    "gn:name":"W\u0101n S\u00fcng",
    "gn:population":0,
    "gn:timezone":"Asia/Yangon",
    "iso:country":"MM",
    "wof:name":"Wan Sueng",
    "wof:placetype":"locality"
},
  "geometry": {"coordinates":[99.74409,21.81366],"type":"Point"}
}