{
  "type": "Feature",
  "properties": {
    "gn:admin1_code":"10.0",
    "gn:admin2_code":"MMR005D002",
    "gn:admin3_code":"MMR005011",
    "gn:asciiname":"Uyinma",
    "gn:country_code":"MM",
    "gn:dem":212,
    "gn:feature_class":"P",
    "gn:feature_code":"PPL",
    "gn:name":"Uyinma",
    "gn:population":0,
    "gn:timezone":"Asia/Yangon",
    "iso:country":"MM",
    "wof:name":"Uyinma",
    "wof:placetype":"locality"
},
  "geometry": {"coordinates":[95.06667,23.28333],"type":"Point"}
}