{
  "type": "Feature",
  "properties": {
    "gn:admin1_code":"1.0",
    "gn:admin2_code":"MMR012D005",
    "gn:admin3_code":"MMR012005",
    "gn:asciiname":"Kambo",
    "gn:country_code":"MM",
    "gn:dem":38,
    "gn:feature_class":"P",
    "gn:feature_code":"PPL",
    "gn:name":"Kambo",
    "gn:population":0,
    "gn:timezone":"Asia/Yangon",
    "iso:country":"MM",
    "wof:name":"Kambo",
    "wof:placetype":"locality"
},
  "geometry": {"coordinates":[93.58146000000001,20.26838],"type":"Point"}
}