{
  "type": "Feature",
  "properties": {
    "gn:admin1_code":"3.0",
    "gn:admin2_code":"MMR017D002",
    "gn:admin3_code":"MMR017008",
    "gn:asciiname":"Thayetchaung",
    "gn:country_code":"MM",
    "gn:dem":20,
    "gn:feature_class":"P",
    "gn:feature_code":"PPL",
    "gn:name":"Thayetchaung",
    "gn:population":0,
    "gn:timezone":"Asia/Yangon",
    "iso:country":"MM",
    "name:mya_x_preferred":[
        "\u101e\u101b\u1000\u103a\u1001\u103b\u1031\u102c\u1004\u103a\u1038\u1019\u103c\u102d\u102f\u1037"
    ],
    "name:shn_x_preferred":[
        "\u1010\u101a\u1085\u1010\u103a\u1089\u1076\u103b\u103d\u1004\u103a\u1038\u104a \u101d\u1035\u1004\u103a\u1038"
    ],
    "name:swe_x_preferred":[
        "Thayetchaung"
    ],
    "wof:name":"Thayetchaung",
    "wof:placetype":"locality"
},
  "geometry": {"coordinates":[95.36775,17.60772],"type":"Point"}
}