{
  "type": "Feature",
  "properties": {
    "gn:admin1_code":"5.0",
    "gn:admin2_code":"MMR003D001",
    "gn:admin3_code":"MMR003002",
    "gn:asciiname":"Htiluthakhi",
    "gn:country_code":"MM",
    "gn:dem":492,
    "gn:feature_class":"P",
    "gn:feature_code":"PPL",
    "gn:name":"Htil\u016bthakhi",
    "gn:population":0,
    "gn:timezone":"Asia/Yangon",
    "iso:country":"MM",
    "wof:name":"Htiluthakhi",
    "wof:placetype":"locality"
},
  "geometry": {"coordinates":[97.7693,17.66271],"type":"Point"}
}