{
  "type": "Feature",
  "properties": {
    "gn:admin1_code":"15.0",
    "gn:admin2_code":"MMR009D004",
    "gn:admin3_code":"MMR009020",
    "gn:asciiname":"Thabyedon",
    "gn:country_code":"MM",
    "gn:dem":228,
    "gn:feature_class":"P",
    "gn:feature_code":"PPL",
    "gn:name":"Thabyedon",
    "gn:population":0,
    "gn:timezone":"Asia/Yangon",
    "iso:country":"MM",
    "wof:name":"Thabyedon",
    "wof:placetype":"locality"
},
  "geometry": {"coordinates":[94.78332,21.44125],"type":"Point"}
}