{
  "type": "Feature",
  "properties": {
    "gn:admin1_code":"8.0",
    "gn:admin2_code":"MMR010D002",
    "gn:admin3_code":"MMR010008",
    "gn:asciiname":"Yok-kya",
    "gn:country_code":"MM",
    "gn:dem":803,
    "gn:feature_class":"P",
    "gn:feature_code":"PPL",
    "gn:name":"Yok-kya",
    "gn:population":0,
    "gn:timezone":"Asia/Yangon",
    "iso:country":"MM",
    "wof:name":"Yok-kya",
    "wof:placetype":"locality"
},
  "geometry": {"coordinates":[96.36673999999999,21.8004],"type":"Point"}
}