{
  "type": "Feature",
  "properties": {
    "gn:admin1_code":"17.0",
    "gn:admin2_code":"MMR013D003",
    "gn:admin3_code":"MMR013023",
    "gn:asciiname":"Ngabyema",
    "gn:country_code":"MM",
    "gn:dem":7,
    "gn:feature_class":"P",
    "gn:feature_code":"PPL",
    "gn:name":"Ngabyema",
    "gn:population":0,
    "gn:timezone":"Asia/Yangon",
    "iso:country":"MM",
    "wof:name":"Ngabyema",
    "wof:placetype":"locality"
},
  "geometry": {"coordinates":[96.29613000000001,16.78887000000001],"type":"Point"}
}