{
  "type": "Feature",
  "properties": {
    "gn:admin1_code":"11.0",
    "gn:admin2_code":"MMR015D005",
    "gn:admin3_code":"MMR015023",
    "gn:asciiname":"Namwanhsan",
    "gn:country_code":"MM",
    "gn:dem":1193,
    "gn:feature_class":"P",
    "gn:feature_code":"PPL",
    "gn:name":"Namwanhsan",
    "gn:population":0,
    "gn:timezone":"Asia/Yangon",
    "iso:country":"MM",
    "wof:name":"Namwanhsan",
    "wof:placetype":"locality"
},
  "geometry": {"coordinates":[98.47732000000001,23.91249],"type":"Point"}
}