{
  "type": "Feature",
  "properties": {
    "gn:admin1_code":"10.0",
    "gn:admin2_code":"MMR005D009",
    "gn:admin3_code":"MMR005018",
    "gn:asciiname":"Aleywa",
    "gn:country_code":"MM",
    "gn:dem":133,
    "gn:feature_class":"P",
    "gn:feature_code":"PPL",
    "gn:name":"Aleywa",
    "gn:population":0,
    "gn:timezone":"Asia/Yangon",
    "iso:country":"MM",
    "wof:name":"Aleywa",
    "wof:placetype":"locality"
},
  "geometry": {"coordinates":[94.95641999999999,22.00878],"type":"Point"}
}