{
  "type": "Feature",
  "properties": {
    "gn:admin1_code":"11.0",
    "gn:admin2_code":"MMR016D001",
    "gn:admin3_code":"MMR016001",
    "gn:asciiname":"Wan Pang",
    "gn:country_code":"MM",
    "gn:dem":819,
    "gn:feature_class":"P",
    "gn:feature_code":"PPL",
    "gn:name":"W\u0101n Pang",
    "gn:population":0,
    "gn:timezone":"Asia/Yangon",
    "iso:country":"MM",
    "wof:name":"Wan Pang",
    "wof:placetype":"locality"
},
  "geometry": {"coordinates":[99.64353,21.22302],"type":"Point"}
}