{
  "type": "Feature",
  "properties": {
    "gn:admin1_code":"11.0",
    "gn:admin2_code":"MMR015D003",
    "gn:admin3_code":"MMR015012",
    "gn:asciiname":"Moengnoi",
    "gn:country_code":"MM",
    "gn:dem":665,
    "gn:feature_class":"P",
    "gn:feature_code":"PPL",
    "gn:name":"M\u00f6ngnoi",
    "gn:population":0,
    "gn:timezone":"Asia/Yangon",
    "iso:country":"MM",
    "wof:name":"Moengnoi",
    "wof:placetype":"locality"
},
  "geometry": {"coordinates":[97.14632,22.40537],"type":"Point"}
}