{
  "type": "Feature",
  "properties": {
    "gn:admin1_code":"16.0",
    "gn:admin2_code":"MMR007D002",
    "gn:admin3_code":"MMR007014",
    "gn:asciiname":"Sabagyi Ashe",
    "gn:country_code":"MM",
    "gn:dem":40,
    "gn:feature_class":"P",
    "gn:feature_code":"PPL",
    "gn:name":"Sabagyi Ashe",
    "gn:population":0,
    "gn:timezone":"Asia/Yangon",
    "iso:country":"MM",
    "name:und_x_variant":[
        "Sabgyi Ashe",
        "Sabakyi-atet",
        "Sabagyi Ashe"
    ],
    "wof:name":"Sabagyi Ashe",
    "wof:placetype":"locality"
},
  "geometry": {"coordinates":[96.44758,18.7147],"type":"Point"}
}