{
  "type": "Feature",
  "properties": {
    "gn:admin1_code":"11.0",
    "gn:admin2_code":"MMR015D001",
    "gn:admin3_code":"MMR015003",
    "gn:asciiname":"Hwe-lue",
    "gn:country_code":"MM",
    "gn:dem":656,
    "gn:feature_class":"P",
    "gn:feature_code":"PPL",
    "gn:name":"Hw\u00e8-l\u00fc",
    "gn:population":0,
    "gn:timezone":"Asia/Yangon",
    "iso:country":"MM",
    "wof:name":"Hwe-lue",
    "wof:placetype":"locality"
},
  "geometry": {"coordinates":[97.93083,22.72961],"type":"Point"}
}