{
  "type": "Feature",
  "properties": {
    "gn:admin1_code":"4.0",
    "gn:admin2_code":"MMR001D003",
    "gn:admin3_code":"MMR001012",
    "gn:asciiname":"Pangmo",
    "gn:country_code":"MM",
    "gn:dem":1666,
    "gn:feature_class":"P",
    "gn:feature_code":"PPL",
    "gn:name":"Pangmo",
    "gn:population":0,
    "gn:timezone":"Asia/Yangon",
    "iso:country":"MM",
    "wof:name":"Pangmo",
    "wof:placetype":"locality"
},
  "geometry": {"coordinates":[97.50364999999999,24.25886],"type":"Point"}
}