{
  "type": "Feature",
  "properties": {
    "gn:admin1_code":"15.0",
    "gn:admin2_code":"MMR009D001",
    "gn:admin3_code":"MMR009002",
    "gn:asciiname":"Sibinywazo",
    "gn:country_code":"MM",
    "gn:dem":163,
    "gn:feature_class":"P",
    "gn:feature_code":"PPL",
    "gn:name":"Sibinywazo",
    "gn:population":0,
    "gn:timezone":"Asia/Yangon",
    "iso:country":"MM",
    "wof:name":"Sibinywazo",
    "wof:placetype":"locality"
},
  "geometry": {"coordinates":[95.06094,20.57674],"type":"Point"}
}