{
  "type": "Feature",
  "properties": {
    "gn:admin1_code":"11.0",
    "gn:admin2_code":"MMR016D001",
    "gn:admin3_code":"MMR016005",
    "gn:asciiname":"Wan Hwe-hoek",
    "gn:country_code":"MM",
    "gn:dem":1249,
    "gn:feature_class":"P",
    "gn:feature_code":"PPL",
    "gn:name":"W\u0101n Hw\u00e8-h\u00f6k",
    "gn:population":0,
    "gn:timezone":"Asia/Yangon",
    "iso:country":"MM",
    "wof:name":"Wan Hwe-hoek",
    "wof:placetype":"locality"
},
  "geometry": {"coordinates":[99.73376,21.72063],"type":"Point"}
}