{
  "type": "Feature",
  "properties": {
    "gn:admin1_code":"4.0",
    "gn:admin2_code":"MMR001D004",
    "gn:admin3_code":"MMR001017",
    "gn:asciiname":"Ba Baw",
    "gn:country_code":"MM",
    "gn:dem":514,
    "gn:feature_class":"P",
    "gn:feature_code":"PPL",
    "gn:name":"Ba Baw",
    "gn:population":0,
    "gn:timezone":"Asia/Yangon",
    "iso:country":"MM",
    "wof:name":"Ba Baw",
    "wof:placetype":"locality"
},
  "geometry": {"coordinates":[97.88981,27.36735],"type":"Point"}
}