{
  "type": "Feature",
  "properties": {
    "gn:admin1_code":"11.0",
    "gn:admin2_code":"MMR016D001",
    "gn:admin3_code":"MMR016001",
    "gn:asciiname":"Wan Kaw Namti",
    "gn:country_code":"MM",
    "gn:dem":1706,
    "gn:feature_class":"P",
    "gn:feature_code":"PPL",
    "gn:name":"W\u0101n Kaw Namti",
    "gn:population":0,
    "gn:timezone":"Asia/Yangon",
    "iso:country":"MM",
    "name:und_x_variant":[
        "W\u0101n Namti",
        "W\u0101n Kaw Namti"
    ],
    "wof:name":"Wan Kaw Namti",
    "wof:placetype":"locality"
},
  "geometry": {"coordinates":[99.84560999999999,21.28158],"type":"Point"}
}