{
  "type": "Feature",
  "properties": {
    "gn:admin1_code":"6.0",
    "gn:admin2_code":"MMR002D001",
    "gn:admin3_code":"MMR002004",
    "gn:asciiname":"Daw Mi-ku",
    "gn:country_code":"MM",
    "gn:dem":954,
    "gn:feature_class":"P",
    "gn:feature_code":"PPL",
    "gn:name":"Daw Mi-ku",
    "gn:population":0,
    "gn:timezone":"Asia/Yangon",
    "iso:country":"MM",
    "name:und_x_variant":[
        "Daw Me-ku",
        "Daw Mi-ku"
    ],
    "wof:name":"Daw Mi-ku",
    "wof:placetype":"locality"
},
  "geometry": {"coordinates":[97.55537,19.5167],"type":"Point"}
}