{
  "type": "Feature",
  "properties": {
    "gn:admin1_code":"16.0",
    "gn:admin2_code":"MMR008D002",
    "gn:admin3_code":"MMR008008",
    "gn:asciiname":"Chaungthongwa",
    "gn:country_code":"MM",
    "gn:dem":20,
    "gn:feature_class":"P",
    "gn:feature_code":"PPL",
    "gn:name":"Chaungthongwa",
    "gn:population":0,
    "gn:timezone":"Asia/Yangon",
    "iso:country":"MM",
    "wof:name":"Chaungthongwa",
    "wof:placetype":"locality"
},
  "geometry": {"coordinates":[95.64091999999999,17.75825],"type":"Point"}
}