{
  "type": "Feature",
  "properties": {
    "gn:admin1_code":"6.0",
    "gn:admin2_code":"MMR002D001",
    "gn:admin3_code":"MMR002003",
    "gn:asciiname":"Namhpe",
    "gn:country_code":"MM",
    "gn:dem":354,
    "gn:feature_class":"P",
    "gn:feature_code":"PPL",
    "gn:name":"Namhpe",
    "gn:population":0,
    "gn:timezone":"Asia/Yangon",
    "iso:country":"MM",
    "wof:name":"Namhpe",
    "wof:placetype":"locality"
},
  "geometry": {"coordinates":[97.2132,19.21377],"type":"Point"}
}