{
  "type": "Feature",
  "properties": {
    "gn:admin1_code":"15.0",
    "gn:admin2_code":"MMR009D003",
    "gn:admin3_code":"MMR009012",
    "gn:asciiname":"Ton",
    "gn:country_code":"MM",
    "gn:dem":57,
    "gn:feature_class":"P",
    "gn:feature_code":"PPL",
    "gn:name":"T\u00f4n",
    "gn:population":0,
    "gn:timezone":"Asia/Yangon",
    "iso:country":"MM",
    "name:deu_x_preferred":[
        "Tonne"
    ],
    "name:eus_x_preferred":[
        "Tona ingelesa"
    ],
    "name:nno_x_preferred":[
        "Megagram"
    ],
    "name:nor_x_preferred":[
        "Megagram"
    ],
    "name:swe_x_preferred":[
        "Ton"
    ],
    "name:tel_x_preferred":[
        "\u0c1f\u0c28\u0c4d"
    ],
    "wof:name":"Ton",
    "wof:placetype":"locality"
},
  "geometry": {"coordinates":[95.04724,19.21333],"type":"Point"}
}