{
  "type": "Feature",
  "properties": {
    "gn:admin1_code":"8.0",
    "gn:admin2_code":"MMR010D004",
    "gn:admin3_code":"MMR010017",
    "gn:asciiname":"Pinle",
    "gn:country_code":"MM",
    "gn:dem":121,
    "gn:feature_class":"P",
    "gn:feature_code":"PPL",
    "gn:name":"Pinle",
    "gn:population":0,
    "gn:timezone":"Asia/Yangon",
    "iso:country":"MM",
    "name:fra_x_preferred":[
        "Pinle"
    ],
    "name:mya_x_preferred":[
        "\u1015\u1004\u103a\u101c\u101a\u103a\u1019\u103c\u102d\u102f\u1037\u101f\u1031\u102c\u1004\u103a\u1038"
    ],
    "name:tha_x_preferred":[
        "\u0e1b\u0e35\u0e19\u0e41\u0e25"
    ],
    "wof:name":"Pinle",
    "wof:placetype":"locality"
},
  "geometry": {"coordinates":[95.52245000000001,21.69836],"type":"Point"}
}