{
  "type": "Feature",
  "properties": {
    "gn:admin1_code":"1.0",
    "gn:admin2_code":"MMR012D001",
    "gn:admin3_code":"MMR012007",
    "gn:asciiname":"Pyaingdaung",
    "gn:country_code":"MM",
    "gn:dem":12,
    "gn:feature_class":"P",
    "gn:feature_code":"PPL",
    "gn:name":"Pyaingdaung",
    "gn:population":0,
    "gn:timezone":"Asia/Yangon",
    "iso:country":"MM",
    "wof:name":"Pyaingdaung",
    "wof:placetype":"locality"
},
  "geometry": {"coordinates":[92.96867,20.03252],"type":"Point"}
}