{
  "type": "Feature",
  "properties": {
    "gn:admin1_code":"11.0",
    "gn:admin2_code":"MMR015D005",
    "gn:admin3_code":"MMR015022",
    "gn:asciiname":"Wan Shihfang",
    "gn:country_code":"MM",
    "gn:dem":1397,
    "gn:feature_class":"P",
    "gn:feature_code":"PPL",
    "gn:name":"W\u0101n Shihfang",
    "gn:population":0,
    "gn:timezone":"Asia/Yangon",
    "iso:country":"MM",
    "name:und_x_variant":[
        "Wan Shinfang",
        "W\u0101n Shihfang"
    ],
    "wof:name":"Wan Shihfang",
    "wof:placetype":"locality"
},
  "geometry": {"coordinates":[98.72565,23.70291],"type":"Point"}
}