{
  "type": "Feature",
  "properties": {
    "gn:admin1_code":"10.0",
    "gn:admin2_code":"MMR005D002",
    "gn:admin3_code":"MMR005010",
    "gn:asciiname":"Kyakat",
    "gn:country_code":"MM",
    "gn:dem":107,
    "gn:feature_class":"P",
    "gn:feature_code":"PPL",
    "gn:name":"Kyakat",
    "gn:population":0,
    "gn:timezone":"Asia/Yangon",
    "iso:country":"MM",
    "wof:name":"Kyakat",
    "wof:placetype":"locality"
},
  "geometry": {"coordinates":[95.26933,22.59617],"type":"Point"}
}