{
  "type": "Feature",
  "properties": {
    "gn:admin1_code":"3.0",
    "gn:admin2_code":"MMR017D006",
    "gn:admin3_code":"MMR017024",
    "gn:asciiname":"Lagayet",
    "gn:country_code":"MM",
    "gn:dem":5,
    "gn:feature_class":"P",
    "gn:feature_code":"PPL",
    "gn:name":"Lagayet",
    "gn:population":0,
    "gn:timezone":"Asia/Yangon",
    "iso:country":"MM",
    "wof:name":"Lagayet",
    "wof:placetype":"locality"
},
  "geometry": {"coordinates":[95.51063000000001,16.0775],"type":"Point"}
}