{
  "type": "Feature",
  "properties": {
    "gn:admin1_code":"11.0",
    "gn:admin2_code":"MMR014D001",
    "gn:admin3_code":"MMR014006",
    "gn:asciiname":"Tame",
    "gn:country_code":"MM",
    "gn:dem":1335,
    "gn:feature_class":"P",
    "gn:feature_code":"PPL",
    "gn:name":"Tame",
    "gn:population":0,
    "gn:timezone":"Asia/Yangon",
    "iso:country":"MM",
    "wof:name":"Tame",
    "wof:placetype":"locality"
},
  "geometry": {"coordinates":[96.69636,20.88488],"type":"Point"}
}