{
  "type": "Feature",
  "properties": {
    "gn:admin1_code":"15.0",
    "gn:admin2_code":"MMR009D002",
    "gn:admin3_code":"MMR009010",
    "gn:asciiname":"Tebokkan",
    "gn:country_code":"MM",
    "gn:dem":103,
    "gn:feature_class":"P",
    "gn:feature_code":"PPL",
    "gn:name":"Tebokkan",
    "gn:population":0,
    "gn:timezone":"Asia/Yangon",
    "iso:country":"MM",
    "wof:name":"Tebokkan",
    "wof:placetype":"locality"
},
  "geometry": {"coordinates":[94.59869,20.48716],"type":"Point"}
}