{
  "type": "Feature",
  "properties": {
    "gn:admin1_code":"16.0",
    "gn:admin2_code":"MMR007D002",
    "gn:admin3_code":"MMR007010",
    "gn:asciiname":"Kayinlegyin",
    "gn:country_code":"MM",
    "gn:dem":141,
    "gn:feature_class":"P",
    "gn:feature_code":"PPL",
    "gn:name":"Kayinlegyin",
    "gn:population":0,
    "gn:timezone":"Asia/Yangon",
    "iso:country":"MM",
    "name:und_x_variant":[
        "Kayinlagyin",
        "Kayinlegyin"
    ],
    "wof:name":"Kayinlegyin",
    "wof:placetype":"locality"
},
  "geometry": {"coordinates":[96.1742,19.39472],"type":"Point"}
}