{
  "type": "Feature",
  "properties": {
    "gn:admin1_code":"4.0",
    "gn:admin2_code":"MMR001D004",
    "gn:admin3_code":"MMR001017",
    "gn:asciiname":"Komieng Ga",
    "gn:country_code":"MM",
    "gn:dem":1248,
    "gn:feature_class":"P",
    "gn:feature_code":"PPL",
    "gn:name":"Komieng Ga",
    "gn:population":0,
    "gn:timezone":"Asia/Yangon",
    "iso:country":"MM",
    "wof:name":"Komieng Ga",
    "wof:placetype":"locality"
},
  "geometry": {"coordinates":[97.90514,27.48244],"type":"Point"}
}