{
  "type": "Feature",
  "properties": {
    "gn:admin1_code":"16.0",
    "gn:admin2_code":"MMR008D002",
    "gn:admin3_code":"MMR008011",
    "gn:asciiname":"Ngagyi",
    "gn:country_code":"MM",
    "gn:dem":89,
    "gn:feature_class":"P",
    "gn:feature_code":"PPL",
    "gn:name":"Ngagyi",
    "gn:population":0,
    "gn:timezone":"Asia/Yangon",
    "iso:country":"MM",
    "wof:name":"Ngagyi",
    "wof:placetype":"locality"
},
  "geometry": {"coordinates":[95.78525,18.40852000000001],"type":"Point"}
}