{
  "type": "Feature",
  "properties": {
    "gn:admin1_code":"10.0",
    "gn:admin2_code":"MMR005D005",
    "gn:admin3_code":"MMR005029",
    "gn:asciiname":"Myoma",
    "gn:country_code":"MM",
    "gn:dem":108,
    "gn:feature_class":"P",
    "gn:feature_code":"PPL",
    "gn:name":"Myoma",
    "gn:population":0,
    "gn:timezone":"Asia/Yangon",
    "iso:country":"MM",
    "name:aze_x_preferred":[
        "U\u015faql\u0131q miomas\u0131"
    ],
    "name:bul_x_preferred":[
        "\u041c\u0438\u043e\u043c\u0430"
    ],
    "name:cat_x_preferred":[
        "Mioma"
    ],
    "name:deu_x_preferred":[
        "Myom"
    ],
    "name:ell_x_preferred":[
        "\u0399\u03bd\u03bf\u03bc\u03c5\u03ce\u03bc\u03b1\u03c4\u03b1"
    ],
    "name:fin_x_preferred":[
        "Myooma"
    ],
    "name:fra_x_preferred":[
        "Myome"
    ],
    "name:heb_x_preferred":[
        "\u05de\u05d9\u05d5\u05de\u05d4"
    ],
    "name:hrv_x_preferred":[
        "Miom"
    ],
    "name:hun_x_preferred":[
        "Mi\u00f3ma"
    ],
    "name:hye_x_preferred":[
        "\u0544\u056f\u0561\u0576\u0578\u0582\u057c\u0578\u0582\u0581\u0584"
    ],
    "name:lav_x_preferred":[
        "Mioma"
    ],
    "name:lit_x_preferred":[
        "Mioma"
    ],
    "name:nld_x_preferred":[
        "Myoom"
    ],
    "name:pol_x_preferred":[
        "Mi\u0119\u015bniak"
    ],
    "name:por_x_preferred":[
        "Mioma"
    ],
    "name:rus_x_preferred":[
        "\u041c\u0438\u043e\u043c\u0430 \u043c\u0430\u0442\u043a\u0438"
    ],
    "name:spa_x_preferred":[
        "Mioma"
    ],
    "name:swe_x_preferred":[
        "Myom"
    ],
    "name:tel_x_preferred":[
        "\u0c2e\u0c2f\u0c4b\u0c2e\u0c3e"
    ],
    "name:tur_x_preferred":[
        "Leiyomiyom"
    ],
    "name:urd_x_preferred":[
        "\u06c1\u0645\u0639\u0636\u0644\u0648\u0645\u06c1"
    ],
    "name:uzb_x_preferred":[
        "Mioma"
    ],
    "wof:name":"Myoma",
    "wof:placetype":"locality"
},
  "geometry": {"coordinates":[94.32136,22.91277],"type":"Point"}
}