{
  "type": "Feature",
  "properties": {
    "gn:admin1_code":"10.0",
    "gn:admin2_code":"MMR005D005",
    "gn:admin3_code":"MMR005029",
    "gn:asciiname":"Myoma",
    "gn:country_code":"MM",
    "gn:dem":108,
    "gn:feature_class":"P",
    "gn:feature_code":"PPL",
    "gn:name":"Myoma",
    "gn:population":0,
    "gn:timezone":"Asia/Yangon",
    "iso:country":"MM",
    "wof:name":"Myoma",
    "wof:placetype":"locality"
},
  "geometry": {"coordinates":[94.32136,22.91277],"type":"Point"}
}