{
  "type": "Feature",
  "properties": {
    "gn:admin1_code":"15.0",
    "gn:admin2_code":"MMR009D001",
    "gn:admin3_code":"MMR009003",
    "gn:asciiname":"Nyaungmyitpwa",
    "gn:country_code":"MM",
    "gn:dem":66,
    "gn:feature_class":"P",
    "gn:feature_code":"PPL",
    "gn:name":"Nyaungmyitpwa",
    "gn:population":0,
    "gn:timezone":"Asia/Yangon",
    "iso:country":"MM",
    "wof:name":"Nyaungmyitpwa",
    "wof:placetype":"locality"
},
  "geometry": {"coordinates":[94.74173999999999,20.76454],"type":"Point"}
}