{
  "type": "Feature",
  "properties": {
    "gn:admin1_code":"3.0",
    "gn:admin2_code":"MMR017D006",
    "gn:admin3_code":"MMR017025",
    "gn:asciiname":"Yogwa",
    "gn:country_code":"MM",
    "gn:dem":2,
    "gn:feature_class":"P",
    "gn:feature_code":"PPL",
    "gn:name":"Yogwa",
    "gn:population":0,
    "gn:timezone":"Asia/Yangon",
    "iso:country":"MM",
    "wof:name":"Yogwa",
    "wof:placetype":"locality"
},
  "geometry": {"coordinates":[95.77468,16.54702],"type":"Point"}
}