{
  "type": "Feature",
  "properties": {
    "gn:admin1_code":"11.0",
    "gn:admin2_code":"MMR015D003",
    "gn:admin3_code":"MMR015019",
    "gn:asciiname":"Man Pat",
    "gn:country_code":"MM",
    "gn:dem":1571,
    "gn:feature_class":"P",
    "gn:feature_code":"PPL",
    "gn:name":"M\u0101n Pat",
    "gn:population":0,
    "gn:timezone":"Asia/Yangon",
    "iso:country":"MM",
    "name:und_x_variant":[
        "Rau-nak",
        "M\u0101n Pat"
    ],
    "wof:name":"Man Pat",
    "wof:placetype":"locality"
},
  "geometry": {"coordinates":[97.18510000000001,23.19632],"type":"Point"}
}