{
  "type": "Feature",
  "properties": {
    "gn:admin1_code":"10.0",
    "gn:admin2_code":"MMR005D006",
    "gn:admin3_code":"MMR005030",
    "gn:asciiname":"Moreh",
    "gn:cc2":"MM",
    "gn:country_code":"MM",
    "gn:dem":188,
    "gn:feature_class":"P",
    "gn:feature_code":"PPL",
    "gn:name":"Moreh",
    "gn:population":0,
    "gn:timezone":"Asia/Yangon",
    "iso:country":"MM",
    "name:und_x_variant":[
        "Nampalein",
        "Moreh"
    ],
    "wof:name":"Moreh",
    "wof:placetype":"locality"
},
  "geometry": {"coordinates":[94.31667,24.25],"type":"Point"}
}