{
  "type": "Feature",
  "properties": {
    "gn:admin1_code":"10.0",
    "gn:admin2_code":"MMR005D006",
    "gn:admin3_code":"MMR005030",
    "gn:asciiname":"Moreh",
    "gn:cc2":"MM",
    "gn:country_code":"MM",
    "gn:dem":188,
    "gn:feature_class":"P",
    "gn:feature_code":"PPL",
    "gn:name":"Moreh",
    "gn:population":0,
    "gn:timezone":"Asia/Yangon",
    "iso:country":"MM",
    "name:ara_x_preferred":[
        "\u062c\u0628\u0644 \u0627\u0644\u062f\u062d\u064a"
    ],
    "name:ben_x_preferred":[
        "\u09ae\u09cb\u09b0\u09c7\u09b9\u09cd\u200c"
    ],
    "name:bpy_x_preferred":[
        "\u09ae\u09cb\u09b0\u09c7\u09b9\u09cd\u200c"
    ],
    "name:ceb_x_preferred":[
        "Giv\u2018at HaMore"
    ],
    "name:ces_x_preferred":[
        "Giv'at ha-More"
    ],
    "name:fra_x_preferred":[
        "Mont Mor\u00e9h"
    ],
    "name:heb_x_preferred":[
        "\u05d2\u05d1\u05e2\u05ea \u05d4\u05de\u05d5\u05e8\u05d4"
    ],
    "name:jpn_x_preferred":[
        "\u30e2\u30ec\u306e\u4e18"
    ],
    "name:new_x_preferred":[
        "\u092e\u094b\u0930\u0947\u0939"
    ],
    "name:pol_x_preferred":[
        "Giwat ha-More"
    ],
    "name:por_x_preferred":[
        "Mor\u00e9"
    ],
    "name:swe_x_preferred":[
        "Giv\u2018at HaMore"
    ],
    "name:und_x_variant":[
        "Nampalein"
    ],
    "name:vie_x_preferred":[
        "Moreh"
    ],
    "wof:name":"Moreh",
    "wof:placetype":"locality"
},
  "geometry": {"coordinates":[94.31667,24.25],"type":"Point"}
}