{
  "type": "Feature",
  "properties": {
    "gn:admin1_code":"2.0",
    "gn:admin2_code":"MMR004D003",
    "gn:admin3_code":"MMR004002",
    "gn:asciiname":"Rinte",
    "gn:country_code":"MM",
    "gn:dem":715,
    "gn:feature_class":"P",
    "gn:feature_code":"PPL",
    "gn:name":"Rinte",
    "gn:population":0,
    "gn:timezone":"Asia/Yangon",
    "iso:country":"MM",
    "wof:name":"Rinte",
    "wof:placetype":"locality"
},
  "geometry": {"coordinates":[93.78333000000001,22.76667],"type":"Point"}
}