{
  "type": "Feature",
  "properties": {
    "gn:admin1_code":"2.0",
    "gn:admin2_code":"MMR004D003",
    "gn:admin3_code":"MMR004003",
    "gn:asciiname":"Banawhklang",
    "gn:country_code":"MM",
    "gn:dem":925,
    "gn:feature_class":"P",
    "gn:feature_code":"PPL",
    "gn:name":"Banawhklang",
    "gn:population":0,
    "gn:timezone":"Asia/Yangon",
    "iso:country":"MM",
    "wof:name":"Banawhklang",
    "wof:placetype":"locality"
},
  "geometry": {"coordinates":[93.15000000000001,22.61667000000001],"type":"Point"}
}