{
  "type": "Feature",
  "properties": {
    "gn:admin1_code":"11.0",
    "gn:admin2_code":"MMR015D002",
    "gn:admin3_code":"MMR015010",
    "gn:asciiname":"Kongkang",
    "gn:country_code":"MM",
    "gn:dem":1959,
    "gn:feature_class":"P",
    "gn:feature_code":"PPL",
    "gn:name":"Kongkang",
    "gn:population":0,
    "gn:timezone":"Asia/Yangon",
    "iso:country":"MM",
    "wof:name":"Kongkang",
    "wof:placetype":"locality"
},
  "geometry": {"coordinates":[97.63422,23.65438],"type":"Point"}
}