{
  "type": "Feature",
  "properties": {
    "gn:admin1_code":"11.0",
    "gn:admin2_code":"MMR016D001",
    "gn:admin3_code":"MMR016007",
    "gn:asciiname":"Wan Ho-tang",
    "gn:country_code":"MM",
    "gn:dem":313,
    "gn:feature_class":"P",
    "gn:feature_code":"PPL",
    "gn:name":"W\u0101n Ho-tang",
    "gn:population":0,
    "gn:timezone":"Asia/Yangon",
    "iso:country":"MM",
    "wof:name":"Wan Ho-tang",
    "wof:placetype":"locality"
},
  "geometry": {"coordinates":[98.75257999999999,20.99946],"type":"Point"}
}