{
  "type": "Feature",
  "properties": {
    "gn:admin1_code":"3.0",
    "gn:admin2_code":"MMR017D002",
    "gn:admin3_code":"MMR017009",
    "gn:asciiname":"Mahathagyi",
    "gn:country_code":"MM",
    "gn:dem":19,
    "gn:feature_class":"P",
    "gn:feature_code":"PPL",
    "gn:name":"Mahathagyi",
    "gn:population":0,
    "gn:timezone":"Asia/Yangon",
    "iso:country":"MM",
    "name:und_x_variant":[
        "Mahatha",
        "Mahathagyi"
    ],
    "wof:name":"Mahathagyi",
    "wof:placetype":"locality"
},
  "geometry": {"coordinates":[95.4452,17.41212],"type":"Point"}
}