{
  "type": "Feature",
  "properties": {
    "gn:admin1_code":"16.0",
    "gn:admin2_code":"MMR008D001",
    "gn:admin3_code":"MMR008001",
    "gn:asciiname":"Chaunggwa",
    "gn:country_code":"MM",
    "gn:dem":85,
    "gn:feature_class":"P",
    "gn:feature_code":"PPL",
    "gn:name":"Chaunggwa",
    "gn:population":0,
    "gn:timezone":"Asia/Yangon",
    "iso:country":"MM",
    "wof:name":"Chaunggwa",
    "wof:placetype":"locality"
},
  "geometry": {"coordinates":[95.30231000000001,19.04457],"type":"Point"}
}