{
  "type": "Feature",
  "properties": {
    "gn:admin1_code":"11.0",
    "gn:admin2_code":"MMR015D007",
    "gn:admin3_code":"MMR015005",
    "gn:asciiname":"Man Hpangtu",
    "gn:country_code":"MM",
    "gn:dem":1497,
    "gn:feature_class":"P",
    "gn:feature_code":"PPL",
    "gn:name":"M\u0101n Hpangtu",
    "gn:population":0,
    "gn:timezone":"Asia/Yangon",
    "iso:country":"MM",
    "wof:name":"Man Hpangtu",
    "wof:placetype":"locality"
},
  "geometry": {"coordinates":[98.79074,22.58143],"type":"Point"}
}