{
  "type": "Feature",
  "properties": {
    "gn:admin1_code":"3.0",
    "gn:admin2_code":"MMR017D002",
    "gn:admin3_code":"MMR017009",
    "gn:asciiname":"Kyongyaik",
    "gn:country_code":"MM",
    "gn:dem":16,
    "gn:feature_class":"P",
    "gn:feature_code":"PPL",
    "gn:name":"Kyongyaik",
    "gn:population":0,
    "gn:timezone":"Asia/Yangon",
    "iso:country":"MM",
    "wof:name":"Kyongyaik",
    "wof:placetype":"locality"
},
  "geometry": {"coordinates":[95.43075,17.51749],"type":"Point"}
}