{
  "type": "Feature",
  "properties": {
    "gn:admin1_code":"11.0",
    "gn:admin2_code":"MMR015D005",
    "gn:admin3_code":"MMR015023",
    "gn:asciiname":"Man Chienshan",
    "gn:country_code":"MM",
    "gn:dem":1592,
    "gn:feature_class":"P",
    "gn:feature_code":"PPL",
    "gn:name":"M\u0101n Chienshan",
    "gn:population":0,
    "gn:timezone":"Asia/Yangon",
    "iso:country":"MM",
    "wof:name":"Man Chienshan",
    "wof:placetype":"locality"
},
  "geometry": {"coordinates":[98.63805000000001,24.05101],"type":"Point"}
}