{
  "type": "Feature",
  "properties": {
    "gn:admin1_code":"18.0",
    "gn:admin2_code":"MMR018D001",
    "gn:admin3_code":"MMR018003",
    "gn:asciiname":"Sedo",
    "gn:country_code":"MM",
    "gn:dem":269,
    "gn:feature_class":"P",
    "gn:feature_code":"PPL",
    "gn:name":"Sedo",
    "gn:population":0,
    "gn:timezone":"Asia/Yangon",
    "iso:country":"MM",
    "wof:name":"Sedo",
    "wof:placetype":"locality"
},
  "geometry": {"coordinates":[96.3023,20.30315],"type":"Point"}
}