{
  "type": "Feature",
  "properties": {
    "gn:admin1_code":"4.0",
    "gn:admin2_code":"MMR001D003",
    "gn:admin3_code":"MMR001013",
    "gn:asciiname":"Man Ya",
    "gn:country_code":"MM",
    "gn:dem":126,
    "gn:feature_class":"P",
    "gn:feature_code":"PPL",
    "gn:name":"M\u0101n Ya",
    "gn:population":0,
    "gn:timezone":"Asia/Yangon",
    "iso:country":"MM",
    "wof:name":"Man Ya",
    "wof:placetype":"locality"
},
  "geometry": {"coordinates":[97.15548,24.01587],"type":"Point"}
}