{
  "type": "Feature",
  "properties": {
    "gn:admin1_code":"10.0",
    "gn:admin2_code":"MMR005D002",
    "gn:admin3_code":"MMR005005",
    "gn:asciiname":"Ye-e-gon",
    "gn:country_code":"MM",
    "gn:dem":129,
    "gn:feature_class":"P",
    "gn:feature_code":"PPL",
    "gn:name":"Ye-e-gon",
    "gn:population":0,
    "gn:timezone":"Asia/Yangon",
    "iso:country":"MM",
    "wof:name":"Ye-e-gon",
    "wof:placetype":"locality"
},
  "geometry": {"coordinates":[95.66668,22.70124],"type":"Point"}
}