{
  "type": "Feature",
  "properties": {
    "gn:admin1_code":"11.0",
    "gn:admin2_code":"MMR015D001",
    "gn:admin3_code":"MMR015003",
    "gn:asciiname":"Loi-nguen",
    "gn:country_code":"MM",
    "gn:dem":867,
    "gn:feature_class":"P",
    "gn:feature_code":"PPL",
    "gn:name":"Loi-ng\u00fcn",
    "gn:population":0,
    "gn:timezone":"Asia/Yangon",
    "iso:country":"MM",
    "wof:name":"Loi-nguen",
    "wof:placetype":"locality"
},
  "geometry": {"coordinates":[97.87694,22.37963],"type":"Point"}
}