{
  "type": "Feature",
  "properties": {
    "gn:admin1_code":"6.0",
    "gn:admin2_code":"MMR002D002",
    "gn:admin3_code":"MMR002005",
    "gn:asciiname":"Moeng Noi",
    "gn:country_code":"MM",
    "gn:dem":153,
    "gn:feature_class":"P",
    "gn:feature_code":"PPL",
    "gn:name":"M\u00f6ng Noi",
    "gn:population":0,
    "gn:timezone":"Asia/Yangon",
    "iso:country":"MM",
    "wof:name":"Moeng Noi",
    "wof:placetype":"locality"
},
  "geometry": {"coordinates":[97.37,19.19583],"type":"Point"}
}