{
  "type": "Feature",
  "properties": {
    "gn:admin1_code":"11.0",
    "gn:admin2_code":"MMR016D001",
    "gn:admin3_code":"MMR016001",
    "gn:asciiname":"Wan Panghsang",
    "gn:country_code":"MM",
    "gn:dem":1192,
    "gn:feature_class":"P",
    "gn:feature_code":"PPL",
    "gn:name":"W\u0101n Panghsang",
    "gn:population":0,
    "gn:timezone":"Asia/Yangon",
    "iso:country":"MM",
    "name:und_x_variant":[
        "Wan Kaw Panghsang",
        "W\u0101n Panghsang"
    ],
    "wof:name":"Wan Panghsang",
    "wof:placetype":"locality"
},
  "geometry": {"coordinates":[99.66428000000001,21.07476],"type":"Point"}
}