{
  "type": "Feature",
  "properties": {
    "gn:admin1_code":"10.0",
    "gn:admin2_code":"MMR005D002",
    "gn:admin3_code":"MMR005008",
    "gn:asciiname":"Kyaung In",
    "gn:country_code":"MM",
    "gn:dem":152,
    "gn:feature_class":"P",
    "gn:feature_code":"PPL",
    "gn:name":"Kyaung In",
    "gn:population":0,
    "gn:timezone":"Asia/Yangon",
    "iso:country":"MM",
    "wof:name":"Kyaung In",
    "wof:placetype":"locality"
},
  "geometry": {"coordinates":[95.31859,23.39726],"type":"Point"}
}