{
  "type": "Feature",
  "properties": {
    "gn:admin1_code":"1.0",
    "gn:admin2_code":"MMR012D005",
    "gn:admin3_code":"MMR012006",
    "gn:asciiname":"Thila",
    "gn:country_code":"MM",
    "gn:dem":13,
    "gn:feature_class":"P",
    "gn:feature_code":"PPL",
    "gn:name":"Thila",
    "gn:population":0,
    "gn:timezone":"Asia/Yangon",
    "iso:country":"MM",
    "name:fas_x_preferred":[
        "\u062a\u06cc\u0644\u0627"
    ],
    "name:nno_x_preferred":[
        "Thila"
    ],
    "name:und_x_variant":[
        "Thile",
        "Thila"
    ],
    "name:urd_x_preferred":[
        "\u062a\u06cc\u0644\u0627"
    ],
    "wof:name":"Thila",
    "wof:placetype":"locality"
},
  "geometry": {"coordinates":[93.66082,19.94608],"type":"Point"}
}