{
  "type": "Feature",
  "properties": {
    "gn:admin1_code":"11.0",
    "gn:admin2_code":"MMR014D001",
    "gn:admin3_code":"MMR014008",
    "gn:asciiname":"Einmye",
    "gn:country_code":"MM",
    "gn:dem":1098,
    "gn:feature_class":"P",
    "gn:feature_code":"PPL",
    "gn:name":"Einmye",
    "gn:population":0,
    "gn:timezone":"Asia/Yangon",
    "iso:country":"MM",
    "wof:name":"Einmye",
    "wof:placetype":"locality"
},
  "geometry": {"coordinates":[96.85006,21.14464],"type":"Point"}
}