{
  "type": "Feature",
  "properties": {
    "gn:admin1_code":"10.0",
    "gn:admin2_code":"MMR005D002",
    "gn:admin3_code":"MMR005005",
    "gn:asciiname":"Thayetpinzu",
    "gn:country_code":"MM",
    "gn:dem":108,
    "gn:feature_class":"P",
    "gn:feature_code":"PPL",
    "gn:name":"Thayetpinzu",
    "gn:population":0,
    "gn:timezone":"Asia/Yangon",
    "iso:country":"MM",
    "name:und_x_variant":[
        "Thayetpinzuir",
        "Thayetpinzu"
    ],
    "wof:name":"Thayetpinzu",
    "wof:placetype":"locality"
},
  "geometry": {"coordinates":[95.44647999999999,22.77132000000001],"type":"Point"}
}