{
  "type": "Feature",
  "properties": {
    "gn:admin1_code":"11.0",
    "gn:admin2_code":"MMR014D002",
    "gn:admin3_code":"MMR014017",
    "gn:asciiname":"Hwe-hoi",
    "gn:country_code":"MM",
    "gn:dem":683,
    "gn:feature_class":"P",
    "gn:feature_code":"PPL",
    "gn:name":"Hw\u00e8-hoi",
    "gn:population":0,
    "gn:timezone":"Asia/Yangon",
    "iso:country":"MM",
    "wof:name":"Hwe-hoi",
    "wof:placetype":"locality"
},
  "geometry": {"coordinates":[98.3618,21.63526],"type":"Point"}
}