{
  "type": "Feature",
  "properties": {
    "gn:admin1_code":"4.0",
    "gn:admin2_code":"MMR001D003",
    "gn:admin3_code":"MMR001010",
    "gn:asciiname":"Kawngbu",
    "gn:country_code":"MM",
    "gn:dem":357,
    "gn:feature_class":"P",
    "gn:feature_code":"PPL",
    "gn:name":"Kawngbu",
    "gn:population":0,
    "gn:timezone":"Asia/Yangon",
    "iso:country":"MM",
    "wof:name":"Kawngbu",
    "wof:placetype":"locality"
},
  "geometry": {"coordinates":[97.08111,24.46943],"type":"Point"}
}