{
  "type": "Feature",
  "properties": {
    "gn:admin1_code":"12.0",
    "gn:admin2_code":"MMR006D002",
    "gn:admin3_code":"MMR006008",
    "gn:asciiname":"Tagu",
    "gn:country_code":"MM",
    "gn:dem":25,
    "gn:feature_class":"P",
    "gn:feature_code":"PPL",
    "gn:name":"Tagu",
    "gn:population":0,
    "gn:timezone":"Asia/Yangon",
    "iso:country":"MM",
    "name:mya_x_preferred":[
        "\u1010\u1014\u103a\u1001\u1030\u1038\u101c"
    ],
    "wof:name":"Tagu",
    "wof:placetype":"locality"
},
  "geometry": {"coordinates":[99.04528000000001,12.26163],"type":"Point"}
}