{
  "type": "Feature",
  "properties": {
    "gn:admin1_code":"10.0",
    "gn:admin2_code":"MMR005D004",
    "gn:admin3_code":"MMR005024",
    "gn:asciiname":"Taung-yagyidaw",
    "gn:country_code":"MM",
    "gn:dem":183,
    "gn:feature_class":"P",
    "gn:feature_code":"PPL",
    "gn:name":"Taung-yagyidaw",
    "gn:population":0,
    "gn:timezone":"Asia/Yangon",
    "iso:country":"MM",
    "wof:name":"Taung-yagyidaw",
    "wof:placetype":"locality"
},
  "geometry": {"coordinates":[95.65206000000001,23.75276],"type":"Point"}
}