{
  "type": "Feature",
  "properties": {
    "gn:admin1_code":"8.0",
    "gn:admin2_code":"MMR010D004",
    "gn:admin3_code":"MMR010018",
    "gn:asciiname":"Yanginthazi",
    "gn:country_code":"MM",
    "gn:dem":198,
    "gn:feature_class":"P",
    "gn:feature_code":"PPL",
    "gn:name":"Yanginthazi",
    "gn:population":0,
    "gn:timezone":"Asia/Yangon",
    "iso:country":"MM",
    "wof:name":"Yanginthazi",
    "wof:placetype":"locality"
},
  "geometry": {"coordinates":[95.5115,21.31711],"type":"Point"}
}