{
  "type": "Feature",
  "properties": {
    "gn:admin1_code":"11.0",
    "gn:admin2_code":"MMR014D002",
    "gn:admin3_code":"MMR014013",
    "gn:asciiname":"Wan Li",
    "gn:country_code":"MM",
    "gn:dem":1013,
    "gn:feature_class":"P",
    "gn:feature_code":"PPL",
    "gn:name":"W\u0101n Li",
    "gn:population":0,
    "gn:timezone":"Asia/Yangon",
    "iso:country":"MM",
    "name:ara_x_preferred":[
        "\u0648\u0627\u0646 \u0644\u064a"
    ],
    "name:deu_x_preferred":[
        "Wan Li"
    ],
    "name:fra_x_preferred":[
        "Wan Li"
    ],
    "name:nor_x_preferred":[
        "Wan Li"
    ],
    "name:pol_x_preferred":[
        "Wan Li"
    ],
    "name:rus_x_preferred":[
        "\u0412\u0430\u043d\u044c \u041b\u0438"
    ],
    "name:swe_x_preferred":[
        "Wan Li"
    ],
    "name:vie_x_preferred":[
        "V\u1ea1n L\u00fd"
    ],
    "wof:name":"Wan Li",
    "wof:placetype":"locality"
},
  "geometry": {"coordinates":[97.59072,20.70941],"type":"Point"}
}