{
  "type": "Feature",
  "properties": {
    "gn:admin1_code":"18.0",
    "gn:admin2_code":"MMR018D002",
    "gn:admin3_code":"MMR018006",
    "gn:asciiname":"Kadozeik",
    "gn:country_code":"MM",
    "gn:dem":88,
    "gn:feature_class":"P",
    "gn:feature_code":"PPL",
    "gn:name":"Kadozeik",
    "gn:population":0,
    "gn:timezone":"Asia/Yangon",
    "iso:country":"MM",
    "wof:name":"Kadozeik",
    "wof:placetype":"locality"
},
  "geometry": {"coordinates":[96.29416000000001,19.69868],"type":"Point"}
}