{
  "type": "Feature",
  "properties": {
    "gn:admin1_code":"12.0",
    "gn:admin2_code":"MMR006D001",
    "gn:admin3_code":"MMR006001",
    "gn:asciiname":"Hermyingyi",
    "gn:country_code":"MM",
    "gn:dem":233,
    "gn:feature_class":"P",
    "gn:feature_code":"PPL",
    "gn:name":"Hermyingyi",
    "gn:population":0,
    "gn:timezone":"Asia/Yangon",
    "iso:country":"MM",
    "name:und_x_variant":[
        "Hainyingyi",
        "Hermyingyi"
    ],
    "wof:name":"Hermyingyi",
    "wof:placetype":"locality"
},
  "geometry": {"coordinates":[98.3479,14.24705],"type":"Point"}
}