{
  "type": "Feature",
  "properties": {
    "gn:admin1_code":"4.0",
    "gn:admin2_code":"MMR001D001",
    "gn:admin3_code":"MMR001003",
    "gn:asciiname":"Shingbwi",
    "gn:country_code":"MM",
    "gn:dem":1170,
    "gn:feature_class":"P",
    "gn:feature_code":"PPL",
    "gn:name":"Shingbwi",
    "gn:population":0,
    "gn:timezone":"Asia/Yangon",
    "iso:country":"MM",
    "wof:name":"Shingbwi",
    "wof:placetype":"locality"
},
  "geometry": {"coordinates":[98.08526999999999,26.21295],"type":"Point"}
}