{
  "type": "Feature",
  "properties": {
    "gn:admin1_code":"11.0",
    "gn:admin2_code":"MMR016D003",
    "gn:admin3_code":"MMR016011",
    "gn:asciiname":"Wan Man",
    "gn:country_code":"MM",
    "gn:dem":537,
    "gn:feature_class":"P",
    "gn:feature_code":"PPL",
    "gn:name":"W\u0101n Man",
    "gn:population":0,
    "gn:timezone":"Asia/Yangon",
    "iso:country":"MM",
    "wof:name":"Wan Man",
    "wof:placetype":"locality"
},
  "geometry": {"coordinates":[100.39678000000001,21.15461],"type":"Point"}
}