{
  "type": "Feature",
  "properties": {
    "gn:admin1_code":"11.0",
    "gn:admin2_code":"MMR015D001",
    "gn:admin3_code":"MMR015003",
    "gn:asciiname":"Ta-hat",
    "gn:country_code":"MM",
    "gn:dem":862,
    "gn:feature_class":"P",
    "gn:feature_code":"PPL",
    "gn:name":"Ta-hat",
    "gn:population":0,
    "gn:timezone":"Asia/Yangon",
    "iso:country":"MM",
    "wof:name":"Ta-hat",
    "wof:placetype":"locality"
},
  "geometry": {"coordinates":[97.97794,22.37154],"type":"Point"}
}