{
  "type": "Feature",
  "properties": {
    "gn:admin1_code":"10.0",
    "gn:admin2_code":"MMR005D002",
    "gn:admin3_code":"MMR005005",
    "gn:asciiname":"Kyunle",
    "gn:country_code":"MM",
    "gn:dem":106,
    "gn:feature_class":"P",
    "gn:feature_code":"PPL",
    "gn:name":"Kyunl\u00e8",
    "gn:population":0,
    "gn:timezone":"Asia/Yangon",
    "iso:country":"MM",
    "wof:name":"Kyunle",
    "wof:placetype":"locality"
},
  "geometry": {"coordinates":[95.48138,22.70152],"type":"Point"}
}