{
  "type": "Feature",
  "properties": {
    "gn:admin1_code":"3.0",
    "gn:admin2_code":"MMR017D003",
    "gn:admin3_code":"MMR017014",
    "gn:asciiname":"Yanmanaing",
    "gn:country_code":"MM",
    "gn:dem":9,
    "gn:feature_class":"P",
    "gn:feature_code":"PPL",
    "gn:name":"Yanmanaing",
    "gn:population":0,
    "gn:timezone":"Asia/Yangon",
    "iso:country":"MM",
    "wof:name":"Yanmanaing",
    "wof:placetype":"locality"
},
  "geometry": {"coordinates":[95.03883,16.46011],"type":"Point"}
}