{
  "type": "Feature",
  "properties": {
    "gn:admin1_code":"11.0",
    "gn:admin2_code":"MMR016D001",
    "gn:admin3_code":"MMR016003",
    "gn:asciiname":"Pang-hsai-ling",
    "gn:country_code":"MM",
    "gn:dem":1259,
    "gn:feature_class":"P",
    "gn:feature_code":"PPL",
    "gn:name":"P\u0101ng-hsai-ling",
    "gn:population":0,
    "gn:timezone":"Asia/Yangon",
    "iso:country":"MM",
    "wof:name":"Pang-hsai-ling",
    "wof:placetype":"locality"
},
  "geometry": {"coordinates":[99.80352000000001,22.02048],"type":"Point"}
}