{
  "type": "Feature",
  "properties": {
    "gn:admin1_code":"11.0",
    "gn:admin2_code":"MMR015D003",
    "gn:admin3_code":"MMR015015",
    "gn:asciiname":"Lao-ka-ya",
    "gn:country_code":"MM",
    "gn:dem":983,
    "gn:feature_class":"P",
    "gn:feature_code":"PPL",
    "gn:name":"Lao-ka-ya",
    "gn:population":0,
    "gn:timezone":"Asia/Yangon",
    "iso:country":"MM",
    "wof:name":"Lao-ka-ya",
    "wof:placetype":"locality"
},
  "geometry": {"coordinates":[97.30287,23.16442],"type":"Point"}
}