{
  "type": "Feature",
  "properties": {
    "gn:admin1_code":"10.0",
    "gn:asciiname":"Mauaukseik",
    "gn:country_code":"MM",
    "gn:dem":73,
    "gn:feature_class":"P",
    "gn:feature_code":"PPL",
    "gn:name":"Mauaukseik",
    "gn:population":0,
    "gn:timezone":"Asia/Yangon",
    "iso:country":"MM",
    "wof:name":"Mauaukseik",
    "wof:placetype":"locality"
},
  "geometry": {"coordinates":[95.19564,21.75335],"type":"Point"}
}