{
  "type": "Feature",
  "properties": {
    "gn:admin1_code":"16.0",
    "gn:admin2_code":"MMR007D001",
    "gn:admin3_code":"MMR007008",
    "gn:asciiname":"Aukchin",
    "gn:country_code":"MM",
    "gn:dem":52,
    "gn:feature_class":"P",
    "gn:feature_code":"PPL",
    "gn:name":"Aukchin",
    "gn:population":0,
    "gn:timezone":"Asia/Yangon",
    "iso:country":"MM",
    "name:und_x_variant":[
        "Auchin"
    ],
    "wof:name":"Aukchin",
    "wof:placetype":"locality"
},
  "geometry": {"coordinates":[96.95729,17.73607],"type":"Point"}
}