{
  "type": "Feature",
  "properties": {
    "iso:country":"MM",
    "name:cat_x_preferred":[
        "Bhamo"
    ],
    "name:deu_x_preferred":[
        "Bhamo"
    ],
    "name:eng_x_preferred":[
        "Bhamo"
    ],
    "name:fra_x_preferred":[
        "Bhamo"
    ],
    "name:ita_x_preferred":[
        "Bhamo"
    ],
    "name:jpn_x_preferred":[
        "\u30d0\u30e2\u30fc"
    ],
    "name:kor_x_preferred":[
        "\ubc14\ubaa8"
    ],
    "name:mya_x_preferred":[
        "\u1017\u1014\u103a\u1038\u1019\u1031\u102c\u103a\u1019\u103c\u102d\u102f\u1037"
    ],
    "name:nld_x_preferred":[
        "Bhamo"
    ],
    "name:pol_x_preferred":[
        "Banmaw"
    ],
    "name:por_x_preferred":[
        "Bhamo"
    ],
    "name:rus_x_preferred":[
        "\u0411\u0430\u043d\u043c\u043e"
    ],
    "name:rus_x_variant":[
        "\u0411\u0430\u043c\u043e"
    ],
    "name:slv_x_preferred":[
        "Bhamo"
    ],
    "name:spa_x_preferred":[
        "Bhamo"
    ],
    "name:swe_x_preferred":[
        "Bhamo"
    ],
    "name:tha_x_preferred":[
        "\u0e1e\u0e30\u0e42\u0e21"
    ],
    "name:unk_x_variant":[
        "Hsinkai"
    ],
    "name:zho_x_preferred":[
        "\u516b\u83ab"
    ],
    "qs:gn_country":"MM",
    "qs:gn_fcode":"PPL",
    "qs:gn_pop":47920,
    "qs:name":"Bhamo",
    "qs:name_adm0":"Myanmar",
    "qs:name_adm1":"Kachin State",
    "qs:photos":0,
    "qs:photos_1k":0,
    "qs:photos_9k":1,
    "qs:photos_9r":1,
    "qs:photos_all":2,
    "qs:photos_sr":0,
    "qs:placetype":"Town",
    "qs:pop_sr":"7",
    "qs:woe_adm0":23424763,
    "wd:wordcount":479,
    "wof:name":"Bhamo",
    "wof:placetype":"locality",
    "wof:population":47920
},
  "geometry": {"coordinates":[97.23357,24.25256],"type":"Point"}
}