{
  "type": "Feature",
  "properties": {
    "gn:admin1_code":"12.0",
    "gn:admin2_code":"MMR006D002",
    "gn:admin3_code":"MMR006005",
    "gn:asciiname":"Pasut",
    "gn:country_code":"MM",
    "gn:dem":6,
    "gn:feature_class":"P",
    "gn:feature_code":"PPL",
    "gn:name":"Pasut",
    "gn:population":0,
    "gn:timezone":"Asia/Yangon",
    "iso:country":"MM",
    "wof:name":"Pasut",
    "wof:placetype":"locality"
},
  "geometry": {"coordinates":[98.69247,12.68727],"type":"Point"}
}