{
  "type": "Feature",
  "properties": {
    "gn:admin1_code":"4.0",
    "gn:admin2_code":"MMR001D001",
    "gn:admin3_code":"MMR001006",
    "gn:asciiname":"Pasai",
    "gn:country_code":"MM",
    "gn:dem":1077,
    "gn:feature_class":"P",
    "gn:feature_code":"PPL",
    "gn:name":"Pasai",
    "gn:population":0,
    "gn:timezone":"Asia/Yangon",
    "iso:country":"MM",
    "wof:name":"Pasai",
    "wof:placetype":"locality"
},
  "geometry": {"coordinates":[98.3117,26.38957000000001],"type":"Point"}
}