{
  "type": "Feature",
  "properties": {
    "gn:admin1_code":"11.0",
    "gn:admin2_code":"MMR015D002",
    "gn:admin3_code":"MMR015009",
    "gn:asciiname":"Hko-hke",
    "gn:country_code":"MM",
    "gn:dem":1054,
    "gn:feature_class":"P",
    "gn:feature_code":"PPL",
    "gn:name":"Hko-hk\u0113",
    "gn:population":0,
    "gn:timezone":"Asia/Yangon",
    "iso:country":"MM",
    "wof:name":"Hko-hke",
    "wof:placetype":"locality"
},
  "geometry": {"coordinates":[98.01971,23.93172],"type":"Point"}
}