{
  "type": "Feature",
  "properties": {
    "gn:admin1_code":"11.0",
    "gn:admin2_code":"MMR016D001",
    "gn:admin3_code":"MMR016007",
    "gn:asciiname":"Wan Kunkawk",
    "gn:country_code":"MM",
    "gn:dem":294,
    "gn:feature_class":"P",
    "gn:feature_code":"PPL",
    "gn:name":"W\u0101n Kunkawk",
    "gn:population":0,
    "gn:timezone":"Asia/Yangon",
    "iso:country":"MM",
    "wof:name":"Wan Kunkawk",
    "wof:placetype":"locality"
},
  "geometry": {"coordinates":[98.75438,20.92856],"type":"Point"}
}