{
  "type": "Feature",
  "properties": {
    "gn:admin1_code":"11.0",
    "gn:admin2_code":"MMR015D003",
    "gn:admin3_code":"MMR015012",
    "gn:asciiname":"Hpa-lueng",
    "gn:country_code":"MM",
    "gn:dem":1109,
    "gn:feature_class":"P",
    "gn:feature_code":"PPL",
    "gn:name":"Hp\u0101-l\u00fcng",
    "gn:population":0,
    "gn:timezone":"Asia/Yangon",
    "iso:country":"MM",
    "wof:name":"Hpa-lueng",
    "wof:placetype":"locality"
},
  "geometry": {"coordinates":[97.12339,22.47001],"type":"Point"}
}