{
  "type": "Feature",
  "properties": {
    "gn:admin1_code":"11.0",
    "gn:admin2_code":"MMR015D005",
    "gn:admin3_code":"MMR015023",
    "gn:asciiname":"Po-hsa-kong",
    "gn:country_code":"MM",
    "gn:dem":1331,
    "gn:feature_class":"P",
    "gn:feature_code":"PPL",
    "gn:name":"P\u014d-hsa-kong",
    "gn:population":0,
    "gn:timezone":"Asia/Yangon",
    "iso:country":"MM",
    "wof:name":"Po-hsa-kong",
    "wof:placetype":"locality"
},
  "geometry": {"coordinates":[98.44329999999999,23.91984],"type":"Point"}
}