{
  "type": "Feature",
  "properties": {
    "gn:admin1_code":"12.0",
    "gn:admin2_code":"MMR006D002",
    "gn:admin3_code":"MMR006007",
    "gn:asciiname":"Tilu",
    "gn:country_code":"MM",
    "gn:dem":49,
    "gn:feature_class":"P",
    "gn:feature_code":"PPL",
    "gn:name":"Tilu",
    "gn:population":0,
    "gn:timezone":"Asia/Yangon",
    "iso:country":"MM",
    "wof:name":"Tilu",
    "wof:placetype":"locality"
},
  "geometry": {"coordinates":[98.72490999999999,13.14804],"type":"Point"}
}