{
  "type": "Feature",
  "properties": {
    "gn:admin1_code":"10.0",
    "gn:admin2_code":"MMR005D004",
    "gn:admin3_code":"MMR005025",
    "gn:asciiname":"Didok",
    "gn:country_code":"MM",
    "gn:dem":186,
    "gn:feature_class":"P",
    "gn:feature_code":"PPL",
    "gn:name":"Didok",
    "gn:population":0,
    "gn:timezone":"Asia/Yangon",
    "iso:country":"MM",
    "name:und_x_variant":[
        "Dondok",
        "Didok"
    ],
    "wof:name":"Didok",
    "wof:placetype":"locality"
},
  "geometry": {"coordinates":[95.76212,23.83166],"type":"Point"}
}