{
  "type": "Feature",
  "properties": {
    "gn:admin1_code":"11.0",
    "gn:admin2_code":"MMR014D002",
    "gn:admin3_code":"MMR014014",
    "gn:asciiname":"Wan Lao",
    "gn:country_code":"MM",
    "gn:dem":468,
    "gn:feature_class":"P",
    "gn:feature_code":"PPL",
    "gn:name":"W\u0101n Lao",
    "gn:population":0,
    "gn:timezone":"Asia/Yangon",
    "iso:country":"MM",
    "name:und_x_variant":[
        "Lao",
        "W\u0101n Lao"
    ],
    "wof:name":"Wan Lao",
    "wof:placetype":"locality"
},
  "geometry": {"coordinates":[98.43949000000001,21.16494],"type":"Point"}
}