{
  "type": "Feature",
  "properties": {
    "gn:admin1_code":"16.0",
    "gn:admin2_code":"MMR007D001",
    "gn:admin3_code":"MMR007008",
    "gn:asciiname":"Ti-nyamoki",
    "gn:country_code":"MM",
    "gn:dem":152,
    "gn:feature_class":"P",
    "gn:feature_code":"PPL",
    "gn:name":"Ti-nyamoki",
    "gn:population":0,
    "gn:timezone":"Asia/Yangon",
    "iso:country":"MM",
    "wof:name":"Ti-nyamoki",
    "wof:placetype":"locality"
},
  "geometry": {"coordinates":[96.98757999999999,18.14582],"type":"Point"}
}