{
  "type": "Feature",
  "properties": {
    "gn:admin1_code":"12.0",
    "gn:admin2_code":"MMR006D002",
    "gn:admin3_code":"MMR006005",
    "gn:asciiname":"Bok",
    "gn:country_code":"MM",
    "gn:dem":23,
    "gn:feature_class":"P",
    "gn:feature_code":"PPL",
    "gn:name":"Bok",
    "gn:population":0,
    "gn:timezone":"Asia/Yangon",
    "iso:country":"MM",
    "name:afr_x_preferred":[
        "Bok"
    ],
    "name:bos_x_preferred":[
        "Bok"
    ],
    "name:ceb_x_preferred":[
        "Bok"
    ],
    "name:ces_x_preferred":[
        "Bok"
    ],
    "name:deu_x_preferred":[
        "Bok"
    ],
    "name:fry_x_preferred":[
        "Bok"
    ],
    "name:nld_x_preferred":[
        "Bok"
    ],
    "name:nor_x_preferred":[
        "Bok"
    ],
    "name:pol_x_preferred":[
        "Bok"
    ],
    "name:por_x_preferred":[
        "Bok"
    ],
    "name:slv_x_preferred":[
        "Bok"
    ],
    "name:swe_x_preferred":[
        "Bok"
    ],
    "name:und_x_variant":[
        "Bok-ywa",
        "Bok"
    ],
    "name:wln_x_preferred":[
        "Bok"
    ],
    "wof:name":"Bok",
    "wof:placetype":"locality"
},
  "geometry": {"coordinates":[98.86673999999999,12.50662],"type":"Point"}
}