{
  "type": "Feature",
  "properties": {
    "gn:admin1_code":"5.0",
    "gn:admin2_code":"MMR003D003",
    "gn:admin3_code":"MMR003007",
    "gn:asciiname":"Pulei",
    "gn:country_code":"MM",
    "gn:dem":19,
    "gn:elevation":"35.0",
    "gn:feature_class":"P",
    "gn:feature_code":"PPL",
    "gn:name":"Pulei",
    "gn:population":2001,
    "gn:timezone":"Asia/Yangon",
    "iso:country":"MM",
    "wof:name":"Pulei",
    "wof:placetype":"locality",
    "wof:population":2001
},
  "geometry": {"coordinates":[97.8828,16.06243],"type":"Point"}
}