{
  "type": "Feature",
  "properties": {
    "gn:admin1_code":"13.0",
    "gn:admin2_code":"MMR011D002",
    "gn:admin3_code":"MMR011008",
    "gn:asciiname":"Kyabo",
    "gn:country_code":"MM",
    "gn:dem":11,
    "gn:feature_class":"P",
    "gn:feature_code":"PPL",
    "gn:name":"Kyabo",
    "gn:population":0,
    "gn:timezone":"Asia/Yangon",
    "iso:country":"MM",
    "wof:name":"Kyabo",
    "wof:placetype":"locality"
},
  "geometry": {"coordinates":[97.40396,16.54499],"type":"Point"}
}