{
  "type": "Feature",
  "properties": {
    "gn:admin1_code":"8.0",
    "gn:admin2_code":"MMR010D004",
    "gn:admin3_code":"MMR010018",
    "gn:asciiname":"Padatsakon",
    "gn:country_code":"MM",
    "gn:dem":137,
    "gn:feature_class":"P",
    "gn:feature_code":"PPL",
    "gn:name":"Padatsakon",
    "gn:population":0,
    "gn:timezone":"Asia/Yangon",
    "iso:country":"MM",
    "wof:name":"Padatsakon",
    "wof:placetype":"locality"
},
  "geometry": {"coordinates":[95.3772,21.23113],"type":"Point"}
}