{
  "type": "Feature",
  "properties": {
    "gn:admin1_code":"11.0",
    "gn:admin2_code":"MMR014D001",
    "gn:admin3_code":"MMR014008",
    "gn:asciiname":"Long Hsiae",
    "gn:country_code":"MM",
    "gn:dem":811,
    "gn:feature_class":"P",
    "gn:feature_code":"PPL",
    "gn:name":"Long Hsiae",
    "gn:population":0,
    "gn:timezone":"Asia/Yangon",
    "iso:country":"MM",
    "wof:name":"Long Hsiae",
    "wof:placetype":"locality"
},
  "geometry": {"coordinates":[97.10428,21.21546],"type":"Point"}
}