{
  "type": "Feature",
  "properties": {
    "gn:admin1_code":"8.0",
    "gn:admin2_code":"MMR010D002",
    "gn:admin3_code":"MMR010010",
    "gn:asciiname":"Ngapyin-in",
    "gn:country_code":"MM",
    "gn:dem":82,
    "gn:feature_class":"P",
    "gn:feature_code":"PPL",
    "gn:name":"Ngapyin-in",
    "gn:population":0,
    "gn:timezone":"Asia/Yangon",
    "iso:country":"MM",
    "wof:name":"Ngapyin-in",
    "wof:placetype":"locality"
},
  "geometry": {"coordinates":[95.95126,22.60506],"type":"Point"}
}