{
  "type": "Feature",
  "properties": {
    "gn:admin1_code":"16.0",
    "gn:admin2_code":"MMR008D002",
    "gn:admin3_code":"MMR008011",
    "gn:asciiname":"Kayugyaung",
    "gn:country_code":"MM",
    "gn:dem":53,
    "gn:feature_class":"P",
    "gn:feature_code":"PPL",
    "gn:name":"Kayugyaung",
    "gn:population":0,
    "gn:timezone":"Asia/Yangon",
    "iso:country":"MM",
    "wof:name":"Kayugyaung",
    "wof:placetype":"locality"
},
  "geometry": {"coordinates":[95.71259000000001,18.39836],"type":"Point"}
}