{
  "type": "Feature",
  "properties": {
    "gn:admin1_code":"16.0",
    "gn:admin2_code":"MMR007D001",
    "gn:admin3_code":"MMR007001",
    "gn:asciiname":"Tagundaing",
    "gn:country_code":"MM",
    "gn:dem":12,
    "gn:feature_class":"P",
    "gn:feature_code":"PPL",
    "gn:name":"Tagundaing",
    "gn:population":0,
    "gn:timezone":"Asia/Yangon",
    "iso:country":"MM",
    "name:mya_x_preferred":[
        "\u1010\u1036\u1001\u103d\u1014\u103a\u1010\u102d\u102f\u1004\u103a"
    ],
    "name:nno_x_preferred":[
        "Tagundaing"
    ],
    "wof:name":"Tagundaing",
    "wof:placetype":"locality"
},
  "geometry": {"coordinates":[96.44123999999999,17.12534],"type":"Point"}
}