{
  "type": "Feature",
  "properties": {
    "gn:admin1_code":"10.0",
    "gn:admin2_code":"MMR005D008",
    "gn:admin3_code":"MMR005036",
    "gn:asciiname":"Paton",
    "gn:country_code":"MM",
    "gn:dem":1149,
    "gn:feature_class":"P",
    "gn:feature_code":"PPL",
    "gn:name":"Paton",
    "gn:population":0,
    "gn:timezone":"Asia/Yangon",
    "iso:country":"MM",
    "name:deu_x_preferred":[
        "Paton"
    ],
    "name:fra_x_preferred":[
        "Paton"
    ],
    "name:nds_x_preferred":[
        "Paton"
    ],
    "name:nld_x_preferred":[
        "Paton"
    ],
    "name:pol_x_preferred":[
        "Paton"
    ],
    "name:rus_x_preferred":[
        "\u041f\u0430\u0442\u043e\u043d"
    ],
    "name:spa_x_preferred":[
        "Paton"
    ],
    "name:srp_x_preferred":[
        "\u041f\u0430\u0442\u043e\u043d"
    ],
    "name:ukr_x_preferred":[
        "\u041f\u0430\u0442\u043e\u043d"
    ],
    "wof:name":"Paton",
    "wof:placetype":"locality"
},
  "geometry": {"coordinates":[95.37461,25.98844],"type":"Point"}
}