{
  "type": "Feature",
  "properties": {
    "gn:admin1_code":"11.0",
    "gn:admin2_code":"MMR016D003",
    "gn:admin3_code":"MMR016009",
    "gn:asciiname":"Wan Hsenhkamhpu",
    "gn:country_code":"MM",
    "gn:dem":632,
    "gn:elevation":"653.0",
    "gn:feature_class":"P",
    "gn:feature_code":"PPL",
    "gn:name":"W\u0101n Hsenhkamhpu",
    "gn:population":0,
    "gn:timezone":"Asia/Yangon",
    "iso:country":"MM",
    "name:und_x_variant":[
        "W\u0101n Hsenhkampu",
        "Wan Hsenhkamhou",
        "W\u0101n Hsenhkamhpu"
    ],
    "wof:name":"Wan Hsenhkamhpu",
    "wof:placetype":"locality"
},
  "geometry": {"coordinates":[99.84988,20.62246],"type":"Point"}
}