{
  "type": "Feature",
  "properties": {
    "gn:admin1_code":"8.0",
    "gn:admin2_code":"MMR010D007",
    "gn:admin3_code":"MMR010030",
    "gn:asciiname":"Nyaunggaing",
    "gn:country_code":"MM",
    "gn:dem":206,
    "gn:feature_class":"P",
    "gn:feature_code":"PPL",
    "gn:name":"Nyaunggaing",
    "gn:population":0,
    "gn:timezone":"Asia/Yangon",
    "iso:country":"MM",
    "name:und_x_variant":[
        "Nyaungaing",
        "Nyaunggaing"
    ],
    "wof:name":"Nyaunggaing",
    "wof:placetype":"locality"
},
  "geometry": {"coordinates":[95.93432,20.90692],"type":"Point"}
}