{
  "type": "Feature",
  "properties": {
    "gn:admin1_code":"1.0",
    "gn:admin2_code":"MMR012D004",
    "gn:admin3_code":"MMR012015",
    "gn:asciiname":"Kyaukalat",
    "gn:country_code":"MM",
    "gn:dem":14,
    "gn:feature_class":"P",
    "gn:feature_code":"PPL",
    "gn:name":"Kyaukalat",
    "gn:population":0,
    "gn:timezone":"Asia/Yangon",
    "iso:country":"MM",
    "wof:name":"Kyaukalat",
    "wof:placetype":"locality"
},
  "geometry": {"coordinates":[94.33058,18.28295],"type":"Point"}
}