{
  "type": "Feature",
  "properties": {
    "gn:admin1_code":"16.0",
    "gn:admin2_code":"MMR007D001",
    "gn:admin3_code":"MMR007006",
    "gn:asciiname":"Kyadwezu",
    "gn:country_code":"MM",
    "gn:dem":41,
    "gn:feature_class":"P",
    "gn:feature_code":"PPL",
    "gn:name":"Kyadwezu",
    "gn:population":0,
    "gn:timezone":"Asia/Yangon",
    "iso:country":"MM",
    "name:und_x_variant":[
        "Seyoginanauksu",
        "Kyadwezu"
    ],
    "wof:name":"Kyadwezu",
    "wof:placetype":"locality"
},
  "geometry": {"coordinates":[96.58589000000001,18.0472],"type":"Point"}
}