{
  "type": "Feature",
  "properties": {
    "gn:admin1_code":"8.0",
    "gn:admin2_code":"MMR010D007",
    "gn:admin3_code":"MMR010031",
    "gn:asciiname":"Payazu",
    "gn:country_code":"MM",
    "gn:dem":144,
    "gn:feature_class":"P",
    "gn:feature_code":"PPL",
    "gn:name":"Payazu",
    "gn:population":0,
    "gn:timezone":"Asia/Yangon",
    "iso:country":"MM",
    "wof:name":"Payazu",
    "wof:placetype":"locality"
},
  "geometry": {"coordinates":[96.0217,21.17156],"type":"Point"}
}