{
  "type": "Feature",
  "properties": {
    "gn:admin1_code":"16.0",
    "gn:admin2_code":"MMR008D001",
    "gn:admin3_code":"MMR008003",
    "gn:asciiname":"Taunggaing",
    "gn:country_code":"MM",
    "gn:dem":37,
    "gn:feature_class":"P",
    "gn:feature_code":"PPL",
    "gn:name":"Taunggaing",
    "gn:population":0,
    "gn:timezone":"Asia/Yangon",
    "iso:country":"MM",
    "name:und_x_variant":[
        "Taunggain",
        "Taunggaing"
    ],
    "wof:name":"Taunggaing",
    "wof:placetype":"locality"
},
  "geometry": {"coordinates":[94.99285999999999,18.73467],"type":"Point"}
}