{
  "type": "Feature",
  "properties": {
    "gn:admin1_code":"4.0",
    "gn:admin2_code":"MMR001D002",
    "gn:admin3_code":"MMR001008",
    "gn:asciiname":"Tingmongyang",
    "gn:country_code":"MM",
    "gn:dem":164,
    "gn:feature_class":"P",
    "gn:feature_code":"PPL",
    "gn:name":"Tingmongyang",
    "gn:population":0,
    "gn:timezone":"Asia/Yangon",
    "iso:country":"MM",
    "wof:name":"Tingmongyang",
    "wof:placetype":"locality"
},
  "geometry": {"coordinates":[96.86438,25.10672000000001],"type":"Point"}
}