{
  "type": "Feature",
  "properties": {
    "gn:admin1_code":"3.0",
    "gn:admin2_code":"MMR017D002",
    "gn:admin3_code":"MMR017010",
    "gn:asciiname":"Gyogon",
    "gn:country_code":"MM",
    "gn:dem":16,
    "gn:feature_class":"P",
    "gn:feature_code":"PPL",
    "gn:name":"Gyogon",
    "gn:population":0,
    "gn:timezone":"Asia/Yangon",
    "iso:country":"MM",
    "wof:name":"Gyogon",
    "wof:placetype":"locality"
},
  "geometry": {"coordinates":[95.03447,17.58591],"type":"Point"}
}