{
  "type": "Feature",
  "properties": {
    "gn:admin1_code":"15.0",
    "gn:admin2_code":"MMR009D005",
    "gn:admin3_code":"MMR009025",
    "gn:asciiname":"Pagyaung",
    "gn:country_code":"MM",
    "gn:dem":425,
    "gn:feature_class":"P",
    "gn:feature_code":"PPL",
    "gn:name":"Pagyaung",
    "gn:population":0,
    "gn:timezone":"Asia/Yangon",
    "iso:country":"MM",
    "wof:name":"Pagyaung",
    "wof:placetype":"locality"
},
  "geometry": {"coordinates":[94.123,20.96458],"type":"Point"}
}