{
  "type": "Feature",
  "properties": {
    "gn:admin1_code":"3.0",
    "gn:admin2_code":"MMR017D002",
    "gn:admin3_code":"MMR017011",
    "gn:asciiname":"Pauk-aing",
    "gn:country_code":"MM",
    "gn:dem":37,
    "gn:feature_class":"P",
    "gn:feature_code":"PPL",
    "gn:name":"Pauk-aing",
    "gn:population":0,
    "gn:timezone":"Asia/Yangon",
    "iso:country":"MM",
    "wof:name":"Pauk-aing",
    "wof:placetype":"locality"
},
  "geometry": {"coordinates":[95.18165,18.10324],"type":"Point"}
}