{
  "type": "Feature",
  "properties": {
    "gn:admin1_code":"11.0",
    "gn:admin2_code":"MMR014D002",
    "gn:admin3_code":"MMR014017",
    "gn:asciiname":"Hsonhkawn",
    "gn:country_code":"MM",
    "gn:dem":742,
    "gn:feature_class":"P",
    "gn:feature_code":"PPL",
    "gn:name":"Hsonhkawn",
    "gn:population":0,
    "gn:timezone":"Asia/Yangon",
    "iso:country":"MM",
    "wof:name":"Hsonhkawn",
    "wof:placetype":"locality"
},
  "geometry": {"coordinates":[98.30179,21.93364],"type":"Point"}
}