{
  "type": "Feature",
  "properties": {
    "gn:admin1_code":"5.0",
    "gn:admin2_code":"MMR003D003",
    "gn:admin3_code":"MMR003007",
    "gn:asciiname":"Inwa",
    "gn:country_code":"MM",
    "gn:dem":14,
    "gn:feature_class":"P",
    "gn:feature_code":"PPL",
    "gn:name":"Inwa",
    "gn:population":0,
    "gn:timezone":"Asia/Yangon",
    "iso:country":"MM",
    "name:cat_x_preferred":[
        "Innwa"
    ],
    "name:deu_x_preferred":[
        "Inwa"
    ],
    "name:fra_x_preferred":[
        "Ava"
    ],
    "name:glg_x_preferred":[
        "Ava"
    ],
    "name:hin_x_preferred":[
        "\u0906\u0935\u093e"
    ],
    "name:ita_x_preferred":[
        "Ava"
    ],
    "name:kor_x_preferred":[
        "\uc544\ubc14"
    ],
    "name:lat_x_preferred":[
        "Ava"
    ],
    "name:lit_x_preferred":[
        "Inva"
    ],
    "name:mya_x_preferred":[
        "\u1021\u1004\u103a\u1038\u101d\u1019\u103c\u102d\u102f\u1037"
    ],
    "name:nld_x_preferred":[
        "Ava"
    ],
    "name:nor_x_preferred":[
        "Innwa"
    ],
    "name:pol_x_preferred":[
        "Inwa"
    ],
    "name:por_x_preferred":[
        "Ava"
    ],
    "name:rus_x_preferred":[
        "\u0410\u0432\u0430"
    ],
    "name:spa_x_preferred":[
        "Ava"
    ],
    "name:swe_x_preferred":[
        "Ava"
    ],
    "name:tam_x_preferred":[
        "\u0b87\u0ba9\u0bcd\u0bb5\u0bbe"
    ],
    "name:tha_x_preferred":[
        "\u0e2d\u0e31\u0e07\u0e27\u0e30"
    ],
    "name:ukr_x_preferred":[
        "\u0410\u0432\u0430"
    ],
    "name:vie_x_preferred":[
        "Inwa"
    ],
    "wof:name":"Inwa",
    "wof:placetype":"locality"
},
  "geometry": {"coordinates":[98.02500000000001,16.06404],"type":"Point"}
}