{
  "type": "Feature",
  "properties": {
    "gn:admin1_code":"6.0",
    "gn:admin2_code":"MMR002D002",
    "gn:admin3_code":"MMR002005",
    "gn:asciiname":"Ho-hwe-ko-sa-pa",
    "gn:country_code":"MM",
    "gn:dem":525,
    "gn:feature_class":"P",
    "gn:feature_code":"PPL",
    "gn:name":"Ho-hw\u0113-ko-sa-pa",
    "gn:population":0,
    "gn:timezone":"Asia/Yangon",
    "iso:country":"MM",
    "wof:name":"Ho-hwe-ko-sa-pa",
    "wof:placetype":"locality"
},
  "geometry": {"coordinates":[97.44324,19.08299],"type":"Point"}
}