{
  "type": "Feature",
  "properties": {
    "gn:admin1_code":"10.0",
    "gn:admin2_code":"MMR005D004",
    "gn:admin3_code":"MMR005022",
    "gn:asciiname":"Lebo",
    "gn:country_code":"MM",
    "gn:dem":176,
    "gn:feature_class":"P",
    "gn:feature_code":"PPL",
    "gn:name":"Lebo",
    "gn:population":0,
    "gn:timezone":"Asia/Yangon",
    "iso:country":"MM",
    "name:ceb_x_preferred":[
        "Lebo"
    ],
    "name:deu_x_preferred":[
        "Lebo"
    ],
    "name:ind_x_preferred":[
        "Lebo"
    ],
    "name:ita_x_preferred":[
        "Lebo"
    ],
    "name:nld_x_preferred":[
        "Lebo"
    ],
    "name:por_x_preferred":[
        "Lebo"
    ],
    "name:swe_x_preferred":[
        "Lebo"
    ],
    "wof:name":"Lebo",
    "wof:placetype":"locality"
},
  "geometry": {"coordinates":[96.47589000000001,23.81681],"type":"Point"}
}