{
  "type": "Feature",
  "properties": {
    "gn:admin1_code":"12.0",
    "gn:admin2_code":"MMR006D003",
    "gn:admin3_code":"MMR006009",
    "gn:asciiname":"Nalingchan",
    "gn:country_code":"MM",
    "gn:dem":8,
    "gn:feature_class":"P",
    "gn:feature_code":"PPL",
    "gn:name":"Nalingchan",
    "gn:population":0,
    "gn:timezone":"Asia/Yangon",
    "iso:country":"MM",
    "wof:name":"Nalingchan",
    "wof:placetype":"locality"
},
  "geometry": {"coordinates":[98.80977,10.50249],"type":"Point"}
}