{
  "type": "Feature",
  "properties": {
    "gn:admin1_code":"4.0",
    "gn:admin2_code":"MMR001D001",
    "gn:admin3_code":"MMR001005",
    "gn:asciiname":"Sipe-hkalaw",
    "gn:country_code":"MM",
    "gn:dem":1841,
    "gn:feature_class":"P",
    "gn:feature_code":"PPL",
    "gn:name":"Sipe-hkalaw",
    "gn:population":0,
    "gn:timezone":"Asia/Yangon",
    "iso:country":"MM",
    "wof:name":"Sipe-hkalaw",
    "wof:placetype":"locality"
},
  "geometry": {"coordinates":[98.56270000000001,26.21729],"type":"Point"}
}