{
  "type": "Feature",
  "properties": {
    "gn:admin1_code":"12.0",
    "gn:admin2_code":"MMR006D001",
    "gn:admin3_code":"MMR006001",
    "gn:asciiname":"Kado",
    "gn:country_code":"MM",
    "gn:dem":13,
    "gn:feature_class":"P",
    "gn:feature_code":"PPL",
    "gn:name":"Kado",
    "gn:population":0,
    "gn:timezone":"Asia/Yangon",
    "iso:country":"MM",
    "name:ceb_x_preferred":[
        "Kado"
    ],
    "name:deu_x_preferred":[
        "Kado"
    ],
    "name:epo_x_preferred":[
        "Kado"
    ],
    "name:fra_x_preferred":[
        "Kado"
    ],
    "name:rus_x_preferred":[
        "\u041a\u0430\u0434\u043e"
    ],
    "name:srp_x_preferred":[
        "\u041a\u0430\u0434\u043e"
    ],
    "name:swe_x_preferred":[
        "Kado"
    ],
    "wof:name":"Kado",
    "wof:placetype":"locality"
},
  "geometry": {"coordinates":[98.22217000000001,14.04879],"type":"Point"}
}