{
  "type": "Feature",
  "properties": {
    "gn:admin1_code":"11.0",
    "gn:admin2_code":"MMR014D002",
    "gn:admin3_code":"MMR014017",
    "gn:asciiname":"Wan Sin",
    "gn:country_code":"MM",
    "gn:dem":814,
    "gn:feature_class":"P",
    "gn:feature_code":"PPL",
    "gn:name":"W\u0101n Sin",
    "gn:population":0,
    "gn:timezone":"Asia/Yangon",
    "iso:country":"MM",
    "wof:name":"Wan Sin",
    "wof:placetype":"locality"
},
  "geometry": {"coordinates":[98.60574,21.57562],"type":"Point"}
}