{
  "type": "Feature",
  "properties": {
    "gn:admin1_code":"11.0",
    "gn:admin2_code":"MMR014D003",
    "gn:admin3_code":"MMR014020",
    "gn:asciiname":"Nammawwan",
    "gn:country_code":"MM",
    "gn:dem":1133,
    "gn:feature_class":"P",
    "gn:feature_code":"PPL",
    "gn:name":"Nammawwan",
    "gn:population":0,
    "gn:timezone":"Asia/Yangon",
    "iso:country":"MM",
    "wof:name":"Nammawwan",
    "wof:placetype":"locality"
},
  "geometry": {"coordinates":[97.59398,20.29266],"type":"Point"}
}