{
  "type": "Feature",
  "properties": {
    "gn:admin1_code":"11.0",
    "gn:admin2_code":"MMR014D002",
    "gn:admin3_code":"MMR014015",
    "gn:asciiname":"Wan Namtakhkek",
    "gn:country_code":"MM",
    "gn:dem":1058,
    "gn:feature_class":"P",
    "gn:feature_code":"PPL",
    "gn:name":"W\u0101n Namtakhkek",
    "gn:population":0,
    "gn:timezone":"Asia/Yangon",
    "iso:country":"MM",
    "wof:name":"Wan Namtakhkek",
    "wof:placetype":"locality"
},
  "geometry": {"coordinates":[97.97678999999999,21.84743],"type":"Point"}
}