{
  "type": "Feature",
  "properties": {
    "gn:admin1_code":"2.0",
    "gn:admin2_code":"MMR004D001",
    "gn:admin3_code":"MMR004001",
    "gn:asciiname":"Haimual",
    "gn:country_code":"MM",
    "gn:dem":1477,
    "gn:feature_class":"P",
    "gn:feature_code":"PPL",
    "gn:name":"Haimual",
    "gn:population":0,
    "gn:timezone":"Asia/Yangon",
    "iso:country":"MM",
    "wof:name":"Haimual",
    "wof:placetype":"locality"
},
  "geometry": {"coordinates":[93.43333,23.01667],"type":"Point"}
}