{
  "type": "Feature",
  "properties": {
    "gn:admin1_code":"10.0",
    "gn:admin2_code":"MMR005D008",
    "gn:admin3_code":"MMR005033",
    "gn:asciiname":"Maung Te",
    "gn:country_code":"MM",
    "gn:dem":529,
    "gn:feature_class":"P",
    "gn:feature_code":"PPL",
    "gn:name":"Maung Te",
    "gn:population":0,
    "gn:timezone":"Asia/Yangon",
    "iso:country":"MM",
    "wof:name":"Maung Te",
    "wof:placetype":"locality"
},
  "geometry": {"coordinates":[95.35944000000001,25.77351],"type":"Point"}
}