{
  "type": "Feature",
  "properties": {
    "gn:admin1_code":"16.0",
    "gn:admin2_code":"MMR007D002",
    "gn:admin3_code":"MMR007012",
    "gn:asciiname":"Kya-in Atet",
    "gn:country_code":"MM",
    "gn:dem":36,
    "gn:feature_class":"P",
    "gn:feature_code":"PPL",
    "gn:name":"Kya-in Atet",
    "gn:population":0,
    "gn:timezone":"Asia/Yangon",
    "iso:country":"MM",
    "name:und_x_variant":[
        "Kyain-anauk",
        "Kya-in Atet"
    ],
    "wof:name":"Kya-in Atet",
    "wof:placetype":"locality"
},
  "geometry": {"coordinates":[96.58412,18.51445],"type":"Point"}
}