{
  "type": "Feature",
  "properties": {
    "gn:admin1_code":"4.0",
    "gn:admin2_code":"MMR001D001",
    "gn:admin3_code":"MMR001004",
    "gn:asciiname":"Yupbang Ga",
    "gn:country_code":"MM",
    "gn:dem":202,
    "gn:feature_class":"P",
    "gn:feature_code":"PPL",
    "gn:name":"Yupbang Ga",
    "gn:population":0,
    "gn:timezone":"Asia/Yangon",
    "iso:country":"MM",
    "name:und_x_variant":[
        "Tabawng Ga",
        "Yupbang Ga"
    ],
    "wof:name":"Yupbang Ga",
    "wof:placetype":"locality"
},
  "geometry": {"coordinates":[96.48282,26.56752],"type":"Point"}
}