{
  "type": "Feature",
  "properties": {
    "gn:admin1_code":"3.0",
    "gn:admin2_code":"MMR017D005",
    "gn:admin3_code":"MMR017019",
    "gn:asciiname":"Petkaw",
    "gn:country_code":"MM",
    "gn:dem":12,
    "gn:feature_class":"P",
    "gn:feature_code":"PPL",
    "gn:name":"Petkaw",
    "gn:population":0,
    "gn:timezone":"Asia/Yangon",
    "iso:country":"MM",
    "wof:name":"Petkaw",
    "wof:placetype":"locality"
},
  "geometry": {"coordinates":[95.66502,16.8063],"type":"Point"}
}