{
  "type": "Feature",
  "properties": {
    "gn:admin1_code":"11.0",
    "gn:admin2_code":"MMR016D003",
    "gn:admin3_code":"MMR016010",
    "gn:asciiname":"Wan Mu-hsoe Pu-kang",
    "gn:country_code":"MM",
    "gn:dem":1318,
    "gn:feature_class":"P",
    "gn:feature_code":"PPL",
    "gn:name":"W\u0101n M\u016b-hs\u00f6 P\u016b-kang",
    "gn:population":0,
    "gn:timezone":"Asia/Yangon",
    "iso:country":"MM",
    "wof:name":"Wan Mu-hsoe Pu-kang",
    "wof:placetype":"locality"
},
  "geometry": {"coordinates":[99.63800999999999,20.92781],"type":"Point"}
}