{
  "type": "Feature",
  "properties": {
    "gn:admin1_code":"3.0",
    "gn:admin2_code":"MMR017D005",
    "gn:admin3_code":"MMR017019",
    "gn:asciiname":"Payathonzu",
    "gn:country_code":"MM",
    "gn:dem":4,
    "gn:feature_class":"P",
    "gn:feature_code":"PPL",
    "gn:name":"Payathonzu",
    "gn:population":0,
    "gn:timezone":"Asia/Yangon",
    "iso:country":"MM",
    "name:mya_x_preferred":[
        "\u1018\u102f\u101b\u102c\u1038\u101e\u102f\u1036\u1038\u1006\u1030\u1019\u103c\u102d\u102f\u1037"
    ],
    "name:pol_x_preferred":[
        "Payathonzu"
    ],
    "name:rus_x_preferred":[
        "\u041f\u0430\u044f\u0442\u043e\u0443\u043d\u0437\u0443"
    ],
    "name:shn_x_preferred":[
        "\u107d\u101a\u1083\u1038\u1010\u1030\u1004\u103a\u1038\u101e\u1030\u1087\u104a \u101d\u1035\u1004\u103a\u1038"
    ],
    "name:tha_x_preferred":[
        "\u0e1e\u0e30\u0e22\u0e48\u0e32\u0e42\u0e15\u0e49\u0e19\u0e0b\u0e39"
    ],
    "wof:name":"Payathonzu",
    "wof:placetype":"locality"
},
  "geometry": {"coordinates":[95.72257999999999,16.63591],"type":"Point"}
}