{
  "type": "Feature",
  "properties": {
    "gn:admin1_code":"5.0",
    "gn:admin2_code":"MMR003D004",
    "gn:admin3_code":"MMR003003",
    "gn:asciiname":"Kyawprekhi",
    "gn:country_code":"MM",
    "gn:dem":486,
    "gn:feature_class":"P",
    "gn:feature_code":"PPL",
    "gn:name":"Kyawprekhi",
    "gn:population":0,
    "gn:timezone":"Asia/Yangon",
    "iso:country":"MM",
    "name:und_x_variant":[
        "Kyawpaliki",
        "Kyawprekhi"
    ],
    "wof:name":"Kyawprekhi",
    "wof:placetype":"locality"
},
  "geometry": {"coordinates":[97.23275,17.71838],"type":"Point"}
}