{
  "type": "Feature",
  "properties": {
    "gn:admin1_code":"11.0",
    "gn:admin2_code":"MMR014D003",
    "gn:admin3_code":"MMR014019",
    "gn:asciiname":"Yawnghwe",
    "gn:country_code":"MM",
    "gn:dem":1128,
    "gn:feature_class":"P",
    "gn:feature_code":"PPL",
    "gn:name":"Yawnghwe",
    "gn:population":0,
    "gn:timezone":"Asia/Yangon",
    "iso:country":"MM",
    "name:cat_x_preferred":[
        "Yawnghwe"
    ],
    "name:ita_x_preferred":[
        "Yawnghwe"
    ],
    "name:mal_x_preferred":[
        "\u0d2f\u0d3e\u0d7a\u0d18\u0d4d\u0d35\u0d46"
    ],
    "wof:name":"Yawnghwe",
    "wof:placetype":"locality"
},
  "geometry": {"coordinates":[97.67413999999999,20.5064],"type":"Point"}
}