{
  "type": "Feature",
  "properties": {
    "gn:admin1_code":"17.0",
    "gn:admin2_code":"MMR013D003",
    "gn:admin3_code":"MMR013027",
    "gn:asciiname":"Thawundaw",
    "gn:country_code":"MM",
    "gn:dem":11,
    "gn:feature_class":"P",
    "gn:feature_code":"PPL",
    "gn:name":"Thawundaw",
    "gn:population":0,
    "gn:timezone":"Asia/Yangon",
    "iso:country":"MM",
    "wof:name":"Thawundaw",
    "wof:placetype":"locality"
},
  "geometry": {"coordinates":[95.93642,16.75898],"type":"Point"}
}