{
  "type": "Feature",
  "properties": {
    "gn:admin1_code":"10.0",
    "gn:admin2_code":"MMR005D002",
    "gn:admin3_code":"MMR005007",
    "gn:asciiname":"Pauktaw",
    "gn:country_code":"MM",
    "gn:dem":221,
    "gn:feature_class":"P",
    "gn:feature_code":"PPL",
    "gn:name":"Pauktaw",
    "gn:population":0,
    "gn:timezone":"Asia/Yangon",
    "iso:country":"MM",
    "wof:name":"Pauktaw",
    "wof:placetype":"locality"
},
  "geometry": {"coordinates":[95.70305999999999,23.48371],"type":"Point"}
}