{
  "type": "Feature",
  "properties": {
    "gn:admin1_code":"10.0",
    "gn:admin2_code":"MMR005D002",
    "gn:admin3_code":"MMR005007",
    "gn:asciiname":"Pauktaw",
    "gn:country_code":"MM",
    "gn:dem":221,
    "gn:feature_class":"P",
    "gn:feature_code":"PPL",
    "gn:name":"Pauktaw",
    "gn:population":0,
    "gn:timezone":"Asia/Yangon",
    "iso:country":"MM",
    "name:mya_x_preferred":[
        "\u1015\u1031\u102b\u1000\u103a\u1010\u1031\u102c\u1019\u103c\u102d\u102f\u1037"
    ],
    "name:shn_x_preferred":[
        "\u1015\u103d\u1075\u103a\u1089\u1010\u1031\u1083\u1038\u104a \u101d\u1035\u1004\u103a\u1038"
    ],
    "wof:name":"Pauktaw",
    "wof:placetype":"locality"
},
  "geometry": {"coordinates":[95.70305999999999,23.48371],"type":"Point"}
}