{
  "type": "Feature",
  "properties": {
    "gn:admin1_code":"10.0",
    "gn:admin2_code":"MMR005D002",
    "gn:admin3_code":"MMR005004",
    "gn:asciiname":"Shadaw",
    "gn:country_code":"MM",
    "gn:dem":103,
    "gn:feature_class":"P",
    "gn:feature_code":"PPL",
    "gn:name":"Shadaw",
    "gn:population":0,
    "gn:timezone":"Asia/Yangon",
    "iso:country":"MM",
    "name:fra_x_preferred":[
        "Shadaw"
    ],
    "name:mya_x_preferred":[
        "\u101b\u103e\u102c\u1038\u1010\u1031\u102c\u1019\u103c\u102d\u102f\u1037"
    ],
    "name:shn_x_preferred":[
        "\u101e\u103b\u1083\u1038\u1010\u1031\u1083\u1038\u104a \u101d\u1035\u1004\u103a\u1038"
    ],
    "wof:name":"Shadaw",
    "wof:placetype":"locality"
},
  "geometry": {"coordinates":[95.69462,22.53526],"type":"Point"}
}