{
  "type": "Feature",
  "properties": {
    "gn:admin1_code":"11.0",
    "gn:admin2_code":"MMR016D001",
    "gn:admin3_code":"MMR016002",
    "gn:asciiname":"Wan Ho-nawng",
    "gn:country_code":"MM",
    "gn:dem":1247,
    "gn:feature_class":"P",
    "gn:feature_code":"PPL",
    "gn:name":"W\u0101n Ho-nawng",
    "gn:population":0,
    "gn:timezone":"Asia/Yangon",
    "iso:country":"MM",
    "wof:name":"Wan Ho-nawng",
    "wof:placetype":"locality"
},
  "geometry": {"coordinates":[99.36997,21.68353],"type":"Point"}
}