{
  "type": "Feature",
  "properties": {
    "gn:admin1_code":"2.0",
    "gn:admin2_code":"MMR004D001",
    "gn:admin3_code":"MMR004005",
    "gn:asciiname":"Serpui",
    "gn:country_code":"MM",
    "gn:dem":1135,
    "gn:feature_class":"P",
    "gn:feature_code":"PPL",
    "gn:name":"Serpui",
    "gn:population":0,
    "gn:timezone":"Asia/Yangon",
    "iso:country":"MM",
    "wof:name":"Serpui",
    "wof:placetype":"locality"
},
  "geometry": {"coordinates":[93.41667,23.91667],"type":"Point"}
}