{
  "type": "Feature",
  "properties": {
    "gn:admin1_code":"11.0",
    "gn:admin2_code":"MMR015D003",
    "gn:admin3_code":"MMR015014",
    "gn:asciiname":"Koengsoeng",
    "gn:country_code":"MM",
    "gn:dem":429,
    "gn:feature_class":"P",
    "gn:feature_code":"PPL",
    "gn:name":"K\u00f6ngs\u00f6ng",
    "gn:population":0,
    "gn:timezone":"Asia/Yangon",
    "iso:country":"MM",
    "wof:name":"Koengsoeng",
    "wof:placetype":"locality"
},
  "geometry": {"coordinates":[97.31291,22.63306],"type":"Point"}
}