{
  "type": "Feature",
  "properties": {
    "gn:admin1_code":"11.0",
    "gn:admin2_code":"MMR015D006",
    "gn:admin3_code":"MMR015021",
    "gn:asciiname":"Man Namsi-yang",
    "gn:country_code":"MM",
    "gn:dem":647,
    "gn:feature_class":"P",
    "gn:feature_code":"PPL",
    "gn:name":"M\u0101n Namsi-yang",
    "gn:population":0,
    "gn:timezone":"Asia/Yangon",
    "iso:country":"MM",
    "name:und_x_variant":[
        "Man Namsi-uang",
        "M\u0101n Namsi-yang"
    ],
    "wof:name":"Man Namsi-yang",
    "wof:placetype":"locality"
},
  "geometry": {"coordinates":[98.81910999999999,23.16387000000001],"type":"Point"}
}