{
  "type": "Feature",
  "properties": {
    "gn:admin1_code":"10.0",
    "gn:admin2_code":"MMR005D002",
    "gn:admin3_code":"MMR005008",
    "gn:asciiname":"Nwalabo",
    "gn:country_code":"MM",
    "gn:dem":167,
    "gn:feature_class":"P",
    "gn:feature_code":"PPL",
    "gn:name":"Nwalabo",
    "gn:population":0,
    "gn:timezone":"Asia/Yangon",
    "iso:country":"MM",
    "wof:name":"Nwalabo",
    "wof:placetype":"locality"
},
  "geometry": {"coordinates":[95.29503,23.42217],"type":"Point"}
}