{
  "type": "Feature",
  "properties": {
    "gn:admin1_code":"12.0",
    "gn:admin2_code":"MMR006D001",
    "gn:admin3_code":"MMR006003",
    "gn:asciiname":"Kyaukse",
    "gn:country_code":"MM",
    "gn:dem":27,
    "gn:feature_class":"P",
    "gn:feature_code":"PPL",
    "gn:name":"Kyaukse",
    "gn:population":0,
    "gn:timezone":"Asia/Yangon",
    "iso:country":"MM",
    "wof:name":"Kyaukse",
    "wof:placetype":"locality"
},
  "geometry": {"coordinates":[98.48246,13.40578],"type":"Point"}
}