{
  "type": "Feature",
  "properties": {
    "gn:admin1_code":"12.0",
    "gn:admin2_code":"MMR006D001",
    "gn:admin3_code":"MMR006003",
    "gn:asciiname":"Kyaukse",
    "gn:country_code":"MM",
    "gn:dem":27,
    "gn:feature_class":"P",
    "gn:feature_code":"PPL",
    "gn:name":"Kyaukse",
    "gn:population":0,
    "gn:timezone":"Asia/Yangon",
    "iso:country":"MM",
    "name:cat_x_preferred":[
        "Kyaukse"
    ],
    "name:ceb_x_preferred":[
        "Kyaukse"
    ],
    "name:fra_x_preferred":[
        "Kyaukse"
    ],
    "name:mya_x_preferred":[
        "\u1000\u103b\u1031\u102c\u1000\u103a\u1006\u100a\u103a\u1019\u103c\u102d\u102f\u1037"
    ],
    "name:sco_x_preferred":[
        "Kyaukse"
    ],
    "name:shn_x_preferred":[
        "\u1075\u103b\u103d\u1075\u103a\u1089\u101e\u1084\u1087\u104a \u101d\u1035\u1004\u103a\u1038"
    ],
    "name:swe_x_preferred":[
        "Kyaukse"
    ],
    "name:vie_x_preferred":[
        "Kyaukse"
    ],
    "wof:name":"Kyaukse",
    "wof:placetype":"locality"
},
  "geometry": {"coordinates":[98.48246,13.40578],"type":"Point"}
}