{
  "type": "Feature",
  "properties": {
    "gn:admin1_code":"4.0",
    "gn:admin2_code":"MMR001D001",
    "gn:admin3_code":"MMR001004",
    "gn:asciiname":"Kawnan Ga",
    "gn:country_code":"MM",
    "gn:dem":831,
    "gn:feature_class":"P",
    "gn:feature_code":"PPL",
    "gn:name":"Kawnan Ga",
    "gn:population":0,
    "gn:timezone":"Asia/Yangon",
    "iso:country":"MM",
    "wof:name":"Kawnan Ga",
    "wof:placetype":"locality"
},
  "geometry": {"coordinates":[96.93226,25.85042],"type":"Point"}
}