{
  "type": "Feature",
  "properties": {
    "gn:admin1_code":"10.0",
    "gn:admin2_code":"MMR005D009",
    "gn:admin3_code":"MMR005019",
    "gn:asciiname":"Aingma",
    "gn:country_code":"MM",
    "gn:dem":278,
    "gn:feature_class":"P",
    "gn:feature_code":"PPL",
    "gn:name":"Aingma",
    "gn:population":0,
    "gn:timezone":"Asia/Yangon",
    "iso:country":"MM",
    "wof:name":"Aingma",
    "wof:placetype":"locality"
},
  "geometry": {"coordinates":[94.5621,22.02577],"type":"Point"}
}