{
  "type": "Feature",
  "properties": {
    "gn:admin1_code":"10.0",
    "gn:admin2_code":"MMR005D007",
    "gn:admin3_code":"MMR005032",
    "gn:asciiname":"Myintha",
    "gn:country_code":"MM",
    "gn:dem":139,
    "gn:feature_class":"P",
    "gn:feature_code":"PPL",
    "gn:name":"Myintha",
    "gn:population":0,
    "gn:timezone":"Asia/Yangon",
    "iso:country":"MM",
    "name:urd_x_preferred":[
        "\u0645\u0627\u0626\u06cc\u0646\u062a\u06be\u0627"
    ],
    "wof:name":"Myintha",
    "wof:placetype":"locality"
},
  "geometry": {"coordinates":[94.91513999999999,24.35419],"type":"Point"}
}