{
  "type": "Feature",
  "properties": {
    "gn:admin1_code":"11.0",
    "gn:admin2_code":"MMR015D003",
    "gn:admin3_code":"MMR015015",
    "gn:asciiname":"Masawpaw",
    "gn:country_code":"MM",
    "gn:dem":711,
    "gn:feature_class":"P",
    "gn:feature_code":"PPL",
    "gn:name":"Masawpaw",
    "gn:population":0,
    "gn:timezone":"Asia/Yangon",
    "iso:country":"MM",
    "name:und_x_variant":[
        "N\u0101-sawpaw",
        "Masawpaw"
    ],
    "wof:name":"Masawpaw",
    "wof:placetype":"locality"
},
  "geometry": {"coordinates":[97.36749,22.78091],"type":"Point"}
}