{
  "type": "Feature",
  "properties": {
    "gn:admin1_code":"11.0",
    "gn:admin2_code":"MMR014D002",
    "gn:admin3_code":"MMR014011",
    "gn:asciiname":"Namhkanlai",
    "gn:country_code":"MM",
    "gn:dem":1593,
    "gn:feature_class":"P",
    "gn:feature_code":"PPL",
    "gn:name":"Namhkanlai",
    "gn:population":0,
    "gn:timezone":"Asia/Yangon",
    "iso:country":"MM",
    "wof:name":"Namhkanlai",
    "wof:placetype":"locality"
},
  "geometry": {"coordinates":[97.48349,20.63023],"type":"Point"}
}