{
  "type": "Feature",
  "properties": {
    "gn:admin1_code":"11.0",
    "gn:admin2_code":"MMR016D003",
    "gn:admin3_code":"MMR016011",
    "gn:asciiname":"Wan Ra-sa-hpi-sai",
    "gn:country_code":"MM",
    "gn:dem":852,
    "gn:feature_class":"P",
    "gn:feature_code":"PPL",
    "gn:name":"W\u0101n Ra-sa-hpi-sai",
    "gn:population":0,
    "gn:timezone":"Asia/Yangon",
    "iso:country":"MM",
    "wof:name":"Wan Ra-sa-hpi-sai",
    "wof:placetype":"locality"
},
  "geometry": {"coordinates":[100.99930000000001,21.69164],"type":"Point"}
}