{
  "type": "Feature",
  "properties": {
    "gn:admin1_code":"11.0",
    "gn:admin2_code":"MMR016D003",
    "gn:admin3_code":"MMR016011",
    "gn:asciiname":"Wan Sa-hta-ni",
    "gn:country_code":"MM",
    "gn:dem":837,
    "gn:feature_class":"P",
    "gn:feature_code":"PPL",
    "gn:name":"W\u0101n S\u0101-hta-ni",
    "gn:population":0,
    "gn:timezone":"Asia/Yangon",
    "iso:country":"MM",
    "wof:name":"Wan Sa-hta-ni",
    "wof:placetype":"locality"
},
  "geometry": {"coordinates":[100.84307,21.3438],"type":"Point"}
}