{
  "type": "Feature",
  "properties": {
    "gn:admin1_code":"15.0",
    "gn:admin2_code":"MMR009D002",
    "gn:admin3_code":"MMR009007",
    "gn:asciiname":"Tharapi",
    "gn:country_code":"MM",
    "gn:dem":139,
    "gn:feature_class":"P",
    "gn:feature_code":"PPL",
    "gn:name":"Tharapi",
    "gn:population":0,
    "gn:timezone":"Asia/Yangon",
    "iso:country":"MM",
    "wof:name":"Tharapi",
    "wof:placetype":"locality"
},
  "geometry": {"coordinates":[94.55222000000001,20.14654],"type":"Point"}
}