{
  "type": "Feature",
  "properties": {
    "gn:admin1_code":"6.0",
    "gn:admin2_code":"MMR002D001",
    "gn:admin3_code":"MMR002004",
    "gn:asciiname":"Daw Ka-to",
    "gn:country_code":"MM",
    "gn:dem":711,
    "gn:feature_class":"P",
    "gn:feature_code":"PPL",
    "gn:name":"Daw Ka-t\u014d",
    "gn:population":0,
    "gn:timezone":"Asia/Yangon",
    "iso:country":"MM",
    "wof:name":"Daw Ka-to",
    "wof:placetype":"locality"
},
  "geometry": {"coordinates":[97.53907,19.48879],"type":"Point"}
}