{
  "type": "Feature",
  "properties": {
    "gn:admin1_code":"2.0",
    "gn:admin2_code":"MMR004D002",
    "gn:admin3_code":"MMR004006",
    "gn:asciiname":"Kumtsawngtsa",
    "gn:country_code":"MM",
    "gn:dem":927,
    "gn:feature_class":"P",
    "gn:feature_code":"PPL",
    "gn:name":"Kumtsawngtsa",
    "gn:population":0,
    "gn:timezone":"Asia/Yangon",
    "iso:country":"MM",
    "wof:name":"Kumtsawngtsa",
    "wof:placetype":"locality"
},
  "geometry": {"coordinates":[93.53814,21.19434],"type":"Point"}
}