{
  "type": "Feature",
  "properties": {
    "gn:admin1_code":"10.0",
    "gn:admin2_code":"MMR005D005",
    "gn:admin3_code":"MMR005027",
    "gn:asciiname":"Kalemyo",
    "gn:country_code":"MM",
    "gn:dem":119,
    "gn:feature_class":"P",
    "gn:feature_code":"PPL",
    "gn:name":"Kalemyo",
    "gn:population":0,
    "gn:timezone":"Asia/Yangon",
    "iso:country":"MM",
    "name:mya_x_preferred":[
        "Kalaymyo"
    ],
    "wof:name":"Kalemyo",
    "wof:placetype":"locality"
},
  "geometry": {"coordinates":[94.06404999999999,23.19014],"type":"Point"}
}