{
  "type": "Feature",
  "properties": {
    "gn:country":"MM",
    "gn:fcode":"PPLX",
    "gn:population":0,
    "iso:country":"MM",
    "name:eng_x_preferred":[
        "Ashebyin"
    ],
    "qs:gn_adm0_cc":"MM",
    "qs:gn_fcode":"PPLX",
    "qs:gn_local":1311874,
    "qs:gn_namadm1":"08",
    "qs:gn_name":"Ashebyin",
    "qs:local_max":2015,
    "qs:local_sum":2465,
    "qs:localhoods":2,
    "qs:name":"Ashebyin",
    "qs:name_adm0":"Myanmar",
    "qs:name_adm1":"Mandalay",
    "qs:name_local":"Mandalay",
    "qs:photo_max":131,
    "qs:photo_sum":450,
    "qs:placetype":"Suburb",
    "qs:quad_count":29,
    "qs:woe_adm0":23424763,
    "qs:woe_adm1":2344817,
    "qs:woe_adm2":0,
    "qs:woe_lau":0,
    "qs:woe_local":1017586,
    "qs:woe_ver":"7.10.0",
    "qs_pg:aaroncc":"MM",
    "qs_pg:gn_country":"MM",
    "qs_pg:gn_fcode":"PPLX",
    "qs_pg:gn_pop":0,
    "qs_pg:name":"Ashebyin",
    "qs_pg:name_adm0":"Myanmar",
    "qs_pg:name_adm1":"Mandalay",
    "qs_pg:photos":405,
    "qs_pg:photos_1k":82,
    "qs_pg:photos_9k":2,
    "qs_pg:photos_9r":5,
    "qs_pg:photos_all":405,
    "qs_pg:photos_sr":6,
    "qs_pg:pop_sr":0,
    "qs_pg:qs_pg_placetype":"neighbourhood",
    "qs_pg:qs_pg_placetype_gp":"Suburb",
    "qs_pg:woe_adm0":23424763,
    "wof:lang":[
        "eng"
    ],
    "wof:name":"Ashebyin",
    "wof:placetype":"neighbourhood"
},
  "geometry": {"coordinates":[96.11318,22.004421],"type":"Point"}
}