{
  "type": "Feature",
  "properties": {
    "gn:admin1_code":"5.0",
    "gn:admin2_code":"MMR003D001",
    "gn:admin3_code":"MMR003001",
    "gn:asciiname":"Myainggale",
    "gn:country_code":"MM",
    "gn:dem":17,
    "gn:feature_class":"P",
    "gn:feature_code":"PPL",
    "gn:name":"Myainggale",
    "gn:population":0,
    "gn:timezone":"Asia/Yangon",
    "iso:country":"MM",
    "wof:name":"Myainggale",
    "wof:placetype":"locality"
},
  "geometry": {"coordinates":[97.59962,16.86685],"type":"Point"}
}