{
  "type": "Feature",
  "properties": {
    "gn:admin1_code":"11.0",
    "gn:admin2_code":"MMR015D006",
    "gn:admin3_code":"MMR015007",
    "gn:asciiname":"Hkrawn-chai",
    "gn:country_code":"MM",
    "gn:dem":1700,
    "gn:feature_class":"P",
    "gn:feature_code":"PPL",
    "gn:name":"Hkrawn-chai",
    "gn:population":0,
    "gn:timezone":"Asia/Yangon",
    "iso:country":"MM",
    "wof:name":"Hkrawn-chai",
    "wof:placetype":"locality"
},
  "geometry": {"coordinates":[99.2675,22.98829],"type":"Point"}
}