{
  "type": "Feature",
  "properties": {
    "gn:admin1_code":"5.0",
    "gn:admin2_code":"MMR003D003",
    "gn:admin3_code":"MMR003007",
    "gn:asciiname":"Winyaw Seikgyi",
    "gn:country_code":"MM",
    "gn:dem":22,
    "gn:feature_class":"P",
    "gn:feature_code":"PPL",
    "gn:name":"Winyaw Seikgyi",
    "gn:population":0,
    "gn:timezone":"Asia/Yangon",
    "iso:country":"MM",
    "wof:name":"Winyaw Seikgyi",
    "wof:placetype":"locality"
},
  "geometry": {"coordinates":[97.96106,15.96092],"type":"Point"}
}