{
  "type": "Feature",
  "properties": {
    "gn:admin1_code":"10.0",
    "gn:admin2_code":"MMR005D002",
    "gn:admin3_code":"MMR005005",
    "gn:asciiname":"Chaungzon",
    "gn:country_code":"MM",
    "gn:dem":135,
    "gn:feature_class":"P",
    "gn:feature_code":"PPL",
    "gn:name":"Chaungzon",
    "gn:population":0,
    "gn:timezone":"Asia/Yangon",
    "iso:country":"MM",
    "wof:name":"Chaungzon",
    "wof:placetype":"locality"
},
  "geometry": {"coordinates":[95.66605,22.74423],"type":"Point"}
}