{
  "type": "Feature",
  "properties": {
    "gn:admin1_code":"11.0",
    "gn:admin2_code":"MMR015D001",
    "gn:admin3_code":"MMR015001",
    "gn:asciiname":"Man-meng-kyeng",
    "gn:country_code":"MM",
    "gn:dem":672,
    "gn:feature_class":"P",
    "gn:feature_code":"PPL",
    "gn:name":"M\u0101n-meng-kyeng",
    "gn:population":0,
    "gn:timezone":"Asia/Yangon",
    "iso:country":"MM",
    "wof:name":"Man-meng-kyeng",
    "wof:placetype":"locality"
},
  "geometry": {"coordinates":[97.75868,22.81758],"type":"Point"}
}