{
  "type": "Feature",
  "properties": {
    "gn:admin1_code":"3.0",
    "gn:admin2_code":"MMR017D003",
    "gn:admin3_code":"MMR017014",
    "gn:asciiname":"Labutkala",
    "gn:country_code":"MM",
    "gn:dem":10,
    "gn:feature_class":"P",
    "gn:feature_code":"PPL",
    "gn:name":"Labutkala",
    "gn:population":0,
    "gn:timezone":"Asia/Yangon",
    "iso:country":"MM",
    "wof:name":"Labutkala",
    "wof:placetype":"locality"
},
  "geometry": {"coordinates":[94.97649,16.51125],"type":"Point"}
}