{
  "type": "Feature",
  "properties": {
    "gn:admin1_code":"2.0",
    "gn:asciiname":"Talegyin",
    "gn:country_code":"MM",
    "gn:dem":208,
    "gn:feature_class":"P",
    "gn:feature_code":"PPL",
    "gn:name":"Tal\u00e8gyin",
    "gn:population":0,
    "gn:timezone":"Asia/Yangon",
    "iso:country":"MM",
    "wof:name":"Talegyin",
    "wof:placetype":"locality"
},
  "geometry": {"coordinates":[94.14444,20.71119],"type":"Point"}
}