{
  "type": "Feature",
  "properties": {
    "gn:admin1_code":"10.0",
    "gn:admin2_code":"MMR005D005",
    "gn:admin3_code":"MMR005029",
    "gn:asciiname":"Pindin",
    "gn:country_code":"MM",
    "gn:dem":95,
    "gn:feature_class":"P",
    "gn:feature_code":"PPL",
    "gn:name":"Pindin",
    "gn:population":0,
    "gn:timezone":"Asia/Yangon",
    "iso:country":"MM",
    "wof:name":"Pindin",
    "wof:placetype":"locality"
},
  "geometry": {"coordinates":[94.62242000000001,22.89911],"type":"Point"}
}