{
  "type": "Feature",
  "properties": {
    "gn:admin1_code":"10.0",
    "gn:admin2_code":"MMR005D007",
    "gn:admin3_code":"MMR005032",
    "gn:asciiname":"Segyaung",
    "gn:country_code":"MM",
    "gn:dem":116,
    "gn:feature_class":"P",
    "gn:feature_code":"PPL",
    "gn:name":"Segyaung",
    "gn:population":0,
    "gn:timezone":"Asia/Yangon",
    "iso:country":"MM",
    "wof:name":"Segyaung",
    "wof:placetype":"locality"
},
  "geometry": {"coordinates":[94.76515999999999,24.27451],"type":"Point"}
}