{
  "type": "Feature",
  "properties": {
    "gn:admin1_code":"11.0",
    "gn:admin2_code":"MMR015D002",
    "gn:admin3_code":"MMR015011",
    "gn:asciiname":"Man Pu-hsi-htao",
    "gn:country_code":"MM",
    "gn:dem":1757,
    "gn:feature_class":"P",
    "gn:feature_code":"PPL",
    "gn:name":"M\u0101n P\u016b-hsi-htao",
    "gn:population":0,
    "gn:timezone":"Asia/Yangon",
    "iso:country":"MM",
    "name:und_x_variant":[
        "M\u0101n P\u014d-hsi-htao",
        "M\u0101n P\u016b-hsi-htao"
    ],
    "wof:name":"Man Pu-hsi-htao",
    "wof:placetype":"locality"
},
  "geometry": {"coordinates":[98.46420999999999,23.67084],"type":"Point"}
}