{
  "type": "Feature",
  "properties": {
    "gn:admin1_code":"11.0",
    "gn:admin2_code":"MMR015D003",
    "gn:admin3_code":"MMR015014",
    "gn:asciiname":"Namakwan",
    "gn:country_code":"MM",
    "gn:dem":653,
    "gn:feature_class":"P",
    "gn:feature_code":"PPL",
    "gn:name":"Namakwan",
    "gn:population":0,
    "gn:timezone":"Asia/Yangon",
    "iso:country":"MM",
    "name:und_x_variant":[
        "N\u0101-mankwan",
        "Namakwan"
    ],
    "wof:name":"Namakwan",
    "wof:placetype":"locality"
},
  "geometry": {"coordinates":[97.38585,22.28513],"type":"Point"}
}