{
  "type": "Feature",
  "properties": {
    "gn:admin1_code":"1.0",
    "gn:admin2_code":"MMR012D005",
    "gn:admin3_code":"MMR012006",
    "gn:asciiname":"Kyaukhpya",
    "gn:country_code":"MM",
    "gn:dem":1,
    "gn:feature_class":"P",
    "gn:feature_code":"PPL",
    "gn:name":"Kyaukhpya",
    "gn:population":0,
    "gn:timezone":"Asia/Yangon",
    "iso:country":"MM",
    "wof:name":"Kyaukhpya",
    "wof:placetype":"locality"
},
  "geometry": {"coordinates":[93.73963999999999,19.69711],"type":"Point"}
}