{
  "type": "Feature",
  "properties": {
    "gn:admin1_code":"6.0",
    "gn:admin2_code":"MMR002D001",
    "gn:admin3_code":"MMR002002",
    "gn:asciiname":"Hti-pa-a-daw",
    "gn:country_code":"MM",
    "gn:dem":925,
    "gn:feature_class":"P",
    "gn:feature_code":"PPL",
    "gn:name":"Hti-pa-a-daw",
    "gn:population":0,
    "gn:timezone":"Asia/Yangon",
    "iso:country":"MM",
    "wof:name":"Hti-pa-a-daw",
    "wof:placetype":"locality"
},
  "geometry": {"coordinates":[97.20692,19.5154],"type":"Point"}
}