{
  "type": "Feature",
  "properties": {
    "gn:admin1_code":"2.0",
    "gn:admin2_code":"MMR004D002",
    "gn:admin3_code":"MMR004008",
    "gn:asciiname":"Pangdag",
    "gn:country_code":"MM",
    "gn:dem":1110,
    "gn:feature_class":"P",
    "gn:feature_code":"PPL",
    "gn:name":"Pangdag",
    "gn:population":0,
    "gn:timezone":"Asia/Yangon",
    "iso:country":"MM",
    "wof:name":"Pangdag",
    "wof:placetype":"locality"
},
  "geometry": {"coordinates":[93.97118,21.05635],"type":"Point"}
}