{
  "type": "Feature",
  "properties": {
    "gn:admin1_code":"12.0",
    "gn:admin2_code":"MMR006D002",
    "gn:admin3_code":"MMR006007",
    "gn:asciiname":"Htitopya",
    "gn:country_code":"MM",
    "gn:dem":101,
    "gn:feature_class":"P",
    "gn:feature_code":"PPL",
    "gn:name":"Htitopya",
    "gn:population":0,
    "gn:timezone":"Asia/Yangon",
    "iso:country":"MM",
    "wof:name":"Htitopya",
    "wof:placetype":"locality"
},
  "geometry": {"coordinates":[98.83327,12.92598],"type":"Point"}
}