{
  "type": "Feature",
  "properties": {
    "gn:admin1_code":"15.0",
    "gn:admin2_code":"MMR009D004",
    "gn:admin3_code":"MMR009021",
    "gn:asciiname":"Indein",
    "gn:country_code":"MM",
    "gn:dem":199,
    "gn:feature_class":"P",
    "gn:feature_code":"PPL",
    "gn:name":"Indein",
    "gn:population":0,
    "gn:timezone":"Asia/Yangon",
    "iso:country":"MM",
    "name:und_x_variant":[
        "Yndein",
        "Indein"
    ],
    "wof:name":"Indein",
    "wof:placetype":"locality"
},
  "geometry": {"coordinates":[94.65534,21.48608],"type":"Point"}
}