{
  "type": "Feature",
  "properties": {
    "gn:admin1_code":"4.0",
    "gn:admin2_code":"MMR001D003",
    "gn:admin3_code":"MMR001013",
    "gn:asciiname":"Wang-gahtawng",
    "gn:country_code":"MM",
    "gn:dem":1149,
    "gn:feature_class":"P",
    "gn:feature_code":"PPL",
    "gn:name":"Wang-gahtawng",
    "gn:population":0,
    "gn:timezone":"Asia/Yangon",
    "iso:country":"MM",
    "wof:name":"Wang-gahtawng",
    "wof:placetype":"locality"
},
  "geometry": {"coordinates":[97.41141,24.04647000000001],"type":"Point"}
}