{
  "type": "Feature",
  "properties": {
    "gn:admin1_code":"3.0",
    "gn:admin2_code":"MMR017D006",
    "gn:admin3_code":"MMR017023",
    "gn:asciiname":"Wegyi",
    "gn:country_code":"MM",
    "gn:dem":4,
    "gn:feature_class":"P",
    "gn:feature_code":"PPL",
    "gn:name":"Wegyi",
    "gn:population":0,
    "gn:timezone":"Asia/Yangon",
    "iso:country":"MM",
    "wof:name":"Wegyi",
    "wof:placetype":"locality"
},
  "geometry": {"coordinates":[95.59296000000001,16.01569],"type":"Point"}
}