{
  "type": "Feature",
  "properties": {
    "gn:admin1_code":"4.0",
    "gn:admin2_code":"MMR001D003",
    "gn:admin3_code":"MMR001013",
    "gn:asciiname":"Wa-sha",
    "gn:country_code":"MM",
    "gn:dem":868,
    "gn:feature_class":"P",
    "gn:feature_code":"PPL",
    "gn:name":"W\u0101-sha",
    "gn:population":0,
    "gn:timezone":"Asia/Yangon",
    "iso:country":"MM",
    "wof:name":"Wa-sha",
    "wof:placetype":"locality"
},
  "geometry": {"coordinates":[97.38247,24.05141],"type":"Point"}
}