{
  "type": "Feature",
  "properties": {
    "gn:admin1_code":"15.0",
    "gn:admin2_code":"MMR009D001",
    "gn:admin3_code":"MMR009004",
    "gn:asciiname":"Pwinhla",
    "gn:country_code":"MM",
    "gn:dem":164,
    "gn:feature_class":"P",
    "gn:feature_code":"PPL",
    "gn:name":"Pwinhla",
    "gn:population":0,
    "gn:timezone":"Asia/Yangon",
    "iso:country":"MM",
    "wof:name":"Pwinhla",
    "wof:placetype":"locality"
},
  "geometry": {"coordinates":[95.58193,19.98119],"type":"Point"}
}