{
  "type": "Feature",
  "properties": {
    "gn:admin1_code":"4.0",
    "gn:admin2_code":"MMR001D004",
    "gn:admin3_code":"MMR001018",
    "gn:asciiname":"Aziyanghtawng",
    "gn:country_code":"MM",
    "gn:dem":1556,
    "gn:feature_class":"P",
    "gn:feature_code":"PPL",
    "gn:name":"Aziy\u0101nghtawng",
    "gn:population":0,
    "gn:timezone":"Asia/Yangon",
    "iso:country":"MM",
    "wof:name":"Aziyanghtawng",
    "wof:placetype":"locality"
},
  "geometry": {"coordinates":[98.42167000000001,26.84506],"type":"Point"}
}