{
  "type": "Feature",
  "properties": {
    "gn:admin1_code":"4.0",
    "gn:admin2_code":"MMR001D003",
    "gn:admin3_code":"MMR001012",
    "gn:asciiname":"Mungdungkong",
    "gn:country_code":"MM",
    "gn:dem":1028,
    "gn:feature_class":"P",
    "gn:feature_code":"PPL",
    "gn:name":"Mungdungkong",
    "gn:population":0,
    "gn:timezone":"Asia/Yangon",
    "iso:country":"MM",
    "wof:name":"Mungdungkong",
    "wof:placetype":"locality"
},
  "geometry": {"coordinates":[97.47396000000001,24.33021],"type":"Point"}
}