{
  "type": "Feature",
  "properties": {
    "gn:admin1_code":"8.0",
    "gn:admin2_code":"MMR010D002",
    "gn:admin3_code":"MMR010011",
    "gn:asciiname":"Wangkapa",
    "gn:country_code":"MM",
    "gn:dem":1159,
    "gn:feature_class":"P",
    "gn:feature_code":"PPL",
    "gn:name":"Wangkapa",
    "gn:population":0,
    "gn:timezone":"Asia/Yangon",
    "iso:country":"MM",
    "wof:name":"Wangkapa",
    "wof:placetype":"locality"
},
  "geometry": {"coordinates":[96.64609,22.89788],"type":"Point"}
}