{
  "type": "Feature",
  "properties": {
    "gn:admin1_code":"15.0",
    "gn:admin2_code":"MMR009D002",
    "gn:admin3_code":"MMR009008",
    "gn:asciiname":"Okpo",
    "gn:country_code":"MM",
    "gn:dem":72,
    "gn:feature_class":"P",
    "gn:feature_code":"PPL",
    "gn:name":"Okpo",
    "gn:population":0,
    "gn:timezone":"Asia/Yangon",
    "iso:country":"MM",
    "wof:name":"Okpo",
    "wof:placetype":"locality"
},
  "geometry": {"coordinates":[94.56883999999999,20.32578],"type":"Point"}
}