{
  "type": "Feature",
  "properties": {
    "gn:admin1_code":"11.0",
    "gn:admin2_code":"MMR016D002",
    "gn:admin3_code":"MMR016006",
    "gn:asciiname":"Wan Kat",
    "gn:country_code":"MM",
    "gn:dem":811,
    "gn:feature_class":"P",
    "gn:feature_code":"PPL",
    "gn:name":"W\u0101n K\u0101t",
    "gn:population":0,
    "gn:timezone":"Asia/Yangon",
    "iso:country":"MM",
    "wof:name":"Wan Kat",
    "wof:placetype":"locality"
},
  "geometry": {"coordinates":[99.46005,20.74556],"type":"Point"}
}