{
  "type": "Feature",
  "properties": {
    "gn:admin1_code":"10.0",
    "gn:admin2_code":"MMR005D002",
    "gn:admin3_code":"MMR005007",
    "gn:asciiname":"Mogyobyit",
    "gn:country_code":"MM",
    "gn:dem":134,
    "gn:feature_class":"P",
    "gn:feature_code":"PPL",
    "gn:name":"Mogyobyit",
    "gn:population":0,
    "gn:timezone":"Asia/Yangon",
    "iso:country":"MM",
    "name:und_x_variant":[
        "Mogyobit",
        "Mogyobyit"
    ],
    "wof:name":"Mogyobyit",
    "wof:placetype":"locality"
},
  "geometry": {"coordinates":[95.48381999999999,23.05606],"type":"Point"}
}