{
  "type": "Feature",
  "properties": {
    "gn:admin1_code":"10.0",
    "gn:asciiname":"Sade",
    "gn:country_code":"MM",
    "gn:dem":113,
    "gn:feature_class":"P",
    "gn:feature_code":"PPL",
    "gn:name":"Sade",
    "gn:population":0,
    "gn:timezone":"Asia/Yangon",
    "iso:country":"MM",
    "name:ces_x_preferred":[
        "Sade"
    ],
    "name:deu_x_preferred":[
        "Sade"
    ],
    "name:fas_x_preferred":[
        "\u0634\u0627\u062f\u0647"
    ],
    "name:fin_x_preferred":[
        "Sade"
    ],
    "name:fra_x_preferred":[
        "Sade"
    ],
    "name:hun_x_preferred":[
        "Sade"
    ],
    "name:ind_x_preferred":[
        "Sade"
    ],
    "name:ita_x_preferred":[
        "Sade"
    ],
    "name:lav_x_preferred":[
        "Sade"
    ],
    "name:nld_x_preferred":[
        "Sade"
    ],
    "name:oci_x_preferred":[
        "Sade"
    ],
    "name:por_x_preferred":[
        "Sade"
    ],
    "name:spa_x_preferred":[
        "Sade"
    ],
    "name:tur_x_preferred":[
        "Sade"
    ],
    "wof:name":"Sade",
    "wof:placetype":"locality"
},
  "geometry": {"coordinates":[95.69801,21.8139],"type":"Point"}
}