{
  "type": "Feature",
  "properties": {
    "gn:admin1_code":"5.0",
    "gn:admin2_code":"MMR003D001",
    "gn:admin3_code":"MMR003004",
    "gn:asciiname":"Tamyagyaung",
    "gn:country_code":"MM",
    "gn:dem":367,
    "gn:feature_class":"P",
    "gn:feature_code":"PPL",
    "gn:name":"Tamyagyaung",
    "gn:population":0,
    "gn:timezone":"Asia/Yangon",
    "iso:country":"MM",
    "name:und_x_variant":[
        "Tamyaukchaung",
        "Tamyagyaung"
    ],
    "wof:name":"Tamyagyaung",
    "wof:placetype":"locality"
},
  "geometry": {"coordinates":[96.69558000000001,18.78638],"type":"Point"}
}