{
  "type": "Feature",
  "properties": {
    "gn:admin1_code":"10.0",
    "gn:admin2_code":"MMR005D008",
    "gn:admin3_code":"MMR005034",
    "gn:asciiname":"Saingkyu",
    "gn:country_code":"MM",
    "gn:dem":170,
    "gn:feature_class":"P",
    "gn:feature_code":"PPL",
    "gn:name":"Saingkyu",
    "gn:population":0,
    "gn:timezone":"Asia/Yangon",
    "iso:country":"MM",
    "name:und_x_variant":[
        "Saingkya",
        "Saingkyu"
    ],
    "wof:name":"Saingkyu",
    "wof:placetype":"locality"
},
  "geometry": {"coordinates":[95.46692,24.78896],"type":"Point"}
}