{
  "type": "Feature",
  "properties": {
    "gn:admin1_code":"4.0",
    "gn:admin2_code":"MMR001D003",
    "gn:admin3_code":"MMR001012",
    "gn:asciiname":"Tun Hong",
    "gn:country_code":"MM",
    "gn:dem":759,
    "gn:feature_class":"P",
    "gn:feature_code":"PPL",
    "gn:name":"Tun Hong",
    "gn:population":0,
    "gn:timezone":"Asia/Yangon",
    "iso:country":"MM",
    "name:und_x_variant":[
        "Tun Houg",
        "Tun Hong"
    ],
    "wof:name":"Tun Hong",
    "wof:placetype":"locality"
},
  "geometry": {"coordinates":[97.55052999999999,24.41355],"type":"Point"}
}