{
  "type": "Feature",
  "properties": {
    "gn:admin1_code":"16.0",
    "gn:admin2_code":"MMR008D002",
    "gn:admin3_code":"MMR008007",
    "gn:asciiname":"Ngaywe",
    "gn:country_code":"MM",
    "gn:dem":93,
    "gn:feature_class":"P",
    "gn:feature_code":"PPL",
    "gn:name":"Ngaywe",
    "gn:population":0,
    "gn:timezone":"Asia/Yangon",
    "iso:country":"MM",
    "wof:name":"Ngaywe",
    "wof:placetype":"locality"
},
  "geometry": {"coordinates":[96.01381000000001,17.77441],"type":"Point"}
}