{
  "type": "Feature",
  "properties": {
    "gn:admin1_code":"16.0",
    "gn:admin2_code":"MMR007D002",
    "gn:admin3_code":"MMR007011",
    "gn:asciiname":"Tatkon",
    "gn:country_code":"MM",
    "gn:dem":36,
    "gn:feature_class":"P",
    "gn:feature_code":"PPL",
    "gn:name":"Tatkon",
    "gn:population":0,
    "gn:timezone":"Asia/Yangon",
    "iso:country":"MM",
    "name:tha_x_preferred":[
        "\u0e15\u0e30\u0e42\u0e01\u0e49\u0e19"
    ],
    "wof:name":"Tatkon",
    "wof:placetype":"locality"
},
  "geometry": {"coordinates":[96.65929,18.47402],"type":"Point"}
}