{
  "type": "Feature",
  "properties": {
    "gn:admin1_code":"3.0",
    "gn:admin2_code":"MMR017D006",
    "gn:admin3_code":"MMR017026",
    "gn:asciiname":"Kyonlutgyi",
    "gn:country_code":"MM",
    "gn:dem":7,
    "gn:feature_class":"P",
    "gn:feature_code":"PPL",
    "gn:name":"Ky\u00f4nlutgyi",
    "gn:population":0,
    "gn:timezone":"Asia/Yangon",
    "iso:country":"MM",
    "name:und_x_variant":[
        "Kyonlutkyi",
        "Ky\u00f4nlutgyi"
    ],
    "wof:name":"Kyonlutgyi",
    "wof:placetype":"locality"
},
  "geometry": {"coordinates":[95.79261,16.18442000000001],"type":"Point"}
}