{
  "type": "Feature",
  "properties": {
    "gn:admin1_code":"17.0",
    "gn:admin2_code":"MMR013D001",
    "gn:admin3_code":"MMR013004",
    "gn:asciiname":"Magyigan",
    "gn:country_code":"MM",
    "gn:dem":18,
    "gn:feature_class":"P",
    "gn:feature_code":"PPL",
    "gn:name":"Magyigan",
    "gn:population":0,
    "gn:timezone":"Asia/Yangon",
    "iso:country":"MM",
    "wof:name":"Magyigan",
    "wof:placetype":"locality"
},
  "geometry": {"coordinates":[96.24451999999999,17.15968],"type":"Point"}
}