{
  "type": "Feature",
  "properties": {
    "gn:admin1_code":"6.0",
    "gn:admin2_code":"MMR002D001",
    "gn:admin3_code":"MMR002003",
    "gn:asciiname":"Lawkoe-hku",
    "gn:country_code":"MM",
    "gn:dem":1001,
    "gn:feature_class":"P",
    "gn:feature_code":"PPL",
    "gn:name":"Lawk\u00f6-hku",
    "gn:population":0,
    "gn:timezone":"Asia/Yangon",
    "iso:country":"MM",
    "wof:name":"Lawkoe-hku",
    "wof:placetype":"locality"
},
  "geometry": {"coordinates":[97.14493,19.3887],"type":"Point"}
}