{
  "type": "Feature",
  "properties": {
    "gn:admin1_code":"11.0",
    "gn:admin2_code":"MMR016D003",
    "gn:admin3_code":"MMR016011",
    "gn:asciiname":"Wan Ta-hsum",
    "gn:cc2":"MM",
    "gn:country_code":"MM",
    "gn:dem":487,
    "gn:feature_class":"P",
    "gn:feature_code":"PPL",
    "gn:name":"W\u0101n Ta-hs\u016bm",
    "gn:population":0,
    "gn:timezone":"Asia/Yangon",
    "iso:country":"MM",
    "name:und_x_variant":[
        "Ta-hs\u016bm",
        "W\u0101n Ta-hs\u016bm"
    ],
    "wof:name":"Wan Ta-hsum",
    "wof:placetype":"locality"
},
  "geometry": {"coordinates":[100.56667,21.33333],"type":"Point"}
}