{
  "type": "Feature",
  "properties": {
    "gn:admin1_code":"11.0",
    "gn:admin2_code":"MMR016D002",
    "gn:admin3_code":"MMR016006",
    "gn:asciiname":"Hpya-moengmoeng",
    "gn:country_code":"MM",
    "gn:dem":950,
    "gn:feature_class":"P",
    "gn:feature_code":"PPL",
    "gn:name":"Hpya-m\u00f6ngm\u00f6ng",
    "gn:population":0,
    "gn:timezone":"Asia/Yangon",
    "iso:country":"MM",
    "wof:name":"Hpya-moengmoeng",
    "wof:placetype":"locality"
},
  "geometry": {"coordinates":[99.20945,20.45748],"type":"Point"}
}