{
  "type": "Feature",
  "properties": {
    "gn:admin1_code":"5.0",
    "gn:admin2_code":"MMR003D003",
    "gn:admin3_code":"MMR003007",
    "gn:asciiname":"Kyondaw",
    "gn:country_code":"MM",
    "gn:dem":66,
    "gn:feature_class":"P",
    "gn:feature_code":"PPL",
    "gn:name":"Ky\u00f4ndaw",
    "gn:population":0,
    "gn:timezone":"Asia/Yangon",
    "iso:country":"MM",
    "wof:name":"Kyondaw",
    "wof:placetype":"locality"
},
  "geometry": {"coordinates":[98.30045,15.38498],"type":"Point"}
}