{
  "type": "Feature",
  "properties": {
    "gn:admin1_code":"11.0",
    "gn:admin2_code":"MMR016D001",
    "gn:admin3_code":"MMR016002",
    "gn:asciiname":"Wan Moeng",
    "gn:country_code":"MM",
    "gn:dem":894,
    "gn:feature_class":"P",
    "gn:feature_code":"PPL",
    "gn:name":"W\u0101n M\u00f6ng",
    "gn:population":0,
    "gn:timezone":"Asia/Yangon",
    "iso:country":"MM",
    "wof:name":"Wan Moeng",
    "wof:placetype":"locality"
},
  "geometry": {"coordinates":[99.40994000000001,21.71102],"type":"Point"}
}