{
  "type": "Feature",
  "properties": {
    "gn:admin1_code":"2.0",
    "gn:admin2_code":"MMR004D001",
    "gn:admin3_code":"MMR004004",
    "gn:asciiname":"Ngalbual",
    "gn:country_code":"MM",
    "gn:dem":1151,
    "gn:feature_class":"P",
    "gn:feature_code":"PPL",
    "gn:name":"Ngalbual",
    "gn:population":0,
    "gn:timezone":"Asia/Yangon",
    "iso:country":"MM",
    "wof:name":"Ngalbual",
    "wof:placetype":"locality"
},
  "geometry": {"coordinates":[93.55,23.53333],"type":"Point"}
}