{
  "type": "Feature",
  "properties": {
    "gn:admin1_code":"10.0",
    "gn:admin2_code":"MMR005D004",
    "gn:admin3_code":"MMR005024",
    "gn:asciiname":"Mokwa",
    "gn:country_code":"MM",
    "gn:dem":212,
    "gn:feature_class":"P",
    "gn:feature_code":"PPL",
    "gn:name":"Mokwa",
    "gn:population":0,
    "gn:timezone":"Asia/Yangon",
    "iso:country":"MM",
    "name:ceb_x_preferred":[
        "Mokwa"
    ],
    "name:fra_x_preferred":[
        "Mokwa"
    ],
    "name:hau_x_preferred":[
        "Mokwa"
    ],
    "name:ita_x_preferred":[
        "Mokwa"
    ],
    "name:spa_x_preferred":[
        "Mokwa"
    ],
    "wof:name":"Mokwa",
    "wof:placetype":"locality"
},
  "geometry": {"coordinates":[95.89828,23.79514],"type":"Point"}
}