{
  "type": "Feature",
  "properties": {
    "gn:admin1_code":"11.0",
    "gn:admin2_code":"MMR015D002",
    "gn:admin3_code":"MMR015009",
    "gn:asciiname":"Man Kawng",
    "gn:country_code":"MM",
    "gn:dem":711,
    "gn:feature_class":"P",
    "gn:feature_code":"PPL",
    "gn:name":"M\u0101n Kawng",
    "gn:population":0,
    "gn:timezone":"Asia/Yangon",
    "iso:country":"MM",
    "wof:name":"Man Kawng",
    "wof:placetype":"locality"
},
  "geometry": {"coordinates":[98.31877,23.93251],"type":"Point"}
}