{
  "type": "Feature",
  "properties": {
    "gn:admin1_code":"13.0",
    "gn:admin2_code":"MMR011D001",
    "gn:admin3_code":"MMR011001",
    "gn:asciiname":"Kharun",
    "gn:country_code":"MM",
    "gn:dem":17,
    "gn:feature_class":"P",
    "gn:feature_code":"PPL",
    "gn:name":"Kharun",
    "gn:population":0,
    "gn:timezone":"Asia/Yangon",
    "iso:country":"MM",
    "wof:name":"Kharun",
    "wof:placetype":"locality"
},
  "geometry": {"coordinates":[97.66206,16.37996],"type":"Point"}
}