{
  "type": "Feature",
  "properties": {
    "gn:admin1_code":"11.0",
    "gn:admin2_code":"MMR014D003",
    "gn:admin3_code":"MMR014018",
    "gn:asciiname":"Wan Makmoeng",
    "gn:country_code":"MM",
    "gn:dem":1198,
    "gn:feature_class":"P",
    "gn:feature_code":"PPL",
    "gn:name":"W\u0101n Makm\u00f6ng",
    "gn:population":0,
    "gn:timezone":"Asia/Yangon",
    "iso:country":"MM",
    "wof:name":"Wan Makmoeng",
    "wof:placetype":"locality"
},
  "geometry": {"coordinates":[98.04778,20.17611],"type":"Point"}
}