{
  "type": "Feature",
  "properties": {
    "gn:admin1_code":"3.0",
    "gn:admin2_code":"MMR017D001",
    "gn:admin3_code":"MMR017001",
    "gn:asciiname":"Kyaukkyi",
    "gn:country_code":"MM",
    "gn:dem":13,
    "gn:feature_class":"P",
    "gn:feature_code":"PPL",
    "gn:name":"Kyaukkyi",
    "gn:population":0,
    "gn:timezone":"Asia/Yangon",
    "iso:country":"MM",
    "name:und_x_variant":[
        "Kyawkkyi",
        "Kyaukkyi"
    ],
    "wof:name":"Kyaukkyi",
    "wof:placetype":"locality"
},
  "geometry": {"coordinates":[94.39238,16.84031],"type":"Point"}
}