{
  "type": "Feature",
  "properties": {
    "gn:admin1_code":"11.0",
    "gn:admin2_code":"MMR014D001",
    "gn:admin3_code":"MMR014002",
    "gn:asciiname":"Lulaywagyi",
    "gn:country_code":"MM",
    "gn:dem":986,
    "gn:feature_class":"P",
    "gn:feature_code":"PPL",
    "gn:name":"Lulaywagyi",
    "gn:population":0,
    "gn:timezone":"Asia/Yangon",
    "iso:country":"MM",
    "name:und_x_variant":[
        "Lulawagyi",
        "Lulaywagyi"
    ],
    "wof:name":"Lulaywagyi",
    "wof:placetype":"locality"
},
  "geometry": {"coordinates":[96.93537000000001,20.301],"type":"Point"}
}