{
  "type": "Feature",
  "properties": {
    "gn:admin1_code":"11.0",
    "gn:admin2_code":"MMR015D003",
    "gn:admin3_code":"MMR015012",
    "gn:asciiname":"Mantali",
    "gn:country_code":"MM",
    "gn:dem":885,
    "gn:feature_class":"P",
    "gn:feature_code":"PPL",
    "gn:name":"M\u00e1ntali",
    "gn:population":0,
    "gn:timezone":"Asia/Yangon",
    "iso:country":"MM",
    "wof:name":"Mantali",
    "wof:placetype":"locality"
},
  "geometry": {"coordinates":[96.76797000000001,22.83694],"type":"Point"}
}