{
  "type": "Feature",
  "properties": {
    "gn:admin1_code":"4.0",
    "gn:admin2_code":"MMR001D001",
    "gn:admin3_code":"MMR001005",
    "gn:asciiname":"Saulang",
    "gn:country_code":"MM",
    "gn:dem":1909,
    "gn:feature_class":"P",
    "gn:feature_code":"PPL",
    "gn:name":"Saulang",
    "gn:population":0,
    "gn:timezone":"Asia/Yangon",
    "iso:country":"MM",
    "name:und_x_variant":[
        "Suklang",
        "Saulang"
    ],
    "wof:name":"Saulang",
    "wof:placetype":"locality"
},
  "geometry": {"coordinates":[98.35346,25.7079],"type":"Point"}
}