{
  "type": "Feature",
  "properties": {
    "gn:admin1_code":"17.0",
    "gn:admin2_code":"MMR013D003",
    "gn:admin3_code":"MMR013029",
    "gn:asciiname":"Kalauktaya",
    "gn:country_code":"MM",
    "gn:dem":11,
    "gn:feature_class":"P",
    "gn:feature_code":"PPL",
    "gn:name":"Kalauktaya",
    "gn:population":0,
    "gn:timezone":"Asia/Yangon",
    "iso:country":"MM",
    "wof:name":"Kalauktaya",
    "wof:placetype":"locality"
},
  "geometry": {"coordinates":[96.09789000000001,16.42498],"type":"Point"}
}