{
  "type": "Feature",
  "properties": {
    "gn:admin1_code":"2.0",
    "gn:admin2_code":"MMR004D002",
    "gn:admin3_code":"MMR004009",
    "gn:asciiname":"Bongyo",
    "gn:country_code":"MM",
    "gn:dem":103,
    "gn:feature_class":"P",
    "gn:feature_code":"PPL",
    "gn:name":"Bongyo",
    "gn:population":0,
    "gn:timezone":"Asia/Yangon",
    "iso:country":"MM",
    "wof:name":"Bongyo",
    "wof:placetype":"locality"
},
  "geometry": {"coordinates":[92.67521000000001,21.40965],"type":"Point"}
}