{
  "type": "Feature",
  "properties": {
    "gn:admin1_code":"15.0",
    "gn:admin2_code":"MMR009D003",
    "gn:admin3_code":"MMR009012",
    "gn:asciiname":"Talabasan",
    "gn:country_code":"MM",
    "gn:dem":128,
    "gn:feature_class":"P",
    "gn:feature_code":"PPL",
    "gn:name":"Talabasan",
    "gn:population":0,
    "gn:timezone":"Asia/Yangon",
    "iso:country":"MM",
    "wof:name":"Talabasan",
    "wof:placetype":"locality"
},
  "geometry": {"coordinates":[95.12811000000001,19.44761],"type":"Point"}
}