{
  "type": "Feature",
  "properties": {
    "gn:admin1_code":"15.0",
    "gn:admin2_code":"MMR009D001",
    "gn:admin3_code":"MMR009005",
    "gn:asciiname":"Yaungmanga",
    "gn:country_code":"MM",
    "gn:dem":120,
    "gn:feature_class":"P",
    "gn:feature_code":"PPL",
    "gn:name":"Yaungmanga",
    "gn:population":0,
    "gn:timezone":"Asia/Yangon",
    "iso:country":"MM",
    "wof:name":"Yaungmanga",
    "wof:placetype":"locality"
},
  "geometry": {"coordinates":[95.40867,20.12771],"type":"Point"}
}