{
  "type": "Feature",
  "properties": {
    "gn:admin1_code":"17.0",
    "gn:admin2_code":"MMR013D003",
    "gn:admin3_code":"MMR013024",
    "gn:asciiname":"Kyagandeik",
    "gn:country_code":"MM",
    "gn:dem":11,
    "gn:feature_class":"P",
    "gn:feature_code":"PPL",
    "gn:name":"Kyagandeik",
    "gn:population":0,
    "gn:timezone":"Asia/Yangon",
    "iso:country":"MM",
    "wof:name":"Kyagandeik",
    "wof:placetype":"locality"
},
  "geometry": {"coordinates":[96.31393,16.64784],"type":"Point"}
}