{
  "type": "Feature",
  "properties": {
    "gn:admin1_code":"4.0",
    "gn:admin2_code":"MMR001D003",
    "gn:admin3_code":"MMR001013",
    "gn:asciiname":"Lu-su",
    "gn:country_code":"MM",
    "gn:dem":1138,
    "gn:feature_class":"P",
    "gn:feature_code":"PPL",
    "gn:name":"Lu-su",
    "gn:population":0,
    "gn:timezone":"Asia/Yangon",
    "iso:country":"MM",
    "wof:name":"Lu-su",
    "wof:placetype":"locality"
},
  "geometry": {"coordinates":[97.50909,24.05948],"type":"Point"}
}