{
  "type": "Feature",
  "properties": {
    "gn:admin1_code":"16.0",
    "gn:admin2_code":"MMR007D001",
    "gn:admin3_code":"MMR007006",
    "gn:asciiname":"San Nyein Te",
    "gn:country_code":"MM",
    "gn:dem":118,
    "gn:feature_class":"P",
    "gn:feature_code":"PPL",
    "gn:name":"San Nyein T\u0113",
    "gn:population":0,
    "gn:timezone":"Asia/Yangon",
    "iso:country":"MM",
    "wof:name":"San Nyein Te",
    "wof:placetype":"locality"
},
  "geometry": {"coordinates":[96.21666999999999,18.13333],"type":"Point"}
}