{
  "type": "Feature",
  "properties": {
    "gn:admin1_code":"11.0",
    "gn:admin2_code":"MMR014D003",
    "gn:admin3_code":"MMR014019",
    "gn:asciiname":"Knoglong",
    "gn:country_code":"MM",
    "gn:dem":1082,
    "gn:feature_class":"P",
    "gn:feature_code":"PPL",
    "gn:name":"Knoglong",
    "gn:population":0,
    "gn:timezone":"Asia/Yangon",
    "iso:country":"MM",
    "name:und_x_variant":[
        "Konglang",
        "Knoglong"
    ],
    "wof:name":"Knoglong",
    "wof:placetype":"locality"
},
  "geometry": {"coordinates":[97.82823999999999,20.50177],"type":"Point"}
}