{
  "type": "Feature",
  "properties": {
    "gn:admin1_code":"11.0",
    "gn:admin2_code":"MMR015D003",
    "gn:admin3_code":"MMR015012",
    "gn:asciiname":"Nanim",
    "gn:country_code":"MM",
    "gn:dem":1029,
    "gn:feature_class":"P",
    "gn:feature_code":"PPL",
    "gn:name":"N\u0101nim",
    "gn:population":0,
    "gn:timezone":"Asia/Yangon",
    "iso:country":"MM",
    "name:und_x_variant":[
        "Nanin",
        "N\u0101nim"
    ],
    "wof:name":"Nanim",
    "wof:placetype":"locality"
},
  "geometry": {"coordinates":[97.10093000000001,22.40905],"type":"Point"}
}