{
  "type": "Feature",
  "properties": {
    "gn:admin1_code":"11.0",
    "gn:admin2_code":"MMR016D001",
    "gn:admin3_code":"MMR016007",
    "gn:asciiname":"Wan Pongkun",
    "gn:country_code":"MM",
    "gn:dem":580,
    "gn:feature_class":"P",
    "gn:feature_code":"PPL",
    "gn:name":"W\u0101n Pongkun",
    "gn:population":0,
    "gn:timezone":"Asia/Yangon",
    "iso:country":"MM",
    "name:und_x_variant":[
        "W\u0101n Punghkun",
        "W\u0101n Pongkun"
    ],
    "wof:name":"Wan Pongkun",
    "wof:placetype":"locality"
},
  "geometry": {"coordinates":[99.03982000000001,20.98697],"type":"Point"}
}