{
  "type": "Feature",
  "properties": {
    "gn:admin1_code":"11.0",
    "gn:admin2_code":"MMR016D003",
    "gn:admin3_code":"MMR016010",
    "gn:asciiname":"Wan Namlang",
    "gn:country_code":"MM",
    "gn:dem":510,
    "gn:feature_class":"P",
    "gn:feature_code":"PPL",
    "gn:name":"W\u0101n Namlang",
    "gn:population":0,
    "gn:timezone":"Asia/Yangon",
    "iso:country":"MM",
    "wof:name":"Wan Namlang",
    "wof:placetype":"locality"
},
  "geometry": {"coordinates":[99.94566,20.90781],"type":"Point"}
}