{
  "type": "Feature",
  "properties": {
    "gn:admin1_code":"4.0",
    "gn:admin2_code":"MMR001D001",
    "gn:admin3_code":"MMR001005",
    "gn:asciiname":"Wusaohkao",
    "gn:country_code":"MM",
    "gn:dem":1878,
    "gn:feature_class":"P",
    "gn:feature_code":"PPL",
    "gn:name":"Wusaohkao",
    "gn:population":0,
    "gn:timezone":"Asia/Yangon",
    "iso:country":"MM",
    "wof:name":"Wusaohkao",
    "wof:placetype":"locality"
},
  "geometry": {"coordinates":[98.52079000000001,26.06088],"type":"Point"}
}