{
  "type": "Feature",
  "properties": {
    "gn:admin1_code":"11.0",
    "gn:admin2_code":"MMR016D001",
    "gn:admin3_code":"MMR016002",
    "gn:asciiname":"Wan Koen",
    "gn:country_code":"MM",
    "gn:dem":1463,
    "gn:feature_class":"P",
    "gn:feature_code":"PPL",
    "gn:name":"W\u0101n K\u00f6n",
    "gn:population":0,
    "gn:timezone":"Asia/Yangon",
    "iso:country":"MM",
    "wof:name":"Wan Koen",
    "wof:placetype":"locality"
},
  "geometry": {"coordinates":[99.26185,21.70275],"type":"Point"}
}