{
  "type": "Feature",
  "properties": {
    "gn:admin1_code":"10.0",
    "gn:admin2_code":"MMR005D005",
    "gn:admin3_code":"MMR005028",
    "gn:asciiname":"Taung Tunhlaw",
    "gn:country_code":"MM",
    "gn:dem":130,
    "gn:feature_class":"P",
    "gn:feature_code":"PPL",
    "gn:name":"Taung Tunhlaw",
    "gn:population":0,
    "gn:timezone":"Asia/Yangon",
    "iso:country":"MM",
    "name:und_x_variant":[
        "Tunhlaw",
        "Taung Tunhlaw"
    ],
    "wof:name":"Taung Tunhlaw",
    "wof:placetype":"locality"
},
  "geometry": {"coordinates":[94.37900999999999,23.43133],"type":"Point"}
}