{
  "type": "Feature",
  "properties": {
    "gn:admin1_code":"8.0",
    "gn:admin2_code":"MMR010D007",
    "gn:admin3_code":"MMR010031",
    "gn:asciiname":"Ingan",
    "gn:country_code":"MM",
    "gn:dem":112,
    "gn:feature_class":"P",
    "gn:feature_code":"PPL",
    "gn:name":"Ingan",
    "gn:population":0,
    "gn:timezone":"Asia/Yangon",
    "iso:country":"MM",
    "wof:name":"Ingan",
    "wof:placetype":"locality"
},
  "geometry": {"coordinates":[96.08092000000001,21.2233],"type":"Point"}
}