{
  "type": "Feature",
  "properties": {
    "gn:admin1_code":"6.0",
    "gn:admin2_code":"MMR002D002",
    "gn:admin3_code":"MMR002006",
    "gn:asciiname":"Kyaukpeneo",
    "gn:country_code":"MM",
    "gn:dem":123,
    "gn:feature_class":"P",
    "gn:feature_code":"PPL",
    "gn:name":"Kyaukpeneo",
    "gn:population":0,
    "gn:timezone":"Asia/Yangon",
    "iso:country":"MM",
    "wof:name":"Kyaukpeneo",
    "wof:placetype":"locality"
},
  "geometry": {"coordinates":[97.32409,18.83215],"type":"Point"}
}