{
  "type": "Feature",
  "properties": {
    "gn:admin1_code":"2.0",
    "gn:admin2_code":"MMR004D002",
    "gn:admin3_code":"MMR004007",
    "gn:asciiname":"Tuiship",
    "gn:country_code":"MM",
    "gn:dem":1018,
    "gn:feature_class":"P",
    "gn:feature_code":"PPL",
    "gn:name":"Tuiship",
    "gn:population":0,
    "gn:timezone":"Asia/Yangon",
    "iso:country":"MM",
    "wof:name":"Tuiship",
    "wof:placetype":"locality"
},
  "geometry": {"coordinates":[93.38661999999999,21.48537],"type":"Point"}
}