{
  "type": "Feature",
  "properties": {
    "gn:admin1_code":"11.0",
    "gn:admin2_code":"MMR015D003",
    "gn:admin3_code":"MMR015014",
    "gn:asciiname":"Hsai-le",
    "gn:country_code":"MM",
    "gn:dem":814,
    "gn:feature_class":"P",
    "gn:feature_code":"PPL",
    "gn:name":"Hsai-le",
    "gn:population":0,
    "gn:timezone":"Asia/Yangon",
    "iso:country":"MM",
    "wof:name":"Hsai-le",
    "wof:placetype":"locality"
},
  "geometry": {"coordinates":[97.5782,22.42338],"type":"Point"}
}