{
  "type": "Feature",
  "properties": {
    "gn:admin1_code":"11.0",
    "gn:admin2_code":"MMR015D001",
    "gn:admin3_code":"MMR015020",
    "gn:asciiname":"Wan Li-tzu-shan",
    "gn:country_code":"MM",
    "gn:dem":1342,
    "gn:feature_class":"P",
    "gn:feature_code":"PPL",
    "gn:name":"W\u0101n Li-tzu-shan",
    "gn:population":0,
    "gn:timezone":"Asia/Yangon",
    "iso:country":"MM",
    "wof:name":"Wan Li-tzu-shan",
    "wof:placetype":"locality"
},
  "geometry": {"coordinates":[98.60062000000001,23.62772],"type":"Point"}
}