{
  "type": "Feature",
  "properties": {
    "gn:admin1_code":"3.0",
    "gn:admin2_code":"MMR017D006",
    "gn:admin3_code":"MMR017026",
    "gn:asciiname":"Thegon",
    "gn:country_code":"MM",
    "gn:dem":6,
    "gn:feature_class":"P",
    "gn:feature_code":"PPL",
    "gn:name":"Th\u0113g\u00f4n",
    "gn:population":0,
    "gn:timezone":"Asia/Yangon",
    "iso:country":"MM",
    "wof:name":"Thegon",
    "wof:placetype":"locality"
},
  "geometry": {"coordinates":[95.87907,16.39714],"type":"Point"}
}