{
  "type": "Feature",
  "properties": {
    "gn:admin1_code":"16.0",
    "gn:admin2_code":"MMR008D001",
    "gn:admin3_code":"MMR008002",
    "gn:asciiname":"Nyaungbin-in",
    "gn:country_code":"MM",
    "gn:dem":61,
    "gn:feature_class":"P",
    "gn:feature_code":"PPL",
    "gn:name":"Nyaungbin-in",
    "gn:population":0,
    "gn:timezone":"Asia/Yangon",
    "iso:country":"MM",
    "wof:name":"Nyaungbin-in",
    "wof:placetype":"locality"
},
  "geometry": {"coordinates":[95.45837,18.94232],"type":"Point"}
}