{
  "type": "Feature",
  "properties": {
    "gn:admin1_code":"10.0",
    "gn:admin2_code":"MMR005D007",
    "gn:admin3_code":"MMR005032",
    "gn:asciiname":"Ywatha",
    "gn:country_code":"MM",
    "gn:dem":176,
    "gn:feature_class":"P",
    "gn:feature_code":"PPL",
    "gn:name":"Ywatha",
    "gn:population":0,
    "gn:timezone":"Asia/Yangon",
    "iso:country":"MM",
    "name:urd_x_preferred":[
        "\u06cc\u0648\u062a\u06be"
    ],
    "wof:name":"Ywatha",
    "wof:placetype":"locality"
},
  "geometry": {"coordinates":[94.79639,23.95424],"type":"Point"}
}