{
  "type": "Feature",
  "properties": {
    "gn:admin1_code":"8.0",
    "gn:admin2_code":"MMR010D003",
    "gn:admin3_code":"MMR010015",
    "gn:asciiname":"Kantigale",
    "gn:country_code":"MM",
    "gn:dem":103,
    "gn:feature_class":"P",
    "gn:feature_code":"PPL",
    "gn:name":"Kantigale",
    "gn:population":0,
    "gn:timezone":"Asia/Yangon",
    "iso:country":"MM",
    "wof:name":"Kantigale",
    "wof:placetype":"locality"
},
  "geometry": {"coordinates":[96.18641,21.42729],"type":"Point"}
}