{
  "type": "Feature",
  "properties": {
    "gn:admin1_code":"12.0",
    "gn:admin2_code":"MMR006D002",
    "gn:admin3_code":"MMR006008",
    "gn:asciiname":"Htong-khap",
    "gn:country_code":"MM",
    "gn:dem":13,
    "gn:feature_class":"P",
    "gn:feature_code":"PPL",
    "gn:name":"Htong-khap",
    "gn:population":0,
    "gn:timezone":"Asia/Yangon",
    "iso:country":"MM",
    "wof:name":"Htong-khap",
    "wof:placetype":"locality"
},
  "geometry": {"coordinates":[99.17395999999999,11.80316],"type":"Point"}
}