{
  "type": "Feature",
  "properties": {
    "gn:admin1_code":"4.0",
    "gn:admin2_code":"MMR001D001",
    "gn:admin3_code":"MMR001002",
    "gn:asciiname":"Tasan",
    "gn:country_code":"MM",
    "gn:dem":137,
    "gn:feature_class":"P",
    "gn:feature_code":"PPL",
    "gn:name":"T\u0101s\u0101n",
    "gn:population":0,
    "gn:timezone":"Asia/Yangon",
    "iso:country":"MM",
    "wof:name":"Tasan",
    "wof:placetype":"locality"
},
  "geometry": {"coordinates":[97.28072,25.24268],"type":"Point"}
}