{
  "type": "Feature",
  "properties": {
    "gn:admin1_code":"11.0",
    "gn:admin2_code":"MMR016D003",
    "gn:admin3_code":"MMR016011",
    "gn:asciiname":"Wan Hpya-kanhta",
    "gn:country_code":"MM",
    "gn:dem":1039,
    "gn:feature_class":"P",
    "gn:feature_code":"PPL",
    "gn:name":"W\u0101n Hpya-kanhta",
    "gn:population":0,
    "gn:timezone":"Asia/Yangon",
    "iso:country":"MM",
    "name:und_x_variant":[
        "Hpya-kanhta",
        "W\u0101n Hpya-kanhta"
    ],
    "wof:name":"Wan Hpya-kanhta",
    "wof:placetype":"locality"
},
  "geometry": {"coordinates":[100.27361000000001,21.41588],"type":"Point"}
}