{
  "type": "Feature",
  "properties": {
    "gn:admin1_code":"11.0",
    "gn:admin2_code":"MMR016D003",
    "gn:admin3_code":"MMR016009",
    "gn:asciiname":"Wan Htawngmaw-tem",
    "gn:country_code":"MM",
    "gn:dem":587,
    "gn:feature_class":"P",
    "gn:feature_code":"PPL",
    "gn:name":"W\u0101n Htawngmaw-tem",
    "gn:population":0,
    "gn:timezone":"Asia/Yangon",
    "iso:country":"MM",
    "wof:name":"Wan Htawngmaw-tem",
    "wof:placetype":"locality"
},
  "geometry": {"coordinates":[100.30907000000001,20.80207],"type":"Point"}
}