{
  "type": "Feature",
  "properties": {
    "gn:admin1_code":"11.0",
    "gn:admin2_code":"MMR014D002",
    "gn:admin3_code":"MMR014017",
    "gn:asciiname":"Pangwet",
    "gn:country_code":"MM",
    "gn:dem":799,
    "gn:feature_class":"P",
    "gn:feature_code":"PPL",
    "gn:name":"Pangwet",
    "gn:population":0,
    "gn:timezone":"Asia/Yangon",
    "iso:country":"MM",
    "wof:name":"Pangwet",
    "wof:placetype":"locality"
},
  "geometry": {"coordinates":[98.23308,21.93061],"type":"Point"}
}