{
  "type": "Feature",
  "properties": {
    "gn:admin1_code":"10.0",
    "gn:admin2_code":"MMR005D005",
    "gn:admin3_code":"MMR005027",
    "gn:asciiname":"Bogon",
    "gn:country_code":"MM",
    "gn:dem":143,
    "gn:feature_class":"P",
    "gn:feature_code":"PPL",
    "gn:name":"Bogon",
    "gn:population":0,
    "gn:timezone":"Asia/Yangon",
    "iso:country":"MM",
    "name:ceb_x_preferred":[
        "Bogon"
    ],
    "wof:name":"Bogon",
    "wof:placetype":"locality"
},
  "geometry": {"coordinates":[94.04042,22.90833],"type":"Point"}
}