{
  "type": "Feature",
  "properties": {
    "gn:admin1_code":"17.0",
    "gn:admin2_code":"MMR013D001",
    "gn:admin3_code":"MMR013004",
    "gn:asciiname":"Hlegu",
    "gn:country_code":"MM",
    "gn:dem":13,
    "gn:feature_class":"P",
    "gn:feature_code":"PPL",
    "gn:name":"Hlegu",
    "gn:population":0,
    "gn:timezone":"Asia/Yangon",
    "iso:country":"MM",
    "name:deu_x_preferred":[
        "Hlegu"
    ],
    "name:mya_x_preferred":[
        "\u101c\u103e\u100a\u103a\u1038\u1000\u1030\u1038\u1019\u103c\u102d\u102f\u1037"
    ],
    "name:swe_x_preferred":[
        "Hlegu"
    ],
    "wof:name":"Hlegu",
    "wof:placetype":"locality"
},
  "geometry": {"coordinates":[96.22056000000001,17.09567],"type":"Point"}
}