{
  "type": "Feature",
  "properties": {
    "gn:admin1_code":"10.0",
    "gn:admin2_code":"MMR005D002",
    "gn:admin3_code":"MMR005004",
    "gn:asciiname":"Zidaw",
    "gn:country_code":"MM",
    "gn:dem":98,
    "gn:feature_class":"P",
    "gn:feature_code":"PPL",
    "gn:name":"Zidaw",
    "gn:population":0,
    "gn:timezone":"Asia/Yangon",
    "iso:country":"MM",
    "wof:name":"Zidaw",
    "wof:placetype":"locality"
},
  "geometry": {"coordinates":[95.67283999999999,22.52182],"type":"Point"}
}