{
  "type": "Feature",
  "properties": {
    "gn:admin1_code":"6.0",
    "gn:admin2_code":"MMR002D002",
    "gn:admin3_code":"MMR002005",
    "gn:asciiname":"Wan Hsoppai",
    "gn:country_code":"MM",
    "gn:dem":137,
    "gn:feature_class":"P",
    "gn:feature_code":"PPL",
    "gn:name":"W\u0101n Hs\u014dppai",
    "gn:population":0,
    "gn:timezone":"Asia/Yangon",
    "iso:country":"MM",
    "name:und_x_variant":[
        "Wan Sutpa",
        "W\u0101n Hs\u014dppai"
    ],
    "wof:name":"Wan Hsoppai",
    "wof:placetype":"locality"
},
  "geometry": {"coordinates":[97.54461999999999,19.14738],"type":"Point"}
}