{
  "type": "Feature",
  "properties": {
    "gn:admin1_code":"15.0",
    "gn:admin2_code":"MMR009D001",
    "gn:admin3_code":"MMR009005",
    "gn:asciiname":"Shwebon",
    "gn:country_code":"MM",
    "gn:dem":230,
    "gn:feature_class":"P",
    "gn:feature_code":"PPL",
    "gn:name":"Shwebon",
    "gn:population":0,
    "gn:timezone":"Asia/Yangon",
    "iso:country":"MM",
    "wof:name":"Shwebon",
    "wof:placetype":"locality"
},
  "geometry": {"coordinates":[95.72681,20.12759],"type":"Point"}
}