{
  "type": "Feature",
  "properties": {
    "gn:admin1_code":"5.0",
    "gn:admin2_code":"MMR003D001",
    "gn:admin3_code":"MMR003004",
    "gn:asciiname":"Thayedo-atet",
    "gn:country_code":"MM",
    "gn:dem":760,
    "gn:feature_class":"P",
    "gn:feature_code":"PPL",
    "gn:name":"Thayedo-atet",
    "gn:population":0,
    "gn:timezone":"Asia/Yangon",
    "iso:country":"MM",
    "name:und_x_variant":[
        "Thayedo",
        "Thayedo-atet"
    ],
    "wof:name":"Thayedo-atet",
    "wof:placetype":"locality"
},
  "geometry": {"coordinates":[96.81632,18.63717],"type":"Point"}
}