{
  "type": "Feature",
  "properties": {
    "gn:admin1_code":"11.0",
    "gn:admin2_code":"MMR014D003",
    "gn:admin3_code":"MMR014019",
    "gn:asciiname":"Loi-ai",
    "gn:country_code":"MM",
    "gn:dem":1161,
    "gn:feature_class":"P",
    "gn:feature_code":"PPL",
    "gn:name":"Loi-ai",
    "gn:population":0,
    "gn:timezone":"Asia/Yangon",
    "iso:country":"MM",
    "name:cat_x_preferred":[
        "Lonpo"
    ],
    "wof:name":"Loi-ai",
    "wof:placetype":"locality"
},
  "geometry": {"coordinates":[98.02788,20.73472000000001],"type":"Point"}
}