{
  "type": "Feature",
  "properties": {
    "gn:admin1_code":"10.0",
    "gn:admin2_code":"MMR005D008",
    "gn:admin3_code":"MMR005035",
    "gn:asciiname":"Haiken",
    "gn:country_code":"MM",
    "gn:dem":1363,
    "gn:feature_class":"P",
    "gn:feature_code":"PPL",
    "gn:name":"Haiken",
    "gn:population":0,
    "gn:timezone":"Asia/Yangon",
    "iso:country":"MM",
    "wof:name":"Haiken",
    "wof:placetype":"locality"
},
  "geometry": {"coordinates":[94.89451,25.21236],"type":"Point"}
}