{
  "type": "Feature",
  "properties": {
    "gn:admin1_code":"11.0",
    "gn:admin2_code":"MMR014D003",
    "gn:admin3_code":"MMR014019",
    "gn:asciiname":"Wan Ponghpang",
    "gn:country_code":"MM",
    "gn:dem":545,
    "gn:feature_class":"P",
    "gn:feature_code":"PPL",
    "gn:name":"W\u0101n Ponghpang",
    "gn:population":0,
    "gn:timezone":"Asia/Yangon",
    "iso:country":"MM",
    "wof:name":"Wan Ponghpang",
    "wof:placetype":"locality"
},
  "geometry": {"coordinates":[98.34482,20.61284],"type":"Point"}
}