{
  "type": "Feature",
  "properties": {
    "gn:admin1_code":"16.0",
    "gn:admin2_code":"MMR007D001",
    "gn:admin3_code":"MMR007006",
    "gn:asciiname":"Hari",
    "gn:country_code":"MM",
    "gn:dem":29,
    "gn:feature_class":"P",
    "gn:feature_code":"PPL",
    "gn:name":"Hari",
    "gn:population":0,
    "gn:timezone":"Asia/Yangon",
    "iso:country":"MM",
    "wof:name":"Hari",
    "wof:placetype":"locality"
},
  "geometry": {"coordinates":[96.61476999999999,18.11495],"type":"Point"}
}