{
  "type": "Feature",
  "properties": {
    "gn:admin1_code":"15.0",
    "gn:admin2_code":"MMR009D002",
    "gn:admin3_code":"MMR009011",
    "gn:asciiname":"Alegu",
    "gn:country_code":"MM",
    "gn:dem":125,
    "gn:feature_class":"P",
    "gn:feature_code":"PPL",
    "gn:name":"Al\u00e8gu",
    "gn:population":0,
    "gn:timezone":"Asia/Yangon",
    "iso:country":"MM",
    "wof:name":"Alegu",
    "wof:placetype":"locality"
},
  "geometry": {"coordinates":[94.32894,20.27864],"type":"Point"}
}