{
  "type": "Feature",
  "properties": {
    "gn:admin1_code":"11.0",
    "gn:admin2_code":"MMR015D005",
    "gn:admin3_code":"MMR015022",
    "gn:asciiname":"Wan Lao-wangchai",
    "gn:country_code":"MM",
    "gn:dem":1048,
    "gn:feature_class":"P",
    "gn:feature_code":"PPL",
    "gn:name":"W\u0101n Lao-wangchai",
    "gn:population":0,
    "gn:timezone":"Asia/Yangon",
    "iso:country":"MM",
    "wof:name":"Wan Lao-wangchai",
    "wof:placetype":"locality"
},
  "geometry": {"coordinates":[98.74321999999999,23.70357000000001],"type":"Point"}
}