{
  "type": "Feature",
  "properties": {
    "gn:admin1_code":"4.0",
    "gn:admin2_code":"MMR001D003",
    "gn:admin3_code":"MMR001011",
    "gn:asciiname":"Lunghpa",
    "gn:country_code":"MM",
    "gn:dem":663,
    "gn:feature_class":"P",
    "gn:feature_code":"PPL",
    "gn:name":"Lunghpa",
    "gn:population":0,
    "gn:timezone":"Asia/Yangon",
    "iso:country":"MM",
    "wof:name":"Lunghpa",
    "wof:placetype":"locality"
},
  "geometry": {"coordinates":[96.71695,24.55161],"type":"Point"}
}