{
  "type": "Feature",
  "properties": {
    "gn:admin1_code":"11.0",
    "gn:admin2_code":"MMR016D001",
    "gn:admin3_code":"MMR016001",
    "gn:asciiname":"Wan Kawng",
    "gn:country_code":"MM",
    "gn:dem":782,
    "gn:feature_class":"P",
    "gn:feature_code":"PPL",
    "gn:name":"W\u0101n Kawng",
    "gn:population":0,
    "gn:timezone":"Asia/Yangon",
    "iso:country":"MM",
    "name:und_x_variant":[
        "Kawng",
        "W\u0101n Kawng"
    ],
    "wof:name":"Wan Kawng",
    "wof:placetype":"locality"
},
  "geometry": {"coordinates":[99.60244,21.39889],"type":"Point"}
}