{
  "type": "Feature",
  "properties": {
    "gn:admin1_code":"15.0",
    "gn:admin2_code":"MMR009D001",
    "gn:admin3_code":"MMR009004",
    "gn:asciiname":"Didokpin",
    "gn:country_code":"MM",
    "gn:dem":180,
    "gn:feature_class":"P",
    "gn:feature_code":"PPL",
    "gn:name":"Didokpin",
    "gn:population":0,
    "gn:timezone":"Asia/Yangon",
    "iso:country":"MM",
    "wof:name":"Didokpin",
    "wof:placetype":"locality"
},
  "geometry": {"coordinates":[95.33665999999999,19.80522],"type":"Point"}
}