{
  "type": "Feature",
  "properties": {
    "gn:admin1_code":"4.0",
    "gn:admin2_code":"MMR001D002",
    "gn:admin3_code":"MMR001009",
    "gn:asciiname":"Lonkin",
    "gn:country_code":"MM",
    "gn:dem":258,
    "gn:feature_class":"P",
    "gn:feature_code":"PPL",
    "gn:name":"Lonkin",
    "gn:population":0,
    "gn:timezone":"Asia/Yangon",
    "iso:country":"MM",
    "name:und_x_variant":[
        "L\u00f4ngin",
        "Lonkin"
    ],
    "wof:name":"Lonkin",
    "wof:placetype":"locality"
},
  "geometry": {"coordinates":[96.36023,25.65429],"type":"Point"}
}