{
  "type": "Feature",
  "properties": {
    "gn:admin1_code":"15.0",
    "gn:admin2_code":"MMR009D003",
    "gn:admin3_code":"MMR009015",
    "gn:asciiname":"Kanzu",
    "gn:country_code":"MM",
    "gn:dem":38,
    "gn:feature_class":"P",
    "gn:feature_code":"PPL",
    "gn:name":"Kanzu",
    "gn:population":0,
    "gn:timezone":"Asia/Yangon",
    "iso:country":"MM",
    "name:fra_x_preferred":[
        "Kanzu"
    ],
    "name:ita_x_preferred":[
        "Kanzu"
    ],
    "name:spa_x_preferred":[
        "Kanzu"
    ],
    "wof:name":"Kanzu",
    "wof:placetype":"locality"
},
  "geometry": {"coordinates":[95.06788,19.00226],"type":"Point"}
}