{
  "type": "Feature",
  "properties": {
    "gn:admin1_code":"3.0",
    "gn:admin2_code":"MMR017D002",
    "gn:admin3_code":"MMR017013",
    "gn:asciiname":"Yethaukhan",
    "gn:country_code":"MM",
    "gn:dem":19,
    "gn:feature_class":"P",
    "gn:feature_code":"PPL",
    "gn:name":"Yethaukhan",
    "gn:population":0,
    "gn:timezone":"Asia/Yangon",
    "iso:country":"MM",
    "wof:name":"Yethaukhan",
    "wof:placetype":"locality"
},
  "geometry": {"coordinates":[95.11673999999999,17.72716],"type":"Point"}
}