{
  "type": "Feature",
  "properties": {
    "gn:admin1_code":"15.0",
    "gn:admin2_code":"MMR009D005",
    "gn:admin3_code":"MMR009024",
    "gn:asciiname":"Wetthet",
    "gn:country_code":"MM",
    "gn:dem":289,
    "gn:feature_class":"P",
    "gn:feature_code":"PPL",
    "gn:name":"Wetthet",
    "gn:population":0,
    "gn:timezone":"Asia/Yangon",
    "iso:country":"MM",
    "wof:name":"Wetthet",
    "wof:placetype":"locality"
},
  "geometry": {"coordinates":[94.06309,21.78774],"type":"Point"}
}