{
  "type": "Feature",
  "properties": {
    "gn:admin1_code":"3.0",
    "gn:admin2_code":"MMR017D001",
    "gn:admin3_code":"MMR017005",
    "gn:asciiname":"Akegyi",
    "gn:country_code":"MM",
    "gn:dem":15,
    "gn:feature_class":"P",
    "gn:feature_code":"PPL",
    "gn:name":"Akegyi",
    "gn:population":0,
    "gn:timezone":"Asia/Yangon",
    "iso:country":"MM",
    "wof:name":"Akegyi",
    "wof:placetype":"locality"
},
  "geometry": {"coordinates":[95.33459999999999,17.27854],"type":"Point"}
}