{
  "type": "Feature",
  "properties": {
    "gn:admin1_code":"5.0",
    "gn:admin2_code":"MMR003D002",
    "gn:admin3_code":"MMR003005",
    "gn:asciiname":"Hpawwawmo",
    "gn:country_code":"MM",
    "gn:dem":291,
    "gn:feature_class":"P",
    "gn:feature_code":"PPL",
    "gn:name":"Hpawwawmo",
    "gn:population":0,
    "gn:timezone":"Asia/Bangkok",
    "iso:country":"MM",
    "wof:name":"Hpawwawmo",
    "wof:placetype":"locality"
},
  "geometry": {"coordinates":[98.71433,16.29281],"type":"Point"}
}