{
  "type": "Feature",
  "properties": {
    "gn:admin1_code":"11.0",
    "gn:admin2_code":"MMR015D003",
    "gn:admin3_code":"MMR015016",
    "gn:asciiname":"Ompom",
    "gn:country_code":"MM",
    "gn:dem":1395,
    "gn:feature_class":"P",
    "gn:feature_code":"PPL",
    "gn:name":"Ompom",
    "gn:population":0,
    "gn:timezone":"Asia/Yangon",
    "iso:country":"MM",
    "wof:name":"Ompom",
    "wof:placetype":"locality"
},
  "geometry": {"coordinates":[97.11826000000001,22.86301],"type":"Point"}
}