{
  "type": "Feature",
  "properties": {
    "gn:admin1_code":"10.0",
    "gn:admin2_code":"MMR005D004",
    "gn:admin3_code":"MMR005023",
    "gn:asciiname":"Tonbok",
    "gn:country_code":"MM",
    "gn:dem":325,
    "gn:feature_class":"P",
    "gn:feature_code":"PPL",
    "gn:name":"Tonbok",
    "gn:population":0,
    "gn:timezone":"Asia/Yangon",
    "iso:country":"MM",
    "wof:name":"Tonbok",
    "wof:placetype":"locality"
},
  "geometry": {"coordinates":[95.48654000000001,24.43286],"type":"Point"}
}