{
  "type": "Feature",
  "properties": {
    "gn:admin1_code":"11.0",
    "gn:admin2_code":"MMR016D003",
    "gn:admin3_code":"MMR016010",
    "gn:asciiname":"Wan En",
    "gn:cc2":"MM",
    "gn:country_code":"MM",
    "gn:dem":1160,
    "gn:feature_class":"P",
    "gn:feature_code":"PPL",
    "gn:name":"W\u0101n En",
    "gn:population":0,
    "gn:timezone":"Asia/Yangon",
    "iso:country":"MM",
    "name:und_x_variant":[
        "En",
        "W\u0101n En"
    ],
    "wof:name":"Wan En",
    "wof:placetype":"locality"
},
  "geometry": {"coordinates":[99.61639,20.79167],"type":"Point"}
}