{
  "type": "Feature",
  "properties": {
    "gn:admin1_code":"11.0",
    "gn:admin2_code":"MMR015D002",
    "gn:admin3_code":"MMR015009",
    "gn:asciiname":"Kyinyang",
    "gn:country_code":"MM",
    "gn:dem":788,
    "gn:feature_class":"P",
    "gn:feature_code":"PPL",
    "gn:name":"Kyinyang",
    "gn:population":0,
    "gn:timezone":"Asia/Yangon",
    "iso:country":"MM",
    "name:und_x_variant":[
        "Kingyaung",
        "Kyinyang"
    ],
    "wof:name":"Kyinyang",
    "wof:placetype":"locality"
},
  "geometry": {"coordinates":[98.02104,24.05327],"type":"Point"}
}