{
  "type": "Feature",
  "properties": {
    "gn:admin1_code":"12.0",
    "gn:asciiname":"Yegan-nge",
    "gn:country_code":"MM",
    "gn:dem":-9999,
    "gn:feature_class":"P",
    "gn:feature_code":"PPL",
    "gn:name":"Yegan-nge",
    "gn:population":0,
    "gn:timezone":"Asia/Yangon",
    "iso:country":"MM",
    "wof:name":"Yegan-nge",
    "wof:placetype":"locality"
},
  "geometry": {"coordinates":[98.75,11.51667],"type":"Point"}
}