{
  "type": "Feature",
  "properties": {
    "gn:admin1_code":"2.0",
    "gn:admin2_code":"MMR004D003",
    "gn:admin3_code":"MMR004003",
    "gn:asciiname":"Klangkhua",
    "gn:country_code":"MM",
    "gn:dem":1649,
    "gn:feature_class":"P",
    "gn:feature_code":"PPL",
    "gn:name":"Klangkhua",
    "gn:population":0,
    "gn:timezone":"Asia/Yangon",
    "iso:country":"MM",
    "wof:name":"Klangkhua",
    "wof:placetype":"locality"
},
  "geometry": {"coordinates":[93.43333,22.93333],"type":"Point"}
}