{
  "type": "Feature",
  "properties": {
    "gn:admin1_code":"16.0",
    "gn:admin2_code":"MMR007D002",
    "gn:admin3_code":"MMR007012",
    "gn:asciiname":"Ngamyitchin",
    "gn:country_code":"MM",
    "gn:dem":31,
    "gn:feature_class":"P",
    "gn:feature_code":"PPL",
    "gn:name":"Ngamyitchin",
    "gn:population":0,
    "gn:timezone":"Asia/Yangon",
    "iso:country":"MM",
    "name:und_x_variant":[
        "Ngamytchin",
        "Ngamyitchin"
    ],
    "wof:name":"Ngamyitchin",
    "wof:placetype":"locality"
},
  "geometry": {"coordinates":[96.60666999999999,18.3751],"type":"Point"}
}