{
  "type": "Feature",
  "properties": {
    "gn:admin1_code":"16.0",
    "gn:admin2_code":"MMR007D002",
    "gn:admin3_code":"MMR007013",
    "gn:asciiname":"Shanywa",
    "gn:country_code":"MM",
    "gn:dem":63,
    "gn:feature_class":"P",
    "gn:feature_code":"PPL",
    "gn:name":"Shanywa",
    "gn:population":0,
    "gn:timezone":"Asia/Yangon",
    "iso:country":"MM",
    "wof:name":"Shanywa",
    "wof:placetype":"locality"
},
  "geometry": {"coordinates":[96.31417,18.92757000000001],"type":"Point"}
}