{
  "type": "Feature",
  "properties": {
    "gn:admin1_code":"15.0",
    "gn:admin2_code":"MMR009D001",
    "gn:admin3_code":"MMR009006",
    "gn:asciiname":"Kyindegon",
    "gn:country_code":"MM",
    "gn:dem":290,
    "gn:feature_class":"P",
    "gn:feature_code":"PPL",
    "gn:name":"Kyindegon",
    "gn:population":0,
    "gn:timezone":"Asia/Yangon",
    "iso:country":"MM",
    "wof:name":"Kyindegon",
    "wof:placetype":"locality"
},
  "geometry": {"coordinates":[95.42412,20.68729],"type":"Point"}
}