{
  "type": "Feature",
  "properties": {
    "gn:admin1_code":"15.0",
    "gn:admin2_code":"MMR009D003",
    "gn:admin3_code":"MMR009015",
    "gn:asciiname":"Magyi Kwin",
    "gn:country_code":"MM",
    "gn:dem":78,
    "gn:feature_class":"P",
    "gn:feature_code":"PPL",
    "gn:name":"Magyi Kwin",
    "gn:population":0,
    "gn:timezone":"Asia/Yangon",
    "iso:country":"MM",
    "wof:name":"Magyi Kwin",
    "wof:placetype":"locality"
},
  "geometry": {"coordinates":[94.98206999999999,18.96613],"type":"Point"}
}