{
  "type": "Feature",
  "properties": {
    "gn:admin1_code":"8.0",
    "gn:admin2_code":"MMR010D004",
    "gn:admin3_code":"MMR010018",
    "gn:asciiname":"Palin",
    "gn:country_code":"MM",
    "gn:dem":193,
    "gn:feature_class":"P",
    "gn:feature_code":"PPL",
    "gn:name":"Palin",
    "gn:population":0,
    "gn:timezone":"Asia/Yangon",
    "iso:country":"MM",
    "name:ces_x_preferred":[
        "Palin"
    ],
    "wof:name":"Palin",
    "wof:placetype":"locality"
},
  "geometry": {"coordinates":[95.32944999999999,21.20674],"type":"Point"}
}