{
  "type": "Feature",
  "properties": {
    "gn:admin1_code":"15.0",
    "gn:admin2_code":"MMR009D003",
    "gn:admin3_code":"MMR009012",
    "gn:asciiname":"Shwebangaing",
    "gn:country_code":"MM",
    "gn:dem":189,
    "gn:feature_class":"P",
    "gn:feature_code":"PPL",
    "gn:name":"Shwebangaing",
    "gn:population":0,
    "gn:timezone":"Asia/Yangon",
    "iso:country":"MM",
    "wof:name":"Shwebangaing",
    "wof:placetype":"locality"
},
  "geometry": {"coordinates":[94.93557,19.51772],"type":"Point"}
}