{
  "type": "Feature",
  "properties": {
    "gn:admin1_code":"16.0",
    "gn:admin2_code":"MMR007D002",
    "gn:admin3_code":"MMR007013",
    "gn:asciiname":"Yebyukhin",
    "gn:country_code":"MM",
    "gn:dem":52,
    "gn:feature_class":"P",
    "gn:feature_code":"PPL",
    "gn:name":"Yebyukhin",
    "gn:population":0,
    "gn:timezone":"Asia/Yangon",
    "iso:country":"MM",
    "wof:name":"Yebyukhin",
    "wof:placetype":"locality"
},
  "geometry": {"coordinates":[96.43576,18.90753],"type":"Point"}
}