{
  "type": "Feature",
  "properties": {
    "gn:admin1_code":"15.0",
    "gn:admin2_code":"MMR009D001",
    "gn:admin3_code":"MMR009005",
    "gn:asciiname":"Tanaunggwin",
    "gn:country_code":"MM",
    "gn:dem":160,
    "gn:feature_class":"P",
    "gn:feature_code":"PPL",
    "gn:name":"Tanaunggwin",
    "gn:population":0,
    "gn:timezone":"Asia/Yangon",
    "iso:country":"MM",
    "wof:name":"Tanaunggwin",
    "wof:placetype":"locality"
},
  "geometry": {"coordinates":[95.59061,20.10445],"type":"Point"}
}