{
  "type": "Feature",
  "properties": {
    "gn:admin1_code":"10.0",
    "gn:admin2_code":"MMR005D004",
    "gn:admin3_code":"MMR005025",
    "gn:asciiname":"Ywathitkon",
    "gn:country_code":"MM",
    "gn:dem":201,
    "gn:feature_class":"P",
    "gn:feature_code":"PPL",
    "gn:name":"Ywathitk\u00f4n",
    "gn:population":0,
    "gn:timezone":"Asia/Yangon",
    "iso:country":"MM",
    "name:urd_x_preferred":[
        "\u06cc\u0648\u0627\u062a\u06be\u0679\u06a9\u0648\u0646"
    ],
    "wof:name":"Ywathitkon",
    "wof:placetype":"locality"
},
  "geometry": {"coordinates":[95.67494000000001,23.9028],"type":"Point"}
}