{
  "type": "Feature",
  "properties": {
    "gn:admin1_code":"10.0",
    "gn:admin2_code":"MMR005D005",
    "gn:admin3_code":"MMR005027",
    "gn:asciiname":"Ngapa",
    "gn:country_code":"MM",
    "gn:dem":120,
    "gn:feature_class":"P",
    "gn:feature_code":"PPL",
    "gn:name":"Ngapa",
    "gn:population":0,
    "gn:timezone":"Asia/Yangon",
    "iso:country":"MM",
    "wof:name":"Ngapa",
    "wof:placetype":"locality"
},
  "geometry": {"coordinates":[94.05012000000001,22.96719],"type":"Point"}
}