{
  "type": "Feature",
  "properties": {
    "gn:admin1_code":"11.0",
    "gn:admin2_code":"MMR015D003",
    "gn:admin3_code":"MMR015013",
    "gn:asciiname":"Namsaunghu",
    "gn:country_code":"MM",
    "gn:dem":979,
    "gn:feature_class":"P",
    "gn:feature_code":"PPL",
    "gn:name":"Namsaunghu",
    "gn:population":0,
    "gn:timezone":"Asia/Yangon",
    "iso:country":"MM",
    "wof:name":"Namsaunghu",
    "wof:placetype":"locality"
},
  "geometry": {"coordinates":[96.45179,22.4856],"type":"Point"}
}