{
  "type": "Feature",
  "properties": {
    "gn:admin1_code":"11.0",
    "gn:admin2_code":"MMR016D002",
    "gn:admin3_code":"MMR016006",
    "gn:asciiname":"Wan Pa-hok",
    "gn:country_code":"MM",
    "gn:dem":1065,
    "gn:feature_class":"P",
    "gn:feature_code":"PPL",
    "gn:name":"W\u0101n Pa-h\u014dk",
    "gn:population":0,
    "gn:timezone":"Asia/Yangon",
    "iso:country":"MM",
    "name:und_x_variant":[
        "W\u0101n Kaw Pa-h\u00f6k",
        "W\u0101n Pa-h\u014dk"
    ],
    "wof:name":"Wan Pa-hok",
    "wof:placetype":"locality"
},
  "geometry": {"coordinates":[99.60202,20.51967],"type":"Point"}
}