{
  "type": "Feature",
  "properties": {
    "gn:admin1_code":"4.0",
    "gn:admin2_code":"MMR001D001",
    "gn:admin3_code":"MMR001001",
    "gn:asciiname":"Mahtangkawng",
    "gn:country_code":"MM",
    "gn:dem":185,
    "gn:feature_class":"P",
    "gn:feature_code":"PPL",
    "gn:name":"Mahtangkawng",
    "gn:population":0,
    "gn:timezone":"Asia/Yangon",
    "iso:country":"MM",
    "wof:name":"Mahtangkawng",
    "wof:placetype":"locality"
},
  "geometry": {"coordinates":[97.16543,24.83653],"type":"Point"}
}