{
  "type": "Feature",
  "properties": {
    "gn:admin1_code":"11.0",
    "gn:admin2_code":"MMR015D001",
    "gn:admin3_code":"MMR015002",
    "gn:asciiname":"Pangwa",
    "gn:country_code":"MM",
    "gn:dem":879,
    "gn:feature_class":"P",
    "gn:feature_code":"PPL",
    "gn:name":"Pangwa",
    "gn:population":0,
    "gn:timezone":"Asia/Yangon",
    "iso:country":"MM",
    "wof:name":"Pangwa",
    "wof:placetype":"locality"
},
  "geometry": {"coordinates":[98.38751000000001,23.3678],"type":"Point"}
}