{
  "type": "Feature",
  "properties": {
    "gn:admin1_code":"10.0",
    "gn:admin2_code":"MMR005D004",
    "gn:admin3_code":"MMR005023",
    "gn:asciiname":"Magyigon",
    "gn:country_code":"MM",
    "gn:dem":205,
    "gn:feature_class":"P",
    "gn:feature_code":"PPL",
    "gn:name":"Magyigon",
    "gn:population":0,
    "gn:timezone":"Asia/Yangon",
    "iso:country":"MM",
    "name:und_x_variant":[
        "Man-in",
        "Magyigon"
    ],
    "wof:name":"Magyigon",
    "wof:placetype":"locality"
},
  "geometry": {"coordinates":[95.66283,24.7303],"type":"Point"}
}