{
  "type": "Feature",
  "properties": {
    "gn:admin1_code":"17.0",
    "gn:admin2_code":"MMR013D003",
    "gn:admin3_code":"MMR013025",
    "gn:asciiname":"Beiktheik Ohnbinzu",
    "gn:country_code":"MM",
    "gn:dem":8,
    "gn:feature_class":"P",
    "gn:feature_code":"PPL",
    "gn:name":"Beiktheik Ohnbinzu",
    "gn:population":0,
    "gn:timezone":"Asia/Yangon",
    "iso:country":"MM",
    "wof:name":"Beiktheik Ohnbinzu",
    "wof:placetype":"locality"
},
  "geometry": {"coordinates":[96.68838,16.69219],"type":"Point"}
}