{
  "type": "Feature",
  "properties": {
    "gn:admin1_code":"11.0",
    "gn:admin2_code":"MMR016D001",
    "gn:admin3_code":"MMR016002",
    "gn:asciiname":"Wan Muenhkamhpu",
    "gn:country_code":"MM",
    "gn:dem":1579,
    "gn:feature_class":"P",
    "gn:feature_code":"PPL",
    "gn:name":"W\u0101n M\u00fcnhkamhpu",
    "gn:population":0,
    "gn:timezone":"Asia/Yangon",
    "iso:country":"MM",
    "wof:name":"Wan Muenhkamhpu",
    "wof:placetype":"locality"
},
  "geometry": {"coordinates":[99.34356,21.8558],"type":"Point"}
}