{
  "type": "Feature",
  "properties": {
    "gn:admin1_code":"18.0",
    "gn:admin2_code":"MMR018D001",
    "gn:admin3_code":"MMR018003",
    "gn:asciiname":"Magyigon",
    "gn:country_code":"MM",
    "gn:dem":152,
    "gn:feature_class":"P",
    "gn:feature_code":"PPL",
    "gn:name":"Magyigon",
    "gn:population":0,
    "gn:timezone":"Asia/Yangon",
    "iso:country":"MM",
    "wof:name":"Magyigon",
    "wof:placetype":"locality"
},
  "geometry": {"coordinates":[96.26545,20.10971],"type":"Point"}
}