{
  "type": "Feature",
  "properties": {
    "gn:admin1_code":"10.0",
    "gn:admin2_code":"MMR005D008",
    "gn:admin3_code":"MMR005035",
    "gn:asciiname":"Hpuntret",
    "gn:country_code":"MM",
    "gn:dem":1628,
    "gn:feature_class":"P",
    "gn:feature_code":"PPL",
    "gn:name":"Hpuntret",
    "gn:population":0,
    "gn:timezone":"Asia/Yangon",
    "iso:country":"MM",
    "wof:name":"Hpuntret",
    "wof:placetype":"locality"
},
  "geometry": {"coordinates":[94.70729,25.3747],"type":"Point"}
}