{
  "type": "Feature",
  "properties": {
    "gn:admin1_code":"17.0",
    "gn:admin2_code":"MMR013D001",
    "gn:admin3_code":"MMR013002",
    "gn:asciiname":"Thandebin",
    "gn:country_code":"MM",
    "gn:dem":21,
    "gn:feature_class":"P",
    "gn:feature_code":"PPL",
    "gn:name":"Thandebin",
    "gn:population":0,
    "gn:timezone":"Asia/Yangon",
    "iso:country":"MM",
    "wof:name":"Thandebin",
    "wof:placetype":"locality"
},
  "geometry": {"coordinates":[96.11834,17.06287],"type":"Point"}
}