{
  "type": "Feature",
  "properties": {
    "gn:admin1_code":"11.0",
    "gn:admin2_code":"MMR016D002",
    "gn:admin3_code":"MMR016006",
    "gn:asciiname":"Wan Kanghkaw-yao",
    "gn:country_code":"MM",
    "gn:dem":1331,
    "gn:feature_class":"P",
    "gn:feature_code":"PPL",
    "gn:name":"Wan Kanghkaw-yao",
    "gn:population":0,
    "gn:timezone":"Asia/Yangon",
    "iso:country":"MM",
    "wof:name":"Wan Kanghkaw-yao",
    "wof:placetype":"locality"
},
  "geometry": {"coordinates":[99.29000000000001,20.81028],"type":"Point"}
}