{
  "type": "Feature",
  "properties": {
    "gn:admin1_code":"16.0",
    "gn:admin2_code":"MMR007D001",
    "gn:admin3_code":"MMR007008",
    "gn:asciiname":"Lo-e-khi",
    "gn:country_code":"MM",
    "gn:dem":397,
    "gn:feature_class":"P",
    "gn:feature_code":"PPL",
    "gn:name":"Lo-e-khi",
    "gn:population":0,
    "gn:timezone":"Asia/Yangon",
    "iso:country":"MM",
    "name:und_x_variant":[
        "Lo-egyi",
        "Lo-e-khi"
    ],
    "wof:name":"Lo-e-khi",
    "wof:placetype":"locality"
},
  "geometry": {"coordinates":[97.14412,17.67037000000001],"type":"Point"}
}