{
  "type": "Feature",
  "properties": {
    "gn:admin1_code":"16.0",
    "gn:admin2_code":"MMR008D002",
    "gn:admin3_code":"MMR008014",
    "gn:asciiname":"Myetnikwin",
    "gn:country_code":"MM",
    "gn:dem":34,
    "gn:feature_class":"P",
    "gn:feature_code":"PPL",
    "gn:name":"Myetnikwin",
    "gn:population":0,
    "gn:timezone":"Asia/Yangon",
    "iso:country":"MM",
    "wof:name":"Myetnikwin",
    "wof:placetype":"locality"
},
  "geometry": {"coordinates":[95.68891000000001,18.18441],"type":"Point"}
}