{
  "type": "Feature",
  "properties": {
    "gn:admin1_code":"16.0",
    "gn:admin2_code":"MMR007D001",
    "gn:admin3_code":"MMR007008",
    "gn:asciiname":"Hohta",
    "gn:country_code":"MM",
    "gn:dem":147,
    "gn:feature_class":"P",
    "gn:feature_code":"PPL",
    "gn:name":"Hohta",
    "gn:population":0,
    "gn:timezone":"Asia/Yangon",
    "iso:country":"MM",
    "name:und_x_variant":[
        "Bota",
        "Hohta"
    ],
    "wof:name":"Hohta",
    "wof:placetype":"locality"
},
  "geometry": {"coordinates":[97.12481,17.74268],"type":"Point"}
}