{
  "type": "Feature",
  "properties": {
    "gn:admin1_code":"11.0",
    "gn:admin2_code":"MMR014D002",
    "gn:admin3_code":"MMR014013",
    "gn:asciiname":"Ompok",
    "gn:country_code":"MM",
    "gn:dem":912,
    "gn:feature_class":"P",
    "gn:feature_code":"PPL",
    "gn:name":"Ompok",
    "gn:population":0,
    "gn:timezone":"Asia/Yangon",
    "iso:country":"MM",
    "name:ara_x_preferred":[
        "\u0623\u0645\u0628\u0648\u0643"
    ],
    "name:cat_x_preferred":[
        "Ompok"
    ],
    "name:ceb_x_preferred":[
        "Ompok"
    ],
    "name:kan_x_preferred":[
        "\u0c97\u0cca\u0ca1\u0ccd\u0cb2\u0cc6 \u0cae\u0cc0\u0ca8\u0cc1"
    ],
    "name:nld_x_preferred":[
        "Ompok"
    ],
    "name:pol_x_preferred":[
        "Ompok"
    ],
    "name:spa_x_preferred":[
        "Ompok"
    ],
    "name:swe_x_preferred":[
        "Ompok"
    ],
    "name:tha_x_preferred":[
        "\u0e1b\u0e25\u0e32\u0e0a\u0e30\u0e42\u0e2d\u0e19"
    ],
    "name:ukr_x_preferred":[
        "Ompok"
    ],
    "name:vie_x_preferred":[
        "Ompok"
    ],
    "name:war_x_preferred":[
        "Ompok"
    ],
    "name:zho_x_preferred":[
        "\u7d62\u9bf0\u5c6c"
    ],
    "wof:name":"Ompok",
    "wof:placetype":"locality"
},
  "geometry": {"coordinates":[97.96384,21.03769],"type":"Point"}
}