{
  "type": "Feature",
  "properties": {
    "gn:admin1_code":"10.0",
    "gn:admin2_code":"MMR005D001",
    "gn:admin3_code":"MMR005003",
    "gn:asciiname":"Ywathit",
    "gn:country_code":"MM",
    "gn:dem":70,
    "gn:feature_class":"P",
    "gn:feature_code":"PPL",
    "gn:name":"Ywathit",
    "gn:population":0,
    "gn:timezone":"Asia/Yangon",
    "iso:country":"MM",
    "wof:name":"Ywathit",
    "wof:placetype":"locality"
},
  "geometry": {"coordinates":[95.35863000000001,21.70967000000001],"type":"Point"}
}