{
  "type": "Feature",
  "properties": {
    "gn:admin1_code":"16.0",
    "gn:admin2_code":"MMR007D001",
    "gn:admin3_code":"MMR007007",
    "gn:asciiname":"Paungdawthi",
    "gn:country_code":"MM",
    "gn:dem":18,
    "gn:feature_class":"P",
    "gn:feature_code":"PPL",
    "gn:name":"Paungdawthi",
    "gn:population":0,
    "gn:timezone":"Asia/Yangon",
    "iso:country":"MM",
    "name:und_x_variant":[
        "Poungdawthi",
        "Paungdawthi"
    ],
    "wof:name":"Paungdawthi",
    "wof:placetype":"locality"
},
  "geometry": {"coordinates":[96.62560000000001,17.72867999999999],"type":"Point"}
}