{
  "type": "Feature",
  "properties": {
    "gn:admin1_code":"8.0",
    "gn:admin2_code":"MMR010D004",
    "gn:admin3_code":"MMR010019",
    "gn:asciiname":"Oktwin",
    "gn:country_code":"MM",
    "gn:dem":204,
    "gn:feature_class":"P",
    "gn:feature_code":"PPL",
    "gn:name":"Oktwin",
    "gn:population":0,
    "gn:timezone":"Asia/Yangon",
    "iso:country":"MM",
    "name:mya_x_preferred":[
        "\u1021\u102f\u1010\u103a\u1010\u103d\u1004\u103a\u1038\u1019\u103c\u102d\u102f\u1037"
    ],
    "name:shn_x_preferred":[
        "\u1022\u1030\u1075\u103a\u1089\u1010\u1082\u102d\u107c\u103a\u1038\u104a \u101d\u1035\u1004\u103a\u1038"
    ],
    "name:swe_x_preferred":[
        "Oktwin"
    ],
    "wof:name":"Oktwin",
    "wof:placetype":"locality"
},
  "geometry": {"coordinates":[95.73522,21.40213],"type":"Point"}
}