{
  "type": "Feature",
  "properties": {
    "gn:admin1_code":"10.0",
    "gn:admin2_code":"MMR005D003",
    "gn:admin3_code":"MMR005012",
    "gn:asciiname":"Yinmabin",
    "gn:country_code":"MM",
    "gn:dem":183,
    "gn:feature_class":"P",
    "gn:feature_code":"PPL",
    "gn:name":"Yinmabin",
    "gn:population":0,
    "gn:timezone":"Asia/Yangon",
    "iso:country":"MM",
    "name:mya_x_preferred":[
        "\u101a\u1004\u103a\u1038\u1019\u102c\u1015\u1004\u103a\u1019\u103c\u102d\u102f\u1037"
    ],
    "name:urd_x_preferred":[
        "\u06cc\u0646\u0645\u0627\u0628\u06cc\u0646"
    ],
    "wof:name":"Yinmabin",
    "wof:placetype":"locality"
},
  "geometry": {"coordinates":[95.30105,22.16122],"type":"Point"}
}