{
  "type": "Feature",
  "properties": {
    "gn:admin1_code":"3.0",
    "gn:admin2_code":"MMR017D002",
    "gn:admin3_code":"MMR017009",
    "gn:asciiname":"Yele",
    "gn:country_code":"MM",
    "gn:dem":18,
    "gn:feature_class":"P",
    "gn:feature_code":"PPL",
    "gn:name":"Yele",
    "gn:population":0,
    "gn:timezone":"Asia/Yangon",
    "iso:country":"MM",
    "name:ceb_x_preferred":[
        "Yele"
    ],
    "name:fra_x_preferred":[
        "Yele"
    ],
    "name:swe_x_preferred":[
        "Yele"
    ],
    "wof:name":"Yele",
    "wof:placetype":"locality"
},
  "geometry": {"coordinates":[95.65637,17.48265],"type":"Point"}
}