{
  "type": "Feature",
  "properties": {
    "gn:admin1_code":"11.0",
    "gn:admin2_code":"MMR015D001",
    "gn:admin3_code":"MMR015003",
    "gn:asciiname":"Tawngseng",
    "gn:country_code":"MM",
    "gn:dem":1062,
    "gn:feature_class":"P",
    "gn:feature_code":"PPL",
    "gn:name":"Tawngseng",
    "gn:population":0,
    "gn:timezone":"Asia/Yangon",
    "iso:country":"MM",
    "wof:name":"Tawngseng",
    "wof:placetype":"locality"
},
  "geometry": {"coordinates":[98.23392,22.14947],"type":"Point"}
}