{
  "type": "Feature",
  "properties": {
    "gn:admin1_code":"3.0",
    "gn:admin2_code":"MMR017D002",
    "gn:admin3_code":"MMR017011",
    "gn:asciiname":"Sinlu",
    "gn:country_code":"MM",
    "gn:dem":25,
    "gn:feature_class":"P",
    "gn:feature_code":"PPL",
    "gn:name":"Sinlu",
    "gn:population":0,
    "gn:timezone":"Asia/Yangon",
    "iso:country":"MM",
    "wof:name":"Sinlu",
    "wof:placetype":"locality"
},
  "geometry": {"coordinates":[95.34781,18.09928],"type":"Point"}
}