{
  "type": "Feature",
  "properties": {
    "gn:admin1_code":"10.0",
    "gn:admin2_code":"MMR005D002",
    "gn:admin3_code":"MMR005007",
    "gn:asciiname":"Mezaligon",
    "gn:country_code":"MM",
    "gn:dem":147,
    "gn:feature_class":"P",
    "gn:feature_code":"PPL",
    "gn:name":"M\u00e8zaligon",
    "gn:population":0,
    "gn:timezone":"Asia/Yangon",
    "iso:country":"MM",
    "wof:name":"Mezaligon",
    "wof:placetype":"locality"
},
  "geometry": {"coordinates":[95.67014,22.86315],"type":"Point"}
}