{
  "type": "Feature",
  "properties": {
    "gn:admin1_code":"4.0",
    "gn:admin2_code":"MMR001D001",
    "gn:admin3_code":"MMR001002",
    "gn:asciiname":"Wabawng 'Nhkram",
    "gn:country_code":"MM",
    "gn:dem":1029,
    "gn:feature_class":"P",
    "gn:feature_code":"PPL",
    "gn:name":"W\u0101bawng \u2019Nhkram",
    "gn:population":0,
    "gn:timezone":"Asia/Yangon",
    "iso:country":"MM",
    "wof:name":"Wabawng 'Nhkram",
    "wof:placetype":"locality"
},
  "geometry": {"coordinates":[97.78585,25.33899],"type":"Point"}
}