{
  "type": "Feature",
  "properties": {
    "gn:admin1_code":"11.0",
    "gn:admin2_code":"MMR014D001",
    "gn:admin3_code":"MMR014010",
    "gn:asciiname":"Kala",
    "gn:country_code":"MM",
    "gn:dem":1357,
    "gn:feature_class":"P",
    "gn:feature_code":"PPL",
    "gn:name":"Kala",
    "gn:population":0,
    "gn:timezone":"Asia/Yangon",
    "iso:country":"MM",
    "wof:name":"Kala",
    "wof:placetype":"locality"
},
  "geometry": {"coordinates":[96.95926,19.77606],"type":"Point"}
}