{
  "type": "Feature",
  "properties": {
    "gn:admin1_code":"11.0",
    "gn:admin2_code":"MMR015D001",
    "gn:admin3_code":"MMR015004",
    "gn:asciiname":"Man Umhai",
    "gn:country_code":"MM",
    "gn:dem":632,
    "gn:feature_class":"P",
    "gn:feature_code":"PPL",
    "gn:name":"M\u0101n \u016amhai",
    "gn:population":0,
    "gn:timezone":"Asia/Yangon",
    "iso:country":"MM",
    "wof:name":"Man Umhai",
    "wof:placetype":"locality"
},
  "geometry": {"coordinates":[98.58087999999999,22.21277000000001],"type":"Point"}
}