{
  "type": "Feature",
  "properties": {
    "gn:admin1_code":"16.0",
    "gn:admin2_code":"MMR008D002",
    "gn:admin3_code":"MMR008014",
    "gn:asciiname":"Gyobingauk",
    "gn:country_code":"MM",
    "gn:dem":34,
    "gn:feature_class":"P",
    "gn:feature_code":"PPL",
    "gn:name":"Gyobingauk",
    "gn:population":0,
    "gn:timezone":"Asia/Yangon",
    "iso:country":"MM",
    "name:mya_x_preferred":[
        "\u1000\u103c\u102d\u102f\u1037\u1015\u1004\u103a\u1000\u1031\u102c\u1000\u103a\u1019\u103c\u102d\u102f\u1037"
    ],
    "name:shn_x_preferred":[
        "\u1075\u103b\u1030\u101d\u103a\u1089\u1015\u102d\u107c\u103a\u1087\u1075\u103d\u1075\u103a\u1089\u104a \u101d\u1035\u1004\u103a\u1038"
    ],
    "name:swe_x_preferred":[
        "Gyobingauk"
    ],
    "name:und_x_variant":[
        "Kyobingauk",
        "Gobingauk"
    ],
    "wof:name":"Gyobingauk",
    "wof:placetype":"locality"
},
  "geometry": {"coordinates":[95.64879000000001,18.23064],"type":"Point"}
}