{
  "type": "Feature",
  "properties": {
    "gn:admin1_code":"16.0",
    "gn:admin2_code":"MMR008D002",
    "gn:admin3_code":"MMR008014",
    "gn:asciiname":"Gyobingauk",
    "gn:country_code":"MM",
    "gn:dem":34,
    "gn:feature_class":"P",
    "gn:feature_code":"PPL",
    "gn:name":"Gyobingauk",
    "gn:population":0,
    "gn:timezone":"Asia/Yangon",
    "iso:country":"MM",
    "name:und_x_variant":[
        "Kyobingauk",
        "Gobingauk",
        "Gyobingauk"
    ],
    "wof:name":"Gyobingauk",
    "wof:placetype":"locality"
},
  "geometry": {"coordinates":[95.64879000000001,18.23064],"type":"Point"}
}