{
  "type": "Feature",
  "properties": {
    "gn:admin1_code":"11.0",
    "gn:admin2_code":"MMR014D001",
    "gn:admin3_code":"MMR014002",
    "gn:asciiname":"Ligaung",
    "gn:country_code":"MM",
    "gn:dem":887,
    "gn:feature_class":"P",
    "gn:feature_code":"PPL",
    "gn:name":"Ligaung",
    "gn:population":0,
    "gn:timezone":"Asia/Yangon",
    "iso:country":"MM",
    "wof:name":"Ligaung",
    "wof:placetype":"locality"
},
  "geometry": {"coordinates":[96.91262999999999,20.25876],"type":"Point"}
}