{
  "type": "Feature",
  "properties": {
    "gn:admin1_code":"1.0",
    "gn:admin2_code":"MMR012D005",
    "gn:admin3_code":"MMR012004",
    "gn:asciiname":"Tagu",
    "gn:country_code":"MM",
    "gn:dem":13,
    "gn:feature_class":"P",
    "gn:feature_code":"PPL",
    "gn:name":"Tagu",
    "gn:population":0,
    "gn:timezone":"Asia/Yangon",
    "iso:country":"MM",
    "name:mya_x_preferred":[
        "\u1010\u1014\u103a\u1001\u1030\u1038\u101c"
    ],
    "wof:name":"Tagu",
    "wof:placetype":"locality"
},
  "geometry": {"coordinates":[93.12213,20.88143],"type":"Point"}
}