{
  "type": "Feature",
  "properties": {
    "gn:admin1_code":"5.0",
    "gn:admin2_code":"MMR003D001",
    "gn:admin3_code":"MMR003004",
    "gn:asciiname":"Naplawkaw",
    "gn:country_code":"MM",
    "gn:dem":788,
    "gn:feature_class":"P",
    "gn:feature_code":"PPL",
    "gn:name":"Naplawkaw",
    "gn:population":0,
    "gn:timezone":"Asia/Yangon",
    "iso:country":"MM",
    "name:und_x_variant":[
        "Netlawbaw",
        "Naplawkaw"
    ],
    "wof:name":"Naplawkaw",
    "wof:placetype":"locality"
},
  "geometry": {"coordinates":[96.64136000000001,19.23232],"type":"Point"}
}