{
  "type": "Feature",
  "properties": {
    "gn:admin1_code":"15.0",
    "gn:admin2_code":"MMR009D004",
    "gn:admin3_code":"MMR009020",
    "gn:asciiname":"Myaing",
    "gn:country_code":"MM",
    "gn:dem":263,
    "gn:feature_class":"P",
    "gn:feature_code":"PPL",
    "gn:name":"Myaing",
    "gn:population":0,
    "gn:timezone":"Asia/Yangon",
    "iso:country":"MM",
    "name:mya_x_preferred":[
        "\u1019\u103c\u102d\u102f\u1004\u103a\u1019\u103c\u102d\u102f\u1037"
    ],
    "name:shn_x_preferred":[
        "\u1019\u103b\u1085\u1004\u103a\u1087\u104a \u101d\u1035\u1004\u103a\u1038"
    ],
    "name:urd_x_preferred":[
        "\u0645\u06cc\u0627\u0626\u0646\u06af"
    ],
    "wof:name":"Myaing",
    "wof:placetype":"locality"
},
  "geometry": {"coordinates":[94.85415,21.6137],"type":"Point"}
}