{
  "type": "Feature",
  "properties": {
    "gn:admin1_code":"3.0",
    "gn:admin2_code":"MMR017D004",
    "gn:admin3_code":"MMR017016",
    "gn:asciiname":"Baingdaunggyaung",
    "gn:country_code":"MM",
    "gn:dem":15,
    "gn:feature_class":"P",
    "gn:feature_code":"PPL",
    "gn:name":"Baingdaunggyaung",
    "gn:population":0,
    "gn:timezone":"Asia/Yangon",
    "iso:country":"MM",
    "wof:name":"Baingdaunggyaung",
    "wof:placetype":"locality"
},
  "geometry": {"coordinates":[94.79583,16.02652],"type":"Point"}
}