{
  "type": "Feature",
  "properties": {
    "gn:admin1_code":"6.0",
    "gn:admin2_code":"MMR002D001",
    "gn:admin3_code":"MMR002002",
    "gn:asciiname":"Pya-mue-daw",
    "gn:country_code":"MM",
    "gn:dem":892,
    "gn:feature_class":"P",
    "gn:feature_code":"PPL",
    "gn:name":"Pya-m\u00fc-daw",
    "gn:population":0,
    "gn:timezone":"Asia/Yangon",
    "iso:country":"MM",
    "wof:name":"Pya-mue-daw",
    "wof:placetype":"locality"
},
  "geometry": {"coordinates":[97.13984000000001,19.59775],"type":"Point"}
}