{
  "type": "Feature",
  "properties": {
    "gn:admin1_code":"11.0",
    "gn:admin2_code":"MMR014D001",
    "gn:admin3_code":"MMR014009",
    "gn:asciiname":"Yethpautkon",
    "gn:country_code":"MM",
    "gn:dem":378,
    "gn:feature_class":"P",
    "gn:feature_code":"PPL",
    "gn:name":"Yethpautkon",
    "gn:population":0,
    "gn:timezone":"Asia/Yangon",
    "iso:country":"MM",
    "wof:name":"Yethpautkon",
    "wof:placetype":"locality"
},
  "geometry": {"coordinates":[96.54882000000001,20.04113],"type":"Point"}
}