{
  "type": "Feature",
  "properties": {
    "gn:admin1_code":"11.0",
    "gn:admin2_code":"MMR015D001",
    "gn:admin3_code":"MMR015003",
    "gn:asciiname":"Man Kaw-leng",
    "gn:country_code":"MM",
    "gn:dem":857,
    "gn:feature_class":"P",
    "gn:feature_code":"PPL",
    "gn:name":"M\u0101n Kaw-leng",
    "gn:population":0,
    "gn:timezone":"Asia/Yangon",
    "iso:country":"MM",
    "wof:name":"Man Kaw-leng",
    "wof:placetype":"locality"
},
  "geometry": {"coordinates":[97.94525,22.4093],"type":"Point"}
}