{
  "type": "Feature",
  "properties": {
    "gn:admin1_code":"11.0",
    "gn:admin2_code":"MMR016D003",
    "gn:admin3_code":"MMR016009",
    "gn:asciiname":"Wan Ai-hsamhwe-hok",
    "gn:country_code":"MM",
    "gn:dem":536,
    "gn:feature_class":"P",
    "gn:feature_code":"PPL",
    "gn:name":"W\u0101n Ai-hsamhwe-hok",
    "gn:population":0,
    "gn:timezone":"Asia/Yangon",
    "iso:country":"MM",
    "wof:name":"Wan Ai-hsamhwe-hok",
    "wof:placetype":"locality"
},
  "geometry": {"coordinates":[100.11821999999999,20.65798],"type":"Point"}
}