{
  "type": "Feature",
  "properties": {
    "gn:admin1_code":"11.0",
    "gn:admin2_code":"MMR015D001",
    "gn:admin3_code":"MMR015020",
    "gn:asciiname":"Man Hsenhsiao",
    "gn:country_code":"MM",
    "gn:dem":1204,
    "gn:feature_class":"P",
    "gn:feature_code":"PPL",
    "gn:name":"M\u0101n Hsenhsiao",
    "gn:population":0,
    "gn:timezone":"Asia/Yangon",
    "iso:country":"MM",
    "wof:name":"Man Hsenhsiao",
    "wof:placetype":"locality"
},
  "geometry": {"coordinates":[98.63388,23.4454],"type":"Point"}
}