{
  "type": "Feature",
  "properties": {
    "gn:admin1_code":"11.0",
    "gn:admin2_code":"MMR014D002",
    "gn:admin3_code":"MMR014013",
    "gn:asciiname":"Hkawlaw",
    "gn:country_code":"MM",
    "gn:dem":763,
    "gn:feature_class":"P",
    "gn:feature_code":"PPL",
    "gn:name":"Hkawlaw",
    "gn:population":0,
    "gn:timezone":"Asia/Yangon",
    "iso:country":"MM",
    "wof:name":"Hkawlaw",
    "wof:placetype":"locality"
},
  "geometry": {"coordinates":[98.08929999999999,20.7748],"type":"Point"}
}