{
  "type": "Feature",
  "properties": {
    "gn:admin1_code":"11.0",
    "gn:admin2_code":"MMR016D001",
    "gn:admin3_code":"MMR016001",
    "gn:asciiname":"Wan Namlin",
    "gn:country_code":"MM",
    "gn:dem":1811,
    "gn:feature_class":"P",
    "gn:feature_code":"PPL",
    "gn:name":"W\u0101n Namlin",
    "gn:population":0,
    "gn:timezone":"Asia/Yangon",
    "iso:country":"MM",
    "name:und_x_variant":[
        "W\u0101n Kaw Namlin",
        "W\u0101n Namlin"
    ],
    "wof:name":"Wan Namlin",
    "wof:placetype":"locality"
},
  "geometry": {"coordinates":[99.77043999999999,21.36791],"type":"Point"}
}