{
  "type": "Feature",
  "properties": {
    "gn:admin1_code":"12.0",
    "gn:admin2_code":"MMR006D001",
    "gn:admin3_code":"MMR006004",
    "gn:asciiname":"Yebyu",
    "gn:country_code":"MM",
    "gn:dem":21,
    "gn:feature_class":"P",
    "gn:feature_code":"PPL",
    "gn:name":"Yebyu",
    "gn:population":0,
    "gn:timezone":"Asia/Yangon",
    "iso:country":"MM",
    "wof:name":"Yebyu",
    "wof:placetype":"locality"
},
  "geometry": {"coordinates":[98.19835999999999,14.24767],"type":"Point"}
}