{
  "type": "Feature",
  "properties": {
    "gn:admin1_code":"10.0",
    "gn:admin2_code":"MMR005D001",
    "gn:admin3_code":"MMR005001",
    "gn:asciiname":"Kyun-u-daw",
    "gn:country_code":"MM",
    "gn:dem":100,
    "gn:feature_class":"P",
    "gn:feature_code":"PPL",
    "gn:name":"Kyun-u-daw",
    "gn:population":0,
    "gn:timezone":"Asia/Yangon",
    "iso:country":"MM",
    "wof:name":"Kyun-u-daw",
    "wof:placetype":"locality"
},
  "geometry": {"coordinates":[95.87611,22.18031],"type":"Point"}
}