{
  "type": "Feature",
  "properties": {
    "gn:admin1_code":"16.0",
    "gn:admin2_code":"MMR007D001",
    "gn:admin3_code":"MMR007008",
    "gn:asciiname":"Paga",
    "gn:country_code":"MM",
    "gn:dem":78,
    "gn:feature_class":"P",
    "gn:feature_code":"PPL",
    "gn:name":"Paga",
    "gn:population":0,
    "gn:timezone":"Asia/Yangon",
    "iso:country":"MM",
    "name:ceb_x_preferred":[
        "Paga"
    ],
    "name:pol_x_preferred":[
        "Paga"
    ],
    "name:swe_x_preferred":[
        "Paga"
    ],
    "wof:name":"Paga",
    "wof:placetype":"locality"
},
  "geometry": {"coordinates":[96.96402,17.95549],"type":"Point"}
}