{
  "type": "Feature",
  "properties": {
    "gn:admin1_code":"11.0",
    "gn:admin2_code":"MMR016D002",
    "gn:admin3_code":"MMR016008",
    "gn:asciiname":"Wan Hpya-hpom",
    "gn:country_code":"MM",
    "gn:dem":1603,
    "gn:feature_class":"P",
    "gn:feature_code":"PPL",
    "gn:name":"W\u0101n Hpya-hpom",
    "gn:population":0,
    "gn:timezone":"Asia/Yangon",
    "iso:country":"MM",
    "wof:name":"Wan Hpya-hpom",
    "wof:placetype":"locality"
},
  "geometry": {"coordinates":[98.80665999999999,20.08612],"type":"Point"}
}