{
  "type": "Feature",
  "properties": {
    "gn:admin1_code":"3.0",
    "gn:admin2_code":"MMR017D006",
    "gn:admin3_code":"MMR017026",
    "gn:asciiname":"Onbin",
    "gn:country_code":"MM",
    "gn:dem":7,
    "gn:feature_class":"P",
    "gn:feature_code":"PPL",
    "gn:name":"\u00d4nbin",
    "gn:population":0,
    "gn:timezone":"Asia/Yangon",
    "iso:country":"MM",
    "wof:name":"Onbin",
    "wof:placetype":"locality"
},
  "geometry": {"coordinates":[95.69013,16.29829],"type":"Point"}
}