{
  "type": "Feature",
  "properties": {
    "gn:admin1_code":"17.0",
    "gn:admin2_code":"MMR013D003",
    "gn:admin3_code":"MMR013029",
    "gn:asciiname":"Pothigon",
    "gn:country_code":"MM",
    "gn:dem":9,
    "gn:feature_class":"P",
    "gn:feature_code":"PPL",
    "gn:name":"Pothigon",
    "gn:population":0,
    "gn:timezone":"Asia/Yangon",
    "iso:country":"MM",
    "name:und_x_variant":[
        "Bothig\u00f4n",
        "Pothigon"
    ],
    "wof:name":"Pothigon",
    "wof:placetype":"locality"
},
  "geometry": {"coordinates":[96.23038,16.47587],"type":"Point"}
}