{
  "type": "Feature",
  "properties": {
    "gn:admin1_code":"16.0",
    "gn:admin2_code":"MMR007D002",
    "gn:admin3_code":"MMR007014",
    "gn:asciiname":"Shazibo",
    "gn:country_code":"MM",
    "gn:dem":43,
    "gn:feature_class":"P",
    "gn:feature_code":"PPL",
    "gn:name":"Shazibo",
    "gn:population":0,
    "gn:timezone":"Asia/Yangon",
    "iso:country":"MM",
    "name:und_x_variant":[
        "Shazebo",
        "Shazibo"
    ],
    "wof:name":"Shazibo",
    "wof:placetype":"locality"
},
  "geometry": {"coordinates":[96.56765,18.78727],"type":"Point"}
}