{
  "type": "Feature",
  "properties": {
    "gn:admin1_code":"11.0",
    "gn:admin2_code":"MMR016D001",
    "gn:admin3_code":"MMR016005",
    "gn:asciiname":"Wan Singmyen",
    "gn:country_code":"MM",
    "gn:dem":1314,
    "gn:feature_class":"P",
    "gn:feature_code":"PPL",
    "gn:name":"W\u0101n Singmyen",
    "gn:population":0,
    "gn:timezone":"Asia/Yangon",
    "iso:country":"MM",
    "wof:name":"Wan Singmyen",
    "wof:placetype":"locality"
},
  "geometry": {"coordinates":[99.87923000000001,21.67481],"type":"Point"}
}