{
  "type": "Feature",
  "properties": {
    "gn:admin1_code":"10.0",
    "gn:admin2_code":"MMR005D008",
    "gn:admin3_code":"MMR005036",
    "gn:asciiname":"Langcheng",
    "gn:country_code":"MM",
    "gn:dem":1044,
    "gn:feature_class":"P",
    "gn:feature_code":"PPL",
    "gn:name":"Langcheng",
    "gn:population":0,
    "gn:timezone":"Asia/Yangon",
    "iso:country":"MM",
    "name:und_x_variant":[
        "Lanakyeng",
        "Langcheng"
    ],
    "wof:name":"Langcheng",
    "wof:placetype":"locality"
},
  "geometry": {"coordinates":[95.42906000000001,26.1139],"type":"Point"}
}