{
  "type": "Feature",
  "properties": {
    "gn:admin1_code":"2.0",
    "gn:asciiname":"Chindauksok",
    "gn:country_code":"MM",
    "gn:dem":233,
    "gn:feature_class":"P",
    "gn:feature_code":"PPL",
    "gn:name":"Chindauks\u00f4k",
    "gn:population":0,
    "gn:timezone":"Asia/Yangon",
    "iso:country":"MM",
    "wof:name":"Chindauksok",
    "wof:placetype":"locality"
},
  "geometry": {"coordinates":[94.12635,20.74615],"type":"Point"}
}