{
  "type": "Feature",
  "properties": {
    "gn:admin1_code":"11.0",
    "gn:admin2_code":"MMR014D002",
    "gn:admin3_code":"MMR014014",
    "gn:asciiname":"Hwe-long",
    "gn:country_code":"MM",
    "gn:dem":799,
    "gn:feature_class":"P",
    "gn:feature_code":"PPL",
    "gn:name":"Hw\u00e8-long",
    "gn:population":0,
    "gn:timezone":"Asia/Yangon",
    "iso:country":"MM",
    "wof:name":"Hwe-long",
    "wof:placetype":"locality"
},
  "geometry": {"coordinates":[98.37336000000001,21.45843],"type":"Point"}
}