{
  "type": "Feature",
  "properties": {
    "gn:admin1_code":"8.0",
    "gn:admin2_code":"MMR010D003",
    "gn:admin3_code":"MMR010016",
    "gn:asciiname":"Kyibin",
    "gn:country_code":"MM",
    "gn:dem":119,
    "gn:feature_class":"P",
    "gn:feature_code":"PPL",
    "gn:name":"Kyibin",
    "gn:population":0,
    "gn:timezone":"Asia/Yangon",
    "iso:country":"MM",
    "wof:name":"Kyibin",
    "wof:placetype":"locality"
},
  "geometry": {"coordinates":[95.93906,21.53411],"type":"Point"}
}