{
  "type": "Feature",
  "properties": {
    "gn:admin1_code":"15.0",
    "gn:admin2_code":"MMR009D005",
    "gn:admin3_code":"MMR009025",
    "gn:asciiname":"Thayetkyin",
    "gn:country_code":"MM",
    "gn:dem":477,
    "gn:feature_class":"P",
    "gn:feature_code":"PPL",
    "gn:name":"Thayetkyin",
    "gn:population":0,
    "gn:timezone":"Asia/Yangon",
    "iso:country":"MM",
    "wof:name":"Thayetkyin",
    "wof:placetype":"locality"
},
  "geometry": {"coordinates":[94.19773000000001,20.92414],"type":"Point"}
}