{
  "type": "Feature",
  "properties": {
    "gn:admin1_code":"8.0",
    "gn:admin2_code":"MMR010D005",
    "gn:admin3_code":"MMR010020",
    "gn:asciiname":"Daungle",
    "gn:country_code":"MM",
    "gn:dem":438,
    "gn:feature_class":"P",
    "gn:feature_code":"PPL",
    "gn:name":"Daungle",
    "gn:population":0,
    "gn:timezone":"Asia/Yangon",
    "iso:country":"MM",
    "name:und_x_variant":[
        "Taungle",
        "Daungle"
    ],
    "wof:name":"Daungle",
    "wof:placetype":"locality"
},
  "geometry": {"coordinates":[95.18123,20.98314],"type":"Point"}
}