{
  "type": "Feature",
  "properties": {
    "gn:admin1_code":"13.0",
    "gn:admin2_code":"MMR011D001",
    "gn:admin3_code":"MMR011003",
    "gn:asciiname":"Kalaw",
    "gn:country_code":"MM",
    "gn:dem":15,
    "gn:feature_class":"P",
    "gn:feature_code":"PPL",
    "gn:name":"Kalaw",
    "gn:population":0,
    "gn:timezone":"Asia/Yangon",
    "iso:country":"MM",
    "name:deu_x_preferred":[
        "Kalaw"
    ],
    "name:fra_x_preferred":[
        "Kalaw"
    ],
    "name:jpn_x_preferred":[
        "\u30ab\u30ed\u30fc"
    ],
    "name:kor_x_preferred":[
        "\uce7c\ub85c"
    ],
    "name:mya_x_preferred":[
        "\u1000\u101c\u1031\u102c\u1019\u103c\u102d\u102f\u1037"
    ],
    "name:pol_x_preferred":[
        "Kalaw"
    ],
    "name:por_x_preferred":[
        "Kalaw"
    ],
    "name:rus_x_preferred":[
        "\u041a\u0430\u043b\u043e"
    ],
    "name:shn_x_preferred":[
        "\u1075\u1062\u1010\u103a\u1087\u101c\u1031\u1083\u1089"
    ],
    "wof:name":"Kalaw",
    "wof:placetype":"locality"
},
  "geometry": {"coordinates":[97.50467999999999,16.40876],"type":"Point"}
}