{
  "type": "Feature",
  "properties": {
    "gn:admin1_code":"11.0",
    "gn:admin2_code":"MMR014D001",
    "gn:admin3_code":"MMR014001",
    "gn:asciiname":"Pangcho",
    "gn:country_code":"MM",
    "gn:dem":1383,
    "gn:feature_class":"P",
    "gn:feature_code":"PPL",
    "gn:name":"Pangcho",
    "gn:population":0,
    "gn:timezone":"Asia/Yangon",
    "iso:country":"MM",
    "wof:name":"Pangcho",
    "wof:placetype":"locality"
},
  "geometry": {"coordinates":[97.01112999999999,20.47762],"type":"Point"}
}