{
  "type": "Feature",
  "properties": {
    "gn:admin1_code":"8.0",
    "gn:admin2_code":"MMR010D001",
    "gn:admin3_code":"MMR010001",
    "gn:asciiname":"Nyaunggwe",
    "gn:country_code":"MM",
    "gn:dem":73,
    "gn:feature_class":"P",
    "gn:feature_code":"PPL",
    "gn:name":"Nyaunggwe",
    "gn:population":0,
    "gn:timezone":"Asia/Yangon",
    "iso:country":"MM",
    "wof:name":"Nyaunggwe",
    "wof:placetype":"locality"
},
  "geometry": {"coordinates":[96.07794,22.01749],"type":"Point"}
}