{
  "type": "Feature",
  "properties": {
    "gn:admin1_code":"8.0",
    "gn:admin2_code":"MMR010D004",
    "gn:admin3_code":"MMR010019",
    "gn:asciiname":"Leywazon",
    "gn:country_code":"MM",
    "gn:dem":155,
    "gn:feature_class":"P",
    "gn:feature_code":"PPL",
    "gn:name":"Leywazon",
    "gn:population":0,
    "gn:timezone":"Asia/Yangon",
    "iso:country":"MM",
    "wof:name":"Leywazon",
    "wof:placetype":"locality"
},
  "geometry": {"coordinates":[95.89154000000001,21.41009],"type":"Point"}
}