{
  "type": "Feature",
  "properties": {
    "gn:admin1_code":"1.0",
    "gn:admin2_code":"MMR012D002",
    "gn:admin3_code":"MMR012010",
    "gn:asciiname":"Pinigyaung",
    "gn:country_code":"MM",
    "gn:dem":97,
    "gn:feature_class":"P",
    "gn:feature_code":"PPL",
    "gn:name":"Pinigyaung",
    "gn:population":0,
    "gn:timezone":"Asia/Yangon",
    "iso:country":"MM",
    "name:und_x_variant":[
        "Pan\u00e8gyaung",
        "Pinigyaung"
    ],
    "wof:name":"Pinigyaung",
    "wof:placetype":"locality"
},
  "geometry": {"coordinates":[92.57172,21.04821],"type":"Point"}
}