{
  "type": "Feature",
  "properties": {
    "gn:admin1_code":"11.0",
    "gn:admin2_code":"MMR014D002",
    "gn:admin3_code":"MMR014014",
    "gn:asciiname":"Ta Nam-un",
    "gn:country_code":"MM",
    "gn:dem":279,
    "gn:feature_class":"P",
    "gn:feature_code":"PPL",
    "gn:name":"T\u0101 Nam-un",
    "gn:population":0,
    "gn:timezone":"Asia/Yangon",
    "iso:country":"MM",
    "wof:name":"Ta Nam-un",
    "wof:placetype":"locality"
},
  "geometry": {"coordinates":[98.49276999999999,20.9923],"type":"Point"}
}