{
  "type": "Feature",
  "properties": {
    "gn:admin1_code":"11.0",
    "gn:admin2_code":"MMR015D008",
    "gn:admin3_code":"MMR015018",
    "gn:asciiname":"Lakye",
    "gn:country_code":"MM",
    "gn:dem":787,
    "gn:feature_class":"P",
    "gn:feature_code":"PPL",
    "gn:name":"Lakye",
    "gn:population":0,
    "gn:timezone":"Asia/Yangon",
    "iso:country":"MM",
    "wof:name":"Lakye",
    "wof:placetype":"locality"
},
  "geometry": {"coordinates":[97.11606,23.57956],"type":"Point"}
}