{
  "type": "Feature",
  "properties": {
    "gn:admin1_code":"3.0",
    "gn:admin2_code":"MMR017D005",
    "gn:admin3_code":"MMR017021",
    "gn:asciiname":"Momaka",
    "gn:country_code":"MM",
    "gn:dem":3,
    "gn:feature_class":"P",
    "gn:feature_code":"PPL",
    "gn:name":"Momaka",
    "gn:population":0,
    "gn:timezone":"Asia/Yangon",
    "iso:country":"MM",
    "wof:name":"Momaka",
    "wof:placetype":"locality"
},
  "geometry": {"coordinates":[95.70731000000001,17.00194],"type":"Point"}
}