{
  "type": "Feature",
  "properties": {
    "gn:admin1_code":"5.0",
    "gn:admin2_code":"MMR003D003",
    "gn:admin3_code":"MMR003006",
    "gn:asciiname":"Yegyaw",
    "gn:country_code":"MM",
    "gn:dem":21,
    "gn:feature_class":"P",
    "gn:feature_code":"PPL",
    "gn:name":"Yegyaw",
    "gn:population":0,
    "gn:timezone":"Asia/Yangon",
    "iso:country":"MM",
    "name:urd_x_preferred":[
        "\u06cc\u06af\u06cc\u0627\u0648"
    ],
    "wof:name":"Yegyaw",
    "wof:placetype":"locality"
},
  "geometry": {"coordinates":[98.01387,16.42874],"type":"Point"}
}