{
  "type": "Feature",
  "properties": {
    "gn:admin1_code":"1.0",
    "gn:admin2_code":"MMR012D003",
    "gn:admin3_code":"MMR012014",
    "gn:asciiname":"Letmauk",
    "gn:country_code":"MM",
    "gn:dem":26,
    "gn:feature_class":"P",
    "gn:feature_code":"PPL",
    "gn:name":"Letmauk",
    "gn:population":0,
    "gn:timezone":"Asia/Yangon",
    "iso:country":"MM",
    "wof:name":"Letmauk",
    "wof:placetype":"locality"
},
  "geometry": {"coordinates":[93.88464999999999,19.87881],"type":"Point"}
}