{
  "type": "Feature",
  "properties": {
    "gn:admin1_code":"11.0",
    "gn:admin2_code":"MMR016D001",
    "gn:admin3_code":"MMR016002",
    "gn:asciiname":"Wan Kungmong",
    "gn:country_code":"MM",
    "gn:dem":843,
    "gn:feature_class":"P",
    "gn:feature_code":"PPL",
    "gn:name":"W\u0101n K\u016bngm\u014dng",
    "gn:population":0,
    "gn:timezone":"Asia/Yangon",
    "iso:country":"MM",
    "wof:name":"Wan Kungmong",
    "wof:placetype":"locality"
},
  "geometry": {"coordinates":[99.44756,21.72847],"type":"Point"}
}