{
  "type": "Feature",
  "properties": {
    "gn:admin1_code":"11.0",
    "gn:admin2_code":"MMR015D008",
    "gn:admin3_code":"MMR015017",
    "gn:asciiname":"Pyinle",
    "gn:country_code":"MM",
    "gn:dem":176,
    "gn:feature_class":"P",
    "gn:feature_code":"PPL",
    "gn:name":"Pyinle",
    "gn:population":0,
    "gn:timezone":"Asia/Yangon",
    "iso:country":"MM",
    "wof:name":"Pyinle",
    "wof:placetype":"locality"
},
  "geometry": {"coordinates":[96.58719000000001,23.10842],"type":"Point"}
}