{
  "type": "Feature",
  "properties": {
    "gn:admin1_code":"15.0",
    "gn:admin2_code":"MMR009D001",
    "gn:admin3_code":"MMR009001",
    "gn:asciiname":"Migyaungye",
    "gn:country_code":"MM",
    "gn:dem":51,
    "gn:feature_class":"P",
    "gn:feature_code":"PPL",
    "gn:name":"Migyaungye",
    "gn:population":0,
    "gn:timezone":"Asia/Yangon",
    "iso:country":"MM",
    "name:und_x_variant":[
        "Migyaunye",
        "Meegyoungye",
        "Migyaungye"
    ],
    "wof:name":"Migyaungye",
    "wof:placetype":"locality"
},
  "geometry": {"coordinates":[95.10287,19.90238],"type":"Point"}
}