{
  "type": "Feature",
  "properties": {
    "gn:admin1_code":"2.0",
    "gn:admin2_code":"MMR004D001",
    "gn:admin3_code":"MMR004005",
    "gn:asciiname":"Suangbem",
    "gn:country_code":"MM",
    "gn:dem":1039,
    "gn:feature_class":"P",
    "gn:feature_code":"PPL",
    "gn:name":"Suangbem",
    "gn:population":0,
    "gn:timezone":"Asia/Yangon",
    "iso:country":"MM",
    "wof:name":"Suangbem",
    "wof:placetype":"locality"
},
  "geometry": {"coordinates":[93.36667,23.96667],"type":"Point"}
}