{
  "type": "Feature",
  "properties": {
    "gn:admin1_code":"8.0",
    "gn:asciiname":"Kyauklongyi",
    "gn:country_code":"MM",
    "gn:dem":88,
    "gn:feature_class":"P",
    "gn:feature_code":"PPL",
    "gn:name":"Kyauklongyi",
    "gn:population":0,
    "gn:timezone":"Asia/Yangon",
    "iso:country":"MM",
    "wof:name":"Kyauklongyi",
    "wof:placetype":"locality"
},
  "geometry": {"coordinates":[95.97432999999999,23.09588],"type":"Point"}
}