{
  "type": "Feature",
  "properties": {
    "gn:admin1_code":"11.0",
    "gn:admin2_code":"MMR014D003",
    "gn:admin3_code":"MMR014018",
    "gn:asciiname":"Wan Htamkwang",
    "gn:country_code":"MM",
    "gn:dem":812,
    "gn:feature_class":"P",
    "gn:feature_code":"PPL",
    "gn:name":"W\u0101n Htamkw\u0101ng",
    "gn:population":0,
    "gn:timezone":"Asia/Yangon",
    "iso:country":"MM",
    "wof:name":"Wan Htamkwang",
    "wof:placetype":"locality"
},
  "geometry": {"coordinates":[98.21194,19.86139],"type":"Point"}
}