{
  "type": "Feature",
  "properties": {
    "gn:admin1_code":"5.0",
    "gn:admin2_code":"MMR003D001",
    "gn:admin3_code":"MMR003004",
    "gn:asciiname":"Malaukchaung",
    "gn:country_code":"MM",
    "gn:dem":197,
    "gn:feature_class":"P",
    "gn:feature_code":"PPL",
    "gn:name":"Malaukchaung",
    "gn:population":0,
    "gn:timezone":"Asia/Yangon",
    "iso:country":"MM",
    "name:und_x_variant":[
        "Ma-aukchaung",
        "Malaukchaung"
    ],
    "wof:name":"Malaukchaung",
    "wof:placetype":"locality"
},
  "geometry": {"coordinates":[96.42247,19.3937],"type":"Point"}
}