{
  "type": "Feature",
  "properties": {
    "gn:admin1_code":"10.0",
    "gn:admin2_code":"MMR005D004",
    "gn:admin3_code":"MMR005025",
    "gn:asciiname":"Nyaungbintha",
    "gn:country_code":"MM",
    "gn:dem":192,
    "gn:feature_class":"P",
    "gn:feature_code":"PPL",
    "gn:name":"Nyaungbintha",
    "gn:population":0,
    "gn:timezone":"Asia/Yangon",
    "iso:country":"MM",
    "wof:name":"Nyaungbintha",
    "wof:placetype":"locality"
},
  "geometry": {"coordinates":[95.74353000000001,23.85312],"type":"Point"}
}