{
  "type": "Feature",
  "properties": {
    "gn:admin1_code":"16.0",
    "gn:admin2_code":"MMR007D001",
    "gn:admin3_code":"MMR007008",
    "gn:asciiname":"Songwe Ashe",
    "gn:country_code":"MM",
    "gn:dem":12,
    "gn:feature_class":"P",
    "gn:feature_code":"PPL",
    "gn:name":"Songw\u00e8 Ashe",
    "gn:population":0,
    "gn:timezone":"Asia/Yangon",
    "iso:country":"MM",
    "name:und_x_variant":[
        "Songw\u00e8",
        "Songw\u00e8 Ashe"
    ],
    "wof:name":"Songwe Ashe",
    "wof:placetype":"locality"
},
  "geometry": {"coordinates":[96.86669000000001,17.8363],"type":"Point"}
}