{
  "type": "Feature",
  "properties": {
    "gn:admin1_code":"8.0",
    "gn:admin2_code":"MMR010D007",
    "gn:admin3_code":"MMR010028",
    "gn:asciiname":"Nwasangok",
    "gn:country_code":"MM",
    "gn:dem":267,
    "gn:feature_class":"P",
    "gn:feature_code":"PPL",
    "gn:name":"Nwasangok",
    "gn:population":0,
    "gn:timezone":"Asia/Yangon",
    "iso:country":"MM",
    "wof:name":"Nwasangok",
    "wof:placetype":"locality"
},
  "geometry": {"coordinates":[95.77077,20.77926],"type":"Point"}
}