{
  "type": "Feature",
  "properties": {
    "gn:admin1_code":"3.0",
    "gn:admin2_code":"MMR017D002",
    "gn:admin3_code":"MMR017011",
    "gn:asciiname":"Petpyu",
    "gn:country_code":"MM",
    "gn:dem":32,
    "gn:feature_class":"P",
    "gn:feature_code":"PPL",
    "gn:name":"Petpyu",
    "gn:population":0,
    "gn:timezone":"Asia/Yangon",
    "iso:country":"MM",
    "wof:name":"Petpyu",
    "wof:placetype":"locality"
},
  "geometry": {"coordinates":[95.15149,17.97438],"type":"Point"}
}