{
  "type": "Feature",
  "properties": {
    "gn:admin1_code":"16.0",
    "gn:admin2_code":"MMR008D002",
    "gn:admin3_code":"MMR008009",
    "gn:asciiname":"Mokka",
    "gn:country_code":"MM",
    "gn:dem":41,
    "gn:feature_class":"P",
    "gn:feature_code":"PPL",
    "gn:name":"Mokka",
    "gn:population":0,
    "gn:timezone":"Asia/Yangon",
    "iso:country":"MM",
    "wof:name":"Mokka",
    "wof:placetype":"locality"
},
  "geometry": {"coordinates":[95.78367,17.95412],"type":"Point"}
}