{
  "type": "Feature",
  "properties": {
    "gn:admin1_code":"11.0",
    "gn:admin2_code":"MMR014D001",
    "gn:admin3_code":"MMR014008",
    "gn:asciiname":"Nakhaigyi",
    "gn:country_code":"MM",
    "gn:dem":962,
    "gn:feature_class":"P",
    "gn:feature_code":"PPL",
    "gn:name":"Nakhaigyi",
    "gn:population":0,
    "gn:timezone":"Asia/Yangon",
    "iso:country":"MM",
    "wof:name":"Nakhaigyi",
    "wof:placetype":"locality"
},
  "geometry": {"coordinates":[96.93735,21.28037],"type":"Point"}
}