{
  "type": "Feature",
  "properties": {
    "gn:admin1_code":"11.0",
    "gn:admin2_code":"MMR015D003",
    "gn:admin3_code":"MMR015014",
    "gn:asciiname":"Nam-kawng-long-lang",
    "gn:country_code":"MM",
    "gn:dem":659,
    "gn:feature_class":"P",
    "gn:feature_code":"PPL",
    "gn:name":"Nam-kawng-long-lang",
    "gn:population":0,
    "gn:timezone":"Asia/Yangon",
    "iso:country":"MM",
    "name:und_x_variant":[
        "Namkonglonglang",
        "Nam-kawng-long-lang"
    ],
    "wof:name":"Nam-kawng-long-lang",
    "wof:placetype":"locality"
},
  "geometry": {"coordinates":[97.72992000000001,22.58583],"type":"Point"}
}