{
  "type": "Feature",
  "properties": {
    "gn:admin1_code":"11.0",
    "gn:admin2_code":"MMR014D001",
    "gn:admin3_code":"MMR014008",
    "gn:asciiname":"Ho-koi",
    "gn:country_code":"MM",
    "gn:dem":654,
    "gn:feature_class":"P",
    "gn:feature_code":"PPL",
    "gn:name":"Ho-koi",
    "gn:population":0,
    "gn:timezone":"Asia/Yangon",
    "iso:country":"MM",
    "wof:name":"Ho-koi",
    "wof:placetype":"locality"
},
  "geometry": {"coordinates":[97.09307,21.63629],"type":"Point"}
}