{
  "type": "Feature",
  "properties": {
    "gn:admin1_code":"3.0",
    "gn:admin2_code":"MMR017D005",
    "gn:admin3_code":"MMR017019",
    "gn:asciiname":"Aukton",
    "gn:country_code":"MM",
    "gn:dem":10,
    "gn:feature_class":"P",
    "gn:feature_code":"PPL",
    "gn:name":"Aukton",
    "gn:population":0,
    "gn:timezone":"Asia/Yangon",
    "iso:country":"MM",
    "wof:name":"Aukton",
    "wof:placetype":"locality"
},
  "geometry": {"coordinates":[95.47611999999999,16.79688],"type":"Point"}
}