{
  "type": "Feature",
  "properties": {
    "gn:admin1_code":"16.0",
    "gn:admin2_code":"MMR007D002",
    "gn:admin3_code":"MMR007011",
    "gn:asciiname":"Maungde",
    "gn:country_code":"MM",
    "gn:dem":251,
    "gn:feature_class":"P",
    "gn:feature_code":"PPL",
    "gn:name":"Maungde",
    "gn:population":0,
    "gn:timezone":"Asia/Yangon",
    "iso:country":"MM",
    "name:und_x_variant":[
        "Myaungdi",
        "Maungde"
    ],
    "wof:name":"Maungde",
    "wof:placetype":"locality"
},
  "geometry": {"coordinates":[96.8553,18.47221],"type":"Point"}
}