{
  "type": "Feature",
  "properties": {
    "gn:admin1_code":"4.0",
    "gn:admin2_code":"MMR001D003",
    "gn:admin3_code":"MMR001012",
    "gn:asciiname":"Man Kwi",
    "gn:country_code":"MM",
    "gn:dem":146,
    "gn:feature_class":"P",
    "gn:feature_code":"PPL",
    "gn:name":"M\u0101n Kwi",
    "gn:population":0,
    "gn:timezone":"Asia/Yangon",
    "iso:country":"MM",
    "wof:name":"Man Kwi",
    "wof:placetype":"locality"
},
  "geometry": {"coordinates":[97.45799,24.73192],"type":"Point"}
}