{
  "type": "Feature",
  "properties": {
    "gn:admin1_code":"15.0",
    "gn:admin2_code":"MMR009D003",
    "gn:admin3_code":"MMR009016",
    "gn:asciiname":"Dandaung",
    "gn:country_code":"MM",
    "gn:dem":111,
    "gn:feature_class":"P",
    "gn:feature_code":"PPL",
    "gn:name":"Dandaung",
    "gn:population":0,
    "gn:timezone":"Asia/Yangon",
    "iso:country":"MM",
    "wof:name":"Dandaung",
    "wof:placetype":"locality"
},
  "geometry": {"coordinates":[95.52668,19.30913],"type":"Point"}
}