{
  "type": "Feature",
  "properties": {
    "gn:admin1_code":"12.0",
    "gn:admin2_code":"MMR006D001",
    "gn:admin3_code":"MMR006002",
    "gn:asciiname":"Kadetngetein",
    "gn:country_code":"MM",
    "gn:dem":29,
    "gn:feature_class":"P",
    "gn:feature_code":"PPL",
    "gn:name":"Kadetngetein",
    "gn:population":0,
    "gn:timezone":"Asia/Yangon",
    "iso:country":"MM",
    "wof:name":"Kadetngetein",
    "wof:placetype":"locality"
},
  "geometry": {"coordinates":[98.13679999999999,13.8904],"type":"Point"}
}