{
  "type": "Feature",
  "properties": {
    "gn:admin1_code":"11.0",
    "gn:admin2_code":"MMR014D001",
    "gn:admin3_code":"MMR014002",
    "gn:asciiname":"Inbawhkon",
    "gn:country_code":"MM",
    "gn:dem":890,
    "gn:feature_class":"P",
    "gn:feature_code":"PPL",
    "gn:name":"Inbawhkon",
    "gn:population":0,
    "gn:timezone":"Asia/Yangon",
    "iso:country":"MM",
    "name:und_x_variant":[
        "Impawkon",
        "Inbawhkon"
    ],
    "wof:name":"Inbawhkon",
    "wof:placetype":"locality"
},
  "geometry": {"coordinates":[96.89594,20.4459],"type":"Point"}
}