{
  "type": "Feature",
  "properties": {
    "gn:admin1_code":"6.0",
    "gn:admin2_code":"MMR002D001",
    "gn:admin3_code":"MMR002001",
    "gn:asciiname":"We-sue-hso",
    "gn:country_code":"MM",
    "gn:dem":815,
    "gn:feature_class":"P",
    "gn:feature_code":"PPL",
    "gn:name":"W\u00e8-s\u00fc-hso",
    "gn:population":0,
    "gn:timezone":"Asia/Yangon",
    "iso:country":"MM",
    "wof:name":"We-sue-hso",
    "wof:placetype":"locality"
},
  "geometry": {"coordinates":[97.32759,19.57693],"type":"Point"}
}