{
  "type": "Feature",
  "properties": {
    "gn:admin1_code":"10.0",
    "gn:asciiname":"Pauk-ainggon",
    "gn:country_code":"MM",
    "gn:dem":74,
    "gn:feature_class":"P",
    "gn:feature_code":"PPL",
    "gn:name":"Pauk-ainggon",
    "gn:population":0,
    "gn:timezone":"Asia/Yangon",
    "iso:country":"MM",
    "wof:name":"Pauk-ainggon",
    "wof:placetype":"locality"
},
  "geometry": {"coordinates":[95.70716,21.89458],"type":"Point"}
}