{
  "type": "Feature",
  "properties": {
    "gn:admin1_code":"10.0",
    "gn:admin2_code":"MMR005D004",
    "gn:admin3_code":"MMR005023",
    "gn:asciiname":"Tonpin",
    "gn:country_code":"MM",
    "gn:dem":149,
    "gn:feature_class":"P",
    "gn:feature_code":"PPL",
    "gn:name":"Tonpin",
    "gn:population":0,
    "gn:timezone":"Asia/Yangon",
    "iso:country":"MM",
    "wof:name":"Tonpin",
    "wof:placetype":"locality"
},
  "geometry": {"coordinates":[95.92285,24.22021],"type":"Point"}
}