{
  "type": "Feature",
  "properties": {
    "gn:admin1_code":"16.0",
    "gn:admin2_code":"MMR007D002",
    "gn:admin3_code":"MMR007014",
    "gn:asciiname":"Ponye-in",
    "gn:country_code":"MM",
    "gn:dem":39,
    "gn:feature_class":"P",
    "gn:feature_code":"PPL",
    "gn:name":"Ponye-in",
    "gn:population":0,
    "gn:timezone":"Asia/Yangon",
    "iso:country":"MM",
    "name:und_x_variant":[
        "P\u00f4n-y\u00e8-in-ywa",
        "Ponye-in"
    ],
    "wof:name":"Ponye-in",
    "wof:placetype":"locality"
},
  "geometry": {"coordinates":[96.4932,18.75038],"type":"Point"}
}