{
  "type": "Feature",
  "properties": {
    "gn:admin1_code":"11.0",
    "gn:admin2_code":"MMR015D003",
    "gn:admin3_code":"MMR015012",
    "gn:asciiname":"Kawnhsilam",
    "gn:country_code":"MM",
    "gn:dem":1409,
    "gn:feature_class":"P",
    "gn:feature_code":"PPL",
    "gn:name":"Kawnhsil\u00e1m",
    "gn:population":0,
    "gn:timezone":"Asia/Yangon",
    "iso:country":"MM",
    "wof:name":"Kawnhsilam",
    "wof:placetype":"locality"
},
  "geometry": {"coordinates":[96.89427000000001,22.8519],"type":"Point"}
}