{
  "type": "Feature",
  "properties": {
    "gn:admin1_code":"11.0",
    "gn:admin2_code":"MMR016D002",
    "gn:admin3_code":"MMR016006",
    "gn:asciiname":"Wan Hsin-om",
    "gn:cc2":"MM",
    "gn:country_code":"MM",
    "gn:dem":1312,
    "gn:feature_class":"P",
    "gn:feature_code":"PPL",
    "gn:name":"W\u0101n Hsin-om",
    "gn:population":0,
    "gn:timezone":"Asia/Yangon",
    "iso:country":"MM",
    "name:und_x_variant":[
        "Hsin-om",
        "W\u0101n Hsin-om"
    ],
    "wof:name":"Wan Hsin-om",
    "wof:placetype":"locality"
},
  "geometry": {"coordinates":[99.28639,20.71556],"type":"Point"}
}