{
  "type": "Feature",
  "properties": {
    "gn:admin1_code":"11.0",
    "gn:admin2_code":"MMR015D001",
    "gn:admin3_code":"MMR015020",
    "gn:asciiname":"Ma Lengkoe-sai",
    "gn:country_code":"MM",
    "gn:dem":1199,
    "gn:feature_class":"P",
    "gn:feature_code":"PPL",
    "gn:name":"M\u0101 Lengk\u00f6-sai",
    "gn:population":0,
    "gn:timezone":"Asia/Yangon",
    "iso:country":"MM",
    "name:und_x_variant":[
        "M\u0101n Lengk\u00f6",
        "M\u0101 Lengk\u00f6-sai"
    ],
    "wof:name":"Ma Lengkoe-sai",
    "wof:placetype":"locality"
},
  "geometry": {"coordinates":[98.62805,23.59655],"type":"Point"}
}