{
  "type": "Feature",
  "properties": {
    "gn:admin1_code":"10.0",
    "gn:admin2_code":"MMR005D002",
    "gn:admin3_code":"MMR005011",
    "gn:asciiname":"Shwegu",
    "gn:country_code":"MM",
    "gn:dem":145,
    "gn:feature_class":"P",
    "gn:feature_code":"PPL",
    "gn:name":"Shwegu",
    "gn:population":0,
    "gn:timezone":"Asia/Yangon",
    "iso:country":"MM",
    "name:mya_x_preferred":[
        "\u101b\u103d\u103e\u1031\u1000\u1030\u1019\u103c\u102d\u102f\u1037"
    ],
    "name:shn_x_preferred":[
        "\u1081\u1030\u107a\u103a\u1088\u1075\u1030\u1088\u104a \u101d\u1035\u1004\u103a\u1038"
    ],
    "wof:name":"Shwegu",
    "wof:placetype":"locality"
},
  "geometry": {"coordinates":[95.27670000000001,22.87368],"type":"Point"}
}