{
  "type": "Feature",
  "properties": {
    "gn:admin1_code":"17.0",
    "gn:admin2_code":"MMR013D003",
    "gn:admin3_code":"MMR013025",
    "gn:asciiname":"Swedawgyaung",
    "gn:country_code":"MM",
    "gn:dem":9,
    "gn:feature_class":"P",
    "gn:feature_code":"PPL",
    "gn:name":"Swedawgyaung",
    "gn:population":0,
    "gn:timezone":"Asia/Yangon",
    "iso:country":"MM",
    "name:und_x_variant":[
        "Shwedawgyaung",
        "Swedawgyaung"
    ],
    "wof:name":"Swedawgyaung",
    "wof:placetype":"locality"
},
  "geometry": {"coordinates":[96.71905,16.78944],"type":"Point"}
}