{
  "type": "Feature",
  "properties": {
    "gn:admin1_code":"2.0",
    "gn:admin2_code":"MMR004D003",
    "gn:admin3_code":"MMR004003",
    "gn:asciiname":"Zephai",
    "gn:country_code":"MM",
    "gn:dem":1616,
    "gn:feature_class":"P",
    "gn:feature_code":"PPL",
    "gn:name":"Zephai",
    "gn:population":0,
    "gn:timezone":"Asia/Yangon",
    "iso:country":"MM",
    "wof:name":"Zephai",
    "wof:placetype":"locality"
},
  "geometry": {"coordinates":[93.26667,22.45],"type":"Point"}
}