{
  "type": "Feature",
  "properties": {
    "gn:admin1_code":"8.0",
    "gn:admin2_code":"MMR010D006",
    "gn:admin3_code":"MMR010024",
    "gn:asciiname":"Taunggwa",
    "gn:country_code":"MM",
    "gn:dem":240,
    "gn:feature_class":"P",
    "gn:feature_code":"PPL",
    "gn:name":"Taunggwa",
    "gn:population":0,
    "gn:timezone":"Asia/Yangon",
    "iso:country":"MM",
    "wof:name":"Taunggwa",
    "wof:placetype":"locality"
},
  "geometry": {"coordinates":[96.23157999999999,20.69084],"type":"Point"}
}