{
  "type": "Feature",
  "properties": {
    "gn:admin1_code":"15.0",
    "gn:admin2_code":"MMR009D002",
    "gn:admin3_code":"MMR009007",
    "gn:asciiname":"Tanaungdaw",
    "gn:country_code":"MM",
    "gn:dem":57,
    "gn:feature_class":"P",
    "gn:feature_code":"PPL",
    "gn:name":"Tanaungdaw",
    "gn:population":0,
    "gn:timezone":"Asia/Yangon",
    "iso:country":"MM",
    "wof:name":"Tanaungdaw",
    "wof:placetype":"locality"
},
  "geometry": {"coordinates":[94.76053,20.25833],"type":"Point"}
}