{
  "type": "Feature",
  "properties": {
    "gn:admin1_code":"2.0",
    "gn:admin2_code":"MMR004D002",
    "gn:admin3_code":"MMR004009",
    "gn:asciiname":"Turawine",
    "gn:country_code":"MM",
    "gn:dem":55,
    "gn:feature_class":"P",
    "gn:feature_code":"PPL",
    "gn:name":"Turawine",
    "gn:population":0,
    "gn:timezone":"Asia/Yangon",
    "iso:country":"MM",
    "wof:name":"Turawine",
    "wof:placetype":"locality"
},
  "geometry": {"coordinates":[92.74965,21.7005],"type":"Point"}
}