{
  "type": "Feature",
  "properties": {
    "gn:admin1_code":"11.0",
    "gn:admin2_code":"MMR015D001",
    "gn:admin3_code":"MMR015004",
    "gn:asciiname":"Ho-na",
    "gn:country_code":"MM",
    "gn:dem":945,
    "gn:feature_class":"P",
    "gn:feature_code":"PPL",
    "gn:name":"Ho-na",
    "gn:population":0,
    "gn:timezone":"Asia/Yangon",
    "iso:country":"MM",
    "wof:name":"Ho-na",
    "wof:placetype":"locality"
},
  "geometry": {"coordinates":[98.22889000000001,22.48985],"type":"Point"}
}