{
  "type": "Feature",
  "properties": {
    "gn:admin1_code":"2.0",
    "gn:admin2_code":"MMR004D002",
    "gn:admin3_code":"MMR004006",
    "gn:asciiname":"Di",
    "gn:country_code":"MM",
    "gn:dem":1328,
    "gn:feature_class":"P",
    "gn:feature_code":"PPL",
    "gn:name":"Di",
    "gn:population":0,
    "gn:timezone":"Asia/Yangon",
    "iso:country":"MM",
    "name:hye_x_preferred":[
        "\u0534\u056b"
    ],
    "name:ukr_x_preferred":[
        "\u0414\u0456"
    ],
    "wof:name":"Di",
    "wof:placetype":"locality"
},
  "geometry": {"coordinates":[93.96666999999999,21.33333],"type":"Point"}
}