{
  "type": "Feature",
  "properties": {
    "gn:admin1_code":"10.0",
    "gn:admin2_code":"MMR005D001",
    "gn:admin3_code":"MMR005002",
    "gn:asciiname":"Wunbye",
    "gn:country_code":"MM",
    "gn:dem":76,
    "gn:feature_class":"P",
    "gn:feature_code":"PPL",
    "gn:name":"Wunbye",
    "gn:population":0,
    "gn:timezone":"Asia/Yangon",
    "iso:country":"MM",
    "wof:name":"Wunbye",
    "wof:placetype":"locality"
},
  "geometry": {"coordinates":[95.54671999999999,21.93805],"type":"Point"}
}