{
  "type": "Feature",
  "properties": {
    "gn:admin1_code":"16.0",
    "gn:admin2_code":"MMR007D002",
    "gn:admin3_code":"MMR007012",
    "gn:asciiname":"Minganyo",
    "gn:country_code":"MM",
    "gn:dem":55,
    "gn:feature_class":"P",
    "gn:feature_code":"PPL",
    "gn:name":"Minganyo",
    "gn:population":0,
    "gn:timezone":"Asia/Yangon",
    "iso:country":"MM",
    "name:und_x_variant":[
        "Karen",
        "Mikanya-anauk",
        "Minganyo"
    ],
    "wof:name":"Minganyo",
    "wof:placetype":"locality"
},
  "geometry": {"coordinates":[96.40188000000001,18.49968],"type":"Point"}
}