{
  "type": "Feature",
  "properties": {
    "gn:admin1_code":"12.0",
    "gn:admin2_code":"MMR006D001",
    "gn:admin3_code":"MMR006004",
    "gn:asciiname":"Hpaungdaung",
    "gn:country_code":"MM",
    "gn:dem":15,
    "gn:feature_class":"P",
    "gn:feature_code":"PPL",
    "gn:name":"Hpaungdaung",
    "gn:population":0,
    "gn:timezone":"Asia/Yangon",
    "iso:country":"MM",
    "name:und_x_variant":[
        "Hpaungtaung",
        "Hpaungtaung Ywa",
        "Hpaungdaung"
    ],
    "wof:name":"Hpaungdaung",
    "wof:placetype":"locality"
},
  "geometry": {"coordinates":[97.92028000000001,14.56949],"type":"Point"}
}