{
  "type": "Feature",
  "properties": {
    "gn:admin1_code":"3.0",
    "gn:admin2_code":"MMR017D001",
    "gn:admin3_code":"MMR017004",
    "gn:asciiname":"Khalukala",
    "gn:country_code":"MM",
    "gn:dem":6,
    "gn:feature_class":"P",
    "gn:feature_code":"PPL",
    "gn:name":"Khalukala",
    "gn:population":0,
    "gn:timezone":"Asia/Yangon",
    "iso:country":"MM",
    "wof:name":"Khalukala",
    "wof:placetype":"locality"
},
  "geometry": {"coordinates":[94.40000000000001,15.95],"type":"Point"}
}