{
  "type": "Feature",
  "properties": {
    "iso:country":"MM",
    "name:eng_x_preferred":[
        "Thongwa Township"
    ],
    "name:jpn_x_preferred":[
        "\u30c8\u30f3\u30b0\u30ef\u90e1\u533a"
    ],
    "name:mya_x_preferred":[
        "\u101e\u102f\u1036\u1038\u1001\u103d\u1019\u103c\u102d\u102f\u1037"
    ],
    "name:shn_x_preferred":[
        "\u1010\u1030\u1004\u103a\u1038\u1076\u1082\u1083\u1089\u104a \u1078\u1084\u1088\u101d\u1035\u1004\u103a\u1038"
    ],
    "name:und_x_variant":[
        "Thon-Khwa"
    ],
    "name:zho_x_preferred":[
        "\u5b8b\u5272\u93ae"
    ],
    "ne:ADM0CAP":0.0,
    "ne:ADM0NAME":"Myanmar",
    "ne:ADM0_A3":"MMR",
    "ne:ADM1NAME":"Yangon",
    "ne:ADMIN1_COD":17,
    "ne:CAPALT":0,
    "ne:CHANGED":4,
    "ne:CHECKME":0,
    "ne:COMPARE":0,
    "ne:DIFFASCII":0,
    "ne:DIFFNOTE":"Changed scale rank.",
    "ne:ELEVATION":0.0,
    "ne:FEATURECLA":"Populated place",
    "ne:FEATURE_CL":"P",
    "ne:FEATURE_CO":"PPL",
    "ne:GEONAMEID":1291193,
    "ne:GEONAMESNO":"Geonames ascii name + lat.d + long.d matching.",
    "ne:GN_ASCII":"Thongwa",
    "ne:GN_POP":52496,
    "ne:GTOPO30":5.0,
    "ne:ISO_A2":"MM",
    "ne:LABELRANK":5,
    "ne:LATITUDE":16.7547,
    "ne:LONGITUDE":96.519318,
    "ne:LS_MATCH":1,
    "ne:LS_NAME":"Thongwa",
    "ne:MAX_AREAKM":3.0,
    "ne:MAX_AREAMI":1.0,
    "ne:MAX_BBXMAX":96.533333,
    "ne:MAX_BBXMIN":96.516667,
    "ne:MAX_BBYMAX":16.766667,
    "ne:MAX_BBYMIN":16.75,
    "ne:MAX_NATSCA":10.0,
    "ne:MAX_PERKM":7.0,
    "ne:MAX_PERMI":5.0,
    "ne:MAX_POP10":19489,
    "ne:MAX_POP20":0,
    "ne:MAX_POP300":0,
    "ne:MAX_POP310":0,
    "ne:MAX_POP50":0,
    "ne:MEAN_BBXC":96.525,
    "ne:MEAN_BBYC":16.758333,
    "ne:MEGACITY":0,
    "ne:MIN_AREAKM":3.0,
    "ne:MIN_AREAMI":1.0,
    "ne:MIN_BBXMAX":96.533333,
    "ne:MIN_BBXMIN":96.516667,
    "ne:MIN_BBYMAX":16.766667,
    "ne:MIN_BBYMIN":16.75,
    "ne:MIN_PERKM":7.0,
    "ne:MIN_PERMI":5.0,
    "ne:NAME":"Thongwa",
    "ne:NAMEASCII":"Thongwa",
    "ne:NAMEDIFF":0,
    "ne:NATSCALE":20,
    "ne:POP1950":0,
    "ne:POP1955":0,
    "ne:POP1960":0,
    "ne:POP1965":0,
    "ne:POP1970":0,
    "ne:POP1975":0,
    "ne:POP1980":0,
    "ne:POP1985":0,
    "ne:POP1990":0,
    "ne:POP1995":0,
    "ne:POP2000":0,
    "ne:POP2005":0,
    "ne:POP2010":0,
    "ne:POP2015":0,
    "ne:POP2020":0,
    "ne:POP2025":0,
    "ne:POP2050":0,
    "ne:POP_MAX":52496,
    "ne:POP_MIN":19489,
    "ne:POP_OTHER":19489,
    "ne:RANK_MAX":8,
    "ne:RANK_MIN":6,
    "ne:SCALERANK":7,
    "ne:SOV0NAME":"Myanmar",
    "ne:SOV_A3":"MMR",
    "ne:TIMEZONE":"Asia/Rangoon",
    "ne:UN_FID":0,
    "ne:UN_LAT":0.0,
    "ne:UN_LONG":0.0,
    "ne:WORLDCITY":0,
    "qs:gn_country":"MM",
    "qs:gn_fcode":"PPL",
    "qs:gn_pop":52496,
    "qs:name":"Thongwa",
    "qs:name_adm0":"Myanmar",
    "qs:name_adm1":"Yangon",
    "qs:photos":0,
    "qs:photos_1k":0,
    "qs:photos_9k":0,
    "qs:photos_9r":0,
    "qs:photos_all":0,
    "qs:photos_sr":0,
    "qs:placetype":"Town",
    "qs:pop_sr":"8",
    "qs:woe_adm0":23424763,
    "wd:wordcount":44,
    "wof:name":"Thongwa",
    "wof:placetype":"locality",
    "wof:population":52496
},
  "geometry": {"coordinates":[96.52498,16.75998],"type":"Point"}
}