{
  "type": "Feature",
  "properties": {
    "gn:admin1_code":"10.0",
    "gn:admin2_code":"MMR005D003",
    "gn:admin3_code":"MMR005012",
    "gn:asciiname":"Gyogyagan",
    "gn:country_code":"MM",
    "gn:dem":117,
    "gn:feature_class":"P",
    "gn:feature_code":"PPL",
    "gn:name":"Gyogyagan",
    "gn:population":0,
    "gn:timezone":"Asia/Yangon",
    "iso:country":"MM",
    "wof:name":"Gyogyagan",
    "wof:placetype":"locality"
},
  "geometry": {"coordinates":[95.17827,22.25317],"type":"Point"}
}