{
  "type": "Feature",
  "properties": {
    "gn:admin1_code":"15.0",
    "gn:admin2_code":"MMR009D003",
    "gn:admin3_code":"MMR009013",
    "gn:asciiname":"Kyaukletkhat",
    "gn:country_code":"MM",
    "gn:dem":106,
    "gn:feature_class":"P",
    "gn:feature_code":"PPL",
    "gn:name":"Kyaukletkhat",
    "gn:population":0,
    "gn:timezone":"Asia/Yangon",
    "iso:country":"MM",
    "wof:name":"Kyaukletkhat",
    "wof:placetype":"locality"
},
  "geometry": {"coordinates":[95.02898999999999,19.65092000000001],"type":"Point"}
}