{
  "type": "Feature",
  "properties": {
    "gn:admin1_code":"15.0",
    "gn:admin2_code":"MMR009D003",
    "gn:admin3_code":"MMR009015",
    "gn:asciiname":"Gyobin",
    "gn:country_code":"MM",
    "gn:dem":71,
    "gn:feature_class":"P",
    "gn:feature_code":"PPL",
    "gn:name":"Gyobin",
    "gn:population":0,
    "gn:timezone":"Asia/Yangon",
    "iso:country":"MM",
    "wof:name":"Gyobin",
    "wof:placetype":"locality"
},
  "geometry": {"coordinates":[94.89960000000001,19.04085],"type":"Point"}
}