{
  "type": "Feature",
  "properties": {
    "gn:admin1_code":"11.0",
    "gn:admin2_code":"MMR014D001",
    "gn:admin3_code":"MMR014005",
    "gn:asciiname":"Natsegan",
    "gn:country_code":"MM",
    "gn:dem":1385,
    "gn:feature_class":"P",
    "gn:feature_code":"PPL",
    "gn:name":"Natsegan",
    "gn:population":0,
    "gn:timezone":"Asia/Yangon",
    "iso:country":"MM",
    "wof:name":"Natsegan",
    "wof:placetype":"locality"
},
  "geometry": {"coordinates":[96.58396999999999,20.68699],"type":"Point"}
}