{
  "type": "Feature",
  "properties": {
    "gn:admin1_code":"3.0",
    "gn:admin2_code":"MMR017D004",
    "gn:admin3_code":"MMR017016",
    "gn:asciiname":"Sagyet",
    "gn:country_code":"MM",
    "gn:dem":16,
    "gn:feature_class":"P",
    "gn:feature_code":"PPL",
    "gn:name":"S\u0101gyet",
    "gn:population":0,
    "gn:timezone":"Asia/Yangon",
    "iso:country":"MM",
    "wof:name":"Sagyet",
    "wof:placetype":"locality"
},
  "geometry": {"coordinates":[94.88242,15.98588],"type":"Point"}
}