{
  "type": "Feature",
  "properties": {
    "gn:admin1_code":"11.0",
    "gn:admin2_code":"MMR015D005",
    "gn:admin3_code":"MMR015022",
    "gn:asciiname":"Wan Chao-yangchai",
    "gn:country_code":"MM",
    "gn:dem":1543,
    "gn:feature_class":"P",
    "gn:feature_code":"PPL",
    "gn:name":"W\u0101n Chao-yangchai",
    "gn:population":0,
    "gn:timezone":"Asia/Yangon",
    "iso:country":"MM",
    "wof:name":"Wan Chao-yangchai",
    "wof:placetype":"locality"
},
  "geometry": {"coordinates":[98.62629,23.7396],"type":"Point"}
}