{
  "type": "Feature",
  "properties": {
    "gn:admin1_code":"5.0",
    "gn:admin2_code":"MMR003D002",
    "gn:admin3_code":"MMR003005",
    "gn:asciiname":"Powepaw",
    "gn:country_code":"MM",
    "gn:dem":255,
    "gn:feature_class":"P",
    "gn:feature_code":"PPL",
    "gn:name":"Powepaw",
    "gn:population":0,
    "gn:timezone":"Asia/Yangon",
    "iso:country":"MM",
    "wof:name":"Powepaw",
    "wof:placetype":"locality"
},
  "geometry": {"coordinates":[98.28919999999999,16.95141],"type":"Point"}
}