{
  "type": "Feature",
  "properties": {
    "gn:admin1_code":"11.0",
    "gn:admin2_code":"MMR015D003",
    "gn:admin3_code":"MMR015015",
    "gn:asciiname":"Lukleh",
    "gn:country_code":"MM",
    "gn:dem":625,
    "gn:feature_class":"P",
    "gn:feature_code":"PPL",
    "gn:name":"Lukleh",
    "gn:population":0,
    "gn:timezone":"Asia/Yangon",
    "iso:country":"MM",
    "wof:name":"Lukleh",
    "wof:placetype":"locality"
},
  "geometry": {"coordinates":[97.50691,22.9533],"type":"Point"}
}