{
  "type": "Feature",
  "properties": {
    "gn:admin1_code":"10.0",
    "gn:admin2_code":"MMR005D004",
    "gn:admin3_code":"MMR005026",
    "gn:asciiname":"Katpanbok",
    "gn:country_code":"MM",
    "gn:dem":276,
    "gn:feature_class":"P",
    "gn:feature_code":"PPL",
    "gn:name":"Katpanbok",
    "gn:population":0,
    "gn:timezone":"Asia/Yangon",
    "iso:country":"MM",
    "wof:name":"Katpanbok",
    "wof:placetype":"locality"
},
  "geometry": {"coordinates":[95.41709,24.08391],"type":"Point"}
}