{
  "type": "Feature",
  "properties": {
    "gn:admin1_code":"15.0",
    "gn:admin2_code":"MMR009D004",
    "gn:admin3_code":"MMR009021",
    "gn:asciiname":"Kyaunggon",
    "gn:country_code":"MM",
    "gn:dem":125,
    "gn:feature_class":"P",
    "gn:feature_code":"PPL",
    "gn:name":"Kyaunggon",
    "gn:population":0,
    "gn:timezone":"Asia/Yangon",
    "iso:country":"MM",
    "wof:name":"Kyaunggon",
    "wof:placetype":"locality"
},
  "geometry": {"coordinates":[94.66686,21.3056],"type":"Point"}
}