{
  "type": "Feature",
  "properties": {
    "gn:admin1_code":"3.0",
    "gn:admin2_code":"MMR017D001",
    "gn:admin3_code":"MMR017006",
    "gn:asciiname":"Shwelaunggyin",
    "gn:country_code":"MM",
    "gn:dem":26,
    "gn:feature_class":"P",
    "gn:feature_code":"PPL",
    "gn:name":"Shwelaunggyin",
    "gn:population":0,
    "gn:timezone":"Asia/Yangon",
    "iso:country":"MM",
    "wof:name":"Shwelaunggyin",
    "wof:placetype":"locality"
},
  "geometry": {"coordinates":[94.95671,17.55643],"type":"Point"}
}