{
  "type": "Feature",
  "properties": {
    "gn:admin1_code":"8.0",
    "gn:admin2_code":"MMR010D004",
    "gn:admin3_code":"MMR010017",
    "gn:asciiname":"Kada",
    "gn:country_code":"MM",
    "gn:dem":69,
    "gn:feature_class":"P",
    "gn:feature_code":"PPL",
    "gn:name":"Kada",
    "gn:population":0,
    "gn:timezone":"Asia/Yangon",
    "iso:country":"MM",
    "name:ceb_x_preferred":[
        "Kada"
    ],
    "name:deu_x_preferred":[
        "Kada"
    ],
    "name:est_x_preferred":[
        "Kada"
    ],
    "name:fra_x_preferred":[
        "Kada"
    ],
    "name:rus_x_preferred":[
        "\u041a\u0430\u0434\u0430"
    ],
    "name:swe_x_preferred":[
        "Kada"
    ],
    "wof:name":"Kada",
    "wof:placetype":"locality"
},
  "geometry": {"coordinates":[95.37895,21.67],"type":"Point"}
}