{
  "type": "Feature",
  "properties": {
    "gn:admin1_code":"11.0",
    "gn:admin2_code":"MMR015D003",
    "gn:admin3_code":"MMR015014",
    "gn:asciiname":"Ta-ting-ang",
    "gn:country_code":"MM",
    "gn:dem":393,
    "gn:feature_class":"P",
    "gn:feature_code":"PPL",
    "gn:name":"Ta-ting-ang",
    "gn:population":0,
    "gn:timezone":"Asia/Yangon",
    "iso:country":"MM",
    "wof:name":"Ta-ting-ang",
    "wof:placetype":"locality"
},
  "geometry": {"coordinates":[97.34605000000001,22.29061],"type":"Point"}
}