{
  "type": "Feature",
  "properties": {
    "gn:admin1_code":"1.0",
    "gn:admin2_code":"MMR012D004",
    "gn:admin3_code":"MMR012016",
    "gn:asciiname":"Paraba",
    "gn:country_code":"MM",
    "gn:dem":25,
    "gn:feature_class":"P",
    "gn:feature_code":"PPL",
    "gn:name":"Paraba",
    "gn:population":0,
    "gn:timezone":"Asia/Yangon",
    "iso:country":"MM",
    "wof:name":"Paraba",
    "wof:placetype":"locality"
},
  "geometry": {"coordinates":[94.21372,19.19452],"type":"Point"}
}