{
  "type": "Feature",
  "properties": {
    "gn:admin1_code":"3.0",
    "gn:admin2_code":"MMR017D004",
    "gn:admin3_code":"MMR017016",
    "gn:asciiname":"Padaukkon",
    "gn:country_code":"MM",
    "gn:dem":10,
    "gn:feature_class":"P",
    "gn:feature_code":"PPL",
    "gn:name":"Padaukk\u00f4n",
    "gn:population":0,
    "gn:timezone":"Asia/Yangon",
    "iso:country":"MM",
    "name:und_x_variant":[
        "Badaukkon",
        "Padaukk\u00f4n"
    ],
    "wof:name":"Padaukkon",
    "wof:placetype":"locality"
},
  "geometry": {"coordinates":[94.70694,15.87299],"type":"Point"}
}