{
  "type": "Feature",
  "properties": {
    "gn:admin1_code":"15.0",
    "gn:admin2_code":"MMR009D003",
    "gn:admin3_code":"MMR009013",
    "gn:asciiname":"Myinsaing-ywathit",
    "gn:country_code":"MM",
    "gn:dem":259,
    "gn:feature_class":"P",
    "gn:feature_code":"PPL",
    "gn:name":"Myinsaing-ywathit",
    "gn:population":0,
    "gn:timezone":"Asia/Yangon",
    "iso:country":"MM",
    "name:und_x_variant":[
        "Myinzaing Ywathit",
        "Myinsaing-ywathit"
    ],
    "wof:name":"Myinsaing-ywathit",
    "wof:placetype":"locality"
},
  "geometry": {"coordinates":[94.81382000000001,19.8169],"type":"Point"}
}