{
  "type": "Feature",
  "properties": {
    "gn:admin1_code":"11.0",
    "gn:admin2_code":"MMR015D006",
    "gn:admin3_code":"MMR015021",
    "gn:asciiname":"Kawng Ri-ti",
    "gn:country_code":"MM",
    "gn:dem":966,
    "gn:feature_class":"P",
    "gn:feature_code":"PPL",
    "gn:name":"Kawng Ri-ti",
    "gn:population":0,
    "gn:timezone":"Asia/Yangon",
    "iso:country":"MM",
    "wof:name":"Kawng Ri-ti",
    "wof:placetype":"locality"
},
  "geometry": {"coordinates":[98.73819,23.23293],"type":"Point"}
}