{
  "type": "Feature",
  "properties": {
    "gn:admin1_code":"5.0",
    "gn:admin2_code":"MMR003D001",
    "gn:admin3_code":"MMR003002",
    "gn:asciiname":"Tak-re-khi",
    "gn:country_code":"MM",
    "gn:dem":698,
    "gn:feature_class":"P",
    "gn:feature_code":"PPL",
    "gn:name":"Tak-re-khi",
    "gn:population":0,
    "gn:timezone":"Asia/Yangon",
    "iso:country":"MM",
    "wof:name":"Tak-re-khi",
    "wof:placetype":"locality"
},
  "geometry": {"coordinates":[97.99930999999999,17.38071],"type":"Point"}
}