{
  "type": "Feature",
  "properties": {
    "gn:admin1_code":"10.0",
    "gn:admin2_code":"MMR005D004",
    "gn:admin3_code":"MMR005026",
    "gn:asciiname":"Kyudaw-gaing",
    "gn:country_code":"MM",
    "gn:dem":296,
    "gn:feature_class":"P",
    "gn:feature_code":"PPL",
    "gn:name":"Kyudaw-gaing",
    "gn:population":0,
    "gn:timezone":"Asia/Yangon",
    "iso:country":"MM",
    "name:und_x_variant":[
        "Kyudaw-aing",
        "Kyudaw-gaing"
    ],
    "wof:name":"Kyudaw-gaing",
    "wof:placetype":"locality"
},
  "geometry": {"coordinates":[95.4704,23.94021],"type":"Point"}
}