{
  "type": "Feature",
  "properties": {
    "gn:admin1_code":"3.0",
    "gn:admin2_code":"MMR017D002",
    "gn:admin3_code":"MMR017010",
    "gn:asciiname":"Zinbyungon",
    "gn:country_code":"MM",
    "gn:dem":11,
    "gn:feature_class":"P",
    "gn:feature_code":"PPL",
    "gn:name":"Zinbyungon",
    "gn:population":0,
    "gn:timezone":"Asia/Yangon",
    "iso:country":"MM",
    "wof:name":"Zinbyungon",
    "wof:placetype":"locality"
},
  "geometry": {"coordinates":[95.13388999999999,17.50494],"type":"Point"}
}