{
  "type": "Feature",
  "properties": {
    "gn:admin1_code":"3.0",
    "gn:admin2_code":"MMR017D006",
    "gn:admin3_code":"MMR017025",
    "gn:asciiname":"Kywegyaung",
    "gn:country_code":"MM",
    "gn:dem":8,
    "gn:feature_class":"P",
    "gn:feature_code":"PPL",
    "gn:name":"Kyw\u0113gyaung",
    "gn:population":0,
    "gn:timezone":"Asia/Yangon",
    "iso:country":"MM",
    "wof:name":"Kywegyaung",
    "wof:placetype":"locality"
},
  "geometry": {"coordinates":[95.62206999999999,16.45814],"type":"Point"}
}