{
  "type": "Feature",
  "properties": {
    "gn:admin1_code":"4.0",
    "gn:admin2_code":"MMR001D004",
    "gn:admin3_code":"MMR001018",
    "gn:asciiname":"Hkinsarhpa",
    "gn:country_code":"MM",
    "gn:dem":1585,
    "gn:feature_class":"P",
    "gn:feature_code":"PPL",
    "gn:name":"Hkinsarhpa",
    "gn:population":0,
    "gn:timezone":"Asia/Yangon",
    "iso:country":"MM",
    "wof:name":"Hkinsarhpa",
    "wof:placetype":"locality"
},
  "geometry": {"coordinates":[98.49438000000001,26.85193],"type":"Point"}
}