{
  "type": "Feature",
  "properties": {
    "gn:admin1_code":"11.0",
    "gn:admin2_code":"MMR015D001",
    "gn:admin3_code":"MMR015004",
    "gn:asciiname":"Man Hwe-keng",
    "gn:country_code":"MM",
    "gn:dem":1150,
    "gn:feature_class":"P",
    "gn:feature_code":"PPL",
    "gn:name":"M\u0101n Hwe-keng",
    "gn:population":0,
    "gn:timezone":"Asia/Yangon",
    "iso:country":"MM",
    "wof:name":"Man Hwe-keng",
    "wof:placetype":"locality"
},
  "geometry": {"coordinates":[98.50936,22.55253],"type":"Point"}
}