{
  "type": "Feature",
  "properties": {
    "gn:admin1_code":"1.0",
    "gn:admin2_code":"MMR012D002",
    "gn:admin3_code":"MMR012009",
    "gn:asciiname":"Nanthadaung",
    "gn:country_code":"MM",
    "gn:dem":-3,
    "gn:feature_class":"P",
    "gn:feature_code":"PPL",
    "gn:name":"Nanthadaung",
    "gn:population":0,
    "gn:timezone":"Asia/Yangon",
    "iso:country":"MM",
    "wof:name":"Nanthadaung",
    "wof:placetype":"locality"
},
  "geometry": {"coordinates":[92.24368,21.1533],"type":"Point"}
}