{
  "type": "Feature",
  "properties": {
    "gn:admin1_code":"15.0",
    "gn:admin2_code":"MMR009D002",
    "gn:admin3_code":"MMR009011",
    "gn:asciiname":"Gebyit",
    "gn:country_code":"MM",
    "gn:dem":96,
    "gn:feature_class":"P",
    "gn:feature_code":"PPL",
    "gn:name":"G\u00e8byit",
    "gn:population":0,
    "gn:timezone":"Asia/Yangon",
    "iso:country":"MM",
    "wof:name":"Gebyit",
    "wof:placetype":"locality"
},
  "geometry": {"coordinates":[94.35894999999999,20.35028],"type":"Point"}
}