{
  "type": "Feature",
  "properties": {
    "gn:admin1_code":"1.0",
    "gn:admin2_code":"MMR012D005",
    "gn:admin3_code":"MMR012006",
    "gn:asciiname":"Htonggyi",
    "gn:country_code":"MM",
    "gn:dem":17,
    "gn:feature_class":"P",
    "gn:feature_code":"PPL",
    "gn:name":"Htonggyi",
    "gn:population":0,
    "gn:timezone":"Asia/Yangon",
    "iso:country":"MM",
    "wof:name":"Htonggyi",
    "wof:placetype":"locality"
},
  "geometry": {"coordinates":[93.57492000000001,19.71464],"type":"Point"}
}