{
  "type": "Feature",
  "properties": {
    "gn:admin1_code":"11.0",
    "gn:admin2_code":"MMR015D006",
    "gn:admin3_code":"MMR015007",
    "gn:asciiname":"Kanamon",
    "gn:country_code":"MM",
    "gn:dem":953,
    "gn:feature_class":"P",
    "gn:feature_code":"PPL",
    "gn:name":"Kanamon",
    "gn:population":0,
    "gn:timezone":"Asia/Yangon",
    "iso:country":"MM",
    "wof:name":"Kanamon",
    "wof:placetype":"locality"
},
  "geometry": {"coordinates":[99.09999999999999,22.85],"type":"Point"}
}