{
  "type": "Feature",
  "properties": {
    "gn:admin1_code":"11.0",
    "gn:admin2_code":"MMR014D002",
    "gn:admin3_code":"MMR014012",
    "gn:asciiname":"Nawnghkai",
    "gn:country_code":"MM",
    "gn:dem":940,
    "gn:feature_class":"P",
    "gn:feature_code":"PPL",
    "gn:name":"Nawnghkai",
    "gn:population":0,
    "gn:timezone":"Asia/Yangon",
    "iso:country":"MM",
    "wof:name":"Nawnghkai",
    "wof:placetype":"locality"
},
  "geometry": {"coordinates":[98.06645,21.24795],"type":"Point"}
}