{
  "type": "Feature",
  "properties": {
    "gn:admin1_code":"10.0",
    "gn:admin2_code":"MMR005D003",
    "gn:admin3_code":"MMR005012",
    "gn:asciiname":"Lezin",
    "gn:country_code":"MM",
    "gn:dem":84,
    "gn:feature_class":"P",
    "gn:feature_code":"PPL",
    "gn:name":"L\u00e8zin",
    "gn:population":0,
    "gn:timezone":"Asia/Yangon",
    "iso:country":"MM",
    "wof:name":"Lezin",
    "wof:placetype":"locality"
},
  "geometry": {"coordinates":[95.18819000000001,22.08922],"type":"Point"}
}