{
  "type": "Feature",
  "properties": {
    "gn:admin1_code":"4.0",
    "gn:admin2_code":"MMR001D004",
    "gn:admin3_code":"MMR001014",
    "gn:asciiname":"Matayang",
    "gn:country_code":"MM",
    "gn:dem":359,
    "gn:feature_class":"P",
    "gn:feature_code":"PPL",
    "gn:name":"Matayang",
    "gn:population":0,
    "gn:timezone":"Asia/Yangon",
    "iso:country":"MM",
    "wof:name":"Matayang",
    "wof:placetype":"locality"
},
  "geometry": {"coordinates":[97.66667,26.91667],"type":"Point"}
}