{
  "type": "Feature",
  "properties": {
    "gn:admin1_code":"12.0",
    "gn:admin2_code":"MMR006D002",
    "gn:admin3_code":"MMR006005",
    "gn:asciiname":"Salin",
    "gn:country_code":"MM",
    "gn:dem":23,
    "gn:feature_class":"P",
    "gn:feature_code":"PPL",
    "gn:name":"Salin",
    "gn:population":0,
    "gn:timezone":"Asia/Yangon",
    "iso:country":"MM",
    "name:bul_x_preferred":[
        "\u0421\u0430\u043b\u0438\u043d"
    ],
    "name:deu_x_preferred":[
        "Salin"
    ],
    "name:fin_x_preferred":[
        "Salin"
    ],
    "name:fra_x_preferred":[
        "Salin"
    ],
    "name:rus_x_preferred":[
        "\u0421\u0430\u043b\u0438\u043d"
    ],
    "name:srp_x_preferred":[
        "\u0421\u0430\u043b\u0438\u043d"
    ],
    "wof:name":"Salin",
    "wof:placetype":"locality"
},
  "geometry": {"coordinates":[98.76904999999999,12.51457],"type":"Point"}
}