{
  "type": "Feature",
  "properties": {
    "gn:admin1_code":"10.0",
    "gn:admin2_code":"MMR005D004",
    "gn:admin3_code":"MMR005025",
    "gn:asciiname":"Kyauk-myaung",
    "gn:country_code":"MM",
    "gn:dem":243,
    "gn:feature_class":"P",
    "gn:feature_code":"PPL",
    "gn:name":"Kyauk-myaung",
    "gn:population":0,
    "gn:timezone":"Asia/Yangon",
    "iso:country":"MM",
    "wof:name":"Kyauk-myaung",
    "wof:placetype":"locality"
},
  "geometry": {"coordinates":[95.66065999999999,23.92388],"type":"Point"}
}