{
  "type": "Feature",
  "properties": {
    "gn:admin1_code":"11.0",
    "gn:admin2_code":"MMR014D002",
    "gn:admin3_code":"MMR014016",
    "gn:asciiname":"Wan Kongkeng",
    "gn:country_code":"MM",
    "gn:dem":784,
    "gn:feature_class":"P",
    "gn:feature_code":"PPL",
    "gn:name":"W\u0101n Kongkeng",
    "gn:population":0,
    "gn:timezone":"Asia/Yangon",
    "iso:country":"MM",
    "name:und_x_variant":[
        "Wan Kowkeng",
        "W\u0101n Kongkeng"
    ],
    "wof:name":"Wan Kongkeng",
    "wof:placetype":"locality"
},
  "geometry": {"coordinates":[97.32491,21.76657],"type":"Point"}
}