{
  "type": "Feature",
  "properties": {
    "gn:admin1_code":"11.0",
    "gn:admin2_code":"MMR014D002",
    "gn:admin3_code":"MMR014016",
    "gn:asciiname":"Hpa-wan",
    "gn:country_code":"MM",
    "gn:dem":1017,
    "gn:feature_class":"P",
    "gn:feature_code":"PPL",
    "gn:name":"Hpa-wan",
    "gn:population":0,
    "gn:timezone":"Asia/Yangon",
    "iso:country":"MM",
    "wof:name":"Hpa-wan",
    "wof:placetype":"locality"
},
  "geometry": {"coordinates":[97.73193999999999,21.60296],"type":"Point"}
}