{
  "type": "Feature",
  "properties": {
    "gn:admin1_code":"10.0",
    "gn:admin2_code":"MMR005D004",
    "gn:admin3_code":"MMR005026",
    "gn:asciiname":"Auk Su",
    "gn:country_code":"MM",
    "gn:dem":261,
    "gn:feature_class":"P",
    "gn:feature_code":"PPL",
    "gn:name":"Auk Su",
    "gn:population":0,
    "gn:timezone":"Asia/Yangon",
    "iso:country":"MM",
    "wof:name":"Auk Su",
    "wof:placetype":"locality"
},
  "geometry": {"coordinates":[95.4016,23.96932],"type":"Point"}
}