{
  "type": "Feature",
  "properties": {
    "gn:admin1_code":"15.0",
    "gn:admin2_code":"MMR009D003",
    "gn:admin3_code":"MMR009014",
    "gn:asciiname":"Kywebe",
    "gn:country_code":"MM",
    "gn:dem":73,
    "gn:feature_class":"P",
    "gn:feature_code":"PPL",
    "gn:name":"Kywebe",
    "gn:population":0,
    "gn:timezone":"Asia/Yangon",
    "iso:country":"MM",
    "wof:name":"Kywebe",
    "wof:placetype":"locality"
},
  "geometry": {"coordinates":[94.71630999999999,19.34634],"type":"Point"}
}