{
  "type": "Feature",
  "properties": {
    "gn:admin1_code":"4.0",
    "gn:admin2_code":"MMR001D003",
    "gn:admin3_code":"MMR001010",
    "gn:asciiname":"Manking",
    "gn:country_code":"MM",
    "gn:dem":656,
    "gn:feature_class":"P",
    "gn:feature_code":"PPL",
    "gn:name":"Manking",
    "gn:population":0,
    "gn:timezone":"Asia/Yangon",
    "iso:country":"MM",
    "wof:name":"Manking",
    "wof:placetype":"locality"
},
  "geometry": {"coordinates":[96.87524000000001,23.90346],"type":"Point"}
}