{
  "type": "Feature",
  "properties": {
    "gn:admin1_code":"11.0",
    "gn:admin2_code":"MMR016D001",
    "gn:admin3_code":"MMR016001",
    "gn:asciiname":"Wan Hwe-hpun",
    "gn:country_code":"MM",
    "gn:dem":823,
    "gn:feature_class":"P",
    "gn:feature_code":"PPL",
    "gn:name":"W\u0101n Hw\u00e8-hp\u016bn",
    "gn:population":0,
    "gn:timezone":"Asia/Yangon",
    "iso:country":"MM",
    "name:und_x_variant":[
        "Hwe-hpun",
        "W\u0101n Hw\u00e8-hp\u016bn"
    ],
    "wof:name":"Wan Hwe-hpun",
    "wof:placetype":"locality"
},
  "geometry": {"coordinates":[99.59535,21.27107],"type":"Point"}
}