{
  "type": "Feature",
  "properties": {
    "gn:admin1_code":"4.0",
    "gn:admin2_code":"MMR001D004",
    "gn:admin3_code":"MMR001015",
    "gn:asciiname":"Lollam",
    "gn:country_code":"MM",
    "gn:dem":670,
    "gn:feature_class":"P",
    "gn:feature_code":"PPL",
    "gn:name":"Lollam",
    "gn:population":0,
    "gn:timezone":"Asia/Yangon",
    "iso:country":"MM",
    "name:und_x_variant":[
        "Loilam",
        "Lollam"
    ],
    "wof:name":"Lollam",
    "wof:placetype":"locality"
},
  "geometry": {"coordinates":[97.50527,26.28791],"type":"Point"}
}