{
  "type": "Feature",
  "properties": {
    "gn:admin1_code":"15.0",
    "gn:admin2_code":"MMR009D001",
    "gn:admin3_code":"MMR009002",
    "gn:asciiname":"Thapangyaun",
    "gn:country_code":"MM",
    "gn:dem":59,
    "gn:feature_class":"P",
    "gn:feature_code":"PPL",
    "gn:name":"Thapangyaun",
    "gn:population":0,
    "gn:timezone":"Asia/Yangon",
    "iso:country":"MM",
    "wof:name":"Thapangyaun",
    "wof:placetype":"locality"
},
  "geometry": {"coordinates":[94.91491000000001,20.35956],"type":"Point"}
}