{
  "type": "Feature",
  "properties": {
    "gn:admin1_code":"16.0",
    "gn:admin2_code":"MMR007D002",
    "gn:admin3_code":"MMR007011",
    "gn:asciiname":"Yele Kayinywa",
    "gn:country_code":"MM",
    "gn:dem":28,
    "gn:feature_class":"P",
    "gn:feature_code":"PPL",
    "gn:name":"Yele Kayinywa",
    "gn:population":0,
    "gn:timezone":"Asia/Yangon",
    "iso:country":"MM",
    "name:und_x_variant":[
        "Yel\u0113 Karen",
        "Yele Kayinywa"
    ],
    "wof:name":"Yele Kayinywa",
    "wof:placetype":"locality"
},
  "geometry": {"coordinates":[96.69201,18.31249],"type":"Point"}
}