{
  "type": "Feature",
  "properties": {
    "gn:admin1_code":"2.0",
    "gn:admin2_code":"MMR004D001",
    "gn:admin3_code":"MMR004001",
    "gn:asciiname":"Khawpisip",
    "gn:country_code":"MM",
    "gn:dem":1487,
    "gn:feature_class":"P",
    "gn:feature_code":"PPL",
    "gn:name":"Khawpisip",
    "gn:population":0,
    "gn:timezone":"Asia/Yangon",
    "iso:country":"MM",
    "wof:name":"Khawpisip",
    "wof:placetype":"locality"
},
  "geometry": {"coordinates":[93.43333,23.18333],"type":"Point"}
}