{
  "type": "Feature",
  "properties": {
    "gn:admin1_code":"3.0",
    "gn:admin2_code":"MMR017D005",
    "gn:admin3_code":"MMR017022",
    "gn:asciiname":"Sangin",
    "gn:country_code":"MM",
    "gn:dem":14,
    "gn:feature_class":"P",
    "gn:feature_code":"PPL",
    "gn:name":"Sangin",
    "gn:population":0,
    "gn:timezone":"Asia/Yangon",
    "iso:country":"MM",
    "name:ara_x_preferred":[
        "\u0633\u0646\u062c\u064a\u0646"
    ],
    "name:ast_x_preferred":[
        "Sangin"
    ],
    "name:ceb_x_preferred":[
        "Sang\u012bn"
    ],
    "name:fas_x_preferred":[
        "\u0633\u0646\u06af\u06cc\u0646"
    ],
    "name:ita_x_preferred":[
        "Sangin"
    ],
    "name:pus_x_preferred":[
        "\u0633\u0646\u06af\u064a\u0646"
    ],
    "name:rus_x_preferred":[
        "\u0421\u0430\u043d\u0433\u0438\u043d"
    ],
    "name:spa_x_preferred":[
        "Sang\u012bn"
    ],
    "name:swe_x_preferred":[
        "Sang\u012bn"
    ],
    "wof:name":"Sangin",
    "wof:placetype":"locality"
},
  "geometry": {"coordinates":[95.62143,17.23186],"type":"Point"}
}