{
  "type": "Feature",
  "properties": {
    "gn:admin1_code":"11.0",
    "gn:admin2_code":"MMR015D001",
    "gn:admin3_code":"MMR015001",
    "gn:asciiname":"Nam-hpuk-tok",
    "gn:country_code":"MM",
    "gn:dem":804,
    "gn:feature_class":"P",
    "gn:feature_code":"PPL",
    "gn:name":"Nam-hpuk-tok",
    "gn:population":0,
    "gn:timezone":"Asia/Yangon",
    "iso:country":"MM",
    "wof:name":"Nam-hpuk-tok",
    "wof:placetype":"locality"
},
  "geometry": {"coordinates":[97.66041,22.79312],"type":"Point"}
}