{
  "type": "Feature",
  "properties": {
    "gn:admin1_code":"11.0",
    "gn:admin2_code":"MMR015D007",
    "gn:admin3_code":"MMR015005",
    "gn:asciiname":"Man Kawnghka",
    "gn:country_code":"MM",
    "gn:dem":952,
    "gn:feature_class":"P",
    "gn:feature_code":"PPL",
    "gn:name":"M\u0101n Kawnghka",
    "gn:population":0,
    "gn:timezone":"Asia/Yangon",
    "iso:country":"MM",
    "wof:name":"Man Kawnghka",
    "wof:placetype":"locality"
},
  "geometry": {"coordinates":[99.03739,22.23797],"type":"Point"}
}