{
  "type": "Feature",
  "properties": {
    "gn:admin1_code":"4.0",
    "gn:admin2_code":"MMR001D002",
    "gn:admin3_code":"MMR001009",
    "gn:asciiname":"Yihku",
    "gn:country_code":"MM",
    "gn:dem":225,
    "gn:feature_class":"P",
    "gn:feature_code":"PPL",
    "gn:name":"Yihku",
    "gn:population":0,
    "gn:timezone":"Asia/Yangon",
    "iso:country":"MM",
    "name:urd_x_preferred":[
        "\u06cc\u06be\u06a9\u0648"
    ],
    "wof:name":"Yihku",
    "wof:placetype":"locality"
},
  "geometry": {"coordinates":[96.82928,25.52959],"type":"Point"}
}