{
  "type": "Feature",
  "properties": {
    "gn:admin1_code":"11.0",
    "gn:admin2_code":"MMR016D001",
    "gn:admin3_code":"MMR016007",
    "gn:asciiname":"Ka-lo",
    "gn:country_code":"MM",
    "gn:dem":405,
    "gn:feature_class":"P",
    "gn:feature_code":"PPL",
    "gn:name":"Ka-lo",
    "gn:population":0,
    "gn:timezone":"Asia/Yangon",
    "iso:country":"MM",
    "wof:name":"Ka-lo",
    "wof:placetype":"locality"
},
  "geometry": {"coordinates":[98.58592,21.54314],"type":"Point"}
}