{
  "type": "Feature",
  "properties": {
    "gn:admin1_code":"2.0",
    "gn:admin2_code":"MMR004D002",
    "gn:admin3_code":"MMR004006",
    "gn:asciiname":"Hnum",
    "gn:country_code":"MM",
    "gn:dem":1593,
    "gn:feature_class":"P",
    "gn:feature_code":"PPL",
    "gn:name":"Hnum",
    "gn:population":0,
    "gn:timezone":"Asia/Yangon",
    "iso:country":"MM",
    "wof:name":"Hnum",
    "wof:placetype":"locality"
},
  "geometry": {"coordinates":[93.79949999999999,21.26139],"type":"Point"}
}