{
  "type": "Feature",
  "properties": {
    "gn:admin1_code":"11.0",
    "gn:admin2_code":"MMR015D003",
    "gn:admin3_code":"MMR015019",
    "gn:asciiname":"Rau-wai",
    "gn:country_code":"MM",
    "gn:dem":1411,
    "gn:feature_class":"P",
    "gn:feature_code":"PPL",
    "gn:name":"Rau-wai",
    "gn:population":0,
    "gn:timezone":"Asia/Yangon",
    "iso:country":"MM",
    "name:und_x_variant":[
        "Man Pun",
        "Rau-wai"
    ],
    "wof:name":"Rau-wai",
    "wof:placetype":"locality"
},
  "geometry": {"coordinates":[97.03242,23.17107],"type":"Point"}
}