{
  "type": "Feature",
  "properties": {
    "gn:admin1_code":"6.0",
    "gn:admin2_code":"MMR002D001",
    "gn:admin3_code":"MMR002003",
    "gn:asciiname":"Na-hpa-chi",
    "gn:country_code":"MM",
    "gn:dem":855,
    "gn:feature_class":"P",
    "gn:feature_code":"PPL",
    "gn:name":"Na-hpa-chi",
    "gn:population":0,
    "gn:timezone":"Asia/Yangon",
    "iso:country":"MM",
    "wof:name":"Na-hpa-chi",
    "wof:placetype":"locality"
},
  "geometry": {"coordinates":[97.03431999999999,19.12499],"type":"Point"}
}