{
  "type": "Feature",
  "properties": {
    "gn:admin1_code":"11.0",
    "gn:asciiname":"Dawlaw-kle",
    "gn:country_code":"MM",
    "gn:dem":723,
    "gn:feature_class":"P",
    "gn:feature_code":"PPL",
    "gn:name":"Dawlaw-kl\u00e8",
    "gn:population":0,
    "gn:timezone":"Asia/Yangon",
    "iso:country":"MM",
    "wof:name":"Dawlaw-kle",
    "wof:placetype":"locality"
},
  "geometry": {"coordinates":[97.31204,19.88335],"type":"Point"}
}