{
  "type": "Feature",
  "properties": {
    "gn:admin1_code":"12.0",
    "gn:admin2_code":"MMR006D003",
    "gn:admin3_code":"MMR006010",
    "gn:asciiname":"Pisanduangsaung",
    "gn:country_code":"MM",
    "gn:dem":16,
    "gn:feature_class":"P",
    "gn:feature_code":"PPL",
    "gn:name":"Pisanduangsaung",
    "gn:population":0,
    "gn:timezone":"Asia/Yangon",
    "iso:country":"MM",
    "wof:name":"Pisanduangsaung",
    "wof:placetype":"locality"
},
  "geometry": {"coordinates":[98.70218,11.40754],"type":"Point"}
}