{
  "type": "Feature",
  "properties": {
    "gn:admin1_code":"3.0",
    "gn:admin2_code":"MMR017D004",
    "gn:admin3_code":"MMR017016",
    "gn:asciiname":"Kyigyaung Peikta",
    "gn:country_code":"MM",
    "gn:dem":4,
    "gn:feature_class":"P",
    "gn:feature_code":"PPL",
    "gn:name":"Kyigyaung Peikta",
    "gn:population":0,
    "gn:timezone":"Asia/Yangon",
    "iso:country":"MM",
    "wof:name":"Kyigyaung Peikta",
    "wof:placetype":"locality"
},
  "geometry": {"coordinates":[95.04192999999999,16.31188],"type":"Point"}
}