{
  "type": "Feature",
  "properties": {
    "gn:admin1_code":"15.0",
    "gn:admin2_code":"MMR009D005",
    "gn:admin3_code":"MMR009025",
    "gn:asciiname":"Lebyu",
    "gn:country_code":"MM",
    "gn:dem":428,
    "gn:feature_class":"P",
    "gn:feature_code":"PPL",
    "gn:name":"Lebyu",
    "gn:population":0,
    "gn:timezone":"Asia/Yangon",
    "iso:country":"MM",
    "wof:name":"Lebyu",
    "wof:placetype":"locality"
},
  "geometry": {"coordinates":[94.19485,21.07366],"type":"Point"}
}