{
  "type": "Feature",
  "properties": {
    "gn:admin1_code":"17.0",
    "gn:admin2_code":"MMR013D001",
    "gn:admin3_code":"MMR013006",
    "gn:asciiname":"Kyaikkana",
    "gn:country_code":"MM",
    "gn:dem":8,
    "gn:feature_class":"P",
    "gn:feature_code":"PPL",
    "gn:name":"Kyaikkana",
    "gn:population":0,
    "gn:timezone":"Asia/Yangon",
    "iso:country":"MM",
    "wof:name":"Kyaikkana",
    "wof:placetype":"locality"
},
  "geometry": {"coordinates":[95.97699,16.90997999999999],"type":"Point"}
}