{
  "type": "Feature",
  "properties": {
    "gn:admin1_code":"10.0",
    "gn:admin2_code":"MMR005D006",
    "gn:admin3_code":"MMR005030",
    "gn:asciiname":"Hlezeik",
    "gn:country_code":"MM",
    "gn:dem":170,
    "gn:feature_class":"P",
    "gn:feature_code":"PPL",
    "gn:name":"Hlezeik",
    "gn:population":0,
    "gn:timezone":"Asia/Yangon",
    "iso:country":"MM",
    "wof:name":"Hlezeik",
    "wof:placetype":"locality"
},
  "geometry": {"coordinates":[94.45793,24.40451],"type":"Point"}
}