{
  "type": "Feature",
  "properties": {
    "gn:admin1_code":"4.0",
    "gn:admin2_code":"MMR001D001",
    "gn:admin3_code":"MMR001001",
    "gn:asciiname":"Simalhka",
    "gn:country_code":"MM",
    "gn:dem":145,
    "gn:feature_class":"P",
    "gn:feature_code":"PPL",
    "gn:name":"Simalhka",
    "gn:population":0,
    "gn:timezone":"Asia/Yangon",
    "iso:country":"MM",
    "name:und_x_variant":[
        "Sanunka",
        "Simalhka"
    ],
    "wof:name":"Simalhka",
    "wof:placetype":"locality"
},
  "geometry": {"coordinates":[97.44555,25.47322],"type":"Point"}
}