{
  "type": "Feature",
  "properties": {
    "gn:admin1_code":"2.0",
    "gn:admin2_code":"MMR004D003",
    "gn:admin3_code":"MMR004003",
    "gn:asciiname":"Ngaiphaipi",
    "gn:country_code":"MM",
    "gn:dem":1561,
    "gn:feature_class":"P",
    "gn:feature_code":"PPL",
    "gn:name":"Ngaiphaipi",
    "gn:population":0,
    "gn:timezone":"Asia/Yangon",
    "iso:country":"MM",
    "name:und_x_variant":[
        "Ngaipnaipi",
        "Ngaiphaipi"
    ],
    "wof:name":"Ngaiphaipi",
    "wof:placetype":"locality"
},
  "geometry": {"coordinates":[93.25002000000001,22.23656],"type":"Point"}
}