{
  "type": "Feature",
  "properties": {
    "gn:admin1_code":"11.0",
    "gn:admin2_code":"MMR015D003",
    "gn:admin3_code":"MMR015014",
    "gn:asciiname":"Htangsang",
    "gn:country_code":"MM",
    "gn:dem":1327,
    "gn:feature_class":"P",
    "gn:feature_code":"PPL",
    "gn:name":"Ht\u0101ngsang",
    "gn:population":0,
    "gn:timezone":"Asia/Yangon",
    "iso:country":"MM",
    "wof:name":"Htangsang",
    "wof:placetype":"locality"
},
  "geometry": {"coordinates":[97.16998,22.67558],"type":"Point"}
}