{
  "type": "Feature",
  "properties": {
    "gn:admin1_code":"15.0",
    "gn:asciiname":"Setsetyo",
    "gn:country_code":"MM",
    "gn:dem":181,
    "gn:feature_class":"P",
    "gn:feature_code":"PPL",
    "gn:name":"Setsetyo",
    "gn:population":0,
    "gn:timezone":"Asia/Yangon",
    "iso:country":"MM",
    "wof:name":"Setsetyo",
    "wof:placetype":"locality"
},
  "geometry": {"coordinates":[95.43953999999999,19.17295],"type":"Point"}
}