{
  "type": "Feature",
  "properties": {
    "gn:admin1_code":"10.0",
    "gn:admin2_code":"MMR005D008",
    "gn:admin3_code":"MMR005037",
    "gn:asciiname":"Rara",
    "gn:country_code":"MM",
    "gn:dem":761,
    "gn:feature_class":"P",
    "gn:feature_code":"PPL",
    "gn:name":"R\u0101ra",
    "gn:population":0,
    "gn:timezone":"Asia/Yangon",
    "iso:country":"MM",
    "wof:name":"Rara",
    "wof:placetype":"locality"
},
  "geometry": {"coordinates":[95.73333,26.58333],"type":"Point"}
}