{
  "type": "Feature",
  "properties": {
    "gn:admin1_code":"11.0",
    "gn:admin2_code":"MMR014D002",
    "gn:admin3_code":"MMR014014",
    "gn:asciiname":"Wan Ta-hkan",
    "gn:country_code":"MM",
    "gn:dem":449,
    "gn:feature_class":"P",
    "gn:feature_code":"PPL",
    "gn:name":"W\u0101n T\u0101-hkan",
    "gn:population":0,
    "gn:timezone":"Asia/Yangon",
    "iso:country":"MM",
    "wof:name":"Wan Ta-hkan",
    "wof:placetype":"locality"
},
  "geometry": {"coordinates":[98.39449999999999,20.98312],"type":"Point"}
}