{
  "type": "Feature",
  "properties": {
    "gn:admin1_code":"11.0",
    "gn:admin2_code":"MMR015D007",
    "gn:admin3_code":"MMR015024",
    "gn:asciiname":"Makmang",
    "gn:country_code":"MM",
    "gn:dem":1260,
    "gn:feature_class":"P",
    "gn:feature_code":"PPL",
    "gn:name":"M\u0101kmang",
    "gn:population":0,
    "gn:timezone":"Asia/Yangon",
    "iso:country":"MM",
    "wof:name":"Makmang",
    "wof:placetype":"locality"
},
  "geometry": {"coordinates":[98.87622,21.94228],"type":"Point"}
}