{
  "type": "Feature",
  "properties": {
    "gn:admin1_code":"16.0",
    "gn:admin2_code":"MMR007D002",
    "gn:admin3_code":"MMR007009",
    "gn:asciiname":"Zigwe Te",
    "gn:country_code":"MM",
    "gn:dem":166,
    "gn:feature_class":"P",
    "gn:feature_code":"PPL",
    "gn:name":"Zigw\u0113 T\u0113",
    "gn:population":0,
    "gn:timezone":"Asia/Yangon",
    "iso:country":"MM",
    "wof:name":"Zigwe Te",
    "wof:placetype":"locality"
},
  "geometry": {"coordinates":[96.13333,18.98333],"type":"Point"}
}