{
  "type": "Feature",
  "properties": {
    "gn:admin1_code":"2.0",
    "gn:admin2_code":"MMR004D001",
    "gn:admin3_code":"MMR004005",
    "gn:asciiname":"Shiallup",
    "gn:country_code":"MM",
    "gn:dem":1008,
    "gn:feature_class":"P",
    "gn:feature_code":"PPL",
    "gn:name":"Shiallup",
    "gn:population":0,
    "gn:timezone":"Asia/Yangon",
    "iso:country":"MM",
    "wof:name":"Shiallup",
    "wof:placetype":"locality"
},
  "geometry": {"coordinates":[94.00753,23.80134],"type":"Point"}
}