{
  "type": "Feature",
  "properties": {
    "gn:admin1_code":"10.0",
    "gn:admin2_code":"MMR005D001",
    "gn:admin3_code":"MMR005001",
    "gn:asciiname":"Kandawyo",
    "gn:country_code":"MM",
    "gn:dem":85,
    "gn:feature_class":"P",
    "gn:feature_code":"PPL",
    "gn:name":"Kandawyo",
    "gn:population":0,
    "gn:timezone":"Asia/Yangon",
    "iso:country":"MM",
    "wof:name":"Kandawyo",
    "wof:placetype":"locality"
},
  "geometry": {"coordinates":[95.7183,22.22734],"type":"Point"}
}