{
  "type": "Feature",
  "properties": {
    "gn:admin1_code":"11.0",
    "gn:admin2_code":"MMR016D003",
    "gn:admin3_code":"MMR016009",
    "gn:asciiname":"Wan Ra-sa-hsumpan",
    "gn:country_code":"MM",
    "gn:dem":567,
    "gn:feature_class":"P",
    "gn:feature_code":"PPL",
    "gn:name":"W\u0101n Ra-sa-hsumpan",
    "gn:population":0,
    "gn:timezone":"Asia/Yangon",
    "iso:country":"MM",
    "name:und_x_variant":[
        "Wan Ra-sa-hsumpa",
        "W\u0101n Ra-sa-hsumpan"
    ],
    "wof:name":"Wan Ra-sa-hsumpan",
    "wof:placetype":"locality"
},
  "geometry": {"coordinates":[100.04773,20.58678],"type":"Point"}
}