{
  "type": "Feature",
  "properties": {
    "gn:admin1_code":"11.0",
    "gn:admin2_code":"MMR016D001",
    "gn:admin3_code":"MMR016003",
    "gn:asciiname":"Wan Ho-pang",
    "gn:country_code":"MM",
    "gn:dem":890,
    "gn:feature_class":"P",
    "gn:feature_code":"PPL",
    "gn:name":"W\u0101n Ho-p\u0101ng",
    "gn:population":0,
    "gn:timezone":"Asia/Yangon",
    "iso:country":"MM",
    "wof:name":"Wan Ho-pang",
    "wof:placetype":"locality"
},
  "geometry": {"coordinates":[99.62224000000001,21.90855],"type":"Point"}
}