{
  "type": "Feature",
  "properties": {
    "gn:admin1_code":"10.0",
    "gn:admin2_code":"MMR005D001",
    "gn:admin3_code":"MMR005002",
    "gn:asciiname":"Pedaung",
    "gn:country_code":"MM",
    "gn:dem":142,
    "gn:feature_class":"P",
    "gn:feature_code":"PPL",
    "gn:name":"Pedaung",
    "gn:population":0,
    "gn:timezone":"Asia/Yangon",
    "iso:country":"MM",
    "wof:name":"Pedaung",
    "wof:placetype":"locality"
},
  "geometry": {"coordinates":[95.39637999999999,21.99621],"type":"Point"}
}