{
  "type": "Feature",
  "properties": {
    "gn:admin1_code":"8.0",
    "gn:admin2_code":"MMR010D005",
    "gn:admin3_code":"MMR010022",
    "gn:asciiname":"Kabani",
    "gn:country_code":"MM",
    "gn:dem":128,
    "gn:feature_class":"P",
    "gn:feature_code":"PPL",
    "gn:name":"Kabani",
    "gn:population":0,
    "gn:timezone":"Asia/Yangon",
    "iso:country":"MM",
    "name:ceb_x_preferred":[
        "Kabani"
    ],
    "name:swe_x_preferred":[
        "Kabani"
    ],
    "wof:name":"Kabani",
    "wof:placetype":"locality"
},
  "geometry": {"coordinates":[94.96975999999999,21.1831],"type":"Point"}
}