{
  "type": "Feature",
  "properties": {
    "gn:admin1_code":"3.0",
    "gn:admin2_code":"MMR017D002",
    "gn:admin3_code":"MMR017010",
    "gn:asciiname":"Lemyethna",
    "gn:country_code":"MM",
    "gn:dem":14,
    "gn:feature_class":"P",
    "gn:feature_code":"PPL",
    "gn:name":"Lemyethna",
    "gn:population":0,
    "gn:timezone":"Asia/Yangon",
    "iso:country":"MM",
    "name:mya_x_preferred":[
        "\u101c\u1031\u1038\u1019\u103b\u1000\u103a\u1014\u103e\u102c\u1019\u103c\u102d\u102f\u1037"
    ],
    "wof:name":"Lemyethna",
    "wof:placetype":"locality"
},
  "geometry": {"coordinates":[95.13862,17.60405],"type":"Point"}
}