{
  "type": "Feature",
  "properties": {
    "gn:admin1_code":"4.0",
    "gn:admin2_code":"MMR001D003",
    "gn:admin3_code":"MMR001013",
    "gn:asciiname":"Sama",
    "gn:country_code":"MM",
    "gn:dem":1316,
    "gn:feature_class":"P",
    "gn:feature_code":"PPL",
    "gn:name":"Sama",
    "gn:population":0,
    "gn:timezone":"Asia/Yangon",
    "iso:country":"MM",
    "name:ast_x_preferred":[
        "Sama"
    ],
    "name:ceb_x_preferred":[
        "Sama"
    ],
    "name:deu_x_preferred":[
        "Sama"
    ],
    "name:fin_x_preferred":[
        "Sama"
    ],
    "name:fra_x_preferred":[
        "Sama"
    ],
    "name:ind_x_preferred":[
        "Sama"
    ],
    "name:ita_x_preferred":[
        "Sama"
    ],
    "name:por_x_preferred":[
        "Sama"
    ],
    "name:spa_x_preferred":[
        "Sama"
    ],
    "name:swe_x_preferred":[
        "Sama"
    ],
    "name:urd_x_preferred":[
        "\u0633\u0627\u0645\u0627"
    ],
    "wof:name":"Sama",
    "wof:placetype":"locality"
},
  "geometry": {"coordinates":[97.40738,23.93539],"type":"Point"}
}