{
  "type": "Feature",
  "properties": {
    "gn:admin1_code":"11.0",
    "gn:admin2_code":"MMR014D003",
    "gn:admin3_code":"MMR014020",
    "gn:asciiname":"Wan Loi-lim",
    "gn:country_code":"MM",
    "gn:dem":578,
    "gn:feature_class":"P",
    "gn:feature_code":"PPL",
    "gn:name":"W\u0101n Loi-lim",
    "gn:population":0,
    "gn:timezone":"Asia/Yangon",
    "iso:country":"MM",
    "wof:name":"Wan Loi-lim",
    "wof:placetype":"locality"
},
  "geometry": {"coordinates":[97.69159000000001,20.0928],"type":"Point"}
}