{
  "type": "Feature",
  "properties": {
    "gn:admin1_code":"1.0",
    "gn:admin2_code":"MMR012D003",
    "gn:admin3_code":"MMR012011",
    "gn:asciiname":"Sane",
    "gn:country_code":"MM",
    "gn:dem":5,
    "gn:feature_class":"P",
    "gn:feature_code":"PPL",
    "gn:name":"Sane",
    "gn:population":0,
    "gn:timezone":"Asia/Yangon",
    "iso:country":"MM",
    "name:cat_x_preferred":[
        "Sane"
    ],
    "name:ceb_x_preferred":[
        "Sane"
    ],
    "name:fin_x_preferred":[
        "Sane"
    ],
    "name:heb_x_preferred":[
        "\u05e1\u05d0\u05e0\u05d4"
    ],
    "name:kaz_x_preferred":[
        "\u0421\u0430\u043d\u043a"
    ],
    "name:spa_x_preferred":[
        "Sane"
    ],
    "name:swe_x_preferred":[
        "Sane"
    ],
    "wof:name":"Sane",
    "wof:placetype":"locality"
},
  "geometry": {"coordinates":[93.73233999999999,19.21628],"type":"Point"}
}