{
  "type": "Feature",
  "properties": {
    "gn:admin1_code":"1.0",
    "gn:admin2_code":"MMR012D003",
    "gn:admin3_code":"MMR012011",
    "gn:asciiname":"Sane",
    "gn:country_code":"MM",
    "gn:dem":5,
    "gn:feature_class":"P",
    "gn:feature_code":"PPL",
    "gn:name":"Sane",
    "gn:population":0,
    "gn:timezone":"Asia/Yangon",
    "iso:country":"MM",
    "name:cat_x_preferred":[
        "Sane"
    ],
    "name:ceb_x_preferred":[
        "Sane"
    ],
    "name:fin_x_preferred":[
        "Sane"
    ],
    "name:heb_x_preferred":[
        "\u05e1\u05d0\u05e0\u05b6\u05d4"
    ],
    "name:heb_x_variant":[
        "\u05e1\u05d0\u05e0\u05d4"
    ],
    "name:hin_x_preferred":[
        "\u0938\u0947\u0928"
    ],
    "name:hun_x_preferred":[
        "Sane"
    ],
    "name:ind_x_preferred":[
        "Sane"
    ],
    "name:ita_x_preferred":[
        "Sane"
    ],
    "name:jpn_x_preferred":[
        "\u30bb\u30fc\u30cc\u5ddd"
    ],
    "name:kaz_x_preferred":[
        "\u0421\u0430\u043d\u043a"
    ],
    "name:kor_x_preferred":[
        "\uc138\uc778"
    ],
    "name:nld_x_preferred":[
        "Sa\u00f4ne"
    ],
    "name:pol_x_preferred":[
        "Sane"
    ],
    "name:por_x_preferred":[
        "Sena"
    ],
    "name:rus_x_preferred":[
        "\u0440\u0435\u043a\u0430 \u0421\u043e\u043d\u0430"
    ],
    "name:spa_x_preferred":[
        "Sane"
    ],
    "name:swe_x_preferred":[
        "Sa\u00f4ne"
    ],
    "name:swe_x_variant":[
        "Sane"
    ],
    "name:tur_x_preferred":[
        "Sane"
    ],
    "name:ukr_x_preferred":[
        "\u0421\u0435\u0439\u043d"
    ],
    "name:urd_x_preferred":[
        "\u0633\u06cc\u0646"
    ],
    "name:vie_x_preferred":[
        "S\u00f4ng Sane"
    ],
    "name:zho_cn_x_preferred":[
        "\u8428\u5185\u6cb3"
    ],
    "name:zho_tw_x_preferred":[
        "\u585e\u7d0d\u6cb3"
    ],
    "wof:name":"Sane",
    "wof:placetype":"locality"
},
  "geometry": {"coordinates":[93.73233999999999,19.21628],"type":"Point"}
}