{
  "type": "Feature",
  "properties": {
    "gn:admin1_code":"16.0",
    "gn:admin2_code":"MMR008D001",
    "gn:admin3_code":"MMR008003",
    "gn:asciiname":"Nyaung-chi-dauk",
    "gn:country_code":"MM",
    "gn:dem":47,
    "gn:feature_class":"P",
    "gn:feature_code":"PPL",
    "gn:name":"Nyaung-chi-dauk",
    "gn:population":0,
    "gn:timezone":"Asia/Yangon",
    "iso:country":"MM",
    "wof:name":"Nyaung-chi-dauk",
    "wof:placetype":"locality"
},
  "geometry": {"coordinates":[94.96852,18.68208],"type":"Point"}
}