{
  "type": "Feature",
  "properties": {
    "gn:admin1_code":"3.0",
    "gn:admin2_code":"MMR017D001",
    "gn:admin3_code":"MMR017002",
    "gn:asciiname":"Kyaiklat",
    "gn:country_code":"MM",
    "gn:dem":10,
    "gn:feature_class":"P",
    "gn:feature_code":"PPL",
    "gn:name":"Kyaiklat",
    "gn:population":0,
    "gn:timezone":"Asia/Yangon",
    "iso:country":"MM",
    "name:und_x_variant":[
        "Kayiklat",
        "Kyaiklat"
    ],
    "wof:name":"Kyaiklat",
    "wof:placetype":"locality"
},
  "geometry": {"coordinates":[94.86212999999999,16.77397],"type":"Point"}
}