{
  "type": "Feature",
  "properties": {
    "gn:admin1_code":"4.0",
    "gn:admin2_code":"MMR001D002",
    "gn:admin3_code":"MMR001008",
    "gn:asciiname":"Latao",
    "gn:country_code":"MM",
    "gn:dem":201,
    "gn:feature_class":"P",
    "gn:feature_code":"PPL",
    "gn:name":"Latao",
    "gn:population":0,
    "gn:timezone":"Asia/Yangon",
    "iso:country":"MM",
    "wof:name":"Latao",
    "wof:placetype":"locality"
},
  "geometry": {"coordinates":[96.91459999999999,25.12422],"type":"Point"}
}