{
  "type": "Feature",
  "properties": {
    "gn:admin1_code":"12.0",
    "gn:admin2_code":"MMR006D002",
    "gn:admin3_code":"MMR006008",
    "gn:asciiname":"Tanintharyi",
    "gn:country_code":"MM",
    "gn:dem":15,
    "gn:feature_class":"P",
    "gn:feature_code":"PPL",
    "gn:name":"Tanintharyi",
    "gn:population":0,
    "gn:timezone":"Asia/Yangon",
    "iso:country":"MM",
    "name:fra_x_preferred":[
        "Tanintharyi"
    ],
    "name:heb_x_preferred":[
        "\u05d8\u05d0\u05e0\u05d9\u05e0\u05d8\u05d0\u05e8\u05d9"
    ],
    "name:hun_x_preferred":[
        "Tanintharyi"
    ],
    "name:mya_x_preferred":[
        "\u1010\u1014\u1004\u103a\u1039\u101e\u102c\u101b\u102e\u1019\u103c\u102d\u102f\u1037"
    ],
    "name:por_x_preferred":[
        "Tanintharyi"
    ],
    "name:rus_x_preferred":[
        "\u0422\u0430\u043d\u0438\u043d\u0442\u0430\u0439\u0438"
    ],
    "name:shn_x_preferred":[
        "\u1010\u107c\u102d\u107c\u103a\u1038\u1010\u1083\u1087\u101a\u102e\u1087\u104a \u101d\u1035\u1004\u103a\u1038"
    ],
    "name:tha_x_preferred":[
        "\u0e15\u0e30\u0e19\u0e32\u0e27\u0e28\u0e23\u0e35"
    ],
    "name:und_x_variant":[
        "Tenasserim",
        "Tanangthayi",
        "Tanintayi",
        "Taninthayi"
    ],
    "wof:name":"Tanintharyi",
    "wof:placetype":"locality"
},
  "geometry": {"coordinates":[99.01165,12.09032],"type":"Point"}
}