{
  "type": "Feature",
  "properties": {
    "gn:admin1_code":"12.0",
    "gn:admin2_code":"MMR006D002",
    "gn:admin3_code":"MMR006008",
    "gn:asciiname":"Tanintharyi",
    "gn:country_code":"MM",
    "gn:dem":15,
    "gn:feature_class":"P",
    "gn:feature_code":"PPL",
    "gn:name":"Tanintharyi",
    "gn:population":0,
    "gn:timezone":"Asia/Yangon",
    "iso:country":"MM",
    "name:rus_x_preferred":[
        "\u0422\u0430\u043d\u0438\u043d\u0442\u0430\u0439\u0438"
    ],
    "name:und_x_variant":[
        "Tenasserim",
        "Tanangthayi",
        "Tanintayi",
        "Taninthayi",
        "Tanintharyi"
    ],
    "wof:name":"Tanintharyi",
    "wof:placetype":"locality"
},
  "geometry": {"coordinates":[99.01165,12.09032],"type":"Point"}
}