{
  "type": "Feature",
  "properties": {
    "gn:admin1_code":"12.0",
    "gn:admin2_code":"MMR006D001",
    "gn:admin3_code":"MMR006001",
    "gn:asciiname":"Sanke",
    "gn:country_code":"MM",
    "gn:dem":198,
    "gn:feature_class":"P",
    "gn:feature_code":"PPL",
    "gn:name":"Sank\u00e8",
    "gn:population":0,
    "gn:timezone":"Asia/Yangon",
    "iso:country":"MM",
    "wof:name":"Sanke",
    "wof:placetype":"locality"
},
  "geometry": {"coordinates":[98.52925999999999,14.12706],"type":"Point"}
}