{
  "type": "Feature",
  "properties": {
    "gn:admin1_code":"5.0",
    "gn:admin2_code":"MMR003D001",
    "gn:admin3_code":"MMR003001",
    "gn:asciiname":"Peinnedaw",
    "gn:country_code":"MM",
    "gn:dem":18,
    "gn:feature_class":"P",
    "gn:feature_code":"PPL",
    "gn:name":"Peinn\u0113daw",
    "gn:population":0,
    "gn:timezone":"Asia/Yangon",
    "iso:country":"MM",
    "name:und_x_variant":[
        "Pemn\u0113daw",
        "Peinn\u0113daw"
    ],
    "wof:name":"Peinnedaw",
    "wof:placetype":"locality"
},
  "geometry": {"coordinates":[97.67287,16.87652000000001],"type":"Point"}
}