{
  "type": "Feature",
  "properties": {
    "gn:admin1_code":"4.0",
    "gn:admin2_code":"MMR001D004",
    "gn:admin3_code":"MMR001015",
    "gn:asciiname":"Kadaukawng",
    "gn:country_code":"MM",
    "gn:dem":913,
    "gn:feature_class":"P",
    "gn:feature_code":"PPL",
    "gn:name":"Kadaukawng",
    "gn:population":0,
    "gn:timezone":"Asia/Yangon",
    "iso:country":"MM",
    "wof:name":"Kadaukawng",
    "wof:placetype":"locality"
},
  "geometry": {"coordinates":[97.33687,26.46486],"type":"Point"}
}