{
  "type": "Feature",
  "properties": {
    "gn:admin1_code":"1.0",
    "gn:admin2_code":"MMR012D002",
    "gn:admin3_code":"MMR012009",
    "gn:asciiname":"Shidapara",
    "gn:country_code":"MM",
    "gn:dem":21,
    "gn:feature_class":"P",
    "gn:feature_code":"PPL",
    "gn:name":"Shid\u0101p\u0101ra",
    "gn:population":0,
    "gn:timezone":"Asia/Yangon",
    "iso:country":"MM",
    "wof:name":"Shidapara",
    "wof:placetype":"locality"
},
  "geometry": {"coordinates":[92.23647,21.31297],"type":"Point"}
}