{
  "type": "Feature",
  "properties": {
    "gn:admin1_code":"15.0",
    "gn:admin2_code":"MMR009D004",
    "gn:admin3_code":"MMR009018",
    "gn:asciiname":"Lanywa",
    "gn:country_code":"MM",
    "gn:dem":58,
    "gn:feature_class":"P",
    "gn:feature_code":"PPL",
    "gn:name":"Lanywa",
    "gn:population":0,
    "gn:timezone":"Asia/Yangon",
    "iso:country":"MM",
    "name:mya_x_preferred":[
        "\u101c\u1019\u103a\u1038\u101b\u103d\u102c"
    ],
    "name:urd_x_preferred":[
        "\u0644\u0627\u0646\u06cc\u0648\u0627"
    ],
    "wof:name":"Lanywa",
    "wof:placetype":"locality"
},
  "geometry": {"coordinates":[94.82156999999999,20.96816],"type":"Point"}
}