{
  "type": "Feature",
  "properties": {
    "gn:admin1_code":"16.0",
    "gn:admin2_code":"MMR007D001",
    "gn:admin3_code":"MMR007008",
    "gn:asciiname":"Thauthekhi",
    "gn:country_code":"MM",
    "gn:dem":88,
    "gn:feature_class":"P",
    "gn:feature_code":"PPL",
    "gn:name":"Thauthekhi",
    "gn:population":0,
    "gn:timezone":"Asia/Yangon",
    "iso:country":"MM",
    "wof:name":"Thauthekhi",
    "wof:placetype":"locality"
},
  "geometry": {"coordinates":[97.01600999999999,18.0111],"type":"Point"}
}