{
  "type": "Feature",
  "properties": {
    "gn:admin1_code":"18.0",
    "gn:admin2_code":"MMR018D002",
    "gn:admin3_code":"MMR018007",
    "gn:asciiname":"Kyi-aung",
    "gn:country_code":"MM",
    "gn:dem":154,
    "gn:feature_class":"P",
    "gn:feature_code":"PPL",
    "gn:name":"Kyi-aung",
    "gn:population":0,
    "gn:timezone":"Asia/Yangon",
    "iso:country":"MM",
    "name:und_x_variant":[
        "Kyi-aung-ywa",
        "Kyi-aung"
    ],
    "wof:name":"Kyi-aung",
    "wof:placetype":"locality"
},
  "geometry": {"coordinates":[96.02554000000001,19.4991],"type":"Point"}
}