{
  "type": "Feature",
  "properties": {
    "gn:admin1_code":"15.0",
    "gn:admin2_code":"MMR009D003",
    "gn:admin3_code":"MMR009017",
    "gn:asciiname":"Thahnga",
    "gn:country_code":"MM",
    "gn:dem":138,
    "gn:feature_class":"P",
    "gn:feature_code":"PPL",
    "gn:name":"Thahnga",
    "gn:population":0,
    "gn:timezone":"Asia/Yangon",
    "iso:country":"MM",
    "wof:name":"Thahnga",
    "wof:placetype":"locality"
},
  "geometry": {"coordinates":[95.33862999999999,19.53739],"type":"Point"}
}