{
  "type": "Feature",
  "properties": {
    "gn:admin1_code":"18.0",
    "gn:admin2_code":"MMR018D001",
    "gn:admin3_code":"MMR018003",
    "gn:asciiname":"Thayetpin",
    "gn:country_code":"MM",
    "gn:dem":173,
    "gn:feature_class":"P",
    "gn:feature_code":"PPL",
    "gn:name":"Thayetpin",
    "gn:population":0,
    "gn:timezone":"Asia/Yangon",
    "iso:country":"MM",
    "wof:name":"Thayetpin",
    "wof:placetype":"locality"
},
  "geometry": {"coordinates":[96.21785,20.2502],"type":"Point"}
}