{
  "type": "Feature",
  "properties": {
    "gn:admin1_code":"11.0",
    "gn:admin2_code":"MMR015D007",
    "gn:admin3_code":"MMR015024",
    "gn:asciiname":"Wan Makwo",
    "gn:country_code":"MM",
    "gn:dem":566,
    "gn:feature_class":"P",
    "gn:feature_code":"PPL",
    "gn:name":"W\u0101n Makwo",
    "gn:population":0,
    "gn:timezone":"Asia/Yangon",
    "iso:country":"MM",
    "wof:name":"Wan Makwo",
    "wof:placetype":"locality"
},
  "geometry": {"coordinates":[98.64364999999999,21.90683],"type":"Point"}
}