{
  "type": "Feature",
  "properties": {
    "gn:admin1_code":"11.0",
    "gn:admin2_code":"MMR014D001",
    "gn:admin3_code":"MMR014004",
    "gn:asciiname":"Poenglau",
    "gn:country_code":"MM",
    "gn:dem":1003,
    "gn:feature_class":"P",
    "gn:feature_code":"PPL",
    "gn:name":"P\u00f6nglau",
    "gn:population":0,
    "gn:timezone":"Asia/Yangon",
    "iso:country":"MM",
    "name:und_x_variant":[
        "Ponglaw",
        "P\u00f6nglau"
    ],
    "wof:name":"Poenglau",
    "wof:placetype":"locality"
},
  "geometry": {"coordinates":[97.19316999999999,20.39497],"type":"Point"}
}