{
  "type": "Feature",
  "properties": {
    "gn:admin1_code":"3.0",
    "gn:admin2_code":"MMR017D001",
    "gn:admin3_code":"MMR017007",
    "gn:asciiname":"Hle-da-chaung",
    "gn:country_code":"MM",
    "gn:dem":13,
    "gn:feature_class":"P",
    "gn:feature_code":"PPL",
    "gn:name":"Hle-da-chaung",
    "gn:population":0,
    "gn:timezone":"Asia/Yangon",
    "iso:country":"MM",
    "wof:name":"Hle-da-chaung",
    "wof:placetype":"locality"
},
  "geometry": {"coordinates":[95.09636999999999,17.1132],"type":"Point"}
}