{
  "type": "Feature",
  "properties": {
    "gn:admin1_code":"1.0",
    "gn:admin2_code":"MMR012D003",
    "gn:admin3_code":"MMR012012",
    "gn:asciiname":"Ngaungbin Hla",
    "gn:country_code":"MM",
    "gn:dem":17,
    "gn:feature_class":"P",
    "gn:feature_code":"PPL",
    "gn:name":"Ngaungbin Hla",
    "gn:population":0,
    "gn:timezone":"Asia/Yangon",
    "iso:country":"MM",
    "wof:name":"Ngaungbin Hla",
    "wof:placetype":"locality"
},
  "geometry": {"coordinates":[93.68177,18.79351],"type":"Point"}
}