{
  "type": "Feature",
  "properties": {
    "gn:admin1_code":"8.0",
    "gn:admin2_code":"MMR010D007",
    "gn:admin3_code":"MMR010028",
    "gn:asciiname":"Antu",
    "gn:country_code":"MM",
    "gn:dem":257,
    "gn:feature_class":"P",
    "gn:feature_code":"PPL",
    "gn:name":"Antu",
    "gn:population":0,
    "gn:timezone":"Asia/Yangon",
    "iso:country":"MM",
    "name:ceb_x_preferred":[
        "Antu"
    ],
    "name:deu_x_preferred":[
        "Antu"
    ],
    "name:fra_x_preferred":[
        "Antu"
    ],
    "name:ita_x_preferred":[
        "Antu"
    ],
    "name:new_x_preferred":[
        "\u0905\u0928\u094d\u0924\u0941"
    ],
    "name:nld_x_preferred":[
        "Antu"
    ],
    "name:pol_x_preferred":[
        "Antu"
    ],
    "name:spa_x_preferred":[
        "Antu"
    ],
    "name:swe_x_preferred":[
        "Antu"
    ],
    "name:tur_x_preferred":[
        "Antu"
    ],
    "wof:name":"Antu",
    "wof:placetype":"locality"
},
  "geometry": {"coordinates":[95.80069,20.91894],"type":"Point"}
}