{
  "type": "Feature",
  "properties": {
    "gn:admin1_code":"5.0",
    "gn:admin2_code":"MMR003D004",
    "gn:admin3_code":"MMR003003",
    "gn:asciiname":"Shantaung-ywa",
    "gn:country_code":"MM",
    "gn:dem":47,
    "gn:feature_class":"P",
    "gn:feature_code":"PPL",
    "gn:name":"Shantaung-ywa",
    "gn:population":0,
    "gn:timezone":"Asia/Yangon",
    "iso:country":"MM",
    "name:und_x_variant":[
        "Shantaung"
    ],
    "wof:name":"Shantaung-ywa",
    "wof:placetype":"locality"
},
  "geometry": {"coordinates":[97.68248,17.47972],"type":"Point"}
}