{
  "type": "Feature",
  "properties": {
    "gn:admin1_code":"5.0",
    "gn:admin2_code":"MMR003D004",
    "gn:admin3_code":"MMR003003",
    "gn:asciiname":"Methukhi",
    "gn:country_code":"MM",
    "gn:dem":609,
    "gn:feature_class":"P",
    "gn:feature_code":"PPL",
    "gn:name":"M\u0113thukhi",
    "gn:population":0,
    "gn:timezone":"Asia/Yangon",
    "iso:country":"MM",
    "wof:name":"Methukhi",
    "wof:placetype":"locality"
},
  "geometry": {"coordinates":[97.21046,17.87971],"type":"Point"}
}