{
  "type": "Feature",
  "properties": {
    "gn:admin1_code":"11.0",
    "gn:admin2_code":"MMR015D005",
    "gn:admin3_code":"MMR015023",
    "gn:asciiname":"Saopa Chai",
    "gn:country_code":"MM",
    "gn:dem":1187,
    "gn:feature_class":"P",
    "gn:feature_code":"PPL",
    "gn:name":"Saopa Chai",
    "gn:population":0,
    "gn:timezone":"Asia/Yangon",
    "iso:country":"MM",
    "wof:name":"Saopa Chai",
    "wof:placetype":"locality"
},
  "geometry": {"coordinates":[98.58714999999999,23.9131],"type":"Point"}
}