{
  "type": "Feature",
  "properties": {
    "gn:admin1_code":"11.0",
    "gn:admin2_code":"MMR014D001",
    "gn:admin3_code":"MMR014005",
    "gn:asciiname":"Wetpyuye",
    "gn:country_code":"MM",
    "gn:dem":837,
    "gn:feature_class":"P",
    "gn:feature_code":"PPL",
    "gn:name":"Wetpyuye",
    "gn:population":0,
    "gn:timezone":"Asia/Yangon",
    "iso:country":"MM",
    "wof:name":"Wetpyuye",
    "wof:placetype":"locality"
},
  "geometry": {"coordinates":[96.51251000000001,20.70399],"type":"Point"}
}