{
  "type": "Feature",
  "properties": {
    "gn:admin1_code":"10.0",
    "gn:admin2_code":"MMR005D008",
    "gn:admin3_code":"MMR005036",
    "gn:asciiname":"Tauko",
    "gn:country_code":"MM",
    "gn:dem":1138,
    "gn:feature_class":"P",
    "gn:feature_code":"PPL",
    "gn:name":"Tauko",
    "gn:population":0,
    "gn:timezone":"Asia/Yangon",
    "iso:country":"MM",
    "wof:name":"Tauko",
    "wof:placetype":"locality"
},
  "geometry": {"coordinates":[95.18992,26.62788],"type":"Point"}
}