{
  "type": "Feature",
  "properties": {
    "gn:admin1_code":"3.0",
    "gn:admin2_code":"MMR017D002",
    "gn:admin3_code":"MMR017011",
    "gn:asciiname":"Kanaung",
    "gn:country_code":"MM",
    "gn:dem":25,
    "gn:feature_class":"P",
    "gn:feature_code":"PPL",
    "gn:name":"Kanaung",
    "gn:population":0,
    "gn:timezone":"Asia/Yangon",
    "iso:country":"MM",
    "name:mya_x_preferred":[
        "\u1000\u1014\u1031\u102c\u1004\u103a\u1019\u103c\u102d\u102f\u1037"
    ],
    "name:tha_x_preferred":[
        "\u0e01\u0e30\u0e19\u0e2d\u0e07"
    ],
    "name:und_x_variant":[
        "Kanaunggale",
        "Kanoung",
        "Kanaung"
    ],
    "wof:name":"Kanaung",
    "wof:placetype":"locality"
},
  "geometry": {"coordinates":[95.38164999999999,18.2168],"type":"Point"}
}