{
  "type": "Feature",
  "properties": {
    "gn:admin1_code":"10.0",
    "gn:admin2_code":"MMR005D004",
    "gn:admin3_code":"MMR005022",
    "gn:asciiname":"Sinchidaing",
    "gn:country_code":"MM",
    "gn:dem":85,
    "gn:feature_class":"P",
    "gn:feature_code":"PPL",
    "gn:name":"Sinchidaing",
    "gn:population":0,
    "gn:timezone":"Asia/Yangon",
    "iso:country":"MM",
    "wof:name":"Sinchidaing",
    "wof:placetype":"locality"
},
  "geometry": {"coordinates":[96.04825,23.65184],"type":"Point"}
}