{
  "type": "Feature",
  "properties": {
    "gn:admin1_code":"8.0",
    "gn:admin2_code":"MMR010D006",
    "gn:admin3_code":"MMR010023",
    "gn:asciiname":"Byingat",
    "gn:country_code":"MM",
    "gn:dem":245,
    "gn:feature_class":"P",
    "gn:feature_code":"PPL",
    "gn:name":"Byingat",
    "gn:population":0,
    "gn:timezone":"Asia/Yangon",
    "iso:country":"MM",
    "wof:name":"Byingat",
    "wof:placetype":"locality"
},
  "geometry": {"coordinates":[96.24420000000001,20.41527],"type":"Point"}
}