{
  "type": "Feature",
  "properties": {
    "gn:admin1_code":"11.0",
    "gn:admin2_code":"MMR015D002",
    "gn:admin3_code":"MMR015010",
    "gn:asciiname":"Man Namhsong",
    "gn:country_code":"MM",
    "gn:dem":1305,
    "gn:feature_class":"P",
    "gn:feature_code":"PPL",
    "gn:name":"M\u0101n Namhsong",
    "gn:population":0,
    "gn:timezone":"Asia/Yangon",
    "iso:country":"MM",
    "wof:name":"Man Namhsong",
    "wof:placetype":"locality"
},
  "geometry": {"coordinates":[97.53034,23.54909],"type":"Point"}
}