{
  "type": "Feature",
  "properties": {
    "gn:admin1_code":"8.0",
    "gn:admin2_code":"MMR010D006",
    "gn:admin3_code":"MMR010024",
    "gn:asciiname":"Ketlangyin",
    "gn:country_code":"MM",
    "gn:dem":296,
    "gn:feature_class":"P",
    "gn:feature_code":"PPL",
    "gn:name":"Ketlangyin",
    "gn:population":0,
    "gn:timezone":"Asia/Yangon",
    "iso:country":"MM",
    "wof:name":"Ketlangyin",
    "wof:placetype":"locality"
},
  "geometry": {"coordinates":[95.78561000000001,20.58923],"type":"Point"}
}