{
  "type": "Feature",
  "properties": {
    "gn:admin1_code":"11.0",
    "gn:admin2_code":"MMR015D003",
    "gn:admin3_code":"MMR015013",
    "gn:asciiname":"Pang-yu",
    "gn:country_code":"MM",
    "gn:dem":1054,
    "gn:feature_class":"P",
    "gn:feature_code":"PPL",
    "gn:name":"Pang-yu",
    "gn:population":0,
    "gn:timezone":"Asia/Yangon",
    "iso:country":"MM",
    "name:und_x_variant":[
        "Pang-ye",
        "Pang-yu"
    ],
    "wof:name":"Pang-yu",
    "wof:placetype":"locality"
},
  "geometry": {"coordinates":[96.61306,22.4449],"type":"Point"}
}