{
  "type": "Feature",
  "properties": {
    "gn:admin1_code":"4.0",
    "gn:admin2_code":"MMR001D004",
    "gn:admin3_code":"MMR001018",
    "gn:asciiname":"Laja",
    "gn:country_code":"MM",
    "gn:dem":1306,
    "gn:feature_class":"P",
    "gn:feature_code":"PPL",
    "gn:name":"Laja",
    "gn:population":0,
    "gn:timezone":"Asia/Yangon",
    "iso:country":"MM",
    "name:bre_x_preferred":[
        "Laja"
    ],
    "name:ceb_x_preferred":[
        "Laja"
    ],
    "name:deu_x_preferred":[
        "Laja"
    ],
    "name:eus_x_preferred":[
        "Laja"
    ],
    "name:fra_x_preferred":[
        "Laja"
    ],
    "name:ita_x_preferred":[
        "Laja"
    ],
    "name:nld_x_preferred":[
        "Laja"
    ],
    "name:pol_x_preferred":[
        "Laja"
    ],
    "name:por_x_preferred":[
        "Laja"
    ],
    "name:spa_x_preferred":[
        "Laja"
    ],
    "name:swe_x_preferred":[
        "Laja"
    ],
    "wof:name":"Laja",
    "wof:placetype":"locality"
},
  "geometry": {"coordinates":[98.15527,26.8915],"type":"Point"}
}