{
  "type": "Feature",
  "properties": {
    "gn:admin1_code":"11.0",
    "gn:admin2_code":"MMR014D002",
    "gn:admin3_code":"MMR014013",
    "gn:asciiname":"Wan Kang",
    "gn:country_code":"MM",
    "gn:dem":960,
    "gn:feature_class":"P",
    "gn:feature_code":"PPL",
    "gn:name":"W\u0101n Kang",
    "gn:population":0,
    "gn:timezone":"Asia/Yangon",
    "iso:country":"MM",
    "name:und_x_variant":[
        "An Kang",
        "W\u0101n Kang"
    ],
    "wof:name":"Wan Kang",
    "wof:placetype":"locality"
},
  "geometry": {"coordinates":[98.01884,20.87372],"type":"Point"}
}