{
  "type": "Feature",
  "properties": {
    "gn:admin1_code":"10.0",
    "gn:admin2_code":"MMR005D001",
    "gn:admin3_code":"MMR005001",
    "gn:asciiname":"Monnyo",
    "gn:country_code":"MM",
    "gn:dem":93,
    "gn:feature_class":"P",
    "gn:feature_code":"PPL",
    "gn:name":"Monnyo",
    "gn:population":0,
    "gn:timezone":"Asia/Yangon",
    "iso:country":"MM",
    "wof:name":"Monnyo",
    "wof:placetype":"locality"
},
  "geometry": {"coordinates":[95.87942,22.12498],"type":"Point"}
}