{
  "type": "Feature",
  "properties": {
    "gn:admin1_code":"16.0",
    "gn:admin2_code":"MMR007D002",
    "gn:admin3_code":"MMR007014",
    "gn:asciiname":"Thetkegon",
    "gn:country_code":"MM",
    "gn:dem":31,
    "gn:feature_class":"P",
    "gn:feature_code":"PPL",
    "gn:name":"Thetkegon",
    "gn:population":0,
    "gn:timezone":"Asia/Yangon",
    "iso:country":"MM",
    "wof:name":"Thetkegon",
    "wof:placetype":"locality"
},
  "geometry": {"coordinates":[96.54075,18.63644],"type":"Point"}
}