{
  "type": "Feature",
  "properties": {
    "gn:admin1_code":"4.0",
    "gn:admin2_code":"MMR001D001",
    "gn:admin3_code":"MMR001001",
    "gn:asciiname":"Radhapur",
    "gn:country_code":"MM",
    "gn:dem":146,
    "gn:feature_class":"P",
    "gn:feature_code":"PPL",
    "gn:name":"Radhapur",
    "gn:population":0,
    "gn:timezone":"Asia/Yangon",
    "iso:country":"MM",
    "wof:name":"Radhapur",
    "wof:placetype":"locality"
},
  "geometry": {"coordinates":[97.39539000000001,25.42224],"type":"Point"}
}