{
  "type": "Feature",
  "properties": {
    "gn:admin1_code":"11.0",
    "gn:admin2_code":"MMR015D001",
    "gn:admin3_code":"MMR015004",
    "gn:asciiname":"Moeng Pat",
    "gn:country_code":"MM",
    "gn:dem":952,
    "gn:feature_class":"P",
    "gn:feature_code":"PPL",
    "gn:name":"M\u00f6ng Pat",
    "gn:population":0,
    "gn:timezone":"Asia/Yangon",
    "iso:country":"MM",
    "name:und_x_variant":[
        "Mong Pa",
        "M\u00f6ng Pat"
    ],
    "wof:name":"Moeng Pat",
    "wof:placetype":"locality"
},
  "geometry": {"coordinates":[98.07505999999999,22.52789],"type":"Point"}
}