{
  "type": "Feature",
  "properties": {
    "gn:admin1_code":"1.0",
    "gn:admin2_code":"MMR012D002",
    "gn:admin3_code":"MMR012010",
    "gn:asciiname":"Prinkhaung",
    "gn:country_code":"MM",
    "gn:dem":11,
    "gn:feature_class":"P",
    "gn:feature_code":"PPL",
    "gn:name":"Prinkhaung",
    "gn:population":0,
    "gn:timezone":"Asia/Yangon",
    "iso:country":"MM",
    "wof:name":"Prinkhaung",
    "wof:placetype":"locality"
},
  "geometry": {"coordinates":[92.45556000000001,21.01701],"type":"Point"}
}