{
  "type": "Feature",
  "properties": {
    "gn:admin1_code":"11.0",
    "gn:admin2_code":"MMR016D003",
    "gn:admin3_code":"MMR016009",
    "gn:asciiname":"Wan Hsenkem",
    "gn:country_code":"MM",
    "gn:dem":886,
    "gn:feature_class":"P",
    "gn:feature_code":"PPL",
    "gn:name":"W\u0101n Hsenk\u0113m",
    "gn:population":0,
    "gn:timezone":"Asia/Yangon",
    "iso:country":"MM",
    "wof:name":"Wan Hsenkem",
    "wof:placetype":"locality"
},
  "geometry": {"coordinates":[100.23935,20.84918],"type":"Point"}
}