{
  "type": "Feature",
  "properties": {
    "gn:admin1_code":"3.0",
    "gn:admin2_code":"MMR017D005",
    "gn:admin3_code":"MMR017021",
    "gn:asciiname":"Wedaung Apyin",
    "gn:country_code":"MM",
    "gn:dem":2,
    "gn:feature_class":"P",
    "gn:feature_code":"PPL",
    "gn:name":"Wedaung Apyin",
    "gn:population":0,
    "gn:timezone":"Asia/Yangon",
    "iso:country":"MM",
    "wof:name":"Wedaung Apyin",
    "wof:placetype":"locality"
},
  "geometry": {"coordinates":[95.68352,17.06607],"type":"Point"}
}