{
  "type": "Feature",
  "properties": {
    "gn:admin1_code":"15.0",
    "gn:admin2_code":"MMR009D005",
    "gn:admin3_code":"MMR009024",
    "gn:asciiname":"Thanle",
    "gn:country_code":"MM",
    "gn:dem":581,
    "gn:feature_class":"P",
    "gn:feature_code":"PPL",
    "gn:name":"Thanl\u00e8",
    "gn:population":0,
    "gn:timezone":"Asia/Yangon",
    "iso:country":"MM",
    "wof:name":"Thanle",
    "wof:placetype":"locality"
},
  "geometry": {"coordinates":[94.29045000000001,21.69279],"type":"Point"}
}