{
  "type": "Feature",
  "properties": {
    "gn:admin1_code":"6.0",
    "gn:admin2_code":"MMR002D002",
    "gn:admin3_code":"MMR002006",
    "gn:asciiname":"Nammawkom",
    "gn:country_code":"MM",
    "gn:dem":114,
    "gn:feature_class":"P",
    "gn:feature_code":"PPL",
    "gn:name":"Nammawkom",
    "gn:population":0,
    "gn:timezone":"Asia/Yangon",
    "iso:country":"MM",
    "name:und_x_variant":[
        "Nammaukom",
        "Nammawkom"
    ],
    "wof:name":"Nammawkom",
    "wof:placetype":"locality"
},
  "geometry": {"coordinates":[97.31377999999999,18.85386],"type":"Point"}
}