{
  "type": "Feature",
  "properties": {
    "gn:admin1_code":"6.0",
    "gn:admin2_code":"MMR002D002",
    "gn:admin3_code":"MMR002007",
    "gn:asciiname":"Mese Auk",
    "gn:country_code":"MM",
    "gn:dem":547,
    "gn:feature_class":"P",
    "gn:feature_code":"PPL",
    "gn:name":"M\u00e8s\u00e8 Auk",
    "gn:population":0,
    "gn:timezone":"Asia/Yangon",
    "iso:country":"MM",
    "wof:name":"Mese Auk",
    "wof:placetype":"locality"
},
  "geometry": {"coordinates":[97.69477999999999,18.60659],"type":"Point"}
}