{
  "type": "Feature",
  "properties": {
    "gn:admin1_code":"1.0",
    "gn:admin2_code":"MMR012D003",
    "gn:admin3_code":"MMR012014",
    "gn:asciiname":"Ale Kodu",
    "gn:country_code":"MM",
    "gn:dem":49,
    "gn:feature_class":"P",
    "gn:feature_code":"PPL",
    "gn:name":"Al\u0113 Kodu",
    "gn:population":0,
    "gn:timezone":"Asia/Yangon",
    "iso:country":"MM",
    "name:und_x_variant":[
        "Kodu",
        "Al\u0113 Kodu"
    ],
    "wof:name":"Ale Kodu",
    "wof:placetype":"locality"
},
  "geometry": {"coordinates":[93.98885,19.90406],"type":"Point"}
}