{
  "type": "Feature",
  "properties": {
    "gn:admin1_code":"16.0",
    "gn:admin2_code":"MMR007D001",
    "gn:admin3_code":"MMR007004",
    "gn:asciiname":"Hpalauk Myauk",
    "gn:country_code":"MM",
    "gn:dem":8,
    "gn:feature_class":"P",
    "gn:feature_code":"PPL",
    "gn:name":"Hpalauk Myauk",
    "gn:population":0,
    "gn:timezone":"Asia/Yangon",
    "iso:country":"MM",
    "wof:name":"Hpalauk Myauk",
    "wof:placetype":"locality"
},
  "geometry": {"coordinates":[96.6405,17.60249],"type":"Point"}
}