{
  "type": "Feature",
  "properties": {
    "gn:admin1_code":"16.0",
    "gn:admin2_code":"MMR008D001",
    "gn:admin3_code":"MMR008003",
    "gn:asciiname":"Tonkin",
    "gn:country_code":"MM",
    "gn:dem":46,
    "gn:feature_class":"P",
    "gn:feature_code":"PPL",
    "gn:name":"Tonkin",
    "gn:population":0,
    "gn:timezone":"Asia/Yangon",
    "iso:country":"MM",
    "name:ara_x_preferred":[
        "\u062a\u0648\u0646\u0643\u064a\u0646"
    ],
    "name:bel_x_preferred":[
        "\u0411\u0430\u043a\u0431\u043e"
    ],
    "name:bre_x_preferred":[
        "Tonkin"
    ],
    "name:cat_x_preferred":[
        "Tonqu\u00edn"
    ],
    "name:ces_x_preferred":[
        "Tonkin"
    ],
    "name:dan_x_preferred":[
        "Tonkin"
    ],
    "name:deu_x_preferred":[
        "Tonkin"
    ],
    "name:ell_x_preferred":[
        "\u03a4\u03bf\u03bd\u03ba\u03af\u03bd\u03bf"
    ],
    "name:epo_x_preferred":[
        "Tonkino"
    ],
    "name:eus_x_preferred":[
        "Tonkin"
    ],
    "name:fin_x_preferred":[
        "Tonkin"
    ],
    "name:fra_x_preferred":[
        "Tonkin"
    ],
    "name:glg_x_preferred":[
        "Tonk\u00edn"
    ],
    "name:heb_x_preferred":[
        "\u05d8\u05d5\u05e0\u05e7\u05d9\u05df"
    ],
    "name:hin_x_preferred":[
        "\u0924\u094b\u0902\u0915\u093f\u0928"
    ],
    "name:ind_x_preferred":[
        "Tonkin"
    ],
    "name:ita_x_preferred":[
        "Tonchino"
    ],
    "name:jpn_x_preferred":[
        "\u30c8\u30f3\u30ad\u30f3"
    ],
    "name:khm_x_preferred":[
        "\u178f\u17bb\u1784\u1780\u17b9\u1784"
    ],
    "name:msa_x_preferred":[
        "Tonkin"
    ],
    "name:nor_x_preferred":[
        "Tonkin"
    ],
    "name:pol_x_preferred":[
        "Tonkin"
    ],
    "name:por_x_preferred":[
        "Tonquim"
    ],
    "name:ron_x_preferred":[
        "Tonkin"
    ],
    "name:rus_x_preferred":[
        "\u0411\u0430\u043a\u0431\u043e"
    ],
    "name:slk_x_preferred":[
        "Tonkin"
    ],
    "name:swe_x_preferred":[
        "Tonkin"
    ],
    "name:tha_x_preferred":[
        "\u0e15\u0e31\u0e07\u0e40\u0e01\u0e35\u0e4b\u0e22"
    ],
    "name:zho_x_preferred":[
        "\u4e1c\u4eac"
    ],
    "wof:name":"Tonkin",
    "wof:placetype":"locality"
},
  "geometry": {"coordinates":[95.03194999999999,18.456],"type":"Point"}
}