{
  "type": "Feature",
  "properties": {
    "gn:admin1_code":"16.0",
    "gn:admin2_code":"MMR007D001",
    "gn:admin3_code":"MMR007008",
    "gn:asciiname":"Htiphado",
    "gn:country_code":"MM",
    "gn:dem":141,
    "gn:feature_class":"P",
    "gn:feature_code":"PPL",
    "gn:name":"Htiphado",
    "gn:population":0,
    "gn:timezone":"Asia/Yangon",
    "iso:country":"MM",
    "name:und_x_variant":[
        "Tipad\u00f4n",
        "Htiphado"
    ],
    "wof:name":"Htiphado",
    "wof:placetype":"locality"
},
  "geometry": {"coordinates":[97.12851999999999,17.71795],"type":"Point"}
}