{
  "type": "Feature",
  "properties": {
    "gn:admin1_code":"5.0",
    "gn:admin2_code":"MMR003D004",
    "gn:admin3_code":"MMR003003",
    "gn:asciiname":"Sisukhi",
    "gn:country_code":"MM",
    "gn:dem":1152,
    "gn:feature_class":"P",
    "gn:feature_code":"PPL",
    "gn:name":"Sisukhi",
    "gn:population":0,
    "gn:timezone":"Asia/Yangon",
    "iso:country":"MM",
    "wof:name":"Sisukhi",
    "wof:placetype":"locality"
},
  "geometry": {"coordinates":[97.06207000000001,18.59158],"type":"Point"}
}