{
  "type": "Feature",
  "properties": {
    "gn:admin1_code":"17.0",
    "gn:admin2_code":"MMR013D003",
    "gn:admin3_code":"MMR013028",
    "gn:asciiname":"Kyagan",
    "gn:country_code":"MM",
    "gn:dem":5,
    "gn:feature_class":"P",
    "gn:feature_code":"PPL",
    "gn:name":"Kyagan",
    "gn:population":0,
    "gn:timezone":"Asia/Yangon",
    "iso:country":"MM",
    "name:und_x_variant":[
        "Kyag\u00f4n",
        "Kyagan"
    ],
    "wof:name":"Kyagan",
    "wof:placetype":"locality"
},
  "geometry": {"coordinates":[96.09619000000001,16.60782],"type":"Point"}
}