{
  "type": "Feature",
  "properties": {
    "gn:admin1_code":"5.0",
    "gn:admin2_code":"MMR003D001",
    "gn:admin3_code":"MMR003004",
    "gn:asciiname":"Zindainggale",
    "gn:country_code":"MM",
    "gn:dem":419,
    "gn:feature_class":"P",
    "gn:feature_code":"PPL",
    "gn:name":"Zindainggale",
    "gn:population":0,
    "gn:timezone":"Asia/Yangon",
    "iso:country":"MM",
    "wof:name":"Zindainggale",
    "wof:placetype":"locality"
},
  "geometry": {"coordinates":[96.7529,18.7178],"type":"Point"}
}