{
  "type": "Feature",
  "properties": {
    "gn:admin1_code":"11.0",
    "gn:admin2_code":"MMR014D002",
    "gn:admin3_code":"MMR014015",
    "gn:asciiname":"Wan Peng",
    "gn:country_code":"MM",
    "gn:dem":901,
    "gn:feature_class":"P",
    "gn:feature_code":"PPL",
    "gn:name":"W\u0101n P\u00ebng",
    "gn:population":0,
    "gn:timezone":"Asia/Yangon",
    "iso:country":"MM",
    "wof:name":"Wan Peng",
    "wof:placetype":"locality"
},
  "geometry": {"coordinates":[98.16471,21.4755],"type":"Point"}
}