{
  "type": "Feature",
  "properties": {
    "gn:admin1_code":"6.0",
    "gn:admin2_code":"MMR002D001",
    "gn:admin3_code":"MMR002001",
    "gn:asciiname":"Dawlaw-kle",
    "gn:country_code":"MM",
    "gn:dem":699,
    "gn:feature_class":"P",
    "gn:feature_code":"PPL",
    "gn:name":"Dawlaw-kl\u00e8",
    "gn:population":0,
    "gn:timezone":"Asia/Yangon",
    "iso:country":"MM",
    "wof:name":"Dawlaw-kle",
    "wof:placetype":"locality"
},
  "geometry": {"coordinates":[97.32268999999999,19.88391],"type":"Point"}
}