{
  "type": "Feature",
  "properties": {
    "gn:admin1_code":"11.0",
    "gn:admin2_code":"MMR015D003",
    "gn:admin3_code":"MMR015014",
    "gn:asciiname":"Koenghsatapi",
    "gn:country_code":"MM",
    "gn:dem":900,
    "gn:feature_class":"P",
    "gn:feature_code":"PPL",
    "gn:name":"K\u00f6nghsatapi",
    "gn:population":0,
    "gn:timezone":"Asia/Yangon",
    "iso:country":"MM",
    "name:und_x_variant":[
        "K\u00f6nghs\u0101-ta-pa",
        "K\u00f6nghsatapi"
    ],
    "wof:name":"Koenghsatapi",
    "wof:placetype":"locality"
},
  "geometry": {"coordinates":[97.41036,22.15013],"type":"Point"}
}