{
  "type": "Feature",
  "properties": {
    "gn:admin1_code":"10.0",
    "gn:admin2_code":"MMR005D007",
    "gn:admin3_code":"MMR005032",
    "gn:asciiname":"Kundaw",
    "gn:country_code":"MM",
    "gn:dem":122,
    "gn:feature_class":"P",
    "gn:feature_code":"PPL",
    "gn:name":"Kundaw",
    "gn:population":0,
    "gn:timezone":"Asia/Yangon",
    "iso:country":"MM",
    "name:und_x_variant":[
        "Kuntaw",
        "Kundaw"
    ],
    "wof:name":"Kundaw",
    "wof:placetype":"locality"
},
  "geometry": {"coordinates":[94.60489,24.09573],"type":"Point"}
}