{
  "type": "Feature",
  "properties": {
    "gn:admin1_code":"3.0",
    "gn:admin2_code":"MMR017D001",
    "gn:admin3_code":"MMR017004",
    "gn:asciiname":"Wagon",
    "gn:country_code":"MM",
    "gn:dem":14,
    "gn:feature_class":"P",
    "gn:feature_code":"PPL",
    "gn:name":"Wag\u00f4n",
    "gn:population":0,
    "gn:timezone":"Asia/Yangon",
    "iso:country":"MM",
    "name:cat_x_preferred":[
        "Vag\u00f3"
    ],
    "name:csb_x_preferred":[
        "F\u00f9rm\u00f3nka"
    ],
    "name:cym_x_preferred":[
        "Gambo"
    ],
    "name:dan_x_preferred":[
        "Vogn"
    ],
    "name:eml_x_preferred":[
        "C\u00e2r"
    ],
    "name:est_x_preferred":[
        "Vanker"
    ],
    "name:fas_x_preferred":[
        "\u06af\u0627\u0631\u06cc"
    ],
    "name:fin_x_preferred":[
        "Vankkuri"
    ],
    "name:fra_x_preferred":[
        "Chariot"
    ],
    "name:heb_x_preferred":[
        "\u05e7\u05e8\u05d5\u05df"
    ],
    "name:hun_x_preferred":[
        "Szek\u00e9r"
    ],
    "name:ido_x_preferred":[
        "Charioto"
    ],
    "name:ind_x_preferred":[
        "Wagon"
    ],
    "name:ita_x_preferred":[
        "Carro"
    ],
    "name:lat_x_preferred":[
        "Plaustrum"
    ],
    "name:nld_x_preferred":[
        "Wagen"
    ],
    "name:nno_x_preferred":[
        "Vogn"
    ],
    "name:pdc_x_preferred":[
        "Waage"
    ],
    "name:pol_x_preferred":[
        "Fura"
    ],
    "name:ron_x_preferred":[
        "C\u0103ru\u021b\u0103"
    ],
    "name:slv_x_preferred":[
        "Voz"
    ],
    "name:stq_x_preferred":[
        "Woain"
    ],
    "name:swe_x_preferred":[
        "Vagn"
    ],
    "name:tur_x_preferred":[
        "Araba"
    ],
    "name:ukr_x_preferred":[
        "\u0412\u0456\u0437"
    ],
    "name:uzb_x_preferred":[
        "Arava"
    ],
    "name:wln_x_preferred":[
        "Tch\u00e5r"
    ],
    "wof:name":"Wagon",
    "wof:placetype":"locality"
},
  "geometry": {"coordinates":[94.39512999999999,15.92206],"type":"Point"}
}