{
  "type": "Feature",
  "properties": {
    "gn:admin1_code":"11.0",
    "gn:admin2_code":"MMR016D003",
    "gn:admin3_code":"MMR016010",
    "gn:asciiname":"Wan Hsenlong",
    "gn:country_code":"MM",
    "gn:dem":1387,
    "gn:feature_class":"P",
    "gn:feature_code":"PPL",
    "gn:name":"W\u0101n Hsenl\u014dng",
    "gn:population":0,
    "gn:timezone":"Asia/Yangon",
    "iso:country":"MM",
    "wof:name":"Wan Hsenlong",
    "wof:placetype":"locality"
},
  "geometry": {"coordinates":[99.96380000000001,21.14278],"type":"Point"}
}