{
  "type": "Feature",
  "properties": {
    "gn:admin1_code":"5.0",
    "gn:admin2_code":"MMR003D001",
    "gn:admin3_code":"MMR003004",
    "gn:asciiname":"Tibuchi",
    "gn:country_code":"MM",
    "gn:dem":655,
    "gn:feature_class":"P",
    "gn:feature_code":"PPL",
    "gn:name":"Tibuchi",
    "gn:population":0,
    "gn:timezone":"Asia/Yangon",
    "iso:country":"MM",
    "name:und_x_variant":[
        "Thabuchi",
        "Tibuchi"
    ],
    "wof:name":"Tibuchi",
    "wof:placetype":"locality"
},
  "geometry": {"coordinates":[96.73125,19.13907],"type":"Point"}
}