{
  "type": "Feature",
  "properties": {
    "gn:admin1_code":"1.0",
    "gn:admin2_code":"MMR012D004",
    "gn:admin3_code":"MMR012015",
    "gn:asciiname":"Talinseik",
    "gn:country_code":"MM",
    "gn:dem":8,
    "gn:feature_class":"P",
    "gn:feature_code":"PPL",
    "gn:name":"Talinseik",
    "gn:population":0,
    "gn:timezone":"Asia/Yangon",
    "iso:country":"MM",
    "name:und_x_variant":[
        "Talinselk",
        "Talinseik"
    ],
    "wof:name":"Talinseik",
    "wof:placetype":"locality"
},
  "geometry": {"coordinates":[94.38686,18.46619],"type":"Point"}
}