{
  "type": "Feature",
  "properties": {
    "gn:admin1_code":"11.0",
    "gn:admin2_code":"MMR016D003",
    "gn:admin3_code":"MMR016011",
    "gn:asciiname":"Wan Hpya-longhkoen",
    "gn:country_code":"MM",
    "gn:dem":1012,
    "gn:feature_class":"P",
    "gn:feature_code":"PPL",
    "gn:name":"W\u0101n Hpya-l\u014dnghk\u00f6n",
    "gn:population":0,
    "gn:timezone":"Asia/Yangon",
    "iso:country":"MM",
    "wof:name":"Wan Hpya-longhkoen",
    "wof:placetype":"locality"
},
  "geometry": {"coordinates":[100.65000000000001,21.43333],"type":"Point"}
}