{
  "type": "Feature",
  "properties": {
    "gn:admin1_code":"8.0",
    "gn:admin2_code":"MMR010D007",
    "gn:admin3_code":"MMR010028",
    "gn:asciiname":"Kyabinin",
    "gn:country_code":"MM",
    "gn:dem":220,
    "gn:feature_class":"P",
    "gn:feature_code":"PPL",
    "gn:name":"Kyabinin",
    "gn:population":0,
    "gn:timezone":"Asia/Yangon",
    "iso:country":"MM",
    "wof:name":"Kyabinin",
    "wof:placetype":"locality"
},
  "geometry": {"coordinates":[95.88961,20.77648],"type":"Point"}
}