{
  "type": "Feature",
  "properties": {
    "gn:admin1_code":"10.0",
    "gn:admin2_code":"MMR005D002",
    "gn:admin3_code":"MMR005011",
    "gn:asciiname":"Inywa",
    "gn:country_code":"MM",
    "gn:dem":291,
    "gn:feature_class":"P",
    "gn:feature_code":"PPL",
    "gn:name":"Inywa",
    "gn:population":0,
    "gn:timezone":"Asia/Yangon",
    "iso:country":"MM",
    "wof:name":"Inywa",
    "wof:placetype":"locality"
},
  "geometry": {"coordinates":[94.99894999999999,23.17105],"type":"Point"}
}