{
  "type": "Feature",
  "properties": {
    "gn:admin1_code":"11.0",
    "gn:admin2_code":"MMR014D001",
    "gn:admin3_code":"MMR014001",
    "gn:asciiname":"Nawngsang",
    "gn:country_code":"MM",
    "gn:dem":1001,
    "gn:feature_class":"P",
    "gn:feature_code":"PPL",
    "gn:name":"Nawngsang",
    "gn:population":0,
    "gn:timezone":"Asia/Yangon",
    "iso:country":"MM",
    "wof:name":"Nawngsang",
    "wof:placetype":"locality"
},
  "geometry": {"coordinates":[97.15488000000001,20.49351],"type":"Point"}
}