{
  "type": "Feature",
  "properties": {
    "gn:admin1_code":"1.0",
    "gn:admin2_code":"MMR012D003",
    "gn:admin3_code":"MMR012014",
    "gn:asciiname":"Lok-ywa",
    "gn:country_code":"MM",
    "gn:dem":4,
    "gn:feature_class":"P",
    "gn:feature_code":"PPL",
    "gn:name":"L\u00f4k-ywa",
    "gn:population":0,
    "gn:timezone":"Asia/Yangon",
    "iso:country":"MM",
    "wof:name":"Lok-ywa",
    "wof:placetype":"locality"
},
  "geometry": {"coordinates":[93.93088,19.60165],"type":"Point"}
}