{
  "type": "Feature",
  "properties": {
    "gn:admin1_code":"11.0",
    "gn:admin2_code":"MMR014D003",
    "gn:admin3_code":"MMR014020",
    "gn:asciiname":"Wan Kungpao",
    "gn:country_code":"MM",
    "gn:dem":555,
    "gn:feature_class":"P",
    "gn:feature_code":"PPL",
    "gn:name":"W\u0101n K\u016bngpao",
    "gn:population":0,
    "gn:timezone":"Asia/Yangon",
    "iso:country":"MM",
    "name:und_x_variant":[
        "W\u0101n K\u016bngnao",
        "W\u0101n K\u016bngpao"
    ],
    "wof:name":"Wan Kungpao",
    "wof:placetype":"locality"
},
  "geometry": {"coordinates":[97.61769,19.96811],"type":"Point"}
}