{
  "type": "Feature",
  "properties": {
    "gn:admin1_code":"2.0",
    "gn:admin2_code":"MMR004D002",
    "gn:admin3_code":"MMR004009",
    "gn:asciiname":"Lathton",
    "gn:country_code":"MM",
    "gn:dem":59,
    "gn:feature_class":"P",
    "gn:feature_code":"PPL",
    "gn:name":"Lathton",
    "gn:population":0,
    "gn:timezone":"Asia/Yangon",
    "iso:country":"MM",
    "wof:name":"Lathton",
    "wof:placetype":"locality"
},
  "geometry": {"coordinates":[93.19681,20.91273],"type":"Point"}
}