{
  "type": "Feature",
  "properties": {
    "gn:admin1_code":"16.0",
    "gn:admin2_code":"MMR007D002",
    "gn:admin3_code":"MMR007011",
    "gn:asciiname":"Mawlaw",
    "gn:country_code":"MM",
    "gn:dem":988,
    "gn:feature_class":"P",
    "gn:feature_code":"PPL",
    "gn:name":"Mawlaw",
    "gn:population":0,
    "gn:timezone":"Asia/Yangon",
    "iso:country":"MM",
    "name:und_x_variant":[
        "Malaw",
        "Mawlaw"
    ],
    "wof:name":"Mawlaw",
    "wof:placetype":"locality"
},
  "geometry": {"coordinates":[97.07395,18.2904],"type":"Point"}
}