{
  "type": "Feature",
  "properties": {
    "gn:admin1_code":"13.0",
    "gn:admin2_code":"MMR011D002",
    "gn:admin3_code":"MMR011010",
    "gn:asciiname":"Bakye",
    "gn:country_code":"MM",
    "gn:dem":71,
    "gn:feature_class":"P",
    "gn:feature_code":"PPL",
    "gn:name":"Bakye",
    "gn:population":0,
    "gn:timezone":"Asia/Yangon",
    "iso:country":"MM",
    "wof:name":"Bakye",
    "wof:placetype":"locality"
},
  "geometry": {"coordinates":[97.35473,17.38744],"type":"Point"}
}