{
  "type": "Feature",
  "properties": {
    "gn:admin1_code":"6.0",
    "gn:admin2_code":"MMR002D001",
    "gn:admin3_code":"MMR002001",
    "gn:asciiname":"Dawta-cha",
    "gn:country_code":"MM",
    "gn:dem":872,
    "gn:feature_class":"P",
    "gn:feature_code":"PPL",
    "gn:name":"Dawta-cha",
    "gn:population":0,
    "gn:timezone":"Asia/Yangon",
    "iso:country":"MM",
    "wof:name":"Dawta-cha",
    "wof:placetype":"locality"
},
  "geometry": {"coordinates":[97.27424999999999,19.64785],"type":"Point"}
}