{
  "type": "Feature",
  "properties": {
    "gn:admin1_code":"11.0",
    "gn:admin2_code":"MMR015D003",
    "gn:admin3_code":"MMR015019",
    "gn:asciiname":"Ho-it",
    "gn:country_code":"MM",
    "gn:dem":1969,
    "gn:feature_class":"P",
    "gn:feature_code":"PPL",
    "gn:name":"Ho-it",
    "gn:population":0,
    "gn:timezone":"Asia/Yangon",
    "iso:country":"MM",
    "wof:name":"Ho-it",
    "wof:placetype":"locality"
},
  "geometry": {"coordinates":[97.24654,23.31185],"type":"Point"}
}