{
  "type": "Feature",
  "properties": {
    "gn:admin1_code":"10.0",
    "gn:admin2_code":"MMR005D009",
    "gn:admin3_code":"MMR005017",
    "gn:asciiname":"Yinyein",
    "gn:country_code":"MM",
    "gn:dem":89,
    "gn:feature_class":"P",
    "gn:feature_code":"PPL",
    "gn:name":"Yiny\u00e8in",
    "gn:population":0,
    "gn:timezone":"Asia/Yangon",
    "iso:country":"MM",
    "wof:name":"Yinyein",
    "wof:placetype":"locality"
},
  "geometry": {"coordinates":[94.75776999999999,22.59773],"type":"Point"}
}