{
  "type": "Feature",
  "properties": {
    "gn:admin1_code":"11.0",
    "gn:admin2_code":"MMR014D002",
    "gn:admin3_code":"MMR014016",
    "gn:asciiname":"Konghai-ping",
    "gn:country_code":"MM",
    "gn:dem":1082,
    "gn:feature_class":"P",
    "gn:feature_code":"PPL",
    "gn:name":"Konghai-ping",
    "gn:population":0,
    "gn:timezone":"Asia/Yangon",
    "iso:country":"MM",
    "wof:name":"Konghai-ping",
    "wof:placetype":"locality"
},
  "geometry": {"coordinates":[97.58488,21.80575],"type":"Point"}
}