{
  "type": "Feature",
  "properties": {
    "gn:admin1_code":"10.0",
    "gn:admin2_code":"MMR005D008",
    "gn:admin3_code":"MMR005037",
    "gn:asciiname":"Kaha",
    "gn:country_code":"MM",
    "gn:dem":1078,
    "gn:feature_class":"P",
    "gn:feature_code":"PPL",
    "gn:name":"Kaha",
    "gn:population":0,
    "gn:timezone":"Asia/Yangon",
    "iso:country":"MM",
    "name:ceb_x_preferred":[
        "Kaha"
    ],
    "name:swe_x_preferred":[
        "Kaha"
    ],
    "wof:name":"Kaha",
    "wof:placetype":"locality"
},
  "geometry": {"coordinates":[95.74628,26.63418],"type":"Point"}
}