{
  "type": "Feature",
  "properties": {
    "gn:admin1_code":"15.0",
    "gn:admin2_code":"MMR009D004",
    "gn:admin3_code":"MMR009021",
    "gn:asciiname":"Kaingdawye",
    "gn:country_code":"MM",
    "gn:dem":153,
    "gn:feature_class":"P",
    "gn:feature_code":"PPL",
    "gn:name":"Kaingdawye",
    "gn:population":0,
    "gn:timezone":"Asia/Yangon",
    "iso:country":"MM",
    "wof:name":"Kaingdawye",
    "wof:placetype":"locality"
},
  "geometry": {"coordinates":[94.62387,21.31274],"type":"Point"}
}