{
  "type": "Feature",
  "properties": {
    "gn:admin1_code":"11.0",
    "gn:admin2_code":"MMR014D002",
    "gn:admin3_code":"MMR014013",
    "gn:asciiname":"Nayai",
    "gn:country_code":"MM",
    "gn:dem":1103,
    "gn:feature_class":"P",
    "gn:feature_code":"PPL",
    "gn:name":"N\u0101yai",
    "gn:population":0,
    "gn:timezone":"Asia/Yangon",
    "iso:country":"MM",
    "wof:name":"Nayai",
    "wof:placetype":"locality"
},
  "geometry": {"coordinates":[97.65098,20.60461],"type":"Point"}
}