{
  "type": "Feature",
  "properties": {
    "gn:admin1_code":"15.0",
    "gn:admin2_code":"MMR009D003",
    "gn:admin3_code":"MMR009013",
    "gn:asciiname":"Yedwinmyaung",
    "gn:country_code":"MM",
    "gn:dem":178,
    "gn:feature_class":"P",
    "gn:feature_code":"PPL",
    "gn:name":"Yedwinmyaung",
    "gn:population":0,
    "gn:timezone":"Asia/Yangon",
    "iso:country":"MM",
    "wof:name":"Yedwinmyaung",
    "wof:placetype":"locality"
},
  "geometry": {"coordinates":[95.00924999999999,19.74259],"type":"Point"}
}