{
  "type": "Feature",
  "properties": {
    "gn:admin1_code":"8.0",
    "gn:admin2_code":"MMR010D003",
    "gn:admin3_code":"MMR010015",
    "gn:asciiname":"Yauksauk",
    "gn:country_code":"MM",
    "gn:dem":98,
    "gn:feature_class":"P",
    "gn:feature_code":"PPL",
    "gn:name":"Yauksauk",
    "gn:population":0,
    "gn:timezone":"Asia/Yangon",
    "iso:country":"MM",
    "wof:name":"Yauksauk",
    "wof:placetype":"locality"
},
  "geometry": {"coordinates":[96.17494000000001,21.4387],"type":"Point"}
}