{
  "type": "Feature",
  "properties": {
    "gn:admin1_code":"4.0",
    "gn:admin2_code":"MMR001D001",
    "gn:admin3_code":"MMR001001",
    "gn:asciiname":"'Njumgahtawng",
    "gn:country_code":"MM",
    "gn:dem":685,
    "gn:feature_class":"P",
    "gn:feature_code":"PPL",
    "gn:name":"\u2019Njumgahtawng",
    "gn:population":0,
    "gn:timezone":"Asia/Yangon",
    "iso:country":"MM",
    "wof:name":"'Njumgahtawng",
    "wof:placetype":"locality"
},
  "geometry": {"coordinates":[97.36599,25.74812],"type":"Point"}
}