{
  "type": "Feature",
  "properties": {
    "gn:admin1_code":"11.0",
    "gn:admin2_code":"MMR014D002",
    "gn:admin3_code":"MMR014012",
    "gn:asciiname":"Hpongayin",
    "gn:country_code":"MM",
    "gn:dem":1031,
    "gn:feature_class":"P",
    "gn:feature_code":"PPL",
    "gn:name":"Hpongayin",
    "gn:population":0,
    "gn:timezone":"Asia/Yangon",
    "iso:country":"MM",
    "name:und_x_variant":[
        "Hpongsyin",
        "Hpongayin"
    ],
    "wof:name":"Hpongayin",
    "wof:placetype":"locality"
},
  "geometry": {"coordinates":[97.82080000000001,21.37726],"type":"Point"}
}