{
  "type": "Feature",
  "properties": {
    "gn:admin1_code":"11.0",
    "gn:admin2_code":"MMR015D001",
    "gn:admin3_code":"MMR015001",
    "gn:asciiname":"Poengga-taw",
    "gn:country_code":"MM",
    "gn:dem":513,
    "gn:feature_class":"P",
    "gn:feature_code":"PPL",
    "gn:name":"P\u00f6ngga-taw",
    "gn:population":0,
    "gn:timezone":"Asia/Yangon",
    "iso:country":"MM",
    "wof:name":"Poengga-taw",
    "wof:placetype":"locality"
},
  "geometry": {"coordinates":[97.55701000000001,22.74393],"type":"Point"}
}