{
  "type": "Feature",
  "properties": {
    "gn:admin1_code":"11.0",
    "gn:admin2_code":"MMR014D002",
    "gn:admin3_code":"MMR014015",
    "gn:asciiname":"Tanamu-nao",
    "gn:country_code":"MM",
    "gn:dem":1149,
    "gn:feature_class":"P",
    "gn:feature_code":"PPL",
    "gn:name":"Tanamu-nao",
    "gn:population":0,
    "gn:timezone":"Asia/Yangon",
    "iso:country":"MM",
    "wof:name":"Tanamu-nao",
    "wof:placetype":"locality"
},
  "geometry": {"coordinates":[97.96944000000001,21.59495],"type":"Point"}
}