{
  "type": "Feature",
  "properties": {
    "gn:admin1_code":"5.0",
    "gn:admin2_code":"MMR003D003",
    "gn:admin3_code":"MMR003006",
    "gn:asciiname":"Kyaukpya",
    "gn:country_code":"MM",
    "gn:dem":28,
    "gn:feature_class":"P",
    "gn:feature_code":"PPL",
    "gn:name":"Kyaukpya",
    "gn:population":0,
    "gn:timezone":"Asia/Yangon",
    "iso:country":"MM",
    "name:und_x_variant":[
        "Kyaukhpya",
        "Kyaukpya"
    ],
    "wof:name":"Kyaukpya",
    "wof:placetype":"locality"
},
  "geometry": {"coordinates":[98.03457,16.50978],"type":"Point"}
}