{
  "type": "Feature",
  "properties": {
    "gn:admin1_code":"11.0",
    "gn:admin2_code":"MMR014D001",
    "gn:admin3_code":"MMR014003",
    "gn:asciiname":"Nawng Pa Kin",
    "gn:country_code":"MM",
    "gn:dem":820,
    "gn:feature_class":"P",
    "gn:feature_code":"PPL",
    "gn:name":"Nawng Pa Kin",
    "gn:population":0,
    "gn:timezone":"Asia/Yangon",
    "iso:country":"MM",
    "wof:name":"Nawng Pa Kin",
    "wof:placetype":"locality"
},
  "geometry": {"coordinates":[97.1163,21.17497],"type":"Point"}
}