{
  "type": "Feature",
  "properties": {
    "gn:admin1_code":"11.0",
    "gn:admin2_code":"MMR014D001",
    "gn:admin3_code":"MMR014001",
    "gn:asciiname":"Lwetaw Kyaungna",
    "gn:country_code":"MM",
    "gn:dem":1116,
    "gn:feature_class":"P",
    "gn:feature_code":"PPL",
    "gn:name":"Lwetaw Kyaungna",
    "gn:population":0,
    "gn:timezone":"Asia/Yangon",
    "iso:country":"MM",
    "wof:name":"Lwetaw Kyaungna",
    "wof:placetype":"locality"
},
  "geometry": {"coordinates":[97.08528,20.97564],"type":"Point"}
}