{
  "type": "Feature",
  "properties": {
    "gn:admin1_code":"11.0",
    "gn:admin2_code":"MMR014D001",
    "gn:admin3_code":"MMR014010",
    "gn:asciiname":"Lapalun",
    "gn:country_code":"MM",
    "gn:dem":1212,
    "gn:feature_class":"P",
    "gn:feature_code":"PPL",
    "gn:name":"Lapalun",
    "gn:population":0,
    "gn:timezone":"Asia/Yangon",
    "iso:country":"MM",
    "wof:name":"Lapalun",
    "wof:placetype":"locality"
},
  "geometry": {"coordinates":[96.98112999999999,19.68488],"type":"Point"}
}