{
  "type": "Feature",
  "properties": {
    "gn:admin1_code":"17.0",
    "gn:admin2_code":"MMR013D004",
    "gn:admin3_code":"MMR013041",
    "gn:asciiname":"Sinyedwin",
    "gn:country_code":"MM",
    "gn:dem":13,
    "gn:feature_class":"P",
    "gn:feature_code":"PPL",
    "gn:name":"Sinyedwin",
    "gn:population":0,
    "gn:timezone":"Asia/Yangon",
    "iso:country":"MM",
    "wof:name":"Sinyedwin",
    "wof:placetype":"locality"
},
  "geometry": {"coordinates":[96.12851999999999,16.8329],"type":"Point"}
}