{
  "type": "Feature",
  "properties": {
    "gn:admin1_code":"13.0",
    "gn:admin2_code":"MMR011D002",
    "gn:admin3_code":"MMR011009",
    "gn:asciiname":"Kwingale",
    "gn:country_code":"MM",
    "gn:dem":20,
    "gn:feature_class":"P",
    "gn:feature_code":"PPL",
    "gn:name":"Kwingale",
    "gn:population":0,
    "gn:timezone":"Asia/Yangon",
    "iso:country":"MM",
    "wof:name":"Kwingale",
    "wof:placetype":"locality"
},
  "geometry": {"coordinates":[97.0031,17.36211],"type":"Point"}
}