{
  "type": "Feature",
  "properties": {
    "gn:admin1_code":"4.0",
    "gn:admin2_code":"MMR001D003",
    "gn:admin3_code":"MMR001013",
    "gn:asciiname":"Madang",
    "gn:country_code":"MM",
    "gn:dem":1012,
    "gn:feature_class":"P",
    "gn:feature_code":"PPL",
    "gn:name":"M\u0101dang",
    "gn:population":0,
    "gn:timezone":"Asia/Yangon",
    "iso:country":"MM",
    "name:ceb_x_preferred":[
        "Madang"
    ],
    "name:deu_x_preferred":[
        "Madang"
    ],
    "name:fas_x_preferred":[
        "\u0645\u0627\u062f\u0627\u0646\u06af"
    ],
    "name:fin_x_preferred":[
        "Madang"
    ],
    "name:fra_x_preferred":[
        "Madang"
    ],
    "name:glg_x_preferred":[
        "Madang"
    ],
    "name:heb_x_preferred":[
        "\u05de\u05d3\u05e0\u05d2"
    ],
    "name:ind_x_preferred":[
        "Madang"
    ],
    "name:ita_x_preferred":[
        "Madang"
    ],
    "name:jpn_x_preferred":[
        "\u30de\u30c0\u30f3"
    ],
    "name:kor_x_preferred":[
        "\ub9c8\ub2f9"
    ],
    "name:lit_x_preferred":[
        "Madangas"
    ],
    "name:nld_x_preferred":[
        "Madang"
    ],
    "name:pol_x_preferred":[
        "Madang"
    ],
    "name:por_x_preferred":[
        "Madang"
    ],
    "name:rus_x_preferred":[
        "\u041c\u0430\u0434\u0430\u043d\u0433"
    ],
    "name:spa_x_preferred":[
        "Madang"
    ],
    "name:swe_x_preferred":[
        "Madang"
    ],
    "name:tpi_x_preferred":[
        "Madang"
    ],
    "name:ukr_x_preferred":[
        "\u041c\u0430\u0434\u0430\u043d\u0433"
    ],
    "name:urd_x_preferred":[
        "\u0645\u0627\u062f\u0646\u06af"
    ],
    "wof:name":"Madang",
    "wof:placetype":"locality"
},
  "geometry": {"coordinates":[97.44422,24.05101],"type":"Point"}
}