{
  "type": "Feature",
  "properties": {
    "gn:admin1_code":"6.0",
    "gn:admin2_code":"MMR002D001",
    "gn:admin3_code":"MMR002001",
    "gn:asciiname":"Daw Kyi-ne",
    "gn:country_code":"MM",
    "gn:dem":874,
    "gn:feature_class":"P",
    "gn:feature_code":"PPL",
    "gn:name":"Daw Kyi-n\u00e8",
    "gn:population":0,
    "gn:timezone":"Asia/Yangon",
    "iso:country":"MM",
    "wof:name":"Daw Kyi-ne",
    "wof:placetype":"locality"
},
  "geometry": {"coordinates":[97.14663,19.71239],"type":"Point"}
}