{
  "type": "Feature",
  "properties": {
    "gn:admin1_code":"11.0",
    "gn:admin2_code":"MMR015D006",
    "gn:admin3_code":"MMR015008",
    "gn:asciiname":"Motlong",
    "gn:country_code":"MM",
    "gn:dem":799,
    "gn:feature_class":"P",
    "gn:feature_code":"PPL",
    "gn:name":"Motlong",
    "gn:population":0,
    "gn:timezone":"Asia/Yangon",
    "iso:country":"MM",
    "wof:name":"Motlong",
    "wof:placetype":"locality"
},
  "geometry": {"coordinates":[98.72580000000001,22.98987],"type":"Point"}
}