{
  "type": "Feature",
  "properties": {
    "gn:admin1_code":"16.0",
    "gn:admin2_code":"MMR008D002",
    "gn:admin3_code":"MMR008010",
    "gn:asciiname":"Teinhmyok",
    "gn:country_code":"MM",
    "gn:dem":38,
    "gn:feature_class":"P",
    "gn:feature_code":"PPL",
    "gn:name":"Teinhmyok",
    "gn:population":0,
    "gn:timezone":"Asia/Yangon",
    "iso:country":"MM",
    "wof:name":"Teinhmyok",
    "wof:placetype":"locality"
},
  "geometry": {"coordinates":[95.77968,18.12082],"type":"Point"}
}