{
  "type": "Feature",
  "properties": {
    "gn:admin1_code":"11.0",
    "gn:admin2_code":"MMR016D001",
    "gn:admin3_code":"MMR016002",
    "gn:asciiname":"Wan Panghso",
    "gn:country_code":"MM",
    "gn:dem":1638,
    "gn:feature_class":"P",
    "gn:feature_code":"PPL",
    "gn:name":"W\u0101n Panghso",
    "gn:population":0,
    "gn:timezone":"Asia/Yangon",
    "iso:country":"MM",
    "wof:name":"Wan Panghso",
    "wof:placetype":"locality"
},
  "geometry": {"coordinates":[99.38074,21.55453],"type":"Point"}
}