{
  "type": "Feature",
  "properties": {
    "gn:admin1_code":"4.0",
    "gn:admin2_code":"MMR001D003",
    "gn:admin3_code":"MMR001010",
    "gn:asciiname":"Walu",
    "gn:country_code":"MM",
    "gn:dem":422,
    "gn:feature_class":"P",
    "gn:feature_code":"PPL",
    "gn:name":"Walu",
    "gn:population":0,
    "gn:timezone":"Asia/Yangon",
    "iso:country":"MM",
    "name:ceb_x_preferred":[
        "Walu"
    ],
    "name:swe_x_preferred":[
        "Walu"
    ],
    "wof:name":"Walu",
    "wof:placetype":"locality"
},
  "geometry": {"coordinates":[96.95019000000001,23.90418],"type":"Point"}
}