{
  "type": "Feature",
  "properties": {
    "gn:admin1_code":"10.0",
    "gn:admin2_code":"MMR005D003",
    "gn:admin3_code":"MMR005013",
    "gn:asciiname":"Magyigan",
    "gn:country_code":"MM",
    "gn:dem":118,
    "gn:feature_class":"P",
    "gn:feature_code":"PPL",
    "gn:name":"Magyigan",
    "gn:population":0,
    "gn:timezone":"Asia/Yangon",
    "iso:country":"MM",
    "wof:name":"Magyigan",
    "wof:placetype":"locality"
},
  "geometry": {"coordinates":[94.97456,22.41029],"type":"Point"}
}