{
  "type": "Feature",
  "properties": {
    "gn:admin1_code":"8.0",
    "gn:admin2_code":"MMR010D007",
    "gn:admin3_code":"MMR010031",
    "gn:asciiname":"Thitpalwegan",
    "gn:country_code":"MM",
    "gn:dem":176,
    "gn:feature_class":"P",
    "gn:feature_code":"PPL",
    "gn:name":"Thitpalwegan",
    "gn:population":0,
    "gn:timezone":"Asia/Yangon",
    "iso:country":"MM",
    "wof:name":"Thitpalwegan",
    "wof:placetype":"locality"
},
  "geometry": {"coordinates":[95.90988,21.11421],"type":"Point"}
}