{
  "type": "Feature",
  "properties": {
    "gn:admin1_code":"10.0",
    "gn:admin2_code":"MMR005D003",
    "gn:admin3_code":"MMR005014",
    "gn:asciiname":"Yatha",
    "gn:country_code":"MM",
    "gn:dem":115,
    "gn:feature_class":"P",
    "gn:feature_code":"PPL",
    "gn:name":"Yatha",
    "gn:population":0,
    "gn:timezone":"Asia/Yangon",
    "iso:country":"MM",
    "wof:name":"Yatha",
    "wof:placetype":"locality"
},
  "geometry": {"coordinates":[95.58083999999999,22.13141],"type":"Point"}
}