{
  "type": "Feature",
  "properties": {
    "gn:admin1_code":"3.0",
    "gn:admin2_code":"MMR017D006",
    "gn:admin3_code":"MMR017024",
    "gn:asciiname":"Tamawa",
    "gn:country_code":"MM",
    "gn:dem":4,
    "gn:feature_class":"P",
    "gn:feature_code":"PPL",
    "gn:name":"Tam\u0101wa",
    "gn:population":0,
    "gn:timezone":"Asia/Yangon",
    "iso:country":"MM",
    "wof:name":"Tamawa",
    "wof:placetype":"locality"
},
  "geometry": {"coordinates":[95.54965,16.15477000000001],"type":"Point"}
}