{
  "type": "Feature",
  "properties": {
    "gn:admin1_code":"8.0",
    "gn:admin2_code":"MMR010D001",
    "gn:admin3_code":"MMR010004",
    "gn:asciiname":"Aungbinle",
    "gn:country_code":"MM",
    "gn:dem":79,
    "gn:feature_class":"P",
    "gn:feature_code":"PPL",
    "gn:name":"Aungbinle",
    "gn:population":0,
    "gn:timezone":"Asia/Yangon",
    "iso:country":"MM",
    "wof:name":"Aungbinle",
    "wof:placetype":"locality"
},
  "geometry": {"coordinates":[96.12672999999999,21.94661],"type":"Point"}
}