{
  "type": "Feature",
  "properties": {
    "gn:admin1_code":"10.0",
    "gn:admin2_code":"MMR005D004",
    "gn:admin3_code":"MMR005024",
    "gn:asciiname":"Panmaye",
    "gn:country_code":"MM",
    "gn:dem":172,
    "gn:feature_class":"P",
    "gn:feature_code":"PPL",
    "gn:name":"Panmaye",
    "gn:population":0,
    "gn:timezone":"Asia/Yangon",
    "iso:country":"MM",
    "wof:name":"Panmaye",
    "wof:placetype":"locality"
},
  "geometry": {"coordinates":[95.42192,23.55308],"type":"Point"}
}