{
  "type": "Feature",
  "properties": {
    "gn:admin1_code":"17.0",
    "gn:admin2_code":"MMR013D001",
    "gn:admin3_code":"MMR013004",
    "gn:asciiname":"Mokso-nyaungbin",
    "gn:country_code":"MM",
    "gn:dem":11,
    "gn:feature_class":"P",
    "gn:feature_code":"PPL",
    "gn:name":"Mokso-nyaungbin",
    "gn:population":0,
    "gn:timezone":"Asia/Yangon",
    "iso:country":"MM",
    "wof:name":"Mokso-nyaungbin",
    "wof:placetype":"locality"
},
  "geometry": {"coordinates":[96.24999,17.05787],"type":"Point"}
}