{
  "type": "Feature",
  "properties": {
    "gn:admin1_code":"16.0",
    "gn:admin2_code":"MMR007D002",
    "gn:admin3_code":"MMR007011",
    "gn:asciiname":"Kapetki",
    "gn:country_code":"MM",
    "gn:dem":767,
    "gn:feature_class":"P",
    "gn:feature_code":"PPL",
    "gn:name":"Kapetki",
    "gn:population":0,
    "gn:timezone":"Asia/Yangon",
    "iso:country":"MM",
    "wof:name":"Kapetki",
    "wof:placetype":"locality"
},
  "geometry": {"coordinates":[96.94781999999999,18.47302],"type":"Point"}
}