{
  "type": "Feature",
  "properties": {
    "gn:admin1_code":"15.0",
    "gn:admin2_code":"MMR009D001",
    "gn:admin3_code":"MMR009006",
    "gn:asciiname":"Kyauktaga",
    "gn:country_code":"MM",
    "gn:dem":306,
    "gn:feature_class":"P",
    "gn:feature_code":"PPL",
    "gn:name":"Kyauktaga",
    "gn:population":0,
    "gn:timezone":"Asia/Yangon",
    "iso:country":"MM",
    "wof:name":"Kyauktaga",
    "wof:placetype":"locality"
},
  "geometry": {"coordinates":[95.46277000000001,20.69937],"type":"Point"}
}