{
  "type": "Feature",
  "properties": {
    "gn:admin1_code":"8.0",
    "gn:admin2_code":"MMR010D005",
    "gn:admin3_code":"MMR010022",
    "gn:asciiname":"Pyawgan",
    "gn:country_code":"MM",
    "gn:dem":113,
    "gn:feature_class":"P",
    "gn:feature_code":"PPL",
    "gn:name":"Pyawgan",
    "gn:population":0,
    "gn:timezone":"Asia/Yangon",
    "iso:country":"MM",
    "wof:name":"Pyawgan",
    "wof:placetype":"locality"
},
  "geometry": {"coordinates":[95.06354,21.23898],"type":"Point"}
}