{
  "type": "Feature",
  "properties": {
    "gn:admin1_code":"16.0",
    "gn:admin2_code":"MMR007D001",
    "gn:admin3_code":"MMR007006",
    "gn:asciiname":"Letpandan",
    "gn:country_code":"MM",
    "gn:dem":47,
    "gn:feature_class":"P",
    "gn:feature_code":"PPL",
    "gn:name":"Letpandan",
    "gn:population":0,
    "gn:timezone":"Asia/Yangon",
    "iso:country":"MM",
    "name:und_x_variant":[
        "Letpadan",
        "Letpandan"
    ],
    "wof:name":"Letpandan",
    "wof:placetype":"locality"
},
  "geometry": {"coordinates":[96.53952,18.02722],"type":"Point"}
}