{
  "type": "Feature",
  "properties": {
    "gn:admin1_code":"11.0",
    "gn:admin2_code":"MMR014D003",
    "gn:admin3_code":"MMR014020",
    "gn:asciiname":"Wan Mak",
    "gn:country_code":"MM",
    "gn:dem":1084,
    "gn:feature_class":"P",
    "gn:feature_code":"PPL",
    "gn:name":"W\u0101n M\u0101k",
    "gn:population":0,
    "gn:timezone":"Asia/Yangon",
    "iso:country":"MM",
    "wof:name":"Wan Mak",
    "wof:placetype":"locality"
},
  "geometry": {"coordinates":[97.58056000000001,20.34022],"type":"Point"}
}