{
  "type": "Feature",
  "properties": {
    "gn:admin1_code":"12.0",
    "gn:admin2_code":"MMR006D002",
    "gn:admin3_code":"MMR006007",
    "gn:asciiname":"Minbyintein",
    "gn:country_code":"MM",
    "gn:dem":21,
    "gn:feature_class":"P",
    "gn:feature_code":"PPL",
    "gn:name":"Minbyintein",
    "gn:population":0,
    "gn:timezone":"Asia/Yangon",
    "iso:country":"MM",
    "wof:name":"Minbyintein",
    "wof:placetype":"locality"
},
  "geometry": {"coordinates":[98.65609000000001,12.96038],"type":"Point"}
}