{
  "type": "Feature",
  "properties": {
    "gn:admin1_code":"10.0",
    "gn:admin2_code":"MMR005D009",
    "gn:admin3_code":"MMR005019",
    "gn:asciiname":"Tane",
    "gn:country_code":"MM",
    "gn:dem":178,
    "gn:feature_class":"P",
    "gn:feature_code":"PPL",
    "gn:name":"Tan\u00e8",
    "gn:population":0,
    "gn:timezone":"Asia/Yangon",
    "iso:country":"MM",
    "name:ceb_x_preferred":[
        "Tane"
    ],
    "name:deu_x_preferred":[
        "Tane"
    ],
    "name:fra_x_preferred":[
        "Tane"
    ],
    "name:ita_x_preferred":[
        "Tane"
    ],
    "wof:name":"Tane",
    "wof:placetype":"locality"
},
  "geometry": {"coordinates":[94.77943999999999,21.85817],"type":"Point"}
}