{
  "type": "Feature",
  "properties": {
    "gn:admin1_code":"17.0",
    "gn:admin2_code":"MMR013D003",
    "gn:admin3_code":"MMR013028",
    "gn:asciiname":"Payani",
    "gn:country_code":"MM",
    "gn:dem":14,
    "gn:feature_class":"P",
    "gn:feature_code":"PPL",
    "gn:name":"Payani",
    "gn:population":0,
    "gn:timezone":"Asia/Yangon",
    "iso:country":"MM",
    "name:ara_x_preferred":[
        "\u0628\u0627\u064a\u0646\u064a"
    ],
    "name:fas_x_preferred":[
        "\u067e\u0627\u06cc\u0646\u06cc"
    ],
    "name:msa_x_preferred":[
        "Payani"
    ],
    "wof:name":"Payani",
    "wof:placetype":"locality"
},
  "geometry": {"coordinates":[95.95408,16.61788],"type":"Point"}
}