{
  "type": "Feature",
  "properties": {
    "gn:admin1_code":"8.0",
    "gn:admin2_code":"MMR010D003",
    "gn:admin3_code":"MMR010015",
    "gn:asciiname":"Kyunhla",
    "gn:country_code":"MM",
    "gn:dem":94,
    "gn:feature_class":"P",
    "gn:feature_code":"PPL",
    "gn:name":"Kyunhla",
    "gn:population":0,
    "gn:timezone":"Asia/Yangon",
    "iso:country":"MM",
    "name:mya_x_preferred":[
        "\u1000\u103b\u103d\u1014\u103a\u1038\u101c\u103e\u1019\u103c\u102d\u102f\u1037"
    ],
    "wof:name":"Kyunhla",
    "wof:placetype":"locality"
},
  "geometry": {"coordinates":[96.11731,21.45564],"type":"Point"}
}