{
  "type": "Feature",
  "properties": {
    "gn:admin1_code":"4.0",
    "gn:admin2_code":"MMR001D003",
    "gn:admin3_code":"MMR001011",
    "gn:asciiname":"Pankhongyang",
    "gn:country_code":"MM",
    "gn:dem":238,
    "gn:feature_class":"P",
    "gn:feature_code":"PPL",
    "gn:name":"Pankhongyang",
    "gn:population":0,
    "gn:timezone":"Asia/Yangon",
    "iso:country":"MM",
    "wof:name":"Pankhongyang",
    "wof:placetype":"locality"
},
  "geometry": {"coordinates":[96.89026,24.52952],"type":"Point"}
}