{
  "type": "Feature",
  "properties": {
    "gn:admin1_code":"16.0",
    "gn:admin2_code":"MMR008D002",
    "gn:admin3_code":"MMR008009",
    "gn:asciiname":"Anyadan",
    "gn:country_code":"MM",
    "gn:dem":32,
    "gn:feature_class":"P",
    "gn:feature_code":"PPL",
    "gn:name":"Anyadan",
    "gn:population":0,
    "gn:timezone":"Asia/Yangon",
    "iso:country":"MM",
    "wof:name":"Anyadan",
    "wof:placetype":"locality"
},
  "geometry": {"coordinates":[95.7225,17.89895],"type":"Point"}
}