{
  "type": "Feature",
  "properties": {
    "gn:admin1_code":"4.0",
    "gn:admin2_code":"MMR001D004",
    "gn:admin3_code":"MMR001014",
    "gn:asciiname":"Ndaung Ga",
    "gn:country_code":"MM",
    "gn:dem":509,
    "gn:feature_class":"P",
    "gn:feature_code":"PPL",
    "gn:name":"Ndaung Ga",
    "gn:population":0,
    "gn:timezone":"Asia/Yangon",
    "iso:country":"MM",
    "wof:name":"Ndaung Ga",
    "wof:placetype":"locality"
},
  "geometry": {"coordinates":[97.54984,27.13229],"type":"Point"}
}