{
  "type": "Feature",
  "properties": {
    "gn:admin1_code":"13.0",
    "gn:admin2_code":"MMR011D001",
    "gn:admin3_code":"MMR011003",
    "gn:asciiname":"Kawkadaik",
    "gn:country_code":"MM",
    "gn:dem":29,
    "gn:feature_class":"P",
    "gn:feature_code":"PPL",
    "gn:name":"Kawkadaik",
    "gn:population":0,
    "gn:timezone":"Asia/Yangon",
    "iso:country":"MM",
    "wof:name":"Kawkadaik",
    "wof:placetype":"locality"
},
  "geometry": {"coordinates":[97.54797000000001,16.27615],"type":"Point"}
}