{
  "type": "Feature",
  "properties": {
    "gn:admin1_code":"11.0",
    "gn:admin2_code":"MMR014D002",
    "gn:admin3_code":"MMR014015",
    "gn:asciiname":"Namhsong",
    "gn:country_code":"MM",
    "gn:dem":1006,
    "gn:feature_class":"P",
    "gn:feature_code":"PPL",
    "gn:name":"Namhsong",
    "gn:population":0,
    "gn:timezone":"Asia/Yangon",
    "iso:country":"MM",
    "name:und_x_variant":[
        "Namhsohg",
        "Namhsong"
    ],
    "wof:name":"Namhsong",
    "wof:placetype":"locality"
},
  "geometry": {"coordinates":[97.98587999999999,21.88336],"type":"Point"}
}