{
  "type": "Feature",
  "properties": {
    "gn:admin1_code":"11.0",
    "gn:admin2_code":"MMR014D001",
    "gn:admin3_code":"MMR014001",
    "gn:asciiname":"Nahi",
    "gn:country_code":"MM",
    "gn:dem":1316,
    "gn:feature_class":"P",
    "gn:feature_code":"PPL",
    "gn:name":"Nahi",
    "gn:population":0,
    "gn:timezone":"Asia/Yangon",
    "iso:country":"MM",
    "name:ceb_x_preferred":[
        "Nahi"
    ],
    "name:eus_x_preferred":[
        "Nahi"
    ],
    "name:swe_x_preferred":[
        "Nahi"
    ],
    "wof:name":"Nahi",
    "wof:placetype":"locality"
},
  "geometry": {"coordinates":[97.06562,20.52363],"type":"Point"}
}