{
  "type": "Feature",
  "properties": {
    "gn:admin1_code":"8.0",
    "gn:admin2_code":"MMR010D002",
    "gn:admin3_code":"MMR010008",
    "gn:asciiname":"Lema",
    "gn:country_code":"MM",
    "gn:dem":139,
    "gn:feature_class":"P",
    "gn:feature_code":"PPL",
    "gn:name":"Lema",
    "gn:population":0,
    "gn:timezone":"Asia/Yangon",
    "iso:country":"MM",
    "name:cat_x_preferred":[
        "Lema"
    ],
    "name:ceb_x_preferred":[
        "Lema"
    ],
    "name:deu_x_preferred":[
        "Lema"
    ],
    "name:eus_x_preferred":[
        "Lema"
    ],
    "name:glg_x_preferred":[
        "Lema"
    ],
    "name:ita_x_preferred":[
        "Lema"
    ],
    "name:por_x_preferred":[
        "Lema"
    ],
    "name:spa_x_preferred":[
        "Lema"
    ],
    "name:swe_x_preferred":[
        "Lema"
    ],
    "wof:name":"Lema",
    "wof:placetype":"locality"
},
  "geometry": {"coordinates":[96.49294,21.81849],"type":"Point"}
}