{
  "type": "Feature",
  "properties": {
    "gn:admin1_code":"10.0",
    "gn:admin2_code":"MMR005D003",
    "gn:admin3_code":"MMR005012",
    "gn:asciiname":"Kyweye",
    "gn:country_code":"MM",
    "gn:dem":84,
    "gn:feature_class":"P",
    "gn:feature_code":"PPL",
    "gn:name":"Kyw\u00e8y\u00e8",
    "gn:population":0,
    "gn:timezone":"Asia/Yangon",
    "iso:country":"MM",
    "wof:name":"Kyweye",
    "wof:placetype":"locality"
},
  "geometry": {"coordinates":[95.12336000000001,22.18858],"type":"Point"}
}