{
  "type": "Feature",
  "properties": {
    "gn:admin1_code":"17.0",
    "gn:admin2_code":"MMR013D001",
    "gn:admin3_code":"MMR013005",
    "gn:asciiname":"Taikkyi",
    "gn:country_code":"MM",
    "gn:dem":21,
    "gn:feature_class":"P",
    "gn:feature_code":"PPL",
    "gn:name":"Taikkyi",
    "gn:population":0,
    "gn:timezone":"Asia/Yangon",
    "iso:country":"MM",
    "wof:name":"Taikkyi",
    "wof:placetype":"locality"
},
  "geometry": {"coordinates":[95.96293,17.31439],"type":"Point"}
}