{
  "type": "Feature",
  "properties": {
    "gn:admin1_code":"11.0",
    "gn:admin2_code":"MMR015D007",
    "gn:admin3_code":"MMR015005",
    "gn:asciiname":"Hpa-ku-lam",
    "gn:country_code":"MM",
    "gn:dem":1168,
    "gn:feature_class":"P",
    "gn:feature_code":"PPL",
    "gn:name":"Hpa-ku-lam",
    "gn:population":0,
    "gn:timezone":"Asia/Yangon",
    "iso:country":"MM",
    "wof:name":"Hpa-ku-lam",
    "wof:placetype":"locality"
},
  "geometry": {"coordinates":[98.69246,22.72617],"type":"Point"}
}