{
  "type": "Feature",
  "properties": {
    "gn:admin1_code":"11.0",
    "gn:admin2_code":"MMR014D001",
    "gn:admin3_code":"MMR014001",
    "gn:asciiname":"Shwenyaung",
    "gn:country_code":"MM",
    "gn:dem":899,
    "gn:feature_class":"P",
    "gn:feature_code":"PPL",
    "gn:name":"Shwenyaung",
    "gn:population":0,
    "gn:timezone":"Asia/Yangon",
    "iso:country":"MM",
    "name:und_x_variant":[
        "Shwanyaung",
        "Shwenyaung"
    ],
    "wof:name":"Shwenyaung",
    "wof:placetype":"locality"
},
  "geometry": {"coordinates":[96.94379000000001,20.76437],"type":"Point"}
}