{
  "type": "Feature",
  "properties": {
    "gn:admin1_code":"10.0",
    "gn:admin2_code":"MMR005D003",
    "gn:admin3_code":"MMR005013",
    "gn:asciiname":"Yondaw",
    "gn:country_code":"MM",
    "gn:dem":111,
    "gn:feature_class":"P",
    "gn:feature_code":"PPL",
    "gn:name":"Yondaw",
    "gn:population":0,
    "gn:timezone":"Asia/Yangon",
    "iso:country":"MM",
    "wof:name":"Yondaw",
    "wof:placetype":"locality"
},
  "geometry": {"coordinates":[95.14686,22.30843],"type":"Point"}
}