{
  "type": "Feature",
  "properties": {
    "gn:admin1_code":"12.0",
    "gn:admin2_code":"MMR006D001",
    "gn:admin3_code":"MMR006001",
    "gn:asciiname":"Pyathachaungywa",
    "gn:country_code":"MM",
    "gn:dem":208,
    "gn:feature_class":"P",
    "gn:feature_code":"PPL",
    "gn:name":"Pyathachaungywa",
    "gn:population":0,
    "gn:timezone":"Asia/Yangon",
    "iso:country":"MM",
    "name:und_x_variant":[
        "Pyathachaung",
        "Pyathachaungywa"
    ],
    "wof:name":"Pyathachaungywa",
    "wof:placetype":"locality"
},
  "geometry": {"coordinates":[98.46229,14.30634],"type":"Point"}
}