{
  "type": "Feature",
  "properties": {
    "gn:admin1_code":"11.0",
    "gn:admin2_code":"MMR016D003",
    "gn:admin3_code":"MMR016011",
    "gn:asciiname":"Wan Hsenhkamhawng",
    "gn:country_code":"MM",
    "gn:dem":914,
    "gn:feature_class":"P",
    "gn:feature_code":"PPL",
    "gn:name":"W\u0101n Hsenhkamhawng",
    "gn:population":0,
    "gn:timezone":"Asia/Yangon",
    "iso:country":"MM",
    "name:und_x_variant":[
        "Hsenhkamhawng",
        "W\u0101n Hsenhkamhawng"
    ],
    "wof:name":"Wan Hsenhkamhawng",
    "wof:placetype":"locality"
},
  "geometry": {"coordinates":[100.95437,21.65395],"type":"Point"}
}