{
  "type": "Feature",
  "properties": {
    "gn:admin1_code":"11.0",
    "gn:admin2_code":"MMR015D005",
    "gn:admin3_code":"MMR015022",
    "gn:asciiname":"Man Lunghtang",
    "gn:country_code":"MM",
    "gn:dem":700,
    "gn:feature_class":"P",
    "gn:feature_code":"PPL",
    "gn:name":"M\u0101n Lunghtang",
    "gn:population":0,
    "gn:timezone":"Asia/Yangon",
    "iso:country":"MM",
    "wof:name":"Man Lunghtang",
    "wof:placetype":"locality"
},
  "geometry": {"coordinates":[98.59247999999999,23.49372],"type":"Point"}
}