{
  "type": "Feature",
  "properties": {
    "gn:admin1_code":"11.0",
    "gn:admin2_code":"MMR014D001",
    "gn:admin3_code":"MMR014007",
    "gn:asciiname":"Me-byo",
    "gn:country_code":"MM",
    "gn:dem":1529,
    "gn:feature_class":"P",
    "gn:feature_code":"PPL",
    "gn:name":"Me-byo",
    "gn:population":0,
    "gn:timezone":"Asia/Yangon",
    "iso:country":"MM",
    "wof:name":"Me-byo",
    "wof:placetype":"locality"
},
  "geometry": {"coordinates":[96.5904,21.03185],"type":"Point"}
}