{
  "type": "Feature",
  "properties": {
    "gn:admin1_code":"11.0",
    "gn:admin2_code":"MMR014D001",
    "gn:admin3_code":"MMR014002",
    "gn:asciiname":"Ywama",
    "gn:country_code":"MM",
    "gn:dem":890,
    "gn:feature_class":"P",
    "gn:feature_code":"PPL",
    "gn:name":"Ywama",
    "gn:population":480,
    "gn:timezone":"Asia/Yangon",
    "iso:country":"MM",
    "name:slv_x_preferred":[
        "Ywama"
    ],
    "name:urd_x_preferred":[
        "\u06cc\u0648\u0645\u0627"
    ],
    "wof:name":"Ywama",
    "wof:placetype":"locality",
    "wof:population":480
},
  "geometry": {"coordinates":[96.88262,20.4928],"type":"Point"}
}