{
  "type": "Feature",
  "properties": {
    "gn:admin1_code":"11.0",
    "gn:admin2_code":"MMR016D003",
    "gn:admin3_code":"MMR016009",
    "gn:asciiname":"Wan Mak-yang",
    "gn:country_code":"MM",
    "gn:dem":397,
    "gn:feature_class":"P",
    "gn:feature_code":"PPL",
    "gn:name":"W\u0101n Mak-y\u0101ng",
    "gn:population":0,
    "gn:timezone":"Asia/Yangon",
    "iso:country":"MM",
    "wof:name":"Wan Mak-yang",
    "wof:placetype":"locality"
},
  "geometry": {"coordinates":[99.96817,20.57328],"type":"Point"}
}