{
  "type": "Feature",
  "properties": {
    "gn:admin1_code":"1.0",
    "gn:admin2_code":"MMR012D002",
    "gn:admin3_code":"MMR012010",
    "gn:asciiname":"Ngofewngrowa",
    "gn:country_code":"MM",
    "gn:dem":73,
    "gn:feature_class":"P",
    "gn:feature_code":"PPL",
    "gn:name":"Ngofewngrowa",
    "gn:population":0,
    "gn:timezone":"Asia/Yangon",
    "iso:country":"MM",
    "name:und_x_variant":[
        "Ngabay\u00f4nwa",
        "Ngotewngrowa",
        "Ngofewngrowa"
    ],
    "wof:name":"Ngofewngrowa",
    "wof:placetype":"locality"
},
  "geometry": {"coordinates":[92.53088,21.23531],"type":"Point"}
}