{
  "type": "Feature",
  "properties": {
    "gn:admin1_code":"10.0",
    "gn:admin2_code":"MMR005D004",
    "gn:admin3_code":"MMR005022",
    "gn:asciiname":"Kyetthongin",
    "gn:country_code":"MM",
    "gn:dem":94,
    "gn:feature_class":"P",
    "gn:feature_code":"PPL",
    "gn:name":"Kyetthongin",
    "gn:population":0,
    "gn:timezone":"Asia/Yangon",
    "iso:country":"MM",
    "wof:name":"Kyetthongin",
    "wof:placetype":"locality"
},
  "geometry": {"coordinates":[96.1284,23.7526],"type":"Point"}
}