{
  "type": "Feature",
  "properties": {
    "gn:admin1_code":"12.0",
    "gn:admin2_code":"MMR006D001",
    "gn:admin3_code":"MMR006003",
    "gn:asciiname":"Kya-in",
    "gn:country_code":"MM",
    "gn:dem":54,
    "gn:feature_class":"P",
    "gn:feature_code":"PPL",
    "gn:name":"Kya-in",
    "gn:population":0,
    "gn:timezone":"Asia/Yangon",
    "iso:country":"MM",
    "wof:name":"Kya-in",
    "wof:placetype":"locality"
},
  "geometry": {"coordinates":[98.25181000000001,13.995],"type":"Point"}
}