{
  "type": "Feature",
  "properties": {
    "gn:admin1_code":"11.0",
    "gn:admin2_code":"MMR015D006",
    "gn:admin3_code":"MMR015007",
    "gn:asciiname":"Kawngrang",
    "gn:country_code":"MM",
    "gn:dem":1279,
    "gn:feature_class":"P",
    "gn:feature_code":"PPL",
    "gn:name":"Kawngrang",
    "gn:population":0,
    "gn:timezone":"Asia/Yangon",
    "iso:country":"MM",
    "name:und_x_variant":[
        "Kowngrang",
        "Kawngrang"
    ],
    "wof:name":"Kawngrang",
    "wof:placetype":"locality"
},
  "geometry": {"coordinates":[99.10601,22.96619],"type":"Point"}
}