{
  "type": "Feature",
  "properties": {
    "gn:admin1_code":"5.0",
    "gn:admin2_code":"MMR003D001",
    "gn:admin3_code":"MMR003004",
    "gn:asciiname":"Tithasaw",
    "gn:country_code":"MM",
    "gn:dem":862,
    "gn:feature_class":"P",
    "gn:feature_code":"PPL",
    "gn:name":"Tithasaw",
    "gn:population":0,
    "gn:timezone":"Asia/Yangon",
    "iso:country":"MM",
    "name:und_x_variant":[
        "Tithasaw-auk",
        "Tithasaw"
    ],
    "wof:name":"Tithasaw",
    "wof:placetype":"locality"
},
  "geometry": {"coordinates":[96.77471,19.22277],"type":"Point"}
}