{
  "type": "Feature",
  "properties": {
    "gn:admin1_code":"1.0",
    "gn:admin2_code":"MMR012D002",
    "gn:admin3_code":"MMR012009",
    "gn:asciiname":"Mingalagyi",
    "gn:country_code":"MM",
    "gn:dem":5,
    "gn:feature_class":"P",
    "gn:feature_code":"PPL",
    "gn:name":"Mingalagyi",
    "gn:population":0,
    "gn:timezone":"Asia/Yangon",
    "iso:country":"MM",
    "name:und_x_variant":[
        "Pyinbyu",
        "Mingalagyi"
    ],
    "wof:name":"Mingalagyi",
    "wof:placetype":"locality"
},
  "geometry": {"coordinates":[92.32862,20.90008],"type":"Point"}
}