{
  "type": "Feature",
  "properties": {
    "gn:admin1_code":"4.0",
    "gn:admin2_code":"MMR001D002",
    "gn:admin3_code":"MMR001009",
    "gn:asciiname":"'Ndup Gahtawng",
    "gn:country_code":"MM",
    "gn:dem":967,
    "gn:feature_class":"P",
    "gn:feature_code":"PPL",
    "gn:name":"\u2019Ndup Gahtawng",
    "gn:population":0,
    "gn:timezone":"Asia/Yangon",
    "iso:country":"MM",
    "wof:name":"'Ndup Gahtawng",
    "wof:placetype":"locality"
},
  "geometry": {"coordinates":[96.2289,25.79947],"type":"Point"}
}