{
  "type": "Feature",
  "properties": {
    "gn:admin1_code":"17.0",
    "gn:admin2_code":"MMR013D001",
    "gn:admin3_code":"MMR013004",
    "gn:asciiname":"Ingyinkwin",
    "gn:country_code":"MM",
    "gn:dem":19,
    "gn:feature_class":"P",
    "gn:feature_code":"PPL",
    "gn:name":"Ingyinkwin",
    "gn:population":0,
    "gn:timezone":"Asia/Yangon",
    "iso:country":"MM",
    "wof:name":"Ingyinkwin",
    "wof:placetype":"locality"
},
  "geometry": {"coordinates":[96.23331,17.21581],"type":"Point"}
}