{
  "type": "Feature",
  "properties": {
    "gn:admin1_code":"16.0",
    "gn:admin2_code":"MMR007D001",
    "gn:admin3_code":"MMR007006",
    "gn:asciiname":"Taunggin",
    "gn:country_code":"MM",
    "gn:dem":25,
    "gn:feature_class":"P",
    "gn:feature_code":"PPL",
    "gn:name":"Taunggin",
    "gn:population":0,
    "gn:timezone":"Asia/Yangon",
    "iso:country":"MM",
    "name:und_x_variant":[
        "Taungginzu",
        "Taunggin"
    ],
    "wof:name":"Taunggin",
    "wof:placetype":"locality"
},
  "geometry": {"coordinates":[96.67966,18.11315],"type":"Point"}
}