{
  "type": "Feature",
  "properties": {
    "gn:admin1_code":"10.0",
    "gn:admin2_code":"MMR005D003",
    "gn:admin3_code":"MMR005013",
    "gn:asciiname":"Wetlu-aing",
    "gn:country_code":"MM",
    "gn:dem":107,
    "gn:feature_class":"P",
    "gn:feature_code":"PPL",
    "gn:name":"Wetlu-aing",
    "gn:population":0,
    "gn:timezone":"Asia/Yangon",
    "iso:country":"MM",
    "wof:name":"Wetlu-aing",
    "wof:placetype":"locality"
},
  "geometry": {"coordinates":[94.95138,22.43593],"type":"Point"}
}