{
  "type": "Feature",
  "properties": {
    "gn:admin1_code":"8.0",
    "gn:admin2_code":"MMR010D002",
    "gn:admin3_code":"MMR010009",
    "gn:asciiname":"Thamingyan",
    "gn:country_code":"MM",
    "gn:dem":76,
    "gn:feature_class":"P",
    "gn:feature_code":"PPL",
    "gn:name":"Thamingyan",
    "gn:population":0,
    "gn:timezone":"Asia/Yangon",
    "iso:country":"MM",
    "wof:name":"Thamingyan",
    "wof:placetype":"locality"
},
  "geometry": {"coordinates":[96.05262999999999,22.03552],"type":"Point"}
}