{
  "type": "Feature",
  "properties": {
    "gn:admin1_code":"4.0",
    "gn:admin2_code":"MMR001D001",
    "gn:admin3_code":"MMR001003",
    "gn:asciiname":"Sumpawngbum",
    "gn:country_code":"MM",
    "gn:dem":939,
    "gn:feature_class":"P",
    "gn:feature_code":"PPL",
    "gn:name":"Sumpawngbum",
    "gn:population":0,
    "gn:timezone":"Asia/Yangon",
    "iso:country":"MM",
    "wof:name":"Sumpawngbum",
    "wof:placetype":"locality"
},
  "geometry": {"coordinates":[97.83158,26.17448],"type":"Point"}
}