{
  "type": "Feature",
  "properties": {
    "gn:admin1_code":"10.0",
    "gn:admin2_code":"MMR005D002",
    "gn:admin3_code":"MMR005006",
    "gn:asciiname":"Wetleywe",
    "gn:country_code":"MM",
    "gn:dem":90,
    "gn:feature_class":"P",
    "gn:feature_code":"PPL",
    "gn:name":"Wetl\u00e8yw\u00e8",
    "gn:population":0,
    "gn:timezone":"Asia/Yangon",
    "iso:country":"MM",
    "wof:name":"Wetleywe",
    "wof:placetype":"locality"
},
  "geometry": {"coordinates":[95.82535,22.34526],"type":"Point"}
}