{
  "type": "Feature",
  "properties": {
    "gn:admin1_code":"16.0",
    "gn:admin2_code":"MMR007D002",
    "gn:admin3_code":"MMR007010",
    "gn:asciiname":"Payagon",
    "gn:country_code":"MM",
    "gn:dem":77,
    "gn:feature_class":"P",
    "gn:feature_code":"PPL",
    "gn:name":"Payagon",
    "gn:population":0,
    "gn:timezone":"Asia/Yangon",
    "iso:country":"MM",
    "name:und_x_variant":[
        "Buyag\u00f4n",
        "Payagon"
    ],
    "wof:name":"Payagon",
    "wof:placetype":"locality"
},
  "geometry": {"coordinates":[96.30284,19.3735],"type":"Point"}
}