{
  "type": "Feature",
  "properties": {
    "gn:admin1_code":"2.0",
    "gn:admin2_code":"MMR004D001",
    "gn:admin3_code":"MMR004001",
    "gn:asciiname":"Thungthul",
    "gn:country_code":"MM",
    "gn:dem":890,
    "gn:feature_class":"P",
    "gn:feature_code":"PPL",
    "gn:name":"Thungthul",
    "gn:population":0,
    "gn:timezone":"Asia/Yangon",
    "iso:country":"MM",
    "wof:name":"Thungthul",
    "wof:placetype":"locality"
},
  "geometry": {"coordinates":[93.75,22.86667000000001],"type":"Point"}
}