{
  "type": "Feature",
  "properties": {
    "gn:admin1_code":"15.0",
    "gn:admin2_code":"MMR009D003",
    "gn:admin3_code":"MMR009015",
    "gn:asciiname":"Inbe",
    "gn:country_code":"MM",
    "gn:dem":31,
    "gn:feature_class":"P",
    "gn:feature_code":"PPL",
    "gn:name":"Inb\u00e8",
    "gn:population":0,
    "gn:timezone":"Asia/Yangon",
    "iso:country":"MM",
    "wof:name":"Inbe",
    "wof:placetype":"locality"
},
  "geometry": {"coordinates":[95.11667,19.08333],"type":"Point"}
}