{
  "type": "Feature",
  "properties": {
    "gn:admin1_code":"11.0",
    "gn:admin2_code":"MMR016D003",
    "gn:admin3_code":"MMR016011",
    "gn:asciiname":"Bok Ten",
    "gn:country_code":"MM",
    "gn:dem":622,
    "gn:feature_class":"P",
    "gn:feature_code":"PPL",
    "gn:name":"B\u014dk Ten",
    "gn:population":0,
    "gn:timezone":"Asia/Yangon",
    "iso:country":"MM",
    "wof:name":"Bok Ten",
    "wof:placetype":"locality"
},
  "geometry": {"coordinates":[100.65000000000001,21.36667000000001],"type":"Point"}
}