{
  "type": "Feature",
  "properties": {
    "gn:admin1_code":"4.0",
    "gn:admin2_code":"MMR001D002",
    "gn:admin3_code":"MMR001008",
    "gn:asciiname":"Namkwin",
    "gn:country_code":"MM",
    "gn:dem":193,
    "gn:feature_class":"P",
    "gn:feature_code":"PPL",
    "gn:name":"Namkwin",
    "gn:population":0,
    "gn:timezone":"Asia/Yangon",
    "iso:country":"MM",
    "wof:name":"Namkwin",
    "wof:placetype":"locality"
},
  "geometry": {"coordinates":[96.59301000000001,25.04752],"type":"Point"}
}