{
  "type": "Feature",
  "properties": {
    "gn:admin1_code":"15.0",
    "gn:admin2_code":"MMR009D002",
    "gn:admin3_code":"MMR009010",
    "gn:asciiname":"Thanatchaungywa",
    "gn:country_code":"MM",
    "gn:dem":160,
    "gn:feature_class":"P",
    "gn:feature_code":"PPL",
    "gn:name":"Thanatchaungywa",
    "gn:population":0,
    "gn:timezone":"Asia/Yangon",
    "iso:country":"MM",
    "name:und_x_variant":[
        "Thanatchungywa",
        "Thanatchaungywa"
    ],
    "wof:name":"Thanatchaungywa",
    "wof:placetype":"locality"
},
  "geometry": {"coordinates":[94.4288,20.81499],"type":"Point"}
}