{
  "type": "Feature",
  "properties": {
    "gn:admin1_code":"11.0",
    "gn:admin2_code":"MMR015D001",
    "gn:admin3_code":"MMR015001",
    "gn:asciiname":"Hsup-tong",
    "gn:country_code":"MM",
    "gn:dem":533,
    "gn:feature_class":"P",
    "gn:feature_code":"PPL",
    "gn:name":"Hsup-t\u014dng",
    "gn:population":0,
    "gn:timezone":"Asia/Yangon",
    "iso:country":"MM",
    "wof:name":"Hsup-tong",
    "wof:placetype":"locality"
},
  "geometry": {"coordinates":[97.70455,22.6399],"type":"Point"}
}