{
  "type": "Feature",
  "properties": {
    "gn:admin1_code":"10.0",
    "gn:asciiname":"Htintamin",
    "gn:country_code":"MM",
    "gn:dem":161,
    "gn:feature_class":"P",
    "gn:feature_code":"PPL",
    "gn:name":"Htintamin",
    "gn:population":0,
    "gn:timezone":"Asia/Yangon",
    "iso:country":"MM",
    "wof:name":"Htintamin",
    "wof:placetype":"locality"
},
  "geometry": {"coordinates":[94.85453,21.84405],"type":"Point"}
}