{
  "type": "Feature",
  "properties": {
    "gn:admin1_code":"11.0",
    "gn:admin2_code":"MMR014D001",
    "gn:admin3_code":"MMR014006",
    "gn:asciiname":"Sizung",
    "gn:country_code":"MM",
    "gn:dem":1118,
    "gn:feature_class":"P",
    "gn:feature_code":"PPL",
    "gn:name":"Sizung",
    "gn:population":0,
    "gn:timezone":"Asia/Yangon",
    "iso:country":"MM",
    "wof:name":"Sizung",
    "wof:placetype":"locality"
},
  "geometry": {"coordinates":[96.66055,21.07055],"type":"Point"}
}