{
  "type": "Feature",
  "properties": {
    "gn:admin1_code":"5.0",
    "gn:admin2_code":"MMR003D003",
    "gn:admin3_code":"MMR003007",
    "gn:asciiname":"Hlaingkawe",
    "gn:country_code":"MM",
    "gn:dem":18,
    "gn:feature_class":"P",
    "gn:feature_code":"PPL",
    "gn:name":"Hlaingkawe",
    "gn:population":0,
    "gn:timezone":"Asia/Yangon",
    "iso:country":"MM",
    "wof:name":"Hlaingkawe",
    "wof:placetype":"locality"
},
  "geometry": {"coordinates":[97.98734,15.95875],"type":"Point"}
}