{
  "type": "Feature",
  "properties": {
    "gn:admin1_code":"4.0",
    "gn:admin2_code":"MMR001D004",
    "gn:admin3_code":"MMR001018",
    "gn:asciiname":"Rawangtung",
    "gn:country_code":"MM",
    "gn:dem":1059,
    "gn:feature_class":"P",
    "gn:feature_code":"PPL",
    "gn:name":"Raw\u0101ngtung",
    "gn:population":0,
    "gn:timezone":"Asia/Yangon",
    "iso:country":"MM",
    "wof:name":"Rawangtung",
    "wof:placetype":"locality"
},
  "geometry": {"coordinates":[98.43989999999999,26.78913],"type":"Point"}
}