{
  "type": "Feature",
  "properties": {
    "gn:admin1_code":"1.0",
    "gn:admin2_code":"MMR012D005",
    "gn:admin3_code":"MMR012005",
    "gn:asciiname":"Kyokyi",
    "gn:country_code":"MM",
    "gn:dem":61,
    "gn:feature_class":"P",
    "gn:feature_code":"PPL",
    "gn:name":"Kyokyi",
    "gn:population":0,
    "gn:timezone":"Asia/Yangon",
    "iso:country":"MM",
    "wof:name":"Kyokyi",
    "wof:placetype":"locality"
},
  "geometry": {"coordinates":[93.56104999999999,20.26976],"type":"Point"}
}