{
  "type": "Feature",
  "properties": {
    "gn:admin1_code":"16.0",
    "gn:admin2_code":"MMR008D002",
    "gn:admin3_code":"MMR008007",
    "gn:asciiname":"Pashwegyaw Taung",
    "gn:country_code":"MM",
    "gn:dem":33,
    "gn:feature_class":"P",
    "gn:feature_code":"PPL",
    "gn:name":"Pashwegyaw Taung",
    "gn:population":0,
    "gn:timezone":"Asia/Yangon",
    "iso:country":"MM",
    "wof:name":"Pashwegyaw Taung",
    "wof:placetype":"locality"
},
  "geometry": {"coordinates":[95.85509999999999,17.70214],"type":"Point"}
}