{
  "type": "Feature",
  "properties": {
    "gn:admin1_code":"8.0",
    "gn:admin2_code":"MMR010D006",
    "gn:admin3_code":"MMR010024",
    "gn:asciiname":"Kande",
    "gn:country_code":"MM",
    "gn:dem":322,
    "gn:feature_class":"P",
    "gn:feature_code":"PPL",
    "gn:name":"Kande",
    "gn:population":0,
    "gn:timezone":"Asia/Yangon",
    "iso:country":"MM",
    "name:ceb_x_preferred":[
        "Kande"
    ],
    "name:swe_x_preferred":[
        "Kande"
    ],
    "wof:name":"Kande",
    "wof:placetype":"locality"
},
  "geometry": {"coordinates":[95.73829000000001,20.55548],"type":"Point"}
}