{
  "type": "Feature",
  "properties": {
    "gn:admin1_code":"15.0",
    "gn:admin2_code":"MMR009D004",
    "gn:admin3_code":"MMR009022",
    "gn:asciiname":"Mingyan",
    "gn:country_code":"MM",
    "gn:dem":203,
    "gn:feature_class":"P",
    "gn:feature_code":"PPL",
    "gn:name":"Mingyan",
    "gn:population":0,
    "gn:timezone":"Asia/Yangon",
    "iso:country":"MM",
    "wof:name":"Mingyan",
    "wof:placetype":"locality"
},
  "geometry": {"coordinates":[94.42789999999999,20.91441],"type":"Point"}
}