{
  "type": "Feature",
  "properties": {
    "gn:admin1_code":"16.0",
    "gn:admin2_code":"MMR007D002",
    "gn:admin3_code":"MMR007010",
    "gn:asciiname":"Thaingwa",
    "gn:country_code":"MM",
    "gn:dem":84,
    "gn:feature_class":"P",
    "gn:feature_code":"PPL",
    "gn:name":"Thaingwa",
    "gn:population":0,
    "gn:timezone":"Asia/Yangon",
    "iso:country":"MM",
    "wof:name":"Thaingwa",
    "wof:placetype":"locality"
},
  "geometry": {"coordinates":[96.24975999999999,19.19366],"type":"Point"}
}