{
  "type": "Feature",
  "properties": {
    "gn:admin1_code":"8.0",
    "gn:admin2_code":"MMR010D007",
    "gn:admin3_code":"MMR010031",
    "gn:asciiname":"Shweku",
    "gn:country_code":"MM",
    "gn:dem":105,
    "gn:feature_class":"P",
    "gn:feature_code":"PPL",
    "gn:name":"Shweku",
    "gn:population":0,
    "gn:timezone":"Asia/Yangon",
    "iso:country":"MM",
    "wof:name":"Shweku",
    "wof:placetype":"locality"
},
  "geometry": {"coordinates":[96.07203,21.34621],"type":"Point"}
}