{
  "type": "Feature",
  "properties": {
    "gn:admin1_code":"17.0",
    "gn:asciiname":"Kyaukmaye",
    "gn:country_code":"MM",
    "gn:dem":1,
    "gn:feature_class":"P",
    "gn:feature_code":"PPL",
    "gn:name":"Kyaukmaye",
    "gn:population":0,
    "gn:timezone":"Asia/Yangon",
    "iso:country":"MM",
    "wof:name":"Kyaukmaye",
    "wof:placetype":"locality"
},
  "geometry": {"coordinates":[96.33389,16.63],"type":"Point"}
}