{
  "type": "Feature",
  "properties": {
    "gn:admin1_code":"11.0",
    "gn:admin2_code":"MMR015D001",
    "gn:admin3_code":"MMR015001",
    "gn:asciiname":"Na-hpai",
    "gn:country_code":"MM",
    "gn:dem":857,
    "gn:feature_class":"P",
    "gn:feature_code":"PPL",
    "gn:name":"Na-hpai",
    "gn:population":0,
    "gn:timezone":"Asia/Yangon",
    "iso:country":"MM",
    "wof:name":"Na-hpai",
    "wof:placetype":"locality"
},
  "geometry": {"coordinates":[98.13043999999999,23.01607000000001],"type":"Point"}
}