{
  "type": "Feature",
  "properties": {
    "gn:admin1_code":"11.0",
    "gn:admin2_code":"MMR016D003",
    "gn:admin3_code":"MMR016009",
    "gn:asciiname":"Wan Tunglung",
    "gn:country_code":"MM",
    "gn:dem":478,
    "gn:feature_class":"P",
    "gn:feature_code":"PPL",
    "gn:name":"W\u0101n T\u016bngl\u016bng",
    "gn:population":0,
    "gn:timezone":"Asia/Yangon",
    "iso:country":"MM",
    "name:und_x_variant":[
        "W\u0101n T\u016bngl\u00f6ng",
        "W\u0101n T\u016bngl\u016bng"
    ],
    "wof:name":"Wan Tunglung",
    "wof:placetype":"locality"
},
  "geometry": {"coordinates":[99.82595000000001,20.76808],"type":"Point"}
}