{
  "type": "Feature",
  "properties": {
    "gn:admin1_code":"11.0",
    "gn:admin2_code":"MMR015D001",
    "gn:admin3_code":"MMR015002",
    "gn:asciiname":"Ho-tu",
    "gn:country_code":"MM",
    "gn:dem":1071,
    "gn:feature_class":"P",
    "gn:feature_code":"PPL",
    "gn:name":"Ho-tu",
    "gn:population":0,
    "gn:timezone":"Asia/Yangon",
    "iso:country":"MM",
    "wof:name":"Ho-tu",
    "wof:placetype":"locality"
},
  "geometry": {"coordinates":[98.29658999999999,23.34514],"type":"Point"}
}