{
  "type": "Feature",
  "properties": {
    "gn:admin1_code":"10.0",
    "gn:admin2_code":"MMR005D002",
    "gn:admin3_code":"MMR005010",
    "gn:asciiname":"Mayagan",
    "gn:country_code":"MM",
    "gn:dem":103,
    "gn:feature_class":"P",
    "gn:feature_code":"PPL",
    "gn:name":"Mayagan",
    "gn:population":0,
    "gn:timezone":"Asia/Yangon",
    "iso:country":"MM",
    "wof:name":"Mayagan",
    "wof:placetype":"locality"
},
  "geometry": {"coordinates":[95.39657,22.6253],"type":"Point"}
}