{
  "type": "Feature",
  "properties": {
    "gn:admin1_code":"11.0",
    "gn:admin2_code":"MMR014D003",
    "gn:admin3_code":"MMR014021",
    "gn:asciiname":"Wan Sawk",
    "gn:country_code":"MM",
    "gn:dem":716,
    "gn:feature_class":"P",
    "gn:feature_code":"PPL",
    "gn:name":"W\u0101n Sawk",
    "gn:population":0,
    "gn:timezone":"Asia/Yangon",
    "iso:country":"MM",
    "wof:name":"Wan Sawk",
    "wof:placetype":"locality"
},
  "geometry": {"coordinates":[98.36311000000001,20.30707],"type":"Point"}
}