{
  "type": "Feature",
  "properties": {
    "gn:admin1_code":"10.0",
    "gn:admin2_code":"MMR005D005",
    "gn:admin3_code":"MMR005027",
    "gn:asciiname":"Haka",
    "gn:country_code":"MM",
    "gn:dem":184,
    "gn:feature_class":"P",
    "gn:feature_code":"PPL",
    "gn:name":"Haka",
    "gn:population":0,
    "gn:timezone":"Asia/Yangon",
    "iso:country":"MM",
    "name:afr_x_preferred":[
        "Haka"
    ],
    "name:ara_x_preferred":[
        "\u0647\u0627\u0643\u0627"
    ],
    "name:arg_x_preferred":[
        "Haka"
    ],
    "name:aze_x_preferred":[
        "Haka"
    ],
    "name:bul_x_preferred":[
        "\u0425\u0430\u043a\u0430"
    ],
    "name:cat_x_preferred":[
        "Haka"
    ],
    "name:ces_x_preferred":[
        "Haka"
    ],
    "name:deu_x_preferred":[
        "Haka"
    ],
    "name:eus_x_preferred":[
        "Haka"
    ],
    "name:ext_x_preferred":[
        "Haka"
    ],
    "name:fas_x_preferred":[
        "\u0647\u0627\u06a9\u0627"
    ],
    "name:fin_x_preferred":[
        "Haka"
    ],
    "name:fra_x_preferred":[
        "Haka"
    ],
    "name:fry_x_preferred":[
        "Haka"
    ],
    "name:glg_x_preferred":[
        "Haka"
    ],
    "name:heb_x_preferred":[
        "\u05d4\u05d0\u05e7\u05d4"
    ],
    "name:hin_x_preferred":[
        "\u0939\u093e\u0915\u093e"
    ],
    "name:hrv_x_preferred":[
        "Haka"
    ],
    "name:hun_x_preferred":[
        "Haka"
    ],
    "name:hye_x_preferred":[
        "\u0540\u0561\u056f\u0561"
    ],
    "name:ido_x_preferred":[
        "Haka"
    ],
    "name:ind_x_preferred":[
        "Haka"
    ],
    "name:ita_x_preferred":[
        "Haka"
    ],
    "name:jpn_x_preferred":[
        "\u30cf\u30ab"
    ],
    "name:kat_x_preferred":[
        "\u10f0\u10d0\u10d9\u10d0"
    ],
    "name:kor_x_preferred":[
        "\ub9c8\uc624\ub9ac \ud558\uce74"
    ],
    "name:lav_x_preferred":[
        "Haka"
    ],
    "name:msa_x_preferred":[
        "Haka"
    ],
    "name:nld_x_preferred":[
        "Haka"
    ],
    "name:nor_x_preferred":[
        "Haka"
    ],
    "name:oci_x_preferred":[
        "Haka"
    ],
    "name:pol_x_preferred":[
        "Haka"
    ],
    "name:por_x_preferred":[
        "Haka"
    ],
    "name:ron_x_preferred":[
        "Haka"
    ],
    "name:rus_x_preferred":[
        "\u0425\u0430\u043a\u0430"
    ],
    "name:spa_x_preferred":[
        "Haka"
    ],
    "name:sqi_x_preferred":[
        "Haka"
    ],
    "name:srp_x_preferred":[
        "\u0425\u0430\u043a\u0430"
    ],
    "name:swe_x_preferred":[
        "Haka"
    ],
    "name:tur_x_preferred":[
        "Haka dans\u0131"
    ],
    "name:ukr_x_preferred":[
        "\u0413\u0430\u043a\u0430"
    ],
    "name:zho_x_preferred":[
        "\u54c8\u5361\u821e"
    ],
    "wof:name":"Haka",
    "wof:placetype":"locality"
},
  "geometry": {"coordinates":[94.00668,22.98256],"type":"Point"}
}