{
  "type": "Feature",
  "properties": {
    "gn:admin1_code":"1.0",
    "gn:admin2_code":"MMR012D001",
    "gn:admin3_code":"MMR012008",
    "gn:asciiname":"Uga-ywa",
    "gn:country_code":"MM",
    "gn:dem":13,
    "gn:feature_class":"P",
    "gn:feature_code":"PPL",
    "gn:name":"Uga-ywa",
    "gn:population":0,
    "gn:timezone":"Asia/Yangon",
    "iso:country":"MM",
    "name:und_x_variant":[
        "Uga",
        "Uga-ywa"
    ],
    "wof:name":"Uga-ywa",
    "wof:placetype":"locality"
},
  "geometry": {"coordinates":[92.79761999999999,20.36716],"type":"Point"}
}