{
  "type": "Feature",
  "properties": {
    "gn:admin1_code":"11.0",
    "gn:admin2_code":"MMR014D003",
    "gn:admin3_code":"MMR014020",
    "gn:asciiname":"Daw Hsa-le",
    "gn:country_code":"MM",
    "gn:dem":556,
    "gn:feature_class":"P",
    "gn:feature_code":"PPL",
    "gn:name":"Daw Hsa-l\u00e8",
    "gn:population":0,
    "gn:timezone":"Asia/Yangon",
    "iso:country":"MM",
    "wof:name":"Daw Hsa-le",
    "wof:placetype":"locality"
},
  "geometry": {"coordinates":[97.60348999999999,19.85425],"type":"Point"}
}