{
  "type": "Feature",
  "properties": {
    "gn:admin1_code":"4.0",
    "gn:admin2_code":"MMR001D001",
    "gn:admin3_code":"MMR001005",
    "gn:asciiname":"Nahpaung",
    "gn:country_code":"MM",
    "gn:dem":614,
    "gn:feature_class":"P",
    "gn:feature_code":"PPL",
    "gn:name":"Nahpaung",
    "gn:population":0,
    "gn:timezone":"Asia/Yangon",
    "iso:country":"MM",
    "name:und_x_variant":[
        "Wahpaung",
        "Nahpaung"
    ],
    "wof:name":"Nahpaung",
    "wof:placetype":"locality"
},
  "geometry": {"coordinates":[98.1028,25.847],"type":"Point"}
}