{
  "type": "Feature",
  "properties": {
    "gn:admin1_code":"11.0",
    "gn:admin2_code":"MMR016D002",
    "gn:admin3_code":"MMR016006",
    "gn:asciiname":"Wan Muenhkamsai",
    "gn:country_code":"MM",
    "gn:dem":1200,
    "gn:feature_class":"P",
    "gn:feature_code":"PPL",
    "gn:name":"W\u0101n M\u00fcnhkamsai",
    "gn:population":0,
    "gn:timezone":"Asia/Yangon",
    "iso:country":"MM",
    "name:und_x_variant":[
        "W\u0101n Mu-hs\u00f6 M\u00fcnhkamsai",
        "W\u0101n M\u00fcnhkamsai"
    ],
    "wof:name":"Wan Muenhkamsai",
    "wof:placetype":"locality"
},
  "geometry": {"coordinates":[99.63094,20.54887],"type":"Point"}
}