{
  "type": "Feature",
  "properties": {
    "gn:admin1_code":"4.0",
    "gn:admin2_code":"MMR001D001",
    "gn:admin3_code":"MMR001004",
    "gn:asciiname":"Gedu Ga",
    "gn:country_code":"MM",
    "gn:dem":864,
    "gn:feature_class":"P",
    "gn:feature_code":"PPL",
    "gn:name":"Gedu Ga",
    "gn:population":0,
    "gn:timezone":"Asia/Yangon",
    "iso:country":"MM",
    "name:und_x_variant":[
        "Langshing",
        "Gedu Ga"
    ],
    "wof:name":"Gedu Ga",
    "wof:placetype":"locality"
},
  "geometry": {"coordinates":[96.34838000000001,26.95157],"type":"Point"}
}