{
  "type": "Feature",
  "properties": {
    "gn:admin1_code":"13.0",
    "gn:admin2_code":"MMR011D001",
    "gn:admin3_code":"MMR011006",
    "gn:asciiname":"Thudaw",
    "gn:country_code":"MM",
    "gn:dem":37,
    "gn:feature_class":"P",
    "gn:feature_code":"PPL",
    "gn:name":"Thudaw",
    "gn:population":0,
    "gn:timezone":"Asia/Yangon",
    "iso:country":"MM",
    "wof:name":"Thudaw",
    "wof:placetype":"locality"
},
  "geometry": {"coordinates":[97.90949999999999,15.60553],"type":"Point"}
}