{
  "type": "Feature",
  "properties": {
    "gn:admin1_code":"15.0",
    "gn:admin2_code":"MMR009D002",
    "gn:admin3_code":"MMR009011",
    "gn:asciiname":"Ponzeik",
    "gn:country_code":"MM",
    "gn:dem":135,
    "gn:feature_class":"P",
    "gn:feature_code":"PPL",
    "gn:name":"P\u00f4nzeik",
    "gn:population":0,
    "gn:timezone":"Asia/Yangon",
    "iso:country":"MM",
    "wof:name":"Ponzeik",
    "wof:placetype":"locality"
},
  "geometry": {"coordinates":[94.20954999999999,20.5175],"type":"Point"}
}