{
  "type": "Feature",
  "properties": {
    "gn:admin1_code":"5.0",
    "gn:admin2_code":"MMR003D003",
    "gn:admin3_code":"MMR003007",
    "gn:asciiname":"Hpanu",
    "gn:country_code":"MM",
    "gn:dem":36,
    "gn:feature_class":"P",
    "gn:feature_code":"PPL",
    "gn:name":"Hpanu",
    "gn:population":0,
    "gn:timezone":"Asia/Yangon",
    "iso:country":"MM",
    "wof:name":"Hpanu",
    "wof:placetype":"locality"
},
  "geometry": {"coordinates":[98.26994999999999,16.20701],"type":"Point"}
}