{
  "type": "Feature",
  "properties": {
    "gn:admin1_code":"11.0",
    "gn:admin2_code":"MMR014D002",
    "gn:admin3_code":"MMR014015",
    "gn:asciiname":"Kai-hpoek",
    "gn:country_code":"MM",
    "gn:dem":872,
    "gn:feature_class":"P",
    "gn:feature_code":"PPL",
    "gn:name":"Kai-hp\u00f6k",
    "gn:population":0,
    "gn:timezone":"Asia/Yangon",
    "iso:country":"MM",
    "wof:name":"Kai-hpoek",
    "wof:placetype":"locality"
},
  "geometry": {"coordinates":[98.0517,22.02724],"type":"Point"}
}