{
  "type": "Feature",
  "properties": {
    "gn:admin1_code":"11.0",
    "gn:admin2_code":"MMR015D008",
    "gn:admin3_code":"MMR015017",
    "gn:asciiname":"Ngawsayup",
    "gn:country_code":"MM",
    "gn:dem":834,
    "gn:feature_class":"P",
    "gn:feature_code":"PPL",
    "gn:name":"Ngawsayup",
    "gn:population":0,
    "gn:timezone":"Asia/Yangon",
    "iso:country":"MM",
    "name:und_x_variant":[
        "Ngawsavup",
        "Ngawsayup"
    ],
    "wof:name":"Ngawsayup",
    "wof:placetype":"locality"
},
  "geometry": {"coordinates":[96.8507,23.3242],"type":"Point"}
}