{
  "type": "Feature",
  "properties": {
    "gn:admin1_code":"16.0",
    "gn:admin2_code":"MMR007D002",
    "gn:admin3_code":"MMR007012",
    "gn:asciiname":"Thamigwe",
    "gn:country_code":"MM",
    "gn:dem":37,
    "gn:feature_class":"P",
    "gn:feature_code":"PPL",
    "gn:name":"Thamigwe",
    "gn:population":0,
    "gn:timezone":"Asia/Yangon",
    "iso:country":"MM",
    "name:und_x_variant":[
        "Thmigw\u00e8",
        "Thamigwe"
    ],
    "wof:name":"Thamigwe",
    "wof:placetype":"locality"
},
  "geometry": {"coordinates":[96.53440999999999,18.36553],"type":"Point"}
}