{
  "type": "Feature",
  "properties": {
    "gn:admin1_code":"11.0",
    "gn:admin2_code":"MMR014D001",
    "gn:admin3_code":"MMR014009",
    "gn:asciiname":"Talaingma",
    "gn:country_code":"MM",
    "gn:dem":377,
    "gn:feature_class":"P",
    "gn:feature_code":"PPL",
    "gn:name":"Talaingma",
    "gn:population":0,
    "gn:timezone":"Asia/Yangon",
    "iso:country":"MM",
    "wof:name":"Talaingma",
    "wof:placetype":"locality"
},
  "geometry": {"coordinates":[96.58307000000001,19.9864],"type":"Point"}
}