{
  "type": "Feature",
  "properties": {
    "gn:admin1_code":"11.0",
    "gn:admin2_code":"MMR014D003",
    "gn:admin3_code":"MMR014018",
    "gn:asciiname":"Ta Hwe-hawn",
    "gn:country_code":"MM",
    "gn:dem":352,
    "gn:feature_class":"P",
    "gn:feature_code":"PPL",
    "gn:name":"Ta Hw\u00e8-hawn",
    "gn:population":0,
    "gn:timezone":"Asia/Yangon",
    "iso:country":"MM",
    "wof:name":"Ta Hwe-hawn",
    "wof:placetype":"locality"
},
  "geometry": {"coordinates":[98.16504999999999,20.43207],"type":"Point"}
}