{
  "type": "Feature",
  "properties": {
    "gn:admin1_code":"8.0",
    "gn:admin2_code":"MMR010D002",
    "gn:admin3_code":"MMR010008",
    "gn:asciiname":"Pathin",
    "gn:country_code":"MM",
    "gn:dem":1146,
    "gn:feature_class":"P",
    "gn:feature_code":"PPL",
    "gn:name":"Pathin",
    "gn:population":0,
    "gn:timezone":"Asia/Yangon",
    "iso:country":"MM",
    "wof:name":"Pathin",
    "wof:placetype":"locality"
},
  "geometry": {"coordinates":[96.50836,21.96342000000001],"type":"Point"}
}