{
  "type": "Feature",
  "properties": {
    "gn:admin1_code":"11.0",
    "gn:admin2_code":"MMR015D002",
    "gn:admin3_code":"MMR015011",
    "gn:asciiname":"Man Maue",
    "gn:country_code":"MM",
    "gn:dem":1267,
    "gn:feature_class":"P",
    "gn:feature_code":"PPL",
    "gn:name":"M\u0101n Ma\u00fc",
    "gn:population":0,
    "gn:timezone":"Asia/Yangon",
    "iso:country":"MM",
    "wof:name":"Man Maue",
    "wof:placetype":"locality"
},
  "geometry": {"coordinates":[98.01895,23.5975],"type":"Point"}
}