{
  "type": "Feature",
  "properties": {
    "gn:admin1_code":"10.0",
    "gn:admin2_code":"MMR005D002",
    "gn:admin3_code":"MMR005009",
    "gn:asciiname":"Kinzan",
    "gn:country_code":"MM",
    "gn:dem":167,
    "gn:feature_class":"P",
    "gn:feature_code":"PPL",
    "gn:name":"Kinzan",
    "gn:population":0,
    "gn:timezone":"Asia/Yangon",
    "iso:country":"MM",
    "wof:name":"Kinzan",
    "wof:placetype":"locality"
},
  "geometry": {"coordinates":[95.18082,22.77912],"type":"Point"}
}