{
  "type": "Feature",
  "properties": {
    "gn:admin1_code":"11.0",
    "gn:admin2_code":"MMR015D003",
    "gn:admin3_code":"MMR015014",
    "gn:asciiname":"Kawnglang",
    "gn:country_code":"MM",
    "gn:dem":697,
    "gn:feature_class":"P",
    "gn:feature_code":"PPL",
    "gn:name":"Kawngl\u0101ng",
    "gn:population":0,
    "gn:timezone":"Asia/Yangon",
    "iso:country":"MM",
    "wof:name":"Kawnglang",
    "wof:placetype":"locality"
},
  "geometry": {"coordinates":[97.45153999999999,22.49782],"type":"Point"}
}