{
  "type": "Feature",
  "properties": {
    "gn:admin1_code":"10.0",
    "gn:admin2_code":"MMR005D002",
    "gn:admin3_code":"MMR005006",
    "gn:asciiname":"Onhnebok",
    "gn:country_code":"MM",
    "gn:dem":101,
    "gn:feature_class":"P",
    "gn:feature_code":"PPL",
    "gn:name":"Onhn\u00e8bok",
    "gn:population":0,
    "gn:timezone":"Asia/Yangon",
    "iso:country":"MM",
    "wof:name":"Onhnebok",
    "wof:placetype":"locality"
},
  "geometry": {"coordinates":[95.90527,22.23578],"type":"Point"}
}