{
  "type": "Feature",
  "properties": {
    "gn:admin1_code":"13.0",
    "gn:admin2_code":"MMR011D002",
    "gn:admin3_code":"MMR011008",
    "gn:asciiname":"Pathein",
    "gn:country_code":"MM",
    "gn:dem":15,
    "gn:feature_class":"P",
    "gn:feature_code":"PPL",
    "gn:name":"Pathein",
    "gn:population":0,
    "gn:timezone":"Asia/Yangon",
    "iso:country":"MM",
    "name:ara_x_preferred":[
        "\u0628\u0627\u062b\u064a\u0646"
    ],
    "name:cat_x_preferred":[
        "Pathein"
    ],
    "name:ceb_x_preferred":[
        "Pathein"
    ],
    "name:deu_x_preferred":[
        "Pathein"
    ],
    "name:epo_x_preferred":[
        "Patejn"
    ],
    "name:fas_x_preferred":[
        "\u067e\u0627\u062a\u06cc\u0646"
    ],
    "name:fin_x_preferred":[
        "Pathein"
    ],
    "name:fra_x_preferred":[
        "Pathein"
    ],
    "name:heb_x_preferred":[
        "\u05e4\u05d0\u05d8\u05d9\u05d9\u05df"
    ],
    "name:hin_x_preferred":[
        "\u092a\u0925\u0947\u0907\u0928"
    ],
    "name:ita_x_preferred":[
        "Pathein"
    ],
    "name:jpn_x_preferred":[
        "\u30d1\u30c6\u30a4\u30f3"
    ],
    "name:kor_x_preferred":[
        "\ud30c\ud14c\uc778"
    ],
    "name:lit_x_preferred":[
        "Patheinas"
    ],
    "name:mya_x_preferred":[
        "\u1015\u102f\u101e\u102d\u1019\u103a\u1019\u103c\u102d\u102f\u1037"
    ],
    "name:nld_x_preferred":[
        "Pathein"
    ],
    "name:nor_x_preferred":[
        "Pathein"
    ],
    "name:pol_x_preferred":[
        "Basejn"
    ],
    "name:por_x_preferred":[
        "Pathein"
    ],
    "name:rus_x_preferred":[
        "\u0411\u0430\u0441\u0441\u0435\u0439\u043d"
    ],
    "name:sco_x_preferred":[
        "Pathein"
    ],
    "name:shn_x_preferred":[
        "\u1015\u1010\u1035\u1004\u103a\u1087\u104a \u101d\u1035\u1004\u103a\u1038"
    ],
    "name:spa_x_preferred":[
        "Pathein"
    ],
    "name:swe_x_preferred":[
        "Pathein"
    ],
    "name:tam_x_preferred":[
        "\u0baa\u0bbe\u0ba4\u0bc0\u0ba9\u0bcd"
    ],
    "name:tha_x_preferred":[
        "\u0e1e\u0e30\u0e2a\u0e34\u0e21"
    ],
    "name:ukr_x_preferred":[
        "\u041f\u0430\u0442\u0435\u0439\u043d"
    ],
    "name:urd_x_preferred":[
        "\u067e\u0627\u062a\u06be\u06cc\u0646"
    ],
    "name:vie_x_preferred":[
        "Pathein"
    ],
    "name:war_x_preferred":[
        "Pathein"
    ],
    "wof:name":"Pathein",
    "wof:placetype":"locality"
},
  "geometry": {"coordinates":[97.58828,16.54604],"type":"Point"}
}