{
  "type": "Feature",
  "properties": {
    "gn:admin1_code":"12.0",
    "gn:admin2_code":"MMR006D003",
    "gn:admin3_code":"MMR006009",
    "gn:asciiname":"Koala Sungei",
    "gn:country_code":"MM",
    "gn:dem":13,
    "gn:feature_class":"P",
    "gn:feature_code":"PPL",
    "gn:name":"Koala Sung\u0113i",
    "gn:population":0,
    "gn:timezone":"Asia/Yangon",
    "iso:country":"MM",
    "name:und_x_variant":[
        "Kampong Ulu",
        "Koala Sung\u0113i"
    ],
    "wof:name":"Koala Sungei",
    "wof:placetype":"locality"
},
  "geometry": {"coordinates":[98.52331,10.04618],"type":"Point"}
}