{
  "type": "Feature",
  "properties": {
    "gn:admin1_code":"8.0",
    "gn:admin2_code":"MMR010D003",
    "gn:admin3_code":"MMR010013",
    "gn:asciiname":"Mwegon",
    "gn:country_code":"MM",
    "gn:dem":95,
    "gn:feature_class":"P",
    "gn:feature_code":"PPL",
    "gn:name":"Mwegon",
    "gn:population":0,
    "gn:timezone":"Asia/Yangon",
    "iso:country":"MM",
    "wof:name":"Mwegon",
    "wof:placetype":"locality"
},
  "geometry": {"coordinates":[96.12493000000001,21.53219],"type":"Point"}
}