{
  "type": "Feature",
  "properties": {
    "gn:admin1_code":"1.0",
    "gn:admin2_code":"MMR012D003",
    "gn:admin3_code":"MMR012013",
    "gn:asciiname":"Saingkhon",
    "gn:country_code":"MM",
    "gn:dem":6,
    "gn:feature_class":"P",
    "gn:feature_code":"PPL",
    "gn:name":"Saingkhon",
    "gn:population":0,
    "gn:timezone":"Asia/Yangon",
    "iso:country":"MM",
    "wof:name":"Saingkhon",
    "wof:placetype":"locality"
},
  "geometry": {"coordinates":[93.78628999999999,19.14267000000001],"type":"Point"}
}