{
  "type": "Feature",
  "properties": {
    "gn:admin1_code":"11.0",
    "gn:admin2_code":"MMR014D001",
    "gn:admin3_code":"MMR014010",
    "gn:asciiname":"Na-hi",
    "gn:country_code":"MM",
    "gn:dem":912,
    "gn:feature_class":"P",
    "gn:feature_code":"PPL",
    "gn:name":"Na-hi",
    "gn:population":0,
    "gn:timezone":"Asia/Yangon",
    "iso:country":"MM",
    "wof:name":"Na-hi",
    "wof:placetype":"locality"
},
  "geometry": {"coordinates":[97.08007000000001,19.9682],"type":"Point"}
}