{
  "type": "Feature",
  "properties": {
    "gn:admin1_code":"16.0",
    "gn:admin2_code":"MMR008D002",
    "gn:admin3_code":"MMR008012",
    "gn:asciiname":"Kyibinzaye",
    "gn:country_code":"MM",
    "gn:dem":29,
    "gn:feature_class":"P",
    "gn:feature_code":"PPL",
    "gn:name":"Kyibinzaye",
    "gn:population":0,
    "gn:timezone":"Asia/Yangon",
    "iso:country":"MM",
    "wof:name":"Kyibinzaye",
    "wof:placetype":"locality"
},
  "geometry": {"coordinates":[95.42803000000001,18.42158],"type":"Point"}
}