{
  "type": "Feature",
  "properties": {
    "gn:admin1_code":"11.0",
    "gn:admin2_code":"MMR016D001",
    "gn:admin3_code":"MMR016007",
    "gn:asciiname":"Hsen Long-ummoeng",
    "gn:country_code":"MM",
    "gn:dem":1085,
    "gn:feature_class":"P",
    "gn:feature_code":"PPL",
    "gn:name":"Hsen L\u014dng-umm\u00f6ng",
    "gn:population":0,
    "gn:timezone":"Asia/Yangon",
    "iso:country":"MM",
    "wof:name":"Hsen Long-ummoeng",
    "wof:placetype":"locality"
},
  "geometry": {"coordinates":[99.29437,21.2337],"type":"Point"}
}