{
  "type": "Feature",
  "properties": {
    "iso:country":"MM",
    "name:bul_x_preferred":[
        "\u041a\u044f\u0438\u043a\u0430\u043c\u0438"
    ],
    "name:cat_x_preferred":[
        "Kyaikkami"
    ],
    "name:ceb_x_preferred":[
        "Kyaikkami"
    ],
    "name:cym_x_preferred":[
        "Kyaikkami"
    ],
    "name:eng_x_preferred":[
        "Kyaikkami"
    ],
    "name:fra_x_preferred":[
        "Kyaikkami"
    ],
    "name:mya_x_preferred":[
        "\u1000\u103b\u102d\u102f\u1000\u1039\u1001\u1019\u102e\u1019\u103c\u102d\u102f\u1037"
    ],
    "name:nld_x_preferred":[
        "Kyaikkami"
    ],
    "name:shn_x_preferred":[
        "\u1075\u103b\u1085\u1075\u103a\u1089\u1076\u1019\u102e\u1087\u104a \u101d\u1035\u1004\u103a\u1038"
    ],
    "name:spa_x_preferred":[
        "Kyaikkami"
    ],
    "name:swe_x_preferred":[
        "Kyaikkami"
    ],
    "name:tha_x_preferred":[
        "\u0e44\u0e08\u0e04\u0e30\u0e21\u0e35"
    ],
    "name:unk_x_variant":[
        "Amherst"
    ],
    "name:zho_x_preferred":[
        "\u658b\u5361\u7c73"
    ],
    "qs:gn_country":"MM",
    "qs:gn_fcode":"PPL",
    "qs:gn_pop":48100,
    "qs:name":"Kyaikkami",
    "qs:name_adm0":"Myanmar",
    "qs:name_adm1":"Mon State",
    "qs:photos":0,
    "qs:photos_1k":0,
    "qs:photos_9k":1,
    "qs:photos_9r":1,
    "qs:photos_all":3,
    "qs:photos_sr":0,
    "qs:placetype":"Town",
    "qs:pop_sr":"7",
    "qs:woe_adm0":23424763,
    "wd:wordcount":678,
    "wof:name":"Kyaikkami",
    "wof:placetype":"locality",
    "wof:population":48100
},
  "geometry": {"coordinates":[97.56388,16.07686],"type":"Point"}
}