{
  "type": "Feature",
  "properties": {
    "gn:admin1_code":"8.0",
    "gn:admin2_code":"MMR010D007",
    "gn:admin3_code":"MMR010030",
    "gn:asciiname":"Ywagyi",
    "gn:country_code":"MM",
    "gn:dem":181,
    "gn:feature_class":"P",
    "gn:feature_code":"PPL",
    "gn:name":"Ywagyi",
    "gn:population":0,
    "gn:timezone":"Asia/Yangon",
    "iso:country":"MM",
    "wof:name":"Ywagyi",
    "wof:placetype":"locality"
},
  "geometry": {"coordinates":[96.00668,20.89043],"type":"Point"}
}