{
  "type": "Feature",
  "properties": {
    "gn:admin1_code":"15.0",
    "gn:admin2_code":"MMR009D003",
    "gn:admin3_code":"MMR009012",
    "gn:asciiname":"Twinle",
    "gn:country_code":"MM",
    "gn:dem":67,
    "gn:feature_class":"P",
    "gn:feature_code":"PPL",
    "gn:name":"Twinl\u00e8",
    "gn:population":0,
    "gn:timezone":"Asia/Yangon",
    "iso:country":"MM",
    "wof:name":"Twinle",
    "wof:placetype":"locality"
},
  "geometry": {"coordinates":[95.01212,19.29538],"type":"Point"}
}