{
  "type": "Feature",
  "properties": {
    "gn:admin1_code":"10.0",
    "gn:admin2_code":"MMR005D008",
    "gn:admin3_code":"MMR005037",
    "gn:asciiname":"Wakkai",
    "gn:country_code":"MM",
    "gn:dem":1236,
    "gn:feature_class":"P",
    "gn:feature_code":"PPL",
    "gn:name":"W\u0101kkai",
    "gn:population":0,
    "gn:timezone":"Asia/Yangon",
    "iso:country":"MM",
    "wof:name":"Wakkai",
    "wof:placetype":"locality"
},
  "geometry": {"coordinates":[95.53671,26.65672],"type":"Point"}
}