{
  "type": "Feature",
  "properties": {
    "gn:admin1_code":"8.0",
    "gn:admin2_code":"MMR010D007",
    "gn:admin3_code":"MMR010028",
    "gn:asciiname":"Kywegan",
    "gn:country_code":"MM",
    "gn:dem":312,
    "gn:feature_class":"P",
    "gn:feature_code":"PPL",
    "gn:name":"Kywegan",
    "gn:population":0,
    "gn:timezone":"Asia/Yangon",
    "iso:country":"MM",
    "name:und_x_variant":[
        "Kyawegon",
        "Kywegan"
    ],
    "wof:name":"Kywegan",
    "wof:placetype":"locality"
},
  "geometry": {"coordinates":[95.72099,20.66708],"type":"Point"}
}