{
  "type": "Feature",
  "properties": {
    "gn:admin1_code":"11.0",
    "gn:admin2_code":"MMR014D002",
    "gn:admin3_code":"MMR014014",
    "gn:asciiname":"Wan Loi-hseng",
    "gn:country_code":"MM",
    "gn:dem":1227,
    "gn:feature_class":"P",
    "gn:feature_code":"PPL",
    "gn:name":"W\u0101n Loi-hseng",
    "gn:population":0,
    "gn:timezone":"Asia/Yangon",
    "iso:country":"MM",
    "wof:name":"Wan Loi-hseng",
    "wof:placetype":"locality"
},
  "geometry": {"coordinates":[98.47172999999999,21.49836],"type":"Point"}
}