{
  "type": "Feature",
  "properties": {
    "gn:admin1_code":"11.0",
    "gn:admin2_code":"MMR014D002",
    "gn:admin3_code":"MMR014012",
    "gn:asciiname":"Nawngwawn",
    "gn:country_code":"MM",
    "gn:dem":941,
    "gn:feature_class":"P",
    "gn:feature_code":"PPL",
    "gn:name":"Nawngwawn",
    "gn:population":0,
    "gn:timezone":"Asia/Yangon",
    "iso:country":"MM",
    "name:cat_x_preferred":[
        "Nawngwawn"
    ],
    "name:lat_x_preferred":[
        "Nawngwawn"
    ],
    "wof:name":"Nawngwawn",
    "wof:placetype":"locality"
},
  "geometry": {"coordinates":[97.94156,21.04539],"type":"Point"}
}