{
  "type": "Feature",
  "properties": {
    "gn:admin1_code":"5.0",
    "gn:admin2_code":"MMR003D004",
    "gn:admin3_code":"MMR003003",
    "gn:asciiname":"Nankhukhi",
    "gn:country_code":"MM",
    "gn:dem":110,
    "gn:feature_class":"P",
    "gn:feature_code":"PPL",
    "gn:name":"Nankhukhi",
    "gn:population":0,
    "gn:timezone":"Asia/Yangon",
    "iso:country":"MM",
    "name:und_x_variant":[
        "Nankhukhio",
        "Nankhukhi"
    ],
    "wof:name":"Nankhukhi",
    "wof:placetype":"locality"
},
  "geometry": {"coordinates":[97.35218999999999,17.91567000000001],"type":"Point"}
}