{
  "type": "Feature",
  "properties": {
    "gn:admin1_code":"16.0",
    "gn:admin2_code":"MMR008D002",
    "gn:admin3_code":"MMR008007",
    "gn:asciiname":"Yindaikkon",
    "gn:country_code":"MM",
    "gn:dem":23,
    "gn:feature_class":"P",
    "gn:feature_code":"PPL",
    "gn:name":"Yindaikkon",
    "gn:population":0,
    "gn:timezone":"Asia/Yangon",
    "iso:country":"MM",
    "wof:name":"Yindaikkon",
    "wof:placetype":"locality"
},
  "geometry": {"coordinates":[95.67892999999999,17.65533],"type":"Point"}
}