{
  "type": "Feature",
  "properties": {
    "gn:admin1_code":"11.0",
    "gn:admin2_code":"MMR014D001",
    "gn:admin3_code":"MMR014001",
    "gn:asciiname":"Kyawkta-long",
    "gn:country_code":"MM",
    "gn:dem":1260,
    "gn:feature_class":"P",
    "gn:feature_code":"PPL",
    "gn:name":"Kyawkta-long",
    "gn:population":0,
    "gn:timezone":"Asia/Yangon",
    "iso:country":"MM",
    "wof:name":"Kyawkta-long",
    "wof:placetype":"locality"
},
  "geometry": {"coordinates":[97.0275,20.37243],"type":"Point"}
}