{
  "type": "Feature",
  "properties": {
    "gn:admin1_code":"11.0",
    "gn:admin2_code":"MMR014D001",
    "gn:admin3_code":"MMR014003",
    "gn:asciiname":"Moengkawk",
    "gn:country_code":"MM",
    "gn:dem":1046,
    "gn:feature_class":"P",
    "gn:feature_code":"PPL",
    "gn:name":"M\u00f6ngkawk",
    "gn:population":0,
    "gn:timezone":"Asia/Yangon",
    "iso:country":"MM",
    "wof:name":"Moengkawk",
    "wof:placetype":"locality"
},
  "geometry": {"coordinates":[97.44589000000001,20.78819],"type":"Point"}
}