{
  "type": "Feature",
  "properties": {
    "gn:admin1_code":"8.0",
    "gn:admin2_code":"MMR010D006",
    "gn:admin3_code":"MMR010023",
    "gn:asciiname":"Pyinbya",
    "gn:country_code":"MM",
    "gn:dem":258,
    "gn:feature_class":"P",
    "gn:feature_code":"PPL",
    "gn:name":"Pyinbya",
    "gn:population":0,
    "gn:timezone":"Asia/Yangon",
    "iso:country":"MM",
    "wof:name":"Pyinbya",
    "wof:placetype":"locality"
},
  "geometry": {"coordinates":[96.25323,20.43893],"type":"Point"}
}