{
  "type": "Feature",
  "properties": {
    "gn:admin1_code":"8.0",
    "gn:admin2_code":"MMR010D006",
    "gn:admin3_code":"MMR010023",
    "gn:asciiname":"Pyinbya",
    "gn:country_code":"MM",
    "gn:dem":258,
    "gn:feature_class":"P",
    "gn:feature_code":"PPL",
    "gn:name":"Pyinbya",
    "gn:population":0,
    "gn:timezone":"Asia/Yangon",
    "iso:country":"MM",
    "name:deu_x_preferred":[
        "Pyinbya"
    ],
    "name:fra_x_preferred":[
        "Pyinbya"
    ],
    "name:ind_x_preferred":[
        "Pyinbya"
    ],
    "name:mya_x_preferred":[
        "\u1015\u103b\u1009\u103a\u1015\u103c\u102c\u1038\u1019\u1004\u103a\u1038"
    ],
    "name:pol_x_preferred":[
        "Pyinbya"
    ],
    "name:tha_x_preferred":[
        "\u0e1e\u0e23\u0e30\u0e40\u0e08\u0e49\u0e32\u0e1b\u0e22\u0e35\u0e19-\u0e1a\u0e22\u0e48\u0e32"
    ],
    "wof:name":"Pyinbya",
    "wof:placetype":"locality"
},
  "geometry": {"coordinates":[96.25323,20.43893],"type":"Point"}
}