{
  "type": "Feature",
  "properties": {
    "gn:admin1_code":"15.0",
    "gn:admin2_code":"MMR009D001",
    "gn:admin3_code":"MMR009005",
    "gn:asciiname":"Kaingywa",
    "gn:country_code":"MM",
    "gn:dem":165,
    "gn:feature_class":"P",
    "gn:feature_code":"PPL",
    "gn:name":"Kaingywa",
    "gn:population":0,
    "gn:timezone":"Asia/Yangon",
    "iso:country":"MM",
    "name:und_x_variant":[
        "Kanywa",
        "Kaingywa"
    ],
    "wof:name":"Kaingywa",
    "wof:placetype":"locality"
},
  "geometry": {"coordinates":[95.40509,20.28251],"type":"Point"}
}