{
  "type": "Feature",
  "properties": {
    "gn:admin1_code":"10.0",
    "gn:asciiname":"Sinbyugon",
    "gn:country_code":"MM",
    "gn:dem":75,
    "gn:feature_class":"P",
    "gn:feature_code":"PPL",
    "gn:name":"Sinbyugon",
    "gn:population":0,
    "gn:timezone":"Asia/Yangon",
    "iso:country":"MM",
    "wof:name":"Sinbyugon",
    "wof:placetype":"locality"
},
  "geometry": {"coordinates":[95.54272,21.85828],"type":"Point"}
}