{
  "type": "Feature",
  "properties": {
    "gn:admin1_code":"12.0",
    "gn:admin2_code":"MMR006D002",
    "gn:admin3_code":"MMR006008",
    "gn:asciiname":"Banlamut",
    "gn:country_code":"MM",
    "gn:dem":43,
    "gn:feature_class":"P",
    "gn:feature_code":"PPL",
    "gn:name":"Banlamut",
    "gn:population":0,
    "gn:timezone":"Asia/Yangon",
    "iso:country":"MM",
    "wof:name":"Banlamut",
    "wof:placetype":"locality"
},
  "geometry": {"coordinates":[98.95565999999999,12.16891],"type":"Point"}
}