{
  "type": "Feature",
  "properties": {
    "gn:admin1_code":"11.0",
    "gn:admin2_code":"MMR015D003",
    "gn:admin3_code":"MMR015013",
    "gn:asciiname":"Nawnghkio-long",
    "gn:country_code":"MM",
    "gn:dem":1011,
    "gn:feature_class":"P",
    "gn:feature_code":"PPL",
    "gn:name":"Nawnghkio-long",
    "gn:population":0,
    "gn:timezone":"Asia/Yangon",
    "iso:country":"MM",
    "wof:name":"Nawnghkio-long",
    "wof:placetype":"locality"
},
  "geometry": {"coordinates":[96.91203,22.23237],"type":"Point"}
}