{
  "type": "Feature",
  "properties": {
    "gn:admin1_code":"15.0",
    "gn:admin2_code":"MMR009D004",
    "gn:admin3_code":"MMR009022",
    "gn:asciiname":"Kabagyi",
    "gn:country_code":"MM",
    "gn:dem":64,
    "gn:feature_class":"P",
    "gn:feature_code":"PPL",
    "gn:name":"Kabagyi",
    "gn:population":0,
    "gn:timezone":"Asia/Yangon",
    "iso:country":"MM",
    "wof:name":"Kabagyi",
    "wof:placetype":"locality"
},
  "geometry": {"coordinates":[94.74594,20.88855],"type":"Point"}
}