{
  "type": "Feature",
  "properties": {
    "gn:admin1_code":"15.0",
    "gn:admin2_code":"MMR009D004",
    "gn:admin3_code":"MMR009020",
    "gn:asciiname":"Nyaungywa",
    "gn:country_code":"MM",
    "gn:dem":263,
    "gn:feature_class":"P",
    "gn:feature_code":"PPL",
    "gn:name":"Nyaungywa",
    "gn:population":0,
    "gn:timezone":"Asia/Yangon",
    "iso:country":"MM",
    "wof:name":"Nyaungywa",
    "wof:placetype":"locality"
},
  "geometry": {"coordinates":[94.81453,21.49102],"type":"Point"}
}