{
  "type": "Feature",
  "properties": {
    "gn:admin1_code":"15.0",
    "gn:admin2_code":"MMR009D001",
    "gn:admin3_code":"MMR009001",
    "gn:asciiname":"Thabutkyaw",
    "gn:country_code":"MM",
    "gn:dem":112,
    "gn:feature_class":"P",
    "gn:feature_code":"PPL",
    "gn:name":"Thabutkyaw",
    "gn:population":0,
    "gn:timezone":"Asia/Yangon",
    "iso:country":"MM",
    "wof:name":"Thabutkyaw",
    "wof:placetype":"locality"
},
  "geometry": {"coordinates":[95.21453,19.84053],"type":"Point"}
}