{
  "type": "Feature",
  "properties": {
    "gn:admin1_code":"16.0",
    "gn:admin2_code":"MMR007D001",
    "gn:admin3_code":"MMR007007",
    "gn:asciiname":"Pyindaungdwin",
    "gn:country_code":"MM",
    "gn:dem":25,
    "gn:feature_class":"P",
    "gn:feature_code":"PPL",
    "gn:name":"Pyindaungdwin",
    "gn:population":0,
    "gn:timezone":"Asia/Yangon",
    "iso:country":"MM",
    "wof:name":"Pyindaungdwin",
    "wof:placetype":"locality"
},
  "geometry": {"coordinates":[96.54295,17.72621000000001],"type":"Point"}
}