{
  "type": "Feature",
  "properties": {
    "gn:admin1_code":"11.0",
    "gn:admin2_code":"MMR014D001",
    "gn:admin3_code":"MMR014001",
    "gn:asciiname":"Makhpa-sut",
    "gn:country_code":"MM",
    "gn:dem":1399,
    "gn:feature_class":"P",
    "gn:feature_code":"PPL",
    "gn:name":"Makhpa-sut",
    "gn:population":0,
    "gn:timezone":"Asia/Yangon",
    "iso:country":"MM",
    "wof:name":"Makhpa-sut",
    "wof:placetype":"locality"
},
  "geometry": {"coordinates":[97.08642999999999,20.75561],"type":"Point"}
}