{
  "type": "Feature",
  "properties": {
    "gn:admin1_code":"12.0",
    "gn:admin2_code":"MMR006D001",
    "gn:admin3_code":"MMR006001",
    "gn:asciiname":"Taungthonlon",
    "gn:country_code":"MM",
    "gn:dem":219,
    "gn:feature_class":"P",
    "gn:feature_code":"PPL",
    "gn:name":"Taungthonlon",
    "gn:population":0,
    "gn:timezone":"Asia/Yangon",
    "iso:country":"MM",
    "wof:name":"Taungthonlon",
    "wof:placetype":"locality"
},
  "geometry": {"coordinates":[98.45959999999999,14.16535],"type":"Point"}
}