{
  "type": "Feature",
  "properties": {
    "gn:admin1_code":"1.0",
    "gn:admin2_code":"MMR012D001",
    "gn:admin3_code":"MMR012002",
    "gn:asciiname":"Pezinan",
    "gn:country_code":"MM",
    "gn:dem":5,
    "gn:feature_class":"P",
    "gn:feature_code":"PPL",
    "gn:name":"Pezinan",
    "gn:population":0,
    "gn:timezone":"Asia/Yangon",
    "iso:country":"MM",
    "wof:name":"Pezinan",
    "wof:placetype":"locality"
},
  "geometry": {"coordinates":[93.02133000000001,20.46146],"type":"Point"}
}