{
  "type": "Feature",
  "properties": {
    "gn:admin1_code":"11.0",
    "gn:admin2_code":"MMR015D003",
    "gn:admin3_code":"MMR015019",
    "gn:asciiname":"Man Mao",
    "gn:country_code":"MM",
    "gn:dem":1140,
    "gn:feature_class":"P",
    "gn:feature_code":"PPL",
    "gn:name":"M\u0101n Mao",
    "gn:population":0,
    "gn:timezone":"Asia/Yangon",
    "iso:country":"MM",
    "name:und_x_variant":[
        "M\u0101n Mau",
        "M\u0101n Mao"
    ],
    "wof:name":"Man Mao",
    "wof:placetype":"locality"
},
  "geometry": {"coordinates":[97.29611,23.47141],"type":"Point"}
}