{
  "type": "Feature",
  "properties": {
    "gn:admin1_code":"17.0",
    "gn:admin2_code":"MMR013D002",
    "gn:admin3_code":"MMR013020",
    "gn:asciiname":"Kyizu",
    "gn:country_code":"MM",
    "gn:dem":11,
    "gn:feature_class":"P",
    "gn:feature_code":"PPL",
    "gn:name":"Kyizu",
    "gn:population":0,
    "gn:timezone":"Asia/Yangon",
    "iso:country":"MM",
    "name:und_x_variant":[
        "Kyizy",
        "Kyizu"
    ],
    "wof:name":"Kyizu",
    "wof:placetype":"locality"
},
  "geometry": {"coordinates":[96.28655000000001,16.89184],"type":"Point"}
}