{
  "type": "Feature",
  "properties": {
    "gn:admin1_code":"10.0",
    "gn:admin2_code":"MMR005D009",
    "gn:admin3_code":"MMR005018",
    "gn:asciiname":"Salingyi",
    "gn:country_code":"MM",
    "gn:dem":102,
    "gn:feature_class":"P",
    "gn:feature_code":"PPL",
    "gn:name":"Salingyi",
    "gn:population":0,
    "gn:timezone":"Asia/Yangon",
    "iso:country":"MM",
    "wof:name":"Salingyi",
    "wof:placetype":"locality"
},
  "geometry": {"coordinates":[95.07773,21.97465],"type":"Point"}
}