{
  "type": "Feature",
  "properties": {
    "gn:admin1_code":"11.0",
    "gn:admin2_code":"MMR015D006",
    "gn:admin3_code":"MMR015008",
    "gn:asciiname":"Myingwe",
    "gn:country_code":"MM",
    "gn:dem":1539,
    "gn:feature_class":"P",
    "gn:feature_code":"PPL",
    "gn:name":"Myingwe",
    "gn:population":0,
    "gn:timezone":"Asia/Yangon",
    "iso:country":"MM",
    "wof:name":"Myingwe",
    "wof:placetype":"locality"
},
  "geometry": {"coordinates":[98.80195999999999,22.75755],"type":"Point"}
}