{
  "type": "Feature",
  "properties": {
    "gn:admin1_code":"16.0",
    "gn:admin2_code":"MMR008D001",
    "gn:admin3_code":"MMR008003",
    "gn:asciiname":"Hpalo",
    "gn:country_code":"MM",
    "gn:dem":43,
    "gn:feature_class":"P",
    "gn:feature_code":"PPL",
    "gn:name":"Hpalo",
    "gn:population":0,
    "gn:timezone":"Asia/Yangon",
    "iso:country":"MM",
    "wof:name":"Hpalo",
    "wof:placetype":"locality"
},
  "geometry": {"coordinates":[94.95328000000001,18.5577],"type":"Point"}
}