{
  "type": "Feature",
  "properties": {
    "gn:admin1_code":"2.0",
    "gn:admin2_code":"MMR004D002",
    "gn:admin3_code":"MMR004009",
    "gn:asciiname":"Kha",
    "gn:country_code":"MM",
    "gn:dem":114,
    "gn:feature_class":"P",
    "gn:feature_code":"PPL",
    "gn:name":"Kha",
    "gn:population":0,
    "gn:timezone":"Asia/Yangon",
    "iso:country":"MM",
    "name:deu_x_preferred":[
        "Kha"
    ],
    "wof:name":"Kha",
    "wof:placetype":"locality"
},
  "geometry": {"coordinates":[93.06667,21.41667],"type":"Point"}
}