{
  "type": "Feature",
  "properties": {
    "gn:admin1_code":"15.0",
    "gn:admin2_code":"MMR009D001",
    "gn:admin3_code":"MMR009003",
    "gn:asciiname":"Thanbin",
    "gn:country_code":"MM",
    "gn:dem":378,
    "gn:feature_class":"P",
    "gn:feature_code":"PPL",
    "gn:name":"Thanbin",
    "gn:population":0,
    "gn:timezone":"Asia/Yangon",
    "iso:country":"MM",
    "wof:name":"Thanbin",
    "wof:placetype":"locality"
},
  "geometry": {"coordinates":[94.94611,20.65507],"type":"Point"}
}