{
  "type": "Feature",
  "properties": {
    "gn:admin1_code":"15.0",
    "gn:admin2_code":"MMR009D002",
    "gn:admin3_code":"MMR009009",
    "gn:asciiname":"Inbo",
    "gn:country_code":"MM",
    "gn:dem":682,
    "gn:feature_class":"P",
    "gn:feature_code":"PPL",
    "gn:name":"Inbo",
    "gn:population":0,
    "gn:timezone":"Asia/Yangon",
    "iso:country":"MM",
    "wof:name":"Inbo",
    "wof:placetype":"locality"
},
  "geometry": {"coordinates":[94.41151000000001,19.9353],"type":"Point"}
}