{
  "type": "Feature",
  "properties": {
    "gn:admin1_code":"1.0",
    "gn:admin2_code":"MMR012D005",
    "gn:admin3_code":"MMR012004",
    "gn:asciiname":"Kokpedaung",
    "gn:country_code":"MM",
    "gn:dem":8,
    "gn:feature_class":"P",
    "gn:feature_code":"PPL",
    "gn:name":"Kokpedaung",
    "gn:population":0,
    "gn:timezone":"Asia/Yangon",
    "iso:country":"MM",
    "name:und_x_variant":[
        "Kokpe Taung",
        "Kokpedaung"
    ],
    "wof:name":"Kokpedaung",
    "wof:placetype":"locality"
},
  "geometry": {"coordinates":[93.01494,20.71038],"type":"Point"}
}