{
  "type": "Feature",
  "properties": {
    "gn:admin1_code":"11.0",
    "gn:admin2_code":"MMR016D002",
    "gn:admin3_code":"MMR016006",
    "gn:asciiname":"Wan Ta",
    "gn:country_code":"MM",
    "gn:dem":589,
    "gn:feature_class":"P",
    "gn:feature_code":"PPL",
    "gn:name":"W\u0101n Ta",
    "gn:population":0,
    "gn:timezone":"Asia/Yangon",
    "iso:country":"MM",
    "wof:name":"Wan Ta",
    "wof:placetype":"locality"
},
  "geometry": {"coordinates":[99.29470999999999,20.45207000000001],"type":"Point"}
}