{
  "type": "Feature",
  "properties": {
    "gn:admin1_code":"6.0",
    "gn:admin2_code":"MMR002D001",
    "gn:admin3_code":"MMR002002",
    "gn:asciiname":"Ngwedaung",
    "gn:country_code":"MM",
    "gn:dem":903,
    "gn:feature_class":"P",
    "gn:feature_code":"PPL",
    "gn:name":"Ngwedaung",
    "gn:population":0,
    "gn:timezone":"Asia/Yangon",
    "iso:country":"MM",
    "name:und_x_variant":[
        "Loingum",
        "Ngwedaung"
    ],
    "wof:name":"Ngwedaung",
    "wof:placetype":"locality"
},
  "geometry": {"coordinates":[97.18165999999999,19.5607],"type":"Point"}
}