{
  "type": "Feature",
  "properties": {
    "gn:admin1_code":"11.0",
    "gn:admin2_code":"MMR016D002",
    "gn:admin3_code":"MMR016008",
    "gn:asciiname":"Wan Panka",
    "gn:country_code":"MM",
    "gn:dem":1064,
    "gn:feature_class":"P",
    "gn:feature_code":"PPL",
    "gn:name":"W\u0101n P\u0101nka",
    "gn:population":0,
    "gn:timezone":"Asia/Yangon",
    "iso:country":"MM",
    "wof:name":"Wan Panka",
    "wof:placetype":"locality"
},
  "geometry": {"coordinates":[98.75857999999999,20.40113],"type":"Point"}
}