{
  "type": "Feature",
  "properties": {
    "gn:admin1_code":"8.0",
    "gn:admin2_code":"MMR010D007",
    "gn:admin3_code":"MMR010031",
    "gn:asciiname":"Palangyin",
    "gn:country_code":"MM",
    "gn:dem":182,
    "gn:feature_class":"P",
    "gn:feature_code":"PPL",
    "gn:name":"Palangyin",
    "gn:population":0,
    "gn:timezone":"Asia/Yangon",
    "iso:country":"MM",
    "wof:name":"Palangyin",
    "wof:placetype":"locality"
},
  "geometry": {"coordinates":[95.87992,21.10313],"type":"Point"}
}