{
  "type": "Feature",
  "properties": {
    "gn:admin1_code":"6.0",
    "gn:admin2_code":"MMR002D001",
    "gn:admin3_code":"MMR002001",
    "gn:asciiname":"Dawhsaw-we",
    "gn:country_code":"MM",
    "gn:dem":821,
    "gn:feature_class":"P",
    "gn:feature_code":"PPL",
    "gn:name":"Dawhsaw-w\u00e8",
    "gn:population":0,
    "gn:timezone":"Asia/Yangon",
    "iso:country":"MM",
    "wof:name":"Dawhsaw-we",
    "wof:placetype":"locality"
},
  "geometry": {"coordinates":[97.27018,19.85581],"type":"Point"}
}