{
  "type": "Feature",
  "properties": {
    "gn:admin1_code":"11.0",
    "gn:admin2_code":"MMR016D002",
    "gn:admin3_code":"MMR016006",
    "gn:asciiname":"Kawngmu-ai-sawk",
    "gn:country_code":"MM",
    "gn:dem":684,
    "gn:feature_class":"P",
    "gn:feature_code":"PPL",
    "gn:name":"Kawngmu-ai-sawk",
    "gn:population":0,
    "gn:timezone":"Asia/Yangon",
    "iso:country":"MM",
    "wof:name":"Kawngmu-ai-sawk",
    "wof:placetype":"locality"
},
  "geometry": {"coordinates":[99.12515999999999,20.45499],"type":"Point"}
}