{
  "type": "Feature",
  "properties": {
    "gn:admin1_code":"6.0",
    "gn:admin2_code":"MMR002D002",
    "gn:admin3_code":"MMR002005",
    "gn:asciiname":"Dawso-hpa",
    "gn:country_code":"MM",
    "gn:dem":776,
    "gn:feature_class":"P",
    "gn:feature_code":"PPL",
    "gn:name":"Dawso-hpa",
    "gn:population":0,
    "gn:timezone":"Asia/Yangon",
    "iso:country":"MM",
    "wof:name":"Dawso-hpa",
    "wof:placetype":"locality"
},
  "geometry": {"coordinates":[97.47785,19.30897],"type":"Point"}
}