{
  "type": "Feature",
  "properties": {
    "gn:admin1_code":"15.0",
    "gn:admin2_code":"MMR009D004",
    "gn:admin3_code":"MMR009021",
    "gn:asciiname":"Nyaungbintha",
    "gn:country_code":"MM",
    "gn:dem":182,
    "gn:feature_class":"P",
    "gn:feature_code":"PPL",
    "gn:name":"Nyaungbintha",
    "gn:population":0,
    "gn:timezone":"Asia/Yangon",
    "iso:country":"MM",
    "wof:name":"Nyaungbintha",
    "wof:placetype":"locality"
},
  "geometry": {"coordinates":[94.41359,21.55767],"type":"Point"}
}