{
  "type": "Feature",
  "properties": {
    "gn:admin1_code":"11.0",
    "gn:admin2_code":"MMR015D002",
    "gn:admin3_code":"MMR015010",
    "gn:asciiname":"U-mya",
    "gn:country_code":"MM",
    "gn:dem":1554,
    "gn:feature_class":"P",
    "gn:feature_code":"PPL",
    "gn:name":"U-mya",
    "gn:population":0,
    "gn:timezone":"Asia/Yangon",
    "iso:country":"MM",
    "wof:name":"U-mya",
    "wof:placetype":"locality"
},
  "geometry": {"coordinates":[97.82313000000001,23.78826],"type":"Point"}
}