{
  "type": "Feature",
  "properties": {
    "gn:admin1_code":"8.0",
    "gn:admin2_code":"MMR010D004",
    "gn:admin3_code":"MMR010017",
    "gn:asciiname":"Balon",
    "gn:country_code":"MM",
    "gn:dem":130,
    "gn:feature_class":"P",
    "gn:feature_code":"PPL",
    "gn:name":"Balon",
    "gn:population":0,
    "gn:timezone":"Asia/Yangon",
    "iso:country":"MM",
    "wof:name":"Balon",
    "wof:placetype":"locality"
},
  "geometry": {"coordinates":[95.47377,21.45332],"type":"Point"}
}