{
  "type": "Feature",
  "properties": {
    "gn:admin1_code":"16.0",
    "gn:admin2_code":"MMR007D001",
    "gn:admin3_code":"MMR007002",
    "gn:asciiname":"Kalagyaunggyi",
    "gn:country_code":"MM",
    "gn:dem":12,
    "gn:feature_class":"P",
    "gn:feature_code":"PPL",
    "gn:name":"Kalagyaunggyi",
    "gn:population":0,
    "gn:timezone":"Asia/Yangon",
    "iso:country":"MM",
    "name:und_x_variant":[
        "Kalachaunggyi",
        "Kalagyaunggyi"
    ],
    "wof:name":"Kalagyaunggyi",
    "wof:placetype":"locality"
},
  "geometry": {"coordinates":[96.77291,17.25079],"type":"Point"}
}