{
  "type": "Feature",
  "properties": {
    "gn:admin1_code":"11.0",
    "gn:admin2_code":"MMR015D001",
    "gn:admin3_code":"MMR015004",
    "gn:asciiname":"Man Mak",
    "gn:country_code":"MM",
    "gn:dem":991,
    "gn:feature_class":"P",
    "gn:feature_code":"PPL",
    "gn:name":"M\u0101n Mak",
    "gn:population":0,
    "gn:timezone":"Asia/Yangon",
    "iso:country":"MM",
    "wof:name":"Man Mak",
    "wof:placetype":"locality"
},
  "geometry": {"coordinates":[98.44631,22.52924],"type":"Point"}
}