{
  "type": "Feature",
  "properties": {
    "gn:admin1_code":"10.0",
    "gn:admin2_code":"MMR005D004",
    "gn:admin3_code":"MMR005024",
    "gn:asciiname":"Nyaungwun",
    "gn:country_code":"MM",
    "gn:dem":177,
    "gn:feature_class":"P",
    "gn:feature_code":"PPL",
    "gn:name":"Nyaungwun",
    "gn:population":0,
    "gn:timezone":"Asia/Yangon",
    "iso:country":"MM",
    "wof:name":"Nyaungwun",
    "wof:placetype":"locality"
},
  "geometry": {"coordinates":[95.68501999999999,23.73449],"type":"Point"}
}