{
  "type": "Feature",
  "properties": {
    "gn:admin1_code":"11.0",
    "gn:admin2_code":"MMR014D001",
    "gn:admin3_code":"MMR014008",
    "gn:asciiname":"Wan Tonghpa-leng",
    "gn:country_code":"MM",
    "gn:dem":635,
    "gn:feature_class":"P",
    "gn:feature_code":"PPL",
    "gn:name":"W\u0101n Tonghpa-leng",
    "gn:population":0,
    "gn:timezone":"Asia/Yangon",
    "iso:country":"MM",
    "wof:name":"Wan Tonghpa-leng",
    "wof:placetype":"locality"
},
  "geometry": {"coordinates":[97.06867,21.76562],"type":"Point"}
}