{
  "type": "Feature",
  "properties": {
    "gn:admin1_code":"11.0",
    "gn:admin2_code":"MMR014D001",
    "gn:admin3_code":"MMR014008",
    "gn:asciiname":"Kongnyawng",
    "gn:country_code":"MM",
    "gn:dem":832,
    "gn:feature_class":"P",
    "gn:feature_code":"PPL",
    "gn:name":"Kongnyawng",
    "gn:population":0,
    "gn:timezone":"Asia/Yangon",
    "iso:country":"MM",
    "name:und_x_variant":[
        "K\u00f6ngnyawg",
        "Kongnyawng"
    ],
    "wof:name":"Kongnyawng",
    "wof:placetype":"locality"
},
  "geometry": {"coordinates":[97.02827000000001,22.20159],"type":"Point"}
}