{
  "type": "Feature",
  "properties": {
    "gn:admin1_code":"10.0",
    "gn:admin2_code":"MMR005D008",
    "gn:admin3_code":"MMR005037",
    "gn:asciiname":"Yuyut",
    "gn:country_code":"MM",
    "gn:dem":1000,
    "gn:feature_class":"P",
    "gn:feature_code":"PPL",
    "gn:name":"Y\u016by\u016bt",
    "gn:population":0,
    "gn:timezone":"Asia/Yangon",
    "iso:country":"MM",
    "wof:name":"Yuyut",
    "wof:placetype":"locality"
},
  "geometry": {"coordinates":[96.01134999999999,26.98635],"type":"Point"}
}