{
  "type": "Feature",
  "properties": {
    "gn:admin1_code":"10.0",
    "gn:admin2_code":"MMR005D003",
    "gn:admin3_code":"MMR005013",
    "gn:asciiname":"Kyetyogon",
    "gn:country_code":"MM",
    "gn:dem":104,
    "gn:feature_class":"P",
    "gn:feature_code":"PPL",
    "gn:name":"Kyetyogon",
    "gn:population":0,
    "gn:timezone":"Asia/Yangon",
    "iso:country":"MM",
    "name:und_x_variant":[
        "Kyetogon",
        "Kyetyogon"
    ],
    "wof:name":"Kyetyogon",
    "wof:placetype":"locality"
},
  "geometry": {"coordinates":[95.08886,22.38895],"type":"Point"}
}