{
  "type": "Feature",
  "properties": {
    "gn:admin1_code":"4.0",
    "gn:admin2_code":"MMR001D002",
    "gn:admin3_code":"MMR001009",
    "gn:asciiname":"Ngumgahtawng",
    "gn:country_code":"MM",
    "gn:dem":480,
    "gn:feature_class":"P",
    "gn:feature_code":"PPL",
    "gn:name":"Ngumgahtawng",
    "gn:population":0,
    "gn:timezone":"Asia/Yangon",
    "iso:country":"MM",
    "name:und_x_variant":[
        "\u2019Ngum Ga",
        "Ngumgahtawng"
    ],
    "wof:name":"Ngumgahtawng",
    "wof:placetype":"locality"
},
  "geometry": {"coordinates":[96.72944,25.77314],"type":"Point"}
}