{
  "type": "Feature",
  "properties": {
    "gn:admin1_code":"11.0",
    "gn:admin2_code":"MMR015D001",
    "gn:admin3_code":"MMR015001",
    "gn:asciiname":"Namee",
    "gn:country_code":"MM",
    "gn:dem":814,
    "gn:feature_class":"P",
    "gn:feature_code":"PPL",
    "gn:name":"Namee",
    "gn:population":0,
    "gn:timezone":"Asia/Yangon",
    "iso:country":"MM",
    "name:und_x_variant":[
        "Nami",
        "Namee"
    ],
    "wof:name":"Namee",
    "wof:placetype":"locality"
},
  "geometry": {"coordinates":[97.90091,22.98776],"type":"Point"}
}