{
  "type": "Feature",
  "properties": {
    "gn:admin1_code":"6.0",
    "gn:admin2_code":"MMR002D001",
    "gn:admin3_code":"MMR002004",
    "gn:asciiname":"Wan Hson-kwe",
    "gn:country_code":"MM",
    "gn:dem":338,
    "gn:feature_class":"P",
    "gn:feature_code":"PPL",
    "gn:name":"W\u0101n Hs\u014dn-kw\u00e8",
    "gn:population":0,
    "gn:timezone":"Asia/Yangon",
    "iso:country":"MM",
    "wof:name":"Wan Hson-kwe",
    "wof:placetype":"locality"
},
  "geometry": {"coordinates":[97.52070000000001,19.64856],"type":"Point"}
}