{
  "type": "Feature",
  "properties": {
    "gn:admin1_code":"11.0",
    "gn:admin2_code":"MMR014D003",
    "gn:admin3_code":"MMR014019",
    "gn:asciiname":"Wan Namtomhkoe-moenga",
    "gn:country_code":"MM",
    "gn:dem":642,
    "gn:feature_class":"P",
    "gn:feature_code":"PPL",
    "gn:name":"W\u0101n Namtomhk\u00f6-m\u00f6ng\u0101",
    "gn:population":0,
    "gn:timezone":"Asia/Yangon",
    "iso:country":"MM",
    "wof:name":"Wan Namtomhkoe-moenga",
    "wof:placetype":"locality"
},
  "geometry": {"coordinates":[98.30273,20.74937000000001],"type":"Point"}
}