{
  "type": "Feature",
  "properties": {
    "gn:admin1_code":"11.0",
    "gn:admin2_code":"MMR015D007",
    "gn:admin3_code":"MMR015024",
    "gn:asciiname":"Yawnghkumwantaue",
    "gn:country_code":"MM",
    "gn:dem":1075,
    "gn:feature_class":"P",
    "gn:feature_code":"PPL",
    "gn:name":"Yawnghkumwanta\u00fc",
    "gn:population":0,
    "gn:timezone":"Asia/Yangon",
    "iso:country":"MM",
    "wof:name":"Yawnghkumwantaue",
    "wof:placetype":"locality"
},
  "geometry": {"coordinates":[98.82648,21.80288],"type":"Point"}
}