{
  "type": "Feature",
  "properties": {
    "gn:admin1_code":"11.0",
    "gn:admin2_code":"MMR014D002",
    "gn:admin3_code":"MMR014014",
    "gn:asciiname":"Wan Ho-tang",
    "gn:country_code":"MM",
    "gn:dem":366,
    "gn:feature_class":"P",
    "gn:feature_code":"PPL",
    "gn:name":"W\u0101n Ho-tang",
    "gn:population":0,
    "gn:timezone":"Asia/Yangon",
    "iso:country":"MM",
    "name:und_x_variant":[
        "Ho-tang",
        "W\u0101n Ho-tang"
    ],
    "wof:name":"Wan Ho-tang",
    "wof:placetype":"locality"
},
  "geometry": {"coordinates":[98.7488,21.00379],"type":"Point"}
}