{
  "type": "Feature",
  "properties": {
    "gn:admin1_code":"15.0",
    "gn:admin2_code":"MMR009D001",
    "gn:admin3_code":"MMR009001",
    "gn:asciiname":"Ngasaung",
    "gn:country_code":"MM",
    "gn:dem":145,
    "gn:feature_class":"P",
    "gn:feature_code":"PPL",
    "gn:name":"Ngasaung",
    "gn:population":0,
    "gn:timezone":"Asia/Yangon",
    "iso:country":"MM",
    "wof:name":"Ngasaung",
    "wof:placetype":"locality"
},
  "geometry": {"coordinates":[95.32437,19.93479],"type":"Point"}
}