{
  "type": "Feature",
  "properties": {
    "gn:admin1_code":"10.0",
    "gn:admin2_code":"MMR005D008",
    "gn:admin3_code":"MMR005034",
    "gn:asciiname":"Nanthabaik",
    "gn:country_code":"MM",
    "gn:dem":262,
    "gn:feature_class":"P",
    "gn:feature_code":"PPL",
    "gn:name":"Nanthabaik",
    "gn:population":0,
    "gn:timezone":"Asia/Yangon",
    "iso:country":"MM",
    "name:und_x_variant":[
        "Nansabeik",
        "Nanthabaik"
    ],
    "wof:name":"Nanthabaik",
    "wof:placetype":"locality"
},
  "geometry": {"coordinates":[95.5261,24.67166],"type":"Point"}
}