{
  "type": "Feature",
  "properties": {
    "gn:admin1_code":"5.0",
    "gn:admin2_code":"MMR003D001",
    "gn:admin3_code":"MMR003004",
    "gn:asciiname":"Kalawkawaw",
    "gn:country_code":"MM",
    "gn:dem":631,
    "gn:feature_class":"P",
    "gn:feature_code":"PPL",
    "gn:name":"Kalawkawaw",
    "gn:population":0,
    "gn:timezone":"Asia/Yangon",
    "iso:country":"MM",
    "wof:name":"Kalawkawaw",
    "wof:placetype":"locality"
},
  "geometry": {"coordinates":[96.90833000000001,18.73642000000001],"type":"Point"}
}