{
  "type": "Feature",
  "properties": {
    "gn:admin1_code":"16.0",
    "gn:asciiname":"Takawhta",
    "gn:country_code":"MM",
    "gn:dem":45,
    "gn:feature_class":"P",
    "gn:feature_code":"PPL",
    "gn:name":"Takawhta",
    "gn:population":0,
    "gn:timezone":"Asia/Yangon",
    "iso:country":"MM",
    "name:und_x_variant":[
        "Takawta",
        "Takawhta"
    ],
    "wof:name":"Takawhta",
    "wof:placetype":"locality"
},
  "geometry": {"coordinates":[97.21737,17.53901],"type":"Point"}
}