{
  "type": "Feature",
  "properties": {
    "gn:admin1_code":"11.0",
    "gn:admin2_code":"MMR014D003",
    "gn:admin3_code":"MMR014018",
    "gn:asciiname":"Hwe-lem",
    "gn:country_code":"MM",
    "gn:dem":882,
    "gn:feature_class":"P",
    "gn:feature_code":"PPL",
    "gn:name":"Hw\u00e8-lem",
    "gn:population":0,
    "gn:timezone":"Asia/Yangon",
    "iso:country":"MM",
    "wof:name":"Hwe-lem",
    "wof:placetype":"locality"
},
  "geometry": {"coordinates":[98.01085999999999,20.03294],"type":"Point"}
}