{
  "type": "Feature",
  "properties": {
    "gn:admin1_code":"11.0",
    "gn:admin2_code":"MMR014D003",
    "gn:admin3_code":"MMR014018",
    "gn:asciiname":"Kiu-maw-ai",
    "gn:country_code":"MM",
    "gn:dem":1187,
    "gn:feature_class":"P",
    "gn:feature_code":"PPL",
    "gn:name":"Kiu-maw-ai",
    "gn:population":0,
    "gn:timezone":"Asia/Yangon",
    "iso:country":"MM",
    "wof:name":"Kiu-maw-ai",
    "wof:placetype":"locality"
},
  "geometry": {"coordinates":[97.90622,19.86073],"type":"Point"}
}