{
  "type": "Feature",
  "properties": {
    "gn:admin1_code":"11.0",
    "gn:admin2_code":"MMR014D003",
    "gn:admin3_code":"MMR014018",
    "gn:asciiname":"Wan Tue-nio",
    "gn:country_code":"MM",
    "gn:dem":297,
    "gn:feature_class":"P",
    "gn:feature_code":"PPL",
    "gn:name":"W\u0101n T\u00fc-nio",
    "gn:population":0,
    "gn:timezone":"Asia/Yangon",
    "iso:country":"MM",
    "wof:name":"Wan Tue-nio",
    "wof:placetype":"locality"
},
  "geometry": {"coordinates":[97.84374,20.20335],"type":"Point"}
}