{
  "type": "Feature",
  "properties": {
    "gn:admin1_code":"2.0",
    "gn:admin2_code":"MMR004D002",
    "gn:admin3_code":"MMR004008",
    "gn:asciiname":"Maungdaw",
    "gn:country_code":"MM",
    "gn:dem":1145,
    "gn:feature_class":"P",
    "gn:feature_code":"PPL",
    "gn:name":"Maungdaw",
    "gn:population":0,
    "gn:timezone":"Asia/Yangon",
    "iso:country":"MM",
    "wof:name":"Maungdaw",
    "wof:placetype":"locality"
},
  "geometry": {"coordinates":[94.07796999999999,21.22857],"type":"Point"}
}