{
  "type": "Feature",
  "properties": {
    "gn:admin1_code":"2.0",
    "gn:admin2_code":"MMR004D002",
    "gn:admin3_code":"MMR004008",
    "gn:asciiname":"Maungdaw",
    "gn:country_code":"MM",
    "gn:dem":1145,
    "gn:feature_class":"P",
    "gn:feature_code":"PPL",
    "gn:name":"Maungdaw",
    "gn:population":0,
    "gn:timezone":"Asia/Yangon",
    "iso:country":"MM",
    "name:ara_x_preferred":[
        "\u0645\u0646\u063a\u062f\u0648"
    ],
    "name:jpn_x_preferred":[
        "\u30de\u30a6\u30f3\u30c9\u30fc"
    ],
    "name:kor_x_preferred":[
        "\ub9c8\uc6c5\ub3c4"
    ],
    "name:lit_x_preferred":[
        "Maungdo"
    ],
    "name:mya_x_preferred":[
        "\u1019\u1031\u102c\u1004\u103a\u1010\u1031\u102c\u1019\u103c\u102d\u102f\u1037"
    ],
    "name:shn_x_preferred":[
        "\u1019\u103d\u1004\u103a\u1087\u1010\u1031\u1083\u1038\u104a \u101d\u1035\u1004\u103a\u1038"
    ],
    "name:tha_x_preferred":[
        "\u0e21\u0e2d\u0e07\u0e14\u0e2d"
    ],
    "wof:name":"Maungdaw",
    "wof:placetype":"locality"
},
  "geometry": {"coordinates":[94.07796999999999,21.22857],"type":"Point"}
}