{
  "type": "Feature",
  "properties": {
    "gn:admin1_code":"10.0",
    "gn:admin2_code":"MMR005D002",
    "gn:admin3_code":"MMR005007",
    "gn:asciiname":"Hnawgon",
    "gn:country_code":"MM",
    "gn:dem":217,
    "gn:feature_class":"P",
    "gn:feature_code":"PPL",
    "gn:name":"Hnawgon",
    "gn:population":0,
    "gn:timezone":"Asia/Yangon",
    "iso:country":"MM",
    "wof:name":"Hnawgon",
    "wof:placetype":"locality"
},
  "geometry": {"coordinates":[95.69795999999999,23.49806],"type":"Point"}
}