{
  "type": "Feature",
  "properties": {
    "gn:admin1_code":"10.0",
    "gn:admin2_code":"MMR005D002",
    "gn:admin3_code":"MMR005004",
    "gn:asciiname":"Tebin",
    "gn:country_code":"MM",
    "gn:dem":92,
    "gn:feature_class":"P",
    "gn:feature_code":"PPL",
    "gn:name":"T\u00e8bin",
    "gn:population":0,
    "gn:timezone":"Asia/Yangon",
    "iso:country":"MM",
    "wof:name":"Tebin",
    "wof:placetype":"locality"
},
  "geometry": {"coordinates":[95.52508,22.51521],"type":"Point"}
}