{
  "type": "Feature",
  "properties": {
    "gn:admin1_code":"16.0",
    "gn:admin2_code":"MMR008D001",
    "gn:admin3_code":"MMR008004",
    "gn:asciiname":"Nabelon",
    "gn:country_code":"MM",
    "gn:dem":54,
    "gn:feature_class":"P",
    "gn:feature_code":"PPL",
    "gn:name":"Nabelon",
    "gn:population":0,
    "gn:timezone":"Asia/Yangon",
    "iso:country":"MM",
    "wof:name":"Nabelon",
    "wof:placetype":"locality"
},
  "geometry": {"coordinates":[95.57281999999999,18.61136],"type":"Point"}
}