{
  "type": "Feature",
  "properties": {
    "gn:admin1_code":"10.0",
    "gn:admin2_code":"MMR005D007",
    "gn:admin3_code":"MMR005031",
    "gn:asciiname":"Kya-in",
    "gn:country_code":"MM",
    "gn:dem":109,
    "gn:feature_class":"P",
    "gn:feature_code":"PPL",
    "gn:name":"Kya-in",
    "gn:population":0,
    "gn:timezone":"Asia/Yangon",
    "iso:country":"MM",
    "wof:name":"Kya-in",
    "wof:placetype":"locality"
},
  "geometry": {"coordinates":[94.43472,23.5782],"type":"Point"}
}