{
  "type": "Feature",
  "properties": {
    "gn:admin1_code":"11.0",
    "gn:admin2_code":"MMR015D003",
    "gn:admin3_code":"MMR015015",
    "gn:asciiname":"Manti",
    "gn:country_code":"MM",
    "gn:dem":596,
    "gn:feature_class":"P",
    "gn:feature_code":"PPL",
    "gn:name":"Manti",
    "gn:population":0,
    "gn:timezone":"Asia/Yangon",
    "iso:country":"MM",
    "name:bar_x_preferred":[
        "Manti"
    ],
    "name:deu_x_preferred":[
        "Manti"
    ],
    "name:fra_x_preferred":[
        "Manti"
    ],
    "name:ita_x_preferred":[
        "Manti"
    ],
    "name:por_x_preferred":[
        "Manti"
    ],
    "name:srp_x_preferred":[
        "\u041c\u0430\u043d\u0442\u0438"
    ],
    "wof:name":"Manti",
    "wof:placetype":"locality"
},
  "geometry": {"coordinates":[97.54554,23.14774],"type":"Point"}
}