{
  "type": "Feature",
  "properties": {
    "gn:admin1_code":"10.0",
    "gn:admin2_code":"MMR005D007",
    "gn:admin3_code":"MMR005032",
    "gn:asciiname":"Ontha",
    "gn:country_code":"MM",
    "gn:dem":146,
    "gn:feature_class":"P",
    "gn:feature_code":"PPL",
    "gn:name":"Ontha",
    "gn:population":0,
    "gn:timezone":"Asia/Yangon",
    "iso:country":"MM",
    "wof:name":"Ontha",
    "wof:placetype":"locality"
},
  "geometry": {"coordinates":[94.84076,24.17173],"type":"Point"}
}