{
  "type": "Feature",
  "properties": {
    "gn:admin1_code":"8.0",
    "gn:admin2_code":"MMR010D006",
    "gn:admin3_code":"MMR010024",
    "gn:asciiname":"Kantha",
    "gn:country_code":"MM",
    "gn:dem":173,
    "gn:feature_class":"P",
    "gn:feature_code":"PPL",
    "gn:name":"Kantha",
    "gn:population":0,
    "gn:timezone":"Asia/Yangon",
    "iso:country":"MM",
    "name:ben_x_preferred":[
        "\u0995\u09be\u0981\u09a5\u09be"
    ],
    "name:hin_x_preferred":[
        "\u0915\u093e\u0928\u094d\u0925\u093e \u0915\u0936\u0940\u0926\u093e\u0915\u093e\u0930\u0940"
    ],
    "name:ori_x_preferred":[
        "\u0b15\u0b28\u0b4d\u0b25\u0b3e"
    ],
    "name:swe_x_preferred":[
        "Kanthabroderi"
    ],
    "wof:name":"Kantha",
    "wof:placetype":"locality"
},
  "geometry": {"coordinates":[96.14896,20.63781],"type":"Point"}
}