{
  "type": "Feature",
  "properties": {
    "gn:admin1_code":"16.0",
    "gn:admin2_code":"MMR007D002",
    "gn:admin3_code":"MMR007009",
    "gn:asciiname":"Nagamauk",
    "gn:country_code":"MM",
    "gn:dem":52,
    "gn:feature_class":"P",
    "gn:feature_code":"PPL",
    "gn:name":"Nagamauk",
    "gn:population":0,
    "gn:timezone":"Asia/Yangon",
    "iso:country":"MM",
    "wof:name":"Nagamauk",
    "wof:placetype":"locality"
},
  "geometry": {"coordinates":[96.55038,18.91269],"type":"Point"}
}