{
  "type": "Feature",
  "properties": {
    "gn:admin1_code":"11.0",
    "gn:admin2_code":"MMR015D003",
    "gn:admin3_code":"MMR015013",
    "gn:asciiname":"Na-pong",
    "gn:country_code":"MM",
    "gn:dem":546,
    "gn:feature_class":"P",
    "gn:feature_code":"PPL",
    "gn:name":"Na-pong",
    "gn:population":0,
    "gn:timezone":"Asia/Yangon",
    "iso:country":"MM",
    "wof:name":"Na-pong",
    "wof:placetype":"locality"
},
  "geometry": {"coordinates":[96.76775000000001,22.37102],"type":"Point"}
}