{
  "type": "Feature",
  "properties": {
    "gn:admin1_code":"11.0",
    "gn:admin2_code":"MMR016D001",
    "gn:admin3_code":"MMR016003",
    "gn:asciiname":"Wan Sanghpoek",
    "gn:country_code":"MM",
    "gn:dem":966,
    "gn:feature_class":"P",
    "gn:feature_code":"PPL",
    "gn:name":"W\u0101n S\u0101nghp\u00f6k",
    "gn:population":0,
    "gn:timezone":"Asia/Yangon",
    "iso:country":"MM",
    "wof:name":"Wan Sanghpoek",
    "wof:placetype":"locality"
},
  "geometry": {"coordinates":[99.65895999999999,21.97639],"type":"Point"}
}