{
  "type": "Feature",
  "properties": {
    "gn:admin1_code":"11.0",
    "gn:admin2_code":"MMR016D001",
    "gn:admin3_code":"MMR016002",
    "gn:asciiname":"Yawngha",
    "gn:country_code":"MM",
    "gn:dem":1175,
    "gn:feature_class":"P",
    "gn:feature_code":"PPL",
    "gn:name":"Yawngha",
    "gn:population":0,
    "gn:timezone":"Asia/Yangon",
    "iso:country":"MM",
    "name:und_x_variant":[
        "Yawnghai",
        "Yawngha"
    ],
    "wof:name":"Yawngha",
    "wof:placetype":"locality"
},
  "geometry": {"coordinates":[98.94079000000001,21.79933],"type":"Point"}
}