{
  "type": "Feature",
  "properties": {
    "gn:admin1_code":"3.0",
    "gn:admin2_code":"MMR017D006",
    "gn:admin3_code":"MMR017025",
    "gn:asciiname":"Kalayat",
    "gn:country_code":"MM",
    "gn:dem":8,
    "gn:feature_class":"P",
    "gn:feature_code":"PPL",
    "gn:name":"Kalayat",
    "gn:population":0,
    "gn:timezone":"Asia/Yangon",
    "iso:country":"MM",
    "name:ben_x_preferred":[
        "\u0995\u09be\u09b2\u09be\u09af\u09bc\u09be\u09a4"
    ],
    "name:bpy_x_preferred":[
        "\u0995\u09be\u09b2\u09be\u09af\u09bc\u09be\u09a4"
    ],
    "name:ceb_x_preferred":[
        "Kal\u0101yat"
    ],
    "name:hin_x_preferred":[
        "\u0915\u0932\u093e\u092f\u0924"
    ],
    "name:ita_x_preferred":[
        "Kalayat"
    ],
    "name:msa_x_preferred":[
        "Kalayat"
    ],
    "name:new_x_preferred":[
        "\u0915\u0932\u093e\u092f\u0924"
    ],
    "name:nld_x_preferred":[
        "Kalayat"
    ],
    "name:pan_x_preferred":[
        "\u0a15\u0a32\u0a3e\u0a07\u0a24"
    ],
    "name:por_x_preferred":[
        "Kalayat"
    ],
    "name:swe_x_preferred":[
        "Kal\u0101yat"
    ],
    "name:vie_x_preferred":[
        "Kalayat"
    ],
    "name:zho_x_preferred":[
        "\u5361\u62c9\u8036\u7279"
    ],
    "wof:name":"Kalayat",
    "wof:placetype":"locality"
},
  "geometry": {"coordinates":[95.69166,16.39757],"type":"Point"}
}