{
  "type": "Feature",
  "properties": {
    "gn:admin1_code":"2.0",
    "gn:admin2_code":"MMR004D003",
    "gn:admin3_code":"MMR004002",
    "gn:asciiname":"Vanha",
    "gn:cc2":"MM",
    "gn:country_code":"MM",
    "gn:dem":1007,
    "gn:feature_class":"P",
    "gn:feature_code":"PPL",
    "gn:name":"Vanha",
    "gn:population":0,
    "gn:timezone":"Asia/Yangon",
    "iso:country":"MM",
    "name:und_x_variant":[
        "Vanhna",
        "Vanha"
    ],
    "wof:name":"Vanha",
    "wof:placetype":"locality"
},
  "geometry": {"coordinates":[93.81667,22.65],"type":"Point"}
}