{
  "type": "Feature",
  "properties": {
    "gn:admin1_code":"11.0",
    "gn:admin2_code":"MMR015D005",
    "gn:admin3_code":"MMR015022",
    "gn:asciiname":"Man Kiu-hkawng",
    "gn:country_code":"MM",
    "gn:dem":1659,
    "gn:feature_class":"P",
    "gn:feature_code":"PPL",
    "gn:name":"M\u0101n Kiu-hkawng",
    "gn:population":0,
    "gn:timezone":"Asia/Yangon",
    "iso:country":"MM",
    "wof:name":"Man Kiu-hkawng",
    "wof:placetype":"locality"
},
  "geometry": {"coordinates":[98.66643999999999,23.48814],"type":"Point"}
}