{
  "type": "Feature",
  "properties": {
    "gn:admin1_code":"3.0",
    "gn:admin2_code":"MMR017D001",
    "gn:admin3_code":"MMR017001",
    "gn:asciiname":"Madawgon",
    "gn:country_code":"MM",
    "gn:dem":19,
    "gn:feature_class":"P",
    "gn:feature_code":"PPL",
    "gn:name":"Madawg\u00f4n",
    "gn:population":0,
    "gn:timezone":"Asia/Yangon",
    "iso:country":"MM",
    "wof:name":"Madawgon",
    "wof:placetype":"locality"
},
  "geometry": {"coordinates":[94.59948,16.66249],"type":"Point"}
}