{
  "type": "Feature",
  "properties": {
    "gn:admin1_code":"10.0",
    "gn:admin2_code":"MMR005D002",
    "gn:admin3_code":"MMR005006",
    "gn:asciiname":"Kanzegon",
    "gn:country_code":"MM",
    "gn:dem":86,
    "gn:feature_class":"P",
    "gn:feature_code":"PPL",
    "gn:name":"Kanzegon",
    "gn:population":0,
    "gn:timezone":"Asia/Yangon",
    "iso:country":"MM",
    "wof:name":"Kanzegon",
    "wof:placetype":"locality"
},
  "geometry": {"coordinates":[95.60500999999999,22.33606],"type":"Point"}
}