{
  "type": "Feature",
  "properties": {
    "gn:admin1_code":"2.0",
    "gn:admin2_code":"MMR004D003",
    "gn:admin3_code":"MMR004002",
    "gn:asciiname":"Sih-hai",
    "gn:country_code":"MM",
    "gn:dem":1149,
    "gn:feature_class":"P",
    "gn:feature_code":"PPL",
    "gn:name":"Sih-hai",
    "gn:population":0,
    "gn:timezone":"Asia/Yangon",
    "iso:country":"MM",
    "wof:name":"Sih-hai",
    "wof:placetype":"locality"
},
  "geometry": {"coordinates":[93.83333,22.68333],"type":"Point"}
}