{
  "type": "Feature",
  "properties": {
    "gn:admin1_code":"6.0",
    "gn:admin2_code":"MMR002D001",
    "gn:admin3_code":"MMR002002",
    "gn:asciiname":"Htu-ra-la-le",
    "gn:country_code":"MM",
    "gn:dem":893,
    "gn:feature_class":"P",
    "gn:feature_code":"PPL",
    "gn:name":"Htu-ra-l\u0101-l\u00e8",
    "gn:population":0,
    "gn:timezone":"Asia/Yangon",
    "iso:country":"MM",
    "wof:name":"Htu-ra-la-le",
    "wof:placetype":"locality"
},
  "geometry": {"coordinates":[97.33259,19.41739],"type":"Point"}
}