{
  "type": "Feature",
  "properties": {
    "gn:admin1_code":"11.0",
    "gn:admin2_code":"MMR014D001",
    "gn:admin3_code":"MMR014003",
    "gn:asciiname":"Ti-lon",
    "gn:country_code":"MM",
    "gn:dem":1427,
    "gn:feature_class":"P",
    "gn:feature_code":"PPL",
    "gn:name":"Ti-lon",
    "gn:population":0,
    "gn:timezone":"Asia/Yangon",
    "iso:country":"MM",
    "wof:name":"Ti-lon",
    "wof:placetype":"locality"
},
  "geometry": {"coordinates":[97.21484,20.92189],"type":"Point"}
}