{
  "type": "Feature",
  "properties": {
    "gn:admin1_code":"12.0",
    "gn:admin2_code":"MMR006D003",
    "gn:admin3_code":"MMR006010",
    "gn:asciiname":"Mawgaungdon Ywa",
    "gn:country_code":"MM",
    "gn:dem":9,
    "gn:feature_class":"P",
    "gn:feature_code":"PPL",
    "gn:name":"Mawgaungdon Ywa",
    "gn:population":0,
    "gn:timezone":"Asia/Yangon",
    "iso:country":"MM",
    "name:und_x_variant":[
        "Mawgaung-don",
        "Mawgaungdon Ywa"
    ],
    "wof:name":"Mawgaungdon Ywa",
    "wof:placetype":"locality"
},
  "geometry": {"coordinates":[98.53743,11.60795],"type":"Point"}
}