{
  "type": "Feature",
  "properties": {
    "gn:admin1_code":"12.0",
    "gn:admin2_code":"MMR006D001",
    "gn:admin3_code":"MMR006001",
    "gn:asciiname":"Wazungyaung",
    "gn:country_code":"MM",
    "gn:dem":329,
    "gn:feature_class":"P",
    "gn:feature_code":"PPL",
    "gn:name":"Wazungyaung",
    "gn:population":0,
    "gn:timezone":"Asia/Yangon",
    "iso:country":"MM",
    "name:und_x_variant":[
        "Wazwin-gan",
        "Wazunchaung",
        "Wazungyaung"
    ],
    "wof:name":"Wazungyaung",
    "wof:placetype":"locality"
},
  "geometry": {"coordinates":[98.47204000000001,14.05334],"type":"Point"}
}