{
  "type": "Feature",
  "properties": {
    "gn:admin1_code":"3.0",
    "gn:admin2_code":"MMR017D003",
    "gn:admin3_code":"MMR017017",
    "gn:asciiname":"Kyonpadaw",
    "gn:country_code":"MM",
    "gn:dem":13,
    "gn:feature_class":"P",
    "gn:feature_code":"PPL",
    "gn:name":"Kyonpadaw",
    "gn:population":0,
    "gn:timezone":"Asia/Yangon",
    "iso:country":"MM",
    "name:und_x_variant":[
        "Kyonpa",
        "Kyonpadaw"
    ],
    "wof:name":"Kyonpadaw",
    "wof:placetype":"locality"
},
  "geometry": {"coordinates":[95.21666999999999,16.78235],"type":"Point"}
}