{
  "type": "Feature",
  "properties": {
    "gn:admin1_code":"2.0",
    "gn:admin2_code":"MMR004D001",
    "gn:admin3_code":"MMR004001",
    "gn:asciiname":"Vaniam",
    "gn:country_code":"MM",
    "gn:dem":1084,
    "gn:feature_class":"P",
    "gn:feature_code":"PPL",
    "gn:name":"Vaniam",
    "gn:population":0,
    "gn:timezone":"Asia/Yangon",
    "iso:country":"MM",
    "wof:name":"Vaniam",
    "wof:placetype":"locality"
},
  "geometry": {"coordinates":[93.78333000000001,22.93333],"type":"Point"}
}