{
  "type": "Feature",
  "properties": {
    "gn:admin1_code":"15.0",
    "gn:admin2_code":"MMR009D003",
    "gn:admin3_code":"MMR009017",
    "gn:asciiname":"Ngazinyaing",
    "gn:country_code":"MM",
    "gn:dem":296,
    "gn:feature_class":"P",
    "gn:feature_code":"PPL",
    "gn:name":"Ngazinyaing",
    "gn:population":0,
    "gn:timezone":"Asia/Yangon",
    "iso:country":"MM",
    "wof:name":"Ngazinyaing",
    "wof:placetype":"locality"
},
  "geometry": {"coordinates":[95.69298999999999,19.63012],"type":"Point"}
}