{
  "type": "Feature",
  "properties": {
    "gn:admin1_code":"11.0",
    "gn:admin2_code":"MMR015D001",
    "gn:admin3_code":"MMR015002",
    "gn:asciiname":"Man Kangmoeng",
    "gn:country_code":"MM",
    "gn:dem":1070,
    "gn:feature_class":"P",
    "gn:feature_code":"PPL",
    "gn:name":"M\u0101n Kangm\u00f6ng",
    "gn:population":0,
    "gn:timezone":"Asia/Yangon",
    "iso:country":"MM",
    "name:und_x_variant":[
        "K\u0101ngm\u00f6ng",
        "M\u00f6ng Kong Mun",
        "M\u0101n Kangm\u00f6ng"
    ],
    "wof:name":"Man Kangmoeng",
    "wof:placetype":"locality"
},
  "geometry": {"coordinates":[98.50344,23.30827],"type":"Point"}
}