{
  "type": "Feature",
  "properties": {
    "gn:admin1_code":"16.0",
    "gn:admin2_code":"MMR007D002",
    "gn:admin3_code":"MMR007013",
    "gn:asciiname":"Thayettaw",
    "gn:country_code":"MM",
    "gn:dem":57,
    "gn:feature_class":"P",
    "gn:feature_code":"PPL",
    "gn:name":"Thayettaw",
    "gn:population":0,
    "gn:timezone":"Asia/Yangon",
    "iso:country":"MM",
    "wof:name":"Thayettaw",
    "wof:placetype":"locality"
},
  "geometry": {"coordinates":[96.37672999999999,18.6946],"type":"Point"}
}