{
  "type": "Feature",
  "properties": {
    "gn:admin1_code":"11.0",
    "gn:admin2_code":"MMR014D001",
    "gn:admin3_code":"MMR014007",
    "gn:asciiname":"Hsinnetchaung",
    "gn:country_code":"MM",
    "gn:dem":1371,
    "gn:feature_class":"P",
    "gn:feature_code":"PPL",
    "gn:name":"Hsinnetchaung",
    "gn:population":0,
    "gn:timezone":"Asia/Yangon",
    "iso:country":"MM",
    "name:und_x_variant":[
        "Hsinnetohaung",
        "Hsinnetchaung"
    ],
    "wof:name":"Hsinnetchaung",
    "wof:placetype":"locality"
},
  "geometry": {"coordinates":[96.44428000000001,21.23418],"type":"Point"}
}