{
  "type": "Feature",
  "properties": {
    "gn:admin1_code":"11.0",
    "gn:admin2_code":"MMR016D003",
    "gn:admin3_code":"MMR016009",
    "gn:asciiname":"Pa-taunghkem",
    "gn:country_code":"MM",
    "gn:dem":427,
    "gn:feature_class":"P",
    "gn:feature_code":"PPL",
    "gn:name":"Pa-t\u0101unghk\u0113m",
    "gn:population":0,
    "gn:timezone":"Asia/Yangon",
    "iso:country":"MM",
    "wof:name":"Pa-taunghkem",
    "wof:placetype":"locality"
},
  "geometry": {"coordinates":[100.08722,20.65778],"type":"Point"}
}