{
  "type": "Feature",
  "properties": {
    "gn:admin1_code":"8.0",
    "gn:admin2_code":"MMR010D002",
    "gn:admin3_code":"MMR010010",
    "gn:asciiname":"Taung-in",
    "gn:country_code":"MM",
    "gn:dem":80,
    "gn:feature_class":"P",
    "gn:feature_code":"PPL",
    "gn:name":"Taung-in",
    "gn:population":0,
    "gn:timezone":"Asia/Yangon",
    "iso:country":"MM",
    "wof:name":"Taung-in",
    "wof:placetype":"locality"
},
  "geometry": {"coordinates":[96.04875,22.44131],"type":"Point"}
}