{
  "type": "Feature",
  "properties": {
    "gn:admin1_code":"16.0",
    "gn:admin2_code":"MMR007D001",
    "gn:admin3_code":"MMR007007",
    "gn:asciiname":"E-gyan",
    "gn:country_code":"MM",
    "gn:dem":27,
    "gn:feature_class":"P",
    "gn:feature_code":"PPL",
    "gn:name":"E-gyan",
    "gn:population":0,
    "gn:timezone":"Asia/Yangon",
    "iso:country":"MM",
    "wof:name":"E-gyan",
    "wof:placetype":"locality"
},
  "geometry": {"coordinates":[96.59999999999999,17.91667],"type":"Point"}
}