{
  "type": "Feature",
  "properties": {
    "gn:admin1_code":"11.0",
    "gn:admin2_code":"MMR016D003",
    "gn:admin3_code":"MMR016011",
    "gn:asciiname":"Wan Hpya Hkuenmoeng",
    "gn:country_code":"MM",
    "gn:dem":913,
    "gn:feature_class":"P",
    "gn:feature_code":"PPL",
    "gn:name":"W\u0101n Hpya Hk\u00fcnm\u00f6ng",
    "gn:population":0,
    "gn:timezone":"Asia/Yangon",
    "iso:country":"MM",
    "name:und_x_variant":[
        "Hpya Hk\u00fcnm\u00f6ng",
        "W\u0101n Hpya Hk\u00fcnm\u00f6ng"
    ],
    "wof:name":"Wan Hpya Hkuenmoeng",
    "wof:placetype":"locality"
},
  "geometry": {"coordinates":[100.65537,21.18605],"type":"Point"}
}