{
  "type": "Feature",
  "properties": {
    "gn:admin1_code":"11.0",
    "gn:admin2_code":"MMR014D001",
    "gn:admin3_code":"MMR014005",
    "gn:asciiname":"Shweminbon",
    "gn:country_code":"MM",
    "gn:dem":1138,
    "gn:feature_class":"P",
    "gn:feature_code":"PPL",
    "gn:name":"Shweminbon",
    "gn:population":0,
    "gn:timezone":"Asia/Yangon",
    "iso:country":"MM",
    "wof:name":"Shweminbon",
    "wof:placetype":"locality"
},
  "geometry": {"coordinates":[96.49372,20.64861],"type":"Point"}
}