{
  "type": "Feature",
  "properties": {
    "gn:admin1_code":"11.0",
    "gn:admin2_code":"MMR016D003",
    "gn:admin3_code":"MMR016011",
    "gn:asciiname":"Wan Pa-man",
    "gn:country_code":"MM",
    "gn:dem":556,
    "gn:feature_class":"P",
    "gn:feature_code":"PPL",
    "gn:name":"W\u0101n P\u0101-man",
    "gn:population":0,
    "gn:timezone":"Asia/Yangon",
    "iso:country":"MM",
    "name:und_x_variant":[
        "P\u0101-man",
        "W\u0101n P\u0101-man"
    ],
    "wof:name":"Wan Pa-man",
    "wof:placetype":"locality"
},
  "geometry": {"coordinates":[100.36375,21.14864],"type":"Point"}
}