{
  "type": "Feature",
  "properties": {
    "gn:admin1_code":"4.0",
    "gn:admin2_code":"MMR001D001",
    "gn:admin3_code":"MMR001005",
    "gn:asciiname":"Wuhpatu",
    "gn:country_code":"MM",
    "gn:dem":1813,
    "gn:feature_class":"P",
    "gn:feature_code":"PPL",
    "gn:name":"Wuhpatu",
    "gn:population":0,
    "gn:timezone":"Asia/Yangon",
    "iso:country":"MM",
    "wof:name":"Wuhpatu",
    "wof:placetype":"locality"
},
  "geometry": {"coordinates":[98.56507000000001,26.1863],"type":"Point"}
}