{
  "type": "Feature",
  "properties": {
    "gn:admin1_code":"11.0",
    "gn:admin2_code":"MMR016D001",
    "gn:admin3_code":"MMR016005",
    "gn:asciiname":"Wan Pangkawng",
    "gn:country_code":"MM",
    "gn:dem":1475,
    "gn:feature_class":"P",
    "gn:feature_code":"PPL",
    "gn:name":"W\u0101n Pangkawng",
    "gn:population":0,
    "gn:timezone":"Asia/Yangon",
    "iso:country":"MM",
    "name:und_x_variant":[
        "Pang-kawng",
        "W\u0101n Pangkawng"
    ],
    "wof:name":"Wan Pangkawng",
    "wof:placetype":"locality"
},
  "geometry": {"coordinates":[100.03388,21.3563],"type":"Point"}
}