{
  "type": "Feature",
  "properties": {
    "gn:admin1_code":"10.0",
    "gn:admin2_code":"MMR005D003",
    "gn:admin3_code":"MMR005012",
    "gn:asciiname":"Nyaungbinde",
    "gn:country_code":"MM",
    "gn:dem":200,
    "gn:feature_class":"P",
    "gn:feature_code":"PPL",
    "gn:name":"Nyaungbind\u00e8",
    "gn:population":0,
    "gn:timezone":"Asia/Yangon",
    "iso:country":"MM",
    "wof:name":"Nyaungbinde",
    "wof:placetype":"locality"
},
  "geometry": {"coordinates":[95.31220999999999,22.13638],"type":"Point"}
}