{
  "type": "Feature",
  "properties": {
    "gn:admin1_code":"5.0",
    "gn:admin2_code":"MMR003D003",
    "gn:admin3_code":"MMR003007",
    "gn:asciiname":"Kharantaw",
    "gn:country_code":"MM",
    "gn:dem":31,
    "gn:feature_class":"P",
    "gn:feature_code":"PPL",
    "gn:name":"Kharantaw",
    "gn:population":0,
    "gn:timezone":"Asia/Yangon",
    "iso:country":"MM",
    "name:und_x_variant":[
        "Kharantow",
        "Khatantow",
        "Kharantaw"
    ],
    "wof:name":"Kharantaw",
    "wof:placetype":"locality"
},
  "geometry": {"coordinates":[98.17245,15.90729],"type":"Point"}
}