{
  "type": "Feature",
  "properties": {
    "gn:admin1_code":"11.0",
    "gn:admin2_code":"MMR015D001",
    "gn:admin3_code":"MMR015001",
    "gn:asciiname":"Lao-yi-sai",
    "gn:country_code":"MM",
    "gn:dem":1562,
    "gn:feature_class":"P",
    "gn:feature_code":"PPL",
    "gn:name":"Lao-yi-sai",
    "gn:population":0,
    "gn:timezone":"Asia/Yangon",
    "iso:country":"MM",
    "wof:name":"Lao-yi-sai",
    "wof:placetype":"locality"
},
  "geometry": {"coordinates":[98.4045,22.98979],"type":"Point"}
}