{
  "type": "Feature",
  "properties": {
    "gn:admin1_code":"4.0",
    "gn:admin2_code":"MMR001D002",
    "gn:admin3_code":"MMR001009",
    "gn:asciiname":"Hkangadaw",
    "gn:country_code":"MM",
    "gn:dem":599,
    "gn:feature_class":"P",
    "gn:feature_code":"PPL",
    "gn:name":"Hkangadaw",
    "gn:population":0,
    "gn:timezone":"Asia/Yangon",
    "iso:country":"MM",
    "wof:name":"Hkangadaw",
    "wof:placetype":"locality"
},
  "geometry": {"coordinates":[96.22414999999999,25.84872],"type":"Point"}
}