{
  "type": "Feature",
  "properties": {
    "gn:admin1_code":"10.0",
    "gn:admin2_code":"MMR005D008",
    "gn:admin3_code":"MMR005037",
    "gn:asciiname":"Shikshao",
    "gn:country_code":"MM",
    "gn:dem":1427,
    "gn:feature_class":"P",
    "gn:feature_code":"PPL",
    "gn:name":"Shikshao",
    "gn:population":0,
    "gn:timezone":"Asia/Yangon",
    "iso:country":"MM",
    "wof:name":"Shikshao",
    "wof:placetype":"locality"
},
  "geometry": {"coordinates":[95.52597,26.54418],"type":"Point"}
}