{
  "type": "Feature",
  "properties": {
    "gn:admin1_code":"4.0",
    "gn:admin2_code":"MMR001D001",
    "gn:admin3_code":"MMR001001",
    "gn:asciiname":"Namponmao",
    "gn:country_code":"MM",
    "gn:dem":144,
    "gn:feature_class":"P",
    "gn:feature_code":"PPL",
    "gn:name":"Namponmao",
    "gn:population":0,
    "gn:timezone":"Asia/Yangon",
    "iso:country":"MM",
    "name:und_x_variant":[
        "Nampongma",
        "Namponmao"
    ],
    "wof:name":"Namponmao",
    "wof:placetype":"locality"
},
  "geometry": {"coordinates":[97.30218000000001,25.34776],"type":"Point"}
}