{
  "type": "Feature",
  "properties": {
    "gn:admin1_code":"11.0",
    "gn:admin2_code":"MMR014D003",
    "gn:admin3_code":"MMR014021",
    "gn:asciiname":"Pawktu",
    "gn:country_code":"MM",
    "gn:dem":675,
    "gn:feature_class":"P",
    "gn:feature_code":"PPL",
    "gn:name":"Pawktu",
    "gn:population":0,
    "gn:timezone":"Asia/Yangon",
    "iso:country":"MM",
    "wof:name":"Pawktu",
    "wof:placetype":"locality"
},
  "geometry": {"coordinates":[98.32778,20.31246],"type":"Point"}
}