{
  "type": "Feature",
  "properties": {
    "gn:admin1_code":"5.0",
    "gn:admin2_code":"MMR003D004",
    "gn:admin3_code":"MMR003003",
    "gn:asciiname":"Watalakhi",
    "gn:country_code":"MM",
    "gn:dem":497,
    "gn:feature_class":"P",
    "gn:feature_code":"PPL",
    "gn:name":"Watalakhi",
    "gn:population":0,
    "gn:timezone":"Asia/Yangon",
    "iso:country":"MM",
    "name:und_x_variant":[
        "Wadalaki",
        "Watalakhi"
    ],
    "wof:name":"Watalakhi",
    "wof:placetype":"locality"
},
  "geometry": {"coordinates":[97.19006,17.70641],"type":"Point"}
}