{
  "type": "Feature",
  "properties": {
    "gn:admin1_code":"11.0",
    "gn:admin2_code":"MMR015D005",
    "gn:admin3_code":"MMR015022",
    "gn:asciiname":"Pa-ka",
    "gn:country_code":"MM",
    "gn:dem":1152,
    "gn:feature_class":"P",
    "gn:feature_code":"PPL",
    "gn:name":"Pa-ka",
    "gn:population":0,
    "gn:timezone":"Asia/Yangon",
    "iso:country":"MM",
    "wof:name":"Pa-ka",
    "wof:placetype":"locality"
},
  "geometry": {"coordinates":[98.81572,23.64937],"type":"Point"}
}