{
  "type": "Feature",
  "properties": {
    "gn:admin1_code":"11.0",
    "gn:admin2_code":"MMR015D007",
    "gn:admin3_code":"MMR015024",
    "gn:asciiname":"Yawng-u",
    "gn:country_code":"MM",
    "gn:dem":1183,
    "gn:feature_class":"P",
    "gn:feature_code":"PPL",
    "gn:name":"Yawng-\u016b",
    "gn:population":0,
    "gn:timezone":"Asia/Yangon",
    "iso:country":"MM",
    "wof:name":"Yawng-u",
    "wof:placetype":"locality"
},
  "geometry": {"coordinates":[98.65298,21.85815],"type":"Point"}
}