{
  "type": "Feature",
  "properties": {
    "gn:admin1_code":"11.0",
    "gn:admin2_code":"MMR016D003",
    "gn:admin3_code":"MMR016011",
    "gn:asciiname":"Moeng Loi",
    "gn:country_code":"MM",
    "gn:dem":505,
    "gn:feature_class":"P",
    "gn:feature_code":"PPL",
    "gn:name":"M\u00f6ng Loi",
    "gn:population":0,
    "gn:timezone":"Asia/Yangon",
    "iso:country":"MM",
    "name:und_x_variant":[
        "M\u00f6ng Lwi",
        "M\u00f6ng Lwe",
        "M\u00f6ng Loi"
    ],
    "wof:name":"Moeng Loi",
    "wof:placetype":"locality"
},
  "geometry": {"coordinates":[100.58333,21.33333],"type":"Point"}
}