{
  "type": "Feature",
  "properties": {
    "gn:admin1_code":"11.0",
    "gn:admin2_code":"MMR016D003",
    "gn:admin3_code":"MMR016009",
    "gn:asciiname":"Wan Me-hkao",
    "gn:country_code":"MM",
    "gn:dem":394,
    "gn:feature_class":"P",
    "gn:feature_code":"PPL",
    "gn:name":"W\u0101n M\u0113-hkao",
    "gn:population":0,
    "gn:timezone":"Asia/Yangon",
    "iso:country":"MM",
    "wof:name":"Wan Me-hkao",
    "wof:placetype":"locality"
},
  "geometry": {"coordinates":[99.90194,20.45139],"type":"Point"}
}