{
  "type": "Feature",
  "properties": {
    "gn:admin1_code":"16.0",
    "gn:admin2_code":"MMR007D002",
    "gn:admin3_code":"MMR007011",
    "gn:asciiname":"Tawgyaungbauk",
    "gn:country_code":"MM",
    "gn:dem":28,
    "gn:feature_class":"P",
    "gn:feature_code":"PPL",
    "gn:name":"Tawgyaungbauk",
    "gn:population":0,
    "gn:timezone":"Asia/Yangon",
    "iso:country":"MM",
    "name:und_x_variant":[
        "Tawgyaung",
        "Tawgyaungbauk"
    ],
    "wof:name":"Tawgyaungbauk",
    "wof:placetype":"locality"
},
  "geometry": {"coordinates":[96.69551,18.21142],"type":"Point"}
}