{
  "type": "Feature",
  "properties": {
    "gn:admin1_code":"11.0",
    "gn:admin2_code":"MMR014D002",
    "gn:admin3_code":"MMR014013",
    "gn:asciiname":"Mawksam",
    "gn:country_code":"MM",
    "gn:dem":872,
    "gn:feature_class":"P",
    "gn:feature_code":"PPL",
    "gn:name":"Mawksam",
    "gn:population":0,
    "gn:timezone":"Asia/Yangon",
    "iso:country":"MM",
    "wof:name":"Mawksam",
    "wof:placetype":"locality"
},
  "geometry": {"coordinates":[97.95,20.86667000000001],"type":"Point"}
}