{
  "type": "Feature",
  "properties": {
    "gn:admin1_code":"8.0",
    "gn:admin2_code":"MMR010D001",
    "gn:admin3_code":"MMR010006",
    "gn:asciiname":"Tamokso",
    "gn:country_code":"MM",
    "gn:dem":83,
    "gn:feature_class":"P",
    "gn:feature_code":"PPL",
    "gn:name":"Tamokso",
    "gn:population":0,
    "gn:timezone":"Asia/Yangon",
    "iso:country":"MM",
    "wof:name":"Tamokso",
    "wof:placetype":"locality"
},
  "geometry": {"coordinates":[96.15616,21.85396],"type":"Point"}
}