{
  "type": "Feature",
  "properties": {
    "gn:admin1_code":"11.0",
    "gn:admin2_code":"MMR016D003",
    "gn:admin3_code":"MMR016011",
    "gn:asciiname":"Wan Ra-sa-hkamhkam",
    "gn:cc2":"MM",
    "gn:country_code":"MM",
    "gn:dem":822,
    "gn:feature_class":"P",
    "gn:feature_code":"PPL",
    "gn:name":"W\u0101n Ra-sa-hkamhkam",
    "gn:population":0,
    "gn:timezone":"Asia/Yangon",
    "iso:country":"MM",
    "name:und_x_variant":[
        "W\u0101n Ra-sa-hkanhkam",
        "W\u0101n Ra-sa-hkamhkam"
    ],
    "wof:name":"Wan Ra-sa-hkamhkam",
    "wof:placetype":"locality"
},
  "geometry": {"coordinates":[101.09999999999999,21.66667],"type":"Point"}
}