{
  "type": "Feature",
  "properties": {
    "gn:admin1_code":"17.0",
    "gn:admin2_code":"MMR013D003",
    "gn:admin3_code":"MMR013031",
    "gn:asciiname":"Gyaungwaing-auk",
    "gn:country_code":"MM",
    "gn:dem":9,
    "gn:feature_class":"P",
    "gn:feature_code":"PPL",
    "gn:name":"Gyaungwaing-auk",
    "gn:population":0,
    "gn:timezone":"Asia/Yangon",
    "iso:country":"MM",
    "wof:name":"Gyaungwaing-auk",
    "wof:placetype":"locality"
},
  "geometry": {"coordinates":[96.10713,16.78182],"type":"Point"}
}