{
  "type": "Feature",
  "properties": {
    "gn:admin1_code":"11.0",
    "gn:admin2_code":"MMR016D003",
    "gn:admin3_code":"MMR016009",
    "gn:asciiname":"Keng Lap",
    "gn:country_code":"MM",
    "gn:dem":443,
    "gn:feature_class":"P",
    "gn:feature_code":"PPL",
    "gn:name":"K\u0113ng Lap",
    "gn:population":0,
    "gn:timezone":"Asia/Yangon",
    "iso:country":"MM",
    "wof:name":"Keng Lap",
    "wof:placetype":"locality"
},
  "geometry": {"coordinates":[100.51246,20.86143],"type":"Point"}
}