{
  "type": "Feature",
  "properties": {
    "gn:admin1_code":"11.0",
    "gn:admin2_code":"MMR015D003",
    "gn:admin3_code":"MMR015019",
    "gn:asciiname":"Man Sao-la",
    "gn:country_code":"MM",
    "gn:dem":885,
    "gn:feature_class":"P",
    "gn:feature_code":"PPL",
    "gn:name":"M\u0101n Sao-la",
    "gn:population":0,
    "gn:timezone":"Asia/Yangon",
    "iso:country":"MM",
    "wof:name":"Man Sao-la",
    "wof:placetype":"locality"
},
  "geometry": {"coordinates":[97.53001999999999,23.38746],"type":"Point"}
}