{
  "type": "Feature",
  "properties": {
    "gn:admin1_code":"4.0",
    "gn:admin2_code":"MMR001D003",
    "gn:admin3_code":"MMR001012",
    "gn:asciiname":"Kumhtat",
    "gn:country_code":"MM",
    "gn:dem":1053,
    "gn:feature_class":"P",
    "gn:feature_code":"PPL",
    "gn:name":"Kumhtat",
    "gn:population":0,
    "gn:timezone":"Asia/Yangon",
    "iso:country":"MM",
    "wof:name":"Kumhtat",
    "wof:placetype":"locality"
},
  "geometry": {"coordinates":[97.47311999999999,24.33632],"type":"Point"}
}