{
  "type": "Feature",
  "properties": {
    "gn:admin1_code":"11.0",
    "gn:admin2_code":"MMR015D001",
    "gn:admin3_code":"MMR015004",
    "gn:asciiname":"Man Loi-se",
    "gn:country_code":"MM",
    "gn:dem":1419,
    "gn:feature_class":"P",
    "gn:feature_code":"PPL",
    "gn:name":"M\u0101n Loi-se",
    "gn:population":0,
    "gn:timezone":"Asia/Yangon",
    "iso:country":"MM",
    "name:und_x_variant":[
        "Loi-se",
        "M\u0101n Loi-se"
    ],
    "wof:name":"Man Loi-se",
    "wof:placetype":"locality"
},
  "geometry": {"coordinates":[98.45256999999999,22.35569],"type":"Point"}
}