{
  "type": "Feature",
  "properties": {
    "gn:admin1_code":"4.0",
    "gn:admin2_code":"MMR001D001",
    "gn:admin3_code":"MMR001006",
    "gn:asciiname":"Pashe",
    "gn:country_code":"MM",
    "gn:dem":970,
    "gn:feature_class":"P",
    "gn:feature_code":"PPL",
    "gn:name":"Pashe",
    "gn:population":0,
    "gn:timezone":"Asia/Yangon",
    "iso:country":"MM",
    "wof:name":"Pashe",
    "wof:placetype":"locality"
},
  "geometry": {"coordinates":[98.30595,26.47851],"type":"Point"}
}