{
  "type": "Feature",
  "properties": {
    "gn:admin1_code":"16.0",
    "gn:admin2_code":"MMR008D002",
    "gn:admin3_code":"MMR008010",
    "gn:asciiname":"Myaung",
    "gn:country_code":"MM",
    "gn:dem":42,
    "gn:feature_class":"P",
    "gn:feature_code":"PPL",
    "gn:name":"Myaung",
    "gn:population":0,
    "gn:timezone":"Asia/Yangon",
    "iso:country":"MM",
    "name:mya_x_preferred":[
        "\u1019\u103c\u1031\u102c\u1004\u103a\u1019\u103c\u102d\u102f\u1037"
    ],
    "name:pol_x_preferred":[
        "Myaung"
    ],
    "wof:name":"Myaung",
    "wof:placetype":"locality"
},
  "geometry": {"coordinates":[95.77811,18.1706],"type":"Point"}
}