{
  "type": "Feature",
  "properties": {
    "gn:admin1_code":"8.0",
    "gn:admin2_code":"MMR010D004",
    "gn:admin3_code":"MMR010019",
    "gn:asciiname":"Tazo",
    "gn:country_code":"MM",
    "gn:dem":162,
    "gn:feature_class":"P",
    "gn:feature_code":"PPL",
    "gn:name":"Tazo",
    "gn:population":0,
    "gn:timezone":"Asia/Yangon",
    "iso:country":"MM",
    "wof:name":"Tazo",
    "wof:placetype":"locality"
},
  "geometry": {"coordinates":[95.50368,21.38691],"type":"Point"}
}