{
  "type": "Feature",
  "properties": {
    "gn:admin1_code":"10.0",
    "gn:admin2_code":"MMR005D008",
    "gn:admin3_code":"MMR005035",
    "gn:asciiname":"Yawpami",
    "gn:country_code":"MM",
    "gn:dem":843,
    "gn:feature_class":"P",
    "gn:feature_code":"PPL",
    "gn:name":"Yawpami",
    "gn:population":0,
    "gn:timezone":"Asia/Yangon",
    "iso:country":"MM",
    "name:und_x_variant":[
        "Lapin",
        "Yawpami"
    ],
    "name:urd_x_preferred":[
        "\u06cc\u0648\u067e\u0645\u06cc"
    ],
    "wof:name":"Yawpami",
    "wof:placetype":"locality"
},
  "geometry": {"coordinates":[95.02862,25.63237],"type":"Point"}
}