{
  "type": "Feature",
  "properties": {
    "gn:admin1_code":"4.0",
    "gn:admin2_code":"MMR001D003",
    "gn:admin3_code":"MMR001012",
    "gn:asciiname":"Wajau-dingsa",
    "gn:country_code":"MM",
    "gn:dem":721,
    "gn:feature_class":"P",
    "gn:feature_code":"PPL",
    "gn:name":"Wajau-dingsa",
    "gn:population":0,
    "gn:timezone":"Asia/Yangon",
    "iso:country":"MM",
    "wof:name":"Wajau-dingsa",
    "wof:placetype":"locality"
},
  "geometry": {"coordinates":[97.55428999999999,24.68964],"type":"Point"}
}