{
  "type": "Feature",
  "properties": {
    "gn:admin1_code":"5.0",
    "gn:admin2_code":"MMR003D001",
    "gn:admin3_code":"MMR003004",
    "gn:asciiname":"Bresso Atet",
    "gn:country_code":"MM",
    "gn:dem":797,
    "gn:feature_class":"P",
    "gn:feature_code":"PPL",
    "gn:name":"Bresso Atet",
    "gn:population":0,
    "gn:timezone":"Asia/Yangon",
    "iso:country":"MM",
    "wof:name":"Bresso Atet",
    "wof:placetype":"locality"
},
  "geometry": {"coordinates":[96.75951000000001,19.37742],"type":"Point"}
}