{
  "type": "Feature",
  "properties": {
    "gn:admin1_code":"11.0",
    "gn:admin2_code":"MMR016D001",
    "gn:admin3_code":"MMR016007",
    "gn:asciiname":"Weng Kao",
    "gn:country_code":"MM",
    "gn:dem":463,
    "gn:feature_class":"P",
    "gn:feature_code":"PPL",
    "gn:name":"Weng Kao",
    "gn:population":0,
    "gn:timezone":"Asia/Yangon",
    "iso:country":"MM",
    "wof:name":"Weng Kao",
    "wof:placetype":"locality"
},
  "geometry": {"coordinates":[99.02,21.34179],"type":"Point"}
}