{
  "type": "Feature",
  "properties": {
    "gn:admin1_code":"8.0",
    "gn:admin2_code":"MMR010D007",
    "gn:admin3_code":"MMR010031",
    "gn:asciiname":"Palawa",
    "gn:country_code":"MM",
    "gn:dem":172,
    "gn:feature_class":"P",
    "gn:feature_code":"PPL",
    "gn:name":"Palawa",
    "gn:population":0,
    "gn:timezone":"Asia/Yangon",
    "iso:country":"MM",
    "name:nld_x_preferred":[
        "Palawa"
    ],
    "wof:name":"Palawa",
    "wof:placetype":"locality"
},
  "geometry": {"coordinates":[95.87523,21.12494],"type":"Point"}
}