{
  "type": "Feature",
  "properties": {
    "gn:admin1_code":"4.0",
    "gn:admin2_code":"MMR001D002",
    "gn:admin3_code":"MMR001007",
    "gn:asciiname":"Pintha",
    "gn:country_code":"MM",
    "gn:dem":247,
    "gn:feature_class":"P",
    "gn:feature_code":"PPL",
    "gn:name":"Pintha",
    "gn:population":0,
    "gn:timezone":"Asia/Yangon",
    "iso:country":"MM",
    "wof:name":"Pintha",
    "wof:placetype":"locality"
},
  "geometry": {"coordinates":[96.31441,24.81046],"type":"Point"}
}