{
  "type": "Feature",
  "properties": {
    "gn:admin1_code":"10.0",
    "gn:admin2_code":"MMR005D008",
    "gn:admin3_code":"MMR005034",
    "gn:asciiname":"Kyaunggon",
    "gn:country_code":"MM",
    "gn:dem":127,
    "gn:feature_class":"P",
    "gn:feature_code":"PPL",
    "gn:name":"Kyaunggon",
    "gn:population":0,
    "gn:timezone":"Asia/Yangon",
    "iso:country":"MM",
    "name:mya_x_preferred":[
        "\u1000\u103b\u1031\u102c\u1004\u103a\u1038\u1000\u102f\u1014\u103a\u1038\u1019\u103c\u102d\u102f\u1037"
    ],
    "wof:name":"Kyaunggon",
    "wof:placetype":"locality"
},
  "geometry": {"coordinates":[94.7593,24.40826],"type":"Point"}
}