{
  "type": "Feature",
  "properties": {
    "gn:admin1_code":"15.0",
    "gn:admin2_code":"MMR009D001",
    "gn:admin3_code":"MMR009003",
    "gn:asciiname":"Thonzin",
    "gn:country_code":"MM",
    "gn:dem":101,
    "gn:feature_class":"P",
    "gn:feature_code":"PPL",
    "gn:name":"Thonzin",
    "gn:population":0,
    "gn:timezone":"Asia/Yangon",
    "iso:country":"MM",
    "wof:name":"Thonzin",
    "wof:placetype":"locality"
},
  "geometry": {"coordinates":[94.79951,20.70112],"type":"Point"}
}