{
  "type": "Feature",
  "properties": {
    "gn:admin1_code":"15.0",
    "gn:admin2_code":"MMR009D004",
    "gn:admin3_code":"MMR009018",
    "gn:asciiname":"Yelekyun",
    "gn:country_code":"MM",
    "gn:dem":61,
    "gn:feature_class":"P",
    "gn:feature_code":"PPL",
    "gn:name":"Yelekyun",
    "gn:population":0,
    "gn:timezone":"Asia/Yangon",
    "iso:country":"MM",
    "wof:name":"Yelekyun",
    "wof:placetype":"locality"
},
  "geometry": {"coordinates":[94.96787999999999,21.24314],"type":"Point"}
}