{
  "type": "Feature",
  "properties": {
    "gn:admin1_code":"11.0",
    "gn:admin2_code":"MMR016D003",
    "gn:admin3_code":"MMR016009",
    "gn:asciiname":"Wan Hsenhkamwang",
    "gn:country_code":"MM",
    "gn:dem":522,
    "gn:elevation":"529.0",
    "gn:feature_class":"P",
    "gn:feature_code":"PPL",
    "gn:name":"W\u0101n Hsenhkamwang",
    "gn:population":0,
    "gn:timezone":"Asia/Yangon",
    "iso:country":"MM",
    "name:und_x_variant":[
        "W\u0101n Hsenhlamwang",
        "W\u0101n Hsenhkamwang"
    ],
    "wof:name":"Wan Hsenhkamwang",
    "wof:placetype":"locality"
},
  "geometry": {"coordinates":[99.82461000000001,20.62767],"type":"Point"}
}