{
  "type": "Feature",
  "properties": {
    "gn:admin1_code":"1.0",
    "gn:admin2_code":"MMR012D002",
    "gn:admin3_code":"MMR012010",
    "gn:asciiname":"Seinnyinbya",
    "gn:country_code":"MM",
    "gn:dem":4,
    "gn:feature_class":"P",
    "gn:feature_code":"PPL",
    "gn:name":"Seinnyinbya",
    "gn:population":0,
    "gn:timezone":"Asia/Yangon",
    "iso:country":"MM",
    "wof:name":"Seinnyinbya",
    "wof:placetype":"locality"
},
  "geometry": {"coordinates":[92.54589,20.76772],"type":"Point"}
}