{
  "type": "Feature",
  "properties": {
    "gn:admin1_code":"10.0",
    "gn:admin2_code":"MMR005D004",
    "gn:admin3_code":"MMR005022",
    "gn:asciiname":"Thaunggyi",
    "gn:country_code":"MM",
    "gn:dem":91,
    "gn:feature_class":"P",
    "gn:feature_code":"PPL",
    "gn:name":"Thaunggyi",
    "gn:population":0,
    "gn:timezone":"Asia/Yangon",
    "iso:country":"MM",
    "wof:name":"Thaunggyi",
    "wof:placetype":"locality"
},
  "geometry": {"coordinates":[96.11327,23.73385],"type":"Point"}
}