{
  "type": "Feature",
  "properties": {
    "gn:admin1_code":"11.0",
    "gn:admin2_code":"MMR014D001",
    "gn:admin3_code":"MMR014004",
    "gn:asciiname":"Wengkau",
    "gn:country_code":"MM",
    "gn:dem":829,
    "gn:feature_class":"P",
    "gn:feature_code":"PPL",
    "gn:name":"Wengkau",
    "gn:population":0,
    "gn:timezone":"Asia/Yangon",
    "iso:country":"MM",
    "wof:name":"Wengkau",
    "wof:placetype":"locality"
},
  "geometry": {"coordinates":[97.19441999999999,20.13358],"type":"Point"}
}