{
  "type": "Feature",
  "properties": {
    "gn:admin1_code":"5.0",
    "gn:admin2_code":"MMR003D001",
    "gn:admin3_code":"MMR003001",
    "gn:asciiname":"Kaya-atwin",
    "gn:country_code":"MM",
    "gn:dem":14,
    "gn:feature_class":"P",
    "gn:feature_code":"PPL",
    "gn:name":"Kaya-atwin",
    "gn:population":0,
    "gn:timezone":"Asia/Yangon",
    "iso:country":"MM",
    "wof:name":"Kaya-atwin",
    "wof:placetype":"locality"
},
  "geometry": {"coordinates":[97.83486000000001,16.6093],"type":"Point"}
}