{
  "type": "Feature",
  "properties": {
    "gn:admin1_code":"2.0",
    "gn:admin2_code":"MMR004D002",
    "gn:admin3_code":"MMR004007",
    "gn:asciiname":"Tangin",
    "gn:country_code":"MM",
    "gn:dem":1273,
    "gn:feature_class":"P",
    "gn:feature_code":"PPL",
    "gn:name":"Tangin",
    "gn:population":0,
    "gn:timezone":"Asia/Yangon",
    "iso:country":"MM",
    "wof:name":"Tangin",
    "wof:placetype":"locality"
},
  "geometry": {"coordinates":[93.42319999999999,21.88829],"type":"Point"}
}