{
  "type": "Feature",
  "properties": {
    "gn:admin1_code":"5.0",
    "gn:admin2_code":"MMR003D001",
    "gn:admin3_code":"MMR003002",
    "gn:asciiname":"Takara",
    "gn:country_code":"MM",
    "gn:dem":25,
    "gn:feature_class":"P",
    "gn:feature_code":"PPL",
    "gn:name":"Takara",
    "gn:population":0,
    "gn:timezone":"Asia/Yangon",
    "iso:country":"MM",
    "name:fra_x_preferred":[
        "Takara"
    ],
    "name:jpn_x_preferred":[
        "\u30bf\u30ab\u30e9"
    ],
    "name:nld_x_preferred":[
        "Takara"
    ],
    "name:por_x_preferred":[
        "Takara"
    ],
    "name:swe_x_preferred":[
        "Takara"
    ],
    "name:zho_x_preferred":[
        "\u7279\u4f73\u9e97"
    ],
    "wof:name":"Takara",
    "wof:placetype":"locality"
},
  "geometry": {"coordinates":[98.08562999999999,16.87358],"type":"Point"}
}