{
  "type": "Feature",
  "properties": {
    "gn:admin1_code":"1.0",
    "gn:admin2_code":"MMR012D004",
    "gn:admin3_code":"MMR012017",
    "gn:asciiname":"Satthwa",
    "gn:country_code":"MM",
    "gn:dem":9,
    "gn:feature_class":"P",
    "gn:feature_code":"PPL",
    "gn:name":"Satthwa",
    "gn:population":0,
    "gn:timezone":"Asia/Yangon",
    "iso:country":"MM",
    "name:und_x_variant":[
        "Hswathwa",
        "Satthwa"
    ],
    "wof:name":"Satthwa",
    "wof:placetype":"locality"
},
  "geometry": {"coordinates":[94.49914,17.77757],"type":"Point"}
}