{
  "type": "Feature",
  "properties": {
    "gn:admin1_code":"11.0",
    "gn:admin2_code":"MMR015D002",
    "gn:admin3_code":"MMR015009",
    "gn:asciiname":"Pangmwi",
    "gn:country_code":"MM",
    "gn:dem":1317,
    "gn:feature_class":"P",
    "gn:feature_code":"PPL",
    "gn:name":"Pangmwi",
    "gn:population":0,
    "gn:timezone":"Asia/Yangon",
    "iso:country":"MM",
    "wof:name":"Pangmwi",
    "wof:placetype":"locality"
},
  "geometry": {"coordinates":[98.41614,24.08753],"type":"Point"}
}