{
  "type": "Feature",
  "properties": {
    "gn:admin1_code":"15.0",
    "gn:admin2_code":"MMR009D001",
    "gn:admin3_code":"MMR009002",
    "gn:asciiname":"Pangasan",
    "gn:country_code":"MM",
    "gn:dem":169,
    "gn:feature_class":"P",
    "gn:feature_code":"PPL",
    "gn:name":"Pangasan",
    "gn:population":0,
    "gn:timezone":"Asia/Yangon",
    "iso:country":"MM",
    "wof:name":"Pangasan",
    "wof:placetype":"locality"
},
  "geometry": {"coordinates":[94.99393000000001,20.39575],"type":"Point"}
}