{
  "type": "Feature",
  "properties": {
    "gn:admin1_code":"11.0",
    "gn:admin2_code":"MMR014D001",
    "gn:admin3_code":"MMR014002",
    "gn:asciiname":"Wan Kunleng",
    "gn:country_code":"MM",
    "gn:dem":894,
    "gn:feature_class":"P",
    "gn:feature_code":"PPL",
    "gn:name":"W\u0101n Kunl\u0113ng",
    "gn:population":0,
    "gn:timezone":"Asia/Yangon",
    "iso:country":"MM",
    "wof:name":"Wan Kunleng",
    "wof:placetype":"locality"
},
  "geometry": {"coordinates":[97.0081,19.99837],"type":"Point"}
}