{
  "type": "Feature",
  "properties": {
    "gn:admin1_code":"15.0",
    "gn:admin2_code":"MMR009D001",
    "gn:admin3_code":"MMR009003",
    "gn:asciiname":"Myezun",
    "gn:country_code":"MM",
    "gn:dem":247,
    "gn:feature_class":"P",
    "gn:feature_code":"PPL",
    "gn:name":"Myezun",
    "gn:population":0,
    "gn:timezone":"Asia/Yangon",
    "iso:country":"MM",
    "wof:name":"Myezun",
    "wof:placetype":"locality"
},
  "geometry": {"coordinates":[94.91146999999999,20.58817],"type":"Point"}
}