{
  "type": "Feature",
  "properties": {
    "gn:admin1_code":"1.0",
    "gn:admin2_code":"MMR012D003",
    "gn:admin3_code":"MMR012014",
    "gn:asciiname":"Sabagyi",
    "gn:country_code":"MM",
    "gn:dem":127,
    "gn:feature_class":"P",
    "gn:feature_code":"PPL",
    "gn:name":"Sabagyi",
    "gn:population":0,
    "gn:timezone":"Asia/Yangon",
    "iso:country":"MM",
    "name:und_x_variant":[
        "Saagyi",
        "Sabagyi"
    ],
    "wof:name":"Sabagyi",
    "wof:placetype":"locality"
},
  "geometry": {"coordinates":[93.93684,19.77806],"type":"Point"}
}