{
  "type": "Feature",
  "properties": {
    "gn:admin1_code":"4.0",
    "gn:admin2_code":"MMR001D001",
    "gn:admin3_code":"MMR001005",
    "gn:asciiname":"Tamtu",
    "gn:country_code":"MM",
    "gn:dem":968,
    "gn:feature_class":"P",
    "gn:feature_code":"PPL",
    "gn:name":"T\u0101mtu",
    "gn:population":0,
    "gn:timezone":"Asia/Yangon",
    "iso:country":"MM",
    "name:und_x_variant":[
        "T\u0101mtu"
    ],
    "wof:name":"Tamtu",
    "wof:placetype":"locality"
},
  "geometry": {"coordinates":[98.15000000000001,26.06667],"type":"Point"}
}