{
  "type": "Feature",
  "properties": {
    "gn:admin1_code":"11.0",
    "gn:admin2_code":"MMR014D001",
    "gn:admin3_code":"MMR014003",
    "gn:asciiname":"Wan Keng",
    "gn:country_code":"MM",
    "gn:dem":1136,
    "gn:feature_class":"P",
    "gn:feature_code":"PPL",
    "gn:name":"W\u0101n Keng",
    "gn:population":0,
    "gn:timezone":"Asia/Yangon",
    "iso:country":"MM",
    "wof:name":"Wan Keng",
    "wof:placetype":"locality"
},
  "geometry": {"coordinates":[97.40837999999999,20.70549],"type":"Point"}
}