{
  "type": "Feature",
  "properties": {
    "gn:admin1_code":"11.0",
    "gn:admin2_code":"MMR014D003",
    "gn:admin3_code":"MMR014018",
    "gn:asciiname":"Wan Pu-ka-loe",
    "gn:country_code":"MM",
    "gn:dem":936,
    "gn:feature_class":"P",
    "gn:feature_code":"PPL",
    "gn:name":"W\u0101n Pu-ka-l\u00f6",
    "gn:population":0,
    "gn:timezone":"Asia/Yangon",
    "iso:country":"MM",
    "wof:name":"Wan Pu-ka-loe",
    "wof:placetype":"locality"
},
  "geometry": {"coordinates":[97.97444,19.7825],"type":"Point"}
}