{
  "type": "Feature",
  "properties": {
    "gn:admin1_code":"3.0",
    "gn:admin2_code":"MMR017D003",
    "gn:admin3_code":"MMR017015",
    "gn:asciiname":"Ywathit",
    "gn:country_code":"MM",
    "gn:dem":11,
    "gn:feature_class":"P",
    "gn:feature_code":"PPL",
    "gn:name":"Ywathit",
    "gn:population":0,
    "gn:timezone":"Asia/Yangon",
    "iso:country":"MM",
    "wof:name":"Ywathit",
    "wof:placetype":"locality"
},
  "geometry": {"coordinates":[95.11268,16.75153],"type":"Point"}
}