{
  "type": "Feature",
  "properties": {
    "gn:admin1_code":"5.0",
    "gn:admin2_code":"MMR003D001",
    "gn:admin3_code":"MMR003001",
    "gn:asciiname":"Kobashu",
    "gn:country_code":"MM",
    "gn:dem":18,
    "gn:feature_class":"P",
    "gn:feature_code":"PPL",
    "gn:name":"Kobashu",
    "gn:population":0,
    "gn:timezone":"Asia/Yangon",
    "iso:country":"MM",
    "name:und_x_variant":[
        "Kobasnu",
        "Kobashu"
    ],
    "wof:name":"Kobashu",
    "wof:placetype":"locality"
},
  "geometry": {"coordinates":[97.71887,16.73302],"type":"Point"}
}