{
  "type": "Feature",
  "properties": {
    "gn:admin1_code":"10.0",
    "gn:admin2_code":"MMR005D009",
    "gn:admin3_code":"MMR005019",
    "gn:asciiname":"Sebyin",
    "gn:country_code":"MM",
    "gn:dem":266,
    "gn:feature_class":"P",
    "gn:feature_code":"PPL",
    "gn:name":"S\u00e8byin",
    "gn:population":0,
    "gn:timezone":"Asia/Yangon",
    "iso:country":"MM",
    "wof:name":"Sebyin",
    "wof:placetype":"locality"
},
  "geometry": {"coordinates":[94.52736,22.03831],"type":"Point"}
}