{
  "type": "Feature",
  "properties": {
    "gn:admin1_code":"3.0",
    "gn:admin2_code":"MMR017D001",
    "gn:admin3_code":"MMR017001",
    "gn:asciiname":"Taungdangon",
    "gn:country_code":"MM",
    "gn:dem":18,
    "gn:feature_class":"P",
    "gn:feature_code":"PPL",
    "gn:name":"Taungdang\u00f4n",
    "gn:population":0,
    "gn:timezone":"Asia/Yangon",
    "iso:country":"MM",
    "wof:name":"Taungdangon",
    "wof:placetype":"locality"
},
  "geometry": {"coordinates":[94.61339,16.64325],"type":"Point"}
}