{
  "type": "Feature",
  "properties": {
    "gn:admin1_code":"11.0",
    "gn:admin2_code":"MMR015D006",
    "gn:admin3_code":"MMR015008",
    "gn:asciiname":"Hpaktu-lin",
    "gn:country_code":"MM",
    "gn:dem":1258,
    "gn:feature_class":"P",
    "gn:feature_code":"PPL",
    "gn:name":"Hpaktu-lin",
    "gn:population":0,
    "gn:timezone":"Asia/Yangon",
    "iso:country":"MM",
    "wof:name":"Hpaktu-lin",
    "wof:placetype":"locality"
},
  "geometry": {"coordinates":[98.86667,22.96667],"type":"Point"}
}