{
  "type": "Feature",
  "properties": {
    "gn:admin1_code":"11.0",
    "gn:admin2_code":"MMR016D003",
    "gn:admin3_code":"MMR016011",
    "gn:asciiname":"Moeng Yawng",
    "gn:country_code":"MM",
    "gn:dem":569,
    "gn:feature_class":"P",
    "gn:feature_code":"PPL",
    "gn:name":"M\u00f6ng Yawng",
    "gn:population":0,
    "gn:timezone":"Asia/Yangon",
    "iso:country":"MM",
    "name:mya_x_preferred":[
        "\u1019\u102d\u102f\u1004\u103a\u1038\u101a\u1031\u102c\u1004\u103a\u1038\u1019\u103c\u102d\u102f\u1037"
    ],
    "name:shn_x_preferred":[
        "\u1019\u102d\u1030\u1004\u103a\u1038\u101a\u103d\u1004\u103a\u1038\u104a \u101d\u1035\u1004\u103a\u1038"
    ],
    "name:und_x_variant":[
        "Maingyaung",
        "Mong Yong",
        "M\u00f6ng Yaung",
        "Meng-yang",
        "M\u00f6ng Yawng"
    ],
    "wof:name":"Moeng Yawng",
    "wof:placetype":"locality"
},
  "geometry": {"coordinates":[100.35760999999999,21.17924],"type":"Point"}
}