{
  "type": "Feature",
  "properties": {
    "gn:admin1_code":"8.0",
    "gn:admin2_code":"MMR010D004",
    "gn:admin3_code":"MMR010017",
    "gn:asciiname":"Kaing",
    "gn:country_code":"MM",
    "gn:dem":55,
    "gn:feature_class":"P",
    "gn:feature_code":"PPL",
    "gn:name":"Kaing",
    "gn:population":0,
    "gn:timezone":"Asia/Yangon",
    "iso:country":"MM",
    "name:und_x_variant":[
        "Kaing North",
        "Kaing"
    ],
    "wof:name":"Kaing",
    "wof:placetype":"locality"
},
  "geometry": {"coordinates":[95.33813000000001,21.43081],"type":"Point"}
}