{
  "type": "Feature",
  "properties": {
    "gn:admin1_code":"10.0",
    "gn:admin2_code":"MMR005D004",
    "gn:admin3_code":"MMR005026",
    "gn:asciiname":"Wayutha",
    "gn:country_code":"MM",
    "gn:dem":260,
    "gn:feature_class":"P",
    "gn:feature_code":"PPL",
    "gn:name":"Wayutha",
    "gn:population":0,
    "gn:timezone":"Asia/Yangon",
    "iso:country":"MM",
    "name:und_x_variant":[
        "Wayontha",
        "Wayutha"
    ],
    "wof:name":"Wayutha",
    "wof:placetype":"locality"
},
  "geometry": {"coordinates":[95.24066000000001,23.92532000000001],"type":"Point"}
}