{
  "type": "Feature",
  "properties": {
    "gn:admin1_code":"11.0",
    "gn:admin2_code":"MMR015D001",
    "gn:admin3_code":"MMR015003",
    "gn:asciiname":"Nawng-hket",
    "gn:country_code":"MM",
    "gn:dem":1187,
    "gn:feature_class":"P",
    "gn:feature_code":"PPL",
    "gn:name":"Nawng-hket",
    "gn:population":0,
    "gn:timezone":"Asia/Yangon",
    "iso:country":"MM",
    "wof:name":"Nawng-hket",
    "wof:placetype":"locality"
},
  "geometry": {"coordinates":[97.91003000000001,22.51163],"type":"Point"}
}