{
  "type": "Feature",
  "properties": {
    "gn:admin1_code":"12.0",
    "gn:admin2_code":"MMR006D001",
    "gn:admin3_code":"MMR006003",
    "gn:asciiname":"Pandaw",
    "gn:country_code":"MM",
    "gn:dem":5,
    "gn:feature_class":"P",
    "gn:feature_code":"PPL",
    "gn:name":"Pandaw",
    "gn:population":0,
    "gn:timezone":"Asia/Yangon",
    "iso:country":"MM",
    "name:und_x_variant":[
        "Pandao",
        "Pandaw"
    ],
    "wof:name":"Pandaw",
    "wof:placetype":"locality"
},
  "geometry": {"coordinates":[98.26384,13.85197],"type":"Point"}
}