{
  "type": "Feature",
  "properties": {
    "gn:admin1_code":"1.0",
    "gn:admin2_code":"MMR012D005",
    "gn:admin3_code":"MMR012004",
    "gn:asciiname":"Thandaung",
    "gn:country_code":"MM",
    "gn:dem":8,
    "gn:feature_class":"P",
    "gn:feature_code":"PPL",
    "gn:name":"Thandaung",
    "gn:population":0,
    "gn:timezone":"Asia/Yangon",
    "iso:country":"MM",
    "name:mya_x_preferred":[
        "\u101e\u1036\u1010\u1031\u102c\u1004\u103a\u1019\u103c\u102d\u102f\u1037"
    ],
    "name:shn_x_preferred":[
        "\u1010\u1062\u107c\u103a\u1087\u1010\u103d\u1004\u103a\u1087\u104a \u101d\u1035\u1004\u103a\u1038"
    ],
    "wof:name":"Thandaung",
    "wof:placetype":"locality"
},
  "geometry": {"coordinates":[92.94377,20.89427],"type":"Point"}
}