{
  "type": "Feature",
  "properties": {
    "gn:admin1_code":"11.0",
    "gn:admin2_code":"MMR014D002",
    "gn:admin3_code":"MMR014016",
    "gn:asciiname":"Wan Hwe-loi",
    "gn:country_code":"MM",
    "gn:dem":748,
    "gn:feature_class":"P",
    "gn:feature_code":"PPL",
    "gn:name":"W\u0101n Hw\u00e8-loi",
    "gn:population":0,
    "gn:timezone":"Asia/Yangon",
    "iso:country":"MM",
    "wof:name":"Wan Hwe-loi",
    "wof:placetype":"locality"
},
  "geometry": {"coordinates":[97.21489,21.68752000000001],"type":"Point"}
}