{
  "type": "Feature",
  "properties": {
    "gn:admin1_code":"4.0",
    "gn:admin2_code":"MMR001D003",
    "gn:admin3_code":"MMR001013",
    "gn:asciiname":"Saga Nam Khum",
    "gn:country_code":"MM",
    "gn:dem":1112,
    "gn:feature_class":"P",
    "gn:feature_code":"PPL",
    "gn:name":"Saga Nam Khum",
    "gn:population":0,
    "gn:timezone":"Asia/Yangon",
    "iso:country":"MM",
    "wof:name":"Saga Nam Khum",
    "wof:placetype":"locality"
},
  "geometry": {"coordinates":[97.13997999999999,23.69192],"type":"Point"}
}