{
  "type": "Feature",
  "properties": {
    "gn:admin1_code":"6.0",
    "gn:admin2_code":"MMR002D001",
    "gn:admin3_code":"MMR002001",
    "gn:asciiname":"Dawta-naw",
    "gn:country_code":"MM",
    "gn:dem":911,
    "gn:feature_class":"P",
    "gn:feature_code":"PPL",
    "gn:name":"Dawta-naw",
    "gn:population":0,
    "gn:timezone":"Asia/Yangon",
    "iso:country":"MM",
    "wof:name":"Dawta-naw",
    "wof:placetype":"locality"
},
  "geometry": {"coordinates":[97.19540000000001,19.84689],"type":"Point"}
}