{
  "type": "Feature",
  "properties": {
    "gn:admin1_code":"15.0",
    "gn:admin2_code":"MMR009D002",
    "gn:admin3_code":"MMR009008",
    "gn:asciiname":"Kinde",
    "gn:country_code":"MM",
    "gn:dem":64,
    "gn:feature_class":"P",
    "gn:feature_code":"PPL",
    "gn:name":"Kinde",
    "gn:population":0,
    "gn:timezone":"Asia/Yangon",
    "iso:country":"MM",
    "wof:name":"Kinde",
    "wof:placetype":"locality"
},
  "geometry": {"coordinates":[94.63974,20.34557],"type":"Point"}
}