{
  "type": "Feature",
  "properties": {
    "gn:admin1_code":"12.0",
    "gn:admin2_code":"MMR006D001",
    "gn:admin3_code":"MMR006003",
    "gn:asciiname":"Sakhumbo",
    "gn:country_code":"MM",
    "gn:dem":15,
    "gn:feature_class":"P",
    "gn:feature_code":"PPL",
    "gn:name":"Sakhumbo",
    "gn:population":0,
    "gn:timezone":"Asia/Yangon",
    "iso:country":"MM",
    "wof:name":"Sakhumbo",
    "wof:placetype":"locality"
},
  "geometry": {"coordinates":[98.46722,13.37314],"type":"Point"}
}