{
  "type": "Feature",
  "properties": {
    "gn:admin1_code":"5.0",
    "gn:admin2_code":"MMR003D003",
    "gn:admin3_code":"MMR003007",
    "gn:asciiname":"Kasat",
    "gn:country_code":"MM",
    "gn:dem":42,
    "gn:feature_class":"P",
    "gn:feature_code":"PPL",
    "gn:name":"Kasat",
    "gn:population":0,
    "gn:timezone":"Asia/Yangon",
    "iso:country":"MM",
    "name:msa_x_preferred":[
        "Kampung Kasat"
    ],
    "wof:name":"Kasat",
    "wof:placetype":"locality"
},
  "geometry": {"coordinates":[98.21093999999999,15.93862],"type":"Point"}
}