{
  "type": "Feature",
  "properties": {
    "gn:admin1_code":"11.0",
    "gn:admin2_code":"MMR015D002",
    "gn:admin3_code":"MMR015011",
    "gn:asciiname":"Man Panglomno",
    "gn:country_code":"MM",
    "gn:dem":1282,
    "gn:feature_class":"P",
    "gn:feature_code":"PPL",
    "gn:name":"M\u0101n Pangl\u014dmn\u014d",
    "gn:population":0,
    "gn:timezone":"Asia/Yangon",
    "iso:country":"MM",
    "wof:name":"Man Panglomno",
    "wof:placetype":"locality"
},
  "geometry": {"coordinates":[98.42467000000001,23.69165],"type":"Point"}
}