{
  "type": "Feature",
  "properties": {
    "gn:admin1_code":"11.0",
    "gn:admin2_code":"MMR015D003",
    "gn:admin3_code":"MMR015013",
    "gn:asciiname":"Pein-in",
    "gn:country_code":"MM",
    "gn:dem":1009,
    "gn:feature_class":"P",
    "gn:feature_code":"PPL",
    "gn:name":"Pein-in",
    "gn:population":0,
    "gn:timezone":"Asia/Yangon",
    "iso:country":"MM",
    "wof:name":"Pein-in",
    "wof:placetype":"locality"
},
  "geometry": {"coordinates":[96.49797,22.31846],"type":"Point"}
}