{
  "type": "Feature",
  "properties": {
    "gn:admin1_code":"11.0",
    "gn:admin2_code":"MMR015D007",
    "gn:admin3_code":"MMR015006",
    "gn:asciiname":"Ving Nguen",
    "gn:country_code":"MM",
    "gn:dem":1567,
    "gn:feature_class":"P",
    "gn:feature_code":"PPL",
    "gn:name":"Ving Ng\u00fcn",
    "gn:population":0,
    "gn:timezone":"Asia/Yangon",
    "iso:country":"MM",
    "name:und_x_variant":[
        "Ngeklet",
        "Ving Ng\u00fcn"
    ],
    "wof:name":"Ving Nguen",
    "wof:placetype":"locality"
},
  "geometry": {"coordinates":[99.26009999999999,22.63332],"type":"Point"}
}