{
  "type": "Feature",
  "properties": {
    "gn:admin1_code":"1.0",
    "gn:admin2_code":"MMR012D003",
    "gn:admin3_code":"MMR012011",
    "gn:asciiname":"Thapanchaung",
    "gn:country_code":"MM",
    "gn:dem":13,
    "gn:feature_class":"P",
    "gn:feature_code":"PPL",
    "gn:name":"Thapanchaung",
    "gn:population":0,
    "gn:timezone":"Asia/Yangon",
    "iso:country":"MM",
    "wof:name":"Thapanchaung",
    "wof:placetype":"locality"
},
  "geometry": {"coordinates":[93.57841999999999,19.25216],"type":"Point"}
}