{
  "type": "Feature",
  "properties": {
    "gn:admin1_code":"10.0",
    "gn:admin2_code":"MMR005D008",
    "gn:admin3_code":"MMR005034",
    "gn:asciiname":"Thabigon",
    "gn:country_code":"MM",
    "gn:dem":145,
    "gn:feature_class":"P",
    "gn:feature_code":"PPL",
    "gn:name":"Thabigon",
    "gn:population":0,
    "gn:timezone":"Asia/Yangon",
    "iso:country":"MM",
    "wof:name":"Thabigon",
    "wof:placetype":"locality"
},
  "geometry": {"coordinates":[95.28355999999999,24.77554],"type":"Point"}
}