{
  "type": "Feature",
  "properties": {
    "gn:admin1_code":"8.0",
    "gn:admin2_code":"MMR010D003",
    "gn:admin3_code":"MMR010014",
    "gn:asciiname":"Zawgyiywa",
    "gn:country_code":"MM",
    "gn:dem":76,
    "gn:feature_class":"P",
    "gn:feature_code":"PPL",
    "gn:name":"Zawgyiywa",
    "gn:population":0,
    "gn:timezone":"Asia/Yangon",
    "iso:country":"MM",
    "name:und_x_variant":[
        "Kalahpongyiywa",
        "Zawgyiywa"
    ],
    "wof:name":"Zawgyiywa",
    "wof:placetype":"locality"
},
  "geometry": {"coordinates":[96.14373999999999,21.74956],"type":"Point"}
}