{
  "type": "Feature",
  "properties": {
    "gn:admin1_code":"4.0",
    "gn:admin2_code":"MMR001D004",
    "gn:admin3_code":"MMR001017",
    "gn:asciiname":"Mayut",
    "gn:country_code":"MM",
    "gn:dem":1206,
    "gn:feature_class":"P",
    "gn:feature_code":"PPL",
    "gn:name":"Mayut",
    "gn:population":0,
    "gn:timezone":"Asia/Yangon",
    "iso:country":"MM",
    "wof:name":"Mayut",
    "wof:placetype":"locality"
},
  "geometry": {"coordinates":[98.14134,27.67783],"type":"Point"}
}