{
  "type": "Feature",
  "properties": {
    "gn:admin1_code":"15.0",
    "gn:admin2_code":"MMR009D003",
    "gn:admin3_code":"MMR009012",
    "gn:asciiname":"Kyaukme",
    "gn:country_code":"MM",
    "gn:dem":153,
    "gn:feature_class":"P",
    "gn:feature_code":"PPL",
    "gn:name":"Kyaukm\u00e8",
    "gn:population":0,
    "gn:timezone":"Asia/Yangon",
    "iso:country":"MM",
    "wof:name":"Kyaukme",
    "wof:placetype":"locality"
},
  "geometry": {"coordinates":[95.06585,19.56538],"type":"Point"}
}