{
  "type": "Feature",
  "properties": {
    "gn:admin1_code":"16.0",
    "gn:admin2_code":"MMR008D002",
    "gn:admin3_code":"MMR008008",
    "gn:asciiname":"Ongon",
    "gn:country_code":"MM",
    "gn:dem":17,
    "gn:feature_class":"P",
    "gn:feature_code":"PPL",
    "gn:name":"Ongon",
    "gn:population":0,
    "gn:timezone":"Asia/Yangon",
    "iso:country":"MM",
    "name:azb_x_preferred":[
        "\u0627\u0648\u0652\u0646\u0642\u0648\u0646"
    ],
    "name:aze_x_preferred":[
        "Onqon"
    ],
    "name:bak_x_preferred":[
        "\u041e\u043d\u0433\u043e\u043d"
    ],
    "name:fra_x_preferred":[
        "Ongon"
    ],
    "name:rus_x_preferred":[
        "\u041e\u043d\u0433\u043e\u043d"
    ],
    "name:tur_x_preferred":[
        "Ongun"
    ],
    "wof:name":"Ongon",
    "wof:placetype":"locality"
},
  "geometry": {"coordinates":[95.49532000000001,17.7705],"type":"Point"}
}