{
  "type": "Feature",
  "properties": {
    "gn:admin1_code":"11.0",
    "gn:admin2_code":"MMR014D002",
    "gn:admin3_code":"MMR014016",
    "gn:asciiname":"Pa-mawng",
    "gn:country_code":"MM",
    "gn:dem":742,
    "gn:feature_class":"P",
    "gn:feature_code":"PPL",
    "gn:name":"Pa-mawng",
    "gn:population":0,
    "gn:timezone":"Asia/Yangon",
    "iso:country":"MM",
    "name:und_x_variant":[
        "Pa-mawn",
        "Pa-mawng"
    ],
    "wof:name":"Pa-mawng",
    "wof:placetype":"locality"
},
  "geometry": {"coordinates":[97.48568,21.90158],"type":"Point"}
}