{
  "type": "Feature",
  "properties": {
    "gn:admin1_code":"11.0",
    "gn:admin2_code":"MMR014D002",
    "gn:admin3_code":"MMR014013",
    "gn:asciiname":"Wan Kenghkam",
    "gn:country_code":"MM",
    "gn:dem":821,
    "gn:feature_class":"P",
    "gn:feature_code":"PPL",
    "gn:name":"W\u0101n K\u0113nghkam",
    "gn:population":0,
    "gn:timezone":"Asia/Yangon",
    "iso:country":"MM",
    "name:und_x_variant":[
        "K\u0113nghkam",
        "W\u0101n K\u0113nghkam"
    ],
    "wof:name":"Wan Kenghkam",
    "wof:placetype":"locality"
},
  "geometry": {"coordinates":[98.11790000000001,20.85629],"type":"Point"}
}