{
  "type": "Feature",
  "properties": {
    "gn:admin1_code":"11.0",
    "gn:admin2_code":"MMR014D002",
    "gn:admin3_code":"MMR014016",
    "gn:asciiname":"Wan Kenghkam",
    "gn:country_code":"MM",
    "gn:dem":799,
    "gn:feature_class":"P",
    "gn:feature_code":"PPL",
    "gn:name":"W\u0101n Kenghkam",
    "gn:population":0,
    "gn:timezone":"Asia/Yangon",
    "iso:country":"MM",
    "name:und_x_variant":[
        "W\u0101n Kengkam",
        "W\u0101n Kenghkam"
    ],
    "wof:name":"Wan Kenghkam",
    "wof:placetype":"locality"
},
  "geometry": {"coordinates":[97.37005000000001,21.86084],"type":"Point"}
}