{
  "type": "Feature",
  "properties": {
    "gn:admin1_code":"10.0",
    "gn:admin2_code":"MMR005D008",
    "gn:admin3_code":"MMR005033",
    "gn:asciiname":"Ngalang Ga",
    "gn:country_code":"MM",
    "gn:dem":357,
    "gn:feature_class":"P",
    "gn:feature_code":"PPL",
    "gn:name":"Ng\u0101lang Ga",
    "gn:population":0,
    "gn:timezone":"Asia/Yangon",
    "iso:country":"MM",
    "name:und_x_variant":[
        "Ng\u0101lang Ga"
    ],
    "wof:name":"Ngalang Ga",
    "wof:placetype":"locality"
},
  "geometry": {"coordinates":[95.95341000000001,26.33446],"type":"Point"}
}