{
  "type": "Feature",
  "properties": {
    "gn:admin1_code":"10.0",
    "gn:admin2_code":"MMR005D004",
    "gn:admin3_code":"MMR005020",
    "gn:asciiname":"Mahe",
    "gn:country_code":"MM",
    "gn:dem":168,
    "gn:feature_class":"P",
    "gn:feature_code":"PPL",
    "gn:name":"Mah\u0113",
    "gn:population":0,
    "gn:timezone":"Asia/Yangon",
    "iso:country":"MM",
    "name:cat_x_preferred":[
        "Mahe"
    ],
    "name:ceb_x_preferred":[
        "Mahe"
    ],
    "name:dan_x_preferred":[
        "Mahe"
    ],
    "name:deu_x_preferred":[
        "Mahe"
    ],
    "name:ita_x_preferred":[
        "Mahe"
    ],
    "name:mal_x_preferred":[
        "\u0d2e\u0d3e\u0d39\u0d3f"
    ],
    "name:rus_x_preferred":[
        "\u041c\u0430\u044d"
    ],
    "name:spa_x_preferred":[
        "Mahe"
    ],
    "name:ukr_x_preferred":[
        "\u041c\u0430\u0435"
    ],
    "wof:name":"Mahe",
    "wof:placetype":"locality"
},
  "geometry": {"coordinates":[96.3946,24.38229],"type":"Point"}
}