{
  "type": "Feature",
  "properties": {
    "gn:admin1_code":"15.0",
    "gn:admin2_code":"MMR009D001",
    "gn:admin3_code":"MMR009001",
    "gn:asciiname":"Asasan",
    "gn:country_code":"MM",
    "gn:dem":181,
    "gn:feature_class":"P",
    "gn:feature_code":"PPL",
    "gn:name":"Asasan",
    "gn:population":0,
    "gn:timezone":"Asia/Yangon",
    "iso:country":"MM",
    "wof:name":"Asasan",
    "wof:placetype":"locality"
},
  "geometry": {"coordinates":[95.28715,19.96484],"type":"Point"}
}