{
  "type": "Feature",
  "properties": {
    "gn:admin1_code":"11.0",
    "gn:admin2_code":"MMR014D003",
    "gn:admin3_code":"MMR014020",
    "gn:asciiname":"Luenghsa-ye",
    "gn:country_code":"MM",
    "gn:dem":1310,
    "gn:feature_class":"P",
    "gn:feature_code":"PPL",
    "gn:name":"L\u00fcnghsa-ye",
    "gn:population":0,
    "gn:timezone":"Asia/Yangon",
    "iso:country":"MM",
    "wof:name":"Luenghsa-ye",
    "wof:placetype":"locality"
},
  "geometry": {"coordinates":[97.53019999999999,20.00392],"type":"Point"}
}