{
  "type": "Feature",
  "properties": {
    "gn:admin1_code":"12.0",
    "gn:admin2_code":"MMR006D001",
    "gn:admin3_code":"MMR006003",
    "gn:asciiname":"Pe",
    "gn:country_code":"MM",
    "gn:dem":57,
    "gn:feature_class":"P",
    "gn:feature_code":"PPL",
    "gn:name":"Pe",
    "gn:population":0,
    "gn:timezone":"Asia/Yangon",
    "iso:country":"MM",
    "name:ceb_x_preferred":[
        "Pe"
    ],
    "name:por_x_preferred":[
        "P\u00e9"
    ],
    "name:swe_x_preferred":[
        "Pe"
    ],
    "wof:name":"Pe",
    "wof:placetype":"locality"
},
  "geometry": {"coordinates":[98.58597,13.54183],"type":"Point"}
}