{
  "type": "Feature",
  "properties": {
    "gn:admin1_code":"11.0",
    "gn:admin2_code":"MMR014D003",
    "gn:admin3_code":"MMR014020",
    "gn:asciiname":"Ngo-yeng",
    "gn:country_code":"MM",
    "gn:dem":1290,
    "gn:feature_class":"P",
    "gn:feature_code":"PPL",
    "gn:name":"Ngo-yeng",
    "gn:population":0,
    "gn:timezone":"Asia/Yangon",
    "iso:country":"MM",
    "wof:name":"Ngo-yeng",
    "wof:placetype":"locality"
},
  "geometry": {"coordinates":[97.49939000000001,20.2018],"type":"Point"}
}