{
  "type": "Feature",
  "properties": {
    "gn:admin1_code":"3.0",
    "gn:admin2_code":"MMR017D006",
    "gn:admin3_code":"MMR017026",
    "gn:asciiname":"Mayan",
    "gn:country_code":"MM",
    "gn:dem":10,
    "gn:feature_class":"P",
    "gn:feature_code":"PPL",
    "gn:name":"Mayan",
    "gn:population":0,
    "gn:timezone":"Asia/Yangon",
    "iso:country":"MM",
    "name:ceb_x_preferred":[
        "Mayan"
    ],
    "name:deu_x_preferred":[
        "Mayan"
    ],
    "name:swe_x_preferred":[
        "Mayan"
    ],
    "wof:name":"Mayan",
    "wof:placetype":"locality"
},
  "geometry": {"coordinates":[95.99539,16.25841],"type":"Point"}
}