{
  "type": "Feature",
  "properties": {
    "gn:admin1_code":"10.0",
    "gn:admin2_code":"MMR005D004",
    "gn:admin3_code":"MMR005021",
    "gn:asciiname":"Pintin",
    "gn:country_code":"MM",
    "gn:dem":242,
    "gn:feature_class":"P",
    "gn:feature_code":"PPL",
    "gn:name":"Pintin",
    "gn:population":0,
    "gn:timezone":"Asia/Yangon",
    "iso:country":"MM",
    "wof:name":"Pintin",
    "wof:placetype":"locality"
},
  "geometry": {"coordinates":[96.2004,24.29714],"type":"Point"}
}