{
  "type": "Feature",
  "properties": {
    "gn:admin1_code":"4.0",
    "gn:admin2_code":"MMR001D002",
    "gn:admin3_code":"MMR001008",
    "gn:asciiname":"Warawkawng",
    "gn:country_code":"MM",
    "gn:dem":719,
    "gn:feature_class":"P",
    "gn:feature_code":"PPL",
    "gn:name":"Warawkawng",
    "gn:population":0,
    "gn:timezone":"Asia/Yangon",
    "iso:country":"MM",
    "wof:name":"Warawkawng",
    "wof:placetype":"locality"
},
  "geometry": {"coordinates":[96.70773,25.35322],"type":"Point"}
}