{
  "type": "Feature",
  "properties": {
    "gn:admin1_code":"11.0",
    "gn:admin2_code":"MMR015D007",
    "gn:admin3_code":"MMR015024",
    "gn:asciiname":"Man Yawngkomnoe",
    "gn:country_code":"MM",
    "gn:dem":1371,
    "gn:feature_class":"P",
    "gn:feature_code":"PPL",
    "gn:name":"M\u0101n Yawngkomn\u00f6",
    "gn:population":0,
    "gn:timezone":"Asia/Yangon",
    "iso:country":"MM",
    "wof:name":"Man Yawngkomnoe",
    "wof:placetype":"locality"
},
  "geometry": {"coordinates":[98.98924,22.09416],"type":"Point"}
}