{
  "type": "Feature",
  "properties": {
    "gn:admin1_code":"15.0",
    "gn:admin2_code":"MMR009D004",
    "gn:admin3_code":"MMR009019",
    "gn:asciiname":"Myebyugyin",
    "gn:country_code":"MM",
    "gn:dem":111,
    "gn:feature_class":"P",
    "gn:feature_code":"PPL",
    "gn:name":"Myebyugyin",
    "gn:population":0,
    "gn:timezone":"Asia/Yangon",
    "iso:country":"MM",
    "wof:name":"Myebyugyin",
    "wof:placetype":"locality"
},
  "geometry": {"coordinates":[95.13236000000001,21.67636],"type":"Point"}
}