{
  "type": "Feature",
  "properties": {
    "gn:admin1_code":"5.0",
    "gn:admin2_code":"MMR003D001",
    "gn:admin3_code":"MMR003002",
    "gn:asciiname":"Kanni",
    "gn:country_code":"MM",
    "gn:dem":23,
    "gn:feature_class":"P",
    "gn:feature_code":"PPL",
    "gn:name":"Kanni",
    "gn:population":0,
    "gn:timezone":"Asia/Yangon",
    "iso:country":"MM",
    "name:fin_x_preferred":[
        "Kanni"
    ],
    "name:jpn_x_preferred":[
        "\u30ab\u30f3\u30a4"
    ],
    "name:mal_x_preferred":[
        "\u0d15\u0d28\u0d4d\u0d28\u0d3f"
    ],
    "name:msa_x_preferred":[
        "Kanni"
    ],
    "name:nor_x_preferred":[
        "Kanni"
    ],
    "name:tam_x_preferred":[
        "\u0b95\u0ba9\u0bcd\u0ba9\u0bbf \u0ba8\u0bbe\u0baf\u0bcd"
    ],
    "name:tcy_x_preferred":[
        "\u0c95\u0ca3\u0ccd\u0ca3\u0cbf"
    ],
    "name:vie_x_preferred":[
        "Ch\u00f3 Kanni"
    ],
    "wof:name":"Kanni",
    "wof:placetype":"locality"
},
  "geometry": {"coordinates":[97.66757,17.18582],"type":"Point"}
}