{
  "type": "Feature",
  "properties": {
    "gn:admin1_code":"5.0",
    "gn:admin2_code":"MMR003D001",
    "gn:admin3_code":"MMR003002",
    "gn:asciiname":"Kanni",
    "gn:country_code":"MM",
    "gn:dem":23,
    "gn:feature_class":"P",
    "gn:feature_code":"PPL",
    "gn:name":"Kanni",
    "gn:population":0,
    "gn:timezone":"Asia/Yangon",
    "iso:country":"MM",
    "wof:name":"Kanni",
    "wof:placetype":"locality"
},
  "geometry": {"coordinates":[97.66757,17.18582],"type":"Point"}
}