{
  "type": "Feature",
  "properties": {
    "gn:admin1_code":"3.0",
    "gn:admin2_code":"MMR017D006",
    "gn:admin3_code":"MMR017023",
    "gn:asciiname":"Daminzeik",
    "gn:country_code":"MM",
    "gn:dem":3,
    "gn:feature_class":"P",
    "gn:feature_code":"PPL",
    "gn:name":"Daminzeik",
    "gn:population":0,
    "gn:timezone":"Asia/Yangon",
    "iso:country":"MM",
    "wof:name":"Daminzeik",
    "wof:placetype":"locality"
},
  "geometry": {"coordinates":[95.72602999999999,16.14292],"type":"Point"}
}