{
  "type": "Feature",
  "properties": {
    "gn:admin1_code":"15.0",
    "gn:admin2_code":"MMR009D001",
    "gn:admin3_code":"MMR009006",
    "gn:asciiname":"Sele",
    "gn:country_code":"MM",
    "gn:dem":354,
    "gn:feature_class":"P",
    "gn:feature_code":"PPL",
    "gn:name":"Sele",
    "gn:population":0,
    "gn:timezone":"Asia/Yangon",
    "iso:country":"MM",
    "name:bos_x_preferred":[
        "Sele"
    ],
    "name:ceb_x_preferred":[
        "Sele"
    ],
    "name:dan_x_preferred":[
        "Sele"
    ],
    "name:deu_x_preferred":[
        "Sele"
    ],
    "name:hrv_x_preferred":[
        "Sele"
    ],
    "name:nld_x_preferred":[
        "Sele"
    ],
    "name:nor_x_preferred":[
        "Sele"
    ],
    "name:pms_x_preferred":[
        "Sele"
    ],
    "name:pol_x_preferred":[
        "Sele"
    ],
    "name:rus_x_preferred":[
        "\u0421\u0435\u043b\u0435"
    ],
    "name:slv_x_preferred":[
        "Sele"
    ],
    "name:srp_x_preferred":[
        "\u0421\u0435\u043b\u0435"
    ],
    "name:swe_x_preferred":[
        "Sele"
    ],
    "wof:name":"Sele",
    "wof:placetype":"locality"
},
  "geometry": {"coordinates":[95.71322000000001,20.41011],"type":"Point"}
}