{
  "type": "Feature",
  "properties": {
    "gn:admin1_code":"13.0",
    "gn:admin2_code":"MMR011D001",
    "gn:admin3_code":"MMR011006",
    "gn:asciiname":"Chaunghnakwa",
    "gn:country_code":"MM",
    "gn:dem":41,
    "gn:feature_class":"P",
    "gn:feature_code":"PPL",
    "gn:name":"Chaunghnakwa",
    "gn:population":0,
    "gn:timezone":"Asia/Yangon",
    "iso:country":"MM",
    "wof:name":"Chaunghnakwa",
    "wof:placetype":"locality"
},
  "geometry": {"coordinates":[97.91909,15.44491],"type":"Point"}
}