{
  "type": "Feature",
  "properties": {
    "gn:admin1_code":"17.0",
    "gn:admin2_code":"MMR013D004",
    "gn:admin3_code":"MMR013041",
    "gn:asciiname":"Kungyan",
    "gn:country_code":"MM",
    "gn:dem":10,
    "gn:feature_class":"P",
    "gn:feature_code":"PPL",
    "gn:name":"Kungyan",
    "gn:population":0,
    "gn:timezone":"Asia/Yangon",
    "iso:country":"MM",
    "wof:name":"Kungyan",
    "wof:placetype":"locality"
},
  "geometry": {"coordinates":[96.12130999999999,16.8234],"type":"Point"}
}