{
  "type": "Feature",
  "properties": {
    "gn:admin1_code":"11.0",
    "gn:admin2_code":"MMR015D003",
    "gn:admin3_code":"MMR015016",
    "gn:asciiname":"Kyaukhpyu",
    "gn:country_code":"MM",
    "gn:dem":1347,
    "gn:feature_class":"P",
    "gn:feature_code":"PPL",
    "gn:name":"Kyaukhpyu",
    "gn:population":0,
    "gn:timezone":"Asia/Yangon",
    "iso:country":"MM",
    "wof:name":"Kyaukhpyu",
    "wof:placetype":"locality"
},
  "geometry": {"coordinates":[97.15441,22.93992],"type":"Point"}
}