{
  "type": "Feature",
  "properties": {
    "gn:admin1_code":"15.0",
    "gn:admin2_code":"MMR009D001",
    "gn:admin3_code":"MMR009004",
    "gn:asciiname":"Pindaing",
    "gn:country_code":"MM",
    "gn:dem":177,
    "gn:feature_class":"P",
    "gn:feature_code":"PPL",
    "gn:name":"Pindaing",
    "gn:population":0,
    "gn:timezone":"Asia/Yangon",
    "iso:country":"MM",
    "wof:name":"Pindaing",
    "wof:placetype":"locality"
},
  "geometry": {"coordinates":[95.60836,19.92953],"type":"Point"}
}