{
  "type": "Feature",
  "properties": {
    "gn:admin1_code":"15.0",
    "gn:admin2_code":"MMR009D001",
    "gn:admin3_code":"MMR009005",
    "gn:asciiname":"Sudatgyi",
    "gn:country_code":"MM",
    "gn:dem":144,
    "gn:feature_class":"P",
    "gn:feature_code":"PPL",
    "gn:name":"Sudatgyi",
    "gn:population":0,
    "gn:timezone":"Asia/Yangon",
    "iso:country":"MM",
    "name:und_x_variant":[
        "Sudatkyi",
        "Sudatgyi"
    ],
    "wof:name":"Sudatgyi",
    "wof:placetype":"locality"
},
  "geometry": {"coordinates":[95.51861,20.12951],"type":"Point"}
}