{
  "type": "Feature",
  "properties": {
    "gn:admin1_code":"1.0",
    "gn:admin2_code":"MMR012D004",
    "gn:admin3_code":"MMR012016",
    "gn:asciiname":"Khaunglaungdu",
    "gn:country_code":"MM",
    "gn:dem":2,
    "gn:feature_class":"P",
    "gn:feature_code":"PPL",
    "gn:name":"Khaunglaungdu",
    "gn:population":0,
    "gn:timezone":"Asia/Yangon",
    "iso:country":"MM",
    "wof:name":"Khaunglaungdu",
    "wof:placetype":"locality"
},
  "geometry": {"coordinates":[94.17585,18.79202],"type":"Point"}
}