{
  "type": "Feature",
  "properties": {
    "gn:admin1_code":"11.0",
    "gn:admin2_code":"MMR014D002",
    "gn:admin3_code":"MMR014015",
    "gn:asciiname":"Hkawkwo",
    "gn:country_code":"MM",
    "gn:dem":870,
    "gn:feature_class":"P",
    "gn:feature_code":"PPL",
    "gn:name":"Hkawkwo",
    "gn:population":0,
    "gn:timezone":"Asia/Yangon",
    "iso:country":"MM",
    "wof:name":"Hkawkwo",
    "wof:placetype":"locality"
},
  "geometry": {"coordinates":[98.31397,22.11768],"type":"Point"}
}