{
  "type": "Feature",
  "properties": {
    "gn:admin1_code":"12.0",
    "gn:admin2_code":"MMR006D002",
    "gn:admin3_code":"MMR006008",
    "gn:asciiname":"Salo",
    "gn:country_code":"MM",
    "gn:dem":10,
    "gn:feature_class":"P",
    "gn:feature_code":"PPL",
    "gn:name":"Salo",
    "gn:population":0,
    "gn:timezone":"Asia/Yangon",
    "iso:country":"MM",
    "name:bel_x_preferred":[
        "\u0421\u0430\u043b\u0430"
    ],
    "name:bul_x_preferred":[
        "\u0421\u0430\u043b\u043e"
    ],
    "name:cat_x_preferred":[
        "Salo"
    ],
    "name:ceb_x_preferred":[
        "Salo"
    ],
    "name:ces_x_preferred":[
        "Salo"
    ],
    "name:deu_x_preferred":[
        "Salo"
    ],
    "name:fin_x_preferred":[
        "Salo"
    ],
    "name:fra_x_preferred":[
        "Salo"
    ],
    "name:heb_x_preferred":[
        "\u05e1\u05d0\u05dc\u05d5"
    ],
    "name:hun_x_preferred":[
        "Salo"
    ],
    "name:ind_x_preferred":[
        "Salo"
    ],
    "name:ita_x_preferred":[
        "Salo"
    ],
    "name:lav_x_preferred":[
        "Salo"
    ],
    "name:nld_x_preferred":[
        "Salo"
    ],
    "name:pol_x_preferred":[
        "Salo"
    ],
    "name:rus_x_preferred":[
        "\u0421\u0430\u043b\u043e"
    ],
    "name:sco_x_preferred":[
        "Salo"
    ],
    "name:slk_x_preferred":[
        "Salo"
    ],
    "name:slv_x_preferred":[
        "Salo"
    ],
    "name:spa_x_preferred":[
        "Salo"
    ],
    "name:srp_x_preferred":[
        "\u0421\u0430\u043b\u043e"
    ],
    "name:swe_x_preferred":[
        "Salo"
    ],
    "name:ukr_x_preferred":[
        "\u0421\u0430\u043b\u043e"
    ],
    "wof:name":"Salo",
    "wof:placetype":"locality"
},
  "geometry": {"coordinates":[98.94475,12.1522],"type":"Point"}
}