{
  "type": "Feature",
  "properties": {
    "gn:admin1_code":"12.0",
    "gn:admin2_code":"MMR006D002",
    "gn:admin3_code":"MMR006008",
    "gn:asciiname":"Salo",
    "gn:country_code":"MM",
    "gn:dem":10,
    "gn:feature_class":"P",
    "gn:feature_code":"PPL",
    "gn:name":"Salo",
    "gn:population":0,
    "gn:timezone":"Asia/Yangon",
    "iso:country":"MM",
    "wof:name":"Salo",
    "wof:placetype":"locality"
},
  "geometry": {"coordinates":[98.94475,12.1522],"type":"Point"}
}