{
  "type": "Feature",
  "properties": {
    "gn:admin1_code":"4.0",
    "gn:admin2_code":"MMR001D001",
    "gn:admin3_code":"MMR001004",
    "gn:asciiname":"Ulangkawng",
    "gn:country_code":"MM",
    "gn:dem":792,
    "gn:feature_class":"P",
    "gn:feature_code":"PPL",
    "gn:name":"Ul\u0101ngkawng",
    "gn:population":0,
    "gn:timezone":"Asia/Yangon",
    "iso:country":"MM",
    "wof:name":"Ulangkawng",
    "wof:placetype":"locality"
},
  "geometry": {"coordinates":[97.01486,25.90865],"type":"Point"}
}