{
  "type": "Feature",
  "properties": {
    "gn:admin1_code":"11.0",
    "gn:admin2_code":"MMR015D002",
    "gn:admin3_code":"MMR015011",
    "gn:asciiname":"Man Ke-hkun",
    "gn:country_code":"MM",
    "gn:dem":989,
    "gn:feature_class":"P",
    "gn:feature_code":"PPL",
    "gn:name":"M\u0101n Ke-hk\u016bn",
    "gn:population":0,
    "gn:timezone":"Asia/Yangon",
    "iso:country":"MM",
    "wof:name":"Man Ke-hkun",
    "wof:placetype":"locality"
},
  "geometry": {"coordinates":[98.34387,23.68731],"type":"Point"}
}