{
  "type": "Feature",
  "properties": {
    "gn:admin1_code":"10.0",
    "gn:admin2_code":"MMR005D002",
    "gn:admin3_code":"MMR005011",
    "gn:asciiname":"Me-ogon",
    "gn:country_code":"MM",
    "gn:dem":190,
    "gn:feature_class":"P",
    "gn:feature_code":"PPL",
    "gn:name":"Me-og\u00f4n",
    "gn:population":0,
    "gn:timezone":"Asia/Yangon",
    "iso:country":"MM",
    "name:und_x_variant":[
        "Me-egon",
        "Me-og\u00f4n"
    ],
    "wof:name":"Me-ogon",
    "wof:placetype":"locality"
},
  "geometry": {"coordinates":[95.15416,23.14062],"type":"Point"}
}