{
  "type": "Feature",
  "properties": {
    "gn:admin1_code":"6.0",
    "gn:admin2_code":"MMR002D001",
    "gn:admin3_code":"MMR002004",
    "gn:asciiname":"Wan Hwe-nawbo-le",
    "gn:country_code":"MM",
    "gn:dem":554,
    "gn:feature_class":"P",
    "gn:feature_code":"PPL",
    "gn:name":"W\u0101n Hw\u00e8-nawbo-l\u00e8",
    "gn:population":0,
    "gn:timezone":"Asia/Yangon",
    "iso:country":"MM",
    "wof:name":"Wan Hwe-nawbo-le",
    "wof:placetype":"locality"
},
  "geometry": {"coordinates":[97.73193999999999,19.34569],"type":"Point"}
}