{
  "type": "Feature",
  "properties": {
    "gn:admin1_code":"6.0",
    "gn:admin2_code":"MMR002D001",
    "gn:admin3_code":"MMR002002",
    "gn:asciiname":"Lawsa-hku",
    "gn:country_code":"MM",
    "gn:dem":1247,
    "gn:feature_class":"P",
    "gn:feature_code":"PPL",
    "gn:name":"Lawsa-hku",
    "gn:population":0,
    "gn:timezone":"Asia/Yangon",
    "iso:country":"MM",
    "wof:name":"Lawsa-hku",
    "wof:placetype":"locality"
},
  "geometry": {"coordinates":[97.2589,19.4542],"type":"Point"}
}