{
  "type": "Feature",
  "properties": {
    "gn:admin1_code":"11.0",
    "gn:admin2_code":"MMR014D002",
    "gn:admin3_code":"MMR014016",
    "gn:asciiname":"Weng-leng",
    "gn:country_code":"MM",
    "gn:dem":1044,
    "gn:feature_class":"P",
    "gn:feature_code":"PPL",
    "gn:name":"W\u00e8ng-leng",
    "gn:population":0,
    "gn:timezone":"Asia/Yangon",
    "iso:country":"MM",
    "wof:name":"Weng-leng",
    "wof:placetype":"locality"
},
  "geometry": {"coordinates":[97.53106,21.65991],"type":"Point"}
}