{
  "type": "Feature",
  "properties": {
    "gn:admin1_code":"11.0",
    "gn:admin2_code":"MMR016D001",
    "gn:admin3_code":"MMR016001",
    "gn:asciiname":"Wan Pa-hka",
    "gn:country_code":"MM",
    "gn:dem":1441,
    "gn:feature_class":"P",
    "gn:feature_code":"PPL",
    "gn:name":"W\u0101n P\u0101-hk\u0101",
    "gn:population":0,
    "gn:timezone":"Asia/Yangon",
    "iso:country":"MM",
    "name:und_x_variant":[
        "W\u0101n Kaw P\u0101-hk\u0101",
        "W\u0101n P\u0101-hk\u0101"
    ],
    "wof:name":"Wan Pa-hka",
    "wof:placetype":"locality"
},
  "geometry": {"coordinates":[99.88303000000001,21.25238],"type":"Point"}
}