{
  "type": "Feature",
  "properties": {
    "gn:admin1_code":"11.0",
    "gn:admin2_code":"MMR014D001",
    "gn:admin3_code":"MMR014009",
    "gn:asciiname":"Kyauksit",
    "gn:country_code":"MM",
    "gn:dem":335,
    "gn:feature_class":"P",
    "gn:feature_code":"PPL",
    "gn:name":"Kyauksit",
    "gn:population":0,
    "gn:timezone":"Asia/Yangon",
    "iso:country":"MM",
    "wof:name":"Kyauksit",
    "wof:placetype":"locality"
},
  "geometry": {"coordinates":[96.61913,19.98065],"type":"Point"}
}