{
  "type": "Feature",
  "properties": {
    "gn:admin1_code":"11.0",
    "gn:admin2_code":"MMR014D003",
    "gn:admin3_code":"MMR014020",
    "gn:asciiname":"Mawkmai",
    "gn:country_code":"MM",
    "gn:dem":495,
    "gn:feature_class":"P",
    "gn:feature_code":"PPL",
    "gn:name":"Mawkmai",
    "gn:population":0,
    "gn:timezone":"Asia/Yangon",
    "iso:country":"MM",
    "name:cat_x_preferred":[
        "Mawkmai"
    ],
    "name:lat_x_preferred":[
        "Mawkmai"
    ],
    "name:mya_x_preferred":[
        "\u1019\u1031\u102c\u1000\u103a\u1019\u101a\u103a\u1019\u103c\u102d\u102f\u1037"
    ],
    "name:por_x_preferred":[
        "Mawkmai"
    ],
    "name:shn_x_preferred":[
        "\u1019\u103d\u1075\u103a\u1087\u1019\u1086\u1087\u104a \u101d\u1035\u1004\u103a\u1038"
    ],
    "name:swe_x_preferred":[
        "Mawkmai"
    ],
    "name:und_x_variant":[
        "Hawk Mai",
        "Maukmai",
        "Maukm\u00e8"
    ],
    "wof:name":"Mawkmai",
    "wof:placetype":"locality"
},
  "geometry": {"coordinates":[97.72506,20.22654],"type":"Point"}
}