{
  "type": "Feature",
  "properties": {
    "gn:admin1_code":"4.0",
    "gn:admin2_code":"MMR001D003",
    "gn:admin3_code":"MMR001010",
    "gn:asciiname":"Nawngsai",
    "gn:country_code":"MM",
    "gn:dem":118,
    "gn:feature_class":"P",
    "gn:feature_code":"PPL",
    "gn:name":"Nawngsai",
    "gn:population":0,
    "gn:timezone":"Asia/Yangon",
    "iso:country":"MM",
    "wof:name":"Nawngsai",
    "wof:placetype":"locality"
},
  "geometry": {"coordinates":[97.28579000000001,24.36286],"type":"Point"}
}