{
  "type": "Feature",
  "properties": {
    "gn:admin1_code":"11.0",
    "gn:admin2_code":"MMR015D007",
    "gn:admin3_code":"MMR015024",
    "gn:asciiname":"Man Paklong",
    "gn:country_code":"MM",
    "gn:dem":993,
    "gn:feature_class":"P",
    "gn:feature_code":"PPL",
    "gn:name":"M\u0101n P\u0101kl\u014dng",
    "gn:population":0,
    "gn:timezone":"Asia/Yangon",
    "iso:country":"MM",
    "wof:name":"Man Paklong",
    "wof:placetype":"locality"
},
  "geometry": {"coordinates":[99.03134,21.92948],"type":"Point"}
}