{
  "type": "Feature",
  "properties": {
    "gn:admin1_code":"13.0",
    "gn:admin2_code":"MMR011D002",
    "gn:admin3_code":"MMR011010",
    "gn:asciiname":"Kawthihta",
    "gn:country_code":"MM",
    "gn:dem":39,
    "gn:feature_class":"P",
    "gn:feature_code":"PPL",
    "gn:name":"Kawthihta",
    "gn:population":0,
    "gn:timezone":"Asia/Yangon",
    "iso:country":"MM",
    "name:und_x_variant":[
        "Kawthi",
        "Kawthihta"
    ],
    "wof:name":"Kawthihta",
    "wof:placetype":"locality"
},
  "geometry": {"coordinates":[97.29673,17.42881],"type":"Point"}
}