{
  "type": "Feature",
  "properties": {
    "gn:admin1_code":"17.0",
    "gn:admin2_code":"MMR013D003",
    "gn:admin3_code":"MMR013025",
    "gn:asciiname":"Taman",
    "gn:country_code":"MM",
    "gn:dem":9,
    "gn:feature_class":"P",
    "gn:feature_code":"PPL",
    "gn:name":"Taman",
    "gn:population":0,
    "gn:timezone":"Asia/Yangon",
    "iso:country":"MM",
    "name:ceb_x_preferred":[
        "Taman"
    ],
    "name:deu_x_preferred":[
        "Taman"
    ],
    "name:fra_x_preferred":[
        "Taman"
    ],
    "name:heb_x_preferred":[
        "\u05d8\u05d0\u05de\u05d0\u05df"
    ],
    "name:jpn_x_preferred":[
        "\u30bf\u30de\u30f3"
    ],
    "name:nld_x_preferred":[
        "Taman"
    ],
    "name:nor_x_preferred":[
        "Taman"
    ],
    "name:por_x_preferred":[
        "Taman"
    ],
    "name:swe_x_preferred":[
        "Taman"
    ],
    "name:zho_x_preferred":[
        "Taman"
    ],
    "wof:name":"Taman",
    "wof:placetype":"locality"
},
  "geometry": {"coordinates":[96.77336,16.80458],"type":"Point"}
}