{
  "type": "Feature",
  "properties": {
    "gn:admin1_code":"2.0",
    "gn:admin2_code":"MMR004D002",
    "gn:admin3_code":"MMR004008",
    "gn:asciiname":"Zinchaung",
    "gn:country_code":"MM",
    "gn:dem":1054,
    "gn:feature_class":"P",
    "gn:feature_code":"PPL",
    "gn:name":"Zinchaung",
    "gn:population":0,
    "gn:timezone":"Asia/Yangon",
    "iso:country":"MM",
    "wof:name":"Zinchaung",
    "wof:placetype":"locality"
},
  "geometry": {"coordinates":[94.02226,21.25195],"type":"Point"}
}