{
  "type": "Feature",
  "properties": {
    "gn:admin1_code":"11.0",
    "gn:admin2_code":"MMR014D002",
    "gn:admin3_code":"MMR014011",
    "gn:asciiname":"Wan Mwe-taw",
    "gn:country_code":"MM",
    "gn:dem":1315,
    "gn:feature_class":"P",
    "gn:feature_code":"PPL",
    "gn:name":"Wan Mwe-taw",
    "gn:population":0,
    "gn:timezone":"Asia/Yangon",
    "iso:country":"MM",
    "wof:name":"Wan Mwe-taw",
    "wof:placetype":"locality"
},
  "geometry": {"coordinates":[97.53821000000001,21.00968],"type":"Point"}
}