{
  "type": "Feature",
  "properties": {
    "gn:admin1_code":"12.0",
    "gn:admin2_code":"MMR006D003",
    "gn:admin3_code":"MMR006010",
    "gn:asciiname":"Hengrai",
    "gn:country_code":"MM",
    "gn:dem":9,
    "gn:feature_class":"P",
    "gn:feature_code":"PPL",
    "gn:name":"Hengrai",
    "gn:population":0,
    "gn:timezone":"Asia/Yangon",
    "iso:country":"MM",
    "wof:name":"Hengrai",
    "wof:placetype":"locality"
},
  "geometry": {"coordinates":[98.98860999999999,11.42606],"type":"Point"}
}