{
  "type": "Feature",
  "properties": {
    "gn:admin1_code":"4.0",
    "gn:admin2_code":"MMR001D004",
    "gn:admin3_code":"MMR001014",
    "gn:asciiname":"Paten",
    "gn:country_code":"MM",
    "gn:dem":436,
    "gn:feature_class":"P",
    "gn:feature_code":"PPL",
    "gn:name":"Paten",
    "gn:population":0,
    "gn:timezone":"Asia/Yangon",
    "iso:country":"MM",
    "name:bel_x_preferred":[
        "\u041f\u0430\u0442\u044d\u043d\u0430"
    ],
    "name:cat_x_preferred":[
        "Patena"
    ],
    "name:ces_x_preferred":[
        "Patena"
    ],
    "name:dan_x_preferred":[
        "Disk"
    ],
    "name:deu_x_preferred":[
        "Patene"
    ],
    "name:epo_x_preferred":[
        "Pateno"
    ],
    "name:fin_x_preferred":[
        "Pateeni"
    ],
    "name:fra_x_preferred":[
        "Pat\u00e8ne"
    ],
    "name:ido_x_preferred":[
        "Pateno"
    ],
    "name:ind_x_preferred":[
        "Patena"
    ],
    "name:ita_x_preferred":[
        "Patena"
    ],
    "name:nld_x_preferred":[
        "Pateen"
    ],
    "name:pol_x_preferred":[
        "Patena"
    ],
    "name:por_x_preferred":[
        "Patena"
    ],
    "name:rus_x_preferred":[
        "\u041f\u0430\u0442\u0435\u043d\u0430"
    ],
    "name:slk_x_preferred":[
        "Pat\u00e9na"
    ],
    "name:slv_x_preferred":[
        "Patena"
    ],
    "name:spa_x_preferred":[
        "Patena"
    ],
    "name:swa_x_preferred":[
        "Patena"
    ],
    "name:swe_x_preferred":[
        "Paten"
    ],
    "wof:name":"Paten",
    "wof:placetype":"locality"
},
  "geometry": {"coordinates":[97.40599,27.32506],"type":"Point"}
}