{
  "type": "Feature",
  "properties": {
    "gn:admin1_code":"11.0",
    "gn:admin2_code":"MMR014D002",
    "gn:admin3_code":"MMR014016",
    "gn:asciiname":"Kun-hsan",
    "gn:country_code":"MM",
    "gn:dem":1124,
    "gn:feature_class":"P",
    "gn:feature_code":"PPL",
    "gn:name":"Kun-hsan",
    "gn:population":0,
    "gn:timezone":"Asia/Yangon",
    "iso:country":"MM",
    "wof:name":"Kun-hsan",
    "wof:placetype":"locality"
},
  "geometry": {"coordinates":[97.63026000000001,21.87028],"type":"Point"}
}