{
  "type": "Feature",
  "properties": {
    "gn:admin1_code":"11.0",
    "gn:admin2_code":"MMR015D001",
    "gn:admin3_code":"MMR015001",
    "gn:asciiname":"Ho-na",
    "gn:country_code":"MM",
    "gn:dem":788,
    "gn:feature_class":"P",
    "gn:feature_code":"PPL",
    "gn:name":"Ho-n\u0101",
    "gn:population":0,
    "gn:timezone":"Asia/Yangon",
    "iso:country":"MM",
    "name:und_x_variant":[
        "Nayama",
        "Ho-n\u0101"
    ],
    "wof:name":"Ho-na",
    "wof:placetype":"locality"
},
  "geometry": {"coordinates":[97.65392,22.79534],"type":"Point"}
}