{
  "type": "Feature",
  "properties": {
    "gn:admin1_code":"4.0",
    "gn:admin2_code":"MMR001D001",
    "gn:admin3_code":"MMR001004",
    "gn:asciiname":"Ganoi Ga",
    "gn:country_code":"MM",
    "gn:dem":244,
    "gn:feature_class":"P",
    "gn:feature_code":"PPL",
    "gn:name":"Ganoi Ga",
    "gn:population":0,
    "gn:timezone":"Asia/Yangon",
    "iso:country":"MM",
    "wof:name":"Ganoi Ga",
    "wof:placetype":"locality"
},
  "geometry": {"coordinates":[96.89634,26.3078],"type":"Point"}
}