{
  "type": "Feature",
  "properties": {
    "gn:admin1_code":"15.0",
    "gn:admin2_code":"MMR009D002",
    "gn:admin3_code":"MMR009010",
    "gn:asciiname":"Paukchon",
    "gn:country_code":"MM",
    "gn:dem":167,
    "gn:feature_class":"P",
    "gn:feature_code":"PPL",
    "gn:name":"Paukch\u00f4n",
    "gn:population":0,
    "gn:timezone":"Asia/Yangon",
    "iso:country":"MM",
    "wof:name":"Paukchon",
    "wof:placetype":"locality"
},
  "geometry": {"coordinates":[94.39915000000001,20.8596],"type":"Point"}
}