{
  "type": "Feature",
  "properties": {
    "gn:admin1_code":"15.0",
    "gn:admin2_code":"MMR009D002",
    "gn:admin3_code":"MMR009007",
    "gn:asciiname":"Alanbe",
    "gn:country_code":"MM",
    "gn:dem":53,
    "gn:feature_class":"P",
    "gn:feature_code":"PPL",
    "gn:name":"Alanbe",
    "gn:population":0,
    "gn:timezone":"Asia/Yangon",
    "iso:country":"MM",
    "name:fas_x_preferred":[
        "\u0627\u0644\u0627\u0646\u0628\u06cc"
    ],
    "wof:name":"Alanbe",
    "wof:placetype":"locality"
},
  "geometry": {"coordinates":[94.83268,20.24316],"type":"Point"}
}