{
  "type": "Feature",
  "properties": {
    "gn:admin1_code":"11.0",
    "gn:admin2_code":"MMR015D001",
    "gn:admin3_code":"MMR015001",
    "gn:asciiname":"Kawnghka",
    "gn:country_code":"MM",
    "gn:dem":1500,
    "gn:feature_class":"P",
    "gn:feature_code":"PPL",
    "gn:name":"Kawnghka",
    "gn:population":0,
    "gn:timezone":"Asia/Yangon",
    "iso:country":"MM",
    "name:mya_x_preferred":[
        "\u1000\u1031\u102c\u1004\u103a\u1038\u1001\u102b\u1038\u101b\u103d\u102c"
    ],
    "wof:name":"Kawnghka",
    "wof:placetype":"locality"
},
  "geometry": {"coordinates":[98.21756000000001,23.04599],"type":"Point"}
}