{
  "type": "Feature",
  "properties": {
    "gn:admin1_code":"8.0",
    "gn:admin2_code":"MMR010D007",
    "gn:admin3_code":"MMR010030",
    "gn:asciiname":"Bondalok",
    "gn:country_code":"MM",
    "gn:dem":182,
    "gn:feature_class":"P",
    "gn:feature_code":"PPL",
    "gn:name":"Bondalok",
    "gn:population":0,
    "gn:timezone":"Asia/Yangon",
    "iso:country":"MM",
    "wof:name":"Bondalok",
    "wof:placetype":"locality"
},
  "geometry": {"coordinates":[96.03788,20.7241],"type":"Point"}
}