{
  "type": "Feature",
  "properties": {
    "gn:admin1_code":"11.0",
    "gn:admin2_code":"MMR014D003",
    "gn:admin3_code":"MMR014020",
    "gn:asciiname":"Wan Hpai-mai",
    "gn:country_code":"MM",
    "gn:dem":1209,
    "gn:feature_class":"P",
    "gn:feature_code":"PPL",
    "gn:name":"W\u0101n Hpai-mai",
    "gn:population":0,
    "gn:timezone":"Asia/Yangon",
    "iso:country":"MM",
    "wof:name":"Wan Hpai-mai",
    "wof:placetype":"locality"
},
  "geometry": {"coordinates":[97.45971,20.02315],"type":"Point"}
}