{
  "type": "Feature",
  "properties": {
    "gn:admin1_code":"17.0",
    "gn:admin2_code":"MMR013D004",
    "gn:admin3_code":"MMR013042",
    "gn:asciiname":"Kyaukkala",
    "gn:country_code":"MM",
    "gn:dem":14,
    "gn:feature_class":"P",
    "gn:feature_code":"PPL",
    "gn:name":"Kyaukkala",
    "gn:population":0,
    "gn:timezone":"Asia/Yangon",
    "iso:country":"MM",
    "wof:name":"Kyaukkala",
    "wof:placetype":"locality"
},
  "geometry": {"coordinates":[96.12423,16.87264],"type":"Point"}
}