{
  "type": "Feature",
  "properties": {
    "gn:admin1_code":"4.0",
    "gn:admin2_code":"MMR001D003",
    "gn:admin3_code":"MMR001013",
    "gn:asciiname":"Tunhok",
    "gn:country_code":"MM",
    "gn:dem":1501,
    "gn:feature_class":"P",
    "gn:feature_code":"PPL",
    "gn:name":"Tunhok",
    "gn:population":0,
    "gn:timezone":"Asia/Yangon",
    "iso:country":"MM",
    "name:und_x_variant":[
        "Dunhung",
        "Tunhok"
    ],
    "wof:name":"Tunhok",
    "wof:placetype":"locality"
},
  "geometry": {"coordinates":[97.35957000000001,23.74671],"type":"Point"}
}