{
  "type": "Feature",
  "properties": {
    "gn:admin1_code":"5.0",
    "gn:admin2_code":"MMR003D004",
    "gn:admin3_code":"MMR003003",
    "gn:asciiname":"Winpa",
    "gn:country_code":"MM",
    "gn:dem":72,
    "gn:feature_class":"P",
    "gn:feature_code":"PPL",
    "gn:name":"Winpa",
    "gn:population":0,
    "gn:timezone":"Asia/Yangon",
    "iso:country":"MM",
    "name:und_x_variant":[
        "Wawpa",
        "Winpa"
    ],
    "wof:name":"Winpa",
    "wof:placetype":"locality"
},
  "geometry": {"coordinates":[97.44276000000001,17.9542],"type":"Point"}
}