{
  "type": "Feature",
  "properties": {
    "gn:admin1_code":"10.0",
    "gn:admin2_code":"MMR005D001",
    "gn:admin3_code":"MMR005002",
    "gn:asciiname":"Hposandin",
    "gn:country_code":"MM",
    "gn:dem":100,
    "gn:feature_class":"P",
    "gn:feature_code":"PPL",
    "gn:name":"Hposandin",
    "gn:population":0,
    "gn:timezone":"Asia/Yangon",
    "iso:country":"MM",
    "wof:name":"Hposandin",
    "wof:placetype":"locality"
},
  "geometry": {"coordinates":[95.45954,21.9598],"type":"Point"}
}