{
  "type": "Feature",
  "properties": {
    "gn:admin1_code":"4.0",
    "gn:admin2_code":"MMR001D004",
    "gn:admin3_code":"MMR001016",
    "gn:asciiname":"Yangtu",
    "gn:country_code":"MM",
    "gn:dem":1256,
    "gn:feature_class":"P",
    "gn:feature_code":"PPL",
    "gn:name":"Yangtu",
    "gn:population":0,
    "gn:timezone":"Asia/Yangon",
    "iso:country":"MM",
    "wof:name":"Yangtu",
    "wof:placetype":"locality"
},
  "geometry": {"coordinates":[97.85235,26.96278],"type":"Point"}
}