{
  "type": "Feature",
  "properties": {
    "gn:admin1_code":"10.0",
    "gn:admin2_code":"MMR005D005",
    "gn:admin3_code":"MMR005027",
    "gn:asciiname":"Sihaung Myauk",
    "gn:country_code":"MM",
    "gn:dem":143,
    "gn:feature_class":"P",
    "gn:feature_code":"PPL",
    "gn:name":"Sihaung Myauk",
    "gn:population":0,
    "gn:timezone":"Asia/Yangon",
    "iso:country":"MM",
    "name:und_x_variant":[
        "Sihaung",
        "Sinaung Myauk",
        "Sihaung Myauk"
    ],
    "wof:name":"Sihaung Myauk",
    "wof:placetype":"locality"
},
  "geometry": {"coordinates":[94.05492,22.86413],"type":"Point"}
}