{
  "type": "Feature",
  "properties": {
    "gn:admin1_code":"11.0",
    "gn:admin2_code":"MMR016D003",
    "gn:admin3_code":"MMR016009",
    "gn:asciiname":"Wan Pa-kok",
    "gn:country_code":"MM",
    "gn:dem":377,
    "gn:feature_class":"P",
    "gn:feature_code":"PPL",
    "gn:name":"W\u0101n Pa-k\u014dk",
    "gn:population":0,
    "gn:timezone":"Asia/Yangon",
    "iso:country":"MM",
    "name:und_x_variant":[
        "Pa-kok",
        "Y\u00f6n",
        "W\u0101n Pa-k\u014dk"
    ],
    "wof:name":"Wan Pa-kok",
    "wof:placetype":"locality"
},
  "geometry": {"coordinates":[100.02115000000001,20.41697000000001],"type":"Point"}
}