{
  "type": "Feature",
  "properties": {
    "gn:admin1_code":"1.0",
    "gn:admin2_code":"MMR012D003",
    "gn:admin3_code":"MMR012014",
    "gn:asciiname":"Auk Pho",
    "gn:country_code":"MM",
    "gn:dem":210,
    "gn:feature_class":"P",
    "gn:feature_code":"PPL",
    "gn:name":"Auk Pho",
    "gn:population":0,
    "gn:timezone":"Asia/Yangon",
    "iso:country":"MM",
    "wof:name":"Auk Pho",
    "wof:placetype":"locality"
},
  "geometry": {"coordinates":[93.87443,20.38184],"type":"Point"}
}