{
  "type": "Feature",
  "properties": {
    "gn:admin1_code":"4.0",
    "gn:admin2_code":"MMR001D004",
    "gn:admin3_code":"MMR001018",
    "gn:asciiname":"Tapu",
    "gn:country_code":"MM",
    "gn:dem":1203,
    "gn:feature_class":"P",
    "gn:feature_code":"PPL",
    "gn:name":"Tapu",
    "gn:population":0,
    "gn:timezone":"Asia/Yangon",
    "iso:country":"MM",
    "name:deu_x_preferred":[
        "Tapu"
    ],
    "wof:name":"Tapu",
    "wof:placetype":"locality"
},
  "geometry": {"coordinates":[98.36125,26.89532],"type":"Point"}
}