{
  "type": "Feature",
  "properties": {
    "gn:admin1_code":"6.0",
    "gn:admin2_code":"MMR002D001",
    "gn:admin3_code":"MMR002004",
    "gn:asciiname":"Daw Hsa-le",
    "gn:country_code":"MM",
    "gn:dem":862,
    "gn:feature_class":"P",
    "gn:feature_code":"PPL",
    "gn:name":"Daw Hsa-l\u00e8",
    "gn:population":0,
    "gn:timezone":"Asia/Yangon",
    "iso:country":"MM",
    "wof:name":"Daw Hsa-le",
    "wof:placetype":"locality"
},
  "geometry": {"coordinates":[97.55222000000001,19.44083],"type":"Point"}
}