{
  "type": "Feature",
  "properties": {
    "gn:admin1_code":"4.0",
    "gn:admin2_code":"MMR001D002",
    "gn:admin3_code":"MMR001007",
    "gn:asciiname":"Manlao",
    "gn:country_code":"MM",
    "gn:dem":220,
    "gn:feature_class":"P",
    "gn:feature_code":"PPL",
    "gn:name":"Manlao",
    "gn:population":0,
    "gn:timezone":"Asia/Yangon",
    "iso:country":"MM",
    "wof:name":"Manlao",
    "wof:placetype":"locality"
},
  "geometry": {"coordinates":[96.33368,25.29364],"type":"Point"}
}