{
  "type": "Feature",
  "properties": {
    "gn:admin1_code":"3.0",
    "gn:admin2_code":"MMR017D003",
    "gn:admin3_code":"MMR017017",
    "gn:asciiname":"Kunthigyaunggale",
    "gn:country_code":"MM",
    "gn:dem":10,
    "gn:feature_class":"P",
    "gn:feature_code":"PPL",
    "gn:name":"Kunthigyaunggale",
    "gn:population":0,
    "gn:timezone":"Asia/Yangon",
    "iso:country":"MM",
    "name:und_x_variant":[
        "Kunthigyaung",
        "Kunthigyaunggale"
    ],
    "wof:name":"Kunthigyaunggale",
    "wof:placetype":"locality"
},
  "geometry": {"coordinates":[95.14758,16.38923],"type":"Point"}
}