{
  "type": "Feature",
  "properties": {
    "gn:admin1_code":"11.0",
    "gn:admin2_code":"MMR014D003",
    "gn:admin3_code":"MMR014018",
    "gn:asciiname":"Wan Loi-lan",
    "gn:country_code":"MM",
    "gn:dem":1416,
    "gn:feature_class":"P",
    "gn:feature_code":"PPL",
    "gn:name":"W\u0101n Loi-lan",
    "gn:population":0,
    "gn:timezone":"Asia/Yangon",
    "iso:country":"MM",
    "wof:name":"Wan Loi-lan",
    "wof:placetype":"locality"
},
  "geometry": {"coordinates":[97.84899,19.65603],"type":"Point"}
}