{
  "type": "Feature",
  "properties": {
    "gn:admin1_code":"4.0",
    "gn:admin2_code":"MMR001D001",
    "gn:admin3_code":"MMR001004",
    "gn:asciiname":"Wangkawng",
    "gn:country_code":"MM",
    "gn:dem":765,
    "gn:feature_class":"P",
    "gn:feature_code":"PPL",
    "gn:name":"W\u0101ngkawng",
    "gn:population":0,
    "gn:timezone":"Asia/Yangon",
    "iso:country":"MM",
    "name:und_x_variant":[
        "Waugkawng",
        "W\u0101ngkawng"
    ],
    "wof:name":"Wangkawng",
    "wof:placetype":"locality"
},
  "geometry": {"coordinates":[97.00615000000001,25.92544],"type":"Point"}
}