{
  "type": "Feature",
  "properties": {
    "gn:admin1_code":"11.0",
    "gn:admin2_code":"MMR014D002",
    "gn:admin3_code":"MMR014014",
    "gn:asciiname":"Wan Kawngmung",
    "gn:country_code":"MM",
    "gn:dem":791,
    "gn:feature_class":"P",
    "gn:feature_code":"PPL",
    "gn:name":"W\u0101n Kawngm\u016bng",
    "gn:population":0,
    "gn:timezone":"Asia/Yangon",
    "iso:country":"MM",
    "name:und_x_variant":[
        "W\u0101n Kongmog",
        "W\u0101n Kongmong",
        "W\u0101n Kawngm\u016bng"
    ],
    "wof:name":"Wan Kawngmung",
    "wof:placetype":"locality"
},
  "geometry": {"coordinates":[98.59463,21.23878],"type":"Point"}
}