{
  "type": "Feature",
  "properties": {
    "gn:admin1_code":"16.0",
    "gn:admin2_code":"MMR007D001",
    "gn:admin3_code":"MMR007003",
    "gn:asciiname":"Thanbanseik-kyaungzu",
    "gn:country_code":"MM",
    "gn:dem":8,
    "gn:feature_class":"P",
    "gn:feature_code":"PPL",
    "gn:name":"Thanbanseik-kyaungzu",
    "gn:population":0,
    "gn:timezone":"Asia/Yangon",
    "iso:country":"MM",
    "wof:name":"Thanbanseik-kyaungzu",
    "wof:placetype":"locality"
},
  "geometry": {"coordinates":[96.85997,17.09731],"type":"Point"}
}