{
  "type": "Feature",
  "properties": {
    "gn:admin1_code":"3.0",
    "gn:admin2_code":"MMR017D002",
    "gn:admin3_code":"MMR017010",
    "gn:asciiname":"Mogok",
    "gn:country_code":"MM",
    "gn:dem":17,
    "gn:feature_class":"P",
    "gn:feature_code":"PPL",
    "gn:name":"Mogok",
    "gn:population":0,
    "gn:timezone":"Asia/Yangon",
    "iso:country":"MM",
    "name:cat_x_preferred":[
        "Mogok"
    ],
    "name:ceb_x_preferred":[
        "Mogok"
    ],
    "name:fas_x_preferred":[
        "\u0645\u06af\u06a9"
    ],
    "name:fra_x_preferred":[
        "Mogok"
    ],
    "name:ita_x_preferred":[
        "Mogok"
    ],
    "name:mya_x_preferred":[
        "\u1019\u102d\u102f\u1038\u1000\u102f\u1010\u103a\u1019\u103c\u102d\u102f\u1037"
    ],
    "name:pol_x_preferred":[
        "Mogok"
    ],
    "name:rus_x_preferred":[
        "\u041c\u043e\u0433\u043e\u0443"
    ],
    "name:shn_x_preferred":[
        "\u1019\u102d\u1030\u1004\u103a\u1038\u1075\u102f\u1010\u103a\u1088\u104a \u101d\u1035\u1004\u103a\u1038"
    ],
    "name:swe_x_preferred":[
        "Mogok"
    ],
    "name:tha_x_preferred":[
        "\u0e42\u0e21\u0e48\u0e42\u0e01\u0e30"
    ],
    "name:ukr_x_preferred":[
        "\u041c\u043e\u0433\u043e\u043a"
    ],
    "name:vie_x_preferred":[
        "Mogok"
    ],
    "wof:name":"Mogok",
    "wof:placetype":"locality"
},
  "geometry": {"coordinates":[95.08159999999999,17.56551],"type":"Point"}
}