{
  "type": "Feature",
  "properties": {
    "gn:admin1_code":"11.0",
    "gn:admin2_code":"MMR016D003",
    "gn:admin3_code":"MMR016010",
    "gn:asciiname":"Wan Mu-la-hsi",
    "gn:country_code":"MM",
    "gn:dem":1233,
    "gn:feature_class":"P",
    "gn:feature_code":"PPL",
    "gn:name":"W\u0101n Mu-la-hsi",
    "gn:population":0,
    "gn:timezone":"Asia/Yangon",
    "iso:country":"MM",
    "name:und_x_variant":[
        "Wan Mu-la-hai",
        "W\u0101n Mu-la-hsi"
    ],
    "wof:name":"Wan Mu-la-hsi",
    "wof:placetype":"locality"
},
  "geometry": {"coordinates":[100.13302,20.94903],"type":"Point"}
}