{
  "type": "Feature",
  "properties": {
    "gn:admin1_code":"4.0",
    "gn:admin2_code":"MMR001D001",
    "gn:admin3_code":"MMR001006",
    "gn:asciiname":"Mangchibuk",
    "gn:country_code":"MM",
    "gn:dem":1424,
    "gn:feature_class":"P",
    "gn:feature_code":"PPL",
    "gn:name":"M\u0101ngchibuk",
    "gn:population":0,
    "gn:timezone":"Asia/Yangon",
    "iso:country":"MM",
    "name:und_x_variant":[
        "M\u0101ngchibuk"
    ],
    "wof:name":"Mangchibuk",
    "wof:placetype":"locality"
},
  "geometry": {"coordinates":[98.27314,26.47457],"type":"Point"}
}