{
  "type": "Feature",
  "properties": {
    "gn:admin1_code":"10.0",
    "gn:admin2_code":"MMR005D001",
    "gn:admin3_code":"MMR005001",
    "gn:asciiname":"Ondaw",
    "gn:country_code":"MM",
    "gn:dem":110,
    "gn:feature_class":"P",
    "gn:feature_code":"PPL",
    "gn:name":"Ondaw",
    "gn:population":0,
    "gn:timezone":"Asia/Yangon",
    "iso:country":"MM",
    "name:und_x_variant":[
        "Ondau",
        "Ondaw"
    ],
    "wof:name":"Ondaw",
    "wof:placetype":"locality"
},
  "geometry": {"coordinates":[95.83141999999999,22.00727],"type":"Point"}
}