{
  "type": "Feature",
  "properties": {
    "gn:admin1_code":"11.0",
    "gn:admin2_code":"MMR014D002",
    "gn:admin3_code":"MMR014014",
    "gn:asciiname":"Wan Ho-hkoe",
    "gn:country_code":"MM",
    "gn:dem":634,
    "gn:feature_class":"P",
    "gn:feature_code":"PPL",
    "gn:name":"W\u0101n Ho-hk\u00f6",
    "gn:population":0,
    "gn:timezone":"Asia/Yangon",
    "iso:country":"MM",
    "wof:name":"Wan Ho-hkoe",
    "wof:placetype":"locality"
},
  "geometry": {"coordinates":[98.37264999999999,21.32526],"type":"Point"}
}