{
  "type": "Feature",
  "properties": {
    "gn:admin1_code":"11.0",
    "gn:admin2_code":"MMR016D003",
    "gn:admin3_code":"MMR016009",
    "gn:asciiname":"Pang Hpakkat",
    "gn:country_code":"MM",
    "gn:dem":390,
    "gn:feature_class":"P",
    "gn:feature_code":"PPL",
    "gn:name":"Pang Hpakkat",
    "gn:population":0,
    "gn:timezone":"Asia/Yangon",
    "iso:country":"MM",
    "wof:name":"Pang Hpakkat",
    "wof:placetype":"locality"
},
  "geometry": {"coordinates":[100.05528,20.45417],"type":"Point"}
}