{
  "type": "Feature",
  "properties": {
    "gn:admin1_code":"11.0",
    "gn:admin2_code":"MMR015D008",
    "gn:admin3_code":"MMR015017",
    "gn:asciiname":"Tingri",
    "gn:country_code":"MM",
    "gn:dem":1623,
    "gn:feature_class":"P",
    "gn:feature_code":"PPL",
    "gn:name":"Tingri",
    "gn:population":0,
    "gn:timezone":"Asia/Yangon",
    "iso:country":"MM",
    "name:ita_x_preferred":[
        "Tingri"
    ],
    "name:nld_x_preferred":[
        "Tingri"
    ],
    "wof:name":"Tingri",
    "wof:placetype":"locality"
},
  "geometry": {"coordinates":[96.88054,23.24891],"type":"Point"}
}