{
  "type": "Feature",
  "properties": {
    "gn:admin1_code":"11.0",
    "gn:admin2_code":"MMR015D003",
    "gn:admin3_code":"MMR015014",
    "gn:asciiname":"Na-lawt",
    "gn:country_code":"MM",
    "gn:dem":604,
    "gn:feature_class":"P",
    "gn:feature_code":"PPL",
    "gn:name":"N\u0101-lawt",
    "gn:population":0,
    "gn:timezone":"Asia/Yangon",
    "iso:country":"MM",
    "wof:name":"Na-lawt",
    "wof:placetype":"locality"
},
  "geometry": {"coordinates":[97.80686,22.68032],"type":"Point"}
}