{
  "type": "Feature",
  "properties": {
    "gn:admin1_code":"10.0",
    "gn:admin2_code":"MMR005D004",
    "gn:admin3_code":"MMR005024",
    "gn:asciiname":"Sedo",
    "gn:country_code":"MM",
    "gn:dem":197,
    "gn:feature_class":"P",
    "gn:feature_code":"PPL",
    "gn:name":"Sedo",
    "gn:population":0,
    "gn:timezone":"Asia/Yangon",
    "iso:country":"MM",
    "name:deu_x_preferred":[
        "Sedo"
    ],
    "wof:name":"Sedo",
    "wof:placetype":"locality"
},
  "geometry": {"coordinates":[95.7366,23.79335],"type":"Point"}
}