{
  "type": "Feature",
  "properties": {
    "gn:admin1_code":"16.0",
    "gn:admin2_code":"MMR007D002",
    "gn:admin3_code":"MMR007012",
    "gn:asciiname":"Gwebinmyaung",
    "gn:country_code":"MM",
    "gn:dem":46,
    "gn:feature_class":"P",
    "gn:feature_code":"PPL",
    "gn:name":"Gwebinmyaung",
    "gn:population":0,
    "gn:timezone":"Asia/Yangon",
    "iso:country":"MM",
    "wof:name":"Gwebinmyaung",
    "wof:placetype":"locality"
},
  "geometry": {"coordinates":[96.47320000000001,18.46071],"type":"Point"}
}