{
  "type": "Feature",
  "properties": {
    "gn:admin1_code":"5.0",
    "gn:admin2_code":"MMR003D001",
    "gn:admin3_code":"MMR003004",
    "gn:asciiname":"Onbingyaung",
    "gn:country_code":"MM",
    "gn:dem":455,
    "gn:feature_class":"P",
    "gn:feature_code":"PPL",
    "gn:name":"Onbingyaung",
    "gn:population":0,
    "gn:timezone":"Asia/Yangon",
    "iso:country":"MM",
    "name:und_x_variant":[
        "Ubokchaung",
        "Onbingyaung"
    ],
    "wof:name":"Onbingyaung",
    "wof:placetype":"locality"
},
  "geometry": {"coordinates":[96.70696,18.84059],"type":"Point"}
}