{
  "type": "Feature",
  "properties": {
    "gn:admin1_code":"11.0",
    "gn:admin2_code":"MMR015D008",
    "gn:admin3_code":"MMR015017",
    "gn:asciiname":"Sitton",
    "gn:country_code":"MM",
    "gn:dem":156,
    "gn:feature_class":"P",
    "gn:feature_code":"PPL",
    "gn:name":"Sitton",
    "gn:population":0,
    "gn:timezone":"Asia/Yangon",
    "iso:country":"MM",
    "wof:name":"Sitton",
    "wof:placetype":"locality"
},
  "geometry": {"coordinates":[96.42346999999999,23.15486],"type":"Point"}
}