{
  "type": "Feature",
  "properties": {
    "gn:admin1_code":"13.0",
    "gn:admin2_code":"MMR011D001",
    "gn:admin3_code":"MMR011003",
    "gn:asciiname":"Kalaukkanaing",
    "gn:country_code":"MM",
    "gn:dem":16,
    "gn:feature_class":"P",
    "gn:feature_code":"PPL",
    "gn:name":"Kalaukkanaing",
    "gn:population":0,
    "gn:timezone":"Asia/Yangon",
    "iso:country":"MM",
    "wof:name":"Kalaukkanaing",
    "wof:placetype":"locality"
},
  "geometry": {"coordinates":[97.5423,16.34024],"type":"Point"}
}