{
  "type": "Feature",
  "properties": {
    "gn:admin1_code":"4.0",
    "gn:admin2_code":"MMR001D004",
    "gn:admin3_code":"MMR001016",
    "gn:asciiname":"Aura",
    "gn:country_code":"MM",
    "gn:dem":1399,
    "gn:feature_class":"P",
    "gn:feature_code":"PPL",
    "gn:name":"Aura",
    "gn:population":0,
    "gn:timezone":"Asia/Yangon",
    "iso:country":"MM",
    "name:bos_x_preferred":[
        "Aura"
    ],
    "name:bul_x_preferred":[
        "\u0410\u0443\u0440\u0430"
    ],
    "name:cat_x_preferred":[
        "Aura"
    ],
    "name:ceb_x_preferred":[
        "Aura"
    ],
    "name:ces_x_preferred":[
        "Aura"
    ],
    "name:dan_x_preferred":[
        "Aura"
    ],
    "name:deu_x_preferred":[
        "Aura"
    ],
    "name:epo_x_preferred":[
        "Aura"
    ],
    "name:est_x_preferred":[
        "Aura"
    ],
    "name:fas_x_preferred":[
        "\u0622\u0626\u0648\u0631\u0627"
    ],
    "name:fin_x_preferred":[
        "Aura"
    ],
    "name:fra_x_preferred":[
        "Aura"
    ],
    "name:fry_x_preferred":[
        "Aura"
    ],
    "name:glg_x_preferred":[
        "Aura"
    ],
    "name:heb_x_preferred":[
        "\u05d4\u05d9\u05dc\u05d4"
    ],
    "name:hun_x_preferred":[
        "Aura"
    ],
    "name:ind_x_preferred":[
        "Aura"
    ],
    "name:ita_x_preferred":[
        "Aura"
    ],
    "name:jpn_x_preferred":[
        "\u30aa\u30fc\u30e9"
    ],
    "name:kor_x_preferred":[
        "\uc544\uc6b0\ub77c"
    ],
    "name:lat_x_preferred":[
        "Aura"
    ],
    "name:lit_x_preferred":[
        "Aura"
    ],
    "name:nld_x_preferred":[
        "Aura"
    ],
    "name:nor_x_preferred":[
        "Aura"
    ],
    "name:oci_x_preferred":[
        "Aura"
    ],
    "name:pol_x_preferred":[
        "Aura"
    ],
    "name:por_x_preferred":[
        "Aura"
    ],
    "name:ron_x_preferred":[
        "Aura"
    ],
    "name:rus_x_preferred":[
        "\u0410\u0443\u0440\u0430"
    ],
    "name:slk_x_preferred":[
        "Aura"
    ],
    "name:spa_x_preferred":[
        "Aura"
    ],
    "name:swe_x_preferred":[
        "Aura"
    ],
    "name:tur_x_preferred":[
        "Aura"
    ],
    "name:ukr_x_preferred":[
        "\u0410\u0443\u0440\u0430"
    ],
    "wof:name":"Aura",
    "wof:placetype":"locality"
},
  "geometry": {"coordinates":[97.95647,26.98171],"type":"Point"}
}