{
  "type": "Feature",
  "properties": {
    "gn:admin1_code":"1.0",
    "gn:admin2_code":"MMR012D003",
    "gn:admin3_code":"MMR012014",
    "gn:asciiname":"Ponnabya",
    "gn:country_code":"MM",
    "gn:dem":138,
    "gn:feature_class":"P",
    "gn:feature_code":"PPL",
    "gn:name":"Ponnabya",
    "gn:population":0,
    "gn:timezone":"Asia/Yangon",
    "iso:country":"MM",
    "name:und_x_variant":[
        "Ponuapya",
        "Ponnabya"
    ],
    "wof:name":"Ponnabya",
    "wof:placetype":"locality"
},
  "geometry": {"coordinates":[94.12470999999999,19.80981],"type":"Point"}
}