{
  "type": "Feature",
  "properties": {
    "gn:admin1_code":"10.0",
    "gn:admin2_code":"MMR005D003",
    "gn:admin3_code":"MMR005012",
    "gn:asciiname":"Yeganzu",
    "gn:country_code":"MM",
    "gn:dem":130,
    "gn:feature_class":"P",
    "gn:feature_code":"PPL",
    "gn:name":"Yeganzu",
    "gn:population":0,
    "gn:timezone":"Asia/Yangon",
    "iso:country":"MM",
    "wof:name":"Yeganzu",
    "wof:placetype":"locality"
},
  "geometry": {"coordinates":[95.23891,22.18501],"type":"Point"}
}