{
  "type": "Feature",
  "properties": {
    "gn:admin1_code":"8.0",
    "gn:admin2_code":"MMR010D007",
    "gn:admin3_code":"MMR010029",
    "gn:asciiname":"Ywadanshe",
    "gn:country_code":"MM",
    "gn:dem":265,
    "gn:feature_class":"P",
    "gn:feature_code":"PPL",
    "gn:name":"Ywadanshe",
    "gn:population":0,
    "gn:timezone":"Asia/Yangon",
    "iso:country":"MM",
    "wof:name":"Ywadanshe",
    "wof:placetype":"locality"
},
  "geometry": {"coordinates":[95.65304,21.19894],"type":"Point"}
}