{
  "type": "Feature",
  "properties": {
    "gn:admin1_code":"4.0",
    "gn:admin2_code":"MMR001D004",
    "gn:admin3_code":"MMR001017",
    "gn:asciiname":"Manelap",
    "gn:country_code":"MM",
    "gn:dem":1543,
    "gn:feature_class":"P",
    "gn:feature_code":"PPL",
    "gn:name":"Manelap",
    "gn:population":0,
    "gn:timezone":"Asia/Yangon",
    "iso:country":"MM",
    "wof:name":"Manelap",
    "wof:placetype":"locality"
},
  "geometry": {"coordinates":[98.2032,27.37724],"type":"Point"}
}