{
  "type": "Feature",
  "properties": {
    "gn:admin1_code":"16.0",
    "gn:admin2_code":"MMR008D001",
    "gn:admin3_code":"MMR008001",
    "gn:asciiname":"Mataw",
    "gn:country_code":"MM",
    "gn:dem":41,
    "gn:feature_class":"P",
    "gn:feature_code":"PPL",
    "gn:name":"Mataw",
    "gn:population":0,
    "gn:timezone":"Asia/Yangon",
    "iso:country":"MM",
    "wof:name":"Mataw",
    "wof:placetype":"locality"
},
  "geometry": {"coordinates":[95.30902,18.79473],"type":"Point"}
}