{
  "type": "Feature",
  "properties": {
    "gn:admin1_code":"16.0",
    "gn:admin2_code":"MMR008D002",
    "gn:admin3_code":"MMR008012",
    "gn:asciiname":"Tanbingon Ashe",
    "gn:country_code":"MM",
    "gn:dem":30,
    "gn:feature_class":"P",
    "gn:feature_code":"PPL",
    "gn:name":"Tanbingon Ashe",
    "gn:population":0,
    "gn:timezone":"Asia/Yangon",
    "iso:country":"MM",
    "name:und_x_variant":[
        "Tanbingon",
        "Tanbingon Ashe"
    ],
    "wof:name":"Tanbingon Ashe",
    "wof:placetype":"locality"
},
  "geometry": {"coordinates":[95.47329000000001,18.41298],"type":"Point"}
}