{
  "type": "Feature",
  "properties": {
    "gn:admin1_code":"10.0",
    "gn:admin2_code":"MMR005D009",
    "gn:admin3_code":"MMR005019",
    "gn:asciiname":"Letpan",
    "gn:country_code":"MM",
    "gn:dem":362,
    "gn:feature_class":"P",
    "gn:feature_code":"PPL",
    "gn:name":"Letpan",
    "gn:population":0,
    "gn:timezone":"Asia/Yangon",
    "iso:country":"MM",
    "wof:name":"Letpan",
    "wof:placetype":"locality"
},
  "geometry": {"coordinates":[94.49633,21.81814],"type":"Point"}
}