{
  "type": "Feature",
  "properties": {
    "gn:admin1_code":"17.0",
    "gn:admin2_code":"MMR013D003",
    "gn:admin3_code":"MMR013028",
    "gn:asciiname":"Apyauk",
    "gn:country_code":"MM",
    "gn:dem":15,
    "gn:feature_class":"P",
    "gn:feature_code":"PPL",
    "gn:name":"Apyauk",
    "gn:population":0,
    "gn:timezone":"Asia/Yangon",
    "iso:country":"MM",
    "name:und_x_variant":[
        "Abyauk",
        "Apyauk"
    ],
    "wof:name":"Apyauk",
    "wof:placetype":"locality"
},
  "geometry": {"coordinates":[96.04788000000001,16.61656],"type":"Point"}
}