{
  "type": "Feature",
  "properties": {
    "gn:admin1_code":"11.0",
    "gn:admin2_code":"MMR016D001",
    "gn:admin3_code":"MMR016005",
    "gn:asciiname":"Wan Kawk",
    "gn:country_code":"MM",
    "gn:dem":699,
    "gn:feature_class":"P",
    "gn:feature_code":"PPL",
    "gn:name":"W\u0101n Kawk",
    "gn:population":0,
    "gn:timezone":"Asia/Yangon",
    "iso:country":"MM",
    "wof:name":"Wan Kawk",
    "wof:placetype":"locality"
},
  "geometry": {"coordinates":[99.92637000000001,21.63272000000001],"type":"Point"}
}