{
  "type": "Feature",
  "properties": {
    "gn:admin1_code":"8.0",
    "gn:admin2_code":"MMR010D002",
    "gn:admin3_code":"MMR010012",
    "gn:asciiname":"Ngayinbyo",
    "gn:country_code":"MM",
    "gn:dem":86,
    "gn:feature_class":"P",
    "gn:feature_code":"PPL",
    "gn:name":"Ngayinbyo",
    "gn:population":0,
    "gn:timezone":"Asia/Yangon",
    "iso:country":"MM",
    "name:und_x_variant":[
        "Ngalinbyu",
        "Ngayinbyo"
    ],
    "wof:name":"Ngayinbyo",
    "wof:placetype":"locality"
},
  "geometry": {"coordinates":[95.99472,23.33507],"type":"Point"}
}