{
  "type": "Feature",
  "properties": {
    "gn:admin1_code":"4.0",
    "gn:admin2_code":"MMR001D003",
    "gn:admin3_code":"MMR001013",
    "gn:asciiname":"Panghkam",
    "gn:country_code":"MM",
    "gn:dem":772,
    "gn:feature_class":"P",
    "gn:feature_code":"PPL",
    "gn:name":"Panghkam",
    "gn:population":0,
    "gn:timezone":"Asia/Yangon",
    "iso:country":"MM",
    "name:und_x_variant":[
        "Tanghkam",
        "Panghkam"
    ],
    "wof:name":"Panghkam",
    "wof:placetype":"locality"
},
  "geometry": {"coordinates":[97.60747000000001,23.88989],"type":"Point"}
}