{
  "type": "Feature",
  "properties": {
    "gn:admin1_code":"11.0",
    "gn:admin2_code":"MMR015D008",
    "gn:admin3_code":"MMR015018",
    "gn:asciiname":"Si-tha",
    "gn:country_code":"MM",
    "gn:dem":203,
    "gn:feature_class":"P",
    "gn:feature_code":"PPL",
    "gn:name":"Si-tha",
    "gn:population":0,
    "gn:timezone":"Asia/Yangon",
    "iso:country":"MM",
    "wof:name":"Si-tha",
    "wof:placetype":"locality"
},
  "geometry": {"coordinates":[96.86453,23.71764],"type":"Point"}
}