{
  "type": "Feature",
  "properties": {
    "gn:admin1_code":"16.0",
    "gn:admin2_code":"MMR007D001",
    "gn:admin3_code":"MMR007001",
    "gn:asciiname":"Zaungtu",
    "gn:country_code":"MM",
    "gn:dem":40,
    "gn:feature_class":"P",
    "gn:feature_code":"PPL",
    "gn:name":"Zaungtu",
    "gn:population":0,
    "gn:timezone":"Asia/Yangon",
    "iso:country":"MM",
    "wof:name":"Zaungtu",
    "wof:placetype":"locality"
},
  "geometry": {"coordinates":[96.22624,17.62962000000001],"type":"Point"}
}