{
  "type": "Feature",
  "properties": {
    "gn:admin1_code":"11.0",
    "gn:admin2_code":"MMR014D002",
    "gn:admin3_code":"MMR014013",
    "gn:asciiname":"Wan Pang",
    "gn:country_code":"MM",
    "gn:dem":1027,
    "gn:feature_class":"P",
    "gn:feature_code":"PPL",
    "gn:name":"W\u0101n P\u0101ng",
    "gn:population":0,
    "gn:timezone":"Asia/Yangon",
    "iso:country":"MM",
    "wof:name":"Wan Pang",
    "wof:placetype":"locality"
},
  "geometry": {"coordinates":[97.70650999999999,20.86079],"type":"Point"}
}