{
  "type": "Feature",
  "properties": {
    "gn:admin1_code":"16.0",
    "gn:admin2_code":"MMR007D001",
    "gn:admin3_code":"MMR007006",
    "gn:asciiname":"Thebyu",
    "gn:country_code":"MM",
    "gn:dem":30,
    "gn:feature_class":"P",
    "gn:feature_code":"PPL",
    "gn:name":"Th\u00e8byu",
    "gn:population":0,
    "gn:timezone":"Asia/Yangon",
    "iso:country":"MM",
    "name:und_x_variant":[
        "Thebyugale",
        "Th\u00e8byu"
    ],
    "wof:name":"Thebyu",
    "wof:placetype":"locality"
},
  "geometry": {"coordinates":[96.60372,18.22159],"type":"Point"}
}