{
  "type": "Feature",
  "properties": {
    "gn:admin1_code":"3.0",
    "gn:admin2_code":"MMR017D001",
    "gn:admin3_code":"MMR017006",
    "gn:asciiname":"Zigon",
    "gn:country_code":"MM",
    "gn:dem":13,
    "gn:feature_class":"P",
    "gn:feature_code":"PPL",
    "gn:name":"Zigon",
    "gn:population":0,
    "gn:timezone":"Asia/Yangon",
    "iso:country":"MM",
    "wof:name":"Zigon",
    "wof:placetype":"locality"
},
  "geometry": {"coordinates":[95.15807,17.36844],"type":"Point"}
}