{
  "type": "Feature",
  "properties": {
    "gn:admin1_code":"11.0",
    "gn:admin2_code":"MMR014D002",
    "gn:admin3_code":"MMR014015",
    "gn:asciiname":"Namhu-hai-hseng",
    "gn:country_code":"MM",
    "gn:dem":663,
    "gn:feature_class":"P",
    "gn:feature_code":"PPL",
    "gn:name":"Namhu-hai-hseng",
    "gn:population":0,
    "gn:timezone":"Asia/Yangon",
    "iso:country":"MM",
    "wof:name":"Namhu-hai-hseng",
    "wof:placetype":"locality"
},
  "geometry": {"coordinates":[98.29982,21.52541],"type":"Point"}
}