{
  "type": "Feature",
  "properties": {
    "gn:admin1_code":"16.0",
    "gn:admin2_code":"MMR007D002",
    "gn:admin3_code":"MMR007011",
    "gn:asciiname":"Sepale",
    "gn:country_code":"MM",
    "gn:dem":31,
    "gn:feature_class":"P",
    "gn:feature_code":"PPL",
    "gn:name":"Sepal\u00e8",
    "gn:population":0,
    "gn:timezone":"Asia/Yangon",
    "iso:country":"MM",
    "name:und_x_variant":[
        "Sebal\u00e8",
        "Sepal\u00e8"
    ],
    "wof:name":"Sepale",
    "wof:placetype":"locality"
},
  "geometry": {"coordinates":[96.66705,18.34716],"type":"Point"}
}