{
  "type": "Feature",
  "properties": {
    "gn:admin1_code":"4.0",
    "gn:admin2_code":"MMR001D001",
    "gn:admin3_code":"MMR001003",
    "gn:asciiname":"Tingputkawng",
    "gn:country_code":"MM",
    "gn:dem":1222,
    "gn:feature_class":"P",
    "gn:feature_code":"PPL",
    "gn:name":"Tingputkawng",
    "gn:population":0,
    "gn:timezone":"Asia/Yangon",
    "iso:country":"MM",
    "wof:name":"Tingputkawng",
    "wof:placetype":"locality"
},
  "geometry": {"coordinates":[98.00725,26.05428],"type":"Point"}
}