{
  "type": "Feature",
  "properties": {
    "gn:admin1_code":"8.0",
    "gn:admin2_code":"MMR010D006",
    "gn:admin3_code":"MMR010024",
    "gn:asciiname":"Yongon",
    "gn:country_code":"MM",
    "gn:dem":176,
    "gn:feature_class":"P",
    "gn:feature_code":"PPL",
    "gn:name":"Yongon",
    "gn:population":0,
    "gn:timezone":"Asia/Yangon",
    "iso:country":"MM",
    "wof:name":"Yongon",
    "wof:placetype":"locality"
},
  "geometry": {"coordinates":[96.18115,20.65764],"type":"Point"}
}