{
  "type": "Feature",
  "properties": {
    "gn:admin1_code":"11.0",
    "gn:admin2_code":"MMR015D006",
    "gn:admin3_code":"MMR015008",
    "gn:asciiname":"Mo-rai-yo",
    "gn:country_code":"MM",
    "gn:dem":1524,
    "gn:feature_class":"P",
    "gn:feature_code":"PPL",
    "gn:name":"Mo-rai-yo",
    "gn:population":0,
    "gn:timezone":"Asia/Yangon",
    "iso:country":"MM",
    "wof:name":"Mo-rai-yo",
    "wof:placetype":"locality"
},
  "geometry": {"coordinates":[98.7863,22.78147],"type":"Point"}
}