{
  "type": "Feature",
  "properties": {
    "gn:admin1_code":"1.0",
    "gn:admin2_code":"MMR012D001",
    "gn:admin3_code":"MMR012002",
    "gn:asciiname":"Mraunggri",
    "gn:country_code":"MM",
    "gn:dem":13,
    "gn:feature_class":"P",
    "gn:feature_code":"PPL",
    "gn:name":"Mraunggri",
    "gn:population":0,
    "gn:timezone":"Asia/Yangon",
    "iso:country":"MM",
    "name:und_x_variant":[
        "Miaunggri",
        "Mraunggri"
    ],
    "wof:name":"Mraunggri",
    "wof:placetype":"locality"
},
  "geometry": {"coordinates":[92.96250999999999,20.34468],"type":"Point"}
}