{
  "type": "Feature",
  "properties": {
    "gn:admin1_code":"11.0",
    "gn:admin2_code":"MMR016D003",
    "gn:admin3_code":"MMR016010",
    "gn:asciiname":"Wan Hsenpu-hkam",
    "gn:country_code":"MM",
    "gn:dem":998,
    "gn:feature_class":"P",
    "gn:feature_code":"PPL",
    "gn:name":"W\u0101n Hsenpu-hkam",
    "gn:population":0,
    "gn:timezone":"Asia/Yangon",
    "iso:country":"MM",
    "wof:name":"Wan Hsenpu-hkam",
    "wof:placetype":"locality"
},
  "geometry": {"coordinates":[99.95461,21.08566],"type":"Point"}
}