{
  "type": "Feature",
  "properties": {
    "gn:admin1_code":"10.0",
    "gn:asciiname":"Bontha",
    "gn:country_code":"MM",
    "gn:dem":152,
    "gn:feature_class":"P",
    "gn:feature_code":"PPL",
    "gn:name":"Bontha",
    "gn:population":0,
    "gn:timezone":"Asia/Yangon",
    "iso:country":"MM",
    "wof:name":"Bontha",
    "wof:placetype":"locality"
},
  "geometry": {"coordinates":[95.77607,21.81829],"type":"Point"}
}