{
  "type": "Feature",
  "properties": {
    "gn:admin1_code":"18.0",
    "gn:admin2_code":"MMR018D001",
    "gn:admin3_code":"MMR018001",
    "gn:asciiname":"Shanywa",
    "gn:country_code":"MM",
    "gn:dem":134,
    "gn:feature_class":"P",
    "gn:feature_code":"PPL",
    "gn:name":"Shanywa",
    "gn:population":0,
    "gn:timezone":"Asia/Yangon",
    "iso:country":"MM",
    "wof:name":"Shanywa",
    "wof:placetype":"locality"
},
  "geometry": {"coordinates":[96.29227,19.88115],"type":"Point"}
}