{
  "type": "Feature",
  "properties": {
    "gn:admin1_code":"10.0",
    "gn:admin2_code":"MMR005D004",
    "gn:admin3_code":"MMR005020",
    "gn:asciiname":"Kinmongyun",
    "gn:country_code":"MM",
    "gn:dem":106,
    "gn:feature_class":"P",
    "gn:feature_code":"PPL",
    "gn:name":"Kinmongyun",
    "gn:population":0,
    "gn:timezone":"Asia/Yangon",
    "iso:country":"MM",
    "wof:name":"Kinmongyun",
    "wof:placetype":"locality"
},
  "geometry": {"coordinates":[96.37194,24.02645],"type":"Point"}
}