{
  "type": "Feature",
  "properties": {
    "gn:admin1_code":"1.0",
    "gn:admin2_code":"MMR012D002",
    "gn:admin3_code":"MMR012009",
    "gn:asciiname":"Shambala",
    "gn:country_code":"MM",
    "gn:dem":8,
    "gn:feature_class":"P",
    "gn:feature_code":"PPL",
    "gn:name":"Shambala",
    "gn:population":0,
    "gn:timezone":"Asia/Yangon",
    "iso:country":"MM",
    "name:bel_x_preferred":[
        "\u0428\u0430\u043c\u0431\u0430\u043b\u0430"
    ],
    "name:deu_x_preferred":[
        "Shambala"
    ],
    "name:fra_x_preferred":[
        "Shambhala"
    ],
    "name:ita_x_preferred":[
        "Shambala"
    ],
    "name:jpn_x_preferred":[
        "\u30b7\u30e3\u30f3\u30d0\u30e9"
    ],
    "name:lat_x_preferred":[
        "Shambhala"
    ],
    "name:nld_x_preferred":[
        "Shambala"
    ],
    "name:rus_x_preferred":[
        "\u0428\u0430\u043c\u0431\u0430\u043b\u0430"
    ],
    "name:tha_x_preferred":[
        "\u0e28\u0e31\u0e21\u0e20\u0e25\u0e32"
    ],
    "name:ukr_x_preferred":[
        "\u0428\u0430\u043c\u0431\u0430\u043b\u0430"
    ],
    "wof:name":"Shambala",
    "wof:placetype":"locality"
},
  "geometry": {"coordinates":[92.24066000000001,21.17532000000001],"type":"Point"}
}