{
  "type": "Feature",
  "properties": {
    "gn:admin1_code":"11.0",
    "gn:admin2_code":"MMR014D001",
    "gn:admin3_code":"MMR014009",
    "gn:asciiname":"Loi-boun Taung",
    "gn:country_code":"MM",
    "gn:dem":1468,
    "gn:feature_class":"P",
    "gn:feature_code":"PPL",
    "gn:name":"Loi-boun Taung",
    "gn:population":0,
    "gn:timezone":"Asia/Yangon",
    "iso:country":"MM",
    "name:und_x_variant":[
        "Loi-bown",
        "Loi-boun Taung"
    ],
    "wof:name":"Loi-boun Taung",
    "wof:placetype":"locality"
},
  "geometry": {"coordinates":[96.82640000000001,20.28486],"type":"Point"}
}