{
  "type": "Feature",
  "properties": {
    "gn:admin1_code":"16.0",
    "gn:admin2_code":"MMR008D001",
    "gn:admin3_code":"MMR008001",
    "gn:asciiname":"Aukchaing",
    "gn:country_code":"MM",
    "gn:dem":89,
    "gn:feature_class":"P",
    "gn:feature_code":"PPL",
    "gn:name":"Aukchaing",
    "gn:population":0,
    "gn:timezone":"Asia/Yangon",
    "iso:country":"MM",
    "name:und_x_variant":[
        "Aukohaing",
        "Aukchaing"
    ],
    "wof:name":"Aukchaing",
    "wof:placetype":"locality"
},
  "geometry": {"coordinates":[95.31341999999999,19.035],"type":"Point"}
}