{
  "type": "Feature",
  "properties": {
    "gn:admin1_code":"16.0",
    "gn:admin2_code":"MMR007D002",
    "gn:admin3_code":"MMR007011",
    "gn:asciiname":"Thawngedo",
    "gn:country_code":"MM",
    "gn:dem":217,
    "gn:feature_class":"P",
    "gn:feature_code":"PPL",
    "gn:name":"Thawngedo",
    "gn:population":0,
    "gn:timezone":"Asia/Yangon",
    "iso:country":"MM",
    "name:und_x_variant":[
        "Thaungdo",
        "Thawngedo"
    ],
    "wof:name":"Thawngedo",
    "wof:placetype":"locality"
},
  "geometry": {"coordinates":[96.89133,18.25257],"type":"Point"}
}