{
  "type": "Feature",
  "properties": {
    "gn:admin1_code":"11.0",
    "gn:admin2_code":"MMR014D002",
    "gn:admin3_code":"MMR014011",
    "gn:asciiname":"Panghai",
    "gn:country_code":"MM",
    "gn:dem":1248,
    "gn:feature_class":"P",
    "gn:feature_code":"PPL",
    "gn:name":"Panghai",
    "gn:population":0,
    "gn:timezone":"Asia/Yangon",
    "iso:country":"MM",
    "wof:name":"Panghai",
    "wof:placetype":"locality"
},
  "geometry": {"coordinates":[97.53709000000001,21.18997],"type":"Point"}
}