{
  "type": "Feature",
  "properties": {
    "gn:admin1_code":"4.0",
    "gn:admin2_code":"MMR001D004",
    "gn:admin3_code":"MMR001015",
    "gn:asciiname":"Hjawagtawng",
    "gn:country_code":"MM",
    "gn:dem":698,
    "gn:feature_class":"P",
    "gn:feature_code":"PPL",
    "gn:name":"Hjawagtawng",
    "gn:population":0,
    "gn:timezone":"Asia/Yangon",
    "iso:country":"MM",
    "wof:name":"Hjawagtawng",
    "wof:placetype":"locality"
},
  "geometry": {"coordinates":[97.40600999999999,26.76164],"type":"Point"}
}