{
  "type": "Feature",
  "properties": {
    "gn:admin1_code":"11.0",
    "gn:admin2_code":"MMR014D001",
    "gn:admin3_code":"MMR014008",
    "gn:asciiname":"Na-kat",
    "gn:country_code":"MM",
    "gn:dem":597,
    "gn:feature_class":"P",
    "gn:feature_code":"PPL",
    "gn:name":"N\u0101-kat",
    "gn:population":0,
    "gn:timezone":"Asia/Yangon",
    "iso:country":"MM",
    "wof:name":"Na-kat",
    "wof:placetype":"locality"
},
  "geometry": {"coordinates":[97.12327000000001,21.93923],"type":"Point"}
}