{
  "type": "Feature",
  "properties": {
    "gn:admin1_code":"3.0",
    "gn:admin2_code":"MMR017D002",
    "gn:admin3_code":"MMR017013",
    "gn:asciiname":"Thabaw",
    "gn:country_code":"MM",
    "gn:dem":21,
    "gn:feature_class":"P",
    "gn:feature_code":"PPL",
    "gn:name":"Thabaw",
    "gn:population":0,
    "gn:timezone":"Asia/Yangon",
    "iso:country":"MM",
    "wof:name":"Thabaw",
    "wof:placetype":"locality"
},
  "geometry": {"coordinates":[95.18586999999999,17.86084],"type":"Point"}
}