{
  "type": "Feature",
  "properties": {
    "gn:admin1_code":"16.0",
    "gn:admin2_code":"MMR008D002",
    "gn:admin3_code":"MMR008014",
    "gn:asciiname":"Nyaunggon",
    "gn:country_code":"MM",
    "gn:dem":26,
    "gn:feature_class":"P",
    "gn:feature_code":"PPL",
    "gn:name":"Nyaunggon",
    "gn:population":0,
    "gn:timezone":"Asia/Yangon",
    "iso:country":"MM",
    "wof:name":"Nyaunggon",
    "wof:placetype":"locality"
},
  "geometry": {"coordinates":[95.58987,18.18714],"type":"Point"}
}