{
  "type": "Feature",
  "properties": {
    "gn:admin1_code":"11.0",
    "gn:admin2_code":"MMR015D005",
    "gn:admin3_code":"MMR015022",
    "gn:asciiname":"Wan Ta-shui-tang",
    "gn:country_code":"MM",
    "gn:dem":1783,
    "gn:feature_class":"P",
    "gn:feature_code":"PPL",
    "gn:name":"W\u0101n Ta-shui-tang",
    "gn:population":0,
    "gn:timezone":"Asia/Yangon",
    "iso:country":"MM",
    "wof:name":"Wan Ta-shui-tang",
    "wof:placetype":"locality"
},
  "geometry": {"coordinates":[98.70528,23.72354],"type":"Point"}
}