{
  "type": "Feature",
  "properties": {
    "gn:admin1_code":"12.0",
    "gn:admin2_code":"MMR006D002",
    "gn:admin3_code":"MMR006007",
    "gn:asciiname":"Shanthe Atet",
    "gn:country_code":"MM",
    "gn:dem":384,
    "gn:feature_class":"P",
    "gn:feature_code":"PPL",
    "gn:name":"Shanthe Atet",
    "gn:population":0,
    "gn:timezone":"Asia/Yangon",
    "iso:country":"MM",
    "name:und_x_variant":[
        "Shanthe",
        "Shanthe Atet"
    ],
    "wof:name":"Shanthe Atet",
    "wof:placetype":"locality"
},
  "geometry": {"coordinates":[98.74832000000001,13.10683],"type":"Point"}
}