{
  "type": "Feature",
  "properties": {
    "gn:admin1_code":"4.0",
    "gn:admin2_code":"MMR001D004",
    "gn:admin3_code":"MMR001018",
    "gn:asciiname":"Mawgawng",
    "gn:country_code":"MM",
    "gn:dem":1067,
    "gn:feature_class":"P",
    "gn:feature_code":"PPL",
    "gn:name":"Mawgawng",
    "gn:population":0,
    "gn:timezone":"Asia/Yangon",
    "iso:country":"MM",
    "wof:name":"Mawgawng",
    "wof:placetype":"locality"
},
  "geometry": {"coordinates":[98.25996000000001,27.17039],"type":"Point"}
}