{
  "type": "Feature",
  "properties": {
    "gn:admin1_code":"18.0",
    "gn:admin2_code":"MMR018D002",
    "gn:admin3_code":"MMR018006",
    "gn:asciiname":"Zegon",
    "gn:country_code":"MM",
    "gn:dem":89,
    "gn:feature_class":"P",
    "gn:feature_code":"PPL",
    "gn:name":"Zegon",
    "gn:population":0,
    "gn:timezone":"Asia/Yangon",
    "iso:country":"MM",
    "wof:name":"Zegon",
    "wof:placetype":"locality"
},
  "geometry": {"coordinates":[96.27321000000001,19.71365],"type":"Point"}
}