{
  "type": "Feature",
  "properties": {
    "gn:admin1_code":"2.0",
    "gn:admin2_code":"MMR004D002",
    "gn:admin3_code":"MMR004006",
    "gn:asciiname":"Lungsu-loisan",
    "gn:country_code":"MM",
    "gn:dem":850,
    "gn:feature_class":"P",
    "gn:feature_code":"PPL",
    "gn:name":"Lungsu-loisan",
    "gn:population":0,
    "gn:timezone":"Asia/Yangon",
    "iso:country":"MM",
    "wof:name":"Lungsu-loisan",
    "wof:placetype":"locality"
},
  "geometry": {"coordinates":[93.56667,21.38333],"type":"Point"}
}