{
  "type": "Feature",
  "properties": {
    "gn:admin1_code":"4.0",
    "gn:admin2_code":"MMR001D002",
    "gn:admin3_code":"MMR001009",
    "gn:asciiname":"Mupaw Ga",
    "gn:country_code":"MM",
    "gn:dem":933,
    "gn:feature_class":"P",
    "gn:feature_code":"PPL",
    "gn:name":"Mupaw Ga",
    "gn:population":0,
    "gn:timezone":"Asia/Yangon",
    "iso:country":"MM",
    "wof:name":"Mupaw Ga",
    "wof:placetype":"locality"
},
  "geometry": {"coordinates":[96.89087000000001,25.87769],"type":"Point"}
}