{
  "type": "Feature",
  "properties": {
    "gn:admin1_code":"11.0",
    "gn:admin2_code":"MMR015D003",
    "gn:admin3_code":"MMR015012",
    "gn:asciiname":"Loihkamhaung",
    "gn:country_code":"MM",
    "gn:dem":1643,
    "gn:feature_class":"P",
    "gn:feature_code":"PPL",
    "gn:name":"Loihkamhaung",
    "gn:population":0,
    "gn:timezone":"Asia/Yangon",
    "iso:country":"MM",
    "wof:name":"Loihkamhaung",
    "wof:placetype":"locality"
},
  "geometry": {"coordinates":[96.85267,22.90624],"type":"Point"}
}