{
  "type": "Feature",
  "properties": {
    "gn:admin1_code":"15.0",
    "gn:admin2_code":"MMR009D002",
    "gn:admin3_code":"MMR009011",
    "gn:asciiname":"Ngatawzok",
    "gn:country_code":"MM",
    "gn:dem":329,
    "gn:feature_class":"P",
    "gn:feature_code":"PPL",
    "gn:name":"Ngatawz\u00f4k",
    "gn:population":0,
    "gn:timezone":"Asia/Yangon",
    "iso:country":"MM",
    "wof:name":"Ngatawzok",
    "wof:placetype":"locality"
},
  "geometry": {"coordinates":[94.08869,20.83464],"type":"Point"}
}