{
  "type": "Feature",
  "properties": {
    "gn:admin1_code":"11.0",
    "gn:admin2_code":"MMR015D001",
    "gn:admin3_code":"MMR015001",
    "gn:asciiname":"Man-ai",
    "gn:country_code":"MM",
    "gn:dem":969,
    "gn:feature_class":"P",
    "gn:feature_code":"PPL",
    "gn:name":"M\u0101n-ai",
    "gn:population":0,
    "gn:timezone":"Asia/Yangon",
    "iso:country":"MM",
    "wof:name":"Man-ai",
    "wof:placetype":"locality"
},
  "geometry": {"coordinates":[97.75418000000001,22.91135],"type":"Point"}
}