{
  "type": "Feature",
  "properties": {
    "gn:admin1_code":"11.0",
    "gn:admin2_code":"MMR016D001",
    "gn:admin3_code":"MMR016003",
    "gn:asciiname":"Wan Ha-hko",
    "gn:country_code":"MM",
    "gn:dem":891,
    "gn:feature_class":"P",
    "gn:feature_code":"PPL",
    "gn:name":"W\u0101n Ha-hko",
    "gn:population":0,
    "gn:timezone":"Asia/Yangon",
    "iso:country":"MM",
    "wof:name":"Wan Ha-hko",
    "wof:placetype":"locality"
},
  "geometry": {"coordinates":[99.62566,21.86127],"type":"Point"}
}