{
  "type": "Feature",
  "properties": {
    "gn:admin1_code":"11.0",
    "gn:admin2_code":"MMR015D001",
    "gn:admin3_code":"MMR015001",
    "gn:asciiname":"Na-hken",
    "gn:country_code":"MM",
    "gn:dem":986,
    "gn:feature_class":"P",
    "gn:feature_code":"PPL",
    "gn:name":"N\u0101-hken",
    "gn:population":0,
    "gn:timezone":"Asia/Yangon",
    "iso:country":"MM",
    "wof:name":"Na-hken",
    "wof:placetype":"locality"
},
  "geometry": {"coordinates":[98.0211,22.96373],"type":"Point"}
}