{
  "type": "Feature",
  "properties": {
    "gn:admin1_code":"16.0",
    "gn:admin2_code":"MMR008D002",
    "gn:admin3_code":"MMR008009",
    "gn:asciiname":"Kywedegon",
    "gn:country_code":"MM",
    "gn:dem":25,
    "gn:feature_class":"P",
    "gn:feature_code":"PPL",
    "gn:name":"Kyw\u00e8d\u00e8gon",
    "gn:population":0,
    "gn:timezone":"Asia/Yangon",
    "iso:country":"MM",
    "wof:name":"Kywedegon",
    "wof:placetype":"locality"
},
  "geometry": {"coordinates":[95.69992000000001,17.98623],"type":"Point"}
}