{
  "type": "Feature",
  "properties": {
    "gn:admin1_code":"3.0",
    "gn:admin2_code":"MMR017D003",
    "gn:admin3_code":"MMR017014",
    "gn:asciiname":"Pyinbon",
    "gn:country_code":"MM",
    "gn:dem":34,
    "gn:feature_class":"P",
    "gn:feature_code":"PPL",
    "gn:name":"Pyinb\u00f4n",
    "gn:population":0,
    "gn:timezone":"Asia/Yangon",
    "iso:country":"MM",
    "wof:name":"Pyinbon",
    "wof:placetype":"locality"
},
  "geometry": {"coordinates":[94.78528,16.46958],"type":"Point"}
}