{
  "type": "Feature",
  "properties": {
    "gn:admin1_code":"4.0",
    "gn:admin2_code":"MMR001D003",
    "gn:admin3_code":"MMR001012",
    "gn:asciiname":"Nawku Lungbyen",
    "gn:country_code":"MM",
    "gn:dem":1369,
    "gn:feature_class":"P",
    "gn:feature_code":"PPL",
    "gn:name":"Nawku Lungbyen",
    "gn:population":0,
    "gn:timezone":"Asia/Yangon",
    "iso:country":"MM",
    "wof:name":"Nawku Lungbyen",
    "wof:placetype":"locality"
},
  "geometry": {"coordinates":[97.54365,24.61006],"type":"Point"}
}