{
  "type": "Feature",
  "properties": {
    "gn:admin1_code":"4.0",
    "gn:admin2_code":"MMR001D002",
    "gn:admin3_code":"MMR001009",
    "gn:asciiname":"Marim",
    "gn:country_code":"MM",
    "gn:dem":221,
    "gn:feature_class":"P",
    "gn:feature_code":"PPL",
    "gn:name":"Marim",
    "gn:population":0,
    "gn:timezone":"Asia/Yangon",
    "iso:country":"MM",
    "wof:name":"Marim",
    "wof:placetype":"locality"
},
  "geometry": {"coordinates":[96.51560000000001,25.4122],"type":"Point"}
}