{
  "type": "Feature",
  "properties": {
    "gn:admin1_code":"8.0",
    "gn:admin2_code":"MMR010D001",
    "gn:admin3_code":"MMR010007",
    "gn:asciiname":"Khangon",
    "gn:country_code":"MM",
    "gn:dem":79,
    "gn:feature_class":"P",
    "gn:feature_code":"PPL",
    "gn:name":"Khangon",
    "gn:population":0,
    "gn:timezone":"Asia/Yangon",
    "iso:country":"MM",
    "wof:name":"Khangon",
    "wof:placetype":"locality"
},
  "geometry": {"coordinates":[96.09679,22.0274],"type":"Point"}
}