{
  "type": "Feature",
  "properties": {
    "gn:admin1_code":"11.0",
    "gn:admin2_code":"MMR015D008",
    "gn:admin3_code":"MMR015018",
    "gn:asciiname":"Man Hawn",
    "gn:country_code":"MM",
    "gn:dem":177,
    "gn:feature_class":"P",
    "gn:feature_code":"PPL",
    "gn:name":"Man Hawn",
    "gn:population":0,
    "gn:timezone":"Asia/Yangon",
    "iso:country":"MM",
    "name:und_x_variant":[
        "M\u0101n Hawn"
    ],
    "wof:name":"Man Hawn",
    "wof:placetype":"locality"
},
  "geometry": {"coordinates":[97.00292,23.63812],"type":"Point"}
}