{
  "type": "Feature",
  "properties": {
    "gn:admin1_code":"15.0",
    "gn:admin2_code":"MMR009D001",
    "gn:admin3_code":"MMR009002",
    "gn:asciiname":"O-hla",
    "gn:country_code":"MM",
    "gn:dem":170,
    "gn:feature_class":"P",
    "gn:feature_code":"PPL",
    "gn:name":"O-hla",
    "gn:population":0,
    "gn:timezone":"Asia/Yangon",
    "iso:country":"MM",
    "name:und_x_variant":[
        "Okhla",
        "O-hla"
    ],
    "wof:name":"O-hla",
    "wof:placetype":"locality"
},
  "geometry": {"coordinates":[95.02867999999999,20.34878],"type":"Point"}
}