{
  "type": "Feature",
  "properties": {
    "gn:admin1_code":"3.0",
    "gn:admin2_code":"MMR017D001",
    "gn:admin3_code":"MMR017004",
    "gn:asciiname":"Tingyaung",
    "gn:country_code":"MM",
    "gn:dem":11,
    "gn:feature_class":"P",
    "gn:feature_code":"PPL",
    "gn:name":"Tingyaung",
    "gn:population":0,
    "gn:timezone":"Asia/Yangon",
    "iso:country":"MM",
    "name:und_x_variant":[
        "Tengkhyaung",
        "Tingyaung"
    ],
    "wof:name":"Tingyaung",
    "wof:placetype":"locality"
},
  "geometry": {"coordinates":[94.44486000000001,16.38528],"type":"Point"}
}