{
  "type": "Feature",
  "properties": {
    "gn:admin1_code":"10.0",
    "gn:admin2_code":"MMR005D009",
    "gn:admin3_code":"MMR005018",
    "gn:asciiname":"Shwehle",
    "gn:country_code":"MM",
    "gn:dem":78,
    "gn:feature_class":"P",
    "gn:feature_code":"PPL",
    "gn:name":"Shwehle",
    "gn:population":0,
    "gn:timezone":"Asia/Yangon",
    "iso:country":"MM",
    "wof:name":"Shwehle",
    "wof:placetype":"locality"
},
  "geometry": {"coordinates":[95.12302,22.07115],"type":"Point"}
}