{
  "type": "Feature",
  "properties": {
    "gn:admin1_code":"4.0",
    "gn:admin2_code":"MMR001D002",
    "gn:admin3_code":"MMR001009",
    "gn:asciiname":"Saihkao",
    "gn:country_code":"MM",
    "gn:dem":194,
    "gn:feature_class":"P",
    "gn:feature_code":"PPL",
    "gn:name":"Saihkao",
    "gn:population":0,
    "gn:timezone":"Asia/Yangon",
    "iso:country":"MM",
    "name:und_x_variant":[
        "Sathkao",
        "Saihkao"
    ],
    "wof:name":"Saihkao",
    "wof:placetype":"locality"
},
  "geometry": {"coordinates":[96.00664999999999,25.34839],"type":"Point"}
}