{
  "type": "Feature",
  "properties": {
    "gn:admin1_code":"10.0",
    "gn:admin2_code":"MMR005D004",
    "gn:admin3_code":"MMR005020",
    "gn:asciiname":"Shwebohtha",
    "gn:country_code":"MM",
    "gn:dem":97,
    "gn:feature_class":"P",
    "gn:feature_code":"PPL",
    "gn:name":"Shweb\u00f4htha",
    "gn:population":0,
    "gn:timezone":"Asia/Yangon",
    "iso:country":"MM",
    "name:und_x_variant":[
        "Shwebontha",
        "Shweb\u00f4htha"
    ],
    "wof:name":"Shwebohtha",
    "wof:placetype":"locality"
},
  "geometry": {"coordinates":[96.28547,23.9379],"type":"Point"}
}