{
  "type": "Feature",
  "properties": {
    "gn:admin1_code":"11.0",
    "gn:admin2_code":"MMR016D003",
    "gn:admin3_code":"MMR016009",
    "gn:asciiname":"Wan Muenlong",
    "gn:country_code":"MM",
    "gn:dem":1039,
    "gn:feature_class":"P",
    "gn:feature_code":"PPL",
    "gn:name":"W\u0101n M\u00fcnl\u014dng",
    "gn:population":0,
    "gn:timezone":"Asia/Yangon",
    "iso:country":"MM",
    "wof:name":"Wan Muenlong",
    "wof:placetype":"locality"
},
  "geometry": {"coordinates":[100.21467,20.85943],"type":"Point"}
}