{
  "type": "Feature",
  "properties": {
    "gn:admin1_code":"6.0",
    "gn:admin2_code":"MMR002D002",
    "gn:admin3_code":"MMR002006",
    "gn:asciiname":"Ka-pwe",
    "gn:country_code":"MM",
    "gn:dem":979,
    "gn:feature_class":"P",
    "gn:feature_code":"PPL",
    "gn:name":"Ka-pw\u00e8",
    "gn:population":0,
    "gn:timezone":"Asia/Yangon",
    "iso:country":"MM",
    "wof:name":"Ka-pwe",
    "wof:placetype":"locality"
},
  "geometry": {"coordinates":[97.06573,19.01835],"type":"Point"}
}