{
  "type": "Feature",
  "properties": {
    "gn:admin1_code":"10.0",
    "gn:admin2_code":"MMR005D004",
    "gn:admin3_code":"MMR005026",
    "gn:asciiname":"Thinbaunggyin",
    "gn:country_code":"MM",
    "gn:dem":232,
    "gn:feature_class":"P",
    "gn:feature_code":"PPL",
    "gn:name":"Thinbaunggyin",
    "gn:population":0,
    "gn:timezone":"Asia/Yangon",
    "iso:country":"MM",
    "wof:name":"Thinbaunggyin",
    "wof:placetype":"locality"
},
  "geometry": {"coordinates":[95.29651,23.89154],"type":"Point"}
}