{
  "type": "Feature",
  "properties": {
    "gn:admin1_code":"1.0",
    "gn:admin2_code":"MMR012D003",
    "gn:admin3_code":"MMR012011",
    "gn:asciiname":"Kalaba",
    "gn:country_code":"MM",
    "gn:dem":12,
    "gn:feature_class":"P",
    "gn:feature_code":"PPL",
    "gn:name":"Kalaba",
    "gn:population":0,
    "gn:timezone":"Asia/Yangon",
    "iso:country":"MM",
    "name:ceb_x_preferred":[
        "Kalaba"
    ],
    "name:deu_x_preferred":[
        "Kalaba"
    ],
    "name:fra_x_preferred":[
        "Kalaba"
    ],
    "name:swe_x_preferred":[
        "Kalaba"
    ],
    "name:tur_x_preferred":[
        "Kalaba"
    ],
    "wof:name":"Kalaba",
    "wof:placetype":"locality"
},
  "geometry": {"coordinates":[93.5081,19.33677],"type":"Point"}
}