{
  "type": "Feature",
  "properties": {
    "gn:admin1_code":"11.0",
    "gn:admin2_code":"MMR014D001",
    "gn:admin3_code":"MMR014003",
    "gn:asciiname":"Pang Nyim",
    "gn:country_code":"MM",
    "gn:dem":1101,
    "gn:feature_class":"P",
    "gn:feature_code":"PPL",
    "gn:name":"Pang Nyim",
    "gn:population":0,
    "gn:timezone":"Asia/Yangon",
    "iso:country":"MM",
    "name:und_x_variant":[
        "P\u0101ngnyin",
        "Pang Nyim"
    ],
    "wof:name":"Pang Nyim",
    "wof:placetype":"locality"
},
  "geometry": {"coordinates":[97.44447,20.74589],"type":"Point"}
}