{
  "type": "Feature",
  "properties": {
    "gn:admin1_code":"5.0",
    "gn:admin2_code":"MMR003D003",
    "gn:admin3_code":"MMR003007",
    "gn:asciiname":"Thabyegon",
    "gn:country_code":"MM",
    "gn:dem":25,
    "gn:feature_class":"P",
    "gn:feature_code":"PPL",
    "gn:name":"Thabyegon",
    "gn:population":0,
    "gn:timezone":"Asia/Yangon",
    "iso:country":"MM",
    "wof:name":"Thabyegon",
    "wof:placetype":"locality"
},
  "geometry": {"coordinates":[97.97638000000001,15.83952],"type":"Point"}
}