{
  "type": "Feature",
  "properties": {
    "gn:admin1_code":"11.0",
    "gn:admin2_code":"MMR016D002",
    "gn:admin3_code":"MMR016008",
    "gn:asciiname":"Wan Ho-pang",
    "gn:country_code":"MM",
    "gn:dem":523,
    "gn:feature_class":"P",
    "gn:feature_code":"PPL",
    "gn:name":"W\u0101n Ho-p\u0101ng",
    "gn:population":0,
    "gn:timezone":"Asia/Yangon",
    "iso:country":"MM",
    "wof:name":"Wan Ho-pang",
    "wof:placetype":"locality"
},
  "geometry": {"coordinates":[98.93348,20.01087],"type":"Point"}
}