{
  "type": "Feature",
  "properties": {
    "gn:admin1_code":"16.0",
    "gn:admin2_code":"MMR007D002",
    "gn:admin3_code":"MMR007013",
    "gn:asciiname":"Gonmin",
    "gn:country_code":"MM",
    "gn:dem":42,
    "gn:feature_class":"P",
    "gn:feature_code":"PPL",
    "gn:name":"Gonmin",
    "gn:population":0,
    "gn:timezone":"Asia/Yangon",
    "iso:country":"MM",
    "name:und_x_variant":[
        "Gonminta",
        "Gonmin"
    ],
    "wof:name":"Gonmin",
    "wof:placetype":"locality"
},
  "geometry": {"coordinates":[96.43089999999999,18.65491],"type":"Point"}
}