{
  "type": "Feature",
  "properties": {
    "gn:admin1_code":"4.0",
    "gn:admin2_code":"MMR001D001",
    "gn:admin3_code":"MMR001003",
    "gn:asciiname":"Chingma Ga",
    "gn:country_code":"MM",
    "gn:dem":955,
    "gn:feature_class":"P",
    "gn:feature_code":"PPL",
    "gn:name":"Chingma Ga",
    "gn:population":0,
    "gn:timezone":"Asia/Yangon",
    "iso:country":"MM",
    "wof:name":"Chingma Ga",
    "wof:placetype":"locality"
},
  "geometry": {"coordinates":[98.03907,26.17893],"type":"Point"}
}