{
  "type": "Feature",
  "properties": {
    "gn:admin1_code":"6.0",
    "gn:admin2_code":"MMR002D001",
    "gn:admin3_code":"MMR002002",
    "gn:asciiname":"Wan Loi-nanghpa",
    "gn:country_code":"MM",
    "gn:dem":944,
    "gn:feature_class":"P",
    "gn:feature_code":"PPL",
    "gn:name":"W\u0101n Loi-nanghpa",
    "gn:population":0,
    "gn:timezone":"Asia/Yangon",
    "iso:country":"MM",
    "wof:name":"Wan Loi-nanghpa",
    "wof:placetype":"locality"
},
  "geometry": {"coordinates":[97.07093999999999,19.59715],"type":"Point"}
}