{
  "type": "Feature",
  "properties": {
    "gn:admin1_code":"11.0",
    "gn:admin2_code":"MMR015D003",
    "gn:admin3_code":"MMR015014",
    "gn:asciiname":"Hsi-htawk",
    "gn:country_code":"MM",
    "gn:dem":878,
    "gn:feature_class":"P",
    "gn:feature_code":"PPL",
    "gn:name":"Hsi-htawk",
    "gn:population":0,
    "gn:timezone":"Asia/Yangon",
    "iso:country":"MM",
    "wof:name":"Hsi-htawk",
    "wof:placetype":"locality"
},
  "geometry": {"coordinates":[97.51909000000001,22.3347],"type":"Point"}
}