{
  "type": "Feature",
  "properties": {
    "gn:admin1_code":"11.0",
    "gn:admin2_code":"MMR014D003",
    "gn:admin3_code":"MMR014018",
    "gn:asciiname":"Wan Me-yup-yap",
    "gn:country_code":"MM",
    "gn:dem":952,
    "gn:feature_class":"P",
    "gn:feature_code":"PPL",
    "gn:name":"W\u0101n M\u00e8-y\u016bp-y\u0101p",
    "gn:population":0,
    "gn:timezone":"Asia/Yangon",
    "iso:country":"MM",
    "name:und_x_variant":[
        "W\u0101n M\u00e8-y\u0101p-yen",
        "W\u0101n M\u00e8-y\u016bp-y\u0101p"
    ],
    "wof:name":"Wan Me-yup-yap",
    "wof:placetype":"locality"
},
  "geometry": {"coordinates":[97.92180999999999,19.8612],"type":"Point"}
}