{
  "type": "Feature",
  "properties": {
    "gn:admin1_code":"16.0",
    "gn:admin2_code":"MMR007D001",
    "gn:admin3_code":"MMR007001",
    "gn:asciiname":"Alaingni-atet",
    "gn:country_code":"MM",
    "gn:dem":40,
    "gn:feature_class":"P",
    "gn:feature_code":"PPL",
    "gn:name":"Alaingni-atet",
    "gn:population":0,
    "gn:timezone":"Asia/Yangon",
    "iso:country":"MM",
    "name:und_x_variant":[
        "Alaingni",
        "Alaingni-atet"
    ],
    "wof:name":"Alaingni-atet",
    "wof:placetype":"locality"
},
  "geometry": {"coordinates":[96.37287999999999,17.30289],"type":"Point"}
}