{
  "type": "Feature",
  "properties": {
    "gn:admin1_code":"11.0",
    "gn:admin2_code":"MMR016D001",
    "gn:admin3_code":"MMR016007",
    "gn:asciiname":"Moeng Pu-awn",
    "gn:country_code":"MM",
    "gn:dem":720,
    "gn:feature_class":"P",
    "gn:feature_code":"PPL",
    "gn:name":"M\u00f6ng Pu-awn",
    "gn:population":0,
    "gn:timezone":"Asia/Yangon",
    "iso:country":"MM",
    "wof:name":"Moeng Pu-awn",
    "wof:placetype":"locality"
},
  "geometry": {"coordinates":[99.07783999999999,21.19033],"type":"Point"}
}