{
  "type": "Feature",
  "properties": {
    "gn:admin1_code":"11.0",
    "gn:admin2_code":"MMR014D003",
    "gn:admin3_code":"MMR014019",
    "gn:asciiname":"Wan Hkoe-nim",
    "gn:country_code":"MM",
    "gn:dem":708,
    "gn:feature_class":"P",
    "gn:feature_code":"PPL",
    "gn:name":"W\u0101n Hk\u00f6-nim",
    "gn:population":0,
    "gn:timezone":"Asia/Yangon",
    "iso:country":"MM",
    "wof:name":"Wan Hkoe-nim",
    "wof:placetype":"locality"
},
  "geometry": {"coordinates":[98.27795999999999,20.8651],"type":"Point"}
}