{
  "type": "Feature",
  "properties": {
    "gn:admin1_code":"5.0",
    "gn:admin2_code":"MMR003D002",
    "gn:admin3_code":"MMR003005",
    "gn:asciiname":"Ale Mekane",
    "gn:country_code":"MM",
    "gn:dem":217,
    "gn:feature_class":"P",
    "gn:feature_code":"PPL",
    "gn:name":"Al\u00e8 M\u00e8kane",
    "gn:population":0,
    "gn:timezone":"Asia/Yangon",
    "iso:country":"MM",
    "wof:name":"Ale Mekane",
    "wof:placetype":"locality"
},
  "geometry": {"coordinates":[98.41699,16.6667],"type":"Point"}
}