{
  "type": "Feature",
  "properties": {
    "gn:admin1_code":"3.0",
    "gn:admin2_code":"MMR017D002",
    "gn:admin3_code":"MMR017013",
    "gn:asciiname":"Magyibingwin",
    "gn:country_code":"MM",
    "gn:dem":43,
    "gn:feature_class":"P",
    "gn:feature_code":"PPL",
    "gn:name":"Magyibingwin",
    "gn:population":0,
    "gn:timezone":"Asia/Yangon",
    "iso:country":"MM",
    "wof:name":"Magyibingwin",
    "wof:placetype":"locality"
},
  "geometry": {"coordinates":[95.09486,17.89916000000001],"type":"Point"}
}