{
  "type": "Feature",
  "properties": {
    "gn:admin1_code":"8.0",
    "gn:admin2_code":"MMR010D007",
    "gn:admin3_code":"MMR010030",
    "gn:asciiname":"Kombamyin",
    "gn:country_code":"MM",
    "gn:dem":196,
    "gn:feature_class":"P",
    "gn:feature_code":"PPL",
    "gn:name":"Kombamyin",
    "gn:population":0,
    "gn:timezone":"Asia/Yangon",
    "iso:country":"MM",
    "wof:name":"Kombamyin",
    "wof:placetype":"locality"
},
  "geometry": {"coordinates":[95.95759,20.91019],"type":"Point"}
}