{
  "type": "Feature",
  "properties": {
    "gn:admin1_code":"13.0",
    "gn:admin2_code":"MMR011D001",
    "gn:admin3_code":"MMR011005",
    "gn:asciiname":"Kamaok",
    "gn:country_code":"MM",
    "gn:dem":10,
    "gn:feature_class":"P",
    "gn:feature_code":"PPL",
    "gn:name":"Kamaok",
    "gn:population":0,
    "gn:timezone":"Asia/Yangon",
    "iso:country":"MM",
    "wof:name":"Kamaok",
    "wof:placetype":"locality"
},
  "geometry": {"coordinates":[97.62564999999999,16.13122000000001],"type":"Point"}
}