{
  "type": "Feature",
  "properties": {
    "gn:admin1_code":"11.0",
    "gn:admin2_code":"MMR014D002",
    "gn:admin3_code":"MMR014013",
    "gn:asciiname":"Pangkullaklai",
    "gn:country_code":"MM",
    "gn:dem":1017,
    "gn:feature_class":"P",
    "gn:feature_code":"PPL",
    "gn:name":"Pangkullaklai",
    "gn:population":0,
    "gn:timezone":"Asia/Yangon",
    "iso:country":"MM",
    "name:und_x_variant":[
        "P\u0101ngkui-laklai",
        "Pangkullaklai"
    ],
    "wof:name":"Pangkullaklai",
    "wof:placetype":"locality"
},
  "geometry": {"coordinates":[97.62438,20.72802],"type":"Point"}
}