{
  "type": "Feature",
  "properties": {
    "gn:admin1_code":"3.0",
    "gn:admin2_code":"MMR017D002",
    "gn:admin3_code":"MMR017008",
    "gn:asciiname":"Migyaung-u",
    "gn:country_code":"MM",
    "gn:dem":15,
    "gn:feature_class":"P",
    "gn:feature_code":"PPL",
    "gn:name":"Migyaung-u",
    "gn:population":0,
    "gn:timezone":"Asia/Yangon",
    "iso:country":"MM",
    "wof:name":"Migyaung-u",
    "wof:placetype":"locality"
},
  "geometry": {"coordinates":[95.31171000000001,17.48387],"type":"Point"}
}