{
  "type": "Feature",
  "properties": {
    "gn:admin1_code":"4.0",
    "gn:admin2_code":"MMR001D001",
    "gn:admin3_code":"MMR001006",
    "gn:asciiname":"Mitlam",
    "gn:country_code":"MM",
    "gn:dem":1008,
    "gn:feature_class":"P",
    "gn:feature_code":"PPL",
    "gn:name":"Mitl\u0101m",
    "gn:population":0,
    "gn:timezone":"Asia/Yangon",
    "iso:country":"MM",
    "name:und_x_variant":[
        "Mitl\u0101m"
    ],
    "wof:name":"Mitlam",
    "wof:placetype":"locality"
},
  "geometry": {"coordinates":[98.31793,26.58362],"type":"Point"}
}