{
  "type": "Feature",
  "properties": {
    "gn:admin1_code":"11.0",
    "gn:admin2_code":"MMR014D001",
    "gn:admin3_code":"MMR014009",
    "gn:asciiname":"Pinkyain Ywathit",
    "gn:country_code":"MM",
    "gn:dem":1509,
    "gn:feature_class":"P",
    "gn:feature_code":"PPL",
    "gn:name":"Pinkyain Ywathit",
    "gn:population":0,
    "gn:timezone":"Asia/Yangon",
    "iso:country":"MM",
    "name:und_x_variant":[
        "Pinkyam Ywathit",
        "Pinkyain Ywathit"
    ],
    "wof:name":"Pinkyain Ywathit",
    "wof:placetype":"locality"
},
  "geometry": {"coordinates":[96.77871,20.03421],"type":"Point"}
}