{
  "type": "Feature",
  "properties": {
    "gn:admin1_code":"6.0",
    "gn:admin2_code":"MMR002D001",
    "gn:admin3_code":"MMR002002",
    "gn:asciiname":"Daw Ta-sa",
    "gn:country_code":"MM",
    "gn:dem":891,
    "gn:feature_class":"P",
    "gn:feature_code":"PPL",
    "gn:name":"Daw Ta-sa",
    "gn:population":0,
    "gn:timezone":"Asia/Yangon",
    "iso:country":"MM",
    "wof:name":"Daw Ta-sa",
    "wof:placetype":"locality"
},
  "geometry": {"coordinates":[97.12657,19.62168],"type":"Point"}
}