{
  "type": "Feature",
  "properties": {
    "gn:admin1_code":"10.0",
    "gn:admin2_code":"MMR005D002",
    "gn:admin3_code":"MMR005008",
    "gn:asciiname":"Mawke",
    "gn:country_code":"MM",
    "gn:dem":224,
    "gn:feature_class":"P",
    "gn:feature_code":"PPL",
    "gn:name":"Mawke",
    "gn:population":0,
    "gn:timezone":"Asia/Yangon",
    "iso:country":"MM",
    "wof:name":"Mawke",
    "wof:placetype":"locality"
},
  "geometry": {"coordinates":[95.06093,23.4572],"type":"Point"}
}