{
  "type": "Feature",
  "properties": {
    "gn:admin1_code":"10.0",
    "gn:admin2_code":"MMR005D008",
    "gn:admin3_code":"MMR005037",
    "gn:asciiname":"Hpachet Hi",
    "gn:country_code":"MM",
    "gn:dem":913,
    "gn:feature_class":"P",
    "gn:feature_code":"PPL",
    "gn:name":"Hp\u0101chet Hi",
    "gn:population":0,
    "gn:timezone":"Asia/Yangon",
    "iso:country":"MM",
    "wof:name":"Hpachet Hi",
    "wof:placetype":"locality"
},
  "geometry": {"coordinates":[95.91137000000001,26.92731],"type":"Point"}
}