{
  "type": "Feature",
  "properties": {
    "gn:admin1_code":"8.0",
    "gn:admin2_code":"MMR010D002",
    "gn:admin3_code":"MMR010009",
    "gn:asciiname":"Setzaw",
    "gn:country_code":"MM",
    "gn:dem":94,
    "gn:feature_class":"P",
    "gn:feature_code":"PPL",
    "gn:name":"Setzaw",
    "gn:population":0,
    "gn:timezone":"Asia/Yangon",
    "iso:country":"MM",
    "wof:name":"Setzaw",
    "wof:placetype":"locality"
},
  "geometry": {"coordinates":[96.19781999999999,22.2322],"type":"Point"}
}