{
  "type": "Feature",
  "properties": {
    "gn:admin1_code":"11.0",
    "gn:admin2_code":"MMR014D001",
    "gn:admin3_code":"MMR014007",
    "gn:asciiname":"Myazedi",
    "gn:country_code":"MM",
    "gn:dem":1299,
    "gn:feature_class":"P",
    "gn:feature_code":"PPL",
    "gn:name":"Myazedi",
    "gn:population":0,
    "gn:timezone":"Asia/Yangon",
    "iso:country":"MM",
    "name:urd_x_preferred":[
        "\u0645\u06cc\u0627\u0632\u06cc\u062f\u06cc"
    ],
    "wof:name":"Myazedi",
    "wof:placetype":"locality"
},
  "geometry": {"coordinates":[96.5299,21.09754],"type":"Point"}
}