{
  "type": "Feature",
  "properties": {
    "gn:admin1_code":"3.0",
    "gn:admin2_code":"MMR017D005",
    "gn:admin3_code":"MMR017019",
    "gn:asciiname":"Inte-atwinywa",
    "gn:country_code":"MM",
    "gn:dem":7,
    "gn:feature_class":"P",
    "gn:feature_code":"PPL",
    "gn:name":"Inte-atwinywa",
    "gn:population":0,
    "gn:timezone":"Asia/Yangon",
    "iso:country":"MM",
    "name:und_x_variant":[
        "Inteywa",
        "Inte-atwinywa"
    ],
    "wof:name":"Inte-atwinywa",
    "wof:placetype":"locality"
},
  "geometry": {"coordinates":[95.50584000000001,16.77993],"type":"Point"}
}