{
  "type": "Feature",
  "properties": {
    "gn:admin1_code":"3.0",
    "gn:admin2_code":"MMR017D002",
    "gn:admin3_code":"MMR017013",
    "gn:asciiname":"Gyibaukkon",
    "gn:country_code":"MM",
    "gn:dem":24,
    "gn:feature_class":"P",
    "gn:feature_code":"PPL",
    "gn:name":"Gyibaukkon",
    "gn:population":0,
    "gn:timezone":"Asia/Yangon",
    "iso:country":"MM",
    "wof:name":"Gyibaukkon",
    "wof:placetype":"locality"
},
  "geometry": {"coordinates":[95.27012000000001,17.77592000000001],"type":"Point"}
}