{
  "type": "Feature",
  "properties": {
    "gn:admin1_code":"11.0",
    "gn:admin2_code":"MMR014D001",
    "gn:admin3_code":"MMR014007",
    "gn:asciiname":"Peinnegon",
    "gn:country_code":"MM",
    "gn:dem":1079,
    "gn:feature_class":"P",
    "gn:feature_code":"PPL",
    "gn:name":"Peinnegon",
    "gn:population":0,
    "gn:timezone":"Asia/Yangon",
    "iso:country":"MM",
    "wof:name":"Peinnegon",
    "wof:placetype":"locality"
},
  "geometry": {"coordinates":[96.46261,21.07969],"type":"Point"}
}