{
  "type": "Feature",
  "properties": {
    "gn:admin1_code":"11.0",
    "gn:admin2_code":"MMR014D001",
    "gn:admin3_code":"MMR014002",
    "gn:asciiname":"Konzon",
    "gn:country_code":"MM",
    "gn:dem":1458,
    "gn:feature_class":"P",
    "gn:feature_code":"PPL",
    "gn:name":"Konzon",
    "gn:population":0,
    "gn:timezone":"Asia/Yangon",
    "iso:country":"MM",
    "wof:name":"Konzon",
    "wof:placetype":"locality"
},
  "geometry": {"coordinates":[96.99135,20.61995],"type":"Point"}
}