{
  "type": "Feature",
  "properties": {
    "gn:admin1_code":"11.0",
    "gn:admin2_code":"MMR016D001",
    "gn:admin3_code":"MMR016007",
    "gn:asciiname":"Wan Nawnghkai",
    "gn:country_code":"MM",
    "gn:dem":427,
    "gn:feature_class":"P",
    "gn:feature_code":"PPL",
    "gn:name":"W\u0101n Nawnghkai",
    "gn:population":0,
    "gn:timezone":"Asia/Yangon",
    "iso:country":"MM",
    "wof:name":"Wan Nawnghkai",
    "wof:placetype":"locality"
},
  "geometry": {"coordinates":[98.98538000000001,21.45503],"type":"Point"}
}