{
  "type": "Feature",
  "properties": {
    "gn:admin1_code":"8.0",
    "gn:admin2_code":"MMR010D004",
    "gn:admin3_code":"MMR010018",
    "gn:asciiname":"Nyaunggon",
    "gn:country_code":"MM",
    "gn:dem":196,
    "gn:feature_class":"P",
    "gn:feature_code":"PPL",
    "gn:name":"Nyaunggon",
    "gn:population":0,
    "gn:timezone":"Asia/Yangon",
    "iso:country":"MM",
    "wof:name":"Nyaunggon",
    "wof:placetype":"locality"
},
  "geometry": {"coordinates":[95.49001,21.18102],"type":"Point"}
}