{
  "type": "Feature",
  "properties": {
    "gn:admin1_code":"1.0",
    "gn:admin2_code":"MMR012D004",
    "gn:admin3_code":"MMR012015",
    "gn:asciiname":"Gwedaukkon",
    "gn:country_code":"MM",
    "gn:dem":12,
    "gn:feature_class":"P",
    "gn:feature_code":"PPL",
    "gn:name":"Gwedaukk\u00f4n",
    "gn:population":0,
    "gn:timezone":"Asia/Yangon",
    "iso:country":"MM",
    "wof:name":"Gwedaukkon",
    "wof:placetype":"locality"
},
  "geometry": {"coordinates":[94.44289999999999,18.44392],"type":"Point"}
}