{
  "type": "Feature",
  "properties": {
    "gn:admin1_code":"8.0",
    "gn:admin2_code":"MMR010D005",
    "gn:admin3_code":"MMR010022",
    "gn:asciiname":"Myene",
    "gn:country_code":"MM",
    "gn:dem":96,
    "gn:feature_class":"P",
    "gn:feature_code":"PPL",
    "gn:name":"Myene",
    "gn:population":0,
    "gn:timezone":"Asia/Yangon",
    "iso:country":"MM",
    "wof:name":"Myene",
    "wof:placetype":"locality"
},
  "geometry": {"coordinates":[94.91658,21.17871],"type":"Point"}
}