{
  "type": "Feature",
  "properties": {
    "gn:admin1_code":"11.0",
    "gn:admin2_code":"MMR014D003",
    "gn:admin3_code":"MMR014020",
    "gn:asciiname":"Komka",
    "gn:country_code":"MM",
    "gn:dem":1211,
    "gn:feature_class":"P",
    "gn:feature_code":"PPL",
    "gn:name":"Komka",
    "gn:population":0,
    "gn:timezone":"Asia/Yangon",
    "iso:country":"MM",
    "wof:name":"Komka",
    "wof:placetype":"locality"
},
  "geometry": {"coordinates":[97.5068,20.31145],"type":"Point"}
}