{
  "type": "Feature",
  "properties": {
    "gn:admin1_code":"3.0",
    "gn:admin2_code":"MMR017D006",
    "gn:admin3_code":"MMR017024",
    "gn:asciiname":"Tawbaingzu",
    "gn:country_code":"MM",
    "gn:dem":3,
    "gn:feature_class":"P",
    "gn:feature_code":"PPL",
    "gn:name":"Tawbaingzu",
    "gn:population":0,
    "gn:timezone":"Asia/Yangon",
    "iso:country":"MM",
    "wof:name":"Tawbaingzu",
    "wof:placetype":"locality"
},
  "geometry": {"coordinates":[95.47526999999999,15.99619],"type":"Point"}
}