{
  "type": "Feature",
  "properties": {
    "gn:admin1_code":"11.0",
    "gn:admin2_code":"MMR015D005",
    "gn:admin3_code":"MMR015023",
    "gn:asciiname":"Kya-hsu-wa",
    "gn:country_code":"MM",
    "gn:dem":1561,
    "gn:feature_class":"P",
    "gn:feature_code":"PPL",
    "gn:name":"Kya-hsu-wa",
    "gn:population":0,
    "gn:timezone":"Asia/Yangon",
    "iso:country":"MM",
    "wof:name":"Kya-hsu-wa",
    "wof:placetype":"locality"
},
  "geometry": {"coordinates":[98.44553000000001,23.94266],"type":"Point"}
}