{
  "type": "Feature",
  "properties": {
    "gn:admin1_code":"10.0",
    "gn:admin2_code":"MMR005D005",
    "gn:admin3_code":"MMR005029",
    "gn:asciiname":"Ongwe Zayat",
    "gn:country_code":"MM",
    "gn:dem":240,
    "gn:feature_class":"P",
    "gn:feature_code":"PPL",
    "gn:name":"Ongwe Zayat",
    "gn:population":0,
    "gn:timezone":"Asia/Yangon",
    "iso:country":"MM",
    "wof:name":"Ongwe Zayat",
    "wof:placetype":"locality"
},
  "geometry": {"coordinates":[94.42478,22.78941],"type":"Point"}
}