{
  "type": "Feature",
  "properties": {
    "gn:admin1_code":"13.0",
    "gn:admin2_code":"MMR011D002",
    "gn:admin3_code":"MMR011009",
    "gn:asciiname":"Kanyinchaung",
    "gn:country_code":"MM",
    "gn:dem":33,
    "gn:feature_class":"P",
    "gn:feature_code":"PPL",
    "gn:name":"Kanyinchaung",
    "gn:population":0,
    "gn:timezone":"Asia/Yangon",
    "iso:country":"MM",
    "wof:name":"Kanyinchaung",
    "wof:placetype":"locality"
},
  "geometry": {"coordinates":[97.10760000000001,17.32561],"type":"Point"}
}