{
  "type": "Feature",
  "properties": {
    "gn:admin1_code":"15.0",
    "gn:admin2_code":"MMR009D001",
    "gn:admin3_code":"MMR009002",
    "gn:asciiname":"Kyungyaunggyi",
    "gn:country_code":"MM",
    "gn:dem":151,
    "gn:feature_class":"P",
    "gn:feature_code":"PPL",
    "gn:name":"Kyungyaunggyi",
    "gn:population":0,
    "gn:timezone":"Asia/Yangon",
    "iso:country":"MM",
    "name:und_x_variant":[
        "Kyungyaung",
        "Kyungyaunggyi"
    ],
    "wof:name":"Kyungyaunggyi",
    "wof:placetype":"locality"
},
  "geometry": {"coordinates":[95.0639,20.3628],"type":"Point"}
}