{
  "type": "Feature",
  "properties": {
    "gn:admin1_code":"18.0",
    "gn:admin2_code":"MMR018D002",
    "gn:admin3_code":"MMR018007",
    "gn:asciiname":"Yebyayo",
    "gn:country_code":"MM",
    "gn:dem":120,
    "gn:feature_class":"P",
    "gn:feature_code":"PPL",
    "gn:name":"Yebyayo",
    "gn:population":0,
    "gn:timezone":"Asia/Yangon",
    "iso:country":"MM",
    "wof:name":"Yebyayo",
    "wof:placetype":"locality"
},
  "geometry": {"coordinates":[96.11749,19.55007],"type":"Point"}
}