{
  "type": "Feature",
  "properties": {
    "gn:admin1_code":"12.0",
    "gn:asciiname":"Yengangyi",
    "gn:country_code":"MM",
    "gn:dem":7,
    "gn:feature_class":"P",
    "gn:feature_code":"PPL",
    "gn:name":"Yengangyi",
    "gn:population":0,
    "gn:timezone":"Asia/Yangon",
    "iso:country":"MM",
    "wof:name":"Yengangyi",
    "wof:placetype":"locality"
},
  "geometry": {"coordinates":[98.76403999999999,11.46234],"type":"Point"}
}