{
  "type": "Feature",
  "properties": {
    "gn:admin1_code":"10.0",
    "gn:admin2_code":"MMR005D008",
    "gn:admin3_code":"MMR005033",
    "gn:asciiname":"Zu Mawlaw",
    "gn:country_code":"MM",
    "gn:dem":1049,
    "gn:feature_class":"P",
    "gn:feature_code":"PPL",
    "gn:name":"Zu Mawlaw",
    "gn:population":0,
    "gn:timezone":"Asia/Yangon",
    "iso:country":"MM",
    "wof:name":"Zu Mawlaw",
    "wof:placetype":"locality"
},
  "geometry": {"coordinates":[95.29792999999999,25.96748],"type":"Point"}
}