{
  "type": "Feature",
  "properties": {
    "gn:admin1_code":"11.0",
    "gn:admin2_code":"MMR014D003",
    "gn:admin3_code":"MMR014019",
    "gn:asciiname":"Wan Tu-hsaw",
    "gn:country_code":"MM",
    "gn:dem":640,
    "gn:feature_class":"P",
    "gn:feature_code":"PPL",
    "gn:name":"W\u00e3n Tu-hsaw",
    "gn:population":0,
    "gn:timezone":"Asia/Yangon",
    "iso:country":"MM",
    "wof:name":"Wan Tu-hsaw",
    "wof:placetype":"locality"
},
  "geometry": {"coordinates":[98.31854,20.73597],"type":"Point"}
}