{
  "type": "Feature",
  "properties": {
    "gn:admin1_code":"11.0",
    "gn:admin2_code":"MMR014D003",
    "gn:admin3_code":"MMR014019",
    "gn:asciiname":"Wan Hsenhkuenkiao",
    "gn:country_code":"MM",
    "gn:dem":1117,
    "gn:feature_class":"P",
    "gn:feature_code":"PPL",
    "gn:name":"W\u0101n Hsenhk\u00fcnkiao",
    "gn:population":0,
    "gn:timezone":"Asia/Yangon",
    "iso:country":"MM",
    "wof:name":"Wan Hsenhkuenkiao",
    "wof:placetype":"locality"
},
  "geometry": {"coordinates":[98.25,20.83333],"type":"Point"}
}