{
  "type": "Feature",
  "properties": {
    "gn:admin1_code":"16.0",
    "gn:admin2_code":"MMR007D002",
    "gn:admin3_code":"MMR007011",
    "gn:asciiname":"Kamuthi",
    "gn:country_code":"MM",
    "gn:dem":961,
    "gn:feature_class":"P",
    "gn:feature_code":"PPL",
    "gn:name":"Kamuthi",
    "gn:population":0,
    "gn:timezone":"Asia/Yangon",
    "iso:country":"MM",
    "name:bpy_x_preferred":[
        "\u0995\u09be\u09ae\u0989\u09a5\u09bf"
    ],
    "name:ceb_x_preferred":[
        "Kamuthi"
    ],
    "name:ita_x_preferred":[
        "Kamuthi"
    ],
    "name:msa_x_preferred":[
        "Kamuthi"
    ],
    "name:new_x_preferred":[
        "\u0915\u092e\u0941\u0925\u0940"
    ],
    "name:nld_x_preferred":[
        "Kamuthi"
    ],
    "name:por_x_preferred":[
        "Kamuthi"
    ],
    "name:swe_x_preferred":[
        "Kamuthi"
    ],
    "name:tam_x_preferred":[
        "\u0b95\u0bae\u0bc1\u0ba4\u0bbf"
    ],
    "name:vie_x_preferred":[
        "Kamuthi"
    ],
    "name:zho_x_preferred":[
        "\u5361\u7a46\u8482"
    ],
    "wof:name":"Kamuthi",
    "wof:placetype":"locality"
},
  "geometry": {"coordinates":[97.00277,18.29009],"type":"Point"}
}