{
  "type": "Feature",
  "properties": {
    "iso:country":"MM",
    "name:eng_x_preferred":[
        "Aungban"
    ],
    "name:mya_x_preferred":[
        "\u1021\u1031\u102c\u1004\u103a\u1015\u1014\u103a\u1038\u1019\u103c\u102d\u102f\u1037"
    ],
    "name:nld_x_preferred":[
        "Aungban"
    ],
    "name:por_x_preferred":[
        "Aungban"
    ],
    "name:shn_x_preferred":[
        "\u1022\u102f\u1019\u103a\u1087\u1015\u101d\u103a\u1038"
    ],
    "name:tgl_x_preferred":[
        "Aungban"
    ],
    "name:zho_x_preferred":[
        "\u6602\u73ed"
    ],
    "qs:gn_country":"MM",
    "qs:gn_fcode":"PPL",
    "qs:gn_pop":0,
    "qs:name":"Aungban",
    "qs:name_adm0":"Myanmar",
    "qs:name_adm1":"Shan State",
    "qs:photos":270,
    "qs:photos_1k":55,
    "qs:photos_9k":1,
    "qs:photos_9r":4,
    "qs:photos_all":270,
    "qs:photos_sr":5,
    "qs:placetype":"Town",
    "qs:pop_sr":"5",
    "qs:woe_adm0":23424763,
    "wd:wordcount":69,
    "wof:name":"Aungban",
    "wof:placetype":"locality"
},
  "geometry": {"coordinates":[96.63488,20.6606],"type":"Point"}
}