{
  "type": "Feature",
  "properties": {
    "gn:admin1_code":"10.0",
    "gn:admin2_code":"MMR005D002",
    "gn:admin3_code":"MMR005009",
    "gn:asciiname":"Wunbye",
    "gn:country_code":"MM",
    "gn:dem":118,
    "gn:feature_class":"P",
    "gn:feature_code":"PPL",
    "gn:name":"Wunbye",
    "gn:population":0,
    "gn:timezone":"Asia/Yangon",
    "iso:country":"MM",
    "wof:name":"Wunbye",
    "wof:placetype":"locality"
},
  "geometry": {"coordinates":[95.28870999999999,22.74031],"type":"Point"}
}