{
  "type": "Feature",
  "properties": {
    "gn:admin1_code":"16.0",
    "gn:admin2_code":"MMR008D001",
    "gn:admin3_code":"MMR008002",
    "gn:asciiname":"Lelu",
    "gn:country_code":"MM",
    "gn:dem":148,
    "gn:feature_class":"P",
    "gn:feature_code":"PPL",
    "gn:name":"Lelu",
    "gn:population":0,
    "gn:timezone":"Asia/Yangon",
    "iso:country":"MM",
    "wof:name":"Lelu",
    "wof:placetype":"locality"
},
  "geometry": {"coordinates":[95.50673999999999,19.06599],"type":"Point"}
}