{
  "type": "Feature",
  "properties": {
    "gn:admin1_code":"15.0",
    "gn:admin2_code":"MMR009D004",
    "gn:admin3_code":"MMR009020",
    "gn:asciiname":"Wagan",
    "gn:country_code":"MM",
    "gn:dem":186,
    "gn:feature_class":"P",
    "gn:feature_code":"PPL",
    "gn:name":"Wagan",
    "gn:population":0,
    "gn:timezone":"Asia/Yangon",
    "iso:country":"MM",
    "name:fra_x_preferred":[
        "Wagan"
    ],
    "name:pol_x_preferred":[
        "Wagan"
    ],
    "name:ukr_x_preferred":[
        "\u0412\u0430\u0491\u0430\u043d"
    ],
    "wof:name":"Wagan",
    "wof:placetype":"locality"
},
  "geometry": {"coordinates":[95.02966000000001,21.53429],"type":"Point"}
}