{
  "type": "Feature",
  "properties": {
    "gn:admin1_code":"11.0",
    "gn:admin2_code":"MMR014D002",
    "gn:admin3_code":"MMR014013",
    "gn:asciiname":"Wan Long",
    "gn:country_code":"MM",
    "gn:dem":1014,
    "gn:feature_class":"P",
    "gn:feature_code":"PPL",
    "gn:name":"W\u0101n Long",
    "gn:population":0,
    "gn:timezone":"Asia/Yangon",
    "iso:country":"MM",
    "name:und_x_variant":[
        "Long",
        "W\u0101n Long"
    ],
    "wof:name":"Wan Long",
    "wof:placetype":"locality"
},
  "geometry": {"coordinates":[97.5748,20.78782],"type":"Point"}
}