{
  "type": "Feature",
  "properties": {
    "gn:admin1_code":"3.0",
    "gn:admin2_code":"MMR017D001",
    "gn:admin3_code":"MMR017005",
    "gn:asciiname":"Yottha",
    "gn:country_code":"MM",
    "gn:dem":16,
    "gn:feature_class":"P",
    "gn:feature_code":"PPL",
    "gn:name":"Yottha",
    "gn:population":0,
    "gn:timezone":"Asia/Yangon",
    "iso:country":"MM",
    "wof:name":"Yottha",
    "wof:placetype":"locality"
},
  "geometry": {"coordinates":[95.23465,17.37194],"type":"Point"}
}