{
  "type": "Feature",
  "properties": {
    "gn:admin1_code":"15.0",
    "gn:admin2_code":"MMR009D004",
    "gn:admin3_code":"MMR009018",
    "gn:asciiname":"Leya",
    "gn:country_code":"MM",
    "gn:dem":69,
    "gn:feature_class":"P",
    "gn:feature_code":"PPL",
    "gn:name":"Leya",
    "gn:population":0,
    "gn:timezone":"Asia/Yangon",
    "iso:country":"MM",
    "name:deu_x_preferred":[
        "Leya"
    ],
    "wof:name":"Leya",
    "wof:placetype":"locality"
},
  "geometry": {"coordinates":[95.02399,21.32926],"type":"Point"}
}