{
  "type": "Feature",
  "properties": {
    "gn:admin1_code":"11.0",
    "gn:admin2_code":"MMR015D002",
    "gn:admin3_code":"MMR015009",
    "gn:asciiname":"Kawngsong",
    "gn:country_code":"MM",
    "gn:dem":1723,
    "gn:feature_class":"P",
    "gn:feature_code":"PPL",
    "gn:name":"Kawngsong",
    "gn:population":0,
    "gn:timezone":"Asia/Yangon",
    "iso:country":"MM",
    "wof:name":"Kawngsong",
    "wof:placetype":"locality"
},
  "geometry": {"coordinates":[98.2064,23.96108],"type":"Point"}
}