{
  "type": "Feature",
  "properties": {
    "gn:admin1_code":"10.0",
    "gn:admin2_code":"MMR005D002",
    "gn:admin3_code":"MMR005011",
    "gn:asciiname":"Ngapyawdaw",
    "gn:country_code":"MM",
    "gn:dem":146,
    "gn:feature_class":"P",
    "gn:feature_code":"PPL",
    "gn:name":"Ngapyawdaw",
    "gn:population":0,
    "gn:timezone":"Asia/Yangon",
    "iso:country":"MM",
    "name:und_x_variant":[
        "Hngetpyawdaw",
        "Ngapyawdaw"
    ],
    "wof:name":"Ngapyawdaw",
    "wof:placetype":"locality"
},
  "geometry": {"coordinates":[95.32068,23.06043],"type":"Point"}
}