{
  "type": "Feature",
  "properties": {
    "gn:admin1_code":"11.0",
    "gn:admin2_code":"MMR014D002",
    "gn:admin3_code":"MMR014014",
    "gn:asciiname":"Wan Maw-loi-ho",
    "gn:country_code":"MM",
    "gn:dem":829,
    "gn:feature_class":"P",
    "gn:feature_code":"PPL",
    "gn:name":"W\u0101n Maw-loi-ho",
    "gn:population":0,
    "gn:timezone":"Asia/Yangon",
    "iso:country":"MM",
    "name:und_x_variant":[
        "W\u0101n Mau-loi-h\u00f6",
        "W\u0101n Maw-loi-ho"
    ],
    "wof:name":"Wan Maw-loi-ho",
    "wof:placetype":"locality"
},
  "geometry": {"coordinates":[98.61499999999999,21.21366],"type":"Point"}
}