{
  "type": "Feature",
  "properties": {
    "gn:admin1_code":"4.0",
    "gn:admin2_code":"MMR001D001",
    "gn:admin3_code":"MMR001004",
    "gn:asciiname":"'Nhkang Kayang Ga",
    "gn:country_code":"MM",
    "gn:dem":240,
    "gn:feature_class":"P",
    "gn:feature_code":"PPL",
    "gn:name":"\u2019Nhkang Kayang Ga",
    "gn:population":0,
    "gn:timezone":"Asia/Yangon",
    "iso:country":"MM",
    "name:und_x_variant":[
        "\u2019Nhkang Kayang",
        "\u2019Nhkang Kayang Ga"
    ],
    "wof:name":"'Nhkang Kayang Ga",
    "wof:placetype":"locality"
},
  "geometry": {"coordinates":[96.68944999999999,26.54762],"type":"Point"}
}