{
  "type": "Feature",
  "properties": {
    "gn:admin1_code":"12.0",
    "gn:admin2_code":"MMR006D003",
    "gn:admin3_code":"MMR006009",
    "gn:asciiname":"Ban Kamou",
    "gn:country_code":"MM",
    "gn:dem":12,
    "gn:feature_class":"P",
    "gn:feature_code":"PPL",
    "gn:name":"B\u0101n Kamou",
    "gn:population":0,
    "gn:timezone":"Asia/Yangon",
    "iso:country":"MM",
    "name:und_x_variant":[
        "Kamou",
        "B\u0101n Kamou"
    ],
    "wof:name":"Ban Kamou",
    "wof:placetype":"locality"
},
  "geometry": {"coordinates":[98.62641000000001,10.35828],"type":"Point"}
}