{
  "type": "Feature",
  "properties": {
    "gn:admin1_code":"15.0",
    "gn:admin2_code":"MMR009D003",
    "gn:admin3_code":"MMR009013",
    "gn:asciiname":"Kokko",
    "gn:country_code":"MM",
    "gn:dem":254,
    "gn:feature_class":"P",
    "gn:feature_code":"PPL",
    "gn:name":"Kokko",
    "gn:population":0,
    "gn:timezone":"Asia/Yangon",
    "iso:country":"MM",
    "name:ceb_x_preferred":[
        "Kokko"
    ],
    "name:deu_x_preferred":[
        "Kokko"
    ],
    "name:fin_x_preferred":[
        "Kokko"
    ],
    "name:rus_x_preferred":[
        "\u041a\u043e\u043a\u043a\u043e"
    ],
    "name:swe_x_preferred":[
        "Kokko"
    ],
    "wof:name":"Kokko",
    "wof:placetype":"locality"
},
  "geometry": {"coordinates":[94.84,19.74129],"type":"Point"}
}