{
  "type": "Feature",
  "properties": {
    "gn:admin1_code":"10.0",
    "gn:admin2_code":"MMR005D001",
    "gn:admin3_code":"MMR005001",
    "gn:asciiname":"Mingun",
    "gn:country_code":"MM",
    "gn:dem":79,
    "gn:feature_class":"P",
    "gn:feature_code":"PPL",
    "gn:name":"Mingun",
    "gn:population":400,
    "gn:timezone":"Asia/Yangon",
    "iso:country":"MM",
    "name:cat_x_preferred":[
        "Mingun"
    ],
    "name:deu_x_preferred":[
        "Mingun"
    ],
    "name:mya_x_preferred":[
        "\u1019\u1004\u103a\u1038\u1000\u103d\u1014\u103a\u1038\u1019\u103c\u102d\u102f\u1037"
    ],
    "name:rus_x_preferred":[
        "\u041c\u0438\u043d\u0433\u0443\u043d"
    ],
    "name:swe_x_preferred":[
        "Mingun"
    ],
    "wof:name":"Mingun",
    "wof:placetype":"locality",
    "wof:population":400
},
  "geometry": {"coordinates":[96.01975,22.04197000000001],"type":"Point"}
}