{
  "type": "Feature",
  "properties": {
    "gn:admin1_code":"10.0",
    "gn:admin2_code":"MMR005D009",
    "gn:admin3_code":"MMR005017",
    "gn:asciiname":"Sulegon",
    "gn:country_code":"MM",
    "gn:dem":104,
    "gn:feature_class":"P",
    "gn:feature_code":"PPL",
    "gn:name":"Sul\u00e8g\u00f4n",
    "gn:population":0,
    "gn:timezone":"Asia/Yangon",
    "iso:country":"MM",
    "wof:name":"Sulegon",
    "wof:placetype":"locality"
},
  "geometry": {"coordinates":[94.88963,22.48354],"type":"Point"}
}