{
  "type": "Feature",
  "properties": {
    "gn:admin1_code":"4.0",
    "gn:admin2_code":"MMR001D001",
    "gn:admin3_code":"MMR001002",
    "gn:asciiname":"Loingu",
    "gn:country_code":"MM",
    "gn:dem":397,
    "gn:feature_class":"P",
    "gn:feature_code":"PPL",
    "gn:name":"Loingu",
    "gn:population":0,
    "gn:timezone":"Asia/Yangon",
    "iso:country":"MM",
    "wof:name":"Loingu",
    "wof:placetype":"locality"
},
  "geometry": {"coordinates":[97.77925,25.55811],"type":"Point"}
}