{
  "type": "Feature",
  "properties": {
    "gn:admin1_code":"11.0",
    "gn:admin2_code":"MMR016D001",
    "gn:admin3_code":"MMR016005",
    "gn:asciiname":"Wan Pung",
    "gn:country_code":"MM",
    "gn:dem":726,
    "gn:feature_class":"P",
    "gn:feature_code":"PPL",
    "gn:name":"W\u0101n P\u016bng",
    "gn:population":0,
    "gn:timezone":"Asia/Yangon",
    "iso:country":"MM",
    "wof:name":"Wan Pung",
    "wof:placetype":"locality"
},
  "geometry": {"coordinates":[99.87917,21.58476],"type":"Point"}
}