{
  "type": "Feature",
  "properties": {
    "gn:admin1_code":"6.0",
    "gn:admin2_code":"MMR002D001",
    "gn:admin3_code":"MMR002003",
    "gn:asciiname":"Biya",
    "gn:country_code":"MM",
    "gn:dem":1338,
    "gn:feature_class":"P",
    "gn:feature_code":"PPL",
    "gn:name":"Biya",
    "gn:population":0,
    "gn:timezone":"Asia/Yangon",
    "iso:country":"MM",
    "name:ceb_x_preferred":[
        "Biya"
    ],
    "name:deu_x_preferred":[
        "Biya"
    ],
    "name:fra_x_preferred":[
        "Biya"
    ],
    "name:swe_x_preferred":[
        "Biya"
    ],
    "name:uzb_x_preferred":[
        "Biya"
    ],
    "wof:name":"Biya",
    "wof:placetype":"locality"
},
  "geometry": {"coordinates":[96.97402,19.35754],"type":"Point"}
}