{
  "type": "Feature",
  "properties": {
    "gn:admin1_code":"6.0",
    "gn:admin2_code":"MMR002D001",
    "gn:admin3_code":"MMR002003",
    "gn:asciiname":"Biya",
    "gn:country_code":"MM",
    "gn:dem":1338,
    "gn:feature_class":"P",
    "gn:feature_code":"PPL",
    "gn:name":"Biya",
    "gn:population":0,
    "gn:timezone":"Asia/Yangon",
    "iso:country":"MM",
    "name:ara_x_preferred":[
        "\u0628\u064a\u0627"
    ],
    "name:ceb_x_preferred":[
        "Biya"
    ],
    "name:deu_x_preferred":[
        "Biya"
    ],
    "name:ell_x_preferred":[
        "\u039c\u03c0\u03af\u03b3\u03b9\u03b1"
    ],
    "name:fra_x_preferred":[
        "Biya"
    ],
    "name:heb_x_preferred":[
        "\u05d1\u05d9\u05d4"
    ],
    "name:ind_x_preferred":[
        "Biya"
    ],
    "name:por_x_preferred":[
        "Biya"
    ],
    "name:swe_x_preferred":[
        "Bija"
    ],
    "name:swe_x_variant":[
        "Biya"
    ],
    "name:urd_x_preferred":[
        "\u0628\u06cc\u0627"
    ],
    "name:uzb_x_preferred":[
        "Biya"
    ],
    "name:vie_x_preferred":[
        "S\u00f4ng Biya"
    ],
    "wof:name":"Biya",
    "wof:placetype":"locality"
},
  "geometry": {"coordinates":[96.97402,19.35754],"type":"Point"}
}