{
  "type": "Feature",
  "properties": {
    "gn:admin1_code":"3.0",
    "gn:admin2_code":"MMR017D005",
    "gn:admin3_code":"MMR017022",
    "gn:asciiname":"Chaungzauk",
    "gn:country_code":"MM",
    "gn:dem":17,
    "gn:feature_class":"P",
    "gn:feature_code":"PPL",
    "gn:name":"Chaungzauk",
    "gn:population":0,
    "gn:timezone":"Asia/Yangon",
    "iso:country":"MM",
    "wof:name":"Chaungzauk",
    "wof:placetype":"locality"
},
  "geometry": {"coordinates":[95.62748999999999,17.30027],"type":"Point"}
}