{
  "type": "Feature",
  "properties": {
    "gn:admin1_code":"4.0",
    "gn:admin2_code":"MMR001D001",
    "gn:admin3_code":"MMR001005",
    "gn:asciiname":"Pawzang",
    "gn:country_code":"MM",
    "gn:dem":1756,
    "gn:feature_class":"P",
    "gn:feature_code":"PPL",
    "gn:name":"Pawzang",
    "gn:population":0,
    "gn:timezone":"Asia/Yangon",
    "iso:country":"MM",
    "wof:name":"Pawzang",
    "wof:placetype":"locality"
},
  "geometry": {"coordinates":[98.22772000000001,25.7977],"type":"Point"}
}