{
  "type": "Feature",
  "properties": {
    "gn:admin1_code":"8.0",
    "gn:admin2_code":"MMR010D003",
    "gn:admin3_code":"MMR010013",
    "gn:asciiname":"Mezebin",
    "gn:country_code":"MM",
    "gn:dem":92,
    "gn:feature_class":"P",
    "gn:feature_code":"PPL",
    "gn:name":"Mezebin",
    "gn:population":0,
    "gn:timezone":"Asia/Yangon",
    "iso:country":"MM",
    "wof:name":"Mezebin",
    "wof:placetype":"locality"
},
  "geometry": {"coordinates":[96.12069,21.61124],"type":"Point"}
}