{
  "type": "Feature",
  "properties": {
    "gn:admin1_code":"13.0",
    "gn:admin2_code":"MMR011D001",
    "gn:admin3_code":"MMR011005",
    "gn:asciiname":"Kalawthut",
    "gn:country_code":"MM",
    "gn:dem":23,
    "gn:feature_class":"P",
    "gn:feature_code":"PPL",
    "gn:name":"Kalawthut",
    "gn:population":0,
    "gn:timezone":"Asia/Yangon",
    "iso:country":"MM",
    "name:und_x_variant":[
        "Hpankala",
        "Kalawthut"
    ],
    "wof:name":"Kalawthut",
    "wof:placetype":"locality"
},
  "geometry": {"coordinates":[97.73049,16.00793],"type":"Point"}
}