{
  "type": "Feature",
  "properties": {
    "gn:admin1_code":"10.0",
    "gn:admin2_code":"MMR005D003",
    "gn:admin3_code":"MMR005013",
    "gn:asciiname":"Dandaing",
    "gn:country_code":"MM",
    "gn:dem":104,
    "gn:feature_class":"P",
    "gn:feature_code":"PPL",
    "gn:name":"Dandaing",
    "gn:population":0,
    "gn:timezone":"Asia/Yangon",
    "iso:country":"MM",
    "wof:name":"Dandaing",
    "wof:placetype":"locality"
},
  "geometry": {"coordinates":[95.09869,22.40325],"type":"Point"}
}