{
  "type": "Feature",
  "properties": {
    "gn:admin1_code":"16.0",
    "gn:admin2_code":"MMR007D001",
    "gn:admin3_code":"MMR007003",
    "gn:asciiname":"Sunpi-athin",
    "gn:country_code":"MM",
    "gn:dem":9,
    "gn:feature_class":"P",
    "gn:feature_code":"PPL",
    "gn:name":"Sunpi-athin",
    "gn:population":0,
    "gn:timezone":"Asia/Yangon",
    "iso:country":"MM",
    "wof:name":"Sunpi-athin",
    "wof:placetype":"locality"
},
  "geometry": {"coordinates":[96.78079,17.10037],"type":"Point"}
}