{
  "type": "Feature",
  "properties": {
    "gn:admin1_code":"11.0",
    "gn:admin2_code":"MMR014D002",
    "gn:admin3_code":"MMR014011",
    "gn:asciiname":"Na-sam",
    "gn:country_code":"MM",
    "gn:dem":1373,
    "gn:feature_class":"P",
    "gn:feature_code":"PPL",
    "gn:name":"N\u0101-sam",
    "gn:population":0,
    "gn:timezone":"Asia/Yangon",
    "iso:country":"MM",
    "wof:name":"Na-sam",
    "wof:placetype":"locality"
},
  "geometry": {"coordinates":[97.49521,21.04998],"type":"Point"}
}