{
  "type": "Feature",
  "properties": {
    "gn:admin1_code":"4.0",
    "gn:asciiname":"Mangpu",
    "gn:country_code":"MM",
    "gn:dem":1327,
    "gn:feature_class":"P",
    "gn:feature_code":"PPL",
    "gn:name":"M\u0101ngpu",
    "gn:population":0,
    "gn:timezone":"Asia/Yangon",
    "iso:country":"MM",
    "wof:name":"Mangpu",
    "wof:placetype":"locality"
},
  "geometry": {"coordinates":[97.56928000000001,23.70254],"type":"Point"}
}