{
  "type": "Feature",
  "properties": {
    "gn:admin1_code":"12.0",
    "gn:admin2_code":"MMR006D003",
    "gn:admin3_code":"MMR006006",
    "gn:asciiname":"Tharawungyi",
    "gn:country_code":"MM",
    "gn:dem":26,
    "gn:feature_class":"P",
    "gn:feature_code":"PPL",
    "gn:name":"Tharawungyi",
    "gn:population":0,
    "gn:timezone":"Asia/Yangon",
    "iso:country":"MM",
    "wof:name":"Tharawungyi",
    "wof:placetype":"locality"
},
  "geometry": {"coordinates":[98.33571000000001,12.38478],"type":"Point"}
}