{
  "type": "Feature",
  "properties": {
    "gn:admin1_code":"11.0",
    "gn:admin2_code":"MMR015D005",
    "gn:admin3_code":"MMR015023",
    "gn:asciiname":"Man Chit",
    "gn:country_code":"MM",
    "gn:dem":1189,
    "gn:feature_class":"P",
    "gn:feature_code":"PPL",
    "gn:name":"M\u0101n Chit",
    "gn:population":0,
    "gn:timezone":"Asia/Yangon",
    "iso:country":"MM",
    "name:und_x_variant":[
        "Man-chi",
        "M\u0101n Chit"
    ],
    "wof:name":"Man Chit",
    "wof:placetype":"locality"
},
  "geometry": {"coordinates":[98.55318,23.78076],"type":"Point"}
}