{
  "type": "Feature",
  "properties": {
    "gn:admin1_code":"11.0",
    "gn:admin2_code":"MMR015D001",
    "gn:admin3_code":"MMR015001",
    "gn:asciiname":"Ungkyawng",
    "gn:country_code":"MM",
    "gn:dem":900,
    "gn:feature_class":"P",
    "gn:feature_code":"PPL",
    "gn:name":"Ungkyawng",
    "gn:population":0,
    "gn:timezone":"Asia/Yangon",
    "iso:country":"MM",
    "wof:name":"Ungkyawng",
    "wof:placetype":"locality"
},
  "geometry": {"coordinates":[98.16160000000001,23.07157],"type":"Point"}
}