{
  "type": "Feature",
  "properties": {
    "gn:admin1_code":"5.0",
    "gn:admin2_code":"MMR003D004",
    "gn:admin3_code":"MMR003003",
    "gn:asciiname":"Kalaykalawmudo",
    "gn:country_code":"MM",
    "gn:dem":466,
    "gn:feature_class":"P",
    "gn:feature_code":"PPL",
    "gn:name":"Kalaykalawmudo",
    "gn:population":0,
    "gn:timezone":"Asia/Yangon",
    "iso:country":"MM",
    "name:und_x_variant":[
        "Kalaykalawmudu",
        "Kalaykalawmudo"
    ],
    "wof:name":"Kalaykalawmudo",
    "wof:placetype":"locality"
},
  "geometry": {"coordinates":[97.48426000000001,18.21252],"type":"Point"}
}