{
  "type": "Feature",
  "properties": {
    "gn:admin1_code":"8.0",
    "gn:admin2_code":"MMR010D003",
    "gn:admin3_code":"MMR010014",
    "gn:asciiname":"Mithwebok",
    "gn:country_code":"MM",
    "gn:dem":84,
    "gn:feature_class":"P",
    "gn:feature_code":"PPL",
    "gn:name":"Mithwebok",
    "gn:population":0,
    "gn:timezone":"Asia/Yangon",
    "iso:country":"MM",
    "wof:name":"Mithwebok",
    "wof:placetype":"locality"
},
  "geometry": {"coordinates":[96.21404,21.83567],"type":"Point"}
}