{
  "type": "Feature",
  "properties": {
    "gn:admin1_code":"6.0",
    "gn:admin2_code":"MMR002D001",
    "gn:admin3_code":"MMR002004",
    "gn:asciiname":"Daw Me-ku",
    "gn:country_code":"MM",
    "gn:dem":918,
    "gn:feature_class":"P",
    "gn:feature_code":"PPL",
    "gn:name":"Daw M\u00e8-ku",
    "gn:population":0,
    "gn:timezone":"Asia/Yangon",
    "iso:country":"MM",
    "wof:name":"Daw Me-ku",
    "wof:placetype":"locality"
},
  "geometry": {"coordinates":[97.50472000000001,19.49917],"type":"Point"}
}