{
  "type": "Feature",
  "properties": {
    "gn:admin1_code":"12.0",
    "gn:admin2_code":"MMR006D001",
    "gn:admin3_code":"MMR006001",
    "gn:asciiname":"Kataungni",
    "gn:country_code":"MM",
    "gn:dem":200,
    "gn:feature_class":"P",
    "gn:feature_code":"PPL",
    "gn:name":"Kataungni",
    "gn:population":0,
    "gn:timezone":"Asia/Yangon",
    "iso:country":"MM",
    "wof:name":"Kataungni",
    "wof:placetype":"locality"
},
  "geometry": {"coordinates":[98.47523,14.22907],"type":"Point"}
}