{
  "type": "Feature",
  "properties": {
    "gn:admin1_code":"2.0",
    "gn:admin2_code":"MMR004D002",
    "gn:admin3_code":"MMR004009",
    "gn:asciiname":"Yapi",
    "gn:country_code":"MM",
    "gn:dem":745,
    "gn:feature_class":"P",
    "gn:feature_code":"PPL",
    "gn:name":"Yapi",
    "gn:population":0,
    "gn:timezone":"Asia/Yangon",
    "iso:country":"MM",
    "name:deu_x_preferred":[
        "Yapi"
    ],
    "wof:name":"Yapi",
    "wof:placetype":"locality"
},
  "geometry": {"coordinates":[93.53521000000001,20.81900000000001],"type":"Point"}
}