{
  "type": "Feature",
  "properties": {
    "gn:admin1_code":"8.0",
    "gn:admin2_code":"MMR010D003",
    "gn:admin3_code":"MMR010013",
    "gn:asciiname":"Yanbetlo",
    "gn:country_code":"MM",
    "gn:dem":89,
    "gn:feature_class":"P",
    "gn:feature_code":"PPL",
    "gn:name":"Yanbetlo",
    "gn:population":0,
    "gn:timezone":"Asia/Yangon",
    "iso:country":"MM",
    "wof:name":"Yanbetlo",
    "wof:placetype":"locality"
},
  "geometry": {"coordinates":[96.05983999999999,21.53191],"type":"Point"}
}