{
  "type": "Feature",
  "properties": {
    "gn:admin1_code":"11.0",
    "gn:admin2_code":"MMR016D003",
    "gn:admin3_code":"MMR016009",
    "gn:asciiname":"Wan Pa-hsang",
    "gn:country_code":"MM",
    "gn:dem":1077,
    "gn:feature_class":"P",
    "gn:feature_code":"PPL",
    "gn:name":"W\u0101n P\u0101-hsang",
    "gn:population":0,
    "gn:timezone":"Asia/Yangon",
    "iso:country":"MM",
    "name:und_x_variant":[
        "W\u0101n Kaw P\u0101-hsang",
        "W\u0101n P\u0101-hsang"
    ],
    "wof:name":"Wan Pa-hsang",
    "wof:placetype":"locality"
},
  "geometry": {"coordinates":[99.56613,20.67427],"type":"Point"}
}