{
  "type": "Feature",
  "properties": {
    "gn:admin1_code":"3.0",
    "gn:admin2_code":"MMR017D001",
    "gn:admin3_code":"MMR017002",
    "gn:asciiname":"Thebyu",
    "gn:country_code":"MM",
    "gn:dem":14,
    "gn:feature_class":"P",
    "gn:feature_code":"PPL",
    "gn:name":"Th\u0113byu",
    "gn:population":0,
    "gn:timezone":"Asia/Yangon",
    "iso:country":"MM",
    "wof:name":"Thebyu",
    "wof:placetype":"locality"
},
  "geometry": {"coordinates":[94.81677000000001,16.75647],"type":"Point"}
}