{
  "type": "Feature",
  "properties": {
    "gn:admin1_code":"11.0",
    "gn:admin2_code":"MMR015D007",
    "gn:admin3_code":"MMR015005",
    "gn:asciiname":"Yawng Kung",
    "gn:country_code":"MM",
    "gn:dem":1359,
    "gn:feature_class":"P",
    "gn:feature_code":"PPL",
    "gn:name":"Yawng K\u016bng",
    "gn:population":0,
    "gn:timezone":"Asia/Yangon",
    "iso:country":"MM",
    "wof:name":"Yawng Kung",
    "wof:placetype":"locality"
},
  "geometry": {"coordinates":[98.90026,22.43255],"type":"Point"}
}