{
  "type": "Feature",
  "properties": {
    "gn:admin1_code":"10.0",
    "gn:admin2_code":"MMR005D004",
    "gn:admin3_code":"MMR005021",
    "gn:asciiname":"Taungyagyi",
    "gn:country_code":"MM",
    "gn:dem":186,
    "gn:feature_class":"P",
    "gn:feature_code":"PPL",
    "gn:name":"Taungyagyi",
    "gn:population":0,
    "gn:timezone":"Asia/Yangon",
    "iso:country":"MM",
    "wof:name":"Taungyagyi",
    "wof:placetype":"locality"
},
  "geometry": {"coordinates":[96.09963,24.09532],"type":"Point"}
}