{
  "type": "Feature",
  "properties": {
    "gn:admin1_code":"11.0",
    "gn:admin2_code":"MMR014D002",
    "gn:admin3_code":"MMR014015",
    "gn:asciiname":"Ke-hsi Mansam",
    "gn:country_code":"MM",
    "gn:dem":983,
    "gn:feature_class":"P",
    "gn:feature_code":"PPL",
    "gn:name":"Ke-hsi M\u0101ns\u0101m",
    "gn:population":0,
    "gn:timezone":"Asia/Yangon",
    "iso:country":"MM",
    "name:und_x_variant":[
        "Kyethimanzan",
        "Ke-hsi Mansan",
        "Ke-hsi",
        "Ke-hsi M\u0101ns\u0101m"
    ],
    "wof:name":"Ke-hsi Mansam",
    "wof:placetype":"locality"
},
  "geometry": {"coordinates":[97.82098999999999,21.92913],"type":"Point"}
}