{
  "type": "Feature",
  "properties": {
    "gn:admin1_code":"6.0",
    "gn:admin2_code":"MMR002D001",
    "gn:admin3_code":"MMR002002",
    "gn:asciiname":"Dawwe-ne",
    "gn:country_code":"MM",
    "gn:dem":206,
    "gn:feature_class":"P",
    "gn:feature_code":"PPL",
    "gn:name":"Daww\u00e8-n\u00e8",
    "gn:population":0,
    "gn:timezone":"Asia/Yangon",
    "iso:country":"MM",
    "wof:name":"Dawwe-ne",
    "wof:placetype":"locality"
},
  "geometry": {"coordinates":[97.39906999999999,19.3816],"type":"Point"}
}