{
  "type": "Feature",
  "properties": {
    "gn:admin1_code":"10.0",
    "gn:admin2_code":"MMR005D003",
    "gn:admin3_code":"MMR005015",
    "gn:asciiname":"Chaung-u",
    "gn:country_code":"MM",
    "gn:dem":84,
    "gn:feature_class":"P",
    "gn:feature_code":"PPL",
    "gn:name":"Chaung-u",
    "gn:population":0,
    "gn:timezone":"Asia/Yangon",
    "iso:country":"MM",
    "wof:name":"Chaung-u",
    "wof:placetype":"locality"
},
  "geometry": {"coordinates":[95.27063,21.95755],"type":"Point"}
}