{
  "type": "Feature",
  "properties": {
    "gn:admin1_code":"10.0",
    "gn:admin2_code":"MMR005D002",
    "gn:admin3_code":"MMR005011",
    "gn:asciiname":"Tasegye",
    "gn:country_code":"MM",
    "gn:dem":135,
    "gn:feature_class":"P",
    "gn:feature_code":"PPL",
    "gn:name":"Tasegye",
    "gn:population":0,
    "gn:timezone":"Asia/Yangon",
    "iso:country":"MM",
    "name:und_x_variant":[
        "Tas\u00e8gyi",
        "Tasegye"
    ],
    "wof:name":"Tasegye",
    "wof:placetype":"locality"
},
  "geometry": {"coordinates":[95.36442,23.05592],"type":"Point"}
}