{
  "type": "Feature",
  "properties": {
    "gn:admin1_code":"15.0",
    "gn:admin2_code":"MMR009D002",
    "gn:admin3_code":"MMR009009",
    "gn:asciiname":"Le-einzu",
    "gn:country_code":"MM",
    "gn:dem":182,
    "gn:feature_class":"P",
    "gn:feature_code":"PPL",
    "gn:name":"Le-einzu",
    "gn:population":0,
    "gn:timezone":"Asia/Yangon",
    "iso:country":"MM",
    "wof:name":"Le-einzu",
    "wof:placetype":"locality"
},
  "geometry": {"coordinates":[94.4324,20.13047000000001],"type":"Point"}
}