{
  "type": "Feature",
  "properties": {
    "gn:admin1_code":"8.0",
    "gn:admin2_code":"MMR010D002",
    "gn:admin3_code":"MMR010008",
    "gn:asciiname":"Bo-so-kon",
    "gn:country_code":"MM",
    "gn:dem":1156,
    "gn:feature_class":"P",
    "gn:feature_code":"PPL",
    "gn:name":"Bo-so-k\u00f4n",
    "gn:population":0,
    "gn:timezone":"Asia/Yangon",
    "iso:country":"MM",
    "wof:name":"Bo-so-kon",
    "wof:placetype":"locality"
},
  "geometry": {"coordinates":[96.49760999999999,22.11562],"type":"Point"}
}