{
  "type": "Feature",
  "properties": {
    "gn:admin1_code":"17.0",
    "gn:admin2_code":"MMR013D002",
    "gn:admin3_code":"MMR013020",
    "gn:asciiname":"Malit-ashe",
    "gn:country_code":"MM",
    "gn:dem":9,
    "gn:feature_class":"P",
    "gn:feature_code":"PPL",
    "gn:name":"Malit-ashe",
    "gn:population":0,
    "gn:timezone":"Asia/Yangon",
    "iso:country":"MM",
    "wof:name":"Malit-ashe",
    "wof:placetype":"locality"
},
  "geometry": {"coordinates":[96.24778000000001,16.98972],"type":"Point"}
}