{
  "type": "Feature",
  "properties": {
    "gn:admin1_code":"11.0",
    "gn:admin2_code":"MMR015D003",
    "gn:admin3_code":"MMR015016",
    "gn:asciiname":"Manloitaoe",
    "gn:country_code":"MM",
    "gn:dem":1547,
    "gn:feature_class":"P",
    "gn:feature_code":"PPL",
    "gn:name":"M\u0101nloita\u00f6",
    "gn:population":0,
    "gn:timezone":"Asia/Yangon",
    "iso:country":"MM",
    "wof:name":"Manloitaoe",
    "wof:placetype":"locality"
},
  "geometry": {"coordinates":[97.21881,22.97246],"type":"Point"}
}