{
  "type": "Feature",
  "properties": {
    "gn:admin1_code":"3.0",
    "gn:admin2_code":"MMR017D002",
    "gn:admin3_code":"MMR017013",
    "gn:asciiname":"Kyani Myauk",
    "gn:country_code":"MM",
    "gn:dem":31,
    "gn:feature_class":"P",
    "gn:feature_code":"PPL",
    "gn:name":"Kyani Myauk",
    "gn:population":0,
    "gn:timezone":"Asia/Yangon",
    "iso:country":"MM",
    "wof:name":"Kyani Myauk",
    "wof:placetype":"locality"
},
  "geometry": {"coordinates":[95.19297,17.96043],"type":"Point"}
}