{
  "type": "Feature",
  "properties": {
    "gn:admin1_code":"10.0",
    "gn:asciiname":"Htontha",
    "gn:country_code":"MM",
    "gn:dem":117,
    "gn:feature_class":"P",
    "gn:feature_code":"PPL",
    "gn:name":"Htontha",
    "gn:population":0,
    "gn:timezone":"Asia/Yangon",
    "iso:country":"MM",
    "wof:name":"Htontha",
    "wof:placetype":"locality"
},
  "geometry": {"coordinates":[95.67668,21.8023],"type":"Point"}
}