{
  "type": "Feature",
  "properties": {
    "gn:admin1_code":"16.0",
    "gn:admin2_code":"MMR007D002",
    "gn:admin3_code":"MMR007014",
    "gn:asciiname":"Kyaukpon-ale",
    "gn:country_code":"MM",
    "gn:dem":39,
    "gn:feature_class":"P",
    "gn:feature_code":"PPL",
    "gn:name":"Kyaukpon-ale",
    "gn:population":0,
    "gn:timezone":"Asia/Yangon",
    "iso:country":"MM",
    "name:und_x_variant":[
        "Kyaukoon",
        "Kyaukpon",
        "Kyaukpon-ale"
    ],
    "wof:name":"Kyaukpon-ale",
    "wof:placetype":"locality"
},
  "geometry": {"coordinates":[96.52551,18.84787],"type":"Point"}
}