{
  "type": "Feature",
  "properties": {
    "gn:admin1_code":"15.0",
    "gn:admin2_code":"MMR009D002",
    "gn:admin3_code":"MMR009009",
    "gn:asciiname":"Dowa",
    "gn:country_code":"MM",
    "gn:dem":187,
    "gn:feature_class":"P",
    "gn:feature_code":"PPL",
    "gn:name":"Dowa",
    "gn:population":0,
    "gn:timezone":"Asia/Yangon",
    "iso:country":"MM",
    "name:ceb_x_preferred":[
        "Dowa"
    ],
    "name:fra_x_preferred":[
        "Dowa"
    ],
    "name:ita_x_preferred":[
        "Dowa"
    ],
    "name:nld_x_preferred":[
        "Dowa"
    ],
    "name:swe_x_preferred":[
        "Dowa"
    ],
    "wof:name":"Dowa",
    "wof:placetype":"locality"
},
  "geometry": {"coordinates":[94.4205,20.0805],"type":"Point"}
}