{
  "type": "Feature",
  "properties": {
    "gn:admin1_code":"13.0",
    "gn:asciiname":"Makala",
    "gn:country_code":"MM",
    "gn:dem":46,
    "gn:feature_class":"P",
    "gn:feature_code":"PPL",
    "gn:name":"Makala",
    "gn:population":0,
    "gn:timezone":"Asia/Yangon",
    "iso:country":"MM",
    "name:eus_x_preferred":[
        "Makala"
    ],
    "name:fra_x_preferred":[
        "Makala"
    ],
    "name:lin_x_preferred":[
        "Mak\u00e1la"
    ],
    "name:pol_x_preferred":[
        "Makala"
    ],
    "name:und_x_variant":[
        "M\u00e8kata-ywa"
    ],
    "wof:name":"Makala",
    "wof:placetype":"locality"
},
  "geometry": {"coordinates":[97.01855999999999,17.57481],"type":"Point"}
}