{
  "type": "Feature",
  "properties": {
    "gn:admin1_code":"10.0",
    "gn:admin2_code":"MMR005D002",
    "gn:admin3_code":"MMR005010",
    "gn:asciiname":"Indainggale",
    "gn:country_code":"MM",
    "gn:dem":117,
    "gn:feature_class":"P",
    "gn:feature_code":"PPL",
    "gn:name":"Indainggale",
    "gn:population":0,
    "gn:timezone":"Asia/Yangon",
    "iso:country":"MM",
    "name:und_x_variant":[
        "Indaunggale",
        "Indainggale"
    ],
    "wof:name":"Indainggale",
    "wof:placetype":"locality"
},
  "geometry": {"coordinates":[95.26436,22.69931],"type":"Point"}
}