{
  "type": "Feature",
  "properties": {
    "gn:admin1_code":"1.0",
    "gn:admin2_code":"MMR012D005",
    "gn:admin3_code":"MMR012006",
    "gn:asciiname":"Ngamankai",
    "gn:country_code":"MM",
    "gn:dem":10,
    "gn:feature_class":"P",
    "gn:feature_code":"PPL",
    "gn:name":"Ngamankai",
    "gn:population":0,
    "gn:timezone":"Asia/Yangon",
    "iso:country":"MM",
    "name:und_x_variant":[
        "Ngamankai Ywat Hit",
        "Ngamankai"
    ],
    "wof:name":"Ngamankai",
    "wof:placetype":"locality"
},
  "geometry": {"coordinates":[93.78552000000001,19.87394],"type":"Point"}
}