{
  "type": "Feature",
  "properties": {
    "gn:admin1_code":"10.0",
    "gn:admin2_code":"MMR005D006",
    "gn:admin3_code":"MMR005030",
    "gn:asciiname":"Htinzin",
    "gn:country_code":"MM",
    "gn:dem":166,
    "gn:feature_class":"P",
    "gn:feature_code":"PPL",
    "gn:name":"Htinzin",
    "gn:population":0,
    "gn:timezone":"Asia/Yangon",
    "iso:country":"MM",
    "name:und_x_variant":[
        "Tinzin",
        "Htinzin"
    ],
    "wof:name":"Htinzin",
    "wof:placetype":"locality"
},
  "geometry": {"coordinates":[94.18098999999999,23.86821],"type":"Point"}
}