{
  "type": "Feature",
  "properties": {
    "gn:admin1_code":"10.0",
    "gn:admin2_code":"MMR005D002",
    "gn:admin3_code":"MMR005005",
    "gn:asciiname":"Wetthe",
    "gn:country_code":"MM",
    "gn:dem":157,
    "gn:feature_class":"P",
    "gn:feature_code":"PPL",
    "gn:name":"Wetth\u00e8",
    "gn:population":0,
    "gn:timezone":"Asia/Yangon",
    "iso:country":"MM",
    "wof:name":"Wetthe",
    "wof:placetype":"locality"
},
  "geometry": {"coordinates":[95.78124,22.70399],"type":"Point"}
}