{
  "type": "Feature",
  "properties": {
    "gn:admin1_code":"15.0",
    "gn:admin2_code":"MMR009D003",
    "gn:admin3_code":"MMR009016",
    "gn:asciiname":"Pyinbinhla",
    "gn:country_code":"MM",
    "gn:dem":41,
    "gn:feature_class":"P",
    "gn:feature_code":"PPL",
    "gn:name":"Pyinbinhla",
    "gn:population":0,
    "gn:timezone":"Asia/Yangon",
    "iso:country":"MM",
    "name:und_x_variant":[
        "Pyinbinla",
        "Pyinbinhla"
    ],
    "wof:name":"Pyinbinhla",
    "wof:placetype":"locality"
},
  "geometry": {"coordinates":[95.17523,19.11451],"type":"Point"}
}