{
  "type": "Feature",
  "properties": {
    "gn:admin1_code":"4.0",
    "gn:admin2_code":"MMR001D003",
    "gn:admin3_code":"MMR001011",
    "gn:asciiname":"Shu-u-kawng",
    "gn:country_code":"MM",
    "gn:dem":345,
    "gn:feature_class":"P",
    "gn:feature_code":"PPL",
    "gn:name":"Shu-u-kawng",
    "gn:population":0,
    "gn:timezone":"Asia/Yangon",
    "iso:country":"MM",
    "wof:name":"Shu-u-kawng",
    "wof:placetype":"locality"
},
  "geometry": {"coordinates":[96.7124,24.62156],"type":"Point"}
}