{
  "type": "Feature",
  "properties": {
    "gn:admin1_code":"12.0",
    "gn:admin2_code":"MMR006D001",
    "gn:admin3_code":"MMR006003",
    "gn:asciiname":"Kanetthiri",
    "gn:country_code":"MM",
    "gn:dem":38,
    "gn:feature_class":"P",
    "gn:feature_code":"PPL",
    "gn:name":"Kanetthiri",
    "gn:population":0,
    "gn:timezone":"Asia/Yangon",
    "iso:country":"MM",
    "name:und_x_variant":[
        "Kanetthira",
        "Kanatheri",
        "Kanetthiri"
    ],
    "wof:name":"Kanetthiri",
    "wof:placetype":"locality"
},
  "geometry": {"coordinates":[98.30277,13.66087],"type":"Point"}
}