{
  "type": "Feature",
  "properties": {
    "gn:admin1_code":"8.0",
    "gn:admin2_code":"MMR010D005",
    "gn:admin3_code":"MMR010020",
    "gn:asciiname":"Kanlwin",
    "gn:country_code":"MM",
    "gn:dem":271,
    "gn:feature_class":"P",
    "gn:feature_code":"PPL",
    "gn:name":"Kanlwin",
    "gn:population":0,
    "gn:timezone":"Asia/Yangon",
    "iso:country":"MM",
    "wof:name":"Kanlwin",
    "wof:placetype":"locality"
},
  "geometry": {"coordinates":[95.08857999999999,20.70126],"type":"Point"}
}