{
  "type": "Feature",
  "properties": {
    "gn:admin1_code":"11.0",
    "gn:admin2_code":"MMR015D007",
    "gn:admin3_code":"MMR015005",
    "gn:asciiname":"Hsa-rang",
    "gn:country_code":"MM",
    "gn:dem":1299,
    "gn:feature_class":"P",
    "gn:feature_code":"PPL",
    "gn:name":"Hsa-rang",
    "gn:population":0,
    "gn:timezone":"Asia/Yangon",
    "iso:country":"MM",
    "wof:name":"Hsa-rang",
    "wof:placetype":"locality"
},
  "geometry": {"coordinates":[98.8993,22.5874],"type":"Point"}
}