{
  "type": "Feature",
  "properties": {
    "gn:admin1_code":"16.0",
    "gn:admin2_code":"MMR008D002",
    "gn:admin3_code":"MMR008010",
    "gn:asciiname":"Gyokobin",
    "gn:country_code":"MM",
    "gn:dem":54,
    "gn:feature_class":"P",
    "gn:feature_code":"PPL",
    "gn:name":"Gyokobin",
    "gn:population":0,
    "gn:timezone":"Asia/Yangon",
    "iso:country":"MM",
    "wof:name":"Gyokobin",
    "wof:placetype":"locality"
},
  "geometry": {"coordinates":[95.7968,18.23311],"type":"Point"}
}